Workbook

Sheet Intro
A1: This is a sheet for standardisation of inputs for the Meta Analysis of Abatement Costs from Alternative Fuel Pathways in Commercial Aviation

Sheet Steps

Sheet Inputs
A1: Scenario Selected | B1: Reference Oil Price | C1: Electricity and CO2 Price | D1: Reference
A2: Parameter | B2: Year | C2: Value | D2: Unit
A3: Standard Values
A4: Current Year | C4: 2024
A5: Inflation | C5: 0.02
A6: WACC | C6: 0.07
A7: USD to EUR | C7: 0.9
A8: Electricity
A9: LCOE | B9: 2024 | C9: {=_xlfn.IFS($D$1 = "Low Electricity and CO2", Electricity!F30, $D$1 = "Reference",'Standard Input Calculations'!E13, $D$1="High Electricity and CO2",Electricity!F34)} -> 64 | D9: $/MWh
A10: LCOE | B10: 2050 | C10: 39 | D10: $/MWh | E10: Vary this for electricity price scenarios
A11: Jet Fuel A-1 Characteristics
A12: Emissions Intensity | B12: 2024 | C12: ='Standard Input Calculations'!C63 -> 88.7 | D12: gCO2/MJ
A13: Emissions Intensity | B13: 2050 | C13: ='Standard Input Calculations'!D63 -> 88.7 | D13: gCO2/MJ
A14: Energy Density | C14: ='Standard Input Calculations'!C110 -> 43.2 | D14: MJ/kg
A15: Energy Density | C15: =C14*C16 -> 34.6896 | D15: MJ/l
A16: Volumetric Density | C16: ='Standard Input Calculations'!C111 -> 0.803 | D16: kg/l
A17: Jet Fuel A-1 Price | B17: 2024 | C17: ='Standard Input Calculations'!C73 -> 0.8 | D17: $/l
A18: Scenario Specific Values
A19: Jet Fuel A-1 Price | B19: 2050 | C19: 0.8 | D19: $/l | E19: Average fuel price across scenarios
A20: IEA Reference
A21: Jet Fuel A-1 Price | B21: 2024 | C21: ='Standard Input Calculations'!D103 -> 0.32246154 | D21: $/l
A22: Jet Fuel A-1 Price | B22: 2050 | C22: ='Standard Input Calculations'!E103 -> 0.20923077 | D22: $/l
A23: EIA Reference
A24: Jet Fuel A-1 Price | B24: 2024 | C24: ='Standard Input Calculations'!D104 -> 1.0209014 | D24: $/l
A25: Jet Fuel A-1 Price | B25: 2050 | C25: ='Standard Input Calculations'!E104 -> 2.0095594 | D25: $/l
A26: EIA Low Oil Price Scenario
A27: Jet Fuel A-1 Price | B27: 2024 | C27: ='Standard Input Calculations'!D106 -> 0.48286833 | D27: $/l
A28: Jet Fuel A-1 Price | B28: 2050 | C28: ='Standard Input Calculations'!E106 -> 0.89646575 | D28: $/l
A29: EIA High Scenario
A30: Jet Fuel A-1 Price | B30: 2024 | C30: ='Standard Input Calculations'!D105 -> 1.8838713 | D30: $/l
A31: Jet Fuel A-1 Price | B31: 2050 | C31: ='Standard Input Calculations'!E105 -> 3.7893731 | D31: $/l
A32: Direct Air Capture
A33: LCOR | B33: 2024 | C33: ='Standard Input Calculations'!C52 -> 440 | D33: $/tCO2 | E33: Modified as needed for Low CO2, median CO2, and high CO2 runs.
A34: LCOR | B34: 2050 | C34: ='Standard Input Calculations'!D52 -> 235 | D34: $/tCO2 | E34: Modified as needed for Low CO2, median CO2, and high CO2 runs.

Sheet Electricity
A1: Technology | B1: Scenario | C1: Period raw | D1: 2022 | E1: 2023 | F1: 2024 | G1: 2025 | H1: 2026 | I1: 2027 | J1: 2028 | K1: 2029 | L1: 2030 | M1: 2031 | N1: 2032 | O1: 2033 | P1: 2034 | Q1: 2035 | R1: 2036 | S1: 2037 | T1: 2038 | U1: 2039 | V1: 2040 | W1: 2041 | X1: 2042 | Y1: 2043 | Z1: 2044 | AA1: 2045 | AB1: 2046 | AC1: 2047 | AD1: 2048 | AE1: 2049 | AF1: 2050 | AG1: Source | AH1: Note | AI1: Link | AJ1: carbon_intensity | AK1: unit | AL1: Source
A2: PV tracking with storage | B2: LCOE $/MWh (avg) | C2: 2022 2H | D2: 111 | E2: 97 | F2: 84 | G2: 75 | H2: 68 | I2: 62 | J2: 58 | K2: 55 | L2: 53 | M2: 50 | N2: 48 | O2: 47 | P2: 45 | Q2: 44 | R2: 43 | S2: 43 | T2: 42 | U2: 41 | V2: 41 | W2: 41 | X2: 40 | Y2: 41 | Z2: 40 | AA2: 40 | AB2: 40 | AC2: 39 | AD2: 40 | AE2: 39 | AF2: 39 | AG2: BNEF LCOE - All Technologies - Unites States - LCOE Forecast 2022 | AH2: To be converted in $/GJ with conversion factor in Universal Inputs "conversion_electricity" OR just | AI2: https://www.bnef.com/flagships/lcoe | AJ2: =15.3/1000 -> 0.0153 | AK2: [t-CO2,eq GJ-1] | AL2: Young et al. (2023)
A3: CCGT | B3: LCOE $/GJ (low) | C3: 2022 2H | D3: 47 | E3: 48 | F3: 48 | G3: 48 | H3: 49 | I3: 49 | J3: 50 | K3: 51 | L3: 51 | M3: 52 | N3: 52 | O3: 53 | P3: 53 | Q3: 54 | R3: 54 | S3: 54 | T3: 55 | U3: 55 | V3: 56 | W3: 56 | X3: 56 | Y3: 56 | Z3: 57 | AA3: 57 | AB3: 57 | AC3: 57 | AD3: 57 | AE3: 57 | AF3: 57 | AG3: BNEF LCOE - All Technologies - Unites States - LCOE Forecast 2022 | AH3: To be converted in $/GJ with conversion factor in Universal Inputs "conversion_electricity" OR just | AI3: https://www.bnef.com/flagships/lcoe
A4: CCGT CCS | B4: LCOE $/MWh (low) | C4: 2022 2H | D4: 151 | E4: 141 | F4: 132 | G4: 121 | H4: 112 | I4: 102 | J4: 92 | K4: 82 | L4: 72 | M4: 73 | N4: 74 | O4: 74 | P4: 75 | Q4: 75 | R4: 76 | S4: 76 | T4: 77 | U4: 77 | V4: 77 | W4: 78 | X4: 78 | Y4: 79 | Z4: 79 | AA4: 79 | AB4: 79 | AC4: 79 | AD4: 79 | AE4: 79 | AF4: 79 | AG4: BNEF LCOE - All Technologies - Unites States - LCOE Forecast 2022 | AH4: To be converted in $/GJ with conversion factor in Universal Inputs "conversion_electricity" OR just | AI4: https://www.bnef.com/flagships/lcoe
A5: CCGT Hydrogen | B5: LCOE $/MWh (low) | C5: 2022 2H | D5: 152 | E5: 141 | F5: 130 | G5: 120 | H5: 112 | I5: 104 | J5: 98 | K5: 93 | L5: 89 | M5: 86 | N5: 83 | O5: 81 | P5: 78 | Q5: 76 | R5: 74 | S5: 72 | T5: 71 | U5: 70 | V5: 69 | W5: 68 | X5: 68 | Y5: 67 | Z5: 67 | AA5: 66 | AB5: 66 | AC5: 65 | AD5: 65 | AE5: 65 | AF5: 65 | AG5: BNEF LCOE - All Technologies - Unites States - LCOE Forecast 2022 | AH5: To be converted in $/GJ with conversion factor in Universal Inputs "conversion_electricity" OR just | AI5: https://www.bnef.com/flagships/lcoe
A6: Coal | B6: LCOE $/MWh (low) | C6: 2022 2H | D6: 68 | E6: 68 | F6: 68 | G6: 68 | H6: 68 | I6: 69 | J6: 70 | K6: 70 | L6: 71 | M6: 71 | N6: 72 | O6: 72 | P6: 73 | Q6: 73 | R6: 74 | S6: 74 | T6: 74 | U6: 75 | V6: 75 | W6: 76 | X6: 76 | Y6: 76 | Z6: 76 | AA6: 76 | AB6: 76 | AC6: 76 | AD6: 76 | AE6: 76 | AF6: 76 | AG6: BNEF LCOE - All Technologies - Unites States - LCOE Forecast 2022 | AH6: To be converted in $/GJ with conversion factor in Universal Inputs "conversion_electricity" OR just | AI6: https://www.bnef.com/flagships/lcoe
A7: Coal CCS | B7: LCOE $/MWh (low) | C7: 2022 2H | D7: 259 | E7: 246 | F7: 231 | G7: 212 | H7: 194 | I7: 175 | J7: 154 | K7: 133 | L7: 112 | M7: 113 | N7: 114 | O7: 115 | P7: 115 | Q7: 116 | R7: 117 | S7: 117 | T7: 118 | U7: 119 | V7: 119 | W7: 120 | X7: 120 | Y7: 120 | Z7: 120 | AA7: 120 | AB7: 120 | AC7: 120 | AD7: 120 | AE7: 120 | AF7: 120 | AG7: BNEF LCOE - All Technologies - Unites States - LCOE Forecast 2022 | AH7: To be converted in $/GJ with conversion factor in Universal Inputs "conversion_electricity" OR just | AI7: https://www.bnef.com/flagships/lcoe
A8: OCGT | B8: LCOE $/MWh (low) | C8: 2022 2H | D8: 96 | E8: 98 | F8: 99 | G8: 101 | H8: 102 | I8: 103 | J8: 104 | K8: 105 | L8: 106 | M8: 107 | N8: 108 | O8: 109 | P8: 109 | Q8: 110 | R8: 111 | S8: 112 | T8: 112 | U8: 113 | V8: 114 | W8: 114 | X8: 114 | Y8: 115 | Z8: 115 | AA8: 115 | AB8: 116 | AC8: 116 | AD8: 116 | AE8: 116 | AF8: 116 | AG8: BNEF LCOE - All Technologies - Unites States - LCOE Forecast 2022 | AH8: To be converted in $/GJ with conversion factor in Universal Inputs "conversion_electricity" OR just | AI8: https://www.bnef.com/flagships/lcoe
A9: OCGT CCS | B9: LCOE $/MWh (low) | C9: 2022 2H | D9: 455 | E9: 432 | F9: 401 | G9: 366 | H9: 330 | I9: 293 | J9: 255 | K9: 216 | L9: 176 | M9: 178 | N9: 179 | O9: 180 | P9: 181 | Q9: 182 | R9: 183 | S9: 184 | T9: 185 | U9: 186 | V9: 187 | W9: 188 | X9: 188 | Y9: 189 | Z9: 189 | AA9: 189 | AB9: 189 | AC9: 190 | AD9: 190 | AE9: 190 | AF9: 190 | AG9: BNEF LCOE - All Technologies - Unites States - LCOE Forecast 2022 | AH9: To be converted in $/GJ with conversion factor in Universal Inputs "conversion_electricity" OR just | AI9: https://www.bnef.com/flagships/lcoe
A10: OCGT Hydrogen | B10: LCOE $/MWh (low) | C10: 2022 2H | D10: 235 | E10: 224 | F10: 213 | G10: 202 | H10: 192 | I10: 184 | J10: 176 | K10: 170 | L10: 166 | M10: 161 | N10: 158 | O10: 154 | P10: 150 | Q10: 146 | R10: 142 | S10: 139 | T10: 137 | U10: 136 | V10: 134 | W10: 134 | X10: 133 | Y10: 132 | Z10: 131 | AA10: 131 | AB10: 130 | AC10: 130 | AD10: 130 | AE10: 129 | AF10: 129 | AG10: BNEF LCOE - All Technologies - Unites States - LCOE Forecast 2022 | AH10: To be converted in $/GJ with conversion factor in Universal Inputs "conversion_electricity" OR just | AI10: https://www.bnef.com/flagships/lcoe
A11: PV non-tracking | B11: LCOE $/MWh (low) | C11: 2022 2H | D11: 39 | E11: 35 | F11: 33 | G11: 29 | H11: 28 | I11: 27 | J11: 27 | K11: 25 | L11: 23 | M11: 21 | N11: 19 | O11: 19 | P11: 18 | Q11: 18 | R11: 17 | S11: 17 | T11: 16 | U11: 16 | V11: 16 | W11: 15 | X11: 15 | Y11: 15 | Z11: 14 | AA11: 14 | AB11: 14 | AC11: 14 | AD11: 13 | AE11: 13 | AF11: 13 | AG11: BNEF LCOE - All Technologies - Unites States - LCOE Forecast 2022 | AH11: To be converted in $/GJ with conversion factor in Universal Inputs "conversion_electricity" OR just | AI11: https://www.bnef.com/flagships/lcoe
A12: PV non-tracking with storage | B12: LCOE $/MWh (low) | C12: 2022 2H | D12: 58 | E12: 51 | F12: 47 | G12: 42 | H12: 40 | I12: 37 | J12: 36 | K12: 33 | L12: 31 | M12: 29 | N12: 27 | O12: 26 | P12: 26 | Q12: 25 | R12: 25 | S12: 24 | T12: 24 | U12: 23 | V12: 23 | W12: 22 | X12: 22 | Y12: 22 | Z12: 22 | AA12: 21 | AB12: 21 | AC12: 21 | AD12: 21 | AE12: 20 | AF12: 20 | AG12: BNEF LCOE - All Technologies - Unites States - LCOE Forecast 2022 | AH12: To be converted in $/GJ with conversion factor in Universal Inputs "conversion_electricity" OR just | AI12: https://www.bnef.com/flagships/lcoe
A13: PV tracking | B13: LCOE $/MWh (low) | C13: 2022 2H | D13: 34 | E13: 31 | F13: 28 | G13: 25 | H13: 25 | I13: 24 | J13: 23 | K13: 21 | L13: 20 | M13: 18 | N13: 17 | O13: 16 | P13: 16 | Q13: 15 | R13: 15 | S13: 15 | T13: 14 | U13: 14 | V13: 13 | W13: 13 | X13: 13 | Y13: 13 | Z13: 12 | AA13: 12 | AB13: 12 | AC13: 12 | AD13: 12 | AE13: 11 | AF13: 11 | AG13: BNEF LCOE - All Technologies - Unites States - LCOE Forecast 2022 | AH13: To be converted in $/GJ with conversion factor in Universal Inputs "conversion_electricity" OR just | AI13: https://www.bnef.com/flagships/lcoe
A14: PV tracking with storage | B14: LCOE $/MWh (low) | C14: 2022 2H | D14: 38.62069 | E14: 44 | F14: 40 | G14: 35 | H14: 34 | I14: 32 | J14: 30 | K14: 28 | L14: 26 | M14: 25 | N14: 23 | O14: 22 | P14: 22 | Q14: 21 | R14: 21 | S14: 20 | T14: 20 | U14: 20 | V14: 19 | W14: 19 | X14: 19 | Y14: 18 | Z14: 18 | AA14: 18 | AB14: 18 | AC14: 18 | AD14: 17 | AE14: 17 | AF14: 17 | AG14: BNEF LCOE - All Technologies - Unites States - LCOE Forecast 2022 | AH14: To be converted in $/GJ with conversion factor in Universal Inputs "conversion_electricity" OR just | AI14: https://www.bnef.com/flagships/lcoe | AJ14: =15.3/1000 -> 0.0153 | AK14: [t-CO2,eq GJ-1] | AL14: Young et al. (2023)
A15: Utility-scale battery (1h) | B15: LCOE $/MWh (low) | C15: 2022 2H | D15: 160 | E15: 136 | F15: 119 | G15: 106 | H15: 96 | I15: 88 | J15: 81 | K15: 78 | L15: 75 | M15: 71 | N15: 67 | O15: 65 | P15: 63 | Q15: 59 | R15: 58 | S15: 57 | T15: 56 | U15: 55 | V15: 54 | W15: 54 | X15: 54 | Y15: 54 | Z15: 54 | AA15: 54 | AB15: 54 | AC15: 54 | AD15: 54 | AE15: 54 | AF15: 54 | AG15: BNEF LCOE - All Technologies - Unites States - LCOE Forecast 2022 | AH15: To be converted in $/GJ with conversion factor in Universal Inputs "conversion_electricity" OR just | AI15: https://www.bnef.com/flagships/lcoe
A16: Utility-scale battery (4h) | B16: LCOE $/MWh (low) | C16: 2022 2H | D16: 123 | E16: 99 | F16: 83 | G16: 72 | H16: 63 | I16: 56 | J16: 50 | K16: 47 | L16: 45 | M16: 43 | N16: 41 | O16: 39 | P16: 38 | Q16: 36 | R16: 36 | S16: 35 | T16: 35 | U16: 34 | V16: 34 | W16: 34 | X16: 34 | Y16: 34 | Z16: 34 | AA16: 34 | AB16: 34 | AC16: 34 | AD16: 34 | AE16: 34 | AF16: 34 | AG16: BNEF LCOE - All Technologies - Unites States - LCOE Forecast 2022 | AH16: To be converted in $/GJ with conversion factor in Universal Inputs "conversion_electricity" OR just | AI16: https://www.bnef.com/flagships/lcoe
A17: Wind offshore | B17: LCOE $/MWh (low) | C17: 2022 2H | D17: 116 | E17: 107 | F17: 102 | G17: 97 | H17: 94 | I17: 91 | J17: 88 | K17: 86 | L17: 54 | M17: 53 | N17: 52 | O17: 51 | P17: 50 | Q17: 49 | R17: 48 | S17: 47 | T17: 46 | U17: 45 | V17: 44 | W17: 44 | X17: 43 | Y17: 43 | Z17: 42 | AA17: 42 | AB17: 41 | AC17: 40 | AD17: 40 | AE17: 40 | AF17: 40 | AG17: BNEF LCOE - All Technologies - Unites States - LCOE Forecast 2022 | AH17: To be converted in $/GJ with conversion factor in Universal Inputs "conversion_electricity" OR just | AI17: https://www.bnef.com/flagships/lcoe
A18: Wind onshore | B18: LCOE $/MWh (low) | C18: 2022 2H | D18: 33 | E18: 31 | F18: 29 | G18: 28 | H18: 27 | I18: 26 | J18: 25 | K18: 25 | L18: 24 | M18: 24 | N18: 23 | O18: 23 | P18: 22 | Q18: 22 | R18: 22 | S18: 21 | T18: 21 | U18: 21 | V18: 21 | W18: 20 | X18: 20 | Y18: 20 | Z18: 20 | AA18: 20 | AB18: 19 | AC18: 19 | AD18: 19 | AE18: 19 | AF18: 19 | AG18: BNEF LCOE - All Technologies - Unites States - LCOE Forecast 2022 | AH18: To be converted in $/GJ with conversion factor in Universal Inputs "conversion_electricity" OR just | AI18: https://www.bnef.com/flagships/lcoe
A19: Wind onshore with storage | B19: LCOE $/MWh (low) | C19: 2022 2H | D19: 49 | E19: 45 | F19: 42 | G19: 39 | H19: 37 | I19: 36 | J19: 35 | K19: 34 | L19: 33 | M19: 32 | N19: 31 | O19: 31 | P19: 30 | Q19: 30 | R19: 29 | S19: 29 | T19: 29 | U19: 28 | V19: 28 | W19: 28 | X19: 27 | Y19: 27 | Z19: 27 | AA19: 27 | AB19: 26 | AC19: 26 | AD19: 26 | AE19: 26 | AF19: 26 | AG19: BNEF LCOE - All Technologies - Unites States - LCOE Forecast 2022 | AH19: To be converted in $/GJ with conversion factor in Universal Inputs "conversion_electricity" OR just | AI19: https://www.bnef.com/flagships/lcoe | AJ19: =5.9/1000 -> 0.0059 | AK19: [t-CO2,eq GJ-1] | AL19: Young et al. (2023)
A20: CCGT | B20: LCOE $/MWh (high) | C20: 2022 2H | D20: 93 | E20: 91 | F20: 91 | G20: 90 | H20: 90 | I20: 91 | J20: 91 | K20: 92 | L20: 92 | M20: 93 | N20: 93 | O20: 94 | P20: 94 | Q20: 94 | R20: 95 | S20: 95 | T20: 95 | U20: 96 | V20: 96 | W20: 96 | X20: 96 | Y20: 97 | Z20: 97 | AA20: 97 | AB20: 97 | AC20: 97 | AD20: 97 | AE20: 97 | AF20: 97 | AG20: BNEF LCOE - All Technologies - Unites States - LCOE Forecast 2022 | AH20: To be converted in $/GJ with conversion factor in Universal Inputs "conversion_electricity" OR just | AI20: https://www.bnef.com/flagships/lcoe
A21: CCGT CCS | B21: LCOE $/MWh (high) | C21: 2022 2H | D21: 479 | E21: 435 | F21: 395 | G21: 351 | H21: 312 | I21: 274 | J21: 235 | K21: 196 | L21: 158 | M21: 158 | N21: 159 | O21: 159 | P21: 160 | Q21: 160 | R21: 161 | S21: 161 | T21: 161 | U21: 162 | V21: 162 | W21: 162 | X21: 162 | Y21: 163 | Z21: 163 | AA21: 163 | AB21: 163 | AC21: 163 | AD21: 163 | AE21: 163 | AF21: 163 | AG21: BNEF LCOE - All Technologies - Unites States - LCOE Forecast 2022 | AH21: To be converted in $/GJ with conversion factor in Universal Inputs "conversion_electricity" OR just | AI21: https://www.bnef.com/flagships/lcoe
A22: CCGT Hydrogen | B22: LCOE $/MWh (high) | C22: 2022 2H | D22: 214 | E22: 195 | F22: 181 | G22: 168 | H22: 160 | I22: 153 | J22: 147 | K22: 143 | L22: 139 | M22: 136 | N22: 133 | O22: 129 | P22: 126 | Q22: 122 | R22: 119 | S22: 117 | T22: 115 | U22: 113 | V22: 112 | W22: 111 | X22: 111 | Y22: 110 | Z22: 110 | AA22: 109 | AB22: 109 | AC22: 108 | AD22: 108 | AE22: 108 | AF22: 108 | AG22: BNEF LCOE - All Technologies - Unites States - LCOE Forecast 2022 | AH22: To be converted in $/GJ with conversion factor in Universal Inputs "conversion_electricity" OR just | AI22: https://www.bnef.com/flagships/lcoe
A23: Coal | B23: LCOE $/MWh (high) | C23: 2022 2H | D23: 158 | E23: 161 | F23: 164 | G23: 164 | H23: 167 | I23: 170 | J23: 172 | K23: 174 | L23: 176 | M23: 178 | N23: 180 | O23: 182 | P23: 183 | Q23: 185 | R23: 186 | S23: 188 | T23: 189 | U23: 190 | V23: 191 | W23: 192 | X23: 192 | Y23: 192 | Z23: 192 | AA23: 192 | AB23: 192 | AC23: 192 | AD23: 192 | AE23: 192 | AF23: 192 | AG23: BNEF LCOE - All Technologies - Unites States - LCOE Forecast 2022 | AH23: To be converted in $/GJ with conversion factor in Universal Inputs "conversion_electricity" OR just | AI23: https://www.bnef.com/flagships/lcoe
A24: Coal CCS | B24: LCOE $/MWh (high) | C24: 2022 2H | D24: 730 | E24: 699 | F24: 659 | G24: 600 | H24: 546 | I24: 488 | J24: 426 | K24: 361 | L24: 293 | M24: 297 | N24: 300 | O24: 303 | P24: 305 | Q24: 308 | R24: 310 | S24: 313 | T24: 315 | U24: 317 | V24: 319 | W24: 321 | X24: 321 | Y24: 321 | Z24: 321 | AA24: 321 | AB24: 321 | AC24: 321 | AD24: 321 | AE24: 321 | AF24: 321 | AG24: BNEF LCOE - All Technologies - Unites States - LCOE Forecast 2022 | AH24: To be converted in $/GJ with conversion factor in Universal Inputs "conversion_electricity" OR just | AI24: https://www.bnef.com/flagships/lcoe
A25: OCGT | B25: LCOE $/MWh (high) | C25: 2022 2H | D25: 223 | E25: 224 | F25: 225 | G25: 226 | H25: 227 | I25: 229 | J25: 230 | K25: 232 | L25: 233 | M25: 235 | N25: 236 | O25: 237 | P25: 238 | Q25: 239 | R25: 241 | S25: 242 | T25: 243 | U25: 244 | V25: 244 | W25: 245 | X25: 246 | Y25: 247 | Z25: 247 | AA25: 248 | AB25: 248 | AC25: 249 | AD25: 249 | AE25: 249 | AF25: 249 | AG25: BNEF LCOE - All Technologies - Unites States - LCOE Forecast 2022 | AH25: To be converted in $/GJ with conversion factor in Universal Inputs "conversion_electricity" OR just | AI25: https://www.bnef.com/flagships/lcoe
A26: OCGT CCS | B26: LCOE $/MWh (high) | C26: 2022 2H | D26: 1,148 | E26: 1,059 | F26: 964 | G26: 868 | H26: 772 | I26: 678 | J26: 584 | K26: 489 | L26: 395 | M26: 396 | N26: 398 | O26: 399 | P26: 401 | Q26: 402 | R26: 403 | S26: 404 | T26: 405 | U26: 407 | V26: 408 | W26: 409 | X26: 409 | Y26: 410 | Z26: 411 | AA26: 411 | AB26: 412 | AC26: 412 | AD26: 412 | AE26: 412 | AF26: 412 | AG26: BNEF LCOE - All Technologies - Unites States - LCOE Forecast 2022 | AH26: To be converted in $/GJ with conversion factor in Universal Inputs "conversion_electricity" OR just | AI26: https://www.bnef.com/flagships/lcoe
A27: OCGT Hydrogen | B27: LCOE $/MWh (high) | C27: 2022 2H | D27: 540 | E27: 506 | F27: 475 | G27: 447 | H27: 423 | I27: 403 | J27: 385 | K27: 371 | L27: 360 | M27: 350 | N27: 341 | O27: 332 | P27: 323 | Q27: 314 | R27: 306 | S27: 299 | T27: 295 | U27: 291 | V27: 288 | W27: 286 | X27: 284 | Y27: 283 | Z27: 281 | AA27: 280 | AB27: 279 | AC27: 278 | AD27: 278 | AE27: 277 | AF27: 277 | AG27: BNEF LCOE - All Technologies - Unites States - LCOE Forecast 2022 | AH27: To be converted in $/GJ with conversion factor in Universal Inputs "conversion_electricity" OR just | AI27: https://www.bnef.com/flagships/lcoe
A28: PV non-tracking | B28: LCOE $/MWh (high) | C28: 2022 2H | D28: 60 | E28: 53 | F28: 50 | G28: 45 | H28: 43 | I28: 42 | J28: 40 | K28: 38 | L28: 35 | M28: 32 | N28: 29 | O28: 28 | P28: 28 | Q28: 27 | R28: 26 | S28: 26 | T28: 25 | U28: 24 | V28: 24 | W28: 23 | X28: 23 | Y28: 22 | Z28: 22 | AA28: 21 | AB28: 21 | AC28: 21 | AD28: 20 | AE28: 20 | AF28: 20 | AG28: BNEF LCOE - All Technologies - Unites States - LCOE Forecast 2022 | AH28: To be converted in $/GJ with conversion factor in Universal Inputs "conversion_electricity" OR just | AI28: https://www.bnef.com/flagships/lcoe
A29: PV non-tracking with storage | B29: LCOE $/MWh (high) | C29: 2022 2H | D29: 188 | E29: 163 | F29: 146 | G29: 129 | H29: 119 | I29: 110 | J29: 103 | K29: 98 | L29: 93 | M29: 88 | N29: 83 | O29: 81 | P29: 79 | Q29: 76 | R29: 75 | S29: 74 | T29: 73 | U29: 71 | V29: 70 | W29: 70 | X29: 69 | Y29: 69 | Z29: 68 | AA29: 68 | AB29: 67 | AC29: 67 | AD29: 67 | AE29: 66 | AF29: 66 | AG29: BNEF LCOE - All Technologies - Unites States - LCOE Forecast 2022 | AH29: To be converted in $/GJ with conversion factor in Universal Inputs "conversion_electricity" OR just | AI29: https://www.bnef.com/flagships/lcoe
A30: PV tracking | B30: LCOE $/MWh (high) | C30: 2022 2H | D30: 53 | E30: 48 | F30: 44 | G30: 40 | H30: 39 | I30: 37 | J30: 36 | K30: 33 | L30: 31 | M30: 28 | N30: 26 | O30: 25 | P30: 25 | Q30: 24 | R30: 23 | S30: 23 | T30: 22 | U30: 22 | V30: 21 | W30: 21 | X30: 20 | Y30: 20 | Z30: 19 | AA30: 19 | AB30: 19 | AC30: 18 | AD30: 18 | AE30: 18 | AF30: 18 | AG30: BNEF LCOE - All Technologies - Unites States - LCOE Forecast 2022 | AH30: To be converted in $/GJ with conversion factor in Universal Inputs "conversion_electricity" OR just | AI30: https://www.bnef.com/flagships/lcoe
A31: PV tracking with storage | B31: LCOE $/MWh (high) | C31: 2022 2H | D31: 160 | E31: 141 | F31: 124 | G31: 110 | H31: 102 | I31: 94 | J31: 88 | K31: 83 | L31: 79 | M31: 75 | N31: 71 | O31: 69 | P31: 67 | Q31: 65 | R31: 64 | S31: 63 | T31: 62 | U31: 61 | V31: 60 | W31: 60 | X31: 59 | Y31: 59 | Z31: 58 | AA31: 58 | AB31: 58 | AC31: 57 | AD31: 57 | AE31: 56 | AF31: 56 | AG31: BNEF LCOE - All Technologies - Unites States - LCOE Forecast 2022 | AH31: To be converted in $/GJ with conversion factor in Universal Inputs "conversion_electricity" OR just | AI31: https://www.bnef.com/flagships/lcoe | AJ31: =15.3/1000 -> 0.0153 | AK31: [t-CO2,eq GJ-1] | AL31: Young et al. (2023)
A32: Utility-scale battery (1h) | B32: LCOE $/MWh (high) | C32: 2022 2H | D32: 287 | E32: 241 | F32: 209 | G32: 184 | H32: 165 | I32: 151 | J32: 139 | K32: 132 | L32: 127 | M32: 119 | N32: 112 | O32: 109 | P32: 106 | Q32: 98 | R32: 96 | S32: 94 | T32: 92 | U32: 90 | V32: 88 | W32: 88 | X32: 88 | Y32: 88 | Z32: 88 | AA32: 88 | AB32: 88 | AC32: 88 | AD32: 88 | AE32: 88 | AF32: 88 | AG32: BNEF LCOE - All Technologies - Unites States - LCOE Forecast 2022 | AH32: To be converted in $/GJ with conversion factor in Universal Inputs "conversion_electricity" OR just | AI32: https://www.bnef.com/flagships/lcoe
A33: Utility-scale battery (4h) | B33: LCOE $/MWh (high) | C33: 2022 2H | D33: 206 | E33: 172 | F33: 146 | G33: 127 | H33: 112 | I33: 100 | J33: 89 | K33: 85 | L33: 81 | M33: 77 | N33: 74 | O33: 71 | P33: 69 | Q33: 66 | R33: 65 | S33: 63 | T33: 62 | U33: 61 | V33: 60 | W33: 60 | X33: 60 | Y33: 60 | Z33: 60 | AA33: 60 | AB33: 60 | AC33: 60 | AD33: 60 | AE33: 60 | AF33: 60 | AG33: BNEF LCOE - All Technologies - Unites States - LCOE Forecast 2022 | AH33: To be converted in $/GJ with conversion factor in Universal Inputs "conversion_electricity" OR just | AI33: https://www.bnef.com/flagships/lcoe
A34: Wind offshore | B34: LCOE $/MWh (high) | C34: 2022 2H | D34: 150 | E34: 137 | F34: 130 | G34: 124 | H34: 120 | I34: 116 | J34: 113 | K34: 110 | L34: 90 | M34: 88 | N34: 86 | O34: 84 | P34: 82 | Q34: 81 | R34: 79 | S34: 77 | T34: 76 | U34: 74 | V34: 73 | W34: 71 | X34: 71 | Y34: 70 | Z34: 69 | AA34: 68 | AB34: 67 | AC34: 66 | AD34: 66 | AE34: 66 | AF34: 65 | AG34: BNEF LCOE - All Technologies - Unites States - LCOE Forecast 2022 | AH34: To be converted in $/GJ with conversion factor in Universal Inputs "conversion_electricity" OR just | AI34: https://www.bnef.com/flagships/lcoe
A35: Wind onshore | B35: LCOE $/MWh (high) | C35: 2022 2H | D35: 65 | E35: 60 | F35: 55 | G35: 52 | H35: 50 | I35: 48 | J35: 46 | K35: 45 | L35: 44 | M35: 42 | N35: 41 | O35: 41 | P35: 40 | Q35: 39 | R35: 39 | S35: 38 | T35: 38 | U35: 37 | V35: 36 | W35: 36 | X35: 36 | Y35: 35 | Z35: 35 | AA35: 34 | AB35: 34 | AC35: 34 | AD35: 33 | AE35: 33 | AF35: 33 | AG35: BNEF LCOE - All Technologies - Unites States - LCOE Forecast 2022 | AH35: To be converted in $/GJ with conversion factor in Universal Inputs "conversion_electricity" OR just | AI35: https://www.bnef.com/flagships/lcoe
A36: Wind onshore with storage | B36: LCOE $/MWh (high) | C36: 2022 2H | D36: 132 | E36: 114 | F36: 99 | G36: 89 | H36: 82 | I36: 77 | J36: 72 | K36: 69 | L36: 67 | M36: 64 | N36: 62 | O36: 61 | P36: 59 | Q36: 58 | R36: 57 | S36: 56 | T36: 55 | U36: 54 | V36: 53 | W36: 53 | X36: 52 | Y36: 52 | Z36: 51 | AA36: 51 | AB36: 50 | AC36: 50 | AD36: 49 | AE36: 49 | AF36: 48 | AG36: BNEF LCOE - All Technologies - Unites States - LCOE Forecast 2022 | AH36: To be converted in $/GJ with conversion factor in Universal Inputs "conversion_electricity" OR just | AI36: https://www.bnef.com/flagships/lcoe | AJ36: =5.9/1000 -> 0.0059 | AK36: [t-CO2,eq GJ-1] | AL36: Young et al. (2023)
A37: Nuclear | B37: LCOE $/MWh (low) | C37: 2022 2H | D37: 43.9 | AI37: Nuclear Energy Agency (NEA) - Projected Costs of Generating Electricity - 2020 Edition (oecd-nea.org) | AJ37: =1.9/1000 -> 0.0019 | AK37: [t-CO2,eq GJ-1] | AL37: p.59
A38: Nuclear | B38: LCOE $/MWh (high) | C38: 2022 2H | D38: 98.56 | AI38: Nuclear Energy Agency (NEA) - Projected Costs of Generating Electricity - 2020 Edition (oecd-nea.org) | AJ38: =1.9/1000 -> 0.0019 | AL38: p.59
A39: Geothermal | B39: LCOE $/MWh (low) | C39: 2022 2H | D39: 37 | AI39: Renewable Power Generation Costs in 2021 (irena.org) | AJ39: =18.9/1000 -> 0.0189 | AK39: [t-CO2,eq GJ-1] | AL39: Young et al. (2023) | AM39: In line with icelandic LCOE | AN39: Global weighted average
A40: Geothermal | B40: LCOE $/MWh (high) | C40: 2022 2H | D40: 98.879151 | AI40: Renewable Power Generation Costs in 2021 (irena.org) | AJ40: =18.9/1000 -> 0.0189

Sheet Standard Input Calculations
B2: LCOE cost assumption
B4: Source: | C4: BNEF LCOE Forecast 2022
B5: Year | C5: 2022 | D5: 2023 | E5: 2024 | F5: 2025 | G5: 2026 | H5: 2027 | I5: 2028 | J5: 2029 | K5: 2030 | L5: 2031 | M5: 2032 | N5: 2033 | O5: 2034 | P5: 2035 | Q5: 2036 | R5: 2037 | S5: 2038 | T5: 2039 | U5: 2040 | V5: 2041 | W5: 2042 | X5: 2043 | Y5: 2044 | Z5: 2045 | AA5: 2046 | AB5: 2047 | AC5: 2048 | AD5: 2049 | AE5: 2050 | AF5: -
B6: LCOE ($/MWh) | C6: 79 | D6: 70 | E6: 64 | F6: 55 | G6: 52 | H6: 48 | I6: 44 | J6: 42 | K6: 38 | L6: 39 | M6: 35 | N6: 34 | O6: 34 | P6: 33 | Q6: 33 | R6: 30 | S6: 32 | T6: 32 | U6: 31 | V6: 31 | W6: 31 | X6: 28 | Y6: 30 | Z6: 30 | AA6: 30 | AB6: 30 | AC6: 27 | AD6: 29 | AE6: 29
B7: LCOE (€/MWh) | C7: 84 | D7: 75 | E7: 68 | F7: 59 | G7: 55 | H7: 51 | I7: 47 | J7: 45 | K7: 40.53 | L7: 42 | M7: 37 | N7: 36 | O7: 36 | P7: 35 | Q7: 35 | R7: 32 | S7: 34 | T7: 34 | U7: 33 | V7: 33 | W7: 33 | X7: 30 | Y7: 32 | Z7: 32 | AA7: 32 | AB7: 32 | AC7: 29 | AD7: 31 | AE7: 31
B9: Possible sensitivities
B10: PV tracking with storage (high) - 12 battery hours - high
B11: LCOE ($/MWh) | C11: 374 | D11: 327 | E11: 284 | F11: 250 | G11: 228 | H11: 208 | I11: 192 | J11: 183 | K11: 175 | L11: 169 | M11: 161 | N11: 157 | O11: 151 | P11: 147 | Q11: 146 | R11: 143 | S11: 142 | T11: 139 | U11: 138 | V11: 138 | W11: 137 | X11: 137 | Y11: 136 | Z11: 136 | AA11: 136 | AB11: 135 | AC11: 135 | AD11: 132 | AE11: 132
B12: PV tracking with storage (low) - 12 battery hours - high
B13: LCOE ($/MWh) | C13: 79 | D13: 70 | E13: 64 | F13: 55 | G13: 52 | H13: 48 | I13: 44 | J13: 42 | K13: 38 | L13: 39 | M13: 35 | N13: 34 | O13: 34 | P13: 33 | Q13: 33 | R13: 30 | S13: 32 | T13: 32 | U13: 31 | V13: 31 | W13: 31 | X13: 28 | Y13: 30 | Z13: 30 | AA13: 30 | AB13: 30 | AC13: 27 | AD13: 29 | AE13: 29
B14: Wind Offshore
B15: LCOE ($/MWh) | C15: 116 | D15: 107 | E15: 102 | F15: 97 | G15: 94 | H15: 91 | I15: 88 | J15: 86 | K15: 54 | L15: 53 | M15: 52 | N15: 51 | O15: 50 | P15: 49 | Q15: 48 | R15: 47 | S15: 46 | T15: 45 | U15: 44 | V15: 44 | W15: 43 | X15: 43 | Y15: 42 | Z15: 42 | AA15: 41 | AB15: 40 | AC15: 40 | AD15: 40 | AE15: 40
B18: DAC cost assumption | F18: Source | G18: Note
F19: Sievert et. al. (2024) | G19: Multi Component learning curves are considered
C20: Solid Sorbent | D20: Liquid Solvent | E20: CaO ambient weathering
B21: Start Year | C21: 2024 | D21: 2024 | E21: 2024
B22: End Year | C22: 2050 | D22: 2050 | E22: 2050
B25: Year | C25: 2024 | D25: 2050
B27: Solid Sorbent
B28: Capacity (MtCO2/year) | C28: 0.004 | D28: 1000
B29: LCOR ($/tCO2) | C29: 1282 | D29: 374
B30: LCOR low ($/tCO2) | C30: 1180 | D30: 281
B31: LCOR high ($/tCO2) | C31: 1392 | D31: 579
B33: Liquid Solvent
B34: Capacity (MtCO2/year) | C34: 0.5 | D34: 1000
B35: LCOR ($/tCO2) | C35: 670 | D35: 341
B36: LCOR low ($/tCO2) | C36: 521 | D36: 226
B37: LCOR high ($/tCO2) | C37: 894 | D37: 544
B39: CaO ambient weathering
B40: Capacity (MtCO2/year) | C40: 0.001 | D40: 1000
B41: LCOR ($/tCO2) | C41: 2481 | D41: 371
B42: LCOR low ($/tCO2) | C42: 2153 | D42: 230
B43: LCOR high ($/tCO2) | C43: 2874 | D43: 835
B45: Average
B46: LCOR ($/tCO2) | C46: =AVERAGE(C29,C35,C41) -> 1477.6667 | D46: =AVERAGE(D29,D35,D41) -> 362
B47: LCOR low ($/tCO2) | C47: =AVERAGE(C30,C36,C42) -> 1284.6667 | D47: =AVERAGE(D30,D36,D42) -> 245.66667
B48: LCOR high ($/tCO2) | C48: =AVERAGE(C31,C37,C43) -> 1720 | D48: =AVERAGE(D31,D37,D43) -> 652.66667
B50: LCOR DACCS Meta-Analysis
B51: 0.25 | C51: 295 | D51: 142
B52: 0.5 | C52: 440 | D52: 235
B53: 0.75 | C53: 1282 | D53: 479
B55: Discount rate
G57: Source
B58: Discount rate | C58: 0.07 | G58: Average across all studies considered (Multiple sources)
B61: Fossil fuel emissions
C62: 2024 | D62: 2050 | F62: Note | G62: Source
B63: Jet-Fuel A-1 | C63: 88.7 | D63: 88.7 | E63: gCO2/MJ | F63: Global Average WtW CO2 emissions of Jet-A1 (Jing et. al. 2023) | G63: https://www.icao.int/environmental-protection/CORSIA/Pages/SARPs-Annex-16-Volume-IV.aspx
B66: Fossil counterpart costs
B68: Costs from studies | G68: Source
B69: Jet-Fuel A-1 | C69: 0.36 | D69: €/l | E69: Aviation | G69: Martin (2013)
B72: Current fossil fuel costs | F72: Note | G72: Source | H72: Date Retrieved
B73: Jet-Fuel A-1 | C73: 0.8 | D73: $/l | E73: Aviation | F73: Global weighted average | G73: https://www.iata.org/en/publications/economics/fuel-monitor/ | H73: 45458
B74: Oil Price (Dated Brent) | C74: 0.65 | D74: $/l
B75: Price Factor (Jet A-1 to Oil) | C75: =C73/C74 -> 1.2307692
B77: Calculate fossil fuel projections based on IEA oil price projection
B79: 1. Import oil price development IEA (Net Zero, No new oil)
D80: 2010 | E80: 2020 | F80: 2030 | G80: 2040 | H80: 2050 | J80: Source
B81: IEA crude oil (2019 USD/barrel) | D81: 91 | E81: 37 | F81: 35 | G81: 28 | H81: 24 | J81: Net Zero by 2050 report, Table 2.1. (Oil cost in NZE scenario)
B82: IEA crude oil (2022 USD/barrel) | D82: 104.17 | E82: 42.35 | F82: 40.07 | G82: 32.05 | H82: 27.47
B83: IEA crude oil (2022 USD/l) | D83: 0.66 | E83: 0.27 | F83: 0.25 | G83: 0.2 | H83: 0.17
D85: 2024 | E85: 2050
B86: IEA crude oil (2022 USD/l) | D86: =_xlfn.FORECAST.LINEAR(D85,E83:F83,E80:F80) -> 0.262 | E86: 0.17
J87: Source
B88: 2. EIA Crude oil price development scenarios | J88: https://www.eia.gov/outlooks/aeo/data/browser/#/?id=1-AEO2023&region=0-0&cases=ref2023~highprice~lowprice~highogs~lowogs~highZTC~lowZTC~highmachighZTC~highmaclowZTC&start=2021&end=2050&f=A&sourcekey=0
D89: 2022 | E89: 2023 | F89: 2024 | G89: 2025 | H89: 2026 | I89: 2027 | J89: 2028 | K89: 2029 | L89: 2030 | M89: 2031 | N89: 2032 | O89: 2033 | P89: 2034 | Q89: 2035 | R89: 2036 | S89: 2037 | T89: 2038 | U89: 2039 | V89: 2040 | W89: 2041 | X89: 2042 | Y89: 2043 | Z89: 2044 | AA89: 2045 | AB89: 2046 | AC89: 2047 | AD89: 2048 | AE89: 2049 | AF89: 2050
B90: EIA Reference Scenario (2022 USD/barrel) | D90: 102.13 | E90: 95.329002 | F90: 98.708405 | G90: 94.878891 | H90: 97.830475 | I90: 100.42555 | J90: 103.26054 | K90: 106.22783 | L90: 109.43919 | M90: 112.63979 | N90: 116.26587 | O90: 119.61838 | P90: 123.39955 | Q90: 127.45785 | R90: 131.21597 | S90: 135.08392 | T90: 138.85072 | U90: 142.6973 | V90: 146.67824 | W90: 150.81691 | X90: 154.92827 | Y90: 159.09348 | Z90: 163.57149 | AA90: 167.98759 | AB90: 173.31236 | AC90: 178.17406 | AD90: 183.52431 | AE90: 189.21034 | AF90: 194.29927
B91: EIA High Oil Price Scenario (2022 USD/barrel) | D91: 102.13 | E91: 177.06796 | F91: 182.14681 | G91: 191.31384 | H91: 197.33255 | I91: 202.83218 | J91: 211.05893 | K91: 219.21205 | L91: 227.3071 | M91: 236.33316 | N91: 240.69312 | O91: 249.10892 | P91: 260.1398 | Q91: 266.78342 | R91: 272.32071 | S91: 282.42462 | T91: 282.71121 | U91: 288.89121 | V91: 295.32135 | W91: 304.38077 | X91: 312.71564 | Y91: 318.85574 | Z91: 326.68182 | AA91: 331.06988 | AB91: 336.73807 | AC91: 344.56201 | AD91: 354.44208 | AE91: 359.83899 | AF91: 366.38501
B92: EIA Low Oil Price Scenario (2022 USD/barrel) | D92: 102.13 | E92: 44.884354 | F92: 46.687332 | G92: 47.901821 | H92: 49.076511 | I92: 49.748993 | J92: 51.747452 | K92: 52.753216 | L92: 54.358501 | M92: 56.124962 | N92: 57.97823 | O92: 59.941422 | P92: 61.09449 | Q92: 62.968906 | R92: 65.077469 | S92: 66.809425 | T92: 68.127838 | U92: 70.004173 | V92: 70.147186 | W92: 71.453232 | X92: 72.752785 | Y92: 74.057518 | Z92: 76.086876 | AA92: 77.440018 | AB92: 80.134621 | AC92: 80.527222 | AD92: 83.010246 | AE92: 83.836517 | AF92: 86.677032
B94: EIA Reference Scenario (2022 USD/l) | D94: =D90/119 -> 0.85823527 | E94: =E90/119 -> 0.80108405 | F94: =F90/119 -> 0.82948239 | G94: =G90/119 -> 0.79730161 | H94: =H90/119 -> 0.82210483 | I94: =I90/119 -> 0.8439122 | J94: =J90/119 -> 0.86773566 | K94: =K90/119 -> 0.89267083 | ... AF94: =AF90/119 -> 1.632767
B95: EIA High Oil Price Scenario (2022 USD/l) | D95: =D91/119 -> 0.85823527 | E95: =E91/119 -> 1.4879661 | F95: =F91/119 -> 1.5306454 | G95: =G91/119 -> 1.6076794 | H95: =H91/119 -> 1.6582567 | I95: =I91/119 -> 1.7044721 | J95: =J91/119 -> 1.7736044 | K95: =K91/119 -> 1.8421181 | ... AF95: =AF91/119 -> 3.0788656
B96: EIA Low Oil Price Scenario (2022 USD/l) | D96: =D92/119 -> 0.85823527 | E96: =E92/119 -> 0.37717945 | F96: =F92/119 -> 0.39233052 | G96: =G92/119 -> 0.40253631 | H96: =H92/119 -> 0.41240766 | I96: =I92/119 -> 0.41805876 | J96: =J92/119 -> 0.43485254 | K96: =K92/119 -> 0.44330434 | ... AF96: =AF92/119 -> 0.72837842
B101: 3. Assuming "constant price factor", projected jet fuel A-1 costs:
D102: 2024 | E102: 2050
B103: IEA NZE (2022 USD/l) | D103: =D86*C75 -> 0.32246154 | E103: =E86*C75 -> 0.20923077
B104: EIA Reference (2022 USD/l) | D104: =F94*C75 -> 1.0209014 | E104: =AF94*C75 -> 2.0095594
B105: EIA High Oil Price (2022 USD/l) | D105: =F95*C75 -> 1.8838713 | E105: =AF95*C75 -> 3.7893731
B106: EIA Low Oil Price (2022 USD/l) | D106: =F96*C75 -> 0.48286833 | E106: =AF96*C75 -> 0.89646575
B108: Conversion factors
B110: Jet-Fuel A-1 Energy Density | C110: 43.2 | D110: MJ/kg | E110: https://www.energy.gov/sites/prod/files/2020/09/f78/beto-sust-aviation-fuel-sep-2020.pdf
B111: Jet-Fuel Volumetric Density | C111: 0.803 | D111: kg/l | E111: https://www.energy.gov/sites/prod/files/2020/09/f78/beto-sust-aviation-fuel-sep-2020.pdf

Sheet Sensitivities
A1: Coupling of CO2 and Electricity
A2: CO2 Price | B2: Electricity Price
A3: 406 | B3: 79
A4: 358 | B4: 29
A6: Slope | B6: =(A3-A4)/(B3-B4) -> 0.96 | C6: $/t per $/kWh
A9: Electricity Price Range
B10: 2024 | C10: 2050
A11: High | B11: 116 | C11: 40 | D11: Wind Offshore
A12: Low | B12: 64 | C12: 29
A14: CO2 Price Range
B15: 2024 | C15: 2050
A16: High | B16: 1477 | C16: 362
A17: Low | B17: 1284 | C17: 246 | D17: Lower bounds of multi component experience curves

Sheet Notes for Study Parameters
A2: Parameter | B2: Note | C2: Source
A3: Lifetime | B3: If lifetime is not explicitly mentioned, lifetime of Fischer-Tropsch unit or heliostat is considered | C3: FT reactor/heliostat is a critical component
A4: Energy Density of Sustainable Fuel | B4: Energy Density is assumed to be 43.2 MJ/kg if not provided | C4: https://www.energy.gov/sites/prod/files/2020/09/f78/beto-sust-aviation-fuel-sep-2020.pdf
A5: Volumetric Density of Sustainable Fuel | B5: Considered to be 0.76 kg/l if not mentioned | C5: https://www.qcintel.com/biofuels/assessment/sustainable-aviation-fuel-fob-ara-premium-SAFARP.html
A6: Electrolyser | B6: Efficiency assumed to be 85% for PEM. Energy requirement of 40kWh/kg H2 | C6: https://www.enapter.com/kb_post/how-much-hydrogen-can-be-produced-by-enapters-electrolyser-and-how-long-does-it-take-to-fill-a-500-l-tank/ https://www.ise.fraunhofer.de/content/dam/ise/de/documents/publications/studies/cost-forecast-for-low-temperature-electrolysis.pdf
A7: Synthetic Fuel Emissions | B7: If not provided, assumed to be a 70% reduction (minimum under EU Renewable Energy Directive (RED) | C7: https://www.ecac-ceac.org/images/activities/environment/ECAC_Guidance_on_SAF_DGs_endorsed_HighRes.pdf

Sheet Studies current & future cost
A1: Reference | B1: Included | C1: Year of Assumptions in Study | D1: DOI | E1: Pathway | F1: Pathway Detail | G1: Year of Cost | H1: Study Scenario | I1: Baseline | J1: LCOE Harmonized | K1: CO2 Cost Harmonized | L1: Fully Harmonized | M1: Electricity | N1: CO2 | O1: CAPEX | P1: Other OPEX | Q1: Study Type | R1: Plant Location | S1: Production
A2: Albrecht et. al. | C2: 2016 | D2: https://doi.org/10.1016/j.energy.2019.116511 | E2: e-Fuels | F2: Fischer Tropsch | G2: 2024 | H2: Reference | I2: =([1]Outputs!$C$10) * ((1+Inputs!$C$5) ^ (G2-C2)) -> 642.2967 | J2: =([1]Outputs!$D$10) * ((1+Inputs!$C$5) ^ (G2-C2)) -> 768.83261 | K2: =([1]Outputs!$E$10) * ((1+Inputs!$C$5) ^ (G2-C2)) -> 2386.5585 | L2: =([1]Outputs!$F$10) * ((1+Inputs!$C$5) ^ (G2-C2)) -> 2466.5878 | Q2: Industrial | R2: Europe | S2: 1.4477822e+08 | T2: This study has a detailed breakdown but considers a scenario where electricity is an output, leading to lower overall costs.
A3: Bachorz et. al | C3: 2024 | D3: https://www.researchsquare.com/article/rs-4241841/v1 | E3: e-Fuels | F3: Methanol | G3: 2024 | H3: Reference | I3: =[2]Outputs!$C$10 -> 2404.7475 | J3: =[2]Outputs!$D$10 -> 2435.2346 | K3: =[2]Outputs!$E$10 -> 1644.4988 | L3: =[2]Outputs!$F$10 -> 1623.8464 | M3: ='[2]Cost Breakdown'!$B$9 -> 0.091683397 | N3: ='[2]Cost Breakdown'!$B$8 -> 0.37268475 | O3: ='[2]Cost Breakdown'!$B$10 -> 0.51503063 | P3: ='[2]Cost Breakdown'!$B$11 -> 0.020601225 | Q3: Academic | R3: Europe | S3: - | T3: Due to a high WACC assumption (~11%, final wacc correction leads to lower cost)
A4: Brazzola et al. | C4: 2024 | E4: e-Fuels | F4: Fischer Tropsch | H4: Reference | Q4: Academic | R4: Worldwide | S4: -
A5: Dietrich et. al. | C5: 2018 | D5: https://doi.org/10.1016/j.biombioe.2017.07.006 | E5: e-Fuels | F5: Fischer Tropsch | G5: 2024 | H5: Reference | I5: =[3]Outputs!$C$10 -> 1144.7871 | J5: =[3]Outputs!$D$10 -> 706.66811 | K5: =[3]Outputs!$E$10 -> 2210.7958 | L5: =[3]Outputs!$F$10 -> 2210.7958 | M5: ='[3]Received Data'!$N$9 -> 0.11002479 | N5: ='[3]Received Data'!$N$8 -> 0.32309926 | O5: ='[3]Received Data'!$N$10 -> 0.51966602 | P5: ='[3]Received Data'!$N$11 -> 0.04720993 | Q5: Academic | R5: Europe
A6: Falter et. al. | C6: 2020 | D6: https://doi.org/10.1039/d0se00179a | E6: Solar Fuels | F6: Fischer Tropsch | G6: 2024 | H6: Reference | I6: =[4]Outputs!$C$10 * (1+Inputs!C5) ^ ('Standardization Results'!F40-'Standardization Results'!B40) -> 2029.869 | J6: =[4]Outputs!$D$10 * (1+Inputs!C5) ^ ('Standardization Results'!F40-'Standardization Results'!B40) -> 2086.9789 | K6: =[4]Outputs!$E$10 * (1+Inputs!C5) ^ ('Standardization Results'!F40-'Standardization Results'!B40) -> 8021.9643 | L6: =[4]Outputs!$F$10 * (1+Inputs!C5) ^ ('Standardization Results'!F40-'Standardization Results'!B40) -> 7995.8085 | Q6: Academic | R6: MENA | S6: 45872966 | T6: Most assumptions based on previous study
A7: Falter et. al. | C7: 2015 | D7: https://doi.org/10.1021/acs.est.5b03515 | E7: Solar Fuels | F7: Fischer Tropsch | G7: 2024 | H7: Reference | I7: =[5]Outputs!$J$10* (1+Inputs!C5) ^ ('Standardization Results'!F41-'Standardization Results'!B41) -> 471.65912 | J7: =[5]Outputs!$K$10* (1+Inputs!C5) ^ ('Standardization Results'!F41-'Standardization Results'!B41) -> 496.13588 | K7: =[5]Outputs!$L$10* (1+Inputs!C5) ^ ('Standardization Results'!F41-'Standardization Results'!B41) -> 4670.6876 | L7: =[5]Outputs!$M$10* (1+Inputs!C5) ^ ('Standardization Results'!F41-'Standardization Results'!B41) -> 5006.9118 | Q7: Academic | R7: MENA | S7: 58035000
A8: Falter et. al. | C8: 2015 | D8: https://doi.org/10.1021/acs.est.5b03515 | E8: Solar Fuels | F8: Fischer Tropsch | G8: 2024 | H8: Reference | I8: =[5]Outputs!$C$10* (1+Inputs!C5) ^ ('Standardization Results'!F42-'Standardization Results'!B42) -> 667.86758 | J8: =[5]Outputs!$D$10* (1+Inputs!C5) ^ ('Standardization Results'!F42-'Standardization Results'!B42) -> 692.34434 | K8: =[5]Outputs!$E$10* (1+Inputs!C5) ^ ('Standardization Results'!F42-'Standardization Results'!B42) -> 4866.896 | L8: =[5]Outputs!$F$10* (1+Inputs!C5) ^ ('Standardization Results'!F42-'Standardization Results'!B42) -> 5216.4445 | M8: ='[5]Cost Breakdowns'!$B$10 -> 0.058359447 | N8: ='[5]Cost Breakdowns'!$B$9 -> 0.66723593 | O8: ='[5]Cost Breakdowns'!$B$11 -> 0.10459443 | P8: ='[5]Cost Breakdowns'!$B$12 -> 0.1698102 | Q8: Academic | R8: MENA | S8: 58035000 | T8: Initial assumptions are very optimistic (by author's admission), Production is high. Overall process efficiency is 5% according to the author
A9: Gray et al. | C9: 2024 | D9: https://doi.org/10.1016/j.rser.2024.114552 | E9: e-Fuels | F9: Fischer Tropsch | G9: 2024 | H9: Reference DAC Deployment | I9: =[6]Outputs!$J$10 -> 2727.5773 | J9: =[6]Outputs!$K$10 -> 2805.9552 | K9: =[6]Outputs!$L$10 -> 1478.0572 | L9: =[6]Outputs!$M$10 -> 1555.9594 | M9: ='[6]LCOF WACC Corrected'!$J$9 -> 0.36289802 | N9: ='[6]LCOF WACC Corrected'!$J$8 -> 0.35987238 | O9: ='[6]LCOF WACC Corrected'!$J$10 -> 0.18908765 | P9: ='[6]LCOF WACC Corrected'!$J$11 -> 0.088141946 | Q9: Academic | R9: Europe | S9: 39140034
A10: Gray et al. | B10: y | C10: 2024 | D10: https://doi.org/10.1016/j.rser.2024.114552 | E10: e-Fuels | F10: Fischer Tropsch | G10: 2050 | H10: High DAC Deployment | I10: =[6]Outputs!$C$10 -> 1053.0157 | J10: =[6]Outputs!$D$10 -> 1131.3935 | K10: =[6]Outputs!$E$10 -> 1207.0426 | L10: =[6]Outputs!$F$10 -> 1284.9449 | M10: ='[6]LCOF WACC Corrected'!$M$9 -> 0.43600143 | N10: ='[6]LCOF WACC Corrected'!$M$8 -> 0.23092291 | O10: ='[6]LCOF WACC Corrected'!$M$10 -> 0.22717811 | P10: ='[6]LCOF WACC Corrected'!$M$11 -> 0.10589756 | Q10: Academic | R10: Europe | S10: 39140034 | T10: This scenario assumes a decline in CO2 cost but not CAPEX
A11: Marchese et.al. | C11: 2021 | D11: https://doi.org/10.1016/j.jcou.2021.101487 | E11: e-Fuels | F11: Fischer Tropsch | G11: 2024 | H11: C.4 | I11: =[7]Outputs!$X$10* (1+Inputs!$C$5) ^ (G11-C11) -> 1458.3489 | J11: =[7]Outputs!$Y$10* (1+Inputs!$C$5) ^ (G11-C11) -> 751.42719 | K11: =[7]Outputs!$Z$10* (1+Inputs!$C$5)^ (G11-C11) -> 898.0069 | L11: =[7]Outputs!$AA$10* (1+Inputs!$C$5) ^ (G11-C11) -> 883.12721 | Q11: Academic | R11: Europe | S11: 69000000
A12: Marchese et.al. | C12: 2021 | D12: https://doi.org/10.1016/j.jcou.2021.101487 | E12: e-Fuels | F12: Fischer Tropsch | G12: 2024 | H12: C.1 | I12: =[7]Outputs!$C$10 * (1+Inputs!$C$5) ^ (G12-C12) -> 1892.3064 | J12: =[7]Outputs!$D$10* (1+Inputs!$C$5) ^ (G12-C12) -> 1097.7096 | K12: =[7]Outputs!$E$10* (1+Inputs!$C$5) ^ (G12-C12) -> 1157.1299 | L12: =[7]Outputs!$F$10* (1+Inputs!$C$5) ^ (G12-C12) -> 1141.2526 | M12: ='[7]Cost Breakdown'!$B$10 -> 0.27085063 | N12: ='[7]Cost Breakdown'!$B$9 -> 0.1799626 | O12: ='[7]Cost Breakdown'!$B$11 -> 0.30397259 | P12: ='[7]Cost Breakdown'!$B$12 -> 0.24521419 | Q12: Academic | R12: Europe | S12: 87000000
A13: Marchese et.al. | C13: 2021 | D13: https://doi.org/10.1016/j.jcou.2021.101487 | E13: e-Fuels | F13: Fischer Tropsch | G13: 2024 | H13: C.5 | I13: =[7]Outputs!$AE$10* (1+Inputs!$C$5) ^ (G13-C13) -> 1730.5108 | J13: =[7]Outputs!$AF$10* (1+Inputs!$C$5) ^ (G13-C13) -> 823.96436 | K13: =[7]Outputs!$AG$10* (1+Inputs!$C$5) ^ (G13-C13) -> 997.36187 | L13: =[7]Outputs!$AH$10* (1+Inputs!$C$5) ^ (G13-C13) -> 980.42742 | Q13: Academic | R13: Europe | S13: 68000000
A14: Marchese et.al. | C14: 2021 | D14: https://doi.org/10.1016/j.jcou.2021.101487 | E14: e-Fuels | F14: Fischer Tropsch | G14: 2024 | H14: C.3 | I14: =[7]Outputs!$Q$10* (1+Inputs!$C$5) ^ (G14-C14) -> 2708.6121 | J14: =[7]Outputs!$R$10* (1+Inputs!$C$5) ^(G14-C14) -> 1804.7169 | K14: =[7]Outputs!$S$10* (1+Inputs!$C$5) ^ (G14-C14) -> 1941.7692 | L14: =[7]Outputs!$T$10* (1+Inputs!$C$5) ^ (G14-C14) -> 1919.3136 | Q14: Academic | R14: Europe | S14: 48000000
A15: Marchese et.al. | C15: 2021 | D15: https://doi.org/10.1016/j.jcou.2021.101487 | E15: e-Fuels | F15: Fischer Tropsch | G15: 2024 | H15: C.2 | I15: =[7]Outputs!$J$10* 1.02 ^ (G15-C15) -> 2761.7003 | J15: =[7]Outputs!$K$10* 1.02 ^ (G15-C15) -> 1368.7085 | K15: =[7]Outputs!$L$10* 1.02 ^ (G15-C15) -> 1562.0729 | L15: =[7]Outputs!$M$10* 1.02 ^ (G15-C15) -> 1533.3503 | Q15: Academic | R15: Europe | S15: 35000000
A16: Marchese et.al. | B16: y | C16: 2021 | D16: https://doi.org/10.1016/j.jcou.2021.101487 | E16: e-Fuels | F16: Fischer Tropsch | G16: 2050 | H16: C.1 | I16: =[7]Outputs!$C$21* (1+Inputs!$C$5) ^ (G16-C16) -> 597.79762 | J16: =[7]Outputs!$D$21* (1+Inputs!$C$5) ^ (G16-C16) -> 297.6618 | K16: =[7]Outputs!$E$21* (1+Inputs!$C$5) ^ (G16-C16) -> 507.83267 | L16: =[7]Outputs!$F$21* (1+Inputs!$C$5) ^ (G16-C16) -> 497.82439 | M16: ='[7]Cost Breakdown'!$B$22 -> 0.28830506 | N16: ='[7]Cost Breakdown'!$B$21 -> 0.1573409 | O16: ='[7]Cost Breakdown'!$B$23 -> 0.15294257 | P16: ='[7]Cost Breakdown'!$B$24 -> 0.40141147 | Q16: Academic | R16: Europe | S16: 87000000
A17: Marchese et.al. | B17: y | C17: 2021 | D17: https://doi.org/10.1016/j.jcou.2021.101487 | E17: e-Fuels | F17: Fischer Tropsch | G17: 2050 | H17: C.2 | I17: =[7]Outputs!$J$21* (1+Inputs!$C$5) ^ (G17-C17) -> 1954.9193 | J17: =[7]Outputs!$K$21* (1+Inputs!$C$5) ^ (G17-C17) -> 1438.7117 | K17: =[7]Outputs!$L$21* (1+Inputs!$C$5) ^ (G17-C17) -> 1976.4189 | L17: =[7]Outputs!$M$21* (1+Inputs!$C$5) ^ (G17-C17) -> 1958.4433 | Q17: Academic | R17: Europe | S17: 35000000
A18: Marchese et.al. | B18: y | C18: 2021 | D18: https://doi.org/10.1016/j.jcou.2021.101487 | E18: e-Fuels | F18: Fischer Tropsch | G18: 2050 | H18: C.3 | I18: =[7]Outputs!$Q$21* (1+Inputs!$C$5) ^ (G18-C18) -> 1692.7913 | J18: =[7]Outputs!$R$21 * (1+Inputs!$C$5) ^ (G16-C16) -> 1109.928 | K18: =[7]Outputs!$S$21* (1+Inputs!$C$5) ^ (G16-C16) -> 1500.6866 | L18: =[7]Outputs!$T$21* (1+Inputs!$C$5) ^ (G16-C16) -> 1487.0626 | Q18: Academic | R18: Europe | S18: 48000000
A19: Marchese et.al. | B19: y | C19: 2021 | D19: https://doi.org/10.1016/j.jcou.2021.101487 | E19: e-Fuels | F19: Fischer Tropsch | G19: 2050 | H19: C.4 | I19: =[7]Outputs!$X$21* (1+Inputs!$C$5) ^ (G19-C19) -> 310.7968 | J19: =[7]Outputs!$Y$21* (1+Inputs!$C$5) ^ (G19-C19) -> 31.763718 | K19: =[7]Outputs!$Z$21* (1+Inputs!$C$5) ^(G19-C19) -> 320.74468 | L19: =[7]Outputs!$AA$21* (1+Inputs!$C$5) ^ (G19-C19) -> 310.75429 | Q19: Academic | R19: Europe | S19: 69000000
A20: Marchese et.al. | B20: y | C20: 2021 | D20: https://doi.org/10.1016/j.jcou.2021.101487 | E20: e-Fuels | F20: Fischer Tropsch | G20: 2050 | H20: C.5 | I20: =[7]Outputs!$AE$21* (1+Inputs!$C$5) ^ (G20-C20) -> 628.73238 | J20: =[7]Outputs!$AF$21* (1+Inputs!$C$5) ^ (G20-C20) -> 270.87595 | K20: =[7]Outputs!$AG$21* (1+Inputs!$C$5) ^ (G20-C20) -> 572.36067 | L20: =[7]Outputs!$AH$21* (1+Inputs!$C$5) ^ (G20-C20) -> 561.98413 | Q20: Academic | R20: Europe | S20: 68000000
A21: Martin et. al. | C21: 2023 | D21: https://www.sciencedirect.com/science/article/pii/S136403212300494X?via%3Dihub | E21: e-Fuels | F21: Fischer Tropsch | G21: 2024 | H21: Reference | I21: =[8]Outputs!$C$10 * (1+Inputs!C5) ^ ('Standardization Results'!F19-'Standardization Results'!B19) -> 1999.3691 | J21: =[8]Outputs!$D$10* (1+Inputs!C5) ^ ('Standardization Results'!F19-'Standardization Results'!B19) -> 1980.3771 | K21: =[8]Outputs!$E$10* (1+Inputs!C5) ^ ('Standardization Results'!F19-'Standardization Results'!B19) -> 1827.4016 | L21: =[8]Outputs!$F$10* (1+Inputs!C5) ^ ('Standardization Results'!F19-'Standardization Results'!B19) -> 1832.9217 | Q21: Academic | R21: Europe | S21: -
A22: Martin et. al. | B22: y | C22: 2023 | D22: https://www.sciencedirect.com/science/article/pii/S136403212300494X?via%3Dihub | E22: e-Fuels | F22: Fischer Tropsch | G22: 2050 | H22: Reference | I22: =[8]Outputs!$J$10 * (1+Inputs!C5) ^ ('Standardization Results'!F22-'Standardization Results'!B22) -> 209.51492 | J22: =[8]Outputs!$K$10* (1+Inputs!C5) ^ ('Standardization Results'!F22-'Standardization Results'!B22) -> 196.72581 | K22: =[8]Outputs!$L$10* (1+Inputs!C5) ^ ('Standardization Results'!F22-'Standardization Results'!B22) -> 384.1995 | L22: =[8]Outputs!$M$10* (1+Inputs!C5) ^ ('Standardization Results'!F22-'Standardization Results'!B22) -> 385.78482 | Q22: Academic | R22: Europe | S22: -
A23: Meurer et al. | C23: 2024 | D23: https://doi.org/10.1039/D3SE01156A | E23: e-Fuels | F23: Fischer Tropsch | G23: 2024 | H23: Reference | I23: =[9]Outputs!$C$10 -> 1678.5512 | J23: =[9]Outputs!$D$10 -> 1330.6142 | K23: =[9]Outputs!$E$10 -> 2039.9518 | L23: =[9]Outputs!$F$10 -> 2004.6361 | Q23: Academic | R23: Europe | S23: 3650000
A24: Moretti et al. | C24: 2023 | D24: https://doi.org/10.1016/j.scitotenv.2023.166005 | E24: Solar Fuels | F24: Fischer Tropsch | G24: 2024 | H24: Reference | I24: =[10]Outputs!$C$10 -> 838.68815 | J24: =[10]Outputs!$D$10 -> 793.08716 | K24: =[10]Outputs!$E$10 -> 549.23622 | L24: =[10]Outputs!$F$10 -> 614.21669 | M24: ='[10]MFSP WACC Corrected'!$B$39 -> -0.11475881 | N24: ='[10]MFSP WACC Corrected'!$B$40 -> 0.39312614 | O24: ='[10]MFSP WACC Corrected'!$B$38 -> 0.44920104 | P24: ='[10]MFSP WACC Corrected'!$B$41 -> 0.27243164 | Q24: Industrial | R24: MENA | S24: 31354838 | T24: High CO2 cost assumed, hence there is less effect, High Production levels lead to lower costs due to scale and cheaper labour in MENA
A25: Moretti et al. | B25: y | C25: 2023 | D25: https://doi.org/10.1016/j.scitotenv.2023.166005 | E25: Solar Fuels | F25: Fischer Tropsch | G25: 2050 | H25: Reference | I25: =[10]Outputs!$J$10 * (1+Inputs!$C$5) ^ (G25-C25) -> 982.3514 | J25: =[10]Outputs!$K$10 * (1+Inputs!$C$5) ^ (G25-C25) -> 982.36403 | K25: =[10]Outputs!$L$10 * (1+Inputs!$C$5) ^ (G25-C25) -> 976.94296 | L25: =[10]Outputs!$M$10 * (1+Inputs!$C$5) ^ (G25-C25) -> 1076.4346 | M25: ='[10]MFSP WACC Corrected'!$B$53 -> -3.6841458e-05 | N25: ='[10]MFSP WACC Corrected'!$B$54 -> 0.4089253 | O25: ='[10]MFSP WACC Corrected'!$B$52 -> 0.41554006 | P25: ='[10]MFSP WACC Corrected'!$B$55 -> 0.17557148 | Q25: Industrial | R25: MENA | S25: 31354838
A26: Moretti et al. | B26: y | C26: 2023 | D26: https://doi.org/10.1016/j.scitotenv.2023.166005 | E26: Solar Fuels | F26: Fischer Tropsch | G26: 2050 | H26: Optimistic | I26: =[10]Outputs!$Q$10 * (1+Inputs!$C$5) ^ ('Standardization Results'!F18-'Standardization Results'!B18) -> 858.71366 | J26: =[10]Outputs!$R$10* (1+Inputs!$C$5) ^ ('Standardization Results'!F18-'Standardization Results'!B18) -> 858.72679 | K26: =[10]Outputs!$S$10* (1+Inputs!$C$5) ^ ('Standardization Results'!F18-'Standardization Results'!B18) -> 853.08671 | L26: =[10]Outputs!$T$10* (1+Inputs!$C$5) ^ ('Standardization Results'!F18-'Standardization Results'!B18) -> 929.58904 | Q26: Industrial | R26: MENA | S26: 31354838
A27: Peacock et. al. | C27: 2024 | E27: e-Fuels | F27: Fischer Tropsch | G27: 2024 | H27: SOEC, Nuclear + Renewables | I27: =[11]Outputs!$Q$10 -> 2681.2488 | J27: =[11]Outputs!$R$10 -> 2495.6577 | K27: =[11]Outputs!$S$10 -> 2013.7955 | L27: =[11]Outputs!$T$10 -> 1988.4544 | Q27: Academic | R27: United Kingdom | S27: 157410000
A28: Peacock et. al. | C28: 2024 | E28: e-Fuels | F28: Fischer Tropsch | G28: 2024 | H28: PEM, Nuclear | I28: =[11]Outputs!$C$10 -> 3266.1214 | J28: =[11]Outputs!$D$10 -> 2576.9841 | K28: =[11]Outputs!$E$10 -> 1969.1598 | L28: =[11]Outputs!$F$10 -> 1947.4925 | Q28: Academic | R28: United Kingdom | S28: 157410000 | T28: Large scale production but high electrolyser costs and multiple replacements considered (missing from most other studies)
A29: Peacock et. al. | B29: y | C29: 2024 | E29: e-Fuels | F29: Fischer Tropsch | G29: 2050 | H29: PEM, Nuclear | I29: =[11]Outputs!$C$22 * (1+Inputs!$C$5) ^ ('Standardization Results'!F36-'Standardization Results'!B36) -> 1120.7136 | J29: =[11]Outputs!$D$22* (1+Inputs!$C$5) ^ ('Standardization Results'!F36-'Standardization Results'!B36) -> 983.41616 | K29: =[11]Outputs!$E$22* (1+Inputs!$C$5) ^ ('Standardization Results'!F36-'Standardization Results'!B36) -> 1214.6327 | L29: =[11]Outputs!$F$22* (1+Inputs!$C$5) ^ ('Standardization Results'!F36-'Standardization Results'!B36) -> 1197.7597 | Q29: Academic | R29: United Kingdom | S29: 157410000
A30: Peacock et. al. | B30: y | C30: 2024 | E30: e-Fuels | F30: Fischer Tropsch | G30: 2050 | H30: PEM, Nuclear + Renewables | I30: =[11]Outputs!$J$22* (1+Inputs!$C$5) ^ ('Standardization Results'!F37-'Standardization Results'!B37) -> 952.97687 | J30: =[11]Outputs!$K$22* (1+Inputs!$C$5) ^ ('Standardization Results'!F37-'Standardization Results'!B37) -> 964.92098 | K30: =[11]Outputs!$L$22* (1+Inputs!$C$5) ^ ('Standardization Results'!F37-'Standardization Results'!B37) -> 1151.5013 | L30: =[11]Outputs!$M$22* (1+Inputs!$C$5) ^ ('Standardization Results'!F37-'Standardization Results'!B37) -> 1134.6284 | M30: ='[11]Cost Breakdowns'!$B$22 -> 0.40154651 | N30: ='[11]Cost Breakdowns'!$B$21 -> 0.31639384 | O30: ='[11]Cost Breakdowns'!$B$23 -> 0.092223342 | P30: ='[11]Cost Breakdowns'!$B$24 -> 0.1898363 | Q30: Academic | R30: United Kingdom | S30: 157410000
A31: Peacock et. al. | B31: y | C31: 2024 | E31: e-Fuels | F31: Fischer Tropsch | G31: 2050 | H31: SOEC, Nuclear + Renewables | I31: =[11]Outputs!$Q$22 * (1+Inputs!$C$5) ^ ('Standardization Results'!F38-'Standardization Results'!B38) -> 1383.9118 | J31: =[11]Outputs!$R$22* (1+Inputs!$C$5) ^ ('Standardization Results'!F38-'Standardization Results'!B38) -> 1400.7491 | K31: =[11]Outputs!$S$22* (1+Inputs!$C$5) ^ ('Standardization Results'!F38-'Standardization Results'!B38) -> 1708.5223 | L31: =[11]Outputs!$T$22* (1+Inputs!$C$5) ^ ('Standardization Results'!F38-'Standardization Results'!B38) -> 1681.9374 | Q31: Academic | R31: United Kingdom | S31: 157410000
A32: Peacock et. al. | C32: 2024 | E32: e-Fuels | F32: Fischer Tropsch | G32: 2024 | H32: PEM, Nuclear + Renewables | I32: =[11]Outputs!$J$10 -> 2797.4452 | J32: =[11]Outputs!$K$10 -> 2548.3625 | K32: =[11]Outputs!$L$10 -> 2081.0539 | L32: =[11]Outputs!$M$10 -> 2059.3865 | M32: ='[11]Cost Breakdowns'!$B$10 -> 0.36579718 | N32: ='[11]Cost Breakdowns'!$B$9 -> 0.39350094 | O32: ='[11]Cost Breakdowns'!$B$11 -> 0.079277064 | P32: ='[11]Cost Breakdowns'!$B$12 -> 0.16142482 | Q32: Academic | R32: United Kingdom | S32: 157410000
A33: Peters et. al. | C33: 2022 | D33: https://doi.org/10.3390/pr10040699 | E33: e-Fuels | F33: Fischer Tropsch | G33: 2024 | H33: Baseline | I33: =[12]Outputs!$C$10 * (1+Inputs!C5) ^ ('Standardization Results'!F33-'Standardization Results'!B33) -> 642.42374 | J33: =[12]Outputs!$D$10* (1+Inputs!C5) ^ ('Standardization Results'!F33-'Standardization Results'!B33) -> 1011.8769 | K33: =[12]Outputs!$E$10 * (1+Inputs!C5) ^ ('Standardization Results'!F33-'Standardization Results'!B33) -> 3588.7386 | L33: =[12]Outputs!$F$10* (1+Inputs!C5) ^ ('Standardization Results'!F33-'Standardization Results'!B33) -> 3626.2481 | M33: ='[12]Cost of Manufacturing Models'!$F$10 -> 0.066800203 | N33: ='[12]Cost of Manufacturing Models'!$F$9 -> 0.46591807 | O33: ='[12]Cost of Manufacturing Models'!$F$11 -> 0.43493529 | P33: ='[12]Cost of Manufacturing Models'!$F$12 -> 0.032346433 | Q33: Academic | R33: Europe | S33: 208032000 | T33: Low intial electricity and CO2 price assumption lead to lower costs
A34: Rojas-Michaga et. al. | C34: 2023 | D34: https://www.sciencedirect.com/science/article/pii/S0196890423007732?via%3Dihub#s0005 | E34: e-Fuels | F34: Fischer Tropsch | G34: 2024 | H34: Reference | I34: =[13]Outputs!$C$10 * (1+Inputs!C5) ^ ('Standardization Results'!F30-'Standardization Results'!B30) -> 2879.4702 | J34: =[13]Outputs!$D$10 * (1+Inputs!C5) ^ ('Standardization Results'!F30-'Standardization Results'!B30) -> 2389.2886 | K34: =[13]Outputs!$E$10 * (1+Inputs!C5) ^ ('Standardization Results'!F20-'Standardization Results'!B20) -> 5490.9741 | L34: =[13]Outputs!$F$10 * (1+Inputs!C5) ^ ('Standardization Results'!F30-'Standardization Results'!B30) -> 5101.9877 | M34: ='[13]MJSP WACC Corrected'!$B$20 -> 0.28620653 | N34: ='[13]MJSP WACC Corrected'!$B$19 -> 0.47089021 | O34: ='[13]MJSP WACC Corrected'!$B$21 -> 0.025500914 | P34: ='[13]MJSP WACC Corrected'!$B$22 -> 0.21740235 | Q34: Academic | R34: United Kingdom | S34: 25105853 | T34: Very detailed study, we should note that this study considers a wide variety of costs that will be practically applicable (e.g. labour, overhead, catalyst, by-product sales etc.)
A35: Saad et al. | C35: 2024 | D35: https://doi.org/10.1021/acs.est.4c01578 | E35: e-Fuels | F35: Methanol | G35: 2024 | H35: CO2ER | I35: =[14]Outputs!$C$10 -> 6201.6747 | J35: =[14]Outputs!$D$10 -> 3818.5621 | K35: =[14]Outputs!$E$10 -> 3865.4181 | L35: =[14]Outputs!$F$10 -> 3949.4052 | M35: ='[14]Cost Breakdown'!$B$10 -> 0.18840662 | N35: ='[14]Cost Breakdown'!$B$9 -> 0.68456138 | O35: ='[14]Cost Breakdown'!$B$11 -> 0.11897367 | P35: ='[14]Cost Breakdown'!$B$12 -> 0.008058336 | Q35: Academic | R35: Europe | S35: 1250000000 | T35: LCA accounting methodology means that the emissions abated are low, therefore cost is high
A36: Saad et al. | C36: 2024 | D36: https://doi.org/10.1021/acs.est.4c01578 | E36: e-Fuels | F36: Methanol | G36: 2024 | H36: CO2HY | I36: =[14]Outputs!$J$10 -> 5186.3474 | J36: =[14]Outputs!$K$10 -> 3438.5193 | K36: =[14]Outputs!$L$10 -> 5951.2257 | L36: =[14]Outputs!$M$10 -> 6013.8338 | M36: ='[14]Cost Breakdown'!$B$22 -> 0.1011943 | N36: ='[14]Cost Breakdown'!$B$21 -> 0.61193523 | O36: ='[14]Cost Breakdown'!$B$23 -> 0.2723405 | P36: ='[14]Cost Breakdown'!$B$24 -> 0.014529965 | Q36: Academic | R36: Europe | S36: 1250000000
A37: Schmidt et. al. | B37: y | C37: 2024 | D37: https://onlinelibrary.wiley.com/doi/full/10.1002/cite.201700129?saml_referrer https://www.concawe.eu/wp-content/uploads/Rpt_24-4-1.pdf | E37: e-Fuels | F37: Fischer Tropsch | G37: 2050 | H37: EU-North | I37: =[15]Outputs!$C$21*((1+Inputs!$C$5)^($G$9-Inputs!$C$4)) -> 832.71053 | J37: =[15]Outputs!$D$21*((1+Inputs!$C$5)^($G$9-Inputs!$C$4)) -> 712.36778 | K37: =[15]Outputs!$E$21*((1+Inputs!$C$5)^($G$9-Inputs!$C$4)) -> 795.36025 | L37: =[15]Outputs!$F$21*((1+Inputs!$C$5)^($G$9-Inputs!$C$4)) -> 719.69502 | M37: ='[15]Cost Breakdown'!$B$22 -> 0.45315744 | N37: ='[15]Cost Breakdown'!$B$21 -> 0.31792431 | O37: ='[15]Cost Breakdown'!$B$23 -> 0.188823 | P37: ='[15]Cost Breakdown'!$B$24 -> 0.04009525 | Q37: Industrial | R37: Europe | S37: 1000000
A38: Schmidt et. al. | B38: y | C38: 2024 | D38: https://onlinelibrary.wiley.com/doi/full/10.1002/cite.201700129?saml_referrer https://www.concawe.eu/wp-content/uploads/Rpt_24-4-1.pdf | E38: e-Fuels | F38: Fischer Tropsch | G38: 2050 | H38: EU-Central | I38: =[15]Outputs!$J$21*((1+Inputs!$C$5)^($G$10-Inputs!$C$4)) -> 1651.2877 | J38: =[15]Outputs!$K$21*((1+Inputs!$C$5)^($G$10-Inputs!$C$4)) -> 1201.2151 | K38: =[15]Outputs!$L$21*((1+Inputs!$C$5)^($G$10-Inputs!$C$4)) -> 1340.0962 | L38: =[15]Outputs!$M$21*((1+Inputs!$C$5)^($G$10-Inputs!$C$4)) -> 1212.3243 | Q38: Industrial | R38: Europe | S38: 1000000
A39: Schmidt et. al. | B39: y | C39: 2024 | D39: https://onlinelibrary.wiley.com/doi/full/10.1002/cite.201700129?saml_referrer https://www.concawe.eu/wp-content/uploads/Rpt_24-4-1.pdf | E39: e-Fuels | F39: Fischer Tropsch | G39: 2050 | H39: EU-South | I39: =[15]Outputs!$Q$21*((1+Inputs!$C$5)^($G$9-Inputs!$C$4)) -> 832.16394 | J39: =[15]Outputs!$R$21*((1+Inputs!$C$5)^($G$9-Inputs!$C$4)) -> 711.82119 | K39: =[15]Outputs!$S$21*((1+Inputs!$C$5)^($G$9-Inputs!$C$4)) -> 794.81366 | L39: =[15]Outputs!$T$21*((1+Inputs!$C$5)^($G$9-Inputs!$C$4)) -> 719.3307 | Q39: Industrial | R39: Europe | S39: 1000000
A40: Schmidt et. al. | C40: 2024 | D40: https://onlinelibrary.wiley.com/doi/full/10.1002/cite.201700129?saml_referrer https://www.concawe.eu/wp-content/uploads/Rpt_24-4-1.pdf | E40: e-Fuels | F40: Fischer Tropsch | G40: 2024 | H40: EU-Central | I40: =[15]Outputs!$J$10*((1+Inputs!$C$5)^(G40-C40)) -> 1309.1064 | J40: =[15]Outputs!$K$10*((1+Inputs!$C$5)^(G40-C40)) -> 1104.4865 | K40: =[15]Outputs!$L$10*((1+Inputs!$C$5)^(G40-C40)) -> 1387.9542 | L40: =[15]Outputs!$M$10*((1+Inputs!$C$5)^(G40-C40)) -> 1287.5803 | Q40: Industrial | R40: Europe | S40: 1000000
A41: Schmidt et. al. | C41: 2024 | D41: https://onlinelibrary.wiley.com/doi/full/10.1002/cite.201700129?saml_referrer https://www.concawe.eu/wp-content/uploads/Rpt_24-4-1.pdf | E41: e-Fuels | F41: Fischer Tropsch | G41: 2024 | H41: EU-North | I41: =[15]Outputs!$C$10*((1+Inputs!$C$5)^(G41-'Standardization Results'!B23)) -> 1540.7127 | J41: =[15]Outputs!$D$10*((1+Inputs!$C$5)^(G41-'Standardization Results'!B23)) -> 1280.3735 | K41: =[15]Outputs!$E$10*((1+Inputs!$C$5)^(G41-'Standardization Results'!B23)) -> 1569.5106 | L41: =[15]Outputs!$F$10*((1+Inputs!$C$5)^(G41-'Standardization Results'!B23)) -> 1440.6043 | M41: ='[15]Cost Breakdown'!$B$10 -> 0.3247949 | N41: ='[15]Cost Breakdown'!$B$9 -> 0.25998799 | O41: ='[15]Cost Breakdown'!$B$11 -> 0.36706731 | P41: ='[15]Cost Breakdown'!$B$12 -> 0.048149798 | Q41: Industrial | R41: Europe | S41: 1000000 | T41: 1st of a kind industrial plant
A42: Schmidt et. al. | C42: 2024 | D42: https://onlinelibrary.wiley.com/doi/full/10.1002/cite.201700129?saml_referrer https://www.concawe.eu/wp-content/uploads/Rpt_24-4-1.pdf | E42: e-Fuels | F42: Fischer Tropsch | G42: 2024 | H42: EU-South | I42: =[15]Outputs!$Q$10*((1+Inputs!$C$5)^(Inputs!$C$4-'Standardization Results'!B24)) -> 1286.1593 | J42: =[15]Outputs!$R$10*((1+Inputs!$C$5)^(Inputs!$C$4-'Standardization Results'!B24)) -> 1276.9022 | K42: =[15]Outputs!$S$10*((1+Inputs!$C$5)^(Inputs!$C$4-'Standardization Results'!B24)) -> 1560.3699 | L42: =[15]Outputs!$T$10*((1+Inputs!$C$5)^(Inputs!$C$4-'Standardization Results'!B24)) -> 1430.6697 | Q42: Industrial | R42: Europe | S42: 1000000
A43: Seymour et al. | B43: y | C43: 2024 | D43: https://doi.org/10.1039/D3SE00978E | E43: e-Fuels | F43: Fischer Tropsch | G43: 2050 | H43: Reference | I43: =[16]Outputs!$K$10*(1+Inputs!$C$5)^(2050-'Standardization Results'!$B$4) -> 722.87277 | J43: =[16]Outputs!$L$10*(1+Inputs!$C$5)^(2050-'Standardization Results'!$B$4) -> 896.60784 | K43: =[16]Outputs!$M$10*(1+Inputs!$C$5)^(2050-'Standardization Results'!$B$4) -> 962.2823 | L43: =[16]Outputs!$N$10*(1+Inputs!$C$5)^(2050-'Standardization Results'!$B$4) -> 982.24476 | M43: ='[16]MFSP WACC Corrected'!$B$41 -> 0.50281004 | N43: ='[16]MFSP WACC Corrected'!$B$42 -> 0.2793751 | O43: ='[16]MFSP WACC Corrected'!$B$43 -> 0.14260508 | P43: ='[16]MFSP WACC Corrected'!$B$44 -> 0.075209772 | Q43: Academic | R43: United States of America | S43: 2110761
A44: Seymour et al. | C44: 2024 | D44: https://doi.org/10.1039/D3SE00978E | E44: e-Fuels | F44: Fischer Tropsch | G44: 2024 | H44: Reference | I44: =[16]Outputs!$C$10 -> 1703.2942 | J44: =[16]Outputs!$D$10 -> 1744.0993 | K44: =[16]Outputs!$E$10 -> 1362.544 | L44: =[16]Outputs!$F$10 -> 1404.66 | M44: ='[16]MFSP WACC Corrected'!$B$28 -> 0.424956 | N44: ='[16]MFSP WACC Corrected'!$B$29 -> 0.26939974 | O44: ='[16]MFSP WACC Corrected'!$B$30 -> 0.20057854 | P44: ='[16]MFSP WACC Corrected'!$B$31 -> 0.10506572 | Q44: Academic | R44: United States of America | S44: 2110761 | T44: High CO2 cost assumed, hence there is less effect
A45: Sherwin | C45: 2021 | D45: https://doi.org/10.1021/acs.est.0c07955 | E45: e-Fuels | F45: Fischer Tropsch | G45: 2024 | H45: Reference | I45: =[17]Outputs!$C$9 * (1+Inputs!$C$5) ^ (G45-C45) -> 1330.2315 | J45: =[17]Outputs!$D$9 * (1+Inputs!$C$5) ^ (G45-C45) -> 1583.3702 | K45: =[17]Outputs!$E$9 * (1+Inputs!$C$5) ^ (G45-C45) -> 1443.5942 | L45: =[17]Outputs!$F$9 * (1+Inputs!$C$5) ^ (G45-C45) -> 1169.7855 | Q45: Academic | R45: United States of America | S45: -
A46: Sherwin | B46: y | C46: 2021 | D46: https://doi.org/10.1021/acs.est.0c07955 | E46: e-Fuels | F46: Fischer Tropsch | G46: 2050 | H46: Reference | I46: =[17]Outputs!$J$9 * (1 +Inputs!$C$5) ^ ('Standardization Results'!F27-'Standardization Results'!B27) -> 84.263501 | J46: =[17]Outputs!$K$9 * (1 +Inputs!$C$5) ^ ('Standardization Results'!F27-'Standardization Results'!B27) -> 400.61385 | K46: =[17]Outputs!$L$9 * (1 +Inputs!$C$5) ^ ('Standardization Results'!F27-'Standardization Results'!B27) -> 573.6289 | L46: =[17]Outputs!$M$9 * (1 +Inputs!$C$5) ^ ('Standardization Results'!F27-'Standardization Results'!B27) -> 633.64187 | Q46: Academic | R46: United States of America | S46: -
A47: Staples et. al. | C47: 2021 | D47: https://doi.org/10.1021/acs.est.0c07674 | E47: e-Fuels | F47: Fischer Tropsch | G47: 2030 | H47: Reference | I47: =[18]Outputs!$C$10 -> 2544.8085 | J47: =[18]Outputs!$D$10 -> 1510.2027 | Q47: Academic | R47: United States of America | S47: -

Sheet Study Parameters
I1: Costs | M1: Input Values
A2: Reference | B2: Included? | C2: Year | D2: DOI | E2: Pathway | F2: Pathway Detail | G2: Timeline | H2: Learning Rates | I2: Cost Type | J2: Cost Range Short Term | K2: Cost Range 2050 | L2: Unit | M2: WACC / Discount Rate | N2: Electricity Price Range (EUR/MWh) | O2: Electricty Price Source | P2: Battery Storage | Q2: H2/H2O Source | R2: co-SOEC route? | S2: Electrolyser Cost Range (EUR/kW) | T2: H2 Price (EUR/kg) | U2: H2 Price Source | V2: H2 Storage | W2: CO2 Price Range ($/tCO2) | X2: CO2 Price Source | Y2: CO2 Storage | Z2: CO2 consumption (kg/kg fuel) | AA2: Fuel Emissions Intensity (gCO2/MJ) | AB2: Fossil Fuel Price (EUR/l) | AC2: Annual Production | AD2: Unit | AE2: Project Lifetime (Years) | AF2: LCA Methdology | AG2: Notes | AH2: Harmonization Status
A3: Seymour et al. | B3: Yes | C3: 2024 | D3: https://doi.org/10.1039/D3SE00978E | E3: e-Fuels | F3: Fischer Tropsch | G3: 2020-2050 | H3: Yes | I3: Abatement Cost | J3: 1500-1550 | K3: 450-890 | L3: EUR/tCO2 | M3: 0.05 | N3: 20-130 | O3: Eurostat Harmonised Indices of Consumer Prices, HICP | P3: Yes | Q3: PEM, Solid Oxide | R3: No | S3: 358-1084 | T3: - | U3: IEA G20 Hydrogen Report: Assumptions , International energy agency technical report, 2019 | V3: Yes | W3: 199-730 | X3: Fasihi et. al. (2019) (https://www.sciencedirect.com/science/article/pii/S0959652619307772?via%3Dihub) | Y3: Yes | Z3: 3.6 | AA3: 11 | AB3: 0.81 | AC3: 1018750 | AD3: litres | AE3: 30 | AF3: PSI, R.Sacchi | AH3: Fully Completed
A4: Meurer et al. | B4: Yes | C4: 2024 | D4: https://doi.org/10.1039/D3SE01156A | E4: e-Fuels | F4: Fischer Tropsch | G4: 2024-2050 | H4: Yes | I4: Production Cost | J4: 3.2-6.15 | K4: 1.5-2.75 | L4: EUR/l | M4: 0.15 | N4: 50-100 | O4: No Source, assumed | Q4: Solid Oxide | R4: Yes | S4: - | T4: - | U4: T. Smolinka , N. Wiebe , P. Sterchele and A. Palzer , Studie IndWEDe: Industrialisierung der Wasserelektrolyse in Deutschland: Chancen und Herausforderungen für nachhaltigen Wasserstoff für Verkehr, Strom und Wärme , NOW GmbH, 2018 | W4: 54-268 | X4: Fasihi et. al. (2019) (https://www.sciencedirect.com/science/article/pii/S0959652619307772?via%3Dihub) | AA4: - | AB4: - | AC4: 10000 | AD4: litres | AE4: 20 | AF4: GWP (24 parameters) | AH4: Meeting set for 11.07
A5: Martin et. al. | B5: Yes | C5: 2023 | D5: https://doi.org/10.1016/j.rser.2023.113637 | E5: e-Fuels | F5: Fischer Tropsch | G5: 2023-2050 | H5: Yes | I5: Levelised Cost | J5: 3.2-4.6 | K5: 1.1-1.4 | L5: EUR/l | M5: 0.06 | N5: 27.5-31 | O5: Fraunhofer (https://publica.fraunhofer.de/entities/publication/306f4a97-e39e-4570-887d-e4ba8ccd6605/details) | Q5: PEM | R5: No | S5: 330-1100 | T5: - | U5: T. Smolinka , N. Wiebe , P. Sterchele and A. Palzer , Studie IndWEDe: Industrialisierung der Wasserelektrolyse in Deutschland: Chancen und Herausforderungen für nachhaltigen Wasserstoff für Verkehr, Strom und Wärme , NOW GmbH, 2018 | W5: 90-600 | X5: Fasihi et. al. (2019) (https://www.sciencedirect.com/science/article/pii/S0959652619307772?via%3Dihub) | Z5: Not available | AA5: - | AB5: 0.28-0.52 | AC5: - | AE5: 25 | AH5: Fully Completed
A6: Schmidt et. al. | B6: Yes | C6: 2024 | D6: https://www.concawe.eu/wp-content/uploads/Rpt_24-4-1.pdf | E6: e-Fuels | F6: Fischer Tropsch | G6: 2018-2050 | H6: No | I6: Production Cost | J6: 3.1-4.2 | K6: 1.35-1.84 | L6: EUR/l | M6: 0.04 | N6: 66-100 | O6: No Source, assumed | P6: Yes | Q6: Alkaline, PEM | R6: No | S6: 600-1400 | T6: - | U6: https://www.osti.gov/biblio/1214980/ https://www.clean-hydrogen.europa.eu/system/files/2014-09/study%2520electrolyser_0-Logos_0_0.pdf | W6: Ground Up DAC modelling | X6: Climeworks plant, Hinwil, 2017 | AA6: 20 | AB6: - | AC6: - | AE6: - | AH6: Fully Completed
A7: Falter et. al. | B7: Yes | C7: 2015 | D7: https://doi.org/10.1021/acs.est.5b03515 | E7: Solar Fuels | F7: Fischer Tropsch | G7: 2015 | H7: No | I7: Production Cost | J7: 1.28-2.43 | K7: - | L7: EUR/l | M7: 0.06 | N7: 60 | O7: Assumed | P7: No | Q7: Desalination | R7: No | S7: Not Applicable | T7: - | U7: Not Applicable | V7: No | W7: 100 | X7: Assumed | Y7: No | Z7: 6 | AA7: 15 | AB7: - | AC7: 58035000 | AD7: litres | AE7: 25 | AH7: Fully Completed
A8: Staples et. al. | B8: Yes | C8: 2021 | D8: https://doi.org/10.1021/acs.est.0c07674 | E8: e-Fuels | F8: Fischer Tropsch | G8: 2021-2050 | H8: Yes | I8: Production Cost | J8: 2.66-3.11 | K8: 1.82-2.45 | L8: EUR/l | M8: 0.06 | N8: 45-55 | O8: https://www.eia.gov/outlooks/archive/aeo19/ | Q8: PEM, Solid Oxide | R8: No | S8: 920 | T8: - | U8: Albrecht 2020 (https://www.sciencedirect.com/science/article/pii/S0016236116312248?via%3Dihub) | W8: 94-232 | X8: Keith et al. (2018) https://www.cell.com/joule/fulltext/S2542-4351(18)30225-3?_returnURL=https%3A%2F%2Flinkinghub.elsevier.com%2Fretrieve%2Fpii%2FS2542435118302253%3Fshowall%3Dtrue | AA8: 27 | AB8: - | AC8: 58035000 | AD8: litres | AE8: 20 | AF8: GWP, excludes material flows | AH8: Partially Completed, CO2 missing
A9: Moretti et al. | B9: Yes | C9: 2023 | D9: https://doi.org/10.1016/j.scitotenv.2023.166005 | E9: Solar Fuels | F9: Fischer Tropsch | G9: 2023-2050 | H9: Yes | I9: Production Cost | J9: 2.5-3.2 | K9: 0.7-1.62 | L9: EUR/l | M9: 0.065 | N9: 50 | O9: Assumed | P9: No | Q9: Water | R9: No | S9: Not Applicable | T9: - | U9: Not Applicable | W9: 100-730 | X9: Sinha 2019 https://aiche.onlinelibrary.wiley.com/doi/10.1002/aic.16607 Climeworks, 2017 | Z9: 3 | AA9: 17.6 | AB9: - | AC9: 60000 | AD9: litres | AE9: 25 | AF9: Well-to-Wake assessment | AH9: Fully Completed
A10: Falter et. al. | B10: Yes | C10: 2020 | D10: https://doi.org/10.1039/d0se00179a | E10: Solar Fuels | F10: Fischer Tropsch | G10: 2050 | H10: No | I10: Production Cost | J10: - | K10: 1.72-2.55 | L10: EUR/l | M10: 0.08 | N10: 40 | O10: Assumed | P10: No | S10: Not Applicable | T10: - | U10: Not Applicable | W10: 100 | X10: Assumed | Z10: 6 | AA10: 19.7 | AB10: - | AC10: 58035000 | AD10: litres | AE10: 25 | AF10: Comprehensive consideration of all plant components | AH10: Fully Completed
A11: Rojas-Michaga et. al. | B11: Yes | C11: 2023 | D11: https://www.sciencedirect.com/science/article/pii/S0196890423007732?via%3Dihub#s0005 | E11: e-Fuels | F11: Fischer Tropsch | G11: 2023 | H11: No | I11: Production Cost | J11: 6.06 | K11: - | L11: EUR/l | M11: 0.08 | N11: 30-90 | O11: https://www.gov.uk/government/publications/energy-security-bill-factsheets/energy-security-bill-factsheet-network-charging-compensation-scheme-for-energy-intensive-industries | Q11: Alkaline | R11: No | S11: 444-663 | T11: 3.66 | U11: Holst, Marius, et al. "Cost forecast for low-temperature electrolysis-technology driven bottom-up prognosis for PEM and alkaline water electrolysis systems." Fraunhofer Institute for Solar Energy Systems ISE: Freiburg, Germany (2021). | W11: 360 | X11: Fasihi et. al. (2019) (https://www.sciencedirect.com/science/article/pii/S0959652619307772?via%3Dihub) | Z11: 5.28 | AA11: 21.43 | AB11: - | AC11: 21900000 | AD11: litres | AE11: 20 | AF11: Well-to-Wake assessment | AG11: Lifetime not explicitly indicated | AH11: Fully Completed
A12: Martin et. al. | B12: No | C12: 2023 | D12: https://doi.org/10.1016/j.adapen.2023.100156 | E12: e-Fuels | F12: Fischer Tropsch | G12: 2023-2050 | H12: Yes | I12: Abatement Cost | J12: 1100-1600 | K12: 220-400 | L12: EUR/tCO2 | M12: 0.06 | N12: 40 | O12: Fraunhofer (https://publica.fraunhofer.de/entities/publication/306f4a97-e39e-4570-887d-e4ba8ccd6605/details) | Q12: PEM | R12: No | S12: 330-1100 | T12: - | U12: T. Smolinka , N. Wiebe , P. Sterchele and A. Palzer , Studie IndWEDe: Industrialisierung der Wasserelektrolyse in Deutschland: Chancen und Herausforderungen für nachhaltigen Wasserstoff für Verkehr, Strom und Wärme , NOW GmbH, 2018 | W12: 54-268 | X12: Fasihi et. al. (2019) (https://www.sciencedirect.com/science/article/pii/S0959652619307772?via%3Dihub) | Z12: Not available | AA12: 15 | AB12: - | AC12: - | AE12: 15 | AF12: Electricity usage only | AH12: Use existing model with new assumptions
A13: Peters et. al. | B13: Yes | C13: 2022 | D13: https://doi.org/10.3390/pr10040699 | E13: e-Fuels | F13: Fischer Tropsch | G13: 2022 | H13: No | I13: Production Cost | J13: 0.94-1.85 | K13: - | L13: EUR/l | M13: 0.05 | N13: 40 | O13: Fraunhofer (https://publica.fraunhofer.de/entities/publication/306f4a97-e39e-4570-887d-e4ba8ccd6605/details) | Q13: PEM, Solid Oxide | R13: No | S13: 330-1100 | T13: - | U13: Not available | W13: 70 | X13: Assumed | Z13: 3.8 | AA13: - | AB13: - | AC13: 138057600 | AD13: litres | AE13: 20 | AF13: Minimum RED II requirement (70% reduction) | AH13: Fully Completed
A14: Albrecht et. al. | B14: Yes | C14: 2020 | D14: https://doi.org/10.1016/j.energy.2019.116511 | E14: e-Fuels | F14: Fischer Tropsch | G14: 2020 | H14: No | I14: Production Cost | J14: 2.01 | K14: - | L14: EUR/l | M14: 0.05 | N14: 60 | O14: ENTSO-E Denmark (Wind, Rambøll, and M. T. Højgaard. "Kriegers Flak Offshore Wind Farm." Conceptual study of Jacket Foundation for Wind Turbines (2009)) | P14: No | Q14: PEM | R14: No | S14: 950-1500 | T14: - | U14: https://www.sciencedirect.com/science/article/pii/S0360319917339435#sec4 | W14: 100 | X14: Assumed | Z14: 3.1 | AA14: 4.32 | AC14: 88355253 | AD14: litres | AE14: 30 | AF14: RED II sustainability criteria | AH14: Fully Completed
A15: Sherwin | B15: Yes | C15: 2021 | D15: https://doi.org/10.1021/acs.est.0c07955 | E15: e-Fuels | F15: Fischer Tropsch | G15: 2021-2050 | H15: Yes | I15: Production Cost | J15: 3.9-4.2 | K15: 1.1-1.38 | L15: EUR/l | M15: 0.08 | N15: 21-39 | Q15: PEM | S15: 446-1000 | T15: - | W15: 54-268 | X15: Fasihi et. al. (2019) (https://www.sciencedirect.com/science/article/pii/S0959652619307772?via%3Dihub) | AA15: - | AB15: 0.55 | AC15: - | AE15: 25 | AF15: Well to Tank assessment | AH15: Pending
A16: Dietrich et. al. | B16: Yes | C16: 2018 | D16: https://doi.org/10.1016/j.biombioe.2017.07.006 | E16: e-Fuels | F16: Fischer Tropsch | G16: 2018 | H16: No | I16: Production Cost | J16: 3-4.95 | K16: - | L16: EUR/l | M16: - | N16: 100 | Q16: PEM | T16: - | W16: - | X16: Fasihi et. al. (2019) (https://www.sciencedirect.com/science/article/pii/S0959652619307772?via%3Dihub) | AA16: - | AB16: - | AC16: - | AE16: - | AH16: Pending
A17: Brazzola et al. | B17: Yes | C17: 2024 | E17: e-Fuels | F17: Fischer Tropsch | G17: 2024-2050 | H17: Yes | I17: Abatement Cost | L17: EUR/tCO2 | N17: 30 | Q17: Alkaline, PEM | S17: 758-920 | T17: - | W17: 250-870 | AA17: - | AB17: - | AC17: - | AF17: GWP* includes non-CO2 effects | AG17: Lower estimate of CO2 price is from learning rate of 12% for DAC | AH17: Awaiting Author Response
A18: Saad et al. | B18: Yes | C18: 2024 | D18: https://doi.org/10.1021/acs.est.4c01578 | E18: e-Fuels | F18: Methanol | G18: 2024 | H18: No | I18: Production Cost | J18: 9.8-12.5 | K18: - | L18: EUR/l | N18: 195 | Q18: PEM | S18: 1100 | T18: - | W18: 250-1200 | X18: Young et al. (https://chemrxiv.org/engage/chemrxiv/article-details/62c8275b252b2116a8df9365) | Z18: 3.4 | AA18: 45 | AB18: 1.5 | AC18: 80000 | AD18: litres | AE18: 25 | AF18: Well-to-Wake assessment | AG18: CO2 cost from Young et. al. (Climeworks, Hinwil) Annual Production from Sensitivity Analysis
A19: Bachorz et al. | B19: Yes | C19: 2024 | D19: https://www.researchsquare.com/article/rs-4241841/v1 | E19: e-Fuels | F19: Methanol | G19: 2024-2050 | H19: Yes | I19: Production Cost | Z19: 3.24 | AH19: Fully Completed
A20: Gray et al. | B20: Yes | C20: 2024 | D20: https://doi.org/10.1016/j.rser.2024.114552 | E20: e-Fuels | F20: Fischer Tropsch | G20: 2024 | H20: No | I20: Production Cost | J20: 2.5-15 | L20: EUR/l | M20: 0.06 | N20: 40 | Q20: - | S20: 800 | T20: - | W20: 900 | Z20: 4.6 | AA20: 20 | AB20: - | AC20: 24820000 | AD20: litres | AE20: 25 | AG20: Annual Production derived from FT unit capacity factor | AH20: Fully Completed
A21: Marchese et.al | B21: Yes | C21: 2021 | D21: https://doi.org/10.1016/j.jcou.2021.101487 | E21: e-Fuels | F21: Fischer Tropsch | G21: 2021-2050 | I21: Production Cost | N21: 41-210 | O21: Several sources | S21: 360-1050 | W21: Ground Up DAC modelling | X21: Fasihi et. al. (2019) (https://www.sciencedirect.com/science/article/pii/S0959652619307772?via%3Dihub) | Z21: 3.13 | AC21: 87000 | AD21: litres | AF21: Assumed to be net zero using DAC
A22: Peacock et. al. | B22: Yes | C22: 2024 | D22: https://doi.org/10.1016/j.ijhydene.2023.09.094 | E22: e-Fuels | F22: Fischer Tropsch | G22: 2024-2050 | I22: Production Cost | N22: 34 - 105 | Q22: PEM, Solid Oxide | S22: 400-772 | W22: Ground Up DAC modelling (~200) | Z22: 5.08 | AC22: 157410000 | AD22: litres | AF22: Well-toWake assessment
Z23: =AVERAGE(Z3:Z22) -> 4.1858333

Sheet Study Parameters 2050
A1: Reference | B1: Included in Meta-analysis? | C1: Included in code? | D1: Year | E1: DOI | F1: Pathway | G1: Pathway Detail | H1: Baseline Abatement Cost 2050 ($/ton CO2) | I1: WACC / Discount Rate | J1: Electricity Price Range (EUR/MWh) | K1: Electricty Price Source | L1: Battery Storage | M1: H2/H2O Source | N1: co-SOEC route? | O1: Electrolyser Cost Range (EUR/kW) | P1: H2 Price (EUR/kg) | Q1: H2 Price Source | R1: H2 Storage | S1: CO2 Price Range 2050 ($/tCO2) | T1: CO2 Price Source | U1: Learning rate | V1: CO2 Price 2020 | W1: Installed DAC capcaity 2020 | X1: Installed DAC capcaity 2050 | Y1: b
A2: Brazzola et al. | B2: Yes | C2: Yes | D2: 2024 | F2: e-Fuels | G2: Fischer Tropsch | H2: 304 | I2: 0.07 | J2: 20 | O2: 758-920 | S2: =V2*(X2/W2)^Y2 -> 199.6882 | U2: 0.12 | V2: 870 | W2: 10000 | X2: =1*10^9 -> 1000000000 | Y2: =LN(1-0.12) -> -0.12783337
A3: Gray et al. | B3: Yes | C3: Yes | D3: 2024 | E3: https://doi.org/10.1016/j.rser.2024.114552 | F3: e-Fuels | G3: Fischer Tropsch | H3: 1053 | I3: 0.06 | J3: 40 | O3: 800 | S3: 160
A4: Marchese et.al | B4: Yes | C4: Yes | D4: 2021 | E4: https://doi.org/10.1016/j.jcou.2021.101487 | F4: e-Fuels | G4: Fischer Tropsch | H4: 354-1100 | I4: 0.075 | J4: 41-210 | K4: Several sources | O4: 360-1050 | S4: Ground Up DAC modelling | T4: Fasihi et. al. (2019) (https://www.sciencedirect.com/science/article/pii/S0959652619307772?via%3Dihub)
A5: Martin et. al. | B5: Yes | C5: Yes | D5: 2023 | E5: https://www.sciencedirect.com/science/article/pii/S136403212300494X#sec4 | F5: e-Fuels | G5: Fischer Tropsch | H5: 205.5 | I5: 0.08 | J5: 30-48 | O5: 140-490 | S5: 90 | T5: Multiple sources
A6: Moretti et al. | B6: Yes | C6: Yes | D6: 2023 | E6: https://doi.org/10.1016/j.scitotenv.2023.166005 | F6: Solar Fuels | G6: Fischer Tropsch | H6: 483-575 | I6: 0.052 | J6: 50 | O6: Not Applicable, Thermochemical splitting | S6: 237
A7: Peacock et. al. | B7: Yes | C7: Yes | D7: 2024 | E7: https://doi.org/10.1016/j.ijhydene.2023.09.094 | F7: e-Fuels | G7: Fischer Tropsch | H7: 827-1120 | I7: 0.08 | J7: 38-118 | O7: 400 | S7: 200 (Ground Up modelling)
A8: Schmidt et. al. | B8: Yes | C8: Yes | D8: 2024 | E8: https://www.concawe.eu/wp-content/uploads/Rpt_24-4-1.pdf | F8: e-Fuels | G8: Fischer Tropsch | H8: 832-987 | I8: 0.08 | J8: 52 | O8: 600 | S8: 151 (Ground Up modelling)
A9: Seymour et al. | B9: Yes | C9: Yes | D9: 2024 | E9: https://doi.org/10.1039/D3SE00978E | F9: e-Fuels | G9: Fischer Tropsch | H9: 432 | I9: 0.05 | J9: 30 | O9: 358 | S9: 199
A10: Sherwin | B10: Yes | C10: Yes | D10: 2021 | E10: https://doi.org/10.1021/acs.est.0c07955 | F10: e-Fuels | G10: Fischer Tropsch | H10: 50 | I10: 0.05 | J10: 19 | O10: 485 | S10: 100

Sheet Standardization Results
A1: Reference | B1: Year of Assumptions in Study | C1: DOI | D1: Pathway | E1: Pathway Detail | F1: Year of Cost | G1: Study Scenario | H1: Baseline | I1: LCOE Harmonized | J1: CO2 Cost Harmonized | K1: Fully Harmonized | L1: Residual Emissions (gCO2eq/L fuel) | M1: Electricity | N1: CO2 | O1: CAPEX | P1: Other OPEX | Q1: Study Type | R1: Plant Location | S1: Production
A2: Albrecht et. al. | B2: 2016 | C2: https://doi.org/10.1016/j.energy.2019.116511 | D2: e-Fuels | E2: Fischer Tropsch | F2: 2024 | G2: Reference | H2: =([1]Outputs!$C$10) * ((1+Inputs!$C$5) ^ (F2-B2)) -> 642.2967 | I2: =([1]Outputs!$D$10) * ((1+Inputs!$C$5) ^ (F2-B2)) -> 768.83261 | J2: =([1]Outputs!$E$10) * ((1+Inputs!$C$5) ^ (F2-B2)) -> 2386.5585 | K2: =([1]Outputs!$F$10) * ((1+Inputs!$C$5) ^ (F2-B2)) -> 2466.5878 | Q2: Industrial | R2: Europe | S2: 1.4477822e+08 | T2: This study has a detailed breakdown but considers a scenario where electricity is an output, leading to lower overall costs.
A3: Bachorz et. al | B3: 2024 | C3: https://www.researchsquare.com/article/rs-4241841/v1 | D3: e-Fuels | E3: Methanol | F3: 2024 | G3: Reference | H3: =[2]Outputs!$C$10 -> 2404.7475 | I3: =[2]Outputs!$D$10 -> 2435.2346 | J3: =[2]Outputs!$E$10 -> 1644.4988 | K3: =[2]Outputs!$F$10 -> 1623.8464 | M3: ='[2]Cost Breakdown'!$B$9 -> 0.091683397 | N3: ='[2]Cost Breakdown'!$B$8 -> 0.37268475 | O3: ='[2]Cost Breakdown'!$B$10 -> 0.51503063 | P3: ='[2]Cost Breakdown'!$B$11 -> 0.020601225 | Q3: Academic | R3: Europe | S3: - | T3: Due to a high WACC assumption (~11%, final wacc correction leads to lower cost)
A4: Brazzola et al. | B4: 2024 | D4: e-Fuels | E4: Fischer Tropsch | F4: 2024 | G4: Reference | H4: ='[19]Received Data Brazzola'!$D$6 -> 432.43604 | I4: ='[19]LCOE Corrected'!$C$6 -> 859.50423 | J4: ='[19]CO2 Cost Corrected'!$C$6 -> 434.6918 | K4: =[19]Outputs!$B$2 -> 434.6918 | L4: 0 | Q4: Academic | R4: Worldwide | S4: -
A5: Brazzola et al. | B5: 2024 | D5: e-Fuels | E5: Fischer Tropsch | F5: 2050 | G5: Reference | H5: ='[19]Received Data Brazzola'!$D$32 -> 226.43484 | I5: ='[19]LCOE Corrected'!$C$32 -> 507.54963 | J5: ='[19]CO2 Cost Corrected'!$C$32 -> 256.69177 | K5: =[19]Outputs!$B$3 -> 256.69177 | L5: 0 | Q5: Academic | R5: Worldwide | S5: -
A6: Dietrich et. al. | B6: 2018 | C6: https://doi.org/10.1016/j.biombioe.2017.07.006 | D6: e-Fuels | E6: Fischer Tropsch | F6: 2024 | G6: Reference | H6: =[3]Outputs!$C$10 -> 1144.7871 | I6: =[3]Outputs!$D$10 -> 706.66811 | J6: =[3]Outputs!$E$10 -> 2210.7958 | K6: =[3]Outputs!$F$10 -> 2210.7958 | M6: ='[3]Received Data'!$N$9 -> 0.11002479 | N6: ='[3]Received Data'!$N$8 -> 0.32309926 | O6: ='[3]Received Data'!$N$10 -> 0.51966602 | P6: ='[3]Received Data'!$N$11 -> 0.04720993 | Q6: Academic | R6: Europe
A7: Falter et. al. | B7: 2020 | C7: https://doi.org/10.1039/d0se00179a | D7: Solar Fuels | E7: Fischer Tropsch | F7: 2024 | G7: Reference | H7: =[4]Outputs!$C$10 * (1+Inputs!C5) ^ ('Standardization Results'!F40-'Standardization Results'!B40) -> 2029.869 | I7: =[4]Outputs!$D$10 * (1+Inputs!C5) ^ ('Standardization Results'!F40-'Standardization Results'!B40) -> 2086.9789 | J7: =[4]Outputs!$E$10 * (1+Inputs!C5) ^ ('Standardization Results'!F40-'Standardization Results'!B40) -> 8021.9643 | K7: =[4]Outputs!$F$10 * (1+Inputs!C5) ^ ('Standardization Results'!F40-'Standardization Results'!B40) -> 7995.8085 | Q7: Academic | R7: MENA | S7: 45872966 | T7: Most assumptions based on previous study
A8: Falter et. al. | B8: 2015 | C8: https://doi.org/10.1021/acs.est.5b03515 | D8: Solar Fuels | E8: Fischer Tropsch | F8: 2024 | G8: Reference | H8: =[5]Outputs!$J$10* (1+Inputs!C5) ^ ('Standardization Results'!F41-'Standardization Results'!B41) -> 471.65912 | I8: =[5]Outputs!$K$10* (1+Inputs!C5) ^ ('Standardization Results'!F41-'Standardization Results'!B41) -> 496.13588 | J8: =[5]Outputs!$L$10* (1+Inputs!C5) ^ ('Standardization Results'!F41-'Standardization Results'!B41) -> 4670.6876 | K8: =[5]Outputs!$M$10* (1+Inputs!C5) ^ ('Standardization Results'!F41-'Standardization Results'!B41) -> 5006.9118 | Q8: Academic | R8: MENA | S8: 58035000
A9: Falter et. al. | B9: 2015 | C9: https://doi.org/10.1021/acs.est.5b03515 | D9: Solar Fuels | E9: Fischer Tropsch | F9: 2024 | G9: Reference | H9: =[5]Outputs!$C$10* (1+Inputs!C5) ^ ('Standardization Results'!F42-'Standardization Results'!B42) -> 667.86758 | I9: =[5]Outputs!$D$10* (1+Inputs!C5) ^ ('Standardization Results'!F42-'Standardization Results'!B42) -> 692.34434 | J9: =[5]Outputs!$E$10* (1+Inputs!C5) ^ ('Standardization Results'!F42-'Standardization Results'!B42) -> 4866.896 | K9: =[5]Outputs!$F$10* (1+Inputs!C5) ^ ('Standardization Results'!F42-'Standardization Results'!B42) -> 5216.4445 | M9: ='[5]Cost Breakdowns'!$B$10 -> 0.058359447 | N9: ='[5]Cost Breakdowns'!$B$9 -> 0.66723593 | O9: ='[5]Cost Breakdowns'!$B$11 -> 0.10459443 | P9: ='[5]Cost Breakdowns'!$B$12 -> 0.1698102 | Q9: Academic | R9: MENA | S9: 58035000 | T9: Initial assumptions are very optimistic (by author's admission), Production is high. Overall process efficiency is 5% according to the author
A10: Gray et al. | B10: 2024 | C10: https://doi.org/10.1016/j.rser.2024.114552 | D10: e-Fuels | E10: Fischer Tropsch | F10: 2024 | G10: Reference DAC Deployment | H10: =[6]Outputs!$J$10 -> 2727.5773 | I10: =[6]Outputs!$K$10 -> 2805.9552 | J10: =[6]Outputs!$L$10 -> 1478.0572 | K10: =[6]Outputs!$M$10 -> 1555.9594 | L10: =[6]Outputs!$C$14 -> 276.92708 | M10: ='[6]LCOF WACC Corrected'!$J$9 -> 0.36289802 | N10: ='[6]LCOF WACC Corrected'!$J$8 -> 0.35987238 | O10: ='[6]LCOF WACC Corrected'!$J$10 -> 0.18908765 | P10: ='[6]LCOF WACC Corrected'!$J$11 -> 0.088141946 | Q10: Academic | R10: Europe | S10: 39140034
A11: Gray et al. | B11: 2024 | C11: https://doi.org/10.1016/j.rser.2024.114552 | D11: e-Fuels | E11: Fischer Tropsch | F11: 2050 | G11: High DAC Deployment | H11: =[6]Outputs!$C$10 -> 1053.0157 | I11: =[6]Outputs!$D$10 -> 1131.3935 | J11: =[6]Outputs!$E$10 -> 1207.0426 | K11: =[6]Outputs!$F$10 -> 1284.9449 | L11: =[6]Outputs!$C$14 -> 276.92708 | M11: ='[6]LCOF WACC Corrected'!$M$9 -> 0.43600143 | N11: ='[6]LCOF WACC Corrected'!$M$8 -> 0.23092291 | O11: ='[6]LCOF WACC Corrected'!$M$10 -> 0.22717811 | P11: ='[6]LCOF WACC Corrected'!$M$11 -> 0.10589756 | Q11: Academic | R11: Europe | S11: 39140034 | T11: This scenario assumes a decline in CO2 cost but not CAPEX
A12: Marchese et.al. | B12: 2021 | C12: https://doi.org/10.1016/j.jcou.2021.101487 | D12: e-Fuels | E12: Fischer Tropsch | F12: 2024 | G12: C.4 | H12: =[7]Outputs!$X$10* (1+Inputs!$C$5) ^ (F12-B12) -> 1458.3489 | I12: =[7]Outputs!$Y$10* (1+Inputs!$C$5) ^ (F12-B12) -> 751.42719 | J12: =[7]Outputs!$Z$10* (1+Inputs!$C$5)^ (F12-B12) -> 898.0069 | K12: =[7]Outputs!$AA$10* (1+Inputs!$C$5) ^ (F12-B12) -> 883.12721 | L12: 0 | Q12: Academic | R12: Europe | S12: 69000000
A13: Marchese et.al. | B13: 2021 | C13: https://doi.org/10.1016/j.jcou.2021.101487 | D13: e-Fuels | E13: Fischer Tropsch | F13: 2024 | G13: C.1 | H13: =[7]Outputs!$C$10 * (1+Inputs!$C$5) ^ (F13-B13) -> 1892.3064 | I13: =[7]Outputs!$D$10* (1+Inputs!$C$5) ^ (F13-B13) -> 1097.7096 | J13: =[7]Outputs!$E$10* (1+Inputs!$C$5) ^ (F13-B13) -> 1157.1299 | K13: =[7]Outputs!$F$10* (1+Inputs!$C$5) ^ (F13-B13) -> 1141.2526 | L13: 0 | M13: ='[7]Cost Breakdown'!$B$10 -> 0.27085063 | N13: ='[7]Cost Breakdown'!$B$9 -> 0.1799626 | O13: ='[7]Cost Breakdown'!$B$11 -> 0.30397259 | P13: ='[7]Cost Breakdown'!$B$12 -> 0.24521419 | Q13: Academic | R13: Europe | S13: 87000000
A14: Marchese et.al. | B14: 2021 | C14: https://doi.org/10.1016/j.jcou.2021.101487 | D14: e-Fuels | E14: Fischer Tropsch | F14: 2024 | G14: C.5 | H14: =[7]Outputs!$AE$10* (1+Inputs!$C$5) ^ (F14-B14) -> 1730.5108 | I14: =[7]Outputs!$AF$10* (1+Inputs!$C$5) ^ (F14-B14) -> 823.96436 | J14: =[7]Outputs!$AG$10* (1+Inputs!$C$5) ^ (F14-B14) -> 997.36187 | K14: =[7]Outputs!$AH$10* (1+Inputs!$C$5) ^ (F14-B14) -> 980.42742 | L14: 0 | Q14: Academic | R14: Europe | S14: 68000000
A15: Marchese et.al. | B15: 2021 | C15: https://doi.org/10.1016/j.jcou.2021.101487 | D15: e-Fuels | E15: Fischer Tropsch | F15: 2024 | G15: C.3 | H15: =[7]Outputs!$Q$10* (1+Inputs!$C$5) ^ (F15-B15) -> 2708.6121 | I15: =[7]Outputs!$R$10* (1+Inputs!$C$5) ^(F15-B15) -> 1804.7169 | J15: =[7]Outputs!$S$10* (1+Inputs!$C$5) ^ (F15-B15) -> 1941.7692 | K15: =[7]Outputs!$T$10* (1+Inputs!$C$5) ^ (F15-B15) -> 1919.3136 | L15: 0 | Q15: Academic | R15: Europe | S15: 48000000
A16: Marchese et.al. | B16: 2021 | C16: https://doi.org/10.1016/j.jcou.2021.101487 | D16: e-Fuels | E16: Fischer Tropsch | F16: 2024 | G16: C.2 | H16: =[7]Outputs!$J$10* 1.02 ^ (F16-B16) -> 2761.7003 | I16: =[7]Outputs!$K$10* 1.02 ^ (F16-B16) -> 1368.7085 | J16: =[7]Outputs!$L$10* 1.02 ^ (F16-B16) -> 1562.0729 | K16: =[7]Outputs!$M$10* 1.02 ^ (F16-B16) -> 1533.3503 | L16: 0 | Q16: Academic | R16: Europe | S16: 35000000
A17: Marchese et.al. | B17: 2021 | C17: https://doi.org/10.1016/j.jcou.2021.101487 | D17: e-Fuels | E17: Fischer Tropsch | F17: 2050 | G17: C.1 | H17: =[7]Outputs!$C$21* (1+Inputs!$C$5) ^ (F17-B17) -> 597.79762 | I17: =[7]Outputs!$D$21* (1+Inputs!$C$5) ^ (F17-B17) -> 297.6618 | J17: =[7]Outputs!$E$21* (1+Inputs!$C$5) ^ (F17-B17) -> 507.83267 | K17: =[7]Outputs!$F$21* (1+Inputs!$C$5) ^ (F17-B17) -> 497.82439 | L17: 0 | M17: ='[7]Cost Breakdown'!$B$22 -> 0.28830506 | N17: ='[7]Cost Breakdown'!$B$21 -> 0.1573409 | O17: ='[7]Cost Breakdown'!$B$23 -> 0.15294257 | P17: ='[7]Cost Breakdown'!$B$24 -> 0.40141147 | Q17: Academic | R17: Europe | S17: 87000000
A18: Marchese et.al. | B18: 2021 | C18: https://doi.org/10.1016/j.jcou.2021.101487 | D18: e-Fuels | E18: Fischer Tropsch | F18: 2050 | G18: C.2 | H18: =[7]Outputs!$J$21* (1+Inputs!$C$5) ^ (F18-B18) -> 1954.9193 | I18: =[7]Outputs!$K$21* (1+Inputs!$C$5) ^ (F18-B18) -> 1438.7117 | J18: =[7]Outputs!$L$21* (1+Inputs!$C$5) ^ (F18-B18) -> 1976.4189 | K18: =[7]Outputs!$M$21* (1+Inputs!$C$5) ^ (F18-B18) -> 1958.4433 | L18: 0 | Q18: Academic | R18: Europe | S18: 35000000
A19: Marchese et.al. | B19: 2021 | C19: https://doi.org/10.1016/j.jcou.2021.101487 | D19: e-Fuels | E19: Fischer Tropsch | F19: 2050 | G19: C.3 | H19: =[7]Outputs!$Q$21* (1+Inputs!$C$5) ^ (F19-B19) -> 1692.7913 | I19: =[7]Outputs!$R$21 * (1+Inputs!$C$5) ^ (F17-B17) -> 1109.928 | J19: =[7]Outputs!$S$21* (1+Inputs!$C$5) ^ (F17-B17) -> 1500.6866 | K19: =[7]Outputs!$T$21* (1+Inputs!$C$5) ^ (F17-B17) -> 1487.0626 | L19: 0 | Q19: Academic | R19: Europe | S19: 48000000
A20: Marchese et.al. | B20: 2021 | C20: https://doi.org/10.1016/j.jcou.2021.101487 | D20: e-Fuels | E20: Fischer Tropsch | F20: 2050 | G20: C.4 | H20: =[7]Outputs!$X$21* (1+Inputs!$C$5) ^ (F20-B20) -> 310.7968 | I20: =[7]Outputs!$Y$21* (1+Inputs!$C$5) ^ (F20-B20) -> 31.763718 | J20: =[7]Outputs!$Z$21* (1+Inputs!$C$5) ^(F20-B20) -> 320.74468 | K20: =[7]Outputs!$AA$21* (1+Inputs!$C$5) ^ (F20-B20) -> 310.75429 | L20: 0 | Q20: Academic | R20: Europe | S20: 69000000
A21: Marchese et.al. | B21: 2021 | C21: https://doi.org/10.1016/j.jcou.2021.101487 | D21: e-Fuels | E21: Fischer Tropsch | F21: 2050 | G21: C.5 | H21: =[7]Outputs!$AE$21* (1+Inputs!$C$5) ^ (F21-B21) -> 628.73238 | I21: =[7]Outputs!$AF$21* (1+Inputs!$C$5) ^ (F21-B21) -> 270.87595 | J21: =[7]Outputs!$AG$21* (1+Inputs!$C$5) ^ (F21-B21) -> 572.36067 | K21: =[7]Outputs!$AH$21* (1+Inputs!$C$5) ^ (F21-B21) -> 561.98413 | L21: 0 | Q21: Academic | R21: Europe | S21: 68000000
A22: Martin et. al. | B22: 2023 | C22: https://www.sciencedirect.com/science/article/pii/S136403212300494X?via%3Dihub | D22: e-Fuels | E22: Fischer Tropsch | F22: 2024 | G22: Reference | H22: =[8]Outputs!$C$10 * (1+Inputs!C5) ^ ('Standardization Results'!F19-'Standardization Results'!B19) -> 1999.3691 | I22: =[8]Outputs!$D$10* (1+Inputs!C5) ^ ('Standardization Results'!F19-'Standardization Results'!B19) -> 1980.3771 | J22: =[8]Outputs!$E$10* (1+Inputs!C5) ^ ('Standardization Results'!F19-'Standardization Results'!B19) -> 1827.4016 | K22: =[8]Outputs!$F$10* (1+Inputs!C5) ^ ('Standardization Results'!F19-'Standardization Results'!B19) -> 1832.9217 | L22: =[8]Outputs!$C$14 -> 464.84064 | Q22: Academic | R22: Europe | S22: -
A23: Martin et. al. | B23: 2023 | C23: https://www.sciencedirect.com/science/article/pii/S136403212300494X?via%3Dihub | D23: e-Fuels | E23: Fischer Tropsch | F23: 2050 | G23: Reference | H23: =[8]Outputs!$J$10 * (1+Inputs!C5) ^ ('Standardization Results'!F22-'Standardization Results'!B22) -> 209.51492 | I23: =[8]Outputs!$K$10* (1+Inputs!C5) ^ ('Standardization Results'!F22-'Standardization Results'!B22) -> 196.72581 | J23: =[8]Outputs!$L$10* (1+Inputs!C5) ^ ('Standardization Results'!F22-'Standardization Results'!B22) -> 384.1995 | K23: =[8]Outputs!$M$10* (1+Inputs!C5) ^ ('Standardization Results'!F22-'Standardization Results'!B22) -> 385.78482 | L23: =[8]Outputs!$C$14 -> 464.84064 | Q23: Academic | R23: Europe | S23: -
A24: Meurer et al. | B24: 2024 | C24: https://doi.org/10.1039/D3SE01156A | D24: e-Fuels | E24: Fischer Tropsch | F24: 2024 | G24: Reference | H24: =[9]Outputs!$C$10 -> 1678.5512 | I24: =[9]Outputs!$D$10 -> 1330.6142 | J24: =[9]Outputs!$E$10 -> 2039.9518 | K24: =[9]Outputs!$F$10 -> 2004.6361 | Q24: Academic | R24: Europe | S24: 3650000
A25: Moretti et al. | B25: 2023 | C25: https://doi.org/10.1016/j.scitotenv.2023.166005 | D25: Solar Fuels | E25: Fischer Tropsch | F25: 2024 | G25: Reference | H25: =[10]Outputs!$C$10 -> 838.68815 | I25: =[10]Outputs!$D$10 -> 793.08716 | J25: =[10]Outputs!$E$10 -> 549.23622 | K25: =[10]Outputs!$F$10 -> 614.21669 | L25: =[10]Outputs!$C$14 -> 468.3096 | M25: ='[10]MFSP WACC Corrected'!$B$39 -> -0.11475881 | N25: ='[10]MFSP WACC Corrected'!$B$40 -> 0.39312614 | O25: ='[10]MFSP WACC Corrected'!$B$38 -> 0.44920104 | P25: ='[10]MFSP WACC Corrected'!$B$41 -> 0.27243164 | Q25: Industrial | R25: MENA | S25: 31354838 | T25: High CO2 cost assumed, hence there is less effect, High Production levels lead to lower costs due to scale and cheaper labour in MENA
A26: Moretti et al. | B26: 2023 | C26: https://doi.org/10.1016/j.scitotenv.2023.166005 | D26: Solar Fuels | E26: Fischer Tropsch | F26: 2050 | G26: Reference | H26: =[10]Outputs!$J$10 * (1+Inputs!$C$5) ^ (F26-B26) -> 982.3514 | I26: =[10]Outputs!$K$10 * (1+Inputs!$C$5) ^ (F26-B26) -> 982.36403 | J26: =[10]Outputs!$L$10 * (1+Inputs!$C$5) ^ (F26-B26) -> 976.94296 | K26: =[10]Outputs!$M$10 * (1+Inputs!$C$5) ^ (F26-B26) -> 1076.4346 | L26: =[10]Outputs!$C$14 -> 468.3096 | M26: ='[10]MFSP WACC Corrected'!$B$53 -> -3.6841458e-05 | N26: ='[10]MFSP WACC Corrected'!$B$54 -> 0.4089253 | O26: ='[10]MFSP WACC Corrected'!$B$52 -> 0.41554006 | P26: ='[10]MFSP WACC Corrected'!$B$55 -> 0.17557148 | Q26: Industrial | R26: MENA | S26: 31354838
A27: Moretti et al. | B27: 2023 | C27: https://doi.org/10.1016/j.scitotenv.2023.166005 | D27: Solar Fuels | E27: Fischer Tropsch | F27: 2050 | G27: Optimistic | H27: =[10]Outputs!$Q$10 * (1+Inputs!$C$5) ^ ('Standardization Results'!F18-'Standardization Results'!B18) -> 858.71366 | I27: =[10]Outputs!$R$10* (1+Inputs!$C$5) ^ ('Standardization Results'!F18-'Standardization Results'!B18) -> 858.72679 | J27: =[10]Outputs!$S$10* (1+Inputs!$C$5) ^ ('Standardization Results'!F18-'Standardization Results'!B18) -> 853.08671 | K27: =[10]Outputs!$T$10* (1+Inputs!$C$5) ^ ('Standardization Results'!F18-'Standardization Results'!B18) -> 929.58904 | L27: =[10]Outputs!$C$14 -> 468.3096 | Q27: Industrial | R27: MENA | S27: 31354838
A28: Peacock et. al. | B28: 2024 | D28: e-Fuels | E28: Fischer Tropsch | F28: 2024 | G28: SOEC, Nuclear + Renewables | H28: =[11]Outputs!$Q$10 -> 2681.2488 | I28: =[11]Outputs!$R$10 -> 2495.6577 | J28: =[11]Outputs!$S$10 -> 2013.7955 | K28: =[11]Outputs!$T$10 -> 1988.4544 | L28: =[11]Outputs!$C$26 -> 215.38773 | Q28: Academic | R28: United Kingdom | S28: 157410000
A29: Peacock et. al. | B29: 2024 | D29: e-Fuels | E29: Fischer Tropsch | F29: 2024 | G29: PEM, Nuclear | H29: =[11]Outputs!$C$10 -> 3266.1214 | I29: =[11]Outputs!$D$10 -> 2576.9841 | J29: =[11]Outputs!$E$10 -> 1969.1598 | K29: =[11]Outputs!$F$10 -> 1947.4925 | L29: =[11]Outputs!$C$26 -> 215.38773 | Q29: Academic | R29: United Kingdom | S29: 157410000 | T29: Large scale production but high electrolyser costs and multiple replacements considered (missing from most other studies)
A30: Peacock et. al. | B30: 2024 | D30: e-Fuels | E30: Fischer Tropsch | F30: 2050 | G30: PEM, Nuclear | H30: =[11]Outputs!$C$22 * (1+Inputs!$C$5) ^ ('Standardization Results'!F36-'Standardization Results'!B36) -> 1120.7136 | I30: =[11]Outputs!$D$22* (1+Inputs!$C$5) ^ ('Standardization Results'!F36-'Standardization Results'!B36) -> 983.41616 | J30: =[11]Outputs!$E$22* (1+Inputs!$C$5) ^ ('Standardization Results'!F36-'Standardization Results'!B36) -> 1214.6327 | K30: =[11]Outputs!$F$22* (1+Inputs!$C$5) ^ ('Standardization Results'!F36-'Standardization Results'!B36) -> 1197.7597 | L30: =[11]Outputs!$C$26 -> 215.38773 | Q30: Academic | R30: United Kingdom | S30: 157410000
A31: Peacock et. al. | B31: 2024 | D31: e-Fuels | E31: Fischer Tropsch | F31: 2050 | G31: PEM, Nuclear + Renewables | H31: =[11]Outputs!$J$22* (1+Inputs!$C$5) ^ ('Standardization Results'!F37-'Standardization Results'!B37) -> 952.97687 | I31: =[11]Outputs!$K$22* (1+Inputs!$C$5) ^ ('Standardization Results'!F37-'Standardization Results'!B37) -> 964.92098 | J31: =[11]Outputs!$L$22* (1+Inputs!$C$5) ^ ('Standardization Results'!F37-'Standardization Results'!B37) -> 1151.5013 | K31: =[11]Outputs!$M$22* (1+Inputs!$C$5) ^ ('Standardization Results'!F37-'Standardization Results'!B37) -> 1134.6284 | L31: =[11]Outputs!$C$26 -> 215.38773 | M31: ='[11]Cost Breakdowns'!$B$22 -> 0.40154651 | N31: ='[11]Cost Breakdowns'!$B$21 -> 0.31639384 | O31: ='[11]Cost Breakdowns'!$B$23 -> 0.092223342 | P31: ='[11]Cost Breakdowns'!$B$24 -> 0.1898363 | Q31: Academic | R31: United Kingdom | S31: 157410000
A32: Peacock et. al. | B32: 2024 | D32: e-Fuels | E32: Fischer Tropsch | F32: 2050 | G32: SOEC, Nuclear + Renewables | H32: =[11]Outputs!$Q$22 * (1+Inputs!$C$5) ^ ('Standardization Results'!F38-'Standardization Results'!B38) -> 1383.9118 | I32: =[11]Outputs!$R$22* (1+Inputs!$C$5) ^ ('Standardization Results'!F38-'Standardization Results'!B38) -> 1400.7491 | J32: =[11]Outputs!$S$22* (1+Inputs!$C$5) ^ ('Standardization Results'!F38-'Standardization Results'!B38) -> 1708.5223 | K32: =[11]Outputs!$T$22* (1+Inputs!$C$5) ^ ('Standardization Results'!F38-'Standardization Results'!B38) -> 1681.9374 | L32: =[11]Outputs!$C$26 -> 215.38773 | Q32: Academic | R32: United Kingdom | S32: 157410000
A33: Peacock et. al. | B33: 2024 | D33: e-Fuels | E33: Fischer Tropsch | F33: 2024 | G33: PEM, Nuclear + Renewables | H33: =[11]Outputs!$J$10 -> 2797.4452 | I33: =[11]Outputs!$K$10 -> 2548.3625 | J33: =[11]Outputs!$L$10 -> 2081.0539 | K33: =[11]Outputs!$M$10 -> 2059.3865 | L33: =[11]Outputs!$C$26 -> 215.38773 | M33: ='[11]Cost Breakdowns'!$B$10 -> 0.36579718 | N33: ='[11]Cost Breakdowns'!$B$9 -> 0.39350094 | O33: ='[11]Cost Breakdowns'!$B$11 -> 0.079277064 | P33: ='[11]Cost Breakdowns'!$B$12 -> 0.16142482 | Q33: Academic | R33: United Kingdom | S33: 157410000
A34: Peters et. al. | B34: 2022 | C34: https://doi.org/10.3390/pr10040699 | D34: e-Fuels | E34: Fischer Tropsch | F34: 2024 | G34: Baseline | H34: =[12]Outputs!$C$10 * (1+Inputs!C5) ^ ('Standardization Results'!F33-'Standardization Results'!B33) -> 642.42374 | I34: =[12]Outputs!$D$10* (1+Inputs!C5) ^ ('Standardization Results'!F33-'Standardization Results'!B33) -> 1011.8769 | J34: =[12]Outputs!$E$10 * (1+Inputs!C5) ^ ('Standardization Results'!F33-'Standardization Results'!B33) -> 3588.7386 | K34: =[12]Outputs!$F$10* (1+Inputs!C5) ^ ('Standardization Results'!F33-'Standardization Results'!B33) -> 3626.2481 | M34: ='[12]Cost of Manufacturing Models'!$F$10 -> 0.066800203 | N34: ='[12]Cost of Manufacturing Models'!$F$9 -> 0.46591807 | O34: ='[12]Cost of Manufacturing Models'!$F$11 -> 0.43493529 | P34: ='[12]Cost of Manufacturing Models'!$F$12 -> 0.032346433 | Q34: Academic | R34: Europe | S34: 208032000 | T34: Low intial electricity and CO2 price assumption lead to lower costs
A35: Rojas-Michaga et. al. | B35: 2023 | C35: https://www.sciencedirect.com/science/article/pii/S0196890423007732?via%3Dihub#s0005 | D35: e-Fuels | E35: Fischer Tropsch | F35: 2024 | G35: Reference | H35: =[13]Outputs!$C$10 * (1+Inputs!C5) ^ ('Standardization Results'!F30-'Standardization Results'!B30) -> 2879.4702 | I35: =[13]Outputs!$D$10 * (1+Inputs!C5) ^ ('Standardization Results'!F30-'Standardization Results'!B30) -> 2389.2886 | J35: =[13]Outputs!$E$10 * (1+Inputs!C5) ^ ('Standardization Results'!F20-'Standardization Results'!B20) -> 5490.9741 | K35: =[13]Outputs!$F$10 * (1+Inputs!C5) ^ ('Standardization Results'!F30-'Standardization Results'!B30) -> 5101.9877 | M35: ='[13]MJSP WACC Corrected'!$B$20 -> 0.28620653 | N35: ='[13]MJSP WACC Corrected'!$B$19 -> 0.47089021 | O35: ='[13]MJSP WACC Corrected'!$B$21 -> 0.025500914 | P35: ='[13]MJSP WACC Corrected'!$B$22 -> 0.21740235 | Q35: Academic | R35: United Kingdom | S35: 25105853 | T35: Very detailed study, we should note that this study considers a wide variety of costs that will be practically applicable (e.g. labour, overhead, catalyst, by-product sales etc.)
A36: Saad et al. | B36: 2024 | C36: https://doi.org/10.1021/acs.est.4c01578 | D36: e-Fuels | E36: Methanol | F36: 2024 | G36: CO2ER | H36: =[14]Outputs!$C$10 -> 6201.6747 | I36: =[14]Outputs!$D$10 -> 3818.5621 | J36: =[14]Outputs!$E$10 -> 3865.4181 | K36: =[14]Outputs!$F$10 -> 3949.4052 | M36: ='[14]Cost Breakdown'!$B$10 -> 0.18840662 | N36: ='[14]Cost Breakdown'!$B$9 -> 0.68456138 | O36: ='[14]Cost Breakdown'!$B$11 -> 0.11897367 | P36: ='[14]Cost Breakdown'!$B$12 -> 0.008058336 | Q36: Academic | R36: Europe | S36: 1250000000 | T36: LCA accounting methodology means that the emissions abated are low, therefore cost is high
A37: Saad et al. | B37: 2024 | C37: https://doi.org/10.1021/acs.est.4c01578 | D37: e-Fuels | E37: Methanol | F37: 2024 | G37: CO2HY | H37: =[14]Outputs!$J$10 -> 5186.3474 | I37: =[14]Outputs!$K$10 -> 3438.5193 | J37: =[14]Outputs!$L$10 -> 5951.2257 | K37: =[14]Outputs!$M$10 -> 6013.8338 | M37: ='[14]Cost Breakdown'!$B$22 -> 0.1011943 | N37: ='[14]Cost Breakdown'!$B$21 -> 0.61193523 | O37: ='[14]Cost Breakdown'!$B$23 -> 0.2723405 | P37: ='[14]Cost Breakdown'!$B$24 -> 0.014529965 | Q37: Academic | R37: Europe | S37: 1250000000
A38: Schmidt et. al. | B38: 2024 | C38: https://onlinelibrary.wiley.com/doi/full/10.1002/cite.201700129?saml_referrer https://www.concawe.eu/wp-content/uploads/Rpt_24-4-1.pdf | D38: e-Fuels | E38: Fischer Tropsch | F38: 2050 | G38: EU-North | H38: =[15]Outputs!$C$21*((1+Inputs!$C$5)^($F$10-Inputs!$C$4)) -> 832.71053 | I38: =[15]Outputs!$D$21*((1+Inputs!$C$5)^($F$10-Inputs!$C$4)) -> 712.36778 | J38: =[15]Outputs!$E$21*((1+Inputs!$C$5)^($F$10-Inputs!$C$4)) -> 795.36025 | K38: =[15]Outputs!$F$21*((1+Inputs!$C$5)^($F$10-Inputs!$C$4)) -> 719.69502 | L38: =[15]Outputs!$C$32 -> 110.72204 | M38: ='[15]Cost Breakdown'!$B$22 -> 0.45315744 | N38: ='[15]Cost Breakdown'!$B$21 -> 0.31792431 | O38: ='[15]Cost Breakdown'!$B$23 -> 0.188823 | P38: ='[15]Cost Breakdown'!$B$24 -> 0.04009525 | Q38: Industrial | R38: Europe | S38: 1000000
A39: Schmidt et. al. | B39: 2024 | C39: https://onlinelibrary.wiley.com/doi/full/10.1002/cite.201700129?saml_referrer https://www.concawe.eu/wp-content/uploads/Rpt_24-4-1.pdf | D39: e-Fuels | E39: Fischer Tropsch | F39: 2050 | G39: EU-Central | H39: =[15]Outputs!$J$21*((1+Inputs!$C$5)^($F$11-Inputs!$C$4)) -> 1651.2877 | I39: =[15]Outputs!$K$21*((1+Inputs!$C$5)^($F$11-Inputs!$C$4)) -> 1201.2151 | J39: =[15]Outputs!$L$21*((1+Inputs!$C$5)^($F$11-Inputs!$C$4)) -> 1340.0962 | K39: =[15]Outputs!$M$21*((1+Inputs!$C$5)^($F$11-Inputs!$C$4)) -> 1212.3243 | L39: =[15]Outputs!$J$32 -> 126.07289 | Q39: Industrial | R39: Europe | S39: 1000000
A40: Schmidt et. al. | B40: 2024 | C40: https://onlinelibrary.wiley.com/doi/full/10.1002/cite.201700129?saml_referrer https://www.concawe.eu/wp-content/uploads/Rpt_24-4-1.pdf | D40: e-Fuels | E40: Fischer Tropsch | F40: 2050 | G40: EU-South | H40: =[15]Outputs!$Q$21*((1+Inputs!$C$5)^($F$10-Inputs!$C$4)) -> 832.16394 | I40: =[15]Outputs!$R$21*((1+Inputs!$C$5)^($F$10-Inputs!$C$4)) -> 711.82119 | J40: =[15]Outputs!$S$21*((1+Inputs!$C$5)^($F$10-Inputs!$C$4)) -> 794.81366 | K40: =[15]Outputs!$T$21*((1+Inputs!$C$5)^($F$10-Inputs!$C$4)) -> 719.3307 | L40: =[15]Outputs!$Q$32 -> 110.66758 | Q40: Industrial | R40: Europe | S40: 1000000
A41: Schmidt et. al. | B41: 2024 | C41: https://onlinelibrary.wiley.com/doi/full/10.1002/cite.201700129?saml_referrer https://www.concawe.eu/wp-content/uploads/Rpt_24-4-1.pdf | D41: e-Fuels | E41: Fischer Tropsch | F41: 2024 | G41: EU-Central | H41: =[15]Outputs!$J$10*((1+Inputs!$C$5)^(F41-B41)) -> 1309.1064 | I41: =[15]Outputs!$K$10*((1+Inputs!$C$5)^(F41-B41)) -> 1104.4865 | J41: =[15]Outputs!$L$10*((1+Inputs!$C$5)^(F41-B41)) -> 1387.9542 | K41: =[15]Outputs!$M$10*((1+Inputs!$C$5)^(F41-B41)) -> 1287.5803 | L41: =[15]Outputs!$C$25 -> 204.66864 | Q41: Industrial | R41: Europe | S41: 1000000
A42: Schmidt et. al. | B42: 2024 | C42: https://onlinelibrary.wiley.com/doi/full/10.1002/cite.201700129?saml_referrer https://www.concawe.eu/wp-content/uploads/Rpt_24-4-1.pdf | D42: e-Fuels | E42: Fischer Tropsch | F42: 2024 | G42: EU-North | H42: =[15]Outputs!$C$10*((1+Inputs!$C$5)^(F42-'Standardization Results'!B23)) -> 1540.7127 | I42: =[15]Outputs!$D$10*((1+Inputs!$C$5)^(F42-'Standardization Results'!B23)) -> 1280.3735 | J42: =[15]Outputs!$E$10*((1+Inputs!$C$5)^(F42-'Standardization Results'!B23)) -> 1569.5106 | K42: =[15]Outputs!$F$10*((1+Inputs!$C$5)^(F42-'Standardization Results'!B23)) -> 1440.6043 | L42: =[15]Outputs!$C$25 -> 204.66864 | M42: ='[15]Cost Breakdown'!$B$10 -> 0.3247949 | N42: ='[15]Cost Breakdown'!$B$9 -> 0.25998799 | O42: ='[15]Cost Breakdown'!$B$11 -> 0.36706731 | P42: ='[15]Cost Breakdown'!$B$12 -> 0.048149798 | Q42: Industrial | R42: Europe | S42: 1000000 | T42: 1st of a kind industrial plant
A43: Schmidt et. al. | B43: 2024 | C43: https://onlinelibrary.wiley.com/doi/full/10.1002/cite.201700129?saml_referrer https://www.concawe.eu/wp-content/uploads/Rpt_24-4-1.pdf | D43: e-Fuels | E43: Fischer Tropsch | F43: 2024 | G43: EU-South | H43: =[15]Outputs!$Q$10*((1+Inputs!$C$5)^(Inputs!$C$4-'Standardization Results'!B24)) -> 1286.1593 | I43: =[15]Outputs!$R$10*((1+Inputs!$C$5)^(Inputs!$C$4-'Standardization Results'!B24)) -> 1276.9022 | J43: =[15]Outputs!$S$10*((1+Inputs!$C$5)^(Inputs!$C$4-'Standardization Results'!B24)) -> 1560.3699 | K43: =[15]Outputs!$T$10*((1+Inputs!$C$5)^(Inputs!$C$4-'Standardization Results'!B24)) -> 1430.6697 | L43: =[15]Outputs!$C$25 -> 204.66864 | Q43: Industrial | R43: Europe | S43: 1000000
A44: Seymour et al. | B44: 2024 | C44: https://doi.org/10.1039/D3SE00978E | D44: e-Fuels | E44: Fischer Tropsch | F44: 2050 | G44: Reference | H44: =[16]Outputs!$K$10*(1+Inputs!$C$5)^(2050-'Standardization Results'!$B$4) -> 722.87277 | I44: =[16]Outputs!$L$10*(1+Inputs!$C$5)^(2050-'Standardization Results'!$B$4) -> 896.60784 | J44: =[16]Outputs!$M$10*(1+Inputs!$C$5)^(2050-'Standardization Results'!$B$4) -> 962.2823 | K44: =[16]Outputs!$N$10*(1+Inputs!$C$5)^(2050-'Standardization Results'!$B$4) -> 982.24476 | L44: =[16]Outputs!$C$14 -> 305.14 | M44: ='[16]MFSP WACC Corrected'!$B$41 -> 0.50281004 | N44: ='[16]MFSP WACC Corrected'!$B$42 -> 0.2793751 | O44: ='[16]MFSP WACC Corrected'!$B$43 -> 0.14260508 | P44: ='[16]MFSP WACC Corrected'!$B$44 -> 0.075209772 | Q44: Academic | R44: United States of America | S44: 2110761
A45: Seymour et al. | B45: 2024 | C45: https://doi.org/10.1039/D3SE00978E | D45: e-Fuels | E45: Fischer Tropsch | F45: 2024 | G45: Reference | H45: =[16]Outputs!$C$10 -> 1703.2942 | I45: =[16]Outputs!$D$10 -> 1744.0993 | J45: =[16]Outputs!$E$10 -> 1362.544 | K45: =[16]Outputs!$F$10 -> 1404.66 | L45: =[16]Outputs!$C$14 -> 305.14 | M45: ='[16]MFSP WACC Corrected'!$B$28 -> 0.424956 | N45: ='[16]MFSP WACC Corrected'!$B$29 -> 0.26939974 | O45: ='[16]MFSP WACC Corrected'!$B$30 -> 0.20057854 | P45: ='[16]MFSP WACC Corrected'!$B$31 -> 0.10506572 | Q45: Academic | R45: United States of America | S45: 2110761 | T45: High CO2 cost assumed, hence there is less effect
A46: Sherwin | B46: 2021 | C46: https://doi.org/10.1021/acs.est.0c07955 | D46: e-Fuels | E46: Fischer Tropsch | F46: 2024 | G46: Reference | H46: =[17]Outputs!$C$9 * (1+Inputs!$C$5) ^ (F46-B46) -> 1330.2315 | I46: =[17]Outputs!$D$9 * (1+Inputs!$C$5) ^ (F46-B46) -> 1583.3702 | J46: =[17]Outputs!$E$9 * (1+Inputs!$C$5) ^ (F46-B46) -> 1443.5942 | K46: =[17]Outputs!$F$9 * (1+Inputs!$C$5) ^ (F46-B46) -> 1169.7855 | L46: 0 | Q46: Academic | R46: United States of America | S46: -
A47: Sherwin | B47: 2021 | C47: https://doi.org/10.1021/acs.est.0c07955 | D47: e-Fuels | E47: Fischer Tropsch | F47: 2050 | G47: Reference | H47: =[17]Outputs!$J$9 * (1 +Inputs!$C$5) ^ ('Standardization Results'!F27-'Standardization Results'!B27) -> 84.263501 | I47: =[17]Outputs!$K$9 * (1 +Inputs!$C$5) ^ ('Standardization Results'!F27-'Standardization Results'!B27) -> 400.61385 | J47: =[17]Outputs!$L$9 * (1 +Inputs!$C$5) ^ ('Standardization Results'!F27-'Standardization Results'!B27) -> 573.6289 | K47: =[17]Outputs!$M$9 * (1 +Inputs!$C$5) ^ ('Standardization Results'!F27-'Standardization Results'!B27) -> 633.64187 | L47: 0 | Q47: Academic | R47: United States of America | S47: -
A48: Staples et. al. | B48: 2021 | C48: https://doi.org/10.1021/acs.est.0c07674 | D48: e-Fuels | E48: Fischer Tropsch | F48: 2030 | G48: Reference | H48: =[18]Outputs!$C$10 -> 2544.8085 | I48: =[18]Outputs!$D$10 -> 1510.2027 | Q48: Academic | R48: United States of America | S48: -

Sheet CO2 Effect
A1: Reference | B1: Year of Assumptions in Study | C1: DOI | D1: Pathway | E1: Pathway Detail | F1: Year of Cost | G1: Study Scenario | H1: Baseline | I1: LCOE Harmonized | J1: CO2 Cost Harmonized | K1: Fully Harmonized | L1: CO2 Effect | M1: WACC Effect | N1: Cause for CO2 Effect | O1: Electricity | P1: CO2 | Q1: CAPEX | R1: Other OPEX | S1: Study Type | T1: Plant Location | U1: Production | W1: Production
A2: Sherwin | B2: 2021 | C2: https://doi.org/10.1021/acs.est.0c07955 | D2: e-Fuels | E2: Fischer Tropsch | F2: 2050 | G2: Baseline | H2: 87.667746 | I2: 295.79464 | J2: 645.13739 | K2: 707.57489 | L2: =J2-I2 -> 349.34275 | S2: Academic | T2: United States of America | U2: - | W2: -
A3: Marchese et.al. | B3: 2021 | C3: https://doi.org/10.1016/j.jcou.2021.101487 | D3: e-Fuels | E3: Fischer Tropsch | F3: 2050 | G3: C.4 | H3: 310.7968 | I3: -101.10918 | J3: 395.15232 | K3: 385.16193 | L3: =J3-I3 -> 496.2615 | S3: Academic | T3: Europe | U3: 69000000 | W3: 58035000
A4: Martin et. al. | B4: 2023 | C4: https://www.sciencedirect.com/science/article/pii/S136403212300494X?via%3Dihub | D4: e-Fuels | E4: Fischer Tropsch | F4: 2050 | G4: Baseline | H4: 350.60606 | I4: 217.99064 | J4: 804.40002 | K4: 807.05292 | L4: =J4-I4 -> 586.40938 | S4: Academic | T4: Europe | U4: - | W4: 157410000
A5: Falter et. al. | B5: 2015 | C5: https://doi.org/10.1021/acs.est.5b03515 | D5: Solar Fuels | E5: Fischer Tropsch | F5: 2024 | H5: 563.67631 | I5: 592.9283 | J5: 5581.904 | K5: 5983.7231 | L5: =J5-I5 -> 4988.9757 | M5: =K5-J5 -> 401.81909 | N5: CO2 Consumption: 6kg/kg fuel. Initial assumption is very low (€100/t) | S5: Academic | T5: MENA | U5: 58035000 | W5: 157410000
A6: Marchese et.al. | B6: 2021 | C6: https://doi.org/10.1016/j.jcou.2021.101487 | D6: e-Fuels | E6: Fischer Tropsch | F6: 2050 | G6: C.1 | H6: 597.79762 | I6: 154.73998 | J6: 529.30576 | K6: 519.29748 | L6: =J6-I6 -> 374.56577 | O6: 0.21202579 | P6: 0.23970956 | Q6: 0.15126255 | R6: 0.3970021 | S6: Academic | T6: Europe | U6: 87000000 | W6: 48000000
A7: Marchese et.al. | B7: 2021 | C7: https://doi.org/10.1016/j.jcou.2021.101487 | D7: e-Fuels | E7: Fischer Tropsch | F7: 2050 | G7: C.5 | H7: 628.73238 | I7: 100.46812 | J7: 612.28162 | K7: 601.90508 | L7: =J7-I7 -> 511.8135 | S7: Academic | T7: Europe | U7: 68000000 | W7: 58035000
A8: Albrecht et. al. | B8: 2016 | C8: https://doi.org/10.1016/j.energy.2019.116511 | D8: e-Fuels | E8: Fischer Tropsch | F8: 2024 | G8: Baseline | H8: 642.2967 | I8: 768.83261 | J8: 2386.5585 | K8: 2466.5878 | L8: =J8-I8 -> 1617.7259 | M8: =K8-J8 -> 80.02936 | N8: CO2 Consumption: 3.1 kg/kg fuel. Initial assumption is low (€115/t) | S8: Industrial | T8: Europe | U8: 1.4477822e+08 | V8: This study has a detailed breakdown but considers a scenario where electricity is an output, leading to lower overall costs. | W8: -
A9: Peters et. al. | B9: 2022 | C9: https://doi.org/10.3390/pr10040699 | D9: e-Fuels | E9: Fischer Tropsch | F9: 2024 | G9: Baseline | H9: 668.37766 | I9: 1052.7567 | J9: 3733.7237 | K9: 3772.7486 | L9: =J9-I9 -> 2680.967 | M9: =K9-J9 -> 39.024876 | N9: Initial assumption is very low (€70/t) | O9: 0.066800203 | P9: 0.46591807 | Q9: 0.43493529 | R9: 0.032346433 | S9: Academic | T9: Europe | U9: 208032000 | V9: Low intial electricity and CO2 price assumption lead to lower costs | W9: 1000000
A10: Seymour et al. | B10: 2024 | C10: https://doi.org/10.1039/D3SE00978E | D10: e-Fuels | E10: Fischer Tropsch | F10: 2050 | G10: Baseline | H10: 722.87277 | I10: 698.76814 | J10: 996.12746 | K10: 1015.6034 | L10: =J10-I10 -> 297.35932 | O10: 0.36581603 | P10: 0.42106952 | Q10: 0.13952769 | R10: 0.073586759 | S10: Academic | T10: United States of America | U10: 2110761 | W10: -
A11: Falter et. al. | B11: 2015 | C11: https://doi.org/10.1021/acs.est.5b03515 | D11: Solar Fuels | E11: Fischer Tropsch | F11: 2024 | H11: 798.16358 | I11: 827.41558 | J11: 5816.3913 | K11: 6234.134 | L11: =J11-I11 -> 4988.9757 | M11: =K11-J11 -> 417.74275 | N11: CO2 Consumption: 6kg/kg fuel. Initial assumption is very low (€100/t) | O11: 0.058359447 | P11: 0.66723593 | Q11: 0.10459443 | R11: 0.1698102 | S11: Academic | T11: MENA | U11: 58035000 | V11: Initial assumptions are very optimistic (by author's admission), Production is high. Overall process efficiency is 5% according to the author | W11: 35000000
A12: Moretti et al. | B12: 2023 | C12: https://doi.org/10.1016/j.scitotenv.2023.166005 | D12: Solar Fuels | E12: Fischer Tropsch | F12: 2050 | G12: Optimistic | H12: 825.36876 | I12: 825.39286 | J12: 1164.2097 | K12: 1237.7413 | L12: =J12-I12 -> 338.81681 | S12: Industrial | T12: MENA | U12: 31354838 | W12: 69000000
A13: Moretti et al. | B13: 2023 | C13: https://doi.org/10.1016/j.scitotenv.2023.166005 | D13: Solar Fuels | E13: Fischer Tropsch | F13: 2024 | G13: Baseline | H13: 838.68815 | I13: 793.08716 | J13: 1421.7741 | K13: 1486.7546 | L13: =J13-I13 -> 628.68696 | M13: =K13-J13 -> 64.980469 | N13: CO2 Consumption: 2.5 kg/kg fuel is low and initial assumption is €730/t | O13: -0.059549309 | P13: 0.68508807 | Q13: 0.23309418 | R13: 0.14136706 | S13: Industrial | T13: MENA | U13: 31354838 | V13: High CO2 cost assumed, hence there is less effect, High Production levels lead to lower costs due to scale and cheaper labour in MENA | W13: -
A14: Moretti et al. | B14: 2023 | C14: https://doi.org/10.1016/j.scitotenv.2023.166005 | D14: Solar Fuels | E14: Fischer Tropsch | F14: 2050 | G14: Baseline | H14: 982.3514 | I14: 982.3755 | J14: 1321.1923 | K14: 1420.684 | L14: =J14-I14 -> 338.81681 | O14: -3.0173341e-05 | P14: 0.51590683 | Q14: 0.34032941 | R14: 0.14379393 | S14: Industrial | T14: MENA | U14: 31354838 | W14: 1000000
A15: Gray et al. | B15: 2024 | C15: https://doi.org/10.1016/j.rser.2024.114552 | D15: e-Fuels | E15: Fischer Tropsch | F15: 2050 | G15: High DAC Deployment | H15: 1053.0157 | I15: 1131.3935 | J15: 1374.9394 | K15: 1452.8417 | L15: =J15-I15 -> 243.54589 | O15: 0.38762689 | P15: 0.31625232 | Q15: 0.2019726 | R15: 0.094148182 | S15: Academic | T15: Europe | U15: 39140034 | V15: This scenario assumes a decline in CO2 cost but not CAPEX | W15: 68000000
A16: Dietrich et. al. | B16: 2018 | C16: https://doi.org/10.1016/j.biombioe.2017.07.006 | D16: e-Fuels | E16: Fischer Tropsch | F16: 2024 | H16: 1144.7871 | I16: 717.33157 | J16: 2278.5389 | K16: 2313.9915 | L16: =J16-I16 -> 1561.2073 | M16: =K16-J16 -> 35.452605 | N16: CO2 Consumption: 3kg/kg fuel. Initial assumption is very low (€70/t) | O16: 0.11002479 | P16: 0.32309926 | Q16: 0.51966602 | R16: 0.04720993 | S16: Academic | T16: Europe | W16: 39140034
A17: Martin et. al. | B17: 2023 | C17: https://www.sciencedirect.com/science/article/pii/S136403212300494X?via%3Dihub | D17: e-Fuels | E17: Fischer Tropsch | F17: 2024 | G17: Baseline | H17: 1148.3867 | I17: 1137.4782 | J17: 2381.0325 | K17: 2384.2032 | L17: =J17-I17 -> 1243.5543 | M17: =K17-J17 -> 3.1706405 | N17: Not available | S17: Academic | T17: Europe | U17: - | W17: 68000000
A18: Schmidt et. al. | B18: 2024 | C18: https://onlinelibrary.wiley.com/doi/full/10.1002/cite.201700129?saml_referrer https://www.concawe.eu/wp-content/uploads/Rpt_24-4-1.pdf | D18: e-Fuels | E18: Fischer Tropsch | F18: 2024 | G18: EU-South | H18: 1286.1593 | I18: 1276.9022 | J18: 2678.7922 | K18: 2549.092 | L18: =J18-I18 -> 1401.8901 | M18: =K18-J18 -> -129.70025 | N18: CO2 Consumption: 3.7 kg/kg fuel. Initial assumption is low (€177/t) | S18: Industrial | T18: Europe | U18: 1000000 | W18: 31354838
A19: Schmidt et. al. | B19: 2024 | C19: https://onlinelibrary.wiley.com/doi/full/10.1002/cite.201700129?saml_referrer https://www.concawe.eu/wp-content/uploads/Rpt_24-4-1.pdf | D19: e-Fuels | E19: Fischer Tropsch | F19: 2024 | G19: EU-Central | H19: 1309.1064 | I19: 1104.4865 | J19: 2506.3765 | K19: 2406.0026 | L19: =J19-I19 -> 1401.8901 | M19: =K19-J19 -> -100.3739 | N19: CO2 Consumption: 3.7 kg/kg fuel. Initial assumption is low (€177/t) | S19: Industrial | T19: Europe | U19: 1000000 | W19: 35000000
A20: Falter et. al. | B20: 2020 | C20: https://doi.org/10.1039/d0se00179a | D20: Solar Fuels | E20: Fischer Tropsch | F20: 2024 | H20: 1312.9985 | I20: 1349.9394 | J20: 5188.9197 | K20: 5172.001 | L20: =J20-I20 -> 3838.9802 | M20: =K20-J20 -> -16.918643 | N20: CO2 Consumption: 6kg/kg fuel. Initial assumption is very low (€100/t) | S20: Academic | T20: MENA | U20: 45872966 | V20: Most assumptions based on previous study | W20: 157410000
A21: Sherwin | B21: 2021 | C21: https://doi.org/10.1021/acs.est.0c07955 | D21: e-Fuels | E21: Fischer Tropsch | F21: 2024 | G21: Baseline | H21: 1330.2315 | I21: 1583.3702 | J21: 2350.1001 | K21: 2076.2914 | L21: =J21-I21 -> 766.7299 | M21: =K21-J21 -> -273.80867 | N21: CO2 consumption: 3.32 kg/kg fuel. | S21: Academic | T21: United States of America | U21: - | W21: 87000000
A22: Peacock et. al. | B22: 2024 | D22: e-Fuels | E22: Fischer Tropsch | F22: 2050 | G22: SOEC, Nuclear + Renewables | H22: 1383.9118 | I22: 1232.3763 | J22: 2232.7591 | K22: 2206.1742 | L22: =J22-I22 -> 1000.3828 | N22: Lower CO2 consumption compared to other scenarios in the same study | S22: Academic | T22: United Kingdom | U22: 157410000 | W22: 157410000
A23: Schmidt et. al. | B23: 2024 | C23: https://onlinelibrary.wiley.com/doi/full/10.1002/cite.201700129?saml_referrer https://www.concawe.eu/wp-content/uploads/Rpt_24-4-1.pdf | D23: e-Fuels | E23: Fischer Tropsch | F23: 2050 | G23: EU-South | H23: 1392.5582 | I23: 1036.2639 | J23: 1404.2086 | K23: 1277.8941 | L23: =J23-I23 -> 367.94472 | S23: Industrial | T23: Europe | U23: 1000000 | W23: 31354838
A24: Schmidt et. al. | B24: 2024 | C24: https://onlinelibrary.wiley.com/doi/full/10.1002/cite.201700129?saml_referrer https://www.concawe.eu/wp-content/uploads/Rpt_24-4-1.pdf | D24: e-Fuels | E24: Fischer Tropsch | F24: 2050 | G24: EU-North | H24: 1393.4729 | I24: 1037.1786 | J24: 1405.1233 | K24: 1278.5037 | L24: =J24-I24 -> 367.94472 | O24: 0.31920876 | P24: 0.4639346 | Q24: 0.17887399 | R24: 0.037982647 | S24: Industrial | T24: Europe | U24: 1000000 | W24: 2110761
A25: Marchese et.al. | B25: 2021 | C25: https://doi.org/10.1016/j.jcou.2021.101487 | D25: e-Fuels | E25: Fischer Tropsch | F25: 2024 | G25: C.4 | H25: 1458.3489 | I25: 751.42719 | J25: 1910.0714 | K25: 1895.1917 | L25: =J25-I25 -> 1158.6442 | M25: =K25-J25 -> -14.879693 | N25: CO2 Consumption: 3.97 kg/kg fuel | S25: Academic | T25: Europe | U25: 69000000 | W25: 1250000000
A26: Schmidt et. al. | B26: 2024 | C26: https://onlinelibrary.wiley.com/doi/full/10.1002/cite.201700129?saml_referrer https://www.concawe.eu/wp-content/uploads/Rpt_24-4-1.pdf | D26: e-Fuels | E26: Fischer Tropsch | F26: 2024 | G26: EU-North | H26: 1510.5026 | I26: 1255.2682 | J26: 2657.1582 | K26: 2530.7794 | L26: =J26-I26 -> 1401.8901 | M26: =K26-J26 -> -126.37876 | N26: CO2 Consumption: 3.7 kg/kg fuel. Initial assumption is low (€177/t) | O26: 0.20134349 | P26: 0.54125942 | Q26: 0.22754856 | R26: 0.029848524 | S26: Industrial | T26: Europe | U26: 1000000 | V26: 1st of a kind industrial plant | W26: 157410000
A27: Peacock et. al. | B27: 2024 | D27: e-Fuels | E27: Fischer Tropsch | F27: 2050 | G27: PEM, Nuclear + Renewables | H27: 1594.7288 | I27: 1414.8415 | J27: 2451.18 | K27: 2422.9445 | L27: =J27-I27 -> 1036.3385 | O27: 0.34291278 | P27: 0.41621386 | Q27: 0.07875691 | R27: 0.16211645 | S27: Academic | T27: United Kingdom | U27: 157410000 | W27: 1.4477822e+08
A28: Schmidt et. al. | B28: 2024 | C28: https://onlinelibrary.wiley.com/doi/full/10.1002/cite.201700129?saml_referrer https://www.concawe.eu/wp-content/uploads/Rpt_24-4-1.pdf | D28: e-Fuels | E28: Fischer Tropsch | F28: 2050 | G28: EU-Central | H28: 1651.2877 | I28: 1046.3046 | J28: 1414.2493 | K28: 1286.4774 | L28: =J28-I28 -> 367.94472 | S28: Industrial | T28: Europe | U28: 1000000 | W28: 31354838
A29: Meurer et al. | B29: 2024 | C29: https://doi.org/10.1039/D3SE01156A | D29: e-Fuels | E29: Fischer Tropsch | F29: 2024 | H29: 1678.5512 | I29: 1330.6142 | J29: 3382.6072 | K29: 3347.2914 | L29: =J29-I29 -> 2051.993 | M29: =K29-J29 -> -35.315744 | N29: Initial assumption is €770/t | S29: Academic | T29: Europe | U29: 3650000 | W29: 39140034
A30: Marchese et.al. | B30: 2021 | C30: https://doi.org/10.1016/j.jcou.2021.101487 | D30: e-Fuels | E30: Fischer Tropsch | F30: 2050 | G30: C.3 | H30: 1692.7913 | I30: 832.37401 | J30: 1521.0985 | K30: 1507.4744 | L30: =J30-I30 -> 688.72444 | S30: Academic | T30: Europe | U30: 48000000 | W30: 45872966
A31: Seymour et al. | B31: 2024 | C31: https://doi.org/10.1039/D3SE00978E | D31: e-Fuels | E31: Fischer Tropsch | F31: 2024 | G31: Baseline | H31: 1703.2942 | I31: 1744.0993 | J31: 2493.7647 | K31: 2519.6177 | L31: =J31-I31 -> 749.66538 | M31: =K31-J31 -> 25.853081 | N31: CO2 Consumption: 3.6 kg/kg fuel. Overall production is high (1.7Mt/y) | O31: 0.25985878 | P31: 0.55324106 | Q31: 0.12265292 | R31: 0.064247239 | S31: Academic | T31: United States of America | U31: 2110761 | V31: High CO2 cost assumed, hence there is less effect | W31: 48000000
A32: Marchese et.al. | B32: 2021 | C32: https://doi.org/10.1016/j.jcou.2021.101487 | D32: e-Fuels | E32: Fischer Tropsch | F32: 2024 | G32: C.5 | H32: 1730.5108 | I32: 823.96436 | J32: 2024.3097 | K32: 2007.3752 | L32: =J32-I32 -> 1200.3453 | M32: =K32-J32 -> -16.934451 | N32: CO2 Consumption: 4 kg/kg fuel | S32: Academic | T32: Europe | U32: 68000000 | W32: -
A33: Rojas-Michaga et. al. | B33: 2023 | C33: https://www.sciencedirect.com/science/article/pii/S0196890423007732?via%3Dihub#s0005 | D33: e-Fuels | E33: Fischer Tropsch | F33: 2024 | H33: 1755.126 | I33: 1456.3452 | J33: 3092.0351 | K33: 3109.819 | L33: =J33-I33 -> 1635.6899 | M33: =K33-J33 -> 17.783884 | N33: CO2 consmuption : 5.28kg/kg CO2 | O33: 0.28620653 | P33: 0.47089021 | Q33: 0.025500914 | R33: 0.21740235 | S33: Academic | T33: United Kingdom | U33: 25105853 | V33: Very detailed study, we should note that this study considers a wide variety of costs that will be practically applicable (e.g. labour, overhead, catalyst, by-product sales etc.) | W33: 87000000
A34: Peacock et. al. | B34: 2024 | D34: e-Fuels | E34: Fischer Tropsch | F34: 2050 | G34: PEM, Nuclear | H34: 1875.4225 | I34: 1436.7973 | J34: 2556.8251 | K34: 2528.5896 | L34: =J34-I34 -> 1120.0278 | S34: Academic | T34: United Kingdom | U34: 157410000 | W34: 25105853
A35: Marchese et.al. | B35: 2021 | C35: https://doi.org/10.1016/j.jcou.2021.101487 | D35: e-Fuels | E35: Fischer Tropsch | F35: 2024 | G35: C.1 | H35: 1892.3064 | I35: 1097.7096 | J35: 1959.8018 | K35: 1943.9244 | L35: =J35-I35 -> 862.09215 | M35: =K35-J35 -> -15.877313 | N35: CO2 Consumption: 3.1 kg/kg fuel. Lowest of all scenarios in Marchese et. al. | O35: 0.19014911 | P35: 0.42429752 | Q35: 0.21340218 | R35: 0.17215119 | S35: Academic | T35: Europe | U35: 87000000 | W35: -
A36: Marchese et.al. | B36: 2021 | C36: https://doi.org/10.1016/j.jcou.2021.101487 | D36: e-Fuels | E36: Fischer Tropsch | F36: 2050 | G36: C.2 | H36: 1954.9193 | I36: 1192.8986 | J36: 2139.2446 | K36: 2121.2689 | L36: =J36-I36 -> 946.34598 | N36: Lower CO2 consumption compared to other scenarios in the same study | S36: Academic | T36: Europe | U36: 35000000 | W36: 208032000
A37: Bachorz et. al | B37: 2024 | C37: https://www.researchsquare.com/article/rs-4241841/v1 | D37: e-Fuels | E37: Methanol | F37: 2024 | H37: 2404.7475 | I37: 2435.2346 | J37: 2575.7824 | K37: 2555.1301 | L37: =J37-I37 -> 140.54784 | M37: =K37-J37 -> -20.652354 | N37: Study assumption (€1200/t) is very close to standard input supplied | O37: 0.054451686 | P37: 0.62743119 | Q37: 0.30588185 | R37: 0.012235274 | S37: Academic | T37: Europe | U37: - | V37: Due to a high WACC assumption (~11%, final wacc correction leads to lower cost) | W37: 1000000
A38: Peacock et. al. | B38: 2024 | D38: e-Fuels | E38: Fischer Tropsch | F38: 2024 | G38: SOEC, Nuclear + Renewables | H38: 2681.2488 | I38: 2495.6577 | J38: 4573.4254 | K38: 4548.0843 | L38: =J38-I38 -> 2077.7677 | M38: =K38-J38 -> -25.341062 | N38: CO2 Consumption: 5.08 kg/kg fuel Initial assumption is €700/t. | S38: Academic | T38: United Kingdom | U38: 157410000 | W38: 1000000
A39: Marchese et.al. | B39: 2021 | C39: https://doi.org/10.1016/j.jcou.2021.101487 | D39: e-Fuels | E39: Fischer Tropsch | F39: 2024 | G39: C.3 | H39: 2708.6121 | I39: 1804.7169 | J39: 3396.6119 | K39: 3374.1564 | L39: =J39-I39 -> 1591.8951 | M39: =K39-J39 -> -22.455594 | N39: CO2 consumption : 5.62kg/kg fuel | S39: Academic | T39: Europe | U39: 48000000 | W39: 1000000
A40: Gray et al. | B40: 2024 | C40: https://doi.org/10.1016/j.rser.2024.114552 | D40: e-Fuels | E40: Fischer Tropsch | F40: 2024 | G40: Reference DAC Deployment | H40: 2727.5773 | I40: 2805.9552 | J40: 2849.8757 | K40: 2927.778 | L40: =J40-I40 -> 43.92052 | M40: =K40-J40 -> 77.902289 | N40: Study assumption (€1300/t) is very close to standard input supplied | O40: 0.19629913 | P40: 0.65374158 | Q40: 0.10228147 | R40: 0.047677823 | S40: Academic | T40: Europe | U40: 39140034 | W40: 157410000
A41: Marchese et.al. | B41: 2021 | C41: https://doi.org/10.1016/j.jcou.2021.101487 | D41: e-Fuels | E41: Fischer Tropsch | F41: 2024 | G41: C.2 | H41: 2761.7003 | I41: 1368.7085 | J41: 3557.2858 | K41: 3528.5632 | L41: =J41-I41 -> 2188.5773 | M41: =K41-J41 -> -28.722514 | N41: CO2 consumption: 7.7 kg/kg fuel | S41: Academic | T41: Europe | U41: 35000000 | W41: 69000000
A42: Peacock et. al. | B42: 2024 | D42: e-Fuels | E42: Fischer Tropsch | F42: 2024 | G42: PEM, Nuclear + Renewables | H42: 2797.4452 | I42: 2548.3625 | J42: 4640.6838 | K42: 4619.0164 | L42: =J42-I42 -> 2092.3213 | M42: =K42-J42 -> -21.667326 | N42: CO2 Consumption: 5.08 kg/kg fuel Initial assumption is €700/t. | O42: 0.1897282 | P42: 0.68542684 | Q42: 0.041118673 | R42: 0.083726288 | S42: Academic | T42: United Kingdom | U42: 157410000 | W42: 3650000
A43: Peacock et. al. | B43: 2024 | D43: e-Fuels | E43: Fischer Tropsch | F43: 2024 | G43: PEM, Nuclear | H43: 3266.1214 | I43: 2576.9841 | J43: 4528.7897 | K43: 4507.1224 | L43: =J43-I43 -> 1951.8056 | M43: =K43-J43 -> -21.667326 | N43: CO2 Consumption: 5.08 kg/kg fuel Initial assumption is €700/t. | S43: Academic | T43: United Kingdom | U43: 157410000 | V43: Large scale production but high electrolyser costs and multiple replacements considered (missing from most other studies)
A44: Saad et al. | B44: 2024 | C44: https://doi.org/10.1021/acs.est.4c01578 | D44: e-Fuels | E44: Methanol | F44: 2024 | G44: CO2HY | H44: 5186.3474 | I44: 3438.5193 | J44: 5951.2257 | K44: 6013.8338 | L44: =J44-I44 -> 2512.7064 | M44: =K44-J44 -> 62.608074 | N44: CO2 Consumption: 3.1 kg/kg fuel. Very high production quantity (10Mt/year) means effect is larger | O44: 0.1011943 | P44: 0.61193523 | Q44: 0.2723405 | R44: 0.014529965 | S44: Academic | T44: Europe | U44: 1250000000 | W44: 1250000000
A45: Saad et al. | B45: 2024 | C45: https://doi.org/10.1021/acs.est.4c01578 | D45: e-Fuels | E45: Methanol | F45: 2024 | G45: CO2ER | H45: 6201.6747 | I45: 3818.5621 | J45: 3865.4181 | K45: 3949.4052 | L45: =J45-I45 -> 46.856029 | M45: =K45-J45 -> 83.987151 | N45: Lower CO2 consumed than combusted, very low CO2 consumption | O45: 0.18840662 | P45: 0.68456138 | Q45: 0.11897367 | R45: 0.008058336 | S45: Academic | T45: Europe | U45: 1250000000 | V45: LCA accounting methodology means that the emissions abated are low, therefore cost is high | W45: -
A46: Staples et. al. | B46: 2021 | C46: https://doi.org/10.1021/acs.est.0c07674 | D46: e-Fuels | E46: Fischer Tropsch | L46: =J46-I46 -> 0 | S46: Academic | T46: United States of America | U46: - | W46: 1000000
A47: Brazzola et al. | B47: 2024 | D47: e-Fuels | E47: Fischer Tropsch | L47: =J47-I47 -> 0 | S47: Academic | T47: Worldwide | U47: - | W47: 2110761
K49: =AVERAGEIF(F:F,2050,K:K) -> 1339.8347

Sheet Median CO2
A1: Reference | B1: Year of Assumptions in Study | C1: DOI | D1: Pathway | E1: Pathway Detail | F1: Year of Cost | G1: Study Scenario | H1: Baseline | I1: LCOE Harmonized | J1: CO2 Cost Harmonized | K1: Fully Harmonized | L1: Residual Emissions (gCO2eq/L fuel) | M1: Electricity | N1: CO2 | O1: CAPEX | P1: Other OPEX | Q1: Study Type | R1: Plant Location | S1: Production
A2: Brazzola et al. | B2: 2024 | D2: e-Fuels | E2: Fischer Tropsch | F2: 2050 | G2: Reference | H2: 226.43484 | I2: 507.54963 | J2: 256.69177 | K2: 256.69177 | L2: 0 | Q2: Academic | R2: Worldwide | S2: -
A3: Gray et al. | B3: 2024 | C3: https://doi.org/10.1016/j.rser.2024.114552 | D3: e-Fuels | E3: Fischer Tropsch | F3: 2050 | G3: High DAC Deployment | H3: 788.73379 | I3: 867.11163 | J3: 942.76068 | K3: 1020.663 | L3: 276.92708 | M3: 0.43600143 | N3: 0.23092291 | O3: 0.22717811 | P3: 0.10589756 | Q3: Academic | R3: Europe | S3: 39140034 | T3: This scenario assumes a decline in CO2 cost but not CAPEX
A4: Marchese et.al. | B4: 2021 | C4: https://doi.org/10.1016/j.jcou.2021.101487 | D4: e-Fuels | E4: Fischer Tropsch | F4: 2050 | G4: C.1 | H4: 170.71314 | I4: -272.3445 | J4: -62.17363 | K4: -72.181908 | L4: 0 | M4: 0.23149371 | N4: 0.1699007 | O4: 0.16515127 | P4: 0.43345431 | Q4: Academic | R4: Europe | S4: 87000000
A5: Marchese et.al. | B5: 2021 | C5: https://doi.org/10.1016/j.jcou.2021.101487 | D5: e-Fuels | E5: Fischer Tropsch | F5: 2050 | G5: C.2 | H5: 1527.8348 | I5: 765.8141 | J5: 1303.5213 | K5: 1285.5457 | L5: 0 | Q5: Academic | R5: Europe | S5: 35000000
A6: Marchese et.al. | B6: 2021 | C6: https://doi.org/10.1016/j.jcou.2021.101487 | D6: e-Fuels | E6: Fischer Tropsch | F6: 2050 | G6: C.3 | H6: 1265.7068 | I6: 405.28953 | J6: 796.0482 | K6: 782.42414 | L6: 0 | Q6: Academic | R6: Europe | S6: 48000000
A7: Marchese et.al. | B7: 2021 | C7: https://doi.org/10.1016/j.jcou.2021.101487 | D7: e-Fuels | E7: Fischer Tropsch | F7: 2050 | G7: C.4 | H7: -116.28768 | I7: -528.19366 | J7: -239.21269 | K7: -249.20308 | L7: 0 | Q7: Academic | R7: Europe | S7: 69000000
A8: Marchese et.al. | B8: 2021 | C8: https://doi.org/10.1016/j.jcou.2021.101487 | D8: e-Fuels | E8: Fischer Tropsch | F8: 2050 | G8: C.5 | H8: 628.73238 | I8: 100.46812 | J8: -25.131634 | K8: -35.508173 | L8: 0 | Q8: Academic | R8: Europe | S8: 68000000
A9: Martin et. al. | B9: 2023 | C9: https://www.sciencedirect.com/science/article/pii/S136403212300494X?via%3Dihub | D9: e-Fuels | E9: Fischer Tropsch | F9: 2050 | G9: Reference | H9: -79.44501 | I9: -158.69324 | J9: 28.780445 | K9: 30.365765 | L9: 464.84064 | Q9: Academic | R9: Europe | S9: -
A10: Moretti et al. | B10: 2023 | C10: https://doi.org/10.1016/j.scitotenv.2023.166005 | D10: Solar Fuels | E10: Fischer Tropsch | F10: 2050 | G10: Reference | H10: 498.1576 | I10: 498.1817 | J10: 492.76064 | K10: 592.25228 | L10: 468.3096 | M10: -3.6841458e-05 | N10: 0.4089253 | O10: 0.41554006 | P10: 0.17557148 | Q10: Industrial | R10: MENA | S10: 31354838
A11: Moretti et al. | B11: 2023 | C11: https://doi.org/10.1016/j.scitotenv.2023.166005 | D11: Solar Fuels | E11: Fischer Tropsch | F11: 2050 | G11: Optimistic | H11: 354.95843 | I11: 354.9835 | J11: 349.34342 | K11: 425.84575 | L11: 468.3096 | Q11: Industrial | R11: MENA | S11: 31354838
A12: Peacock et. al. | B12: 2024 | D12: e-Fuels | E12: Fischer Tropsch | F12: 2050 | G12: PEM, Nuclear | H12: 862.11521 | I12: 600.00187 | J12: 956.03425 | K12: 939.16132 | L12: 215.38773 | Q12: Academic | R12: United Kingdom | S12: 157410000
A13: Peacock et. al. | B13: 2024 | D13: e-Fuels | E13: Fischer Tropsch | F13: 2050 | G13: PEM, Nuclear + Renewables | H13: 694.37846 | I13: 586.88153 | J13: 892.90292 | K13: 876.02999 | L13: 215.38773 | M13: 0.40154651 | N13: 0.31639384 | O13: 0.092223342 | P13: 0.1898363 | Q13: Academic | R13: United Kingdom | S13: 157410000
A14: Peacock et. al. | B14: 2024 | D14: e-Fuels | E14: Fischer Tropsch | F14: 2050 | G14: SOEC, Nuclear + Renewables | H14: 951.16855 | I14: 799.63305 | J14: 1275.779 | K14: 1249.1941 | L14: 215.38773 | Q14: Academic | R14: United Kingdom | S14: 157410000
A15: Schmidt et. al. | B15: 2024 | C15: https://onlinelibrary.wiley.com/doi/full/10.1002/cite.201700129?saml_referrer https://www.concawe.eu/wp-content/uploads/Rpt_24-4-1.pdf | D15: e-Fuels | E15: Fischer Tropsch | F15: 2050 | G15: EU-North | H15: 575.07717 | I15: 362.16308 | J15: 445.15555 | K15: 369.49032 | L15: 110.72204 | M15: 0.38126388 | N15: 0.35972192 | O15: 0.21364762 | P15: 0.045366585 | Q15: Industrial | R15: Europe | S15: 1000000
A16: Schmidt et. al. | B16: 2024 | C16: https://onlinelibrary.wiley.com/doi/full/10.1002/cite.201700129?saml_referrer https://www.concawe.eu/wp-content/uploads/Rpt_24-4-1.pdf | D16: e-Fuels | E16: Fischer Tropsch | F16: 2050 | G16: EU-Central | H16: 1220.1594 | I16: 615.17623 | J16: 754.05733 | K16: 626.28544 | L16: 126.07289 | Q16: Industrial | R16: Europe | S16: 1000000
A17: Schmidt et. al. | B17: 2024 | C17: https://onlinelibrary.wiley.com/doi/full/10.1002/cite.201700129?saml_referrer https://www.concawe.eu/wp-content/uploads/Rpt_24-4-1.pdf | D17: e-Fuels | E17: Fischer Tropsch | F17: 2050 | G17: EU-South | H17: 574.53058 | I17: 361.61649 | J17: 444.60896 | K17: 369.126 | L17: 110.66758 | Q17: Industrial | R17: Europe | S17: 1000000
A18: Seymour et al. | B18: 2024 | C18: https://doi.org/10.1039/D3SE00978E | D18: e-Fuels | E18: Fischer Tropsch | F18: 2050 | G18: Reference | H18: 276.11719 | I18: 252.01257 | J18: 317.68702 | K18: 340.49371 | L18: 305.14 | M18: 0.42922213 | N18: 0.32072475 | O18: 0.16371172 | P18: 0.086341393 | Q18: Academic | R18: United States of America | S18: 2110761
A19: Sherwin | B19: 2021 | C19: https://doi.org/10.1021/acs.est.0c07955 | D19: e-Fuels | E19: Fischer Tropsch | F19: 2050 | G19: Reference | H19: -326.23677 | I19: -126.19169 | J19: 46.823352 | K19: 106.83633 | L19: 0 | Q19: Academic | R19: United States of America | S19: -
K21: =MEDIAN(K2:K19) -> 397.66804
K22: =QUARTILE(K2:K19,1) -> 144.30019
K23: =QUARTILE(K2:K19,3) -> 852.62852

Sheet Low CO2
A1: Reference | B1: Year of Assumptions in Study | C1: DOI | D1: Pathway | E1: Pathway Detail | F1: Year of Cost | G1: Study Scenario | H1: Baseline | I1: LCOE Harmonized | J1: CO2 Cost Harmonized | K1: Fully Harmonized | L1: Residual Emissions (gCO2eq/L fuel) | M1: Electricity | N1: CO2 | O1: CAPEX | P1: Other OPEX | Q1: Study Type | R1: Plant Location | S1: Production
A2: Albrecht et. al. | B2: 2016 | C2: https://doi.org/10.1016/j.energy.2019.116511 | D2: e-Fuels | E2: Fischer Tropsch | F2: 2024 | G2: Reference | H2: 642.2967 | I2: 768.83261 | J2: 2386.5585 | K2: 2466.5878 | Q2: Industrial | R2: Europe | S2: 1.4477822e+08 | T2: This study has a detailed breakdown but considers a scenario where electricity is an output, leading to lower overall costs.
A3: Bachorz et. al | B3: 2024 | C3: https://www.researchsquare.com/article/rs-4241841/v1 | D3: e-Fuels | E3: Methanol | F3: 2024 | G3: Reference | H3: 2404.7475 | I3: 2435.2346 | J3: 1644.4988 | K3: 1623.8464 | M3: 0.091683397 | N3: 0.37268475 | O3: 0.51503063 | P3: 0.020601225 | Q3: Academic | R3: Europe | S3: - | T3: Due to a high WACC assumption (~11%, final wacc correction leads to lower cost)
A4: Brazzola et al. | B4: 2024 | D4: e-Fuels | E4: Fischer Tropsch | F4: 2024 | G4: Reference | H4: 432.43604 | I4: 859.50423 | J4: 291.44109 | K4: 291.44109 | L4: 0 | Q4: Academic | R4: Worldwide | S4: -
A5: Brazzola et al. | B5: 2024 | D5: e-Fuels | E5: Fischer Tropsch | F5: 2050 | G5: Reference | H5: 226.43484 | I5: 507.54963 | J5: 172.10016 | K5: 172.10016 | L5: 0 | Q5: Academic | R5: Worldwide | S5: -
A6: Dietrich et. al. | B6: 2018 | C6: https://doi.org/10.1016/j.biombioe.2017.07.006 | D6: e-Fuels | E6: Fischer Tropsch | F6: 2024 | G6: Reference | H6: 1144.7871 | I6: 706.66811 | J6: 2210.7958 | K6: 2210.7958 | M6: 0.11002479 | N6: 0.32309926 | O6: 0.51966602 | P6: 0.04720993 | Q6: Academic | R6: Europe
A7: Falter et. al. | B7: 2020 | C7: https://doi.org/10.1039/d0se00179a | D7: Solar Fuels | E7: Fischer Tropsch | F7: 2024 | G7: Reference | H7: 2029.869 | I7: 2086.9789 | J7: 8021.9643 | K7: 7995.8085 | Q7: Academic | R7: MENA | S7: 45872966 | T7: Most assumptions based on previous study
A8: Falter et. al. | B8: 2015 | C8: https://doi.org/10.1021/acs.est.5b03515 | D8: Solar Fuels | E8: Fischer Tropsch | F8: 2024 | G8: Reference | H8: 471.65912 | I8: 496.13588 | J8: 4670.6876 | K8: 5006.9118 | Q8: Academic | R8: MENA | S8: 58035000
A9: Falter et. al. | B9: 2015 | C9: https://doi.org/10.1021/acs.est.5b03515 | D9: Solar Fuels | E9: Fischer Tropsch | F9: 2024 | G9: Reference | H9: 667.86758 | I9: 692.34434 | J9: 4866.896 | K9: 5216.4445 | M9: 0.058359447 | N9: 0.66723593 | O9: 0.10459443 | P9: 0.1698102 | Q9: Academic | R9: MENA | S9: 58035000 | T9: Initial assumptions are very optimistic (by author's admission), Production is high. Overall process efficiency is 5% according to the author
A10: Gray et al. | B10: 2024 | C10: https://doi.org/10.1016/j.rser.2024.114552 | D10: e-Fuels | E10: Fischer Tropsch | F10: 2024 | G10: Reference DAC Deployment | H10: 2727.5773 | I10: 2805.9552 | J10: 1286.3639 | K10: 1364.2662 | L10: 276.92708 | M10: 0.41172643 | N10: 0.27374236 | O10: 0.21452964 | P10: 0.10000156 | Q10: Academic | R10: Europe | S10: 39140034
A11: Gray et al. | B11: 2024 | C11: https://doi.org/10.1016/j.rser.2024.114552 | D11: e-Fuels | E11: Fischer Tropsch | F11: 2050 | G11: High DAC Deployment | H11: 1053.0157 | I11: 1131.3935 | J11: 1084.0945 | K11: 1161.9968 | L11: 276.92708 | M11: 0.47985357 | N11: 0.15357069 | O11: 0.25002722 | P11: 0.11654852 | Q11: Academic | R11: Europe | S11: 39140034 | T11: This scenario assumes a decline in CO2 cost but not CAPEX
A12: Marchese et.al. | B12: 2021 | C12: https://doi.org/10.1016/j.jcou.2021.101487 | D12: e-Fuels | E12: Fischer Tropsch | F12: 2024 | G12: C.4 | H12: 1458.3489 | I12: 751.42719 | J12: 756.58446 | K12: 741.70476 | L12: 0 | Q12: Academic | R12: Europe | S12: 69000000
A13: Marchese et.al. | B13: 2021 | C13: https://doi.org/10.1016/j.jcou.2021.101487 | D13: e-Fuels | E13: Fischer Tropsch | F13: 2024 | G13: C.1 | H13: 1892.3064 | I13: 1097.7096 | J13: 1044.9673 | K13: 1029.09 | L13: 0 | M13: 0.28792635 | N13: 0.12826352 | O13: 0.32313647 | P13: 0.26067366 | Q13: Academic | R13: Europe | S13: 87000000
A14: Marchese et.al. | B14: 2021 | C14: https://doi.org/10.1016/j.jcou.2021.101487 | D14: e-Fuels | E14: Fischer Tropsch | F14: 2024 | G14: C.5 | H14: 1730.5108 | I14: 823.96436 | J14: 853.85969 | K14: 836.92524 | L14: 0 | Q14: Academic | R14: Europe | S14: 68000000
A15: Marchese et.al. | B15: 2021 | C15: https://doi.org/10.1016/j.jcou.2021.101487 | D15: e-Fuels | E15: Fischer Tropsch | F15: 2024 | G15: C.3 | H15: 2708.6121 | I15: 1804.7169 | J15: 1738.4744 | K15: 1716.0189 | L15: 0 | Q15: Academic | R15: Europe | S15: 48000000
A16: Marchese et.al. | B16: 2021 | C16: https://doi.org/10.1016/j.jcou.2021.101487 | D16: e-Fuels | E16: Fischer Tropsch | F16: 2024 | G16: C.2 | H16: 2761.7003 | I16: 1368.7085 | J16: 1283.2686 | K16: 1254.5461 | L16: 0 | Q16: Academic | R16: Europe | S16: 35000000
A17: Marchese et.al. | B17: 2021 | C17: https://doi.org/10.1016/j.jcou.2021.101487 | D17: e-Fuels | E17: Fischer Tropsch | F17: 2050 | G17: C.1 | H17: 597.79762 | I17: 297.6618 | J17: 387.449 | K17: 377.44072 | L17: 0 | M17: 0.30744893 | N17: 0.10138713 | O17: 0.16309817 | P17: 0.42806577 | Q17: Academic | R17: Europe | S17: 87000000
A18: Marchese et.al. | B18: 2021 | C18: https://doi.org/10.1016/j.jcou.2021.101487 | D18: e-Fuels | E18: Fischer Tropsch | F18: 2050 | G18: C.2 | H18: 1954.9193 | I18: 1438.7117 | J18: 1677.1795 | K18: 1659.2039 | L18: 0 | Q18: Academic | R18: Europe | S18: 35000000
A19: Marchese et.al. | B19: 2021 | C19: https://doi.org/10.1016/j.jcou.2021.101487 | D19: e-Fuels | E19: Fischer Tropsch | F19: 2050 | G19: C.3 | H19: 1692.7913 | I19: 1109.928 | J19: 1282.4912 | K19: 1268.8672 | L19: 0 | Q19: Academic | R19: Europe | S19: 48000000
A20: Marchese et.al. | B20: 2021 | C20: https://doi.org/10.1016/j.jcou.2021.101487 | D20: e-Fuels | E20: Fischer Tropsch | F20: 2050 | G20: C.4 | H20: 310.7968 | I20: 31.763718 | J20: 168.95658 | K20: 158.96618 | L20: 0 | Q20: Academic | R20: Europe | S20: 69000000
A21: Marchese et.al. | B21: 2021 | C21: https://doi.org/10.1016/j.jcou.2021.101487 | D21: e-Fuels | E21: Fischer Tropsch | F21: 2050 | G21: C.5 | H21: 628.73238 | I21: 270.87595 | J21: 418.34039 | K21: 407.96385 | L21: 0 | Q21: Academic | R21: Europe | S21: 68000000
A22: Martin et. al. | B22: 2023 | C22: https://www.sciencedirect.com/science/article/pii/S136403212300494X?via%3Dihub | D22: e-Fuels | E22: Fischer Tropsch | F22: 2024 | G22: Reference | H22: 1999.3691 | I22: 1980.3771 | J22: 1503.4875 | K22: 1509.0076 | L22: 464.84064 | Q22: Academic | R22: Europe | S22: -
A23: Martin et. al. | B23: 2023 | C23: https://www.sciencedirect.com/science/article/pii/S136403212300494X?via%3Dihub | D23: e-Fuels | E23: Fischer Tropsch | F23: 2050 | G23: Reference | H23: 209.51492 | I23: 196.72581 | J23: 264.87214 | K23: 266.45746 | L23: 464.84064 | Q23: Academic | R23: Europe | S23: -
A24: Meurer et al. | B24: 2024 | C24: https://doi.org/10.1039/D3SE01156A | D24: e-Fuels | E24: Fischer Tropsch | F24: 2024 | G24: Reference | H24: 1678.5512 | I24: 1330.6142 | J24: 2039.9518 | K24: 2004.6361 | Q24: Academic | R24: Europe | S24: 3650000
A25: Moretti et al. | B25: 2023 | C25: https://doi.org/10.1016/j.scitotenv.2023.166005 | D25: Solar Fuels | E25: Fischer Tropsch | F25: 2024 | G25: Reference | H25: 838.68815 | I25: 793.08716 | J25: 427.31075 | K25: 492.29122 | L25: 468.3096 | M25: -0.13183893 | N25: 0.30280211 | O25: 0.51605784 | P25: 0.31297898 | Q25: Industrial | R25: MENA | S25: 31354838 | T25: High CO2 cost assumed, hence there is less effect, High Production levels lead to lower costs due to scale and cheaper labour in MENA
A26: Moretti et al. | B26: 2023 | C26: https://doi.org/10.1016/j.scitotenv.2023.166005 | D26: Solar Fuels | E26: Fischer Tropsch | F26: 2050 | G26: Reference | H26: 982.3514 | I26: 982.36403 | J26: 724.86325 | K26: 824.3549 | L26: 468.3096 | M26: -4.3954638e-05 | N26: 0.29480331 | O26: 0.49577062 | P26: 0.20947002 | Q26: Industrial | R26: MENA | S26: 31354838
A27: Moretti et al. | B27: 2023 | C27: https://doi.org/10.1016/j.scitotenv.2023.166005 | D27: Solar Fuels | E27: Fischer Tropsch | F27: 2050 | G27: Optimistic | H27: 858.71366 | I27: 858.72679 | J27: 590.82298 | K27: 667.32532 | L27: 468.3096 | Q27: Industrial | R27: MENA | S27: 31354838
A28: Peacock et. al. | B28: 2024 | D28: e-Fuels | E28: Fischer Tropsch | F28: 2024 | G28: SOEC, Nuclear + Renewables | H28: 2681.2488 | I28: 2495.6577 | J28: 1656.1215 | K28: 1630.7805 | L28: 215.38773 | Q28: Academic | R28: United Kingdom | S28: 157410000
A29: Peacock et. al. | B29: 2024 | D29: e-Fuels | E29: Fischer Tropsch | F29: 2024 | G29: PEM, Nuclear | H29: 3266.1214 | I29: 2576.9841 | J29: 1611.4858 | K29: 1589.8185 | L29: 215.38773 | Q29: Academic | R29: United Kingdom | S29: 157410000 | T29: Large scale production but high electrolyser costs and multiple replacements considered (missing from most other studies)
A30: Peacock et. al. | B30: 2024 | D30: e-Fuels | E30: Fischer Tropsch | F30: 2050 | G30: PEM, Nuclear | H30: 1120.7136 | I30: 983.41616 | J30: 985.228 | K30: 968.35506 | L30: 215.38773 | Q30: Academic | R30: United Kingdom | S30: 157410000
A31: Peacock et. al. | B31: 2024 | D31: e-Fuels | E31: Fischer Tropsch | F31: 2050 | G31: PEM, Nuclear + Renewables | H31: 952.97687 | I31: 964.92098 | J31: 922.09666 | K31: 905.22373 | L31: 215.38773 | M31: 0.45902108 | N31: 0.21854722 | O31: 0.10542355 | P31: 0.21700815 | Q31: Academic | R31: United Kingdom | S31: 157410000
A32: Peacock et. al. | B32: 2024 | D32: e-Fuels | E32: Fischer Tropsch | F32: 2050 | G32: SOEC, Nuclear + Renewables | H32: 1383.9118 | I32: 1400.7491 | J32: 1324.6324 | K32: 1298.0474 | L32: 215.38773 | Q32: Academic | R32: United Kingdom | S32: 157410000
A33: Peacock et. al. | B33: 2024 | D33: e-Fuels | E33: Fischer Tropsch | F33: 2024 | G33: PEM, Nuclear + Renewables | H33: 2797.4452 | I33: 2548.3625 | J33: 1723.3799 | K33: 1701.7126 | L33: 215.38773 | M33: 0.42030022 | N33: 0.30313381 | O33: 0.091089185 | P33: 0.18547679 | Q33: Academic | R33: United Kingdom | S33: 157410000
A34: Peters et. al. | B34: 2022 | C34: https://doi.org/10.3390/pr10040699 | D34: e-Fuels | E34: Fischer Tropsch | F34: 2024 | G34: Baseline | H34: 642.42374 | I34: 1011.8769 | J34: 3588.7386 | K34: 3626.2481 | M34: 0.066800203 | N34: 0.46591807 | O34: 0.43493529 | P34: 0.032346433 | Q34: Academic | R34: Europe | S34: 208032000 | T34: Low intial electricity and CO2 price assumption lead to lower costs
A35: Rojas-Michaga et. al. | B35: 2023 | C35: https://www.sciencedirect.com/science/article/pii/S0196890423007732?via%3Dihub#s0005 | D35: e-Fuels | E35: Fischer Tropsch | F35: 2024 | G35: Reference | H35: 2879.4702 | I35: 2389.2886 | J35: 5490.9741 | K35: 5101.9877 | M35: 0.28620653 | N35: 0.47089021 | O35: 0.025500914 | P35: 0.21740235 | Q35: Academic | R35: United Kingdom | S35: 25105853 | T35: Very detailed study, we should note that this study considers a wide variety of costs that will be practically applicable (e.g. labour, overhead, catalyst, by-product sales etc.)
A36: Saad et al. | B36: 2024 | C36: https://doi.org/10.1021/acs.est.4c01578 | D36: e-Fuels | E36: Methanol | F36: 2024 | G36: CO2ER | H36: 6201.6747 | I36: 3818.5621 | J36: 3865.4181 | K36: 3949.4052 | M36: 0.18840662 | N36: 0.68456138 | O36: 0.11897367 | P36: 0.008058336 | Q36: Academic | R36: Europe | S36: 1250000000 | T36: LCA accounting methodology means that the emissions abated are low, therefore cost is high
A37: Saad et al. | B37: 2024 | C37: https://doi.org/10.1021/acs.est.4c01578 | D37: e-Fuels | E37: Methanol | F37: 2024 | G37: CO2HY | H37: 5186.3474 | I37: 3438.5193 | J37: 5951.2257 | K37: 6013.8338 | M37: 0.1011943 | N37: 0.61193523 | O37: 0.2723405 | P37: 0.014529965 | Q37: Academic | R37: Europe | S37: 1250000000
A38: Schmidt et. al. | B38: 2024 | C38: https://onlinelibrary.wiley.com/doi/full/10.1002/cite.201700129?saml_referrer https://www.concawe.eu/wp-content/uploads/Rpt_24-4-1.pdf | D38: e-Fuels | E38: Fischer Tropsch | F38: 2050 | G38: EU-North | H38: 832.71053 | I38: 712.36778 | J38: 695.1226 | K38: 619.45736 | L38: 110.72204 | M38: 0.51837814 | N38: 0.21975653 | O38: 0.21599936 | P38: 0.045865961 | Q38: Industrial | R38: Europe | S38: 1000000
A39: Schmidt et. al. | B39: 2024 | C39: https://onlinelibrary.wiley.com/doi/full/10.1002/cite.201700129?saml_referrer https://www.concawe.eu/wp-content/uploads/Rpt_24-4-1.pdf | D39: e-Fuels | E39: Fischer Tropsch | F39: 2050 | G39: EU-Central | H39: 1651.2877 | I39: 1201.2151 | J39: 1172.3567 | K39: 1044.5848 | L39: 126.07289 | Q39: Industrial | R39: Europe | S39: 1000000
A40: Schmidt et. al. | B40: 2024 | C40: https://onlinelibrary.wiley.com/doi/full/10.1002/cite.201700129?saml_referrer https://www.concawe.eu/wp-content/uploads/Rpt_24-4-1.pdf | D40: e-Fuels | E40: Fischer Tropsch | F40: 2050 | G40: EU-South | H40: 832.16394 | I40: 711.82119 | J40: 694.576 | K40: 619.09305 | L40: 110.66758 | Q40: Industrial | R40: Europe | S40: 1000000
A41: Schmidt et. al. | B41: 2024 | C41: https://onlinelibrary.wiley.com/doi/full/10.1002/cite.201700129?saml_referrer https://www.concawe.eu/wp-content/uploads/Rpt_24-4-1.pdf | D41: e-Fuels | E41: Fischer Tropsch | F41: 2024 | G41: EU-Central | H41: 1309.1064 | I41: 1104.4865 | J41: 1231.6697 | K41: 1131.2958 | L41: 204.66864 | Q41: Industrial | R41: Europe | S41: 1000000
A42: Schmidt et. al. | B42: 2024 | C42: https://onlinelibrary.wiley.com/doi/full/10.1002/cite.201700129?saml_referrer https://www.concawe.eu/wp-content/uploads/Rpt_24-4-1.pdf | D42: e-Fuels | E42: Fischer Tropsch | F42: 2024 | G42: EU-North | H42: 1540.7127 | I42: 1280.3735 | J42: 1410.1004 | K42: 1281.1941 | L42: 204.66864 | M42: 0.35523027 | N42: 0.19064411 | O42: 0.40146388 | P42: 0.052661743 | Q42: Industrial | R42: Europe | S42: 1000000 | T42: 1st of a kind industrial plant
A43: Schmidt et. al. | B43: 2024 | C43: https://onlinelibrary.wiley.com/doi/full/10.1002/cite.201700129?saml_referrer https://www.concawe.eu/wp-content/uploads/Rpt_24-4-1.pdf | D43: e-Fuels | E43: Fischer Tropsch | F43: 2024 | G43: EU-South | H43: 1286.1593 | I43: 1276.9022 | J43: 1404.0854 | K43: 1274.3852 | L43: 204.66864 | Q43: Industrial | R43: Europe | S43: 1000000
A44: Seymour et al. | B44: 2024 | C44: https://doi.org/10.1039/D3SE00978E | D44: e-Fuels | E44: Fischer Tropsch | F44: 2050 | G44: Reference | H44: 722.87277 | I44: 896.60784 | J44: 792.6233 | K44: 815.02486 | L44: 305.14 | M44: 0.56531158 | N44: 0.18979821 | O44: 0.16033153 | P44: 0.084558683 | Q44: Academic | R44: United States of America | S44: 2110761
A45: Seymour et al. | B45: 2024 | C45: https://doi.org/10.1039/D3SE00978E | D45: e-Fuels | E45: Fischer Tropsch | F45: 2024 | G45: Reference | H45: 1703.2942 | I45: 1744.0993 | J45: 1204.471 | K45: 1248.8596 | L45: 305.14 | M45: 0.46635911 | N45: 0.19821796 | O45: 0.22012074 | P45: 0.11530219 | Q45: Academic | R45: United States of America | S45: 2110761 | T45: High CO2 cost assumed, hence there is less effect
A46: Sherwin | B46: 2021 | C46: https://doi.org/10.1021/acs.est.0c07955 | D46: e-Fuels | E46: Fischer Tropsch | F46: 2024 | G46: Reference | H46: 1330.2315 | I46: 1583.3702 | J46: 1316.9221 | K46: 1043.1134 | L46: 0 | Q46: Academic | R46: United States of America | S46: -
A47: Sherwin | B47: 2021 | C47: https://doi.org/10.1021/acs.est.0c07955 | D47: e-Fuels | E47: Fischer Tropsch | F47: 2050 | G47: Reference | H47: 84.263501 | I47: 400.61385 | J47: 454.44075 | K47: 514.45373 | L47: 0 | Q47: Academic | R47: United States of America | S47: -
A48: Staples et. al. | B48: 2021 | C48: https://doi.org/10.1021/acs.est.0c07674 | D48: e-Fuels | E48: Fischer Tropsch | F48: 2030 | G48: Reference | H48: 2544.8085 | I48: 1510.2027 | Q48: Academic | R48: United States of America | S48: -
K55: =MEDIAN(K5:K47) -> 1248.8596

Sheet High CO2
A1: Reference | B1: Year of Assumptions in Study | C1: DOI | D1: Pathway | E1: Pathway Detail | F1: Year of Cost | G1: Study Scenario | H1: Baseline | I1: LCOE Harmonized | J1: CO2 Cost Harmonized | K1: Fully Harmonized | L1: Residual Emissions (gCO2eq/L fuel) | M1: Electricity | N1: CO2 | O1: CAPEX | P1: Other OPEX | Q1: Study Type | R1: Plant Location | S1: Production
A2: Albrecht et. al. | B2: 2016 | C2: https://doi.org/10.1016/j.energy.2019.116511 | D2: e-Fuels | E2: Fischer Tropsch | F2: 2024 | G2: Reference | H2: 642.2967 | I2: 768.83261 | J2: 2386.5585 | K2: 2466.5878 | Q2: Industrial | R2: Europe | S2: 1.4477822e+08 | T2: This study has a detailed breakdown but considers a scenario where electricity is an output, leading to lower overall costs.
A3: Bachorz et. al | B3: 2024 | C3: https://www.researchsquare.com/article/rs-4241841/v1 | D3: e-Fuels | E3: Methanol | F3: 2024 | G3: Reference | H3: 2404.7475 | I3: 2435.2346 | J3: 1644.4988 | K3: 1623.8464 | M3: 0.091683397 | N3: 0.37268475 | O3: 0.51503063 | P3: 0.020601225 | Q3: Academic | R3: Europe | S3: - | T3: Due to a high WACC assumption (~11%, final wacc correction leads to lower cost)
A4: Brazzola et al. | B4: 2024 | D4: e-Fuels | E4: Fischer Tropsch | F4: 2024 | G4: Reference | H4: 432.43604 | I4: 859.50423 | J4: 1266.5338 | K4: 1266.5338 | L4: 0 | Q4: Academic | R4: Worldwide | S4: -
A5: Brazzola et al. | B5: 2024 | D5: e-Fuels | E5: Fischer Tropsch | F5: 2050 | G5: Reference | H5: 226.43484 | I5: 507.54963 | J5: 747.90647 | K5: 747.90647 | L5: 0 | Q5: Academic | R5: Worldwide | S5: -
A6: Dietrich et. al. | B6: 2018 | C6: https://doi.org/10.1016/j.biombioe.2017.07.006 | D6: e-Fuels | E6: Fischer Tropsch | F6: 2024 | G6: Reference | H6: 1144.7871 | I6: 706.66811 | J6: 2210.7958 | K6: 2210.7958 | M6: 0.11002479 | N6: 0.32309926 | O6: 0.51966602 | P6: 0.04720993 | Q6: Academic | R6: Europe
A7: Falter et. al. | B7: 2020 | C7: https://doi.org/10.1039/d0se00179a | D7: Solar Fuels | E7: Fischer Tropsch | F7: 2024 | G7: Reference | H7: 2029.869 | I7: 2086.9789 | J7: 8021.9643 | K7: 7995.8085 | Q7: Academic | R7: MENA | S7: 45872966 | T7: Most assumptions based on previous study
A8: Falter et. al. | B8: 2015 | C8: https://doi.org/10.1021/acs.est.5b03515 | D8: Solar Fuels | E8: Fischer Tropsch | F8: 2024 | G8: Reference | H8: 471.65912 | I8: 496.13588 | J8: 4670.6876 | K8: 5006.9118 | Q8: Academic | R8: MENA | S8: 58035000
A9: Falter et. al. | B9: 2015 | C9: https://doi.org/10.1021/acs.est.5b03515 | D9: Solar Fuels | E9: Fischer Tropsch | F9: 2024 | G9: Reference | H9: 667.86758 | I9: 692.34434 | J9: 4866.896 | K9: 5216.4445 | M9: 0.058359447 | N9: 0.66723593 | O9: 0.10459443 | P9: 0.1698102 | Q9: Academic | R9: MENA | S9: 58035000 | T9: Initial assumptions are very optimistic (by author's admission), Production is high. Overall process efficiency is 5% according to the author
A10: Gray et al. | B10: 2024 | C10: https://doi.org/10.1016/j.rser.2024.114552 | D10: e-Fuels | E10: Fischer Tropsch | F10: 2024 | G10: Reference DAC Deployment | H10: 2727.5773 | I10: 2805.9552 | J10: 2591.2 | K10: 2669.1023 | L10: 276.92708 | M10: 0.21490233 | N10: 0.62092679 | O10: 0.11197464 | P10: 0.052196233 | Q10: Academic | R10: Europe | S10: 39140034
A11: Gray et al. | B11: 2024 | C11: https://doi.org/10.1016/j.rser.2024.114552 | D11: e-Fuels | E11: Fischer Tropsch | F11: 2050 | G11: High DAC Deployment | H11: 1053.0157 | I11: 1131.3935 | J11: 1529.616 | K11: 1607.5183 | L11: 276.92708 | M11: 0.3516802 | N11: 0.37965986 | O11: 0.18324262 | P11: 0.085417323 | Q11: Academic | R11: Europe | S11: 39140034 | T11: This scenario assumes a decline in CO2 cost but not CAPEX
A12: Marchese et.al. | B12: 2021 | C12: https://doi.org/10.1016/j.jcou.2021.101487 | D12: e-Fuels | E12: Fischer Tropsch | F12: 2024 | G12: C.4 | H12: 1458.3489 | I12: 751.42719 | J12: 1719.2324 | K12: 1704.3527 | L12: 0 | Q12: Academic | R12: Europe | S12: 69000000
A13: Marchese et.al. | B13: 2021 | C13: https://doi.org/10.1016/j.jcou.2021.101487 | D13: e-Fuels | E13: Fischer Tropsch | F13: 2024 | G13: C.1 | H13: 1892.3064 | I13: 1097.7096 | J13: 1808.4467 | K13: 1792.5694 | L13: 0 | M13: 0.20146836 | N13: 0.39002693 | O13: 0.22610565 | P13: 0.18239906 | Q13: Academic | R13: Europe | S13: 87000000
A14: Marchese et.al. | B14: 2021 | C14: https://doi.org/10.1016/j.jcou.2021.101487 | D14: e-Fuels | E14: Fischer Tropsch | F14: 2024 | G14: C.5 | H14: 1730.5108 | I14: 823.96436 | J14: 1830.6642 | K14: 1813.7298 | L14: 0 | Q14: Academic | R14: Europe | S14: 68000000
A15: Marchese et.al. | B15: 2021 | C15: https://doi.org/10.1016/j.jcou.2021.101487 | D15: e-Fuels | E15: Fischer Tropsch | F15: 2024 | G15: C.3 | H15: 2708.6121 | I15: 1804.7169 | J15: 3122.2809 | K15: 3099.8253 | L15: 0 | Q15: Academic | R15: Europe | S15: 48000000
A16: Marchese et.al. | B16: 2021 | C16: https://doi.org/10.1016/j.jcou.2021.101487 | D16: e-Fuels | E16: Fischer Tropsch | F16: 2024 | G16: C.2 | H16: 2761.7003 | I16: 1368.7085 | J16: 3181.0603 | K16: 3152.3377 | L16: 0 | Q16: Academic | R16: Europe | S16: 35000000
A17: Marchese et.al. | B17: 2021 | C17: https://doi.org/10.1016/j.jcou.2021.101487 | D17: e-Fuels | E17: Fischer Tropsch | F17: 2050 | G17: C.1 | H17: 597.79762 | I17: 297.6618 | J17: 823.678 | K17: 813.66972 | L17: 0 | M17: 0.24781959 | N17: 0.27567199 | O17: 0.13146548 | P17: 0.34504294 | Q17: Academic | R17: Europe | S17: 87000000
A18: Marchese et.al. | B18: 2021 | C18: https://doi.org/10.1016/j.jcou.2021.101487 | D18: e-Fuels | E18: Fischer Tropsch | F18: 2050 | G18: C.2 | H18: 1954.9193 | I18: 1438.7117 | J18: 2761.5202 | K18: 2743.5445 | L18: 0 | Q18: Academic | R18: Europe | S18: 35000000
A19: Marchese et.al. | B19: 2021 | C19: https://doi.org/10.1016/j.jcou.2021.101487 | D19: e-Fuels | E19: Fischer Tropsch | F19: 2050 | G19: C.3 | H19: 1692.7913 | I19: 1109.928 | J19: 2073.1563 | K19: 2059.5322 | L19: 0 | Q19: Academic | R19: Europe | S19: 48000000
A20: Marchese et.al. | B20: 2021 | C20: https://doi.org/10.1016/j.jcou.2021.101487 | D20: e-Fuels | E20: Fischer Tropsch | F20: 2050 | G20: C.4 | H20: 310.7968 | I20: 31.763718 | J20: 718.98445 | K20: 708.99406 | L20: 0 | Q20: Academic | R20: Europe | S20: 69000000
A21: Marchese et.al. | B21: 2021 | C21: https://doi.org/10.1016/j.jcou.2021.101487 | D21: e-Fuels | E21: Fischer Tropsch | F21: 2050 | G21: C.5 | H21: 628.73238 | I21: 270.87595 | J21: 976.45691 | K21: 966.08037 | L21: 0 | Q21: Academic | R21: Europe | S21: 68000000
A22: Martin et. al. | B22: 2023 | C22: https://www.sciencedirect.com/science/article/pii/S136403212300494X?via%3Dihub | D22: e-Fuels | E22: Fischer Tropsch | F22: 2024 | G22: Reference | H22: 1999.3691 | I22: 1980.3771 | J22: 3708.3374 | K22: 3713.8576 | L22: 464.84064 | Q22: Academic | R22: Europe | S22: -
A23: Martin et. al. | B23: 2023 | C23: https://www.sciencedirect.com/science/article/pii/S136403212300494X?via%3Dihub | D23: e-Fuels | E23: Fischer Tropsch | F23: 2050 | G23: Reference | H23: 209.51492 | I23: 196.72581 | J23: 697.27342 | K23: 698.85874 | L23: 464.84064 | Q23: Academic | R23: Europe | S23: -
A24: Meurer et al. | B24: 2024 | C24: https://doi.org/10.1039/D3SE01156A | D24: e-Fuels | E24: Fischer Tropsch | F24: 2024 | G24: Reference | H24: 1678.5512 | I24: 1330.6142 | J24: 2039.9518 | K24: 2004.6361 | Q24: Academic | R24: Europe | S24: 3650000
A25: Moretti et al. | B25: 2023 | C25: https://doi.org/10.1016/j.scitotenv.2023.166005 | D25: Solar Fuels | E25: Fischer Tropsch | F25: 2024 | G25: Reference | H25: 838.68815 | I25: 793.08716 | J25: 1257.2448 | K25: 1322.2253 | L25: 468.3096 | M25: -0.065490373 | N25: 0.65367021 | O25: 0.25634932 | P25: 0.15547084 | Q25: Industrial | R25: MENA | S25: 31354838 | T25: High CO2 cost assumed, hence there is less effect, High Production levels lead to lower costs due to scale and cheaper labour in MENA
A26: Moretti et al. | B26: 2023 | C26: https://doi.org/10.1016/j.scitotenv.2023.166005 | D26: Solar Fuels | E26: Fischer Tropsch | F26: 2050 | G26: Reference | H26: 982.3514 | I26: 982.36403 | J26: 1638.3134 | K26: 1737.805 | L26: 468.3096 | M26: -2.5861163e-05 | N26: 0.58509028 | O26: 0.29169175 | P26: 0.12324384 | Q26: Industrial | R26: MENA | S26: 31354838
A27: Moretti et al. | B27: 2023 | C27: https://doi.org/10.1016/j.scitotenv.2023.166005 | D27: Solar Fuels | E27: Fischer Tropsch | F27: 2050 | G27: Optimistic | H27: 858.71366 | I27: 858.72679 | J27: 1541.1765 | K27: 1617.6788 | L27: 468.3096 | Q27: Industrial | R27: MENA | S27: 31354838
A28: Peacock et. al. | B28: 2024 | D28: e-Fuels | E28: Fischer Tropsch | F28: 2024 | G28: SOEC, Nuclear + Renewables | H28: 2681.2488 | I28: 2495.6577 | J28: 4090.7711 | K28: 4065.43 | L28: 215.38773 | Q28: Academic | R28: United Kingdom | S28: 157410000
A29: Peacock et. al. | B29: 2024 | D29: e-Fuels | E29: Fischer Tropsch | F29: 2024 | G29: PEM, Nuclear | H29: 3266.1214 | I29: 2576.9841 | J29: 4046.1354 | K29: 4024.4681 | L29: 215.38773 | Q29: Academic | R29: United Kingdom | S29: 157410000 | T29: Large scale production but high electrolyser costs and multiple replacements considered (missing from most other studies)
A30: Peacock et. al. | B30: 2024 | D30: e-Fuels | E30: Fischer Tropsch | F30: 2050 | G30: PEM, Nuclear | H30: 1120.7136 | I30: 983.41616 | J30: 1816.5116 | K30: 1799.6387 | L30: 215.38773 | Q30: Academic | R30: United Kingdom | S30: 157410000
A31: Peacock et. al. | B31: 2024 | D31: e-Fuels | E31: Fischer Tropsch | F31: 2050 | G31: PEM, Nuclear + Renewables | H31: 952.97687 | I31: 964.92098 | J31: 1753.3803 | K31: 1736.5073 | L31: 215.38773 | M31: 0.30225305 | N31: 0.48543434 | O31: 0.069418574 | P31: 0.14289403 | Q31: Academic | R31: United Kingdom | S31: 157410000
A32: Peacock et. al. | B32: 2024 | D32: e-Fuels | E32: Fischer Tropsch | F32: 2050 | G32: SOEC, Nuclear + Renewables | H32: 1383.9118 | I32: 1400.7491 | J32: 2715.7174 | K32: 2689.1325 | L32: 215.38773 | Q32: Academic | R32: United Kingdom | S32: 157410000
A33: Peacock et. al. | B33: 2024 | D33: e-Fuels | E33: Fischer Tropsch | F33: 2024 | G33: PEM, Nuclear + Renewables | H33: 2797.4452 | I33: 2548.3625 | J33: 4158.0295 | K33: 4136.3622 | L33: 215.38773 | M33: 0.20866713 | N33: 0.65402571 | O33: 0.045223196 | P33: 0.092083963 | Q33: Academic | R33: United Kingdom | S33: 157410000
A34: Peters et. al. | B34: 2022 | C34: https://doi.org/10.3390/pr10040699 | D34: e-Fuels | E34: Fischer Tropsch | F34: 2024 | G34: Baseline | H34: 642.42374 | I34: 1011.8769 | J34: 3588.7386 | K34: 3626.2481 | M34: 0.066800203 | N34: 0.46591807 | O34: 0.43493529 | P34: 0.032346433 | Q34: Academic | R34: Europe | S34: 208032000 | T34: Low intial electricity and CO2 price assumption lead to lower costs
A35: Rojas-Michaga et. al. | B35: 2023 | C35: https://www.sciencedirect.com/science/article/pii/S0196890423007732?via%3Dihub#s0005 | D35: e-Fuels | E35: Fischer Tropsch | F35: 2024 | G35: Reference | H35: 2879.4702 | I35: 2389.2886 | J35: 5490.9741 | K35: 5101.9877 | M35: 0.28620653 | N35: 0.47089021 | O35: 0.025500914 | P35: 0.21740235 | Q35: Academic | R35: United Kingdom | S35: 25105853 | T35: Very detailed study, we should note that this study considers a wide variety of costs that will be practically applicable (e.g. labour, overhead, catalyst, by-product sales etc.)
A36: Saad et al. | B36: 2024 | C36: https://doi.org/10.1021/acs.est.4c01578 | D36: e-Fuels | E36: Methanol | F36: 2024 | G36: CO2ER | H36: 6201.6747 | I36: 3818.5621 | J36: 3865.4181 | K36: 3949.4052 | M36: 0.18840662 | N36: 0.68456138 | O36: 0.11897367 | P36: 0.008058336 | Q36: Academic | R36: Europe | S36: 1250000000 | T36: LCA accounting methodology means that the emissions abated are low, therefore cost is high
A37: Saad et al. | B37: 2024 | C37: https://doi.org/10.1021/acs.est.4c01578 | D37: e-Fuels | E37: Methanol | F37: 2024 | G37: CO2HY | H37: 5186.3474 | I37: 3438.5193 | J37: 5951.2257 | K37: 6013.8338 | M37: 0.1011943 | N37: 0.61193523 | O37: 0.2723405 | P37: 0.014529965 | Q37: Academic | R37: Europe | S37: 1250000000
A38: Schmidt et. al. | B38: 2024 | C38: https://onlinelibrary.wiley.com/doi/full/10.1002/cite.201700129?saml_referrer https://www.concawe.eu/wp-content/uploads/Rpt_24-4-1.pdf | D38: e-Fuels | E38: Fischer Tropsch | F38: 2050 | G38: EU-North | H38: 832.71053 | I38: 712.36778 | J38: 1058.3494 | K38: 982.68413 | L38: 110.72204 | M38: 0.34069422 | N38: 0.48719975 | O38: 0.14196149 | P38: 0.030144535 | Q38: Industrial | R38: Europe | S38: 1000000
A39: Schmidt et. al. | B39: 2024 | C39: https://onlinelibrary.wiley.com/doi/full/10.1002/cite.201700129?saml_referrer https://www.concawe.eu/wp-content/uploads/Rpt_24-4-1.pdf | D39: e-Fuels | E39: Fischer Tropsch | F39: 2050 | G39: EU-Central | H39: 1651.2877 | I39: 1201.2151 | J39: 1780.187 | K39: 1652.4151 | L39: 126.07289 | Q39: Industrial | R39: Europe | S39: 1000000
A40: Schmidt et. al. | B40: 2024 | C40: https://onlinelibrary.wiley.com/doi/full/10.1002/cite.201700129?saml_referrer https://www.concawe.eu/wp-content/uploads/Rpt_24-4-1.pdf | D40: e-Fuels | E40: Fischer Tropsch | F40: 2050 | G40: EU-South | H40: 832.16394 | I40: 711.82119 | J40: 1057.8028 | K40: 982.31981 | L40: 110.66758 | Q40: Industrial | R40: Europe | S40: 1000000
A41: Schmidt et. al. | B41: 2024 | C41: https://onlinelibrary.wiley.com/doi/full/10.1002/cite.201700129?saml_referrer https://www.concawe.eu/wp-content/uploads/Rpt_24-4-1.pdf | D41: e-Fuels | E41: Fischer Tropsch | F41: 2024 | G41: EU-Central | H41: 1309.1064 | I41: 1104.4865 | J41: 2295.4822 | K41: 2195.1083 | L41: 204.66864 | Q41: Industrial | R41: Europe | S41: 1000000
A42: Schmidt et. al. | B42: 2024 | C42: https://onlinelibrary.wiley.com/doi/full/10.1002/cite.201700129?saml_referrer https://www.concawe.eu/wp-content/uploads/Rpt_24-4-1.pdf | D42: e-Fuels | E42: Fischer Tropsch | F42: 2024 | G42: EU-North | H42: 1540.7127 | I42: 1280.3735 | J42: 2495.1892 | K42: 2366.2829 | L42: 204.66864 | M42: 0.21688817 | N42: 0.50584247 | O42: 0.2451164 | P42: 0.032152972 | Q42: Industrial | R42: Europe | S42: 1000000 | T42: 1st of a kind industrial plant
A43: Schmidt et. al. | B43: 2024 | C43: https://onlinelibrary.wiley.com/doi/full/10.1002/cite.201700129?saml_referrer https://www.concawe.eu/wp-content/uploads/Rpt_24-4-1.pdf | D43: e-Fuels | E43: Fischer Tropsch | F43: 2024 | G43: EU-South | H43: 1286.1593 | I43: 1276.9022 | J43: 2467.8979 | K43: 2338.1977 | L43: 204.66864 | Q43: Industrial | R43: Europe | S43: 1000000
A44: Seymour et al. | B44: 2024 | C44: https://doi.org/10.1039/D3SE00978E | D44: e-Fuels | E44: Fischer Tropsch | F44: 2050 | G44: Reference | H44: 722.87277 | I44: 896.60784 | J44: 1407.4091 | K44: 1420.9723 | L44: 305.14 | M44: 0.3897527 | N44: 0.44140834 | O44: 0.11054018 | P44: 0.058298779 | Q44: Academic | R44: United States of America | S44: 2110761
A45: Seymour et al. | B45: 2024 | C45: https://doi.org/10.1039/D3SE00978E | D45: e-Fuels | E45: Fischer Tropsch | F45: 2024 | G45: Reference | H45: 1703.2942 | I45: 1744.0993 | J45: 2280.4571 | K45: 2309.3768 | L45: 305.14 | M45: 0.28040034 | N45: 0.51792525 | O45: 0.1323485 | P45: 0.069325914 | Q45: Academic | R45: United States of America | S45: 2110761 | T45: High CO2 cost assumed, hence there is less effect
A46: Sherwin | B46: 2021 | C46: https://doi.org/10.1021/acs.est.0c07955 | D46: e-Fuels | E46: Fischer Tropsch | F46: 2024 | G46: Reference | H46: 1330.2315 | I46: 1583.3702 | J46: 2179.1656 | K46: 1905.357 | L46: 0 | Q46: Academic | R46: United States of America | S46: -
A47: Sherwin | B47: 2021 | C47: https://doi.org/10.1021/acs.est.0c07955 | D47: e-Fuels | E47: Fischer Tropsch | F47: 2050 | G47: Reference | H47: 84.263501 | I47: 400.61385 | J47: 886.33757 | K47: 946.35054 | L47: 0 | Q47: Academic | R47: United States of America | S47: -
A48: Staples et. al. | B48: 2021 | C48: https://doi.org/10.1021/acs.est.0c07674 | D48: e-Fuels | E48: Fischer Tropsch | F48: 2030 | G48: Reference | H48: 2544.8085 | I48: 1510.2027 | Q48: Academic | R48: United States of America | S48: -
K56: =MEDIAN(K5:K47) -> 2059.5322

Sheet Reference
A1: Reference | B1: Year of Assumptions in Study | C1: DOI | D1: Pathway | E1: Pathway Detail | F1: Year of Cost | G1: Study Scenario | H1: Baseline | I1: LCOE Harmonized | J1: CO2 Cost Harmonized | K1: Fully Harmonized | L1: Electricity | M1: CO2 | N1: CAPEX | O1: Other OPEX | P1: Study Type | Q1: Plant Location | R1: Production
A2: Moretti et al. | B2: 2023 | C2: https://doi.org/10.1016/j.scitotenv.2023.166005 | D2: Solar Fuels | E2: Fischer Tropsch | F2: 2024 | G2: Baseline | H2: 838.68815 | I2: 793.08716 | J2: 1421.7741 | K2: 1486.7546 | L2: -0.059549309 | M2: 0.68508807 | N2: 0.23309418 | O2: 0.14136706 | P2: Industrial | Q2: MENA | R2: 31354838 | S2: High CO2 cost assumed, hence there is less effect, High Production levels lead to lower costs due to scale and cheaper labour in MENA
A3: Seymour et al. | B3: 2024 | C3: https://doi.org/10.1039/D3SE00978E | D3: e-Fuels | E3: Fischer Tropsch | F3: 2050 | G3: Baseline | H3: 722.87277 | I3: 698.76814 | J3: 996.12746 | K3: 1015.6034 | L3: 0.36581603 | M3: 0.42106952 | N3: 0.13952769 | O3: 0.073586759 | P3: Academic | Q3: United States of America | R3: 2110761
A4: Meurer et al. | B4: 2024 | C4: https://doi.org/10.1039/D3SE01156A | D4: e-Fuels | E4: Fischer Tropsch | F4: 2024 | H4: 1678.5512 | I4: 1330.6142 | J4: 3382.6072 | K4: 3347.2914 | P4: Academic | Q4: Europe | R4: 3650000
A5: Marchese et.al. | B5: 2021 | C5: https://doi.org/10.1016/j.jcou.2021.101487 | D5: e-Fuels | E5: Fischer Tropsch | F5: 2024 | G5: C.4 | H5: 1458.3489 | I5: 751.42719 | J5: 1910.0714 | K5: 1895.1917 | P5: Academic | Q5: Europe | R5: 69000000
A6: Marchese et.al. | B6: 2021 | C6: https://doi.org/10.1016/j.jcou.2021.101487 | D6: e-Fuels | E6: Fischer Tropsch | F6: 2024 | G6: C.1 | H6: 1892.3064 | I6: 1097.7096 | J6: 1959.8018 | K6: 1943.9244 | L6: 0.19014911 | M6: 0.42429752 | N6: 0.21340218 | O6: 0.17215119 | P6: Academic | Q6: Europe | R6: 87000000
A7: Dietrich et. al. | B7: 2018 | C7: https://doi.org/10.1016/j.biombioe.2017.07.006 | D7: e-Fuels | E7: Fischer Tropsch | F7: 2024 | H7: 1144.7871 | I7: 717.33157 | J7: 2278.5389 | K7: 2313.9915 | L7: 0.11002479 | M7: 0.32309926 | N7: 0.51966602 | O7: 0.04720993 | P7: Academic | Q7: Europe
A8: Schmidt et. al. | B8: 2024 | C8: https://onlinelibrary.wiley.com/doi/full/10.1002/cite.201700129?saml_referrer https://www.concawe.eu/wp-content/uploads/Rpt_24-4-1.pdf | D8: e-Fuels | E8: Fischer Tropsch | F8: 2050 | G8: EU-North | H8: 1393.4729 | I8: 1037.1786 | J8: 1405.1233 | K8: 1278.5037 | L8: 0.31920876 | M8: 0.4639346 | N8: 0.17887399 | O8: 0.037982647 | P8: Industrial | Q8: Europe | R8: 1000000
A9: Schmidt et. al. | B9: 2024 | C9: https://onlinelibrary.wiley.com/doi/full/10.1002/cite.201700129?saml_referrer https://www.concawe.eu/wp-content/uploads/Rpt_24-4-1.pdf | D9: e-Fuels | E9: Fischer Tropsch | F9: 2050 | G9: EU-Central | H9: 1651.2877 | I9: 1046.3046 | J9: 1414.2493 | K9: 1286.4774 | P9: Industrial | Q9: Europe | R9: 1000000
A10: Schmidt et. al. | B10: 2024 | C10: https://onlinelibrary.wiley.com/doi/full/10.1002/cite.201700129?saml_referrer https://www.concawe.eu/wp-content/uploads/Rpt_24-4-1.pdf | D10: e-Fuels | E10: Fischer Tropsch | F10: 2050 | G10: EU-South | H10: 1392.5582 | I10: 1036.2639 | J10: 1404.2086 | K10: 1277.8941 | P10: Industrial | Q10: Europe | R10: 1000000
A11: Marchese et.al. | B11: 2021 | C11: https://doi.org/10.1016/j.jcou.2021.101487 | D11: e-Fuels | E11: Fischer Tropsch | F11: 2024 | G11: C.5 | H11: 1730.5108 | I11: 823.96436 | J11: 2024.3097 | K11: 2007.3752 | P11: Academic | Q11: Europe | R11: 68000000
A12: Sherwin | B12: 2021 | C12: https://doi.org/10.1021/acs.est.0c07955 | D12: e-Fuels | E12: Fischer Tropsch | F12: 2024 | G12: Baseline | H12: 1330.2315 | I12: 1583.3702 | J12: 2350.1001 | K12: 2076.2914 | P12: Academic | Q12: United States of America | R12: -
A13: Staples et. al. | B13: 2021 | C13: https://doi.org/10.1021/acs.est.0c07674 | D13: e-Fuels | E13: Fischer Tropsch | P13: Academic | Q13: United States of America | R13: -
A14: Bachorz et. al | B14: 2024 | C14: https://www.researchsquare.com/article/rs-4241841/v1 | D14: e-Fuels | E14: Methanol | F14: 2024 | H14: 2404.7475 | I14: 2435.2346 | J14: 2575.7824 | K14: 2555.1301 | L14: 0.054451686 | M14: 0.62743119 | N14: 0.30588185 | O14: 0.012235274 | P14: Academic | Q14: Europe | R14: - | S14: Due to a high WACC assumption (~11%, final wacc correction leads to lower cost)
A15: Moretti et al. | B15: 2023 | C15: https://doi.org/10.1016/j.scitotenv.2023.166005 | D15: Solar Fuels | E15: Fischer Tropsch | F15: 2050 | G15: Baseline | H15: 982.3514 | I15: 982.3755 | J15: 1321.1923 | K15: 1420.684 | L15: -3.0173341e-05 | M15: 0.51590683 | N15: 0.34032941 | O15: 0.14379393 | P15: Industrial | Q15: MENA | R15: 31354838
A16: Moretti et al. | B16: 2023 | C16: https://doi.org/10.1016/j.scitotenv.2023.166005 | D16: Solar Fuels | E16: Fischer Tropsch | F16: 2050 | G16: Optimistic | H16: 825.36876 | I16: 825.39286 | J16: 1164.2097 | K16: 1237.7413 | P16: Industrial | Q16: MENA | R16: 31354838
A17: Martin et. al. | B17: 2023 | C17: https://www.sciencedirect.com/science/article/pii/S136403212300494X?via%3Dihub | D17: e-Fuels | E17: Fischer Tropsch | F17: 2024 | G17: Baseline | H17: 1148.3867 | I17: 1137.4782 | J17: 2381.0325 | K17: 2384.2032 | P17: Academic | Q17: Europe | R17: -
A18: Schmidt et. al. | B18: 2024 | C18: https://onlinelibrary.wiley.com/doi/full/10.1002/cite.201700129?saml_referrer https://www.concawe.eu/wp-content/uploads/Rpt_24-4-1.pdf | D18: e-Fuels | E18: Fischer Tropsch | F18: 2024 | G18: EU-Central | H18: 1309.1064 | I18: 1104.4865 | J18: 2506.3765 | K18: 2406.0026 | P18: Industrial | Q18: Europe | R18: 1000000
A19: Albrecht et. al. | B19: 2016 | C19: https://doi.org/10.1016/j.energy.2019.116511 | D19: e-Fuels | E19: Fischer Tropsch | F19: 2024 | G19: Baseline | H19: 642.2967 | I19: 768.83261 | J19: 2386.5585 | K19: 2466.5878 | P19: Industrial | Q19: Europe | R19: 1.4477822e+08 | S19: This study has a detailed breakdown but considers a scenario where electricity is an output, leading to lower overall costs.
A20: Martin et. al. | B20: 2023 | C20: https://www.sciencedirect.com/science/article/pii/S136403212300494X?via%3Dihub | D20: e-Fuels | E20: Fischer Tropsch | F20: 2050 | G20: Baseline | H20: 350.60606 | I20: 217.99064 | J20: 804.40002 | K20: 807.05292 | P20: Academic | Q20: Europe | R20: -
A21: Schmidt et. al. | B21: 2024 | C21: https://onlinelibrary.wiley.com/doi/full/10.1002/cite.201700129?saml_referrer https://www.concawe.eu/wp-content/uploads/Rpt_24-4-1.pdf | D21: e-Fuels | E21: Fischer Tropsch | F21: 2024 | G21: EU-North | H21: 1510.5026 | I21: 1255.2682 | J21: 2657.1582 | K21: 2530.7794 | L21: 0.20134349 | M21: 0.54125942 | N21: 0.22754856 | O21: 0.029848524 | P21: Industrial | Q21: Europe | R21: 1000000 | S21: 1st of a kind industrial plant
A22: Schmidt et. al. | B22: 2024 | C22: https://onlinelibrary.wiley.com/doi/full/10.1002/cite.201700129?saml_referrer https://www.concawe.eu/wp-content/uploads/Rpt_24-4-1.pdf | D22: e-Fuels | E22: Fischer Tropsch | F22: 2024 | G22: EU-South | H22: 1286.1593 | I22: 1276.9022 | J22: 2678.7922 | K22: 2549.092 | P22: Industrial | Q22: Europe | R22: 1000000
A23: Seymour et al. | B23: 2024 | C23: https://doi.org/10.1039/D3SE00978E | D23: e-Fuels | E23: Fischer Tropsch | F23: 2024 | G23: Baseline | H23: 1703.2942 | I23: 1744.0993 | J23: 2493.7647 | K23: 2519.6177 | L23: 0.25985878 | M23: 0.55324106 | N23: 0.12265292 | O23: 0.064247239 | P23: Academic | Q23: United States of America | R23: 2110761 | S23: High CO2 cost assumed, hence there is less effect
A24: Gray et al. | B24: 2024 | C24: https://doi.org/10.1016/j.rser.2024.114552 | D24: e-Fuels | E24: Fischer Tropsch | F24: 2024 | G24: Reference DAC Deployment | H24: 2727.5773 | I24: 2805.9552 | J24: 2849.8757 | K24: 2927.778 | L24: 0.19629913 | M24: 0.65374158 | N24: 0.10228147 | O24: 0.047677823 | P24: Academic | Q24: Europe | R24: 39140034
A25: Sherwin | B25: 2021 | C25: https://doi.org/10.1021/acs.est.0c07955 | D25: e-Fuels | E25: Fischer Tropsch | F25: 2050 | G25: Baseline | H25: 87.667746 | I25: 295.79464 | J25: 645.13739 | K25: 707.57489 | P25: Academic | Q25: United States of America | R25: -
A26: Brazzola et al. | B26: 2024 | D26: e-Fuels | E26: Fischer Tropsch | P26: Academic | Q26: Worldwide | R26: -
A27: Marchese et.al. | B27: 2021 | C27: https://doi.org/10.1016/j.jcou.2021.101487 | D27: e-Fuels | E27: Fischer Tropsch | F27: 2024 | G27: C.3 | H27: 2708.6121 | I27: 1804.7169 | J27: 3396.6119 | K27: 3374.1564 | P27: Academic | Q27: Europe | R27: 48000000
A28: Rojas-Michaga et. al. | B28: 2023 | C28: https://www.sciencedirect.com/science/article/pii/S0196890423007732?via%3Dihub#s0005 | D28: e-Fuels | E28: Fischer Tropsch | F28: 2024 | H28: 1755.126 | I28: 1456.3452 | J28: 3092.0351 | K28: 3109.819 | L28: 0.28620653 | M28: 0.47089021 | N28: 0.025500914 | O28: 0.21740235 | P28: Academic | Q28: United Kingdom | R28: 25105853 | S28: Very detailed study, we should note that this study considers a wide variety of costs that will be practically applicable (e.g. labour, overhead, catalyst, by-product sales etc.)
A29: Marchese et.al. | B29: 2021 | C29: https://doi.org/10.1016/j.jcou.2021.101487 | D29: e-Fuels | E29: Fischer Tropsch | F29: 2024 | G29: C.2 | H29: 2761.7003 | I29: 1368.7085 | J29: 3557.2858 | K29: 3528.5632 | P29: Academic | Q29: Europe | R29: 35000000
A30: Gray et al. | B30: 2024 | C30: https://doi.org/10.1016/j.rser.2024.114552 | D30: e-Fuels | E30: Fischer Tropsch | F30: 2050 | G30: High DAC Deployment | H30: 1053.0157 | I30: 1131.3935 | J30: 1374.9394 | K30: 1452.8417 | L30: 0.38762689 | M30: 0.31625232 | N30: 0.2019726 | O30: 0.094148182 | P30: Academic | Q30: Europe | R30: 39140034 | S30: This scenario assumes a decline in CO2 cost but not CAPEX
A31: Peters et. al. | B31: 2022 | C31: https://doi.org/10.3390/pr10040699 | D31: e-Fuels | E31: Fischer Tropsch | F31: 2024 | G31: Baseline | H31: 668.37766 | I31: 1052.7567 | J31: 3733.7237 | K31: 3772.7486 | L31: 0.066800203 | M31: 0.46591807 | N31: 0.43493529 | O31: 0.032346433 | P31: Academic | Q31: Europe | R31: 208032000 | S31: Low intial electricity and CO2 price assumption lead to lower costs
A32: Saad et al. | B32: 2024 | C32: https://doi.org/10.1021/acs.est.4c01578 | D32: e-Fuels | E32: Methanol | F32: 2024 | G32: CO2ER | H32: 6201.6747 | I32: 3818.5621 | J32: 3865.4181 | K32: 3949.4052 | L32: 0.18840662 | M32: 0.68456138 | N32: 0.11897367 | O32: 0.008058336 | P32: Academic | Q32: Europe | R32: 1250000000 | S32: LCA accounting methodology means that the emissions abated are low, therefore cost is high
A33: Peacock et. al. | B33: 2024 | D33: e-Fuels | E33: Fischer Tropsch | F33: 2024 | G33: SOEC, Nuclear + Renewables | H33: 2681.2488 | I33: 2495.6577 | J33: 4573.4254 | K33: 4548.0843 | P33: Academic | Q33: United Kingdom | R33: 157410000
A34: Peacock et. al. | B34: 2024 | D34: e-Fuels | E34: Fischer Tropsch | F34: 2024 | G34: PEM, Nuclear | H34: 3266.1214 | I34: 2576.9841 | J34: 4528.7897 | K34: 4507.1224 | P34: Academic | Q34: United Kingdom | R34: 157410000 | S34: Large scale production but high electrolyser costs and multiple replacements considered (missing from most other studies)
A35: Peacock et. al. | B35: 2024 | D35: e-Fuels | E35: Fischer Tropsch | F35: 2050 | G35: PEM, Nuclear | H35: 1875.4225 | I35: 1436.7973 | J35: 2556.8251 | K35: 2528.5896 | P35: Academic | Q35: United Kingdom | R35: 157410000
A36: Peacock et. al. | B36: 2024 | D36: e-Fuels | E36: Fischer Tropsch | F36: 2050 | G36: PEM, Nuclear + Renewables | H36: 1594.7288 | I36: 1414.8415 | J36: 2451.18 | K36: 2422.9445 | L36: 0.34291278 | M36: 0.41621386 | N36: 0.07875691 | O36: 0.16211645 | P36: Academic | Q36: United Kingdom | R36: 157410000
A37: Peacock et. al. | B37: 2024 | D37: e-Fuels | E37: Fischer Tropsch | F37: 2050 | G37: SOEC, Nuclear + Renewables | H37: 1383.9118 | I37: 1232.3763 | J37: 2232.7591 | K37: 2206.1742 | P37: Academic | Q37: United Kingdom | R37: 157410000
A38: Peacock et. al. | B38: 2024 | D38: e-Fuels | E38: Fischer Tropsch | F38: 2024 | G38: PEM, Nuclear + Renewables | H38: 2797.4452 | I38: 2548.3625 | J38: 4640.6838 | K38: 4619.0164 | L38: 0.1897282 | M38: 0.68542684 | N38: 0.041118673 | O38: 0.083726288 | P38: Academic | Q38: United Kingdom | R38: 157410000
A39: Falter et. al. | B39: 2020 | C39: https://doi.org/10.1039/d0se00179a | D39: Solar Fuels | E39: Fischer Tropsch | F39: 2024 | H39: 1312.9985 | I39: 1349.9394 | J39: 5188.9197 | K39: 5172.001 | P39: Academic | Q39: MENA | R39: 45872966 | S39: Most assumptions based on previous study
A40: Falter et. al. | B40: 2015 | C40: https://doi.org/10.1021/acs.est.5b03515 | D40: Solar Fuels | E40: Fischer Tropsch | F40: 2024 | H40: 563.67631 | I40: 592.9283 | J40: 5581.904 | K40: 5983.7231 | P40: Academic | Q40: MENA | R40: 58035000
A41: Falter et. al. | B41: 2015 | C41: https://doi.org/10.1021/acs.est.5b03515 | D41: Solar Fuels | E41: Fischer Tropsch | F41: 2024 | H41: 798.16358 | I41: 827.41558 | J41: 5816.3913 | K41: 6234.134 | L41: 0.058359447 | M41: 0.66723593 | N41: 0.10459443 | O41: 0.1698102 | P41: Academic | Q41: MENA | R41: 58035000 | S41: Initial assumptions are very optimistic (by author's admission), Production is high. Overall process efficiency is 5% according to the author
A42: Saad et al. | B42: 2024 | C42: https://doi.org/10.1021/acs.est.4c01578 | D42: e-Fuels | E42: Methanol | F42: 2024 | G42: CO2HY | H42: 5186.3474 | I42: 3438.5193 | J42: 5951.2257 | K42: 6013.8338 | L42: 0.1011943 | M42: 0.61193523 | N42: 0.2723405 | O42: 0.014529965 | P42: Academic | Q42: Europe | R42: 1250000000
A43: Marchese et.al. | B43: 2021 | C43: https://doi.org/10.1016/j.jcou.2021.101487 | D43: e-Fuels | E43: Fischer Tropsch | F43: 2050 | G43: C.1 | H43: 597.79762 | I43: 154.73998 | J43: 529.30576 | K43: 519.29748 | L43: 0.21202579 | M43: 0.23970956 | N43: 0.15126255 | O43: 0.3970021 | P43: Academic | Q43: Europe | R43: 87000000
A44: Marchese et.al. | B44: 2021 | C44: https://doi.org/10.1016/j.jcou.2021.101487 | D44: e-Fuels | E44: Fischer Tropsch | F44: 2050 | G44: C.2 | H44: 1954.9193 | I44: 1192.8986 | J44: 2139.2446 | K44: 2121.2689 | P44: Academic | Q44: Europe | R44: 35000000
A45: Marchese et.al. | B45: 2021 | C45: https://doi.org/10.1016/j.jcou.2021.101487 | D45: e-Fuels | E45: Fischer Tropsch | F45: 2050 | G45: C.3 | H45: 1692.7913 | I45: 832.37401 | J45: 1521.0985 | K45: 1507.4744 | P45: Academic | Q45: Europe | R45: 48000000
A46: Marchese et.al. | B46: 2021 | C46: https://doi.org/10.1016/j.jcou.2021.101487 | D46: e-Fuels | E46: Fischer Tropsch | F46: 2050 | G46: C.4 | H46: 310.7968 | I46: -101.10918 | J46: 395.15232 | K46: 385.16193 | P46: Academic | Q46: Europe | R46: 69000000
A47: Marchese et.al. | B47: 2021 | C47: https://doi.org/10.1016/j.jcou.2021.101487 | D47: e-Fuels | E47: Fischer Tropsch | F47: 2050 | G47: C.5 | H47: 628.73238 | I47: 100.46812 | J47: 612.28162 | K47: 601.90508 | P47: Academic | Q47: Europe | R47: 68000000

Sheet High Elec High CO2
A1: Reference | B1: Year of Assumptions in Study | C1: DOI | D1: Pathway | E1: Pathway Detail | F1: Year of Cost | G1: Study Scenario | H1: Baseline | I1: LCOE Harmonized | J1: CO2 Cost Harmonized | K1: Fully Harmonized | L1: Electricity | M1: CO2 | N1: CAPEX | O1: Other OPEX | P1: Study Type | Q1: Plant Location | R1: Production
A2: Moretti et al. | B2: 2023 | C2: https://doi.org/10.1016/j.scitotenv.2023.166005 | D2: Solar Fuels | E2: Fischer Tropsch | F2: 2024 | G2: Reference | H2: 838.68815 | I2: 634.6837 | J2: 1467.1404 | K2: 1532.1208 | L2: -0.053534562 | M2: 0.71689558 | N2: 0.20955063 | O2: 0.12708835 | P2: Industrial | Q2: MENA | R2: 31354838 | S2: High CO2 cost assumed, hence there is less effect, High Production levels lead to lower costs due to scale and cheaper labour in MENA
A3: Seymour et al. | B3: 2024 | C3: https://doi.org/10.1039/D3SE00978E | D3: e-Fuels | E3: Fischer Tropsch | F3: 2050 | G3: Reference | H3: 722.87277 | I3: 1410.9911 | J3: 2238.6108 | K3: 2240.2242 | L3: 0.45749728 | M3: 0.42359136 | N3: 0.077852189 | O3: 0.041059164 | P3: Academic | Q3: United States of America | R3: 2110761
A4: Meurer et al. | B4: 2024 | C4: https://doi.org/10.1039/D3SE01156A | D4: e-Fuels | E4: Fischer Tropsch | F4: 2024 | G4: Reference | H4: 1678.5512 | I4: 1968.4988 | J4: 4360.7067 | K4: 4325.3909 | P4: Academic | Q4: Europe | R4: 3650000
A5: Marchese et.al. | B5: 2021 | C5: https://doi.org/10.1016/j.jcou.2021.101487 | D5: e-Fuels | E5: Fischer Tropsch | F5: 2024 | G5: C.4 | H5: 1458.3489 | I5: 1275.481 | J5: 2670.4795 | K5: 2655.5998 | P5: Academic | Q5: Europe | R5: 69000000
A6: Marchese et.al. | B6: 2021 | C6: https://doi.org/10.1016/j.jcou.2021.101487 | D6: e-Fuels | E6: Fischer Tropsch | F6: 2024 | G6: C.1 | H6: 1892.3064 | I6: 1625.9656 | J6: 2675.5111 | K6: 2659.6338 | L6: 0.30516555 | M6: 0.3902117 | N6: 0.16860742 | O6: 0.13601533 | P6: Academic | Q6: Europe | R6: 87000000
A7: Dietrich et. al. | B7: 2018 | C7: https://doi.org/10.1016/j.biombioe.2017.07.006 | D7: e-Fuels | E7: Fischer Tropsch | F7: 2024 | G7: Reference | H7: 1144.7871 | I7: 717.33157 | J7: 2278.5389 | K7: 2313.9915 | L7: 0.11002479 | M7: 0.32309926 | N7: 0.51966602 | O7: 0.04720993 | P7: Academic | Q7: Europe
A8: Schmidt et. al. | B8: 2024 | C8: https://onlinelibrary.wiley.com/doi/full/10.1002/cite.201700129?saml_referrer https://www.concawe.eu/wp-content/uploads/Rpt_24-4-1.pdf | D8: e-Fuels | E8: Fischer Tropsch | F8: 2050 | G8: EU-North | H8: 1393.4729 | I8: 1594.8566 | J8: 2487.0624 | K8: 2360.4429 | L8: 0.40449938 | M8: 0.47289782 | N8: 0.10112881 | O8: 0.021473999 | P8: Industrial | Q8: Europe | R8: 1000000
A9: Schmidt et. al. | B9: 2024 | C9: https://onlinelibrary.wiley.com/doi/full/10.1002/cite.201700129?saml_referrer https://www.concawe.eu/wp-content/uploads/Rpt_24-4-1.pdf | D9: e-Fuels | E9: Fischer Tropsch | F9: 2050 | G9: EU-Central | H9: 1651.2877 | I9: 1603.9826 | J9: 2496.1884 | K9: 2368.4165 | P9: Industrial | Q9: Europe | R9: 1000000
A10: Schmidt et. al. | B10: 2024 | C10: https://onlinelibrary.wiley.com/doi/full/10.1002/cite.201700129?saml_referrer https://www.concawe.eu/wp-content/uploads/Rpt_24-4-1.pdf | D10: e-Fuels | E10: Fischer Tropsch | F10: 2050 | G10: EU-South | H10: 1392.5582 | I10: 1593.9419 | J10: 2486.1478 | K10: 2359.8332 | P10: Industrial | Q10: Europe | R10: 1000000
A11: Marchese et.al. | B11: 2021 | C11: https://doi.org/10.1016/j.jcou.2021.101487 | D11: e-Fuels | E11: Fischer Tropsch | F11: 2024 | G11: C.5 | H11: 1730.5108 | I11: 1496.0568 | J11: 2936.2322 | K11: 2919.2978 | P11: Academic | Q11: Europe | R11: 68000000
A12: Sherwin | B12: 2021 | C12: https://doi.org/10.1021/acs.est.0c07955 | D12: e-Fuels | E12: Fischer Tropsch | F12: 2024 | G12: Reference | H12: 1330.2315 | I12: 2251.6563 | J12: 3230.0887 | K12: 2956.28 | P12: Academic | Q12: United States of America | R12: -
A13: Staples et. al. | B13: 2021 | C13: https://doi.org/10.1021/acs.est.0c07674 | D13: e-Fuels | E13: Fischer Tropsch | G13: Reference | P13: Academic | Q13: United States of America | R13: -
A14: Bachorz et. al | B14: 2024 | C14: https://www.researchsquare.com/article/rs-4241841/v1 | D14: e-Fuels | E14: Methanol | F14: 2024 | G14: Reference | H14: 2404.7475 | I14: 2538.1285 | J14: 2914.6539 | K14: 2894.0016 | L14: 0.095427092 | M14: 0.63010977 | N14: 0.26390686 | O14: 0.010556274 | P14: Academic | Q14: Europe | R14: - | S14: Due to a high WACC assumption (~11%, final wacc correction leads to lower cost)
A15: Moretti et al. | B15: 2023 | C15: https://doi.org/10.1016/j.scitotenv.2023.166005 | D15: Solar Fuels | E15: Fischer Tropsch | F15: 2050 | G15: Reference | H15: 982.3514 | I15: 982.33419 | J15: 2109.013 | K15: 2208.5047 | L15: -2.133529e-05 | M15: 0.6577022 | N15: 0.24064378 | O15: 0.10167536 | P15: Industrial | Q15: MENA | R15: 31354838
A16: Moretti et al. | B16: 2023 | C16: https://doi.org/10.1016/j.scitotenv.2023.166005 | D16: Solar Fuels | E16: Fischer Tropsch | F16: 2050 | G16: Optimistic | H16: 825.36876 | I16: 825.35154 | J16: 1952.0304 | K16: 2025.562 | P16: Industrial | Q16: MENA | R16: 31354838
A17: Martin et. al. | B17: 2023 | C17: https://www.sciencedirect.com/science/article/pii/S136403212300494X?via%3Dihub | D17: e-Fuels | E17: Fischer Tropsch | F17: 2024 | G17: Reference | H17: 1148.3867 | I17: 1624.2857 | J17: 3181.9873 | K17: 3185.1579 | P17: Academic | Q17: Europe | R17: -
A18: Schmidt et. al. | B18: 2024 | C18: https://onlinelibrary.wiley.com/doi/full/10.1002/cite.201700129?saml_referrer https://www.concawe.eu/wp-content/uploads/Rpt_24-4-1.pdf | D18: e-Fuels | E18: Fischer Tropsch | F18: 2024 | G18: EU-Central | H18: 1309.1064 | I18: 1715.4573 | J18: 3378.5401 | K18: 3278.1662 | P18: Industrial | Q18: Europe | R18: 1000000
A19: Albrecht et. al. | B19: 2016 | C19: https://doi.org/10.1016/j.energy.2019.116511 | D19: e-Fuels | E19: Fischer Tropsch | F19: 2024 | G19: Reference | H19: 642.2967 | I19: 1361.1283 | J19: 3247.2732 | K19: 3327.3026 | P19: Industrial | Q19: Europe | R19: 1.4477822e+08 | S19: This study has a detailed breakdown but considers a scenario where electricity is an output, leading to lower overall costs.
A20: Martin et. al. | B20: 2023 | C20: https://www.sciencedirect.com/science/article/pii/S136403212300494X?via%3Dihub | D20: e-Fuels | E20: Fischer Tropsch | F20: 2050 | G20: Reference | H20: 350.60606 | I20: 618.36066 | J20: 1828.8738 | K20: 1831.5267 | P20: Academic | Q20: Europe | R20: -
A21: Schmidt et. al. | B21: 2024 | C21: https://onlinelibrary.wiley.com/doi/full/10.1002/cite.201700129?saml_referrer https://www.concawe.eu/wp-content/uploads/Rpt_24-4-1.pdf | D21: e-Fuels | E21: Fischer Tropsch | F21: 2024 | G21: EU-North | H21: 1510.5026 | I21: 1866.239 | J21: 3529.3218 | K21: 3402.943 | L21: 0.31547268 | M21: 0.48597982 | N21: 0.17552335 | O21: 0.023024152 | P21: Industrial | Q21: Europe | R21: 1000000 | S21: 1st of a kind industrial plant
A22: Schmidt et. al. | B22: 2024 | C22: https://onlinelibrary.wiley.com/doi/full/10.1002/cite.201700129?saml_referrer https://www.concawe.eu/wp-content/uploads/Rpt_24-4-1.pdf | D22: e-Fuels | E22: Fischer Tropsch | F22: 2024 | G22: EU-South | H22: 1286.1593 | I22: 1887.873 | J22: 3550.9558 | K22: 3421.2556 | P22: Industrial | Q22: Europe | R22: 1000000
A23: Seymour et al. | B23: 2024 | C23: https://doi.org/10.1039/D3SE00978E | D23: e-Fuels | E23: Fischer Tropsch | F23: 2024 | G23: Reference | H23: 1703.2942 | I23: 2524.3837 | J23: 3538.2307 | K23: 3549.0681 | L23: 0.38848495 | M23: 0.47395793 | N23: 0.090271636 | O23: 0.047285489 | P23: Academic | Q23: United States of America | R23: 2110761 | S23: High CO2 cost assumed, hence there is less effect
A24: Gray et al. | B24: 2024 | C24: https://doi.org/10.1016/j.rser.2024.114552 | D24: e-Fuels | E24: Fischer Tropsch | F24: 2024 | G24: Reference DAC Deployment | H24: 2727.5773 | I24: 3070.4803 | J24: 3434.7709 | K24: 3512.6732 | L24: 0.23824944 | M24: 0.63634714 | N24: 0.085532855 | O24: 0.03987057 | P24: Academic | Q24: Europe | R24: 39140034
A25: Sherwin | B25: 2021 | C25: https://doi.org/10.1021/acs.est.0c07955 | D25: e-Fuels | E25: Fischer Tropsch | F25: 2050 | G25: Reference | H25: 87.667746 | I25: 731.40907 | J25: 1468.3178 | K25: 1530.7553 | P25: Academic | Q25: United States of America | R25: -
A26: Brazzola et al. | B26: 2024 | D26: e-Fuels | E26: Fischer Tropsch | G26: Reference | P26: Academic | Q26: Worldwide | R26: -
A27: Marchese et.al. | B27: 2021 | C27: https://doi.org/10.1016/j.jcou.2021.101487 | D27: e-Fuels | E27: Fischer Tropsch | F27: 2024 | G27: C.3 | H27: 2708.6121 | I27: 2835.1775 | J27: 4766.8318 | K27: 4744.3762 | P27: Academic | Q27: Europe | R27: 48000000
A28: Rojas-Michaga et. al. | B28: 2023 | C28: https://www.sciencedirect.com/science/article/pii/S0196890423007732?via%3Dihub#s0005 | D28: e-Fuels | E28: Fischer Tropsch | F28: 2024 | G28: Reference | H28: 1755.126 | I28: 2989.746 | J28: 4988.7094 | K28: 5044.4268 | L28: 0.42361375 | M28: 0.39939145 | N28: 0.018581591 | O28: 0.1584132 | P28: Academic | Q28: United Kingdom | R28: 25105853 | S28: Very detailed study, we should note that this study considers a wide variety of costs that will be practically applicable (e.g. labour, overhead, catalyst, by-product sales etc.)
A29: Marchese et.al. | B29: 2021 | C29: https://doi.org/10.1016/j.jcou.2021.101487 | D29: e-Fuels | E29: Fischer Tropsch | F29: 2024 | G29: C.2 | H29: 2761.7003 | I29: 2250.1298 | J29: 4904.6627 | K29: 4875.9402 | P29: Academic | Q29: Europe | R29: 35000000
A30: Gray et al. | B30: 2024 | C30: https://doi.org/10.1016/j.rser.2024.114552 | D30: e-Fuels | E30: Fischer Tropsch | F30: 2050 | G30: High DAC Deployment | H30: 1053.0157 | I30: 1395.9187 | J30: 2023.7324 | K30: 2101.6347 | L30: 0.39372297 | M30: 0.39903956 | N30: 0.14134871 | O30: 0.065888757 | P30: Academic | Q30: Europe | R30: 39140034 | S30: This scenario assumes a decline in CO2 cost but not CAPEX
A31: Peters et. al. | B31: 2022 | C31: https://doi.org/10.3390/pr10040699 | D31: e-Fuels | E31: Fischer Tropsch | F31: 2024 | G31: Reference | H31: 668.37766 | I31: 2109.7991 | J31: 5254.8655 | K31: 5293.8904 | L31: 0.19812531 | M31: 0.43229362 | N31: 0.34399772 | O31: 0.025583344 | P31: Academic | Q31: Europe | R31: 208032000 | S31: Low intial electricity and CO2 price assumption lead to lower costs
A32: Saad et al. | B32: 2024 | C32: https://doi.org/10.1021/acs.est.4c01578 | D32: e-Fuels | E32: Methanol | F32: 2024 | G32: CO2ER | H32: 6201.6747 | I32: 5012.2888 | J32: 5371.6468 | K32: 5455.6339 | L32: 0.31370249 | M32: 0.59193064 | N32: 0.08838067 | O32: 0.0059862083 | P32: Academic | Q32: Europe | R32: 1250000000 | S32: LCA accounting methodology means that the emissions abated are low, therefore cost is high
A33: Peacock et. al. | B33: 2024 | D33: e-Fuels | E33: Fischer Tropsch | F33: 2024 | G33: SOEC, Nuclear + Renewables | H33: 2681.2488 | I33: 3270.9116 | J33: 5946.447 | K33: 5921.1059 | P33: Academic | Q33: United Kingdom | R33: 157410000
A34: Peacock et. al. | B34: 2024 | D34: e-Fuels | E34: Fischer Tropsch | F34: 2024 | G34: PEM, Nuclear | H34: 3266.1214 | I34: 3419.2631 | J34: 6051.639 | K34: 6029.9717 | P34: Academic | Q34: United Kingdom | R34: 157410000 | S34: Large scale production but high electrolyser costs and multiple replacements considered (missing from most other studies)
A35: Peacock et. al. | B35: 2024 | D35: e-Fuels | E35: Fischer Tropsch | F35: 2050 | G35: PEM, Nuclear | H35: 1875.4225 | I35: 2188.7262 | J35: 5135.1895 | K35: 5106.954 | P35: Academic | Q35: United Kingdom | R35: 157410000
A36: Peacock et. al. | B36: 2024 | D36: e-Fuels | E36: Fischer Tropsch | F36: 2050 | G36: PEM, Nuclear + Renewables | H36: 1594.7288 | I36: 2134.3907 | J36: 4920.5979 | K36: 4892.3624 | L36: 0.41268558 | M36: 0.44460224 | N36: 0.046661739 | O36: 0.096050434 | P36: Academic | Q36: United Kingdom | R36: 157410000
A37: Peacock et. al. | B37: 2024 | D37: e-Fuels | E37: Fischer Tropsch | F37: 2050 | G37: SOEC, Nuclear + Renewables | H37: 1383.9118 | I37: 1838.5183 | J37: 4494.2638 | K37: 4467.6788 | P37: Academic | Q37: United Kingdom | R37: 157410000
A38: Peacock et. al. | B38: 2024 | D38: e-Fuels | E38: Fischer Tropsch | F38: 2024 | G38: PEM, Nuclear + Renewables | H38: 2797.4452 | I38: 3588.8348 | J38: 6278.9238 | K38: 6257.2565 | L38: 0.29462244 | M38: 0.60993511 | N38: 0.031434724 | O38: 0.064007725 | P38: Academic | Q38: United Kingdom | R38: 157410000
A39: Falter et. al. | B39: 2020 | C39: https://doi.org/10.1039/d0se00179a | D39: Solar Fuels | E39: Fischer Tropsch | F39: 2024 | G39: Reference | H39: 1312.9985 | I39: 1474.6152 | J39: 5994.3675 | K39: 6012.4473 | P39: Academic | Q39: MENA | R39: 45872966 | S39: Most assumptions based on previous study
A40: Falter et. al. | B40: 2015 | C40: https://doi.org/10.1021/acs.est.5b03515 | D40: Solar Fuels | E40: Fischer Tropsch | F40: 2024 | G40: Reference | H40: 563.67631 | I40: 1075.5862 | J40: 6942.1291 | K40: 7436.319 | P40: Academic | Q40: MENA | R40: 58035000
A41: Falter et. al. | B41: 2015 | C41: https://doi.org/10.1021/acs.est.5b03515 | D41: Solar Fuels | E41: Fischer Tropsch | F41: 2024 | G41: Reference | H41: 798.16358 | I41: 1310.0735 | J41: 7176.6164 | K41: 7686.7299 | L41: 0.10135244 | M41: 0.6640351 | N41: 0.089426902 | O41: 0.14518556 | P41: Academic | Q41: MENA | R41: 58035000 | S41: Initial assumptions are very optimistic (by author's admission), Production is high. Overall process efficiency is 5% according to the author
A42: Saad et al. | B42: 2024 | C42: https://doi.org/10.1021/acs.est.4c01578 | D42: e-Fuels | E42: Methanol | F42: 2024 | G42: CO2HY | H42: 5186.3474 | I42: 4314.0252 | J42: 7208.1931 | K42: 7270.8012 | L42: 0.18500752 | M42: 0.58099899 | N42: 0.22214175 | O42: 0.011851751 | P42: Academic | Q42: Europe | R42: 1250000000
A43: Marchese et.al. | B43: 2021 | C43: https://doi.org/10.1016/j.jcou.2021.101487 | D43: e-Fuels | E43: Fischer Tropsch | F43: 2050 | G43: C.1 | H43: 597.79762 | I43: 669.25853 | J43: 1420.0772 | K43: 1410.0689 | L43: 0.32646649 | M43: 0.29689493 | N43: 0.10391206 | O43: 0.27272652 | P43: Academic | Q43: Europe | R43: 87000000
A44: Marchese et.al. | B44: 2021 | C44: https://doi.org/10.1016/j.jcou.2021.101487 | D44: e-Fuels | E44: Fischer Tropsch | F44: 2050 | G44: C.2 | H44: 1954.9193 | I44: 2077.8259 | J44: 3959.4291 | K44: 3941.4534 | P44: Academic | Q44: Europe | R44: 35000000
A45: Marchese et.al. | B45: 2021 | C45: https://doi.org/10.1016/j.jcou.2021.101487 | D45: e-Fuels | E45: Fischer Tropsch | F45: 2050 | G45: C.3 | H45: 1692.7913 | I45: 1831.5683 | J45: 3202.2511 | K45: 3188.6271 | P45: Academic | Q45: Europe | R45: 48000000
A46: Marchese et.al. | B46: 2021 | C46: https://doi.org/10.1016/j.jcou.2021.101487 | D46: e-Fuels | E46: Fischer Tropsch | F46: 2050 | G46: C.4 | H46: 310.7968 | I46: 377.23324 | J46: 1347.9006 | K46: 1337.9102 | P46: Academic | Q46: Europe | R46: 69000000
A47: Marchese et.al. | B47: 2021 | C47: https://doi.org/10.1016/j.jcou.2021.101487 | D47: e-Fuels | E47: Fischer Tropsch | F47: 2050 | G47: C.5 | H47: 628.73238 | I47: 713.9363 | J47: 1707.1322 | K47: 1696.7557 | P47: Academic | Q47: Europe | R47: 68000000

Sheet Low Elec Low CO2
A1: Reference | B1: Year of Assumptions in Study | C1: DOI | D1: Pathway | E1: Pathway Detail | F1: Year of Cost | G1: Study Scenario | H1: Baseline | I1: LCOE Harmonized | J1: CO2 Cost Harmonized | K1: Fully Harmonized | L1: Electricity | M1: CO2 | N1: CAPEX | O1: Other OPEX | P1: Study Type | Q1: Plant Location | R1: Production
A2: Moretti et al. | B2: 2023 | C2: https://doi.org/10.1016/j.scitotenv.2023.166005 | D2: Solar Fuels | E2: Fischer Tropsch | F2: 2024 | G2: Reference | H2: 838.68815 | I2: 841.0882 | J2: 1307.4882 | K2: 1372.4686 | L2: -0.065401447 | M2: 0.65414047 | N2: 0.25600124 | O2: 0.15525974 | P2: Industrial | Q2: MENA | R2: 31354838 | S2: High CO2 cost assumed, hence there is less effect, High Production levels lead to lower costs due to scale and cheaper labour in MENA
A3: Seymour et al. | B3: 2024 | C3: https://doi.org/10.1039/D3SE00978E | D3: e-Fuels | E3: Fischer Tropsch | F3: 2050 | G3: Reference | H3: 722.87277 | I3: 481.14448 | J3: 566.27803 | K3: 591.93362 | L3: 0.31278421 | M3: 0.39363984 | N3: 0.19220646 | O3: 0.10136949 | P3: Academic | Q3: United States of America | R3: 2110761
A4: Meurer et al. | B4: 2024 | C4: https://doi.org/10.1039/D3SE01156A | D4: e-Fuels | E4: Fischer Tropsch | F4: 2024 | G4: Reference | H4: 1678.5512 | I4: 1137.3158 | J4: 2918.3536 | K4: 2883.0379 | P4: Academic | Q4: Europe | R4: 3650000
A5: Marchese et.al. | B5: 2021 | C5: https://doi.org/10.1016/j.jcou.2021.101487 | D5: e-Fuels | E5: Fischer Tropsch | F5: 2024 | G5: C.4 | H5: 1458.3489 | I5: 592.62301 | J5: 1563.0291 | K5: 1548.1494 | P5: Academic | Q5: Europe | R5: 69000000
A6: Marchese et.al. | B6: 2021 | C6: https://doi.org/10.1016/j.jcou.2021.101487 | D6: e-Fuels | E6: Fischer Tropsch | F6: 2024 | G6: C.1 | H6: 1892.3064 | I6: 937.63205 | J6: 1650.4319 | K6: 1634.5546 | L6: 0.14768794 | M6: 0.41673744 | N6: 0.24108873 | O6: 0.19448588 | P6: Academic | Q6: Europe | R6: 87000000
A7: Dietrich et. al. | B7: 2018 | C7: https://doi.org/10.1016/j.biombioe.2017.07.006 | D7: e-Fuels | E7: Fischer Tropsch | F7: 2024 | G7: Reference | H7: 1144.7871 | I7: 717.33157 | J7: 2278.5389 | K7: 2313.9915 | L7: 0.11002479 | M7: 0.32309926 | N7: 0.51966602 | O7: 0.04720993 | P7: Academic | Q7: Europe
A8: Schmidt et. al. | B8: 2024 | C8: https://onlinelibrary.wiley.com/doi/full/10.1002/cite.201700129?saml_referrer https://www.concawe.eu/wp-content/uploads/Rpt_24-4-1.pdf | D8: e-Fuels | E8: Fischer Tropsch | F8: 2050 | G8: EU-North | H8: 1393.4729 | I8: 866.77697 | J8: 1024.897 | K8: 898.27744 | L8: 0.27147379 | M8: 0.43139292 | N8: 0.24509011 | O8: 0.05204318 | P8: Industrial | Q8: Europe | R8: 1000000
