Workbook

Sheet Intro
A1: This is a sheet for standardisation of inputs for the Meta Analysis of Net Removed Cost from Direct Air Capture Transport and Storage

Sheet Steps

Sheet Inputs
A1: Scenario Selected | B1: Reference Oil Price | C1: Electricity and CO2 Price | D1: Reference
A2: Parameter | B2: Year | C2: Value | D2: Unit
A3: Standard Values
A4: Current Year | C4: 2024
A5: Inflation | C5: =Inflation!C22 / 100 -> 0.024532829
A6: WACC | C6: 0.07
A7: USD to EUR | C7: =1/AVERAGE(USD_EUR!B11:B211) -> 0.8187011
A8: Electricity
A9: LCOE | B9: 2024 | C9: {=_xlfn.IFS($D$1 = "Low Electricity and CO2", 'Energy_Carbon intensity'!F30, $D$1 = "Reference",'Standard Input Calculations'!E13, $D$1="High Electricity and CO2",'Energy_Carbon intensity'!F34)} -> 64 | D9: $/MWh | E9: (these are not Sievert et al. Values - where do they come from?)
A10: LCOE | B10: 2050 | C10: 11 | D10: $/MWh | E10: Vary this for electricity price scenarios
A11: LCOH waste heat/combined heat and power | B11: 2024 | C11: 14.47 | D11: $/GJ | E11: See Standardization "Carbon intensity" tab
A12: LCOH waste heat/combined heat and power | B12: 2050 | C12: 10 | D12: $/GJ | E12: See Standardization "Carbon intensity" tab
A13: LCOH waste heat/combined heat and power | B13: 2024 | C13: =C11*$C$29 -> 52.092 | D13: $/MWh
A14: LCOH waste heat/combined heat and power | B14: 2050 | C14: =C12*$C$29 -> 36 | D14: $/MWh
A15: LCOH natural gas | B15: 2024 | C15: 5.49 | D15: $/GJ | E15: See Standardization "Carbon intensity" tab
A16: LCOH natural gas | B16: 2050 | C16: 5.8 | D16: $/GJ | E16: See Standardization "Carbon intensity" tab
A17: LCOH natural gas | B17: 2024 | C17: =C15*C29 -> 19.764 | D17: $/MWh
A18: LCOH natural gas | B18: 2050 | C18: =C16*C29 -> 20.88 | D18: $/MWh
A19: Carbon intensity NG | C19: 0.0176 | D19: tCO2/GJ | E19: See Standardization "Carbon intensity" tab
A20: Carbon intensity electricity (solar PV w/ tracking | C20: 0.0153 | D20: tCO2/GJ | E20: See Standardization "Carbon intensity" tab
A21: Carbon intensity waste heat | C21: =8.43333333333333/1000 -> 0.0084333333 | D21: tCO2/GJ | E21: See Standardization "Carbon intensity" tab
A22: CO2 Transport
A23: CO2 Transport Cost | B23: 2024 | C23: 25 | D23: $/tCO2 | E23: Dummy value for now
A24: CO2 Transport Cost | B24: 2050 | C24: 15 | D24: $/tCO2 | E24: Dummy value for now
A25: CO2 Storage
A26: CO2 Storage Cost | B26: 2024 | C26: 15 | D26: $/tCO2 | E26: Dummy value for now
A27: CO2 Storage Cost | B27: 2050 | C27: 10 | D27: $/tCO2 | E27: Dummy value for now
A29: 1 MWh = 3.6 GJ | C29: 3.6 | E29: conversion factor

Sheet Energy_Carbon intensity
A1: Technology | B1: Scenario | C1: Period raw | D1: 2022 | E1: 2023 | F1: 2024 | G1: 2025 | H1: 2026 | I1: 2027 | J1: 2028 | K1: 2029 | L1: 2030 | M1: 2031 | N1: 2032 | O1: 2033 | P1: 2034 | Q1: 2035 | R1: 2036 | S1: 2037 | T1: 2038 | U1: 2039 | V1: 2040 | W1: 2041 | X1: 2042 | Y1: 2043 | Z1: 2044 | AA1: 2045 | AB1: 2046 | AC1: 2047 | AD1: 2048 | AE1: 2049 | AF1: 2050 | AG1: Source | AH1: Note | AI1: Link | AJ1: carbon_intensity | AK1: unit | AL1: Source
A2: PV tracking with storage | B2: LCOE $/MWh (avg) | C2: 2022 2H | D2: 111 | E2: 97 | F2: 84 | G2: 75 | H2: 68 | I2: 62 | J2: 58 | K2: 55 | L2: 53 | M2: 50 | N2: 48 | O2: 47 | P2: 45 | Q2: 44 | R2: 43 | S2: 43 | T2: 42 | U2: 41 | V2: 41 | W2: 41 | X2: 40 | Y2: 41 | Z2: 40 | AA2: 40 | AB2: 40 | AC2: 39 | AD2: 40 | AE2: 39 | AF2: 39 | AG2: BNEF LCOE - All Technologies - Unites States - LCOE Forecast 2022 | AH2: To be converted in $/GJ with conversion factor in Universal Inputs "conversion_electricity" OR just | AI2: https://www.bnef.com/flagships/lcoe | AJ2: =15.3/1000 -> 0.0153 | AK2: [t-CO2,eq GJ-1] | AL2: Young et al. (2023)
A3: CCGT | B3: LCOE $/GJ (low) | C3: 2022 2H | D3: 47 | E3: 48 | F3: 48 | G3: 48 | H3: 49 | I3: 49 | J3: 50 | K3: 51 | L3: 51 | M3: 52 | N3: 52 | O3: 53 | P3: 53 | Q3: 54 | R3: 54 | S3: 54 | T3: 55 | U3: 55 | V3: 56 | W3: 56 | X3: 56 | Y3: 56 | Z3: 57 | AA3: 57 | AB3: 57 | AC3: 57 | AD3: 57 | AE3: 57 | AF3: 57 | AG3: BNEF LCOE - All Technologies - Unites States - LCOE Forecast 2022 | AH3: To be converted in $/GJ with conversion factor in Universal Inputs "conversion_electricity" OR just | AI3: https://www.bnef.com/flagships/lcoe
A4: CCGT CCS | B4: LCOE $/MWh (low) | C4: 2022 2H | D4: 151 | E4: 141 | F4: 132 | G4: 121 | H4: 112 | I4: 102 | J4: 92 | K4: 82 | L4: 72 | M4: 73 | N4: 74 | O4: 74 | P4: 75 | Q4: 75 | R4: 76 | S4: 76 | T4: 77 | U4: 77 | V4: 77 | W4: 78 | X4: 78 | Y4: 79 | Z4: 79 | AA4: 79 | AB4: 79 | AC4: 79 | AD4: 79 | AE4: 79 | AF4: 79 | AG4: BNEF LCOE - All Technologies - Unites States - LCOE Forecast 2022 | AH4: To be converted in $/GJ with conversion factor in Universal Inputs "conversion_electricity" OR just | AI4: https://www.bnef.com/flagships/lcoe
A5: CCGT Hydrogen | B5: LCOE $/MWh (low) | C5: 2022 2H | D5: 152 | E5: 141 | F5: 130 | G5: 120 | H5: 112 | I5: 104 | J5: 98 | K5: 93 | L5: 89 | M5: 86 | N5: 83 | O5: 81 | P5: 78 | Q5: 76 | R5: 74 | S5: 72 | T5: 71 | U5: 70 | V5: 69 | W5: 68 | X5: 68 | Y5: 67 | Z5: 67 | AA5: 66 | AB5: 66 | AC5: 65 | AD5: 65 | AE5: 65 | AF5: 65 | AG5: BNEF LCOE - All Technologies - Unites States - LCOE Forecast 2022 | AH5: To be converted in $/GJ with conversion factor in Universal Inputs "conversion_electricity" OR just | AI5: https://www.bnef.com/flagships/lcoe
A6: Coal | B6: LCOE $/MWh (low) | C6: 2022 2H | D6: 68 | E6: 68 | F6: 68 | G6: 68 | H6: 68 | I6: 69 | J6: 70 | K6: 70 | L6: 71 | M6: 71 | N6: 72 | O6: 72 | P6: 73 | Q6: 73 | R6: 74 | S6: 74 | T6: 74 | U6: 75 | V6: 75 | W6: 76 | X6: 76 | Y6: 76 | Z6: 76 | AA6: 76 | AB6: 76 | AC6: 76 | AD6: 76 | AE6: 76 | AF6: 76 | AG6: BNEF LCOE - All Technologies - Unites States - LCOE Forecast 2022 | AH6: To be converted in $/GJ with conversion factor in Universal Inputs "conversion_electricity" OR just | AI6: https://www.bnef.com/flagships/lcoe
A7: Coal CCS | B7: LCOE $/MWh (low) | C7: 2022 2H | D7: 259 | E7: 246 | F7: 231 | G7: 212 | H7: 194 | I7: 175 | J7: 154 | K7: 133 | L7: 112 | M7: 113 | N7: 114 | O7: 115 | P7: 115 | Q7: 116 | R7: 117 | S7: 117 | T7: 118 | U7: 119 | V7: 119 | W7: 120 | X7: 120 | Y7: 120 | Z7: 120 | AA7: 120 | AB7: 120 | AC7: 120 | AD7: 120 | AE7: 120 | AF7: 120 | AG7: BNEF LCOE - All Technologies - Unites States - LCOE Forecast 2022 | AH7: To be converted in $/GJ with conversion factor in Universal Inputs "conversion_electricity" OR just | AI7: https://www.bnef.com/flagships/lcoe
A8: OCGT | B8: LCOE $/MWh (low) | C8: 2022 2H | D8: 96 | E8: 98 | F8: 99 | G8: 101 | H8: 102 | I8: 103 | J8: 104 | K8: 105 | L8: 106 | M8: 107 | N8: 108 | O8: 109 | P8: 109 | Q8: 110 | R8: 111 | S8: 112 | T8: 112 | U8: 113 | V8: 114 | W8: 114 | X8: 114 | Y8: 115 | Z8: 115 | AA8: 115 | AB8: 116 | AC8: 116 | AD8: 116 | AE8: 116 | AF8: 116 | AG8: BNEF LCOE - All Technologies - Unites States - LCOE Forecast 2022 | AH8: To be converted in $/GJ with conversion factor in Universal Inputs "conversion_electricity" OR just | AI8: https://www.bnef.com/flagships/lcoe
A9: OCGT CCS | B9: LCOE $/MWh (low) | C9: 2022 2H | D9: 455 | E9: 432 | F9: 401 | G9: 366 | H9: 330 | I9: 293 | J9: 255 | K9: 216 | L9: 176 | M9: 178 | N9: 179 | O9: 180 | P9: 181 | Q9: 182 | R9: 183 | S9: 184 | T9: 185 | U9: 186 | V9: 187 | W9: 188 | X9: 188 | Y9: 189 | Z9: 189 | AA9: 189 | AB9: 189 | AC9: 190 | AD9: 190 | AE9: 190 | AF9: 190 | AG9: BNEF LCOE - All Technologies - Unites States - LCOE Forecast 2022 | AH9: To be converted in $/GJ with conversion factor in Universal Inputs "conversion_electricity" OR just | AI9: https://www.bnef.com/flagships/lcoe
A10: OCGT Hydrogen | B10: LCOE $/MWh (low) | C10: 2022 2H | D10: 235 | E10: 224 | F10: 213 | G10: 202 | H10: 192 | I10: 184 | J10: 176 | K10: 170 | L10: 166 | M10: 161 | N10: 158 | O10: 154 | P10: 150 | Q10: 146 | R10: 142 | S10: 139 | T10: 137 | U10: 136 | V10: 134 | W10: 134 | X10: 133 | Y10: 132 | Z10: 131 | AA10: 131 | AB10: 130 | AC10: 130 | AD10: 130 | AE10: 129 | AF10: 129 | AG10: BNEF LCOE - All Technologies - Unites States - LCOE Forecast 2022 | AH10: To be converted in $/GJ with conversion factor in Universal Inputs "conversion_electricity" OR just | AI10: https://www.bnef.com/flagships/lcoe
A11: PV non-tracking | B11: LCOE $/MWh (low) | C11: 2022 2H | D11: 39 | E11: 35 | F11: 33 | G11: 29 | H11: 28 | I11: 27 | J11: 27 | K11: 25 | L11: 23 | M11: 21 | N11: 19 | O11: 19 | P11: 18 | Q11: 18 | R11: 17 | S11: 17 | T11: 16 | U11: 16 | V11: 16 | W11: 15 | X11: 15 | Y11: 15 | Z11: 14 | AA11: 14 | AB11: 14 | AC11: 14 | AD11: 13 | AE11: 13 | AF11: 13 | AG11: BNEF LCOE - All Technologies - Unites States - LCOE Forecast 2022 | AH11: To be converted in $/GJ with conversion factor in Universal Inputs "conversion_electricity" OR just | AI11: https://www.bnef.com/flagships/lcoe
A12: PV non-tracking with storage | B12: LCOE $/MWh (low) | C12: 2022 2H | D12: 58 | E12: 51 | F12: 47 | G12: 42 | H12: 40 | I12: 37 | J12: 36 | K12: 33 | L12: 31 | M12: 29 | N12: 27 | O12: 26 | P12: 26 | Q12: 25 | R12: 25 | S12: 24 | T12: 24 | U12: 23 | V12: 23 | W12: 22 | X12: 22 | Y12: 22 | Z12: 22 | AA12: 21 | AB12: 21 | AC12: 21 | AD12: 21 | AE12: 20 | AF12: 20 | AG12: BNEF LCOE - All Technologies - Unites States - LCOE Forecast 2022 | AH12: To be converted in $/GJ with conversion factor in Universal Inputs "conversion_electricity" OR just | AI12: https://www.bnef.com/flagships/lcoe
A13: PV tracking | B13: LCOE $/MWh (low) | C13: 2022 2H | D13: 34 | E13: 31 | F13: 28 | G13: 25 | H13: 25 | I13: 24 | J13: 23 | K13: 21 | L13: 20 | M13: 18 | N13: 17 | O13: 16 | P13: 16 | Q13: 15 | R13: 15 | S13: 15 | T13: 14 | U13: 14 | V13: 13 | W13: 13 | X13: 13 | Y13: 13 | Z13: 12 | AA13: 12 | AB13: 12 | AC13: 12 | AD13: 12 | AE13: 11 | AF13: 11 | AG13: BNEF LCOE - All Technologies - Unites States - LCOE Forecast 2022 | AH13: To be converted in $/GJ with conversion factor in Universal Inputs "conversion_electricity" OR just | AI13: https://www.bnef.com/flagships/lcoe
A14: PV tracking with storage | B14: LCOE $/MWh (low) | C14: 2022 2H | D14: 38.62069 | E14: 44 | F14: 40 | G14: 35 | H14: 34 | I14: 32 | J14: 30 | K14: 28 | L14: 26 | M14: 25 | N14: 23 | O14: 22 | P14: 22 | Q14: 21 | R14: 21 | S14: 20 | T14: 20 | U14: 20 | V14: 19 | W14: 19 | X14: 19 | Y14: 18 | Z14: 18 | AA14: 18 | AB14: 18 | AC14: 18 | AD14: 17 | AE14: 17 | AF14: 17 | AG14: BNEF LCOE - All Technologies - Unites States - LCOE Forecast 2022 | AH14: To be converted in $/GJ with conversion factor in Universal Inputs "conversion_electricity" OR just | AI14: https://www.bnef.com/flagships/lcoe | AJ14: =15.3/1000 -> 0.0153 | AK14: [t-CO2,eq GJ-1] | AL14: Young et al. (2023)
A15: Utility-scale battery (1h) | B15: LCOE $/MWh (low) | C15: 2022 2H | D15: 160 | E15: 136 | F15: 119 | G15: 106 | H15: 96 | I15: 88 | J15: 81 | K15: 78 | L15: 75 | M15: 71 | N15: 67 | O15: 65 | P15: 63 | Q15: 59 | R15: 58 | S15: 57 | T15: 56 | U15: 55 | V15: 54 | W15: 54 | X15: 54 | Y15: 54 | Z15: 54 | AA15: 54 | AB15: 54 | AC15: 54 | AD15: 54 | AE15: 54 | AF15: 54 | AG15: BNEF LCOE - All Technologies - Unites States - LCOE Forecast 2022 | AH15: To be converted in $/GJ with conversion factor in Universal Inputs "conversion_electricity" OR just | AI15: https://www.bnef.com/flagships/lcoe
A16: Utility-scale battery (4h) | B16: LCOE $/MWh (low) | C16: 2022 2H | D16: 123 | E16: 99 | F16: 83 | G16: 72 | H16: 63 | I16: 56 | J16: 50 | K16: 47 | L16: 45 | M16: 43 | N16: 41 | O16: 39 | P16: 38 | Q16: 36 | R16: 36 | S16: 35 | T16: 35 | U16: 34 | V16: 34 | W16: 34 | X16: 34 | Y16: 34 | Z16: 34 | AA16: 34 | AB16: 34 | AC16: 34 | AD16: 34 | AE16: 34 | AF16: 34 | AG16: BNEF LCOE - All Technologies - Unites States - LCOE Forecast 2022 | AH16: To be converted in $/GJ with conversion factor in Universal Inputs "conversion_electricity" OR just | AI16: https://www.bnef.com/flagships/lcoe
A17: Wind offshore | B17: LCOE $/MWh (low) | C17: 2022 2H | D17: 116 | E17: 107 | F17: 102 | G17: 97 | H17: 94 | I17: 91 | J17: 88 | K17: 86 | L17: 54 | M17: 53 | N17: 52 | O17: 51 | P17: 50 | Q17: 49 | R17: 48 | S17: 47 | T17: 46 | U17: 45 | V17: 44 | W17: 44 | X17: 43 | Y17: 43 | Z17: 42 | AA17: 42 | AB17: 41 | AC17: 40 | AD17: 40 | AE17: 40 | AF17: 40 | AG17: BNEF LCOE - All Technologies - Unites States - LCOE Forecast 2022 | AH17: To be converted in $/GJ with conversion factor in Universal Inputs "conversion_electricity" OR just | AI17: https://www.bnef.com/flagships/lcoe
A18: Wind onshore | B18: LCOE $/MWh (low) | C18: 2022 2H | D18: 33 | E18: 31 | F18: 29 | G18: 28 | H18: 27 | I18: 26 | J18: 25 | K18: 25 | L18: 24 | M18: 24 | N18: 23 | O18: 23 | P18: 22 | Q18: 22 | R18: 22 | S18: 21 | T18: 21 | U18: 21 | V18: 21 | W18: 20 | X18: 20 | Y18: 20 | Z18: 20 | AA18: 20 | AB18: 19 | AC18: 19 | AD18: 19 | AE18: 19 | AF18: 19 | AG18: BNEF LCOE - All Technologies - Unites States - LCOE Forecast 2022 | AH18: To be converted in $/GJ with conversion factor in Universal Inputs "conversion_electricity" OR just | AI18: https://www.bnef.com/flagships/lcoe
A19: Wind onshore with storage | B19: LCOE $/MWh (low) | C19: 2022 2H | D19: 49 | E19: 45 | F19: 42 | G19: 39 | H19: 37 | I19: 36 | J19: 35 | K19: 34 | L19: 33 | M19: 32 | N19: 31 | O19: 31 | P19: 30 | Q19: 30 | R19: 29 | S19: 29 | T19: 29 | U19: 28 | V19: 28 | W19: 28 | X19: 27 | Y19: 27 | Z19: 27 | AA19: 27 | AB19: 26 | AC19: 26 | AD19: 26 | AE19: 26 | AF19: 26 | AG19: BNEF LCOE - All Technologies - Unites States - LCOE Forecast 2022 | AH19: To be converted in $/GJ with conversion factor in Universal Inputs "conversion_electricity" OR just | AI19: https://www.bnef.com/flagships/lcoe | AJ19: =5.9/1000 -> 0.0059 | AK19: [t-CO2,eq GJ-1] | AL19: Young et al. (2023)
A20: CCGT | B20: LCOE $/MWh (high) | C20: 2022 2H | D20: 93 | E20: 91 | F20: 91 | G20: 90 | H20: 90 | I20: 91 | J20: 91 | K20: 92 | L20: 92 | M20: 93 | N20: 93 | O20: 94 | P20: 94 | Q20: 94 | R20: 95 | S20: 95 | T20: 95 | U20: 96 | V20: 96 | W20: 96 | X20: 96 | Y20: 97 | Z20: 97 | AA20: 97 | AB20: 97 | AC20: 97 | AD20: 97 | AE20: 97 | AF20: 97 | AG20: BNEF LCOE - All Technologies - Unites States - LCOE Forecast 2022 | AH20: To be converted in $/GJ with conversion factor in Universal Inputs "conversion_electricity" OR just | AI20: https://www.bnef.com/flagships/lcoe
A21: CCGT CCS | B21: LCOE $/MWh (high) | C21: 2022 2H | D21: 479 | E21: 435 | F21: 395 | G21: 351 | H21: 312 | I21: 274 | J21: 235 | K21: 196 | L21: 158 | M21: 158 | N21: 159 | O21: 159 | P21: 160 | Q21: 160 | R21: 161 | S21: 161 | T21: 161 | U21: 162 | V21: 162 | W21: 162 | X21: 162 | Y21: 163 | Z21: 163 | AA21: 163 | AB21: 163 | AC21: 163 | AD21: 163 | AE21: 163 | AF21: 163 | AG21: BNEF LCOE - All Technologies - Unites States - LCOE Forecast 2022 | AH21: To be converted in $/GJ with conversion factor in Universal Inputs "conversion_electricity" OR just | AI21: https://www.bnef.com/flagships/lcoe
A22: CCGT Hydrogen | B22: LCOE $/MWh (high) | C22: 2022 2H | D22: 214 | E22: 195 | F22: 181 | G22: 168 | H22: 160 | I22: 153 | J22: 147 | K22: 143 | L22: 139 | M22: 136 | N22: 133 | O22: 129 | P22: 126 | Q22: 122 | R22: 119 | S22: 117 | T22: 115 | U22: 113 | V22: 112 | W22: 111 | X22: 111 | Y22: 110 | Z22: 110 | AA22: 109 | AB22: 109 | AC22: 108 | AD22: 108 | AE22: 108 | AF22: 108 | AG22: BNEF LCOE - All Technologies - Unites States - LCOE Forecast 2022 | AH22: To be converted in $/GJ with conversion factor in Universal Inputs "conversion_electricity" OR just | AI22: https://www.bnef.com/flagships/lcoe
A23: Coal | B23: LCOE $/MWh (high) | C23: 2022 2H | D23: 158 | E23: 161 | F23: 164 | G23: 164 | H23: 167 | I23: 170 | J23: 172 | K23: 174 | L23: 176 | M23: 178 | N23: 180 | O23: 182 | P23: 183 | Q23: 185 | R23: 186 | S23: 188 | T23: 189 | U23: 190 | V23: 191 | W23: 192 | X23: 192 | Y23: 192 | Z23: 192 | AA23: 192 | AB23: 192 | AC23: 192 | AD23: 192 | AE23: 192 | AF23: 192 | AG23: BNEF LCOE - All Technologies - Unites States - LCOE Forecast 2022 | AH23: To be converted in $/GJ with conversion factor in Universal Inputs "conversion_electricity" OR just | AI23: https://www.bnef.com/flagships/lcoe
A24: Coal CCS | B24: LCOE $/MWh (high) | C24: 2022 2H | D24: 730 | E24: 699 | F24: 659 | G24: 600 | H24: 546 | I24: 488 | J24: 426 | K24: 361 | L24: 293 | M24: 297 | N24: 300 | O24: 303 | P24: 305 | Q24: 308 | R24: 310 | S24: 313 | T24: 315 | U24: 317 | V24: 319 | W24: 321 | X24: 321 | Y24: 321 | Z24: 321 | AA24: 321 | AB24: 321 | AC24: 321 | AD24: 321 | AE24: 321 | AF24: 321 | AG24: BNEF LCOE - All Technologies - Unites States - LCOE Forecast 2022 | AH24: To be converted in $/GJ with conversion factor in Universal Inputs "conversion_electricity" OR just | AI24: https://www.bnef.com/flagships/lcoe
A25: OCGT | B25: LCOE $/MWh (high) | C25: 2022 2H | D25: 223 | E25: 224 | F25: 225 | G25: 226 | H25: 227 | I25: 229 | J25: 230 | K25: 232 | L25: 233 | M25: 235 | N25: 236 | O25: 237 | P25: 238 | Q25: 239 | R25: 241 | S25: 242 | T25: 243 | U25: 244 | V25: 244 | W25: 245 | X25: 246 | Y25: 247 | Z25: 247 | AA25: 248 | AB25: 248 | AC25: 249 | AD25: 249 | AE25: 249 | AF25: 249 | AG25: BNEF LCOE - All Technologies - Unites States - LCOE Forecast 2022 | AH25: To be converted in $/GJ with conversion factor in Universal Inputs "conversion_electricity" OR just | AI25: https://www.bnef.com/flagships/lcoe
A26: OCGT CCS | B26: LCOE $/MWh (high) | C26: 2022 2H | D26: 1,148 | E26: 1,059 | F26: 964 | G26: 868 | H26: 772 | I26: 678 | J26: 584 | K26: 489 | L26: 395 | M26: 396 | N26: 398 | O26: 399 | P26: 401 | Q26: 402 | R26: 403 | S26: 404 | T26: 405 | U26: 407 | V26: 408 | W26: 409 | X26: 409 | Y26: 410 | Z26: 411 | AA26: 411 | AB26: 412 | AC26: 412 | AD26: 412 | AE26: 412 | AF26: 412 | AG26: BNEF LCOE - All Technologies - Unites States - LCOE Forecast 2022 | AH26: To be converted in $/GJ with conversion factor in Universal Inputs "conversion_electricity" OR just | AI26: https://www.bnef.com/flagships/lcoe
A27: OCGT Hydrogen | B27: LCOE $/MWh (high) | C27: 2022 2H | D27: 540 | E27: 506 | F27: 475 | G27: 447 | H27: 423 | I27: 403 | J27: 385 | K27: 371 | L27: 360 | M27: 350 | N27: 341 | O27: 332 | P27: 323 | Q27: 314 | R27: 306 | S27: 299 | T27: 295 | U27: 291 | V27: 288 | W27: 286 | X27: 284 | Y27: 283 | Z27: 281 | AA27: 280 | AB27: 279 | AC27: 278 | AD27: 278 | AE27: 277 | AF27: 277 | AG27: BNEF LCOE - All Technologies - Unites States - LCOE Forecast 2022 | AH27: To be converted in $/GJ with conversion factor in Universal Inputs "conversion_electricity" OR just | AI27: https://www.bnef.com/flagships/lcoe
A28: PV non-tracking | B28: LCOE $/MWh (high) | C28: 2022 2H | D28: 60 | E28: 53 | F28: 50 | G28: 45 | H28: 43 | I28: 42 | J28: 40 | K28: 38 | L28: 35 | M28: 32 | N28: 29 | O28: 28 | P28: 28 | Q28: 27 | R28: 26 | S28: 26 | T28: 25 | U28: 24 | V28: 24 | W28: 23 | X28: 23 | Y28: 22 | Z28: 22 | AA28: 21 | AB28: 21 | AC28: 21 | AD28: 20 | AE28: 20 | AF28: 20 | AG28: BNEF LCOE - All Technologies - Unites States - LCOE Forecast 2022 | AH28: To be converted in $/GJ with conversion factor in Universal Inputs "conversion_electricity" OR just | AI28: https://www.bnef.com/flagships/lcoe
A29: PV non-tracking with storage | B29: LCOE $/MWh (high) | C29: 2022 2H | D29: 188 | E29: 163 | F29: 146 | G29: 129 | H29: 119 | I29: 110 | J29: 103 | K29: 98 | L29: 93 | M29: 88 | N29: 83 | O29: 81 | P29: 79 | Q29: 76 | R29: 75 | S29: 74 | T29: 73 | U29: 71 | V29: 70 | W29: 70 | X29: 69 | Y29: 69 | Z29: 68 | AA29: 68 | AB29: 67 | AC29: 67 | AD29: 67 | AE29: 66 | AF29: 66 | AG29: BNEF LCOE - All Technologies - Unites States - LCOE Forecast 2022 | AH29: To be converted in $/GJ with conversion factor in Universal Inputs "conversion_electricity" OR just | AI29: https://www.bnef.com/flagships/lcoe
A30: PV tracking | B30: LCOE $/MWh (high) | C30: 2022 2H | D30: 53 | E30: 48 | F30: 44 | G30: 40 | H30: 39 | I30: 37 | J30: 36 | K30: 33 | L30: 31 | M30: 28 | N30: 26 | O30: 25 | P30: 25 | Q30: 24 | R30: 23 | S30: 23 | T30: 22 | U30: 22 | V30: 21 | W30: 21 | X30: 20 | Y30: 20 | Z30: 19 | AA30: 19 | AB30: 19 | AC30: 18 | AD30: 18 | AE30: 18 | AF30: 18 | AG30: BNEF LCOE - All Technologies - Unites States - LCOE Forecast 2022 | AH30: To be converted in $/GJ with conversion factor in Universal Inputs "conversion_electricity" OR just | AI30: https://www.bnef.com/flagships/lcoe
A31: PV tracking with storage | B31: LCOE $/MWh (high) | C31: 2022 2H | D31: 160 | E31: 141 | F31: 124 | G31: 110 | H31: 102 | I31: 94 | J31: 88 | K31: 83 | L31: 79 | M31: 75 | N31: 71 | O31: 69 | P31: 67 | Q31: 65 | R31: 64 | S31: 63 | T31: 62 | U31: 61 | V31: 60 | W31: 60 | X31: 59 | Y31: 59 | Z31: 58 | AA31: 58 | AB31: 58 | AC31: 57 | AD31: 57 | AE31: 56 | AF31: 56 | AG31: BNEF LCOE - All Technologies - Unites States - LCOE Forecast 2022 | AH31: To be converted in $/GJ with conversion factor in Universal Inputs "conversion_electricity" OR just | AI31: https://www.bnef.com/flagships/lcoe | AJ31: =15.3/1000 -> 0.0153 | AK31: [t-CO2,eq GJ-1] | AL31: Young et al. (2023)
A32: Utility-scale battery (1h) | B32: LCOE $/MWh (high) | C32: 2022 2H | D32: 287 | E32: 241 | F32: 209 | G32: 184 | H32: 165 | I32: 151 | J32: 139 | K32: 132 | L32: 127 | M32: 119 | N32: 112 | O32: 109 | P32: 106 | Q32: 98 | R32: 96 | S32: 94 | T32: 92 | U32: 90 | V32: 88 | W32: 88 | X32: 88 | Y32: 88 | Z32: 88 | AA32: 88 | AB32: 88 | AC32: 88 | AD32: 88 | AE32: 88 | AF32: 88 | AG32: BNEF LCOE - All Technologies - Unites States - LCOE Forecast 2022 | AH32: To be converted in $/GJ with conversion factor in Universal Inputs "conversion_electricity" OR just | AI32: https://www.bnef.com/flagships/lcoe
A33: Utility-scale battery (4h) | B33: LCOE $/MWh (high) | C33: 2022 2H | D33: 206 | E33: 172 | F33: 146 | G33: 127 | H33: 112 | I33: 100 | J33: 89 | K33: 85 | L33: 81 | M33: 77 | N33: 74 | O33: 71 | P33: 69 | Q33: 66 | R33: 65 | S33: 63 | T33: 62 | U33: 61 | V33: 60 | W33: 60 | X33: 60 | Y33: 60 | Z33: 60 | AA33: 60 | AB33: 60 | AC33: 60 | AD33: 60 | AE33: 60 | AF33: 60 | AG33: BNEF LCOE - All Technologies - Unites States - LCOE Forecast 2022 | AH33: To be converted in $/GJ with conversion factor in Universal Inputs "conversion_electricity" OR just | AI33: https://www.bnef.com/flagships/lcoe
A34: Wind offshore | B34: LCOE $/MWh (high) | C34: 2022 2H | D34: 150 | E34: 137 | F34: 130 | G34: 124 | H34: 120 | I34: 116 | J34: 113 | K34: 110 | L34: 90 | M34: 88 | N34: 86 | O34: 84 | P34: 82 | Q34: 81 | R34: 79 | S34: 77 | T34: 76 | U34: 74 | V34: 73 | W34: 71 | X34: 71 | Y34: 70 | Z34: 69 | AA34: 68 | AB34: 67 | AC34: 66 | AD34: 66 | AE34: 66 | AF34: 65 | AG34: BNEF LCOE - All Technologies - Unites States - LCOE Forecast 2022 | AH34: To be converted in $/GJ with conversion factor in Universal Inputs "conversion_electricity" OR just | AI34: https://www.bnef.com/flagships/lcoe
A35: Wind onshore | B35: LCOE $/MWh (high) | C35: 2022 2H | D35: 65 | E35: 60 | F35: 55 | G35: 52 | H35: 50 | I35: 48 | J35: 46 | K35: 45 | L35: 44 | M35: 42 | N35: 41 | O35: 41 | P35: 40 | Q35: 39 | R35: 39 | S35: 38 | T35: 38 | U35: 37 | V35: 36 | W35: 36 | X35: 36 | Y35: 35 | Z35: 35 | AA35: 34 | AB35: 34 | AC35: 34 | AD35: 33 | AE35: 33 | AF35: 33 | AG35: BNEF LCOE - All Technologies - Unites States - LCOE Forecast 2022 | AH35: To be converted in $/GJ with conversion factor in Universal Inputs "conversion_electricity" OR just | AI35: https://www.bnef.com/flagships/lcoe
A36: Wind onshore with storage | B36: LCOE $/MWh (high) | C36: 2022 2H | D36: 132 | E36: 114 | F36: 99 | G36: 89 | H36: 82 | I36: 77 | J36: 72 | K36: 69 | L36: 67 | M36: 64 | N36: 62 | O36: 61 | P36: 59 | Q36: 58 | R36: 57 | S36: 56 | T36: 55 | U36: 54 | V36: 53 | W36: 53 | X36: 52 | Y36: 52 | Z36: 51 | AA36: 51 | AB36: 50 | AC36: 50 | AD36: 49 | AE36: 49 | AF36: 48 | AG36: BNEF LCOE - All Technologies - Unites States - LCOE Forecast 2022 | AH36: To be converted in $/GJ with conversion factor in Universal Inputs "conversion_electricity" OR just | AI36: https://www.bnef.com/flagships/lcoe | AJ36: =5.9/1000 -> 0.0059 | AK36: [t-CO2,eq GJ-1] | AL36: Young et al. (2023)
A37: Nuclear | B37: LCOE $/MWh (low) | C37: 2022 2H | D37: 43.9 | AI37: Nuclear Energy Agency (NEA) - Projected Costs of Generating Electricity - 2020 Edition (oecd-nea.org) | AJ37: =1.9/1000 -> 0.0019 | AK37: [t-CO2,eq GJ-1] | AL37: p.59
A38: Nuclear | B38: LCOE $/MWh (high) | C38: 2022 2H | D38: 98.56 | AI38: Nuclear Energy Agency (NEA) - Projected Costs of Generating Electricity - 2020 Edition (oecd-nea.org) | AJ38: =1.9/1000 -> 0.0019 | AL38: p.59
A39: Geothermal | B39: LCOE $/MWh (low) | C39: 2022 2H | D39: 37 | AI39: Renewable Power Generation Costs in 2021 (irena.org) | AJ39: =18.9/1000 -> 0.0189 | AK39: [t-CO2,eq GJ-1] | AL39: Young et al. (2023) | AM39: In line with icelandic LCOE | AN39: Global weighted average
A40: Geothermal | B40: LCOE $/MWh (high) | C40: 2022 2H | D40: 98.879151 | AI40: Renewable Power Generation Costs in 2021 (irena.org) | AJ40: =18.9/1000 -> 0.0189
A42: Carbon intensities used for heat in standardization taken from Young et al. (2023)
B43: Country | C43: Heat Source | D43: Cost Min [$ GJ-1] | E43: Cost Median [$ GJ-1] | F43: Cost Max [$ GJ-1] | G43: Carbon Intensity [kg CO₂eq GJ-1] | H43: Refs
A44: NATURAL GAS | B44: United States | C44: Natural Gas | D44: 3 | E44: 3.2 | F44: 9.9 | G44: 17.6 | H44: 56 | I44: IEA (2021). Key world energy statistics 2021
B45: United States | C45: Geothermal | D45: 13.8 | E45: 18.7 | F45: 28.1 | G45: 3.8 | H45: 57 | I45: Beckers, K.F., and McCabe, K. (2019). GEOPHIRES v2.0: updated geothermal technoeconomic simulation tool. Geotherm. Energy 7, 5. 10.1186/s40517-019-0119-6.
B46: United States | C46: Solar | D46: 14.2 | E46: 21.5 | F46: 44.2 | G46: 3.9 | H46: 58 | I46: IEA (2021). Levelized cost of heating (LCOH) for consumers, for selected space and water heating technologies and countries.
A47: WASTE HEAT | B47: United states | C47: Average | D47: =AVERAGE(D44:D46) -> 10.333333 | E47: =AVERAGE(E44:E46) -> 14.466667 | F47: =AVERAGE(F44:F46) -> 27.4 | G47: =AVERAGE(G44:G46) -> 8.4333333 | I47: Average of NG, geothermal, solar used for waste heat (low temperature heat) carbon intensity
A48: Table S9 Prices and carbon intensity natural gas (for the high temperature processes >150°C), alongside prices and carbon intensity of low-grade heat from solar and geothermala (for the low temperature processes <150°C).
A49: Low-grade heat can also be supplied with electricity via a heat pump, which assumes the capital cost detailed in Table S1 and a coefficient of performance of 2.b The carbon intensity of geothermal heat is scaled from a baseline reference based on grid intensity,51,52c whilst solar heat is scaled from a baseline based on solar intensity.53,54
A50: Finally, the natural gas carbon intensity is calculated from leakage rates reported by Cooper et al.55 and is not including combustion as the processes that use it are oxyfired so all the carbon dioxide from combustion is captured.

Sheet Standard Input Calculations
B2: LCOE cost assumption
B4: Source: | C4: BNEF LCOE Forecast 2022
B5: Year | C5: 2022 | D5: 2023 | E5: 2024 | F5: 2025 | G5: 2026 | H5: 2027 | I5: 2028 | J5: 2029 | K5: 2030 | L5: 2031 | M5: 2032 | N5: 2033 | O5: 2034 | P5: 2035 | Q5: 2036 | R5: 2037 | S5: 2038 | T5: 2039 | U5: 2040 | V5: 2041 | W5: 2042 | X5: 2043 | Y5: 2044 | Z5: 2045 | AA5: 2046 | AB5: 2047 | AC5: 2048 | AD5: 2049 | AE5: 2050 | AF5: -
B6: LCOE ($/MWh) | C6: 79 | D6: 70 | E6: 64 | F6: 55 | G6: 52 | H6: 48 | I6: 44 | J6: 42 | K6: 38 | L6: 39 | M6: 35 | N6: 34 | O6: 34 | P6: 33 | Q6: 33 | R6: 30 | S6: 32 | T6: 32 | U6: 31 | V6: 31 | W6: 31 | X6: 28 | Y6: 30 | Z6: 30 | AA6: 30 | AB6: 30 | AC6: 27 | AD6: 29 | AE6: 29
B7: LCOE (€/MWh) | C7: 84 | D7: 75 | E7: 68 | F7: 59 | G7: 55 | H7: 51 | I7: 47 | J7: 45 | K7: 40.53 | L7: 42 | M7: 37 | N7: 36 | O7: 36 | P7: 35 | Q7: 35 | R7: 32 | S7: 34 | T7: 34 | U7: 33 | V7: 33 | W7: 33 | X7: 30 | Y7: 32 | Z7: 32 | AA7: 32 | AB7: 32 | AC7: 29 | AD7: 31 | AE7: 31
B9: Possible sensitivities
B10: PV tracking with storage (high) - 12 battery hours - high
B11: LCOE ($/MWh) | C11: 374 | D11: 327 | E11: 284 | F11: 250 | G11: 228 | H11: 208 | I11: 192 | J11: 183 | K11: 175 | L11: 169 | M11: 161 | N11: 157 | O11: 151 | P11: 147 | Q11: 146 | R11: 143 | S11: 142 | T11: 139 | U11: 138 | V11: 138 | W11: 137 | X11: 137 | Y11: 136 | Z11: 136 | AA11: 136 | AB11: 135 | AC11: 135 | AD11: 132 | AE11: 132
B12: PV tracking with storage (low) - 12 battery hours - high
B13: LCOE ($/MWh) | C13: 79 | D13: 70 | E13: 64 | F13: 55 | G13: 52 | H13: 48 | I13: 44 | J13: 42 | K13: 38 | L13: 39 | M13: 35 | N13: 34 | O13: 34 | P13: 33 | Q13: 33 | R13: 30 | S13: 32 | T13: 32 | U13: 31 | V13: 31 | W13: 31 | X13: 28 | Y13: 30 | Z13: 30 | AA13: 30 | AB13: 30 | AC13: 27 | AD13: 29 | AE13: 29
B14: Wind Offshore
B15: LCOE ($/MWh) | C15: 116 | D15: 107 | E15: 102 | F15: 97 | G15: 94 | H15: 91 | I15: 88 | J15: 86 | K15: 54 | L15: 53 | M15: 52 | N15: 51 | O15: 50 | P15: 49 | Q15: 48 | R15: 47 | S15: 46 | T15: 45 | U15: 44 | V15: 44 | W15: 43 | X15: 43 | Y15: 42 | Z15: 42 | AA15: 41 | AB15: 40 | AC15: 40 | AD15: 40 | AE15: 40
B18: Discount rate
G20: Source
B21: Discount rate | C21: 0.07 | G21: Average across all studies considered (Multiple sources)

Sheet Sensitivities
A1: Coupling of CO2 and Electricity
A2: CO2 Price | B2: Electricity Price
A3: 406 | B3: 79
A4: 358 | B4: 29
A6: Slope | B6: =(A3-A4)/(B3-B4) -> 0.96 | C6: $/t per $/kWh
A9: Electricity Price Range
B10: 2024 | C10: 2050
A11: High | B11: 116 | C11: 40 | D11: Wind Offshore
A12: Low | B12: 64 | C12: 29
A14: CO2 Price Range
B15: 2024 | C15: 2050
A16: High | B16: 1477 | C16: 362
A17: Low | B17: 1284 | C17: 246 | D17: Lower bounds of multi component experience curves

Sheet Notes for Study Parameters
A2: Parameter | B2: Note | C2: Source

Sheet Study Selection Step 1
A1: Included? | B1: Title | C1: Journal | D1: Authors | E1: Year of Publication | F1: DOI | G1: Abstract | H1: First Read | I1: Second Read | J1: Cost Type | K1: Timeline | L1: Plant size | M1: Scale | N1: DAC Technology | O1: Year of Assumptions in Study | P1: Electricity Sources | Q1: Method | R1: Frequently Referenced? | S1: Sensitive Parameters | T1: Sensitive parameters CAPEX | U1: Sensitive parameters OPEX | V1: Sensitivity Analysis | W1: Sensitivity for current or future costs | X1: Main Cost Drivers | Y1: CAPEX Driver | Z1: OPEX Driver
A2: y | B2: Young et al. 2023 | C2: One Earth | D2: John Young 1 , Noah McQueen 2 , Charithea Charalambous 1 , Spyros Foteinis 1 , Olivia Hawrot 1 , Manuel Ojeda 1 , Hélène Pilorgé 2 , John Andresen 1 , Peter Psarras 2 , Phil Renforth 1 , Susana Garcia 1 , Mijndert van der Spek 1 3 | E2: 2023 | F2: 10.1016/j.oneear.2023.06.004 | H2: Relevant | L2: Initial plant size | M2: Initial plant | N2: Liquid solvent | O2: 2022 | P2: nuclear energy | Q2: Techno-economic modeling | S2: Capacity factor, Bare erected cost, Materials scaling | T2: Capacity factor | U2: Heat demand | V2: Tornado Chart | W2: current
A3: y | B3: Young et al. 2023 | C3: One Earth | D3: John Young 1 , Noah McQueen 2 , Charithea Charalambous 1 , Spyros Foteinis 1 , Olivia Hawrot 1 , Manuel Ojeda 1 , Hélène Pilorgé 2 , John Andresen 1 , Peter Psarras 2 , Phil Renforth 1 , Susana Garcia 1 , Mijndert van der Spek 1 3 | E3: 2023 | F3: 10.1016/j.oneear.2023.06.004 | H3: Relevant | L3: Initial plant size | M3: Initial plant | N3: Solid sorbent | O3: 2022 | P3: nuclear energy, heat pump | Q3: Techno-economic modeling | S3: Capacity factor, Bare erected cost, Materials scaling | T3: Capacity factor | U3: Electricity price | V3: Tornado Chart | W3: current
A4: y | B4: Young et al. 2023 | C4: One Earth | D4: John Young 1 , Noah McQueen 2 , Charithea Charalambous 1 , Spyros Foteinis 1 , Olivia Hawrot 1 , Manuel Ojeda 1 , Hélène Pilorgé 2 , John Andresen 1 , Peter Psarras 2 , Phil Renforth 1 , Susana Garcia 1 , Mijndert van der Spek 1 3 | E4: 2023 | F4: 10.1016/j.oneear.2023.06.004 | H4: Relevant | L4: Initial plant size | M4: Initial plant | N4: Liquid solvent with electrochemical regeneration | O4: 2022 | P4: nuclear energy | Q4: Techno-economic modeling | S4: Electricity demand, Electricity price, Bare erected cost | T4: Bare erected cost | U4: Electricity requirement, Electricity price | V4: Tornado Chart
A5: y | B5: Young et al. 2023 | C5: One Earth | D5: John Young 1 , Noah McQueen 2 , Charithea Charalambous 1 , Spyros Foteinis 1 , Olivia Hawrot 1 , Manuel Ojeda 1 , Hélène Pilorgé 2 , John Andresen 1 , Peter Psarras 2 , Phil Renforth 1 , Susana Garcia 1 , Mijndert van der Spek 1 3 | E5: 2023 | F5: 10.1016/j.oneear.2023.06.004 | H5: Relevant | L5: Initial plant size | M5: Initial plant | N5: Ambient weathering | O5: 2022 | P5: nuclear energy | Q5: Techno-economic modeling | S5: Bare erected cost, Capacity factor, MgCO3 price | T5: Bare erected cost | U5: MgCO3 price, heat demand | V5: Tornado Chart
A6: y | B6: Young et al. 2023 | C6: One Earth | D6: John Young 1 , Noah McQueen 2 , Charithea Charalambous 1 , Spyros Foteinis 1 , Olivia Hawrot 1 , Manuel Ojeda 1 , Hélène Pilorgé 2 , John Andresen 1 , Peter Psarras 2 , Phil Renforth 1 , Susana Garcia 1 , Mijndert van der Spek 1 3 | E6: 2023 | F6: 10.1016/j.oneear.2023.06.004 | H6: Relevant | L6: 1 Gt CO2/year | M6: Cost projection | N6: Liquid solvent | O6: 2050 | P6: nuclear energy | Q6: Techno-economic modeling | S6: Learning rate, Bare erected cost, Materials scaling | T6: Learning rate | U6: Electricity price | V6: Tornado Chart
A7: y | B7: Young et al. 2023 | C7: One Earth | D7: John Young 1 , Noah McQueen 2 , Charithea Charalambous 1 , Spyros Foteinis 1 , Olivia Hawrot 1 , Manuel Ojeda 1 , Hélène Pilorgé 2 , John Andresen 1 , Peter Psarras 2 , Phil Renforth 1 , Susana Garcia 1 , Mijndert van der Spek 1 3 | E7: 2023 | F7: 10.1016/j.oneear.2023.06.004 | H7: Relevant | L7: 1 Gt CO2/year | M7: Cost projection | N7: Solid sorbent | O7: 2050 | P7: nuclear energy, heat pump | Q7: Techno-economic modeling | S7: Learning rate, Electricity price, Variable OPEX learning rate | T7: Learning rate | U7: COP heat pump, heat demand | V7: Tornado Chart
A8: y | B8: Young et al. 2023 | C8: One Earth | D8: John Young 1 , Noah McQueen 2 , Charithea Charalambous 1 , Spyros Foteinis 1 , Olivia Hawrot 1 , Manuel Ojeda 1 , Hélène Pilorgé 2 , John Andresen 1 , Peter Psarras 2 , Phil Renforth 1 , Susana Garcia 1 , Mijndert van der Spek 1 3 | E8: 2023 | F8: 10.1016/j.oneear.2023.06.004 | H8: Relevant | L8: 1 Gt CO2/year | M8: Cost projection | N8: Liquid solvent with electrochemical regeneration | O8: 2050 | P8: nuclear energy | Q8: Techno-economic modeling | S8: Electricity demand, Electricity price, Variable OPEX learning rate | T8: Learning rate | U8: Electricity demand, electricity price | V8: Tornado Chart
A9: y | B9: Young et al. 2023 | C9: One Earth | D9: John Young 1 , Noah McQueen 2 , Charithea Charalambous 1 , Spyros Foteinis 1 , Olivia Hawrot 1 , Manuel Ojeda 1 , Hélène Pilorgé 2 , John Andresen 1 , Peter Psarras 2 , Phil Renforth 1 , Susana Garcia 1 , Mijndert van der Spek 1 3 | E9: 2023 | F9: 10.1016/j.oneear.2023.06.004 | H9: Relevant | L9: 1 Gt CO2/year | M9: Cost projection | N9: Ambient weathering | O9: 2050 | P9: nuclear energy | Q9: Techno-economic modeling | S9: Learning rate, Bare erected cost, Capacity factor | T9: Learning rate | U9: MgCO3 price, heat demand | V9: Tornado Chart
A10: y | B10: Sievert et al. 2024 | C10: Joule | D10: Sievert, Schmidt, Steffen | E10: 2024 | F10: 10.1016/j.joule.2024.02.005 | H10: Relevant | L10: Initial plant size | M10: Initial plant | N10: Liquid solvent | O10: 2022 | P10: Solar PV with tracking US | Q10: Techno-economic modeling | S10: Capacity factor, WACC, Plant lifetime | T10: Capacity factor | U10: Heat demand | V10: Tornado Chart
A11: y | B11: Sievert et al. 2024 | C11: Joule | D11: Sievert, Schmidt, Steffen | E11: 2024 | F11: 10.1016/j.joule.2024.02.005 | H11: Relevant | L11: 1 Gt CO2/year | M11: Cost projection | N11: Liquid solvent | O11: 2050 | P11: Solar PV with tracking US | Q11: Techno-economic modeling | S11: Capacity factor, WACC, Plant lifetime | T11: Capacity factor | U11: Heat demand | V11: Tornado Chart
A12: y | B12: Sievert et al. 2024 | C12: Joule | D12: Sievert, Schmidt, Steffen | E12: 2024 | F12: 10.1016/j.joule.2024.02.005 | H12: Relevant | L12: Initial plant size | M12: Initial plant | N12: Solid sorbent | O12: 2022 | P12: Solar PV with tracking US | Q12: Techno-economic modeling | S12: Capacity factor, WACC, Plant lifetime | T12: Capacity factor | U12: COP heat pump, Heat demand | V12: Tornado Chart
A13: y | B13: Sievert et al. 2024 | C13: Joule | D13: Sievert, Schmidt, Steffen | E13: 2024 | F13: 10.1016/j.joule.2024.02.005 | H13: Relevant | L13: 1 Gt CO2/year | M13: Cost projection | N13: Solid sorbent | O13: 2050 | P13: Solar PV with tracking US | Q13: Techno-economic modeling | S13: Capacity factor, WACC, learning rate OPEX | T13: Capacity factor | U13: Water requirement and cost | V13: Tornado Chart
A14: y | B14: Sievert et al. 2024 | C14: Joule | D14: Sievert, Schmidt, Steffen | E14: 2024 | F14: 10.1016/j.joule.2024.02.005 | H14: Relevant | L14: Initial plant size | M14: Initial plant | N14: Ambient weathering | O14: 2022 | P14: Solar PV with tracking US | Q14: Techno-economic modeling | S14: Capacity factor, WACC, Calciner CAPEX | T14: Capacity factor, discount rate, Calciner CAPEX | U14: Electricity demand | V14: Tornado Chart
A15: y | B15: Sievert et al. 2024 | C15: Joule | D15: Sievert, Schmidt, Steffen | E15: 2024 | F15: 10.1016/j.joule.2024.02.005 | H15: Relevant | L15: 1 Gt CO2/year | M15: Cost projection | N15: Ambient weathering | O15: 2050 | P15: Solar PV with tracking US | Q15: Techno-economic modeling | S15: Capacity factor, Learning rate system, WACC | T15: Capacity factor, learning rate system | U15: Electricity demand | V15: Tornado Chart
A16: y | B16: McQueen et al. 2020a | C16: Environmental Science & Technology | D16: Noah McQueenPeter PsarrasHélène PilorgéSimona LiguoriJiajun HeMengyao YuanCaleb M. WoodallKourosh KianLara PierpointJacob JurewiczJ. Matthew LucasRory JacobsonNoah DeichJennifer Wilcox* | E16: 2020 | F16: 10.1021/acs.est.0c00476 | H16: Relevant | L16: 100kt CO2/year | M16: Initial plant | N16: Solid sorbent | O16: 2022 | P16: nuclear energy | Q16: Techno-economic modeling | S16: / | V16: no sensitivity analysis | X16: Contactor CAPEX, Electricity, Steam | Y16: Contactor CAPEX | Z16: Electricity demand
A17: y | B17: Sendi et al. 2022 | C17: One Earth | D17: Marwan Sendi 1 2 , Mai Bui 2 3 , Niall Mac Dowell 2 3 , Paul Fennell 1 4 | E17: 2022 | F17: 10.1016/j.oneear.2022.09.003 | H17: Relevant | L17: 1Mt CO2/year | M17: Cost projection | N17: Solid sorbent | O17: 2022 | P17: Solar PV | Q17: Techno-economic modeling | S17: / | V17: no sensitivity analysis | X17: Contactor CAPEX, Steam, Electricity | Y17: Contactor CAPEX | Z17: Electricity demand
A18: y | B18: Fasihi et al. 2019 | C18: Journal of Cleaner Production | D18: Mahdi Fasihi , Olga Efimova , Christian Breyer | E18: 2019 | F18: 10.1016/j.jclepro.2019.03.086 | H18: Relevant | M18: Initial plant | N18: Liquid solvent | S18: WACC, DAC capex, Electricity demand | T18: WACC, DAC capex | U18: Electricity demand | V18: Sensitivity with just one parameter being varied
A19: y | B19: Fasihi et al. 2019 | C19: Journal of Cleaner Production | D19: Mahdi Fasihi , Olga Efimova , Christian Breyer | E19: 2019 | F19: 10.1016/j.jclepro.2019.03.086 | H19: Relevant | M19: Initial plant | N19: Solid sorbent | S19: WACC, DAC capex, heat demand | T19: WACC, DAC capex | U19: heat demand | V19: Sensitivity with just one parameter being varied
A20: y | B20: Mazzotti et al. 2013 | C20: Climatic Change | D20: Marco Mazzotti, Renato Baciocchi, Michael J. Desmond & Robert H. Socolow | E20: 2013 | F20: 10.1007/s10584-012-0679-y | H20: Relevant | M20: Initial plant | N20: Liquid solvent | S20: / | V20: no sensitivity analysis
A21: y | B21: Zeman 2014 | C21: Environmental Science & Technology | D21: Zeman | E21: 2014 | F21: 10.1021/es502887y | H21: Relevant | M21: Initial plant | N21: Liquid solvent | S21: / | V21: no sensitivity analysis
A22: y | B22: Prats-Salvado et al. 2024 | C22: Environmental Science & Technology | D22: Enric Prats-Salvado*Nipun JagtapNathalie MonnerieChristian Sattler | E22: 2024 | F22: 10.1021/acs.est.3c08269 | H22: Relevant | M22: Initial plant | N22: Liquid solvent | S22: / | V22: no sensitivity analysis
A23: y | B23: Prats-Salvado et al. 2024 | C23: Environmental Science & Technology | D23: Enric Prats-Salvado*Nipun JagtapNathalie MonnerieChristian Sattler | E23: 2024 | F23: 10.1021/acs.est.3c08269 | H23: Relevant | M23: Initial plant | N23: Liquid solvent | S23: / | V23: no sensitivity analysis
A24: y | B24: Terlouw et al. 2024 | C24: Environmental Science & Technology | D24: Tom TerlouwDaniel PokrasViola Becattini*Marco Mazzotti* | E24: 2024 | F24: 10.1021/acs.est.3c10041 | H24: Relevant | M24: Initial plant | N24: Solid sorbent | S24: CAPEX scaling factor, Capacity factor, CAPEX | T24: CAPEX scaling factor, Capacity factor | U24: Electricity demand, Electricity grid emission factor | V24: Tornado Chart
A25: y | B25: McQueen et al. 2021 | C25: Frontiers in Climate | D25: \nNoah McQueenNoah McQueen1Michael J. DesmondMichael J. Desmond2Robert H. SocolowRobert H. Socolow3Peter PsarrasPeter Psarras1Jennifer Wilcox Jennifer Wilcox1* | E25: 2021 | F25: 10.3389/fclim.2020.618644 | H25: Relevant | L25: 1Mt CO2/year | M25: Initial plant | N25: Liquid solvent | O25: 2021 | Q25: Techno-economic modeling | S25: Lifetime, WACC, natural gas price | T25: Lifetime, WACC | U25: Heat price | V25: Sensitivity with just one parameter being varied
A26: y | B26: Datta et al. 2023 | C26: Environmental Science & Technology | D26: Aparajita DattaRamanan Krishnamoorti* | E26: 2023 | F26: 10.1021/acs.est.2c05194 | H26: Relevant | M26: Initial plant | N26: Solid sorbent | S26: / | V26: no sensitivity analysis
A27: y | B27: Datta et al. 2023 | C27: Environmental Science & Technology | D27: Aparajita DattaRamanan Krishnamoorti* | E27: 2023 | F27: 10.1021/acs.est.2c05194 | H27: Relevant | M27: Initial plant | N27: Membrane-based m-DAC | S27: / | V27: no sensitivity analysis
A28: y | B28: Sinha et al. 2019 | C28: Sustainable Energy: Process Systems Engineering | D28: Anshuman Sinha, Matthew J. Realff | E28: 2019 | F28: 10.1002/aic.16607 | H28: Relevant | N28: Solid sorbent | S28: /
A29: y | B29: Simon et al. 2011 | C29: Energy Procedia | D29: A.J. Simon , Naluahi B. Kaahaaina , S. Julio Friedmann , Roger D. Aines | E29: 2011 | F29: 10.1016/j.egypro.2011.02.196 | H29: Relevant | M29: Initial plant | N29: Generic (Solid sorbent referenced) | S29: / | V29: no sensitivity analysis
A30: n | B30: Fuhrman et al. 2021 | C30: Environmental Research letters | D30: Jay Fuhrman1,2, Andres Clarens2, Katherine Calvin1, Scott C Doney3, James A Edmonds1, Patrick O'Rourke1, Pralit Patel1, Shreekar Pradhan2, William Shobe4 and Haewon McJeon5,1 | E30: 2021 | F30: 10.1088/1748-9326/ac2db0 | H30: Relevant | I30: Not relevant | L30: IAM integration and DAC modeling not clear; IAM study; exclusion criterion | S30: /
A31: y | B31: Küng et al. 2023 | C31: Energy & Environmental Science | D31: Lukas Küng, ORCID logo ‡a Silvan Aeschlimann, ORCID logo ‡b Charithea Charalambous, ORCID logo ab Fergus McIlwaine, ORCID logo a John Young, ORCID logo a Noah Shannon,b Karen Strassel, ORCID logo c Cara Nichole Maesano,b Rudy Kahsar, ORCID logo b Daniel Pike,b Mijndert van der Spek ORCID logo a and Susana Garcia ORCID logo | E31: 2023 | F31: 10.1039/d3ee01008b | H31: Relevant | M31: Initial plant | N31: Liquid solvent | S31: / | V31: no sensitivity analysis
A32: y | B32: Küng et al. 2023 | C32: Energy & Environmental Science | D32: Lukas Küng, ORCID logo ‡a Silvan Aeschlimann, ORCID logo ‡b Charithea Charalambous, ORCID logo ab Fergus McIlwaine, ORCID logo a John Young, ORCID logo a Noah Shannon,b Karen Strassel, ORCID logo c Cara Nichole Maesano,b Rudy Kahsar, ORCID logo b Daniel Pike,b Mijndert van der Spek ORCID logo a and Susana Garcia ORCID logo | E32: 2023 | F32: 10.1039/d3ee01008b | H32: Relevant | M32: Initial plant | N32: Solid sorbent | S32: / | V32: no sensitivity analysis
A33: y | B33: Mostafa et al. 2022 | C33: Carbon Capture Science & Technology | D33: Mahmoud Mostafa a b , Cristina Antonicelli c , Christopher Varela d e , Diego Barletta c , Edwin Zondervan b | E33: 2022 | F33: 10.1016/j.ccst.2022.100060 | H33: Relevant | M33: Initial plant | N33: Liquid solvent | S33: / | V33: no sensitivity analysis
A34: y | B34: Keith et al. 2018 | C34: Joule | D34: David W. Keith 1 2 3 4, Geoffrey Holmes 3, David St. Angelo 3, Kenton Heidel 3 | E34: 2018 | F34: 10.1016/j.joule.2018.05.006 | H34: Relevant | M34: Initial plant | N34: Liquid solvent | S34: / | V34: no sensitivity analysis
A35: y | B35: Gray et al. 2024 | C35: Renewable and Sustainable Energy Reviews | D35: Nathan Gray a b , Richard O'Shea a b , Beatrice Smyth c , Piet N.L. Lens d , Jerry D. Murphy a b | E35: 2024 | F35: 10.1016/j.rser.2024.114552 | H35: Relevant | M35: Initial plant | N35: Solid sorbent | O35: 2023 | P35: Norwegian Grid | Q35: Techno-economic modeling | S35: Capacity factor, DAC CAPEX, WACC | T35: Capacity factor | U35: Electricity price | V35: Capacity Factor
A36: y | B36: Rosen et al. 2024 | C36: Energy & Fuels | D36: Natalie RosenAndreas WelterMartin SchwanklNicolas PlumeréJúnior StaudtJakob Burger* | E36: 2024 | F36: 10.1021/acs.energyfuels.4c02202 | H36: Relevant | M36: Initial plant | N36: Liquid solvent | S36: / | V36: no sensitivity analysis
A37: y | B37: Rosen et al. 2024 | C37: Energy & Fuels | D37: Natalie RosenAndreas WelterMartin SchwanklNicolas PlumeréJúnior StaudtJakob Burger* | E37: 2024 | F37: 10.1021/acs.energyfuels.4c02202 | H37: Relevant | M37: Initial plant | N37: Liquid solvent with electrochemical regeneration | S37: / | V37: no sensitivity analysis
A38: y | B38: Rosen et al. 2024 | C38: Energy & Fuels | D38: Natalie RosenAndreas WelterMartin SchwanklNicolas PlumeréJúnior StaudtJakob Burger* | E38: 2024 | F38: 10.1021/acs.energyfuels.4c02202 | H38: Relevant | M38: Initial plant | N38: Solid sorbent | S38: / | V38: no sensitivity analysis
A39: y | B39: Rosen et al. 2024 | C39: Energy & Fuels | D39: Natalie RosenAndreas WelterMartin SchwanklNicolas PlumeréJúnior StaudtJakob Burger* | E39: 2024 | F39: 10.1021/acs.energyfuels.4c02202 | H39: Relevant | M39: Initial plant | N39: Electro-swing adsorption (ESA) | S39: / | V39: no sensitivity analysis
A40: y | B40: Sabatino et al. 2020 | C40: Industrial & Engineering Chemistry Research | D40: Francesco SabatinoMayank MehtaAlexa GrimmMatteo GazzaniFausto GallucciGert Jan KramerMartin van Sint Annaland* | E40: 2020 | F40: 10.1021/acs.iecr.9b05641 | H40: Relevant | S40: /
A41: y | B41: McQueen et al. 2020c | C41: Nature Communications | D41: Noah McQueen, Peter Kelemen, Greg Dipple, Phil Renforth & Jennifer Wilcox | E41: 2020 | F41: 10.1038/s41467-020-16510-3 | H41: Relevant | M41: Initial plant | N41: Ambient Weathering | S41: Carbon mineralization efficiency (mass fraction of caustic MgO converted to MgCO3), environmental losses | U41: heat demand, calcination time, calcination temperature | V41: Sensitivity with just one parameter being varied
A42: y | B42: Lee et al. 2023 | C42: Joule | D42: Won Hee Lee 1 , Xin Zhang 1 , Sayan Banerjee 1 , Christopher W. Jones 1 , Matthew J. Realff 1 , Ryan P. Lively 1 2 | E42: 2023 | F42: 10.1016/j.joule.2023.05.016 | H42: Relevant | M42: Initial plant | N42: Solid sorbent | S42: / | T42: not mentioned | U42: Electricity price, Electricity grid emission factor | V42: in text only regarding OPEX
A43: y | B43: Abanades et al. 2023 | C43: Cell Reports Physical Science | D43: J. Carlos Abanades 1 , Yolanda A. Criado 1 2 , Heidi I. White 1 | E43: 2023 | F43: 10.1016/j.xcrp.2023.101339 | H43: Relevant | M43: Initial plant | S43: / | V43: no sensitivity analysis
A44: y | B44: Abanades et al. 2020 | C44: Sustainable Energy & Fuels | D44: J. Carlos Abanades, ORCID logo *a Yolanda A. Criado ORCID logo a and José Ramón Fernández ORCID logo | E44: 2020 | F44: 10.1039/d0se00094a | H44: Relevant | M44: Initial plant | S44: / | V44: no sensitivity analysis
A45: y | B45: Ragipani et al. 2022 | C45: ACS Sustainable Chemistry & Engineering | D45: Raghavendra RagipaniKeerthana SreenivasanRobert P. AnexHang ZhaiBu Wang* | E45: 2022 | F45: 10.1021/acssuschemeng.1c07867 | H45: Relevant | M45: Initial plant | S45: / | V45: no sensitivity analysis
A46: y | B46: Sinha et al. 2017 | C46: Industrial & Engineering Chemistry Research | D46: Anshuman SinhaOrcidLalit A. DarunteOrcidChristopher W. JonesOrcidMatthew J. RealffYoshiaki Kawajiri*Orcid | E46: 2017 | F46: 10.1021/acs.iecr.6b03887 | H46: Relevant | S46: /
A47: n | B47: Realmonte et al. 2019 | C47: Nature Communications | D47: Giulia Realmonte, Laurent Drouet, Ajay Gambhir, James Glynn, Adam Hawkes, Alexandre C. Köberle & Massimo Tavoni | E47: 2019 | F47: 10.1038/s41467-019-10842-5 | H47: Relevant | I47: Not relevant | L47: IAM study; exclusion criterion | S47: /
A48: n | B48: Hanna et al. 2021 | C48: Nature Communications | D48: Ryan Hanna, Ahmed Abdulla, Yangyang Xu & David G. Victor | E48: 2021 | F48: 10.1038/s41467-020-20437-0 | H48: Relevant | I48: Not relevant | L48: IAM study; exclusion criterion | S48: /
A49: y | B49: Pett-Ridge et al. 2024 | C49: Report | D49: Lawrence Livermore National Laboratory | E49: 2024 | F49: Roads to Removal – Options for carbon dioxide removal in the US (roads2removal.org) | H49: Relevant | M49: Initial plant | N49: Solid sorbent | O49: 2025 | S49: / | V49: no sensitivity analysis | X49: Contactor CAPEX, Electricity, Steam | Y49: Monolith CAPEX | Z49: Electricity
A50: y | B50: Pett-Ridge et al. 2024 | C50: Report | D50: Lawrence Livermore National Laboratory | E50: 2024 | F50: Roads to Removal – Options for carbon dioxide removal in the US (roads2removal.org) | H50: Relevant | M50: Cost projection | N50: Solid sorbent | O50: 2050 | S50: / | V50: no sensitivity analysis | X50: Contactor CAPEX, Electricity, Steam | Y50: Monolith CAPEX | Z50: Electricity
A51: y | B51: Pett-Ridge et al. 2024 | C51: Report | D51: Lawrence Livermore National Laboratory | E51: 2024 | F51: Roads to Removal – Options for carbon dioxide removal in the US (roads2removal.org) | H51: Relevant | M51: Initial plant | N51: Liquid solvent | O51: 2025 | S51: / | V51: no sensitivity analysis | X51: CAPEX | Y51: Contactor CAPEX | Z51: Electricity
A52: y | B52: Pett-Ridge et al. 2024 | C52: Report | D52: Lawrence Livermore National Laboratory | E52: 2024 | F52: Roads to Removal – Options for carbon dioxide removal in the US (roads2removal.org) | H52: Relevant | M52: Cost projection | N52: Liquid solvent | O52: 2050 | S52: / | V52: no sensitivity analysis | X52: CAPEX | Y52: Contactor CAPEX | Z52: Electricity
A53: y | B53: NETL/Valentine 2022a | C53: Report | D53: National Energy Technology Laboratory | E53: 2022 | F53: DirectAirCaptureCaseStudiesSolventSystem_083122.pdf (doe.gov) | H53: Relevant | M53: Initial plant | N53: Liquid solvent | S53: Fixed Charge rate, Capacity factor, Natural Gas Price | T53: Fixed Charge Rate, Capacity factor, Capital Cost | U53: Natural Gas Price, Calciner Natural Gas Requirement | V53: Tornado Chart
A54: y | B54: NETL/Valentine 2022b | C54: Report | D54: National Energy Technology Laboratory | E54: 2022 | F54: TECHNICAL REPORT TEMPLATE AND USER GUIDE (doe.gov) | H54: Relevant | M54: Initial plant | N54: Solid sorbent | S54: Sorbent cost, fixed charge rate, Capacity factor | T54: Capacity factor
A55: y | B55: NASEM 2019 | C55: Report | D55: National Academies of Sciences, Engineering, and Medicine | E55: 2019 | F55: https://doi.org/10.17226/25259 | H55: Relevant | M55: Initial plant | N55: Liquid solvent | S55: / | V55: no sensitivity analysis
A56: y | B56: NASEM 2019 | C56: Report | D56: National Academies of Sciences, Engineering, and Medicine | E56: 2019 | F56: https://doi.org/10.17226/25259 | H56: Relevant | M56: Initial plant | N56: Solid sorbent | S56: / | V56: no sensitivity analysis
A57: y | B57: APS 2011 | C57: Report | D57: American Physical Society | E57: 2011 | F57: Direct-Air-Capture-of-CO2-with-Chemicals_snams5.pdf (cloudinary.com) | H57: Relevant | M57: Initial plant | N57: Liquid solvent | S57: no sensitivity analysis

Sheet Studies current &future cost
A1: Reference | B1: Included? | C1: Harmonized by | D1: Type of literature | E1: DOI | F1: DAC Technology | G1: Technology Detail | H1: Timeline | I1: Plant Capacity (Mt CO2/year) | K1: Note for future projection
A2: Young et al. 2023 | B2: y | C2: YD/KS | D2: Journal article | E2: 10.1016/j.oneear.2023.06.004 | F2: Liquid solvent | G2: KOH absorption paired with regeneration via Ca looping | H2: 2022-2100 | I2: 0.98
A3: Young et al. 2023 | B3: y | C3: YD/KS | D3: Journal article | E3: 10.1016/j.oneear.2023.06.004 | F3: Solid sorbent | G3: Solid sorbent DAC using temperature vacuum swing adsorption | H3: 2022-2100 | I3: =46000/10^6 -> 0.046
A4: Young et al. 2023 | B4: y | C4: YD/KS | D4: Journal article | E4: 10.1016/j.oneear.2023.06.004 | F4: Liquid solvent with electrochemical regeneration | G4: Liquid solvent with electrochemical regeneration | H4: 2022-2100 | I4: =960/10^6 -> 0.00096
A5: Young et al. 2023 | B5: y | C5: YD/KS | D5: Journal article | E5: 10.1016/j.oneear.2023.06.004 | F5: Ambient weathering | G5: MgO ambient weathering with regeneration via calcination | H5: 2022-2100 | I5: =1100000/10^6 -> 1.1
A6: Sievert et al. 2024 | B6: y | C6: KS | D6: Journal article | E6: 10.1016/j.joule.2024.02.005 | F6: Liquid solvent | G6: KOH absorption paired with regeneration via Ca looping | H6: 2023-2050 | I6: =500000/10^6 -> 0.5
A7: Sievert et al. 2024 | B7: y | C7: KS | D7: Journal article | E7: 10.1016/j.joule.2024.02.005 | F7: Solid sorbent | G7: Solid sorbent DAC using temperature vacuum swing adsorption | H7: 2023-2050 | I7: =4000/10^6 -> 0.004
A8: Sievert et al. 2024 | B8: y | C8: KS | D8: Journal article | E8: 10.1016/j.joule.2024.02.005 | F8: Ambient weathering | G8: CaO ambient weathering with regeneration via calcination | H8: 2023-2050 | I8: =1000/10^6 -> 0.001
A9: McQueen et al. 2020a | B9: no | C9: YD | D9: Journal article | E9: 10.1021/acs.est.0c00476 | F9: Solid sorbent | G9: Solid sorbent | H9: 2023 | I9: 0.1 | K9: None of key words listed in context of future costs
A10: Sendi et al. 2022 | B10: no | C10: YD | D10: Journal article | E10: 10.1016/j.oneear.2022.09.003 | F10: Solid sorbent | G10: Solid sorbent | H10: 2022 | I10: n/a | K10: None of key words listed in context of future costs | L10: They discuss land use and elec req for 10 Gt CO2/year but they seem to model current costs
A11: Fasihi et al. 2019 | B11: y | C11: KS | D11: Journal article | E11: 10.1016/j.jclepro.2019.03.086 | F11: Liquid solvent | G11: Liquid solvent | H11: 2020-2050 | I11: 1
A12: Fasihi et al. 2019 | B12: y | C12: KS | D12: Journal article | E12: 10.1016/j.jclepro.2019.03.086 | F12: Solid sorbent | G12: Solid sorbent | H12: 2020-2050 | I12: 0.36
A13: Mazzotti et al. 2013 | B13: no | C13: KS | D13: Journal article | E13: 10.1007/s10584-012-0679-y | F13: Liquid solvent | G13: KOH absorption paired with regeneration via Ca looping | H13: 2008/2009 | I13: 1
A14: Zeman 2014 | B14: no | C14: KS | D14: Journal article | E14: 10.1021/es502887y | F14: Liquid solvent | G14: KOH absorption paired with regeneration via Ca looping | H14: 2008/2009 | I14: 1 | AL14: For data points before standardization, adjust Zeman 2014 values for other energy sources to 2023$
A15: Prats-Salvado et al. 2024 | B15: no | C15: KS | D15: Journal article | E15: 10.1021/acs.est.3c08269 | F15: Liquid solvent | G15: Solar thermal powered liquid solvent | H15: 2022 | I15: 1
A16: Prats-Salvado et al. 2024 | B16: no | C16: KS | D16: Journal article | E16: 10.1021/acs.est.3c08269 | F16: Liquid solvent | G16: Conventional: KOH absorption paired with regeneration via Ca looping | H16: 2022 | I16: 1.48
A17: Terlouw et al. 2024 | B17: no | C17: KS | D17: Journal article | E17: 10.1021/acs.est.3c10041 | F17: Solid sorbent | G17: Temperature-vacuum swing adsorption (TVSA) | H17: 2023 | I17: 1
A18: McQueen et al. 2021 | B18: no | C18: YD | D18: Journal article | E18: 10.3389/fclim.2020.618644 | F18: Liquid solvent | H18: 2020 | I18: 1
A19: Datta et al. 2023 | B19: no | C19: KS | D19: Journal article | E19: 10.1021/acs.est.2c05194 | F19: Solid sorbent | G19: Temperature swing adsorption-based DAC | H19: 2023 | I19: =1000/10^6 -> 0.001 | K19: None of key words listed in context of future costs
A20: Datta et al. 2023 | B20: no | C20: KS | D20: Journal article | E20: 10.1021/acs.est.2c05194 | F20: Membrane-based m-DAC | G20: Membrane-based DAC | H20: 2023 | I20: =1000/10^6 -> 0.001
A21: Sinha et al. 2019 | B21: no | D21: Journal article | E21: 10.1002/aic.16607 | F21: Solid sorbent
A22: Simon et al. 2011 | B22: no | C22: YD | D22: Journal article | E22: 10.1016/j.egypro.2011.02.196 | F22: Generic (Solid sorbent referenced) | G22: Generic | H22: 2011 | I22: 1 | K22: None of key words listed in context of future costs | L22: Also kicked out because data is outdated (2011)
A23: Küng et al. 2023 | B23: no | C23: YD | D23: Journal article | E23: 10.1039/d3ee01008b | F23: Liquid solvent | G23: Liquid solvent | H23: 2023 | I23: 1 | K23: Only FOAK and discussion that learning is needed
A24: Küng et al. 2023 | B24: no | C24: YD | D24: Journal article | E24: 10.1039/d3ee01008b | F24: Solid sorbent | G24: Solid sorbent | H24: 2023 | I24: Variable | K24: Only FOAK and discussion that learning is needed
A25: Mostafa et al. 2022 | B25: no | D25: Journal article | E25: 10.1016/j.ccst.2022.100060 | F25: Liquid solvent | G25: NaOH absorption DAC process paired with regeneration via Ca looping | K25: Borderline; Plant capacity: 6.3 million; because of grid emissions only 3.5 Mt CO2/year removed; "large-scale" in title
A26: Keith et al. 2018 | B26: y | C26: KS | D26: Journal article | E26: 10.1016/j.joule.2018.05.006 | F26: Liquid solvent | G26: KOH absorption paired with regeneration via Ca looping | H26: 2016 and Nth kind | I26: 1
A27: Gray et al. 2024 | B27: no | C27: YD | D27: Journal article | E27: 10.1016/j.rser.2024.114552 | F27: Solid sorbent | G27: Solid sorbent | H27: 2024 | I27: 1 | K27: Model first large-scale plant; not 2050 projection
A28: Rosen et al. 2024 | C28: YD | D28: Journal article | E28: 10.1021/acs.energyfuels.4c02202 | F28: Liquid solvent | G28: Absorption with regeneration via chemical looping (ACL) as described by Keith et al.13 (TRL 7) | H28: 2023
A29: Rosen et al. 2024 | C29: YD | D29: Journal article | E29: 10.1021/acs.energyfuels.4c02202 | F29: Liquid solvent with electrochemical regeneration | G29: Absorption with electrochemical regeneration (AEC); carbonate regeneration using a bipolar membrane described by Iizuka et al.53 (TRL 2−3) | H29: 2023
A30: Rosen et al. 2024 | C30: YD | D30: Journal article | E30: 10.1021/acs.energyfuels.4c02202 | F30: Solid sorbent | G30: Temperature-vacuum-swing adsorption (TVSA) with the Wurzbacher et al.69 (TRL 8) | H30: 2023
A31: Rosen et al. 2024 | C31: YD | D31: Journal article | E31: 10.1021/acs.energyfuels.4c02202 | F31: Electro-swing adsorption (ESA) | G31: Electro-swing adsorption (ESA) as described by Voskian and Hatton35 (TRL 1) | H31: 2023
A32: Sabatino et al. 2020 | B32: no | D32: Journal article | E32: 10.1021/acs.iecr.9b05641
A33: McQueen et al. 2020c | B33: no | C33: YD | D33: Journal article | E33: 10.1038/s41467-020-16510-3 | F33: Ambient Weathering | G33: MgO based | H33: 2020 | I33: 64-180 | K33: 64-180 Mt CO2/year removal is huge but no current and future
A34: Lee et al. 2023 | B34: no | C34: KS | D34: Journal article | E34: 10.1016/j.joule.2023.05.016 | F34: Solid sorbent | G34: Solid sorbent DAC via electrically driven temperature swing adsorption (ETSA) | H34: 2023 | I34: unclear
A35: Abanades et al. 2023 | B35: no | C35: YD | D35: Journal article | E35: 10.1016/j.xcrp.2023.101339 | F35: Solid sorbent | G35: CaCO3 based | H35: 2023 | I35: 1
A36: Abanades et al. 2020 | B36: no | C36: YD | D36: Journal article | E36: 10.1039/d0se00094a | F36: Ambient weathering | G36: CaCO3 based | H36: 2020 | I36: 1
A37: Ragipani et al. 2022 | B37: no | C37: YD | D37: Journal article | E37: 10.1021/acssuschemeng.1c07867 | F37: Liquid solvent | H37: 2022 | I37: 0.008
A38: Sinha et al. 2017 | B38: no | D38: Journal article | E38: 10.1021/acs.iecr.6b03887
A39: Pett-Ridge et al. 2024 | B39: y | C39: YD | D39: Report | E39: Roads to Removal – Options for carbon dioxide removal in the US (roads2removal.org) | F39: Solid sorbent | G39: Solid sorbent | H39: 2025-2050 | I39: =1000/10^6 -> 0.001
A40: Pett-Ridge et al. 2024 | B40: y | C40: YD | D40: Report | E40: Roads to Removal – Options for carbon dioxide removal in the US (roads2removal.org) | F40: Liquid solvent | G40: KOH absorption paired with regeneration via Ca looping | H40: 2025-2050 | I40: 1
A41: NETL/Valentine 2022a | B41: no | C41: KS | D41: Report | E41: DirectAirCaptureCaseStudiesSolventSystem_083122.pdf (doe.gov) | F41: Liquid solvent | G41: KOH absorption paired with regeneration via Ca looping | H41: 2022 | I41: (a) 903,970 tCO2/year removed (b) 100,000tCO2/year removed
A42: NETL/Valentine 2022b | B42: no | C42: KS | D42: Report | E42: TECHNICAL REPORT TEMPLATE AND USER GUIDE (doe.gov) | F42: Solid sorbent | G42: monolith-supported sorbent configuration | H42: 2022 | I42: (a) 100,000 (b) 100,000 (c') 1 MtCO2/year net removed
A43: NASEM 2019 | B43: no | C43: KS | D43: Report | E43: https://doi.org/10.17226/25259 | F43: Liquid solvent | G43: KOH absorption paired with regeneration via Ca looping | H43: 2019 | I43: 1000000
A44: NASEM 2019 | B44: no | C44: KS | D44: Report | E44: https://doi.org/10.17226/25259 | F44: Solid sorbent | G44: Solid sorbent | H44: 2019 | I44: 1000000
A45: APS 2011 | B45: no | C45: KS | D45: Report | E45: Direct-Air-Capture-of-CO2-with-Chemicals_snams5.pdf (cloudinary.com) | F45: Liquid solvent | G45: KOH absorption paired with regeneration via Ca looping | H45: end 2008/early 2009
B50: Technology | C50: Cost estimate | D50: 2025 | E50: 2030 | F50: 2035 | G50: 2040 | H50: 2045 | I50: 2050 | J50: 2055 | K50: 2060 | L50: Unit
B51: DACCS | C51: 25th percentile | L51: $/tCO2
C52: 75th percentile | L52: $/tCO2
B53: Synfuels | C53: 25th percentile | L53: $/tCO2
C54: 75th percentile | L54: $/tCO2

Sheet Study Parameters
A1: Reference | B1: Included? | C1: Harmonized by | D1: Type of literature | E1: DOI | F1: DAC Technology | G1: Technology Detail | H1: Timeline | I1: Year Currency | J1: CAPEX Learning Rates (Capital Cost) | K1: OPEX Learning Rates | L1: Cost Type | M1: Cost Range Short Term | N1: Cost Range 2030 | O1: Cost Range 2050 | P1: Unit | Q1: Plant Capacity (Mt CO2/year) | R1: WACC / Discount Rate | S1: Electricity Price Range (EUR/MWh) | T1: Electricity Price Source | U1: Heat Price Range | V1: Heat Price Source | W1: Full load hours | X1: Capacity Factor | Y1: Plant Lifetime [y] | Z1: CO2 Transport and Storage | AA1: Transport cost | AB1: Storage cost | AC1: LCA Methdology | AD1: Data taken from | AE1: Sensitivity Analysis | AF1: Notes | AG1: Harmonization Status | AH1: Net removed cost harmonized | AI1: Request sent to author | AJ1: Answer? | AK1: To do
A2: Young et al. 2023 | B2: y | C2: YD/KS | D2: Journal article | E2: 10.1016/j.oneear.2023.06.004 | F2: Liquid solvent | G2: KOH absorption paired with regeneration via Ca looping | H2: 2022-2100 | I2: 2019 USD | J2: 5-15 | K2: n/a | L2: Net removed cost | M2: 300 - 550 | N2: n/a | O2: 150 - 220 | P2: USD/tCO2 | Q2: 0.98 | R2: 7.5 - 12.5% | S2: 11 - 300 $/MWh | T2: Multiple sources dependent on geographic location | U2: 3 - 114 $/GJ | V2: Prices are based on source (Natural Gas, Geothermal, Solar) and Location | W2: 8,000 (LT) - 8,760 (HT) | X2: 0.9 | Y2: 25 | Z2: Included in net removed cost | AA2: 12.4$/tCO2 | AB2: incl. In transport | AC2: No LCA | AD2: Keith et al. (2018) | AF2: The data for ACL is used from Keith et al.,¹³ AEC from Sabatino et al.,⁵⁴ MgO looping from McQueen et al.,⁶⁸ and the data for TVSA is calculated within their work.⁵¹ | AG2: Completed | AH2: Completed | AI2: 45548 | AK2: Convert to $2023 and connect to master sheet
A3: Young et al. 2023 | B3: y | C3: YD/KS | D3: Journal article | E3: 10.1016/j.oneear.2023.06.004 | F3: Solid sorbent | G3: Solid sorbent DAC using temperature vacuum swing adsorption | H3: 2022-2100 | I3: 2019 USD | J3: 10-19 | K3: n/a | L3: Net removed cost | M3: 1,600 - 2,500 | N3: n/a | O3: 500 - 1,100 | P3: USD/tCO2 | Q3: =46000/10^6 -> 0.046 | R3: 7.5 - 12.5% | S3: 11 - 300 $/MWh | T3: Multiple sources dependent on geographic location | U3: 3 - 114 $/GJ | V3: Prices are based on source (Natural Gas, Geothermal, Solar) and Location | W3: 8,000 (LT) - 8,760 (HT) | X3: 0.9 | Y3: 25 | Z3: Included in net removed cost | AA3: 12.4$/tCO2 | AB3: incl. In transport | AD3: Own modeling | AF3: The data for ACL is used from Keith et al.,¹³ AEC from Sabatino et al.,⁵⁴ MgO looping from McQueen et al.,⁶⁸ and the data for TVSA is calculated within their work.⁵¹ | AG3: Completed | AH3: Completed
A4: Young et al. 2023 | B4: y | C4: YD/KS | D4: Journal article | E4: 10.1016/j.oneear.2023.06.004 | F4: Liquid solvent with electrochemical regeneration | G4: Liquid solvent with electrochemical regeneration | H4: 2022-2100 | I4: 2019 USD | J4: 10-18 | K4: n/a | L4: Net removed cost | M4: 900 - 2,100 | N4: n/a | O4: 200 - 350 | P4: USD/tCO2 | Q4: =960/10^6 -> 0.00096 | R4: 7.5 - 12.5% | S4: 11 - 300 $/MWh | T4: Multiple sources dependent on geographic location | U4: 3 - 114 $/GJ | V4: Prices are based on source (Natural Gas, Geothermal, Solar) and Location | W4: 8,000 (LT) - 8,760 (HT) | X4: 0.9 | Y4: 25 | Z4: Included in net removed cost | AA4: 12.4$/tCO2 | AB4: incl. In transport | AD4: Sabatino et al. 2020 | AF4: The data for ACL is used from Keith et al.,¹³ AEC from Sabatino et al.,⁵⁴ MgO looping from McQueen et al.,⁶⁸ and the data for TVSA is calculated within their work.⁵¹ | AG4: Completed | AH4: Completed
A5: Young et al. 2023 | B5: y | C5: YD/KS | D5: Journal article | E5: 10.1016/j.oneear.2023.06.004 | F5: Ambient weathering | G5: MgO ambient weathering with regeneration via calcination | H5: 2022-2100 | I5: 2019 USD | J5: 5-15 | K5: n/a | L5: Net removed cost | M5: 400 - 500 | N5: n/a | O5: 180 - 250 | P5: USD/tCO2 | Q5: =1100000/10^6 -> 1.1 | R5: 7.5 - 12.5% | S5: 11 - 300 $/MWh | T5: Multiple sources dependent on geographic location | U5: 3 - 114 $/GJ | V5: Prices are based on source (Natural Gas, Geothermal, Solar) and Location | W5: 8,000 (LT) - 8,760 (HT) | X5: 0.9 | Y5: 25 | Z5: Included in net removed cost | AA5: $1.0-4.8/tCO2/km | AB5: incl. In transport | AD5: McQueen et al. (2020c) | AF5: The data for ACL is used from Keith et al.,¹³ AEC from Sabatino et al.,⁵⁴ MgO looping from McQueen et al.,⁶⁸ and the data for TVSA is calculated within their work.⁵¹ | AG5: Completed | AH5: Completed
A6: Sievert et al. 2024 | B6: y | C6: KS | D6: Journal article | E6: 10.1016/j.joule.2024.02.005 | F6: Liquid solvent | G6: KOH absorption paired with regeneration via Ca looping | H6: 2023-2050 | I6: 2022 USD | J6: 8 | K6: 8 | L6: Net removed cost | M6: 521–894 | N6: n/a | O6: 226–544 | P6: USD/tCO2 | Q6: =500000/10^6 -> 0.5 | R6: 0.07 | S6: 39 $/MWh | T6: tracking solar PV with storage | U6: (B) 5.6 $/GJ | V6: natural gas | W6: 8760 | X6: 0.5-0.9 | Y6: 25 | Z6: Included in net removed cost | AA6: $5-12/tCO2 | AB6: $9.74-23.20/tCO2 | AD6: Keith et al. (2018) | AG6: My study | AH6: Completed | AK6: Convert to $2023 and connect to master sheet
A7: Sievert et al. 2024 | B7: y | C7: KS | D7: Journal article | E7: 10.1016/j.joule.2024.02.005 | F7: Solid sorbent | G7: Solid sorbent DAC using temperature vacuum swing adsorption | H7: 2023-2050 | I7: 2022 USD | J7: 12 | K7: 12 | L7: Net removed cost | M7: 1180–1392 | N7: n/a | O7: 281–579 | P7: USD/tCO2 | Q7: =4000/10^6 -> 0.004 | R7: 0.07 | S7: 39 $/MWh | T7: tracking solar PV with storage | U7: (B) 5.6 $/GJ | V7: n/a | W7: 8760 | X7: 0.75-0.9 | Y7: 25 | Z7: Included in net removed cost | AA7: $5-12/tCO2 | AB7: $9.74-23.20/tCO2 | AD7: Young et al. (2023) | AG7: My study | AH7: Completed | AK7: Convert to $2023 and connect to master sheet
A8: Sievert et al. 2024 | B8: y | C8: KS | D8: Journal article | E8: 10.1016/j.joule.2024.02.005 | F8: Ambient weathering | G8: CaO ambient weathering with regeneration via calcination | H8: 2023-2050 | I8: 2022 USD | J8: 14 | K8: 14 | L8: Net removed cost | M8: 2153–2874 | N8: n/a | O8: 230–835 | P8: USD/tCO2 | Q8: =1000/10^6 -> 0.001 | R8: 0.07 | S8: 39 $/MWh | T8: tracking solar PV with storage | U8: (B) 5.6 $/GJ | V8: n/a | W8: 8760 | X8: 0.5-0.9 | Y8: 25 | Z8: Included in net removed cost | AA8: $5-12/tCO2 | AB8: $9.74-23.20/tCO2 | AD8: McQueen et al. (2020c); only partially | AG8: My study | AH8: Completed | AK8: Convert to $2023 and connect to master sheet
A9: McQueen et al. 2020a | B9: y | C9: YD | D9: Journal article | E9: 10.1021/acs.est.0c00476 | F9: Solid sorbent | G9: Solid sorbent | H9: 2023 | I9: 2022 USD | J9: 9-25 | K9: n/a | L9: Levelized cost of capture | M9: 233 - 700 | N9: n/a | O9: n/a | P9: USD/tCO2 | Q9: 0.1 | R9: 12.5% | S9: 30 - 60 $/MWh | T9: United States grid | U9: 2.8 - 3.9 $/GJ | V9: Not specified | W9: 7920 | X9: 0.9 | Y9: 10 | Z9: Included in net removed cost | AA9: $10/tCO2 | AB9: $10/tCO2 | AC9: Electricity | AD9: Own Modelling | AE9: None | AG9: Completed
A10: Sendi et al. 2022 | B10: y | C10: YD | D10: Journal article | E10: 10.1016/j.oneear.2022.09.003 | F10: Solid sorbent | G10: Solid sorbent | H10: 2022 | I10: 2022 USD | J10: n/a | K10: n/a | L10: Net removed cost | M10: 195 - 720 | N10: n/a | O10: n/a | P10: USD/tCO2 | Q10: n/a | R10: 5-21% | S10: 0 - 100$/MWh | T10: Not specified | U10: 0-50 $/MWh | V10: Not specified | W10: Not specified | X10: 0.9 | Y10: 25 | Z10: Not included in CO2 avoided | AA10: n/a | AB10: n/a | AC10: No LCA | AD10: Own Modelling | AE10: None | AG10: Completed | AI10: 45552 | AJ10: Received Inputs
A11: Fasihi et al. 2019 | B11: y | C11: KS | D11: Journal article | E11: 10.1016/j.jclepro.2019.03.086 | F11: Liquid solvent | G11: Liquid solvent | H11: 2020-2050 | I11: 2018 EUR | J11: 10% conservative;15% base case | K11: 0.03 | L11: Levelized cost of capture | M11: 268 | N11: n/a | O11: €54-71 | P11: EUR/tCO2 | Q11: 1 | R11: 0.07 | S11: 50 €/MWhel | T11: Not specified | U11: 25 €/MWhth (900°C) | V11: Not specified | W11: 8000 | Y11: 2020: 25y; 2030: 30y; beyond 2030: 30y | Z11: Not included | AG11: Completed | AH11: Completed | AI11: 45546 | AK11: Convert to $2023 and connect to master sheet
A12: Fasihi et al. 2019 | B12: y | C12: KS | D12: Journal article | E12: 10.1016/j.jclepro.2019.03.086 | F12: Solid sorbent | G12: Solid sorbent | H12: 2020-2050 | I12: 2018 EUR | J12: 10% conservative;15% base case | K12: 0.037 | L12: Levelized cost of capture | M12: 222 | N12: n/a | O12: €38-54 | P12: EUR/tCO2 | Q12: 0.36 | R12: 0.07 | S12: 50 €/MWhel | T12: Not specified | U12: 20€/MWhth (<100°C) | V12: Not specified | W12: 8000 | Y12: 2020: 20y; 2030: 25y; beyond 2030: 30y | Z12: Not included | AG12: Completed | AH12: Completed
A13: Mazzotti et al. 2013 | B13: y | C13: KS | D13: Journal article | E13: 10.1007/s10584-012-0679-y | F13: Liquid solvent | G13: KOH absorption paired with regeneration via Ca looping | H13: 2008/2009 | I13: 2008 USD | J13: n/a | K13: n/a | L13: Cost of CO2 avoided (without transport and storage) | M13: 518-568 | N13: n/a | O13: n/a | P13: USD/tCO2 | Q13: 1 | R13: 0.12 | S13: 71$/MWh | T13: not specified | U13: 5.69$/GJ | V13: Natural gas | W13: 8000 | X13: 0.9 | Y13: 20 | Z13: not included in CO2 avoided | AD13: APS (2011) | AF13: Builds on APS (2011) but changes the cost of absorber and ist energy requirements, and thus the cost of the total system | AG13: Completed
A14: Zeman 2014 | B14: y | C14: KS | D14: Journal article | E14: 10.1021/es502887y | F14: Liquid solvent | G14: KOH absorption paired with regeneration via Ca looping | H14: 2008/2009 | I14: 2008 USD | J14: n/a | K14: n/a | L14: Cost of CO2 avoided (without transport and storage) | M14: 580 | N14: n/a | O14: n/a | P14: USD/tCO2 | Q14: 1 | R14: 0.12 | S14: 71$/MWh | T14: not specified | U14: 5.69$/GJ | V14: Natural gas | W14: 8000 | X14: 0.9 | Y14: 20 | Z14: not included in CO2 avoided | AF14: Connected to APS (2011) and Mazzotti (2013) | AG14: Completed | AK14: Convert to $2023 and connect to master sheet | AL14: For data points before standardization, adjust Zeman 2014 values for other energy sources to 2023$
A15: Prats-Salvado et al. 2024 | B15: y | C15: KS | D15: Journal article | E15: 10.1021/acs.est.3c08269 | F15: Liquid solvent | G15: Solar thermal powered liquid solvent | H15: 2022 | I15: 2022 USD | J15: n/a | K15: n/a | L15: Net removed cost | M15: 256-325 | N15: n/a | O15: n/a | P15: USD/tCO2 | Q15: 1 | R15: 0.042 | S15: 106.1-170.15$/MWh | T15: not specified | U15: 32-51$/MWh | V15: Solar thermal | X15: 0.9 | Y15: 25 | Z15: Storage yes, Transport no | AA15: n/a | AB15: 10$/tCO2 | AD15: Keith et al. (2018) | AG15: Completed | AI15: 45546 | AK15: Convert to $2023 and connect to master sheet
A16: Prats-Salvado et al. 2024 | B16: y | C16: KS | D16: Journal article | E16: 10.1021/acs.est.3c08269 | F16: Liquid solvent | G16: Conventional: KOH absorption paired with regeneration via Ca looping | H16: 2022 | I16: 2022 USD | J16: n/a | K16: n/a | L16: Net removed cost | M16: 310-435 | N16: n/a | O16: n/a | P16: USD/tCO2 | Q16: 1.48 | R16: 0.042 | S16: n/a | T16: not specified | U16: 7.6-23.6$/GJ_LHV | V16: Natural gas | X16: 0.9 | Y16: 25 | Z16: Storage yes, Transport no | AA16: n/a | AB16: 10$/tCO2 | AD16: Keith et al. (2018) | AG16: Completed | AI16: 45546 | AK16: Convert to $2023 and connect to master sheet
A17: Terlouw et al. 2024 | B17: y | C17: KS | D17: Journal article | E17: 10.1021/acs.est.3c10041 | F17: Solid sorbent | G17: Temperature-vacuum swing adsorption (TVSA) | H17: 2023 | I17: 2023 EUR | J17: n/a | K17: n/a | L17: Net removed cost | M17: 750-970 | N17: n/a | O17: n/a | P17: EUR/tCO2 | Q17: 1 | R17: 0.051 | S17: 42-113$/MWh | T17: grid power and waste heat | U17: 30$/MWh | V17: not specified | W17: 8000 | Y17: 20 | Z17: Included in net removed cost | AA17: 21€/tCO2 | AB17: 11€/tCO2 | AG17: Completed | AI17: 45547 | AJ17: He is reviewing it
A18: McQueen et al. 2021 | C18: YD | D18: Journal article | E18: 10.3389/fclim.2020.618644 | F18: Liquid solvent | H18: 2020 | I18: 2019 USD | J18: n/a | K18: n/a | L18: Net removed cost | M18: 225-1731 | N18: n/a | O18: n/a | P18: USD/tCO2 | Q18: 1 | R18: 0.085 | S18: 100-190$/MWh | T18: Multiple sources modelled from scratch, including battery storage | U18: 3.25$/GJ | V18: natural gas | W18: 7884 | X18: 0.9 | Y18: 20 | Z18: Not included | AA18: n/a | AB18: n/a | AC18: Accounts for leakeage and methan emissions using global warming potential | AD18: APS (2011), Mazzotti (2013), Zeman (2014), Keith (2018) | AE18: WACC, Plant Lifetime, and Natural Gas price | AF18: Build on APS (2011), Mazzotti (2013), Zeman (2014), Keith (2018) | AG18: Completed
A19: Datta et al. 2023 | B19: y | C19: KS | D19: Journal article | E19: 10.1021/acs.est.2c05194 | F19: Solid sorbent | G19: Temperature swing adsorption-based DAC | H19: 2023 | I19: 2022 USD | J19: n/a | K19: n/a | L19: Levelized cost of capture | M19: 227$/tCO2 | N19: n/a | O19: n/a | P19: USD/tCO2 | Q19: =1000/10^6 -> 0.001 | R19: 0.12 | S19: 35$/MWh | T19: New onshore wind energy generation resoues entering service in 2025 | U19: n/a | V19: n/a | X19: 1 | Y19: 20 | Z19: Transport neglected; Storage included | AB19: 10$/tCO2 | AF19: Storage cost is included in cost of compression, injection, recycling, and storage per tCO2 $40 | AG19: Completed
A20: Datta et al. 2023 | B20: y | C20: KS | D20: Journal article | E20: 10.1021/acs.est.2c05194 | F20: Membrane-based m-DAC | G20: Membrane-based DAC | H20: 2023 | I20: 2022 USD | J20: n/a | K20: n/a | L20: Levelized cost of capture | M20: 91-95$/tCO2 | N20: n/a | O20: n/a | P20: USD/tCO2 | Q20: =1000/10^6 -> 0.001 | R20: 0.12 | S20: 35$/MWh | T20: New onshore wind energy generation resoues entering service in 2025 | U20: n/a | V20: n/a | X20: 1 | Y20: 20 | Z20: Transport neglected; Storage included | AB20: 10$/tCO2 | AF20: Storage cost is included in cost of compression, injection, recycling, and storage per tCO2 $40 | AG20: Completed
A21: Sinha et al. 2019 | B21: no | D21: Journal article | E21: 10.1002/aic.16607 | F21: Solid sorbent | AF21: Input parameters to calculate OPEX are missing; reached out to Prof Matthew Realff | AG21: Will exclude
A22: Simon et al. 2011 | B22: y | C22: YD | D22: Journal article | E22: 10.1016/j.egypro.2011.02.196 | F22: Generic (Solid sorbent referenced) | G22: Generic | H22: 2011 | I22: 2011 USD | J22: n/a | K22: n/a | L22: Cost of capture, transport, storage | M22: 300 - 865 | N22: n/a | O22: n/a | P22: USD/tCO2 | Q22: 1 | R22: 0.1 | S22: 74-211$/MWh | T22: Not specified | U22: 2-8$/GJ | V22: n/a | W22: 7900 | X22: 0.9 | Y22: 30 | Z22: not included in CO2 avoided | AA22: n/a | AB22: n/a | AC22: No LCA | AD22: Own Modelling | AE22: Tower, Thermal Efficiency | AG22: Completed
A23: Küng et al. 2023 | B23: y | C23: YD | D23: Journal article | E23: 10.1039/d3ee01008b | F23: Liquid solvent | G23: Liquid solvent | H23: 2023 | I23: 2022 USD | J23: n/a | K23: n/a | L23: Net removed cost | M23: 371 - 2750 | N23: n/a | O23: n/a | P23: USD/tCO2 | Q23: 1 | R23: 7.5-12.5% | S23: 68-147$/MWh | T23: NREL Wind LCA(https://www.nrel. gov/docs/fy13osti/57131.pdf),https://www.gov.uk/government/statisticaldata-sets/international-industrial-energy-prices. | U23: 1-4$/MWh | V23: natural gas | W23: 7884 | X23: 0.9 | Y23: 20 | Z23: excluded | AA23: n/a | AB23: n/a | AC23: Global Warming Potential | AE23: No, but multiple scenarios | AF23: Uploaded with code | AG23: Completed | AI23: 18.09.2024; 26.09.24 | AJ23: Python model received from author
A24: Küng et al. 2023 | B24: y | C24: YD | D24: Journal article | E24: 10.1039/d3ee01008b | F24: Solid sorbent | G24: Solid sorbent | H24: 2023 | I24: 2022 USD | J24: n/a | K24: n/a | L24: Net removed cost | M24: 243 - 1750 | N24: n/a | O24: n/a | P24: USD/tCO2 | Q24: Variable | R24: 7.5-12.5% | S24: 68-147$/MWh | T24: NREL Wind LCA(https://www.nrel. gov/docs/fy13osti/57131.pdf),https://www.gov.uk/government/statisticaldata-sets/international-industrial-energy-prices. | U24: 1-4$/MWh | V24: natural gas | W24: 7884 | X24: 0.9 | Y24: 40 | Z24: excluded | AA24: n/a | AB24: n/a | AC24: Global Warming Potential | AE24: No, but multiple scenarios | AF24: Uploaded with code | AG24: Completed | AI24: 18.09.2024; 26.09.24 | AJ24: Python model received from author
A25: Mostafa et al. 2022 | D25: Journal article | E25: 10.1016/j.ccst.2022.100060 | F25: Liquid solvent | G25: NaOH absorption DAC process paired with regeneration via Ca looping | AF25: Reached out to Mostafa to see if he can share excel model | AG25: Awaiting reply | AI25: 18.09.2024; 26.09.24 | AK25: Has three scenarios which should be included
A26: Keith et al. 2018 | B26: y | C26: KS | D26: Journal article | E26: 10.1016/j.joule.2018.05.006 | F26: Liquid solvent | G26: KOH absorption paired with regeneration via Ca looping | H26: 2016 and Nth kind | I26: 2016 USD | J26: n/a | K26: n/a | L26: Levelized cost of capture | M26: 168-232 | N26: n/a | O26: 94-170 (Nth financials) | P26: USD/tCO2 | Q26: 1 | R26: 5.56% and 11.72% | S26: 30-60$/MWh | T26: not specified | U26: 3$/GJ | V26: natural gas | X26: 0.9 | Y26: 25 | Z26: not included | AF26: Keith doesn't account for the indirect emissions (this is expressed as cost per ton of captured CO2, not removed). Our Figure 7 showed certain indirect emissions associated to gas extraction, but those are for Scenario A.In the Scenario C both the NG extraction and the electricity source impact the indirect emissions. | AG26: Completed | AH26: Completed | AK26: Convert to $2023 and connect to master sheet; currently $2016
A27: Gray et al. 2024 | B27: y | C27: YD | D27: Journal article | E27: 10.1016/j.rser.2024.114552 | F27: Solid sorbent | G27: Solid sorbent | H27: 2024 | I27: 2023 EUR | J27: n/a | K27: n/a | L27: Levelized cost of capture | M27: 1014 | N27: n/a | O27: n/a | P27: EUR/tCO2 | Q27: 1 | R27: 0.06 | S27: 40$/MWh | T27: Norwegian grid price average 2023 | U27: n/a | V27: Heat Pump | W27: 8760 | X27: 1 | Y27: 25 | Z27: Included in net removed cost | AA27: n/a | AB27: n/a | AC27: No LCA | AF27: The model is quite simplified but has all inputs we will standardize | AG27: Completed | AH27: Completed | AK27: Convert to $2023 and connect to master sheet. Currently €2023
A28: Rosen et al. 2024 | C28: YD | D28: Journal article | E28: 10.1021/acs.energyfuels.4c02202 | F28: Liquid solvent | G28: Absorption with regeneration via chemical looping (ACL) as described by Keith et al.13 (TRL 7) | H28: 2023 | I28: 2019 USD | L28: Levelized cost of capture | P28: USD/tCO2 | R28: 0.07 | Y28: 20 | Z28: not included | AD28: Keith et al. (2018) | AF28: Electrochemical | AG28: Awaiting reply | AI28: 18.09.2024; 26.09.24 | AJ28: On holiday until October 14 | AK28: Reached out and asked for model/ more detailed data information
A29: Rosen et al. 2024 | C29: YD | D29: Journal article | E29: 10.1021/acs.energyfuels.4c02202 | F29: Liquid solvent with electrochemical regeneration | G29: Absorption with electrochemical regeneration (AEC); carbonate regeneration using a bipolar membrane described by Iizuka et al.53 (TRL 2−3) | H29: 2023 | I29: 2019 USD | L29: Levelized cost of capture | P29: USD/tCO2 | R29: 0.07 | Y29: 20 | Z29: not included | AD29: Iizuka et. al. | AF29: Electrochemical | AG29: Awaiting reply | AI29: 18.09.2024; 26.09.24 | AJ29: On holiday until October 14 | AK29: Reached out and asked for model/ more detailed data information
A30: Rosen et al. 2024 | C30: YD | D30: Journal article | E30: 10.1021/acs.energyfuels.4c02202 | F30: Solid sorbent | G30: Temperature-vacuum-swing adsorption (TVSA) with the Wurzbacher et al.69 (TRL 8) | H30: 2023 | I30: 2019 USD | L30: Levelized cost of capture | P30: USD/tCO2 | R30: 0.07 | Y30: 20 | Z30: not included | AD30: Wurzbacher et al. | AF30: Electrochemical | AG30: Awaiting reply | AI30: 18.09.2024; 26.09.24 | AJ30: On holiday until October 14 | AK30: Reached out and asked for model/ more detailed data information
A31: Rosen et al. 2024 | C31: YD | D31: Journal article | E31: 10.1021/acs.energyfuels.4c02202 | F31: Electro-swing adsorption (ESA) | G31: Electro-swing adsorption (ESA) as described by Voskian and Hatton35 (TRL 1) | H31: 2023 | I31: 2019 USD | L31: Levelized cost of capture | P31: USD/tCO2 | R31: 0.07 | Y31: 20 | Z31: not included | AD31: Voskian and Hatton | AF31: Electrochemical | AG31: Awaiting reply | AI31: 18.09.2024; 26.09.24 | AJ31: On holiday until October 14 | AK31: Reached out and asked for model/ more detailed data information
A32: Sabatino et al. 2020 | D32: Journal article | E32: 10.1021/acs.iecr.9b05641 | AF32: Electrochemical | AG32: Will exclude | AI32: 18.09.2024; 26.09.24 | AK32: Reached out and asked for model/ more detailed data information
A33: McQueen et al. 2020c | C33: YD | D33: Journal article | E33: 10.1038/s41467-020-16510-3 | F33: Ambient Weathering | G33: MgO based | H33: 2020 | I33: 2019 USD | J33: n/a | K33: n/a | L33: Levelized cost of capture | M33: 45-150 | N33: 43-148 | O33: n/a | P33: USD/tCO2 | Q33: 64-180 | R33: 4-11% | S33: 8-16.7$/GJ | T33: US Grid | U33: 3.5$/GJ | V33: natural gas | W33: n/a | X33: 0.9 | Y33: 20 | Z33: not included | AA33: n/a | AB33: n/a | AC33: n/a | AG33: Completed
A34: Lee et al. 2023 | C34: KS | D34: Journal article | E34: 10.1016/j.joule.2023.05.016 | F34: Solid sorbent | G34: Solid sorbent DAC via electrically driven temperature swing adsorption (ETSA) | H34: 2023 | I34: 2022 USD | J34: n/a | K34: n/a | L34: Levelized cost of capture | M34: 160 | N34: n/a | O34: n/a | P34: USD/tCO2 | Q34: unclear | R34: n/a | S34: 0.03 $/kWh | T34: Wind energy | U34: not relevant | V34: not relevant | W34: n/a | X34: n/a | Y34: 10 | Z34: not included | AF34: Not levelized cost but rather cost of capture calculated | AG34: Completed | AI34: 45559
A35: Abanades et al. 2023 | C35: YD | D35: Journal article | E35: 10.1016/j.xcrp.2023.101339 | F35: Solid sorbent | G35: CaCO3 based | H35: 2023 | I35: 2023 USD | J35: n/a | K35: n/a | L35: Levelized cost of capture | M35: 134-256 | N35: n/a | O35: n/a | P35: USD/tCO2 | Q35: 1 | R35: 5-10% | S35: 50-68$/MWh | T35: IEA | U35: 2.2-5.3$/GJ | V35: IEA | W35: 8760 | X35: 0.9 | Y35: 30 | Z35: Included | AA35: 5-20$/tCO2 | AC35: n/a | AD35: Own Modelling, Keith 2018 | AE35: No | AG35: Completed
A36: Abanades et al. 2020 | C36: YD | D36: Journal article | E36: 10.1039/d0se00094a | F36: Ambient weathering | G36: CaCO3 based | H36: 2020 | I36: 2020 USD | J36: n/a | K36: n/a | L36: Levelized cost of capture | M36: 138-331 | N36: n/a | O36: n/a | P36: USD/tCO2 | Q36: 1 | R36: 0.1088 | S36: 9$/GJ | T36: not specified | U36: 2-10$/GJ | V36: Not specified | W36: 8760 | X36: 0.9 | Y36: n/a | Z36: Included | AA36: 5-15$/tCO2 | AC36: n/a | AD36: Own Modelling, Keith 2018 | AE36: No | AG36: Completed
A37: Ragipani et al. 2022 | C37: YD | D37: Journal article | E37: 10.1021/acssuschemeng.1c07867 | F37: Liquid solvent | H37: 2022 | I37: 2019 USD | J37: n/a | K37: n/a | L37: Levelized cost of capture | M37: 121-140 | N37: n/a | O37: n/a | P37: USD/tCO2 | Q37: 0.008 | R37: 0.0556 | S37: 71$/MWh | T37: Not specified | U37: not relevant | V37: n/a | W37: 7884 | X37: 0.9 | Y37: 25 | Z37: not included | AA37: n/a | AB37: n/a | AC37: n/a | AD37: Own Modelling | AE37: No | AG37: Completed
A38: Sinha et al. 2017 | D38: Journal article | E38: 10.1021/acs.iecr.6b03887
A39: Pett-Ridge et al. 2024 | C39: YD | D39: Report | E39: Roads to Removal – Options for carbon dioxide removal in the US (roads2removal.org) | F39: Solid sorbent | G39: Solid sorbent | H39: 2025-2050 | I39: 2024 USD | J39: 10-12% | K39: n/a | L39: Net removed cost | M39: 246-566 | N39: n/a | O39: 127-231 | P39: USD/tCO2 | Q39: =1000/10^6 -> 0.001 | R39: 12.5% | S39: 60-309$/MWh | T39: Grid | U39: $2.9/GJ | V39: natural gas | W39: n/a | X39: 0.9 | Y39: 20 | Z39: Included in net removed cost | AA39: 7.75$/tCO2 | AB39: 10$/tCO2 | AD39: McQueen et. al., 2020 | AE39: No | AF39: Modelled on McQueen et. al. 2020 and Keith et.al, 2018 | AG39: Completed
A40: Pett-Ridge et al. 2024 | C40: YD | D40: Report | E40: Roads to Removal – Options for carbon dioxide removal in the US (roads2removal.org) | F40: Liquid solvent | G40: KOH absorption paired with regeneration via Ca looping | H40: 2025-2050 | I40: 2024 USD | J40: 10-12% | K40: n/a | L40: Net removed cost | M40: 193-331 | N40: n/a | O40: 124 | P40: USD/tCO2 | Q40: 1 | R40: 12.5% | S40: 60-309$/MWh | T40: Grid | U40: $2.9/GJ | V40: natural gas | W40: n/a | X40: 0.9 | Y40: 20 | Z40: Included in net removed cost | AA40: 7.75$/tCO2 | AB40: 10$/tCO2 | AD40: Keith et.al, 2018 | AE40: No | AF40: Modelled on Keith et.al, 2018 | AG40: Completed
A41: NETL/Valentine 2022a | B41: y | C41: KS | D41: Report | E41: DirectAirCaptureCaseStudiesSolventSystem_083122.pdf (doe.gov) | F41: Liquid solvent | G41: KOH absorption paired with regeneration via Ca looping | H41: 2022 | I41: 2019 USD | J41: n/a | K41: n/a | L41: Net removed cost | M41: (a) 293$/tCO2 (903,970 tCO2/year removed) (b) 468$/tCO2 (100000tCO2/year removed) | N41: n/a | O41: n/a | P41: USD/tCO2 | Q41: (a) 903,970 tCO2/year removed (b) 100,000tCO2/year removed | S41: n/a | T41: n/a | U41: 4.42$/MMBtu | V41: natural gas | X41: 85% (sensitivity: 0.3 - 0.95) | Y41: not clear | Z41: included | AA41: 15.2-15.6 for transport and storage | AC41: n/a | AD41: Keith et.al. 2018 | AE41: +/-50 percent uncertainty present in the capital cost estimate; separate sensitivity analysis for capacity factor, system pressure drop, natural gas price, solvent makeup rate, solvent cost, capture fraction, calciner natural gas requirement, financial assumptions (fixed charge rate [FCR]) | AF41: Most sub-systems were modeled directly from Carbon Engineering (CE) process data (Keith et al. (2018); [3] vendor quotes and engineering, procurement, and construction industrial experience were used to model the balance of plant. Independent operating and capital cost estimates based on commercially available technology from reputable suppliers were developed by Black & Veatch using their in-house cost estimating references. The capital cost estimates represent an AACE International (AACE) Class 5 estimate, with an uncertainty range of +/-50 percent. Sensitivity | AG41: Completed
A42: NETL/Valentine 2022b | B42: y | C42: KS | D42: Report | E42: TECHNICAL REPORT TEMPLATE AND USER GUIDE (doe.gov) | F42: Solid sorbent | G42: monolith-supported sorbent configuration | H42: 2022 | I42: 2019 USD | J42: n/a | K42: n/a | L42: Net removed cost | M42: (a)Case 0B $702/tonne ($637/ton) (b) Case 0B-EB $475/tonne ($431/ton) (c) Case 0B $430/tonne ($390/ton) | N42: n/a | O42: n/a | P42: USD/tCO2 | Q42: (a) 100,000 (b) 100,000 (c') 1 MtCO2/year net removed | S42: 60$/MWh | T42: renewable | U42: not relevant | V42: not relevant | X42: 85% (sensitivity: 0.3 - 0.95) | Z42: included | AA42: 23.8-23-9 for transport and storage; 10 for renewable case | AC42: n/a | AE42: +/-50 percent uncertainty present in the capital cost estimate; Sensitivity analysis: include capital cost, natural gas price, sorbent cost, sorbent lifetime, financing assumptions (fixed charge rate), system pressure drop, system capture fraction, sorbent regeneration energy, and a single case addressing CO2 product purity from the adsorber vessels | AG42: Completed
A43: NASEM 2019 | C43: KS | D43: Report | E43: https://doi.org/10.17226/25259 | F43: Liquid solvent | G43: KOH absorption paired with regeneration via Ca looping | H43: 2019 | I43: 2018 USD | J43: n/a | K43: n/a | L43: Net removed cost | M43: 199-357 | N43: n/a | O43: n/a | P43: USD/tCO2 | Q43: 1000000 | R43: 0.1155 | S43: 60$/MWh | T43: not specified | U43: 3.25 | V43: natural gas | X43: not specified | Y43: 30 | Z43: not included | AD43: Keith et al., (2018); Holmes and Keith (2012) | AF43: Modelled based on Holmes and Keith, 2012; and Keith et al. 2018); design “C” configuration, which omits the onsite power island and instead uses grid electricity to supply all electrical work, suitable in regions with available low-carbon electricity. However, the C configuration assumes compression of CO2 to 15 MPa, and compression is not included in the committee’s analysis. Compression results in an energy of 0.48 GJ/tCO2 and cost of $8/tCO2, assuming an electricity cost of $60/MWh—leading to additional emissions of 0.1 Mt CO2 for every Mt CO2 captured, assuming an average grid emissions factor of 744 kgCO2/MWh. | AG43: Completed | AK43: compression is not included in the committee’s analysis. Compression results in an energy of 0.48 GJ/tCO2 and cost of $8/tCO2, assuming an electricity cost of $60/MWh—leading to additional emissions of 0.1 Mt CO2 for every Mt CO2 captured, assuming an average grid emissions factor of 744 kgCO2/MWh.
A44: NASEM 2019 | C44: KS | D44: Report | E44: https://doi.org/10.17226/25259 | F44: Solid sorbent | G44: Solid sorbent | H44: 2019 | I44: 2018 USD | J44: n/a | K44: n/a | L44: Net removed cost | M44: 89-256 | N44: n/a | O44: n/a | P44: USD/tCO2 | Q44: 1000000 | R44: not mentioned | S44: 60$/MWh | T44: solar | U44: 0.65$/GJ | V44: not specified (solar potentially) | X44: not specified | Y44: not specified | Z44: not included | AD44: Own Modelling | AF44: Own modelling | AG44: Completed
A45: APS 2011 | B45: y | C45: KS | D45: Report | E45: Direct-Air-Capture-of-CO2-with-Chemicals_snams5.pdf (cloudinary.com) | F45: Liquid solvent | G45: KOH absorption paired with regeneration via Ca looping | H45: end 2008/early 2009 | I45: 2008 USD | J45: n/a | K45: n/a | L45: Cost of CO2 avoided (without transport and storage) | M45: 610-780$/tCO2 avoided | O45: n/a | R45: 0.12 | S45: 71$/MWh | T45: not specified | U45: 5.69$/GJ | V45: natural gas | W45: not specified | X45: 0.9 | Y45: 20 | Z45: not included in CO2 avoided | AG45: Completed | AK45: Convert to $2023 and connect to master sheet

Sheet Standardization Results
L1: Cost ($/tCO2) | O1: Net removed cost ($/tCO2) | P1: Cost Breakdowns
A2: Reference | B2: Year of Assumptions in Study | C2: DOI | D2: DAC Technology | E2: Technology Detail | F2: Year of Cost Currency | G2: Year of Cost | H2: Currency shown | I2: Study Scenario | J2: Cost type | K2: Cumulative capacity (Mt CO2/year) | L2: Baseline $2023 Any Cost Type | M2: Baseline $2023 Net avoided cost (LCOE and carbon intensity harm) | N2: WACC any cost type Harmonized | O2: Fully Harmonized NET REMOVED COST (incl T&S | P2: Electricity | Q2: CO2 | R2: CAPEX | S2: Other OPEX | T2: Study Type | U2: Plant Location | V2: Production | W2: Notes
A3: Young et al. 2023 | B3: 2022 | C3: ='Study Parameters'!E2 -> 10.1016/j.oneear.2023.06.004 | D3: Liquid solvent | E3: KOH absorption paired with regeneration via Ca looping | F3: 2019 USD | G3: 2019 | H3: USD | I3: Reference | J3: Net removed cost | K3: ='Study Parameters'!Q2 -> 0.98 | L3: ='[1]Young results solar_LS'!$I$2* ((1+Inputs!$C$5) ^ (2023-G3)) -> 564.48965 | O3: ='[1]Inputs and TEA calculations'!$I$2* ((1+Inputs!$C$5) ^ (2023-G3)) -> 414.85426
A4: Young et al. 2023 | B4: 2022 | C4: 10.1016/j.oneear.2023.06.004 | D4: Liquid solvent | E4: KOH absorption paired with regeneration via Ca looping | F4: 2019 USD | G4: 2019 | H4: USD | I4: Low net removed cost | J4: Net removed cost | K4: ='Study Parameters'!Q2 -> 0.98 | L4: ='[1]Young results solar_LS'!$I$3* ((1+Inputs!$C$5) ^ (2023-G4)) -> 387.89988 | O4: ='[1]Inputs and TEA calculations'!$I$3* ((1+Inputs!$C$5) ^ (2023-G4)) -> 342.50358
A5: Young et al. 2023 | B5: 2022 | C5: 10.1016/j.oneear.2023.06.004 | D5: Liquid solvent | E5: KOH absorption paired with regeneration via Ca looping | F5: 2019 USD | G5: 2019 | H5: USD | I5: High net removed cost | J5: Net removed cost | K5: ='Study Parameters'!Q2 -> 0.98 | L5: ='[1]Young results solar_LS'!$I$4* ((1+Inputs!$C$5) ^ (2023-G5)) -> 849.35817 | O5: ='[1]Inputs and TEA calculations'!$I$4* ((1+Inputs!$C$5) ^ (2023-G5)) -> 523.95174
A6: Young et al. 2023 | B6: 2050 | C6: 10.1016/j.oneear.2023.06.004 | D6: Liquid solvent | E6: KOH absorption paired with regeneration via Ca looping | F6: 2019 USD | G6: 2019 | H6: USD | I6: Reference | J6: Net removed cost | K6: 1000 | L6: ='[2]Young results solar_LS'!$I$15* ((1+Inputs!$C$5) ^ (2023-G3)) -> 307.14253 | O6: ='[2]Inputs and TEA calculations'!$I$15* ((1+Inputs!$C$5) ^ (2023-G3)) -> 178.17126
A7: Young et al. 2023 | B7: 2050 | C7: 10.1016/j.oneear.2023.06.004 | D7: Liquid solvent | E7: KOH absorption paired with regeneration via Ca looping | F7: 2019 USD | G7: 2019 | H7: USD | I7: Low net removed cost | J7: Net removed cost | K7: 1000 | L7: ='[2]Young results solar_LS'!$I$16* ((1+Inputs!$C$5) ^ (2023-G3)) -> 162.78469 | O7: ='[2]Inputs and TEA calculations'!$I$16* ((1+Inputs!$C$5) ^ (2023-G3)) -> 115.54375
A8: Young et al. 2023 | B8: 2050 | C8: 10.1016/j.oneear.2023.06.004 | D8: Liquid solvent | E8: KOH absorption paired with regeneration via Ca looping | F8: 2019 USD | G8: 2019 | H8: USD | I8: High net removed cost | J8: Net removed cost | K8: 1000 | L8: ='[2]Young results solar_LS'!$I$17* ((1+Inputs!$C$5) ^ (2023-G3)) -> 659.95769 | O8: ='[2]Inputs and TEA calculations'!$I$17* ((1+Inputs!$C$5) ^ (2023-G3)) -> 330.64194
A9: ='Study Parameters'!A3 -> Young et al. 2023 | B9: 2022 | C9: ='Study Parameters'!E3 -> 10.1016/j.oneear.2023.06.004 | D9: ='Study Parameters'!F3 -> Solid sorbent | E9: ='Study Parameters'!G3 -> Solid sorbent DAC using temperature vacuum swing adsorption | F9: ='Study Parameters'!I3 -> 2019 USD | G9: 2019 | H9: USD | I9: Reference | J9: Net removed cost | K9: ='Study Parameters'!Q3 -> 0.046 | L9: ='[3]Copy of Young results solar_SS'!$I$2* ((1+Inputs!$C$5) ^ (2023-G9)) -> 2531.3605 | O9: ='[3]Inputs and TEA calculations'!$I$2* ((1+Inputs!$C$5) ^ (2023-G9)) -> 2060.1695
A10: Young et al. 2023 | B10: 2022 | C10: 10.1016/j.oneear.2023.06.004 | D10: Solid sorbent | E10: Solid sorbent DAC using temperature vacuum swing adsorption | F10: 2019 USD | G10: 2019 | H10: USD | I10: Low net removed cost | J10: Net removed cost | K10: 0.046 | L10: ='[3]Copy of Young results solar_SS'!$I$3* ((1+Inputs!$C$5) ^ (2023-G10)) -> 1564.9496 | O10: ='[3]Inputs and TEA calculations'!$I$3* ((1+Inputs!$C$5) ^ (2023-G10)) -> 1488.7217
A11: Young et al. 2023 | B11: 2022 | C11: 10.1016/j.oneear.2023.06.004 | D11: Solid sorbent | E11: Solid sorbent DAC using temperature vacuum swing adsorption | F11: 2019 USD | G11: 2019 | H11: USD | I11: High net removed cost | J11: Net removed cost | K11: 0.046 | L11: ='[3]Copy of Young results solar_SS'!$I$4* ((1+Inputs!$C$5) ^ (2023-G11)) -> 3697.1556 | O11: ='[3]Inputs and TEA calculations'!$I$4* ((1+Inputs!$C$5) ^ (2023-G11)) -> 2729.5646
A12: Young et al. 2023 | B12: 2050 | C12: 10.1016/j.oneear.2023.06.004 | D12: Solid sorbent | E12: Solid sorbent DAC using temperature vacuum swing adsorption | F12: 2019 USD | G12: 2019 | H12: USD | I12: Reference | J12: Net removed cost | K12: 1000 | L12: ='[4]Copy of Young results solar_SS'!$I$15* ((1+Inputs!$C$5) ^ (2023-G12)) -> 336.8868 | O12: ='[4]Inputs and TEA calculations'!$I$15* ((1+Inputs!$C$5) ^ (2023-G12)) -> 224.8681
A13: Young et al. 2023 | B13: 2050 | C13: 10.1016/j.oneear.2023.06.004 | D13: Solid sorbent | E13: Solid sorbent DAC using temperature vacuum swing adsorption | F13: 2019 USD | G13: 2019 | H13: USD | I13: Low net removed cost | J13: Net removed cost | K13: 1000 | L13: ='[4]Copy of Young results solar_SS'!$I$16* ((1+Inputs!$C$5) ^ (2023-G13)) -> 175.93259 | O13: ='[4]Inputs and TEA calculations'!$I$16* ((1+Inputs!$C$5) ^ (2023-G13)) -> 118.84522
A14: Young et al. 2023 | B14: 2050 | C14: 10.1016/j.oneear.2023.06.004 | D14: Solid sorbent | E14: Solid sorbent DAC using temperature vacuum swing adsorption | F14: 2019 USD | G14: 2019 | H14: USD | I14: High net removed cost | J14: Net removed cost | K14: 1000 | L14: ='[4]Copy of Young results solar_SS'!$I$17* ((1+Inputs!$C$5) ^ (2023-G14)) -> 879.98761 | O14: ='[4]Inputs and TEA calculations'!$I$17* ((1+Inputs!$C$5) ^ (2023-G14)) -> 519.66873
A15: ='Study Parameters'!A4 -> Young et al. 2023 | B15: 2022 | C15: ='Study Parameters'!E4 -> 10.1016/j.oneear.2023.06.004 | D15: ='Study Parameters'!F4 -> Liquid solvent with electrochemical regeneration | E15: ='Study Parameters'!G4 -> Liquid solvent with electrochemical regeneration | F15: ='Study Parameters'!I4 -> 2019 USD | G15: 2019 | H15: USD | I15: Reference | J15: Net removed cost | K15: ='Study Parameters'!Q4 -> 0.00096 | L15: ='[5]Young results solar_electrochem'!$I$2* ((1+Inputs!$C$5) ^ (2023-G15)) -> 2001.3635 | O15: ='[5]Inputs and TEA calculations'!$I$2* ((1+Inputs!$C$5) ^ (2023-G15)) -> 1308.9151
A16: Young et al. 2023 | B16: 2022 | C16: 10.1016/j.oneear.2023.06.004 | D16: Liquid solvent with electrochemical regeneration | E16: Liquid solvent with electrochemical regeneration | F16: 2019 USD | G16: 2019 | H16: USD | I16: Low net removed cost | J16: Net removed cost | K16: 0.00096 | L16: ='[5]Young results solar_electrochem'!$I$3* ((1+Inputs!$C$5) ^ (2023-G16)) -> 1565.3015 | O16: ='[5]Inputs and TEA calculations'!$I$3* ((1+Inputs!$C$5) ^ (2023-G15)) -> 1185.9076
A17: Young et al. 2023 | B17: 2022 | C17: 10.1016/j.oneear.2023.06.004 | D17: Liquid solvent with electrochemical regeneration | E17: Liquid solvent with electrochemical regeneration | F17: 2019 USD | G17: 2019 | H17: USD | I17: High net removed cost | J17: Net removed cost | K17: 0.00096 | L17: ='[5]Young results solar_electrochem'!$I$4* ((1+Inputs!$C$5) ^ (2023-G17)) -> 2770.1451 | O17: ='[5]Inputs and TEA calculations'!$I$4* ((1+Inputs!$C$5) ^ (2023-G15)) -> 1518.5576
A18: Young et al. 2023 | B18: 2050 | C18: 10.1016/j.oneear.2023.06.004 | D18: Liquid solvent with electrochemical regeneration | E18: Liquid solvent with electrochemical regeneration | F18: 2019 USD | G18: 2019 | H18: USD | I18: Reference | J18: Net removed cost | K18: 1000 | L18: ='[6]Young results solar_electrochem'!$I$15* ((1+Inputs!$C$5) ^ (2023-G17)) -> 978.01181 | O18: ='[6]Inputs and TEA calculations'!$I$2* ((1+Inputs!$C$5) ^ (2023-G18)) -> 998.92902
A19: Young et al. 2023 | B19: 2050 | C19: 10.1016/j.oneear.2023.06.004 | D19: Liquid solvent with electrochemical regeneration | E19: Liquid solvent with electrochemical regeneration | F19: 2019 USD | G19: 2019 | H19: USD | I19: Low net removed cost | J19: Net removed cost | K19: 1000 | L19: ='[6]Young results solar_electrochem'!$I$16* ((1+Inputs!$C$5) ^ (2023-G17)) -> 513.58354 | O19: ='[6]Inputs and TEA calculations'!$I$3* ((1+Inputs!$C$5) ^ (2023-G19)) -> 876.07354
A20: Young et al. 2023 | B20: 2050 | C20: 10.1016/j.oneear.2023.06.004 | D20: Liquid solvent with electrochemical regeneration | E20: Liquid solvent with electrochemical regeneration | F20: 2019 USD | G20: 2019 | H20: USD | I20: High net removed cost | J20: Net removed cost | K20: 1000 | L20: ='[6]Young results solar_electrochem'!$I$17* ((1+Inputs!$C$5) ^ (2023-G17)) -> 2166.1251 | O20: ='[6]Inputs and TEA calculations'!$I$4* ((1+Inputs!$C$5) ^ (2023-G20)) -> 1208.3181
A21: ='Study Parameters'!A5 -> Young et al. 2023 | B21: 2022 | C21: ='Study Parameters'!E5 -> 10.1016/j.oneear.2023.06.004 | D21: ='Study Parameters'!F5 -> Ambient weathering | E21: ='Study Parameters'!G5 -> MgO ambient weathering with regeneration via calcination | F21: ='Study Parameters'!I5 -> 2019 USD | G21: 2019 | H21: USD | I21: Reference | J21: Net removed cost | K21: ='Study Parameters'!Q5 -> 1.1 | L21: ='[7]Copy Young results solar_ambwea'!$I$2* ((1+Inputs!$C$5) ^ (2023-G21)) -> 619.67663 | O21: ='[7]Inputs and TEA calculations'!$I$2* ((1+Inputs!$C$5) ^ (2023-G21)) -> 484.59306
A22: Young et al. 2023 | B22: 2022 | C22: 10.1016/j.oneear.2023.06.004 | D22: Ambient weathering | E22: MgO ambient weathering with regeneration via calcination | F22: 2019 USD | G22: 2019 | H22: USD | I22: Low net removed cost | J22: Net removed cost | K22: 1.1 | L22: ='[7]Copy Young results solar_ambwea'!$I$3* ((1+Inputs!$C$5) ^ (2023-G22)) -> 402.73573 | O22: ='[7]Inputs and TEA calculations'!$I$3* ((1+Inputs!$C$5) ^ (2023-G22)) -> 382.81192
A23: Young et al. 2023 | B23: 2022 | C23: 10.1016/j.oneear.2023.06.004 | D23: Ambient weathering | E23: MgO ambient weathering with regeneration via calcination | F23: 2019 USD | G23: 2019 | H23: USD | I23: High net removed cost | J23: Net removed cost | K23: 1.1 | L23: ='[7]Copy Young results solar_ambwea'!$I$4* ((1+Inputs!$C$5) ^ (2023-G23)) -> 995.17803 | O23: ='[7]Inputs and TEA calculations'!$I$4* ((1+Inputs!$C$5) ^ (2023-G23)) -> 657.89385
A24: Young et al. 2023 | B24: 2050 | C24: 10.1016/j.oneear.2023.06.004 | D24: Ambient weathering | E24: MgO ambient weathering with regeneration via calcination | F24: 2019 USD | G24: 2019 | H24: USD | I24: Reference | J24: Net removed cost | K24: 1000 | L24: ='[8]Copy Young results solar_ambwea'!$I$15* ((1+Inputs!$C$5) ^ (2023-G24)) -> 322.23991 | O24: ='[8]Inputs and TEA calculations'!$I$2* ((1+Inputs!$C$5) ^ (2023-G24)) -> 404.77136
A25: Young et al. 2023 | B25: 2050 | C25: 10.1016/j.oneear.2023.06.004 | D25: Ambient weathering | E25: MgO ambient weathering with regeneration via calcination | F25: 2019 USD | G25: 2019 | H25: USD | I25: Low net removed cost | J25: Net removed cost | K25: 1000 | L25: ='[8]Copy Young results solar_ambwea'!$I$16* ((1+Inputs!$C$5) ^ (2023-G25)) -> 162.24613 | O25: ='[8]Inputs and TEA calculations'!$I$3* ((1+Inputs!$C$5) ^ (2023-G25)) -> 303.01793
A26: Young et al. 2023 | B26: 2050 | C26: 10.1016/j.oneear.2023.06.004 | D26: Ambient weathering | E26: MgO ambient weathering with regeneration via calcination | F26: 2019 USD | G26: 2019 | H26: USD | I26: High net removed cost | J26: Net removed cost | K26: 1000 | L26: ='[8]Copy Young results solar_ambwea'!$I$17* ((1+Inputs!$C$5) ^ (2023-G26)) -> 742.09036 | O26: ='[8]Inputs and TEA calculations'!$I$4* ((1+Inputs!$C$5) ^ (2023-G26)) -> 578.02594
A27: ='Study Parameters'!A6 -> Sievert et al. 2024 | B27: 2022 | C27: ='Study Parameters'!E6 -> 10.1016/j.joule.2024.02.005 | D27: ='Study Parameters'!F6 -> Liquid solvent | E27: ='Study Parameters'!G6 -> KOH absorption paired with regeneration via Ca looping | F27: ='Study Parameters'!I6 -> 2022 USD | G27: 2022 | H27: USD | I27: Reference | J27: Net removed cost | K27: ='Study Parameters'!Q6 -> 0.5 | L27: =[9]LS_summary!$J$2* ((1+Inputs!$C$5) ^ (2022-G27)) -> 635 | O27: 669.94069
A28: Sievert et al. 2024 | B28: 2022 | C28: 10.1016/j.joule.2024.02.005 | D28: Liquid solvent | E28: KOH absorption paired with regeneration via Ca looping | F28: 2022 USD | G28: 2022 | H28: USD | I28: Low net removed cost | J28: Net removed cost | K28: ='Study Parameters'!Q7 -> 0.004 | L28: =[9]LS_summary!$R$2* ((1+Inputs!$C$5) ^ (2022-G28)) -> 527 | O28: 521.31303
A29: Sievert et al. 2024 | B29: 2022 | C29: 10.1016/j.joule.2024.02.005 | D29: Liquid solvent | E29: KOH absorption paired with regeneration via Ca looping | F29: 2022 USD | G29: 2022 | H29: USD | I29: High net removed cost | J29: Net removed cost | K29: ='Study Parameters'!Q8 -> 0.001 | L29: =[9]LS_summary!$B$2* ((1+Inputs!$C$5) ^ (2022-G29)) -> 827 | O29: 894.39776
A30: Sievert et al. 2024 | B30: 2050 | C30: 10.1016/j.joule.2024.02.005 | D30: Liquid solvent | E30: KOH absorption paired with regeneration via Ca looping | F30: 2022 USD | G30: 2022 | H30: USD | I30: Reference | J30: Net removed cost | K30: 1000 | L30: =[9]LS_summary!$J$51* ((1+Inputs!$C$5) ^ (2022-G30)) -> 349 | O30: =[9]LS_summary!$J$51 -> 349
A31: Sievert et al. 2024 | B31: 2050 | C31: 10.1016/j.joule.2024.02.005 | D31: Liquid solvent | E31: KOH absorption paired with regeneration via Ca looping | F31: 2022 USD | G31: 2022 | H31: USD | I31: Low net removed cost | J31: Net removed cost | K31: 1000 | L31: =[9]LS_summary!$R$51* ((1+Inputs!$C$5) ^ (2022-G31)) -> 226 | O31: =[9]LS_summary!$R$51 -> 226
A32: Sievert et al. 2024 | B32: 2050 | C32: 10.1016/j.joule.2024.02.005 | D32: Liquid solvent | E32: KOH absorption paired with regeneration via Ca looping | F32: 2022 USD | G32: 2022 | H32: USD | I32: High net removed cost | J32: Net removed cost | K32: 1000 | L32: =[9]LS_summary!$B$51* ((1+Inputs!$C$5) ^ (2022-G32)) -> 532 | O32: =[9]LS_summary!$B$51 -> 532
A33: ='Study Parameters'!A7 -> Sievert et al. 2024 | B33: 2022 | C33: ='Study Parameters'!E7 -> 10.1016/j.joule.2024.02.005 | D33: ='Study Parameters'!F7 -> Solid sorbent | E33: ='Study Parameters'!G7 -> Solid sorbent DAC using temperature vacuum swing adsorption | F33: ='Study Parameters'!I7 -> 2022 USD | G33: 2022 | H33: USD | I33: Reference | J33: Net removed cost | K33: ='Study Parameters'!Q7 -> 0.004 | L33: =[9]SS_summary!$J$2* ((1+Inputs!$C$5) ^ (2022-G33)) -> 1279 | O33: 1282.3145
A34: Sievert et al. 2024 | B34: 2022 | C34: 10.1016/j.joule.2024.02.005 | D34: Solid sorbent | E34: Solid sorbent DAC using temperature vacuum swing adsorption | F34: 2022 USD | G34: 2022 | H34: USD | I34: Low net removed cost | J34: Net removed cost | K34: 0.004 | L34: =[9]SS_summary!$R$2* ((1+Inputs!$C$5) ^ (2022-G34)) -> 1231 | O34: 1180.0943
A35: Sievert et al. 2024 | B35: 2022 | C35: 10.1016/j.joule.2024.02.005 | D35: Solid sorbent | E35: Solid sorbent DAC using temperature vacuum swing adsorption | F35: 2022 USD | G35: 2022 | H35: USD | I35: High net removed cost | J35: Net removed cost | K35: 0.004 | L35: =[9]SS_summary!$B$2* ((1+Inputs!$C$5) ^ (2022-G35)) -> 1381 | O35: 1392.3243
A36: Sievert et al. 2024 | B36: 2050 | C36: 10.1016/j.joule.2024.02.005 | D36: Solid sorbent | E36: Solid sorbent DAC using temperature vacuum swing adsorption | F36: 2022 USD | G36: 2022 | H36: USD | I36: Reference | J36: Net removed cost | K36: 1000 | L36: =[9]SS_summary!$J$51* ((1+Inputs!$C$5) ^ (2022-G36)) -> 441 | O36: =[9]SS_summary!$J$51 -> 441
A37: Sievert et al. 2024 | B37: 2050 | C37: 10.1016/j.joule.2024.02.005 | D37: Solid sorbent | E37: Solid sorbent DAC using temperature vacuum swing adsorption | F37: 2022 USD | G37: 2022 | H37: USD | I37: Low net removed cost | J37: Net removed cost | K37: 1000 | L37: =[9]SS_summary!$R$51* ((1+Inputs!$C$5) ^ (2022-G37)) -> 308 | O37: ='[9]SS_summary_11$MWh'!$R$51 -> 280
A38: Sievert et al. 2024 | B38: 2050 | C38: 10.1016/j.joule.2024.02.005 | D38: Solid sorbent | E38: Solid sorbent DAC using temperature vacuum swing adsorption | F38: 2022 USD | G38: 2022 | H38: USD | I38: High net removed cost | J38: Net removed cost | K38: 1000 | L38: =[9]SS_summary!$B$51* ((1+Inputs!$C$5) ^ (2022-G38)) -> 702 | O38: =[9]SS_summary!$B$51 -> 702
A39: ='Study Parameters'!A8 -> Sievert et al. 2024 | B39: 2022 | C39: ='Study Parameters'!E8 -> 10.1016/j.joule.2024.02.005 | D39: ='Study Parameters'!F8 -> Ambient weathering | E39: ='Study Parameters'!G8 -> CaO ambient weathering with regeneration via calcination | F39: ='Study Parameters'!I8 -> 2022 USD | G39: 2022 | H39: USD | I39: Reference | J39: Net removed cost | K39: ='Study Parameters'!Q8 -> 0.001 | L39: =[9]CaO_summary!$J$2* ((1+Inputs!$C$5) ^ (2022-G39)) -> 2352 | O39: 2481.348
A40: Sievert et al. 2024 | B40: 2022 | C40: 10.1016/j.joule.2024.02.005 | D40: Ambient weathering | E40: CaO ambient weathering with regeneration via calcination | F40: 2022 USD | G40: 2022 | H40: USD | I40: Low net removed cost | J40: Net removed cost | K40: 0.001 | L40: =[9]CaO_summary!$R$2* ((1+Inputs!$C$5) ^ (2022-G40)) -> 2155 | O40: 2153.1602
A41: Sievert et al. 2024 | B41: 2022 | C41: 10.1016/j.joule.2024.02.005 | D41: Ambient weathering | E41: CaO ambient weathering with regeneration via calcination | F41: 2022 USD | G41: 2022 | H41: USD | I41: High net removed cost | J41: Net removed cost | K41: 0.001 | L41: =[9]CaO_summary!$B$2* ((1+Inputs!$C$5) ^ (2022-G41)) -> 2849 | O41: 2874.32
A42: Sievert et al. 2024 | B42: 2050 | C42: 10.1016/j.joule.2024.02.005 | D42: Ambient weathering | E42: CaO ambient weathering with regeneration via calcination | F42: 2022 USD | G42: 2022 | H42: USD | I42: Reference | J42: Net removed cost | K42: 1000 | L42: =[9]CaO_summary!$J$51* ((1+Inputs!$C$5) ^ (2022-G42)) -> 372 | O42: =[9]CaO_summary!$J$51 -> 372
A43: Sievert et al. 2024 | B43: 2050 | C43: 10.1016/j.joule.2024.02.005 | D43: Ambient weathering | E43: CaO ambient weathering with regeneration via calcination | F43: 2022 USD | G43: 2022 | H43: USD | I43: Low net removed cost | J43: Net removed cost | K43: 1000 | L43: =[9]CaO_summary!$R$51* ((1+Inputs!$C$5) ^ (2022-G43)) -> 318 | O43: ='[9]CaO_summary_11$MWh'!$R$51 -> 260
A44: Sievert et al. 2024 | B44: 2050 | C44: 10.1016/j.joule.2024.02.005 | D44: Ambient weathering | E44: CaO ambient weathering with regeneration via calcination | F44: 2022 USD | G44: 2022 | H44: USD | I44: High net removed cost | J44: Net removed cost | K44: 1000 | L44: =[9]CaO_summary!$B$51* ((1+Inputs!$C$5) ^ (2022-G44)) -> 624 | O44: ='[9]CaO_summary_11$MWh'!$B$51 -> 575
A45: ='Study Parameters'!A9 -> McQueen et al. 2020a | B45: 2023 | C45: ='Study Parameters'!E9 -> 10.1021/acs.est.0c00476 | D45: Solid sorbent | E45: Solid sorbent DAC using temperature vacuum swing adsorption | F45: 2022 USD | G45: 2022 | H45: USD | I45: Base Case | J45: Levelised Cost of Removal | K45: 0.1 | L45: =[10]Baseline!$B$9* ((1+Inputs!$C$5) ^ (2022-G45)) -> 243.19088 | M45: ='[10]Step 1 LCOE - EE'!$B$10 -> 281.46047 | N45: ='[10]Step 2 WACC'!$B$10 -> 253.01246 | O45: ='[10]Step 3 T&S'!$B$10 -> 293.01246
A46: ='Study Parameters'!A9 -> McQueen et al. 2020a | B46: 2023 | C46: ='Study Parameters'!E9 -> 10.1021/acs.est.0c00476 | D46: ='Study Parameters'!F9 -> Solid sorbent | E46: Solid sorbent DAC using temperature vacuum swing adsorption | F46: ='Study Parameters'!I9 -> 2022 USD | G46: 2022 | H46: USD | I46: Geothermal | J46: Levelised Cost of Removal | K46: 0.1 | L46: =[10]Baseline!$B$16* ((1+Inputs!$C$5) ^ (2022-G46)) -> 220.91191 | M46: ='[10]Step 1 LCOE - EE'!$B$18 -> 255.9909 | N46: ='[10]Step 2 WACC'!$B$18 -> 227.3339 | O46: ='[10]Step 3 T&S'!$B$18 -> 267.3339
A47: ='Study Parameters'!A9 -> McQueen et al. 2020a | B47: 2023 | C47: ='Study Parameters'!E9 -> 10.1021/acs.est.0c00476 | D47: ='Study Parameters'!F9 -> Solid sorbent | E47: Solid sorbent DAC using temperature vacuum swing adsorption | F47: ='Study Parameters'!I9 -> 2022 USD | G47: 2022 | H47: USD | I47: Nuclear | J47: Levelised Cost of Removal | K47: 0.1 | L47: =[10]Baseline!$B$23* ((1+Inputs!$C$5) ^ (2022-G47)) -> 252.2929 | M47: ='[10]Step 1 LCOE - EE'!$B$26 -> 291.90515 | N47: ='[10]Step 2 WACC'!$B$26 -> 263.19697 | O47: ='[10]Step 3 T&S'!$B$26 -> 303.19697
A48: ='Study Parameters'!$A$10 -> Sendi et al. 2022 | B48: 2022 | C48: 10.1016/j.oneear.2022.09.003 | D48: Solid sorbent | E48: Solid sorbent | F48: 2022 USD | G48: 2022 | H48: USD | I48: Low - USA | L48: =[11]Baseline!$B$3* ((1+Inputs!$C$5) ^ (2022-G48)) -> 195.79914 | M48: ='[11]Step 1 LCOE - EE'!$B$10 -> 237.9548 | N48: ='[11]Step 2 WACC'!$B$10 -> 238.51244 | O48: ='[11]Step 3 T&S'!$B$3 -> 278.51244
A49: ='Study Parameters'!$A$10 -> Sendi et al. 2022 | B49: 2022 | C49: 10.1016/j.oneear.2022.09.003 | D49: Solid sorbent | E49: Solid sorbent | F49: 2022 USD | G49: 2022 | H49: USD | I49: Low - UK | L49: =[11]Baseline!$B$4* ((1+Inputs!$C$5) ^ (2022-G49)) -> 180.22323 | M49: ='[11]Step 1 LCOE - EE'!$B$11 -> 236.54287 | N49: ='[11]Step 1 LCOE - EE'!$B$11 -> 236.54287 | O49: ='[11]Step 3 T&S'!$B$4 -> 260.17306
A50: ='Study Parameters'!$A$10 -> Sendi et al. 2022 | B50: 2022 | C50: 10.1016/j.oneear.2022.09.003 | D50: Solid sorbent | E50: Solid sorbent | F50: 2022 USD | G50: 2022 | H50: USD | I50: Low - Indonesia | L50: =[11]Baseline!$B$5* ((1+Inputs!$C$5) ^ (2022-G50)) -> 241.93412 | M50: ='[11]Step 1 LCOE - EE'!$B$12 -> 290.12605 | N50: ='[11]Step 1 LCOE - EE'!$B$12 -> 290.12605 | O50: ='[11]Step 3 T&S'!$B$5 -> 334.02175
A51: ='Study Parameters'!$A$10 -> Sendi et al. 2022 | B51: 2022 | C51: 10.1016/j.oneear.2022.09.003 | D51: Solid sorbent | E51: Solid sorbent | F51: 2022 USD | G51: 2022 | H51: USD | I51: Low - Saudi Arabia | L51: =[11]Baseline!$B$6 -> 253.04088 | M51: ='[11]Step 1 LCOE - EE'!$B$13 -> 346.94776 | N51: ='[11]Step 1 LCOE - EE'!$B$13 -> 346.94776 | O51: ='[11]Step 3 T&S'!$B$6 -> 347.52431
A52: ='Study Parameters'!$A$10 -> Sendi et al. 2022 | B52: 2022 | C52: 10.1016/j.oneear.2022.09.003 | D52: Solid sorbent | E52: Solid sorbent | F52: 2022 USD | G52: 2022 | H52: USD | I52: Medium - USA | L52: =[11]Baseline!$C$3* ((1+Inputs!$C$5) ^ (2022-G52)) -> 337.61992 | M52: ='[11]Step 1 LCOE - EE'!$C$10 -> 392.06363 | N52: ='[11]Step 1 LCOE - EE'!$C$10 -> 392.06363 | O52: ='[11]Step 3 T&S'!$C$3 -> 431.20952
A53: ='Study Parameters'!$A$10 -> Sendi et al. 2022 | B53: 2022 | C53: 10.1016/j.oneear.2022.09.003 | D53: Solid sorbent | E53: Solid sorbent | F53: 2022 USD | G53: 2022 | H53: USD | I53: Medium - UK | L53: =[11]Baseline!$C$4* ((1+Inputs!$C$5) ^ (2022-G53)) -> 314.58903 | M53: ='[11]Step 1 LCOE - EE'!$C$11 -> 394.50572 | N53: ='[11]Step 1 LCOE - EE'!$C$11 -> 394.50572 | O53: ='[11]Step 3 T&S'!$C$4 -> 405.58126
A54: ='Study Parameters'!$A$10 -> Sendi et al. 2022 | B54: 2022 | C54: 10.1016/j.oneear.2022.09.003 | D54: Solid sorbent | E54: Solid sorbent | F54: 2022 USD | G54: 2022 | H54: USD | I54: Medium - Indonesia | L54: =[11]Baseline!$C$5* ((1+Inputs!$C$5) ^ (2022-G54)) -> 425.41296 | M54: ='[11]Step 1 LCOE - EE'!$C$12 -> 488.54668 | N54: ='[11]Step 1 LCOE - EE'!$C$12 -> 488.54668 | O54: ='[11]Step 3 T&S'!$C$5 -> 532.88152
A55: ='Study Parameters'!$A$10 -> Sendi et al. 2022 | B55: ='Study Parameters'!H10 -> 2022 | C55: ='Study Parameters'!E10 -> 10.1016/j.oneear.2022.09.003 | D55: ='Study Parameters'!F10 -> Solid sorbent | E55: ='Study Parameters'!G10 -> Solid sorbent | F55: ='Study Parameters'!I10 -> 2022 USD | G55: 2022 | H55: USD | I55: Medium - Saudi Arabia | L55: =[11]Baseline!$C$6* ((1+Inputs!$C$5) ^ (2022-G55)) -> 482.58605 | M55: ='[11]Step 1 LCOE - EE'!$C$13 -> 632.16736 | N55: ='[11]Step 1 LCOE - EE'!$C$13 -> 632.16736 | O55: ='[11]Step 3 T&S'!$C$6 -> 598.00725
A56: ='Study Parameters'!$A$10 -> Sendi et al. 2022 | B56: 2022 | C56: 10.1016/j.oneear.2022.09.003 | D56: Solid sorbent | E56: Solid sorbent | F56: 2022 USD | G56: 2022 | H56: USD | I56: High - USA | L56: =[11]Baseline!$D$3* ((1+Inputs!$C$5) ^ (2022-G56)) -> 488.01437 | M56: ='[11]Step 1 LCOE - EE'!$D$10 -> 556.59092 | N56: ='[11]Step 1 LCOE - EE'!$D$10 -> 556.59092 | O56: ='[11]Step 3 T&S'!$D$3 -> 594.26871
A57: ='Study Parameters'!$A$10 -> Sendi et al. 2022 | B57: 2022 | C57: 10.1016/j.oneear.2022.09.003 | D57: Solid sorbent | E57: Solid sorbent | F57: 2022 USD | G57: 2022 | H57: USD | I57: High - UK | L57: =[11]Baseline!$D$4* ((1+Inputs!$C$5) ^ (2022-G57)) -> 453.60276 | M57: ='[11]Step 1 LCOE - EE'!$D$11 -> 558.56833 | N57: ='[11]Step 1 LCOE - EE'!$D$11 -> 558.56833 | O57: ='[11]Step 3 T&S'!$D$4 -> 556.61505
A58: ='Study Parameters'!$A$10 -> Sendi et al. 2022 | B58: 2022 | C58: 10.1016/j.oneear.2022.09.003 | D58: Solid sorbent | E58: Solid sorbent | F58: 2022 USD | G58: 2022 | H58: USD | I58: High - Indonesia | L58: =[11]Baseline!$D$5* ((1+Inputs!$C$5) ^ (2022-G58)) -> 620.65519 | M58: ='[11]Step 1 LCOE - EE'!$D$12 -> 701.07244 | N58: ='[11]Step 1 LCOE - EE'!$D$12 -> 701.07244 | O58: ='[11]Step 3 T&S'!$D$5 -> 745.92214
A59: ='Study Parameters'!$A$10 -> Sendi et al. 2022 | B59: 2022 | C59: 10.1016/j.oneear.2022.09.003 | D59: Solid sorbent | E59: Solid sorbent | F59: 2022 USD | G59: 2022 | H59: USD | I59: High - Saudi Arabia | L59: =[11]Baseline!$D$6* ((1+Inputs!$C$5) ^ (2022-G59)) -> 724.43465 | M59: ='[11]Step 1 LCOE - EE'!$D$13 -> 934.25436 | N59: ='[11]Step 1 LCOE - EE'!$D$13 -> 934.25436 | O59: ='[11]Step 3 T&S'!$D$6 -> 863.32207
A60: ='Study Parameters'!A11 -> Fasihi et al. 2019 | B60: 2020 | C60: ='Study Parameters'!E11 -> 10.1016/j.jclepro.2019.03.086 | D60: ='Study Parameters'!F11 -> Liquid solvent | E60: ='Study Parameters'!G11 -> Liquid solvent | F60: ='Study Parameters'!I11 -> 2018 EUR | G60: 2018 | H60: USD | I60: Base Case | J60: ='Study Parameters'!L11 -> Levelized cost of capture | K60: 1.5 | L60: ='[12]Base Case LS'!$I$28* ((1+Inputs!$C$5) ^ (2022-G60)) -> 327.72997 | M60: ='[12]Step 1 LCOE LS'!$I$31* ((1+Inputs!$C$5) ^ (2022-G60)) -> 277.94108 | N60: ='[12]Step 2 WACC LS'!$I$31 -> 252.26049 | O60: ='[12]Step 3 T&S LS'!$I$34 -> 289.2143
A61: Fasihi et al. 2019 | B61: 2020 | C61: 10.1016/j.jclepro.2019.03.086 | D61: Liquid solvent | E61: Liquid solvent | F61: 2018 EUR | G61: 2018 | H61: USD | I61: Conservative | J61: Levelized cost of capture | K61: 1.5 | L61: ='[12]Base Case LS'!$D$28* ((1+Inputs!$C$5) ^ (2022-G61)) -> 327.72997 | M61: ='[12]Step 1 LCOE LS'!$D$31* ((1+Inputs!$C$5) ^ (2022-G61)) -> 277.94108 | N61: ='[12]Step 2 WACC LS'!$D$31 -> 252.26049 | O61: ='[12]Step 3 T&S LS'!$D$34 -> 289.2143
A62: Fasihi et al. 2019 | B62: 2050 | C62: 10.1016/j.jclepro.2019.03.086 | D62: Liquid solvent | E62: Liquid solvent | F62: 2018 EUR | G62: 2018 | H62: USD | I62: Base Case | J62: Levelized cost of capture | K62: 15357 | L62: ='[12]Base Case LS'!$L$28* ((1+Inputs!$C$5) ^ (2022-G62)) -> 65.583391 | M62: ='[12]Step 1 LCOE LS'!$L$31* ((1+Inputs!$C$5) ^ (2022-G62)) -> 34.232046 | N62: ='[12]Step 2 WACC LS'!$L$31 -> 31.069148 | O62: ='[12]Step 3 T&S LS'!$L$34 -> 54.165284
A63: Fasihi et al. 2019 | B63: 2050 | C63: 10.1016/j.jclepro.2019.03.086 | D63: Liquid solvent | E63: Liquid solvent | F63: 2018 EUR | G63: 2018 | H63: USD | I63: Conservative | J63: Levelized cost of capture | K63: 7679 | L63: ='[12]Base Case LS'!$G$28* ((1+Inputs!$C$5) ^ (2022-G63)) -> 86.54786 | M63: ='[12]Step 1 LCOE LS'!$G$31* ((1+Inputs!$C$5) ^ (2022-G63)) -> 56.834889 | N63: ='[12]Step 2 WACC LS'!$G$31 -> 51.583582 | O63: ='[12]Step 3 T&S LS'!$G$34 -> 74.679718
A64: ='Study Parameters'!A12 -> Fasihi et al. 2019 | B64: 2020 | C64: ='Study Parameters'!E12 -> 10.1016/j.jclepro.2019.03.086 | D64: ='Study Parameters'!F12 -> Solid sorbent | E64: ='Study Parameters'!G12 -> Solid sorbent | F64: ='Study Parameters'!I12 -> 2018 EUR | G64: 2018 | H64: USD | I64: Base Case | J64: Levelized cost of capture | K64: 1.5 | L64: ='[12]Base Case SS'!$I$28* ((1+Inputs!$C$5) ^ (2022-G64)) -> 272.30053 | M64: ='[12]Step 1 LCOE SS'!$I$31* ((1+Inputs!$C$5) ^ (2022-G64)) -> 281.53878 | N64: ='[12]Step 2 WACC SS'!$I$31 -> 255.52577 | O64: ='[12]Step 3 T&S SS'!$I$34 -> 292.47959
A65: Fasihi et al. 2019 | B65: 2020 | C65: 10.1016/j.jclepro.2019.03.086 | D65: Solid sorbent | E65: Solid sorbent | F65: 2018 EUR | G65: 2018 | H65: USD | I65: Conservative | J65: Levelized cost of capture | K65: 1.5 | L65: ='[12]Base Case SS'!$D$28* ((1+Inputs!$C$5) ^ (2022-G65)) -> 272.30053 | M65: ='[12]Step 1 LCOE SS'!$D$31* ((1+Inputs!$C$5) ^ (2022-G65)) -> 281.53878 | N65: ='[12]Step 2 WACC SS'!$D$31 -> 255.52577 | O65: ='[12]Step 3 T&S SS'!$D$34 -> 292.47959
A66: Fasihi et al. 2019 | B66: 2050 | C66: 10.1016/j.jclepro.2019.03.086 | D66: Solid sorbent | E66: n/a | F66: 2018 EUR | G66: 2018 | H66: USD | I66: Base Case | J66: Levelized cost of capture | K66: 15357 | L66: ='[12]Base Case SS'!$L$28* ((1+Inputs!$C$5) ^ (2022-G66)) -> 47.687621 | M66: ='[12]Step 1 LCOE SS'!$L$31* ((1+Inputs!$C$5) ^ (2022-G66)) -> 67.513183 | N66: ='[12]Step 2 WACC SS'!$L$31 -> 61.275247 | O66: ='[12]Step 3 T&S SS'!$L$34 -> 84.371383
A67: Fasihi et al. 2019 | B67: 2050 | C67: 10.1016/j.jclepro.2019.03.086 | D67: Solid sorbent | E67: n/a | F67: 2018 EUR | G67: 2018 | H67: USD | I67: Conservative | J67: Levelized cost of capture | K67: 7679 | L67: ='[12]Base Case SS'!$G$28* ((1+Inputs!$C$5) ^ (2022-G67)) -> 66.279971 | M67: ='[12]Step 1 LCOE SS'!$G$31* ((1+Inputs!$C$5) ^ (2022-G67)) -> 86.967988 | N67: ='[12]Step 2 WACC SS'!$G$31 -> 78.932509 | O67: ='[12]Step 3 T&S SS'!$G$34 -> 102.02864
A68: ='Study Parameters'!A13 -> Mazzotti et al. 2013 | B68: 2008 | C68: ='Study Parameters'!E13 -> 10.1007/s10584-012-0679-y | D68: ='Study Parameters'!F13 -> Liquid solvent | E68: ='Study Parameters'!G13 -> KOH absorption paired with regeneration via Ca looping | F68: ='Study Parameters'!I13 -> 2008 USD | G68: 2008 | H68: USD | I68: M-250Y Optimization of C_avo | J68: Levelized cost of CO2 avoided (without transport and storage) | K68: ='Study Parameters'!Q13 -> 1 | L68: ='[13]Base Case'!$I$75* ((1+Inputs!$C$5) ^ (2022-G70)) -> 736.05921
A69: Mazzotti et al. 2013 | B69: 2008 | C69: 10.1007/s10584-012-0679-y | D69: Liquid solvent | E69: KOH absorption paired with regeneration via Ca looping | F69: 2008 USD | G69: 2008 | H69: USD | I69: M-500Y Optimization of C_avo | J69: Levelized cost of CO2 avoided (without transport and storage) | K69: 1 | L69: ='[14]Base Case'!$C$58* ((1+Inputs!$C$5) ^ (2022-G71)) -> 814.56687
A70: Mazzotti et al. 2013 | B70: 2008 | C70: 10.1007/s10584-012-0679-y | D70: Liquid solvent | E70: KOH absorption paired with regeneration via Ca looping | F70: 2008 USD | G70: 2008 | H70: USD | I70: M-CC Optimization of C_avo | J70: Levelized cost of CO2 avoided (without transport and storage) | K70: 1 | L70: ='[15]Solar L-DAC'!$G$24* ((1+Inputs!$C$5) ^ (2022-G72)) -> 256.4566
A71: ='Study Parameters'!A14 -> Zeman 2014 | B71: 2008 | C71: ='Study Parameters'!E14 -> 10.1021/es502887y | D71: ='Study Parameters'!F14 -> Liquid solvent | E71: ='Study Parameters'!G14 -> KOH absorption paired with regeneration via Ca looping | F71: ='Study Parameters'!I14 -> 2008 USD | G71: 2008 | H71: USD | I71: Reference | J71: Levelized cost of CO2 avoided (without transport and storage) | K71: ='Study Parameters'!Q14 -> 1 | L71: ='[15]Solar L-DAC'!$H$24* ((1+Inputs!$C$5) ^ (2022-G73)) -> 325.04805
A72: ='Study Parameters'!A15 -> Prats-Salvado et al. 2024 | B72: ='Study Parameters'!H15 -> 2022 | C72: ='Study Parameters'!E15 -> 10.1021/acs.est.3c08269 | D72: ='Study Parameters'!F15 -> Liquid solvent | E72: ='Study Parameters'!G15 -> Solar thermal powered liquid solvent | F72: ='Study Parameters'!I15 -> 2022 USD | G72: 2022 | H72: USD | I72: Chile | J72: ='Study Parameters'!L15 -> Net removed cost | K72: ='Study Parameters'!Q15 -> 1 | L72: =[15]Keith2018_ScenarioA!$D$20* ((1+Inputs!$C$5) ^ (2022-G74)) -> 310.27517
A73: Prats-Salvado et al. 2024 | B73: 2022 | C73: 10.1021/acs.est.3c08269 | D73: Liquid solvent | E73: Solar thermal powered liquid solvent | F73: 2022 USD | G73: 2022 | H73: USD | I73: Portugal | J73: ='Study Parameters'!L16 -> Net removed cost | K73: 1 | L73: =[15]Keith2018_ScenarioA!$E$20* ((1+Inputs!$C$5) ^ (2022-G75)) -> 435.81149
A74: ='Study Parameters'!A16 -> Prats-Salvado et al. 2024 | B74: ='Study Parameters'!H16 -> 2022 | C74: ='Study Parameters'!E16 -> 10.1021/acs.est.3c08269 | D74: ='Study Parameters'!F16 -> Liquid solvent | E74: ='Study Parameters'!G16 -> Conventional: KOH absorption paired with regeneration via Ca looping | F74: ='Study Parameters'!I16 -> 2022 USD | G74: 2022 | H74: USD | I74: US | J74: Net removed cost | K74: ='Study Parameters'!Q16 -> 1.48 | L74: ='[16]Base Case SS'!$E$23* ((1+Inputs!$C$5) ^ (2022-G76)) -> 1052.4287
A75: Prats-Salvado et al. 2024 | B75: 2022 | C75: 10.1021/acs.est.3c08269 | D75: Liquid solvent | E75: Conventional: KOH absorption paired with regeneration via Ca looping | F75: 2022 USD | G75: 2022 | H75: USD | I75: Europe | J75: Net removed cost | K75: 1.48 | L75: ='[16]Base Case SS'!$F$23* ((1+Inputs!$C$5) ^ (2022-G77)) -> 812.9382
A76: ='Study Parameters'!A17 -> Terlouw et al. 2024 | B76: ='Study Parameters'!H17 -> 2023 | C76: ='Study Parameters'!E17 -> 10.1021/acs.est.3c10041 | D76: ='Study Parameters'!F17 -> Solid sorbent | E76: ='Study Parameters'!G17 -> Temperature-vacuum swing adsorption (TVSA) | F76: ='Study Parameters'!I17 -> 2023 EUR | G76: 2023 | H76: USD | I76: Germany grid connected | J76: Net removed cost | K76: 1 | L76: =[17]Baseline!$B$11* ((1+Inputs!$C$5) ^ (2022-G78)) -> 254.43115
A77: Terlouw et al. 2024 | B77: 2023 | C77: 10.1021/acs.est.3c10041 | D77: Solid sorbent | E77: Temperature-vacuum swing adsorption (TVSA) | F77: 2023 EUR | G77: 2023 | H77: USD | I77: Germany grid connected with waste heat | J77: Net removed cost | K77: 1.127554 | L77: =[17]Baseline!$B$15* ((1+Inputs!$C$5) ^ (2022-G79)) -> 349.94165
A78: ='Study Parameters'!A18 -> McQueen et al. 2021 | B78: ='Study Parameters'!H18 -> 2020 | C78: ='Study Parameters'!E18 -> 10.3389/fclim.2020.618644 | D78: ='Study Parameters'!F18 -> Liquid solvent | E78: KOH absorption paired with regeneration via Ca looping | F78: ='Study Parameters'!I18 -> 2019 USD | G78: 2019 | H78: USD | I78: Natural Gas Thermal - GWP excluded - HF | J78: Net removed cost | K78: 1 | L78: =[17]Baseline!$B$12* ((1+Inputs!$C$5) ^ (2022-G80)) -> 400.60217
A79: McQueen et al. 2021 | B79: 2020 | C79: 10.3389/fclim.2020.618644 | D79: Liquid solvent | E79: KOH absorption paired with regeneration via Ca looping | F79: 2019 USD | G79: 2019 | H79: USD | I79: Natural Gas Electric - GWP Excluded - HF | J79: Net removed cost | K79: 1 | L79: =[17]Baseline!$B$16* ((1+Inputs!$C$5) ^ (2022-G81)) -> 881.57371
A80: McQueen et al. 2021 | B80: 2020 | C80: 10.3389/fclim.2020.618644 | D80: Liquid solvent | E80: KOH absorption paired with regeneration via Ca looping | F80: 2019 USD | G80: 2019 | H80: USD | I80: Natural Gas Thermal - GWP Included - HF | J80: Net removed cost | K80: 1 | L80: =[17]Baseline!$B$12* ((1+Inputs!$C$5) ^ (2022-G80)) -> 400.60217
A81: McQueen et al. 2021 | B81: 2020 | C81: 10.3389/fclim.2020.618644 | D81: Liquid solvent | E81: KOH absorption paired with regeneration via Ca looping | F81: 2019 USD | G81: 2019 | H81: USD | I81: Natural Gas Electric - GWP Included - HF | J81: Net removed cost | K81: 1 | L81: =[17]Baseline!$B$16* ((1+Inputs!$C$5) ^ (2022-G81)) -> 881.57371
A82: McQueen et al. 2021 | B82: 2020 | C82: 10.3389/fclim.2020.618644 | D82: Liquid solvent | E82: KOH absorption paired with regeneration via Ca looping | F82: 2019 USD | G82: 2019 | H82: USD | I82: Natural Gas Thermal - GWP excluded - VF | J82: Net removed cost | K82: 1 | L82: =[17]Baseline!$B$26* ((1+Inputs!$C$5) ^ (2022-G82)) -> 463.06098
A83: McQueen et al. 2021 | B83: 2020 | C83: 10.3389/fclim.2020.618644 | D83: Liquid solvent | E83: KOH absorption paired with regeneration via Ca looping | F83: 2019 USD | G83: 2019 | H83: USD | I83: Natural Gas Electric - GWP Excluded - VF | J83: Net removed cost | K83: 1 | L83: =[17]Baseline!$B$30* ((1+Inputs!$C$5) ^ (2022-G83)) -> 558.57147
A84: McQueen et al. 2021 | B84: 2020 | C84: 10.3389/fclim.2020.618644 | D84: Liquid solvent | E84: KOH absorption paired with regeneration via Ca looping | F84: 2019 USD | G84: 2019 | H84: USD | I84: Natural Gas Thermal - GWP Included - VF | J84: Net removed cost | K84: 1 | L84: =[17]Baseline!$B$27* ((1+Inputs!$C$5) ^ (2022-G84)) -> 777.69611
A85: McQueen et al. 2021 | B85: 2020 | C85: 10.3389/fclim.2020.618644 | D85: Liquid solvent | E85: KOH absorption paired with regeneration via Ca looping | F85: 2019 USD | G85: 2019 | H85: USD | I85: Natural Gas Electric - GWP Included - VF | J85: Net removed cost | K85: 1 | L85: =[17]Baseline!$B$31* ((1+Inputs!$C$5) ^ (2022-G85)) -> 2052.1002
A86: ='Study Parameters'!A19 -> Datta et al. 2023 | B86: ='Study Parameters'!H19 -> 2023 | C86: ='Study Parameters'!E19 -> 10.1021/acs.est.2c05194 | D86: ='Study Parameters'!F19 -> Solid sorbent | E86: ='Study Parameters'!G19 -> Temperature swing adsorption-based DAC | F86: ='Study Parameters'!I19 -> 2022 USD | G86: 2022 | H86: USD | I86: Reference | J86: ='Study Parameters'!L19 -> Levelized cost of capture | K86: ='Study Parameters'!Q19 -> 0.001 | L86: ='[18]Base Case SS'!$B$14* ((1+Inputs!$C$5) ^ (2022-G86)) -> 225.16987
A87: ='Study Parameters'!A20 -> Datta et al. 2023 | B87: ='Study Parameters'!H20 -> 2023 | C87: ='Study Parameters'!E20 -> 10.1021/acs.est.2c05194 | D87: ='Study Parameters'!F20 -> Membrane-based m-DAC | E87: ='Study Parameters'!G20 -> Membrane-based DAC | F87: ='Study Parameters'!I20 -> 2022 USD | G87: 2022 | H87: USD | I87: Reference | J87: ='Study Parameters'!L20 -> Levelized cost of capture | K87: ='Study Parameters'!Q20 -> 0.001 | L87: ='[18]Base Case Membrane'!$B$13* ((1+Inputs!$C$5) ^ (2022-G87)) -> 90.328729
A88: Simon et al. 2011 | B88: 2011 | C88: 10.1016/j.egypro.2011.02.196 | D88: Solid sorbent | E88: Generic (Solid sorbent referenced) | F88: 2011 USD | G88: 2011 | H88: USD | I88: Reference - Wind | J88: Cost of capture, transport, storage | K88: 1 | L88: =[19]Baseline!$B$16* ((1+Inputs!$C$5) ^ (2022-G88)) -> 364.39431
A89: Simon et al. 2011 | B89: 2011 | C89: 10.1016/j.egypro.2011.02.196 | D89: Solid sorbent | E89: Generic (Solid sorbent referenced) | F89: 2011 USD | G89: 2011 | H89: USD | I89: Reference - Geothermal | J89: Cost of capture, transport, storage | K89: 1 | L89: =[19]Baseline!$B$17* ((1+Inputs!$C$5) ^ (2022-G89)) -> 355.81578
A90: Simon et al. 2011 | B90: 2011 | C90: 10.1016/j.egypro.2011.02.196 | D90: Solid sorbent | E90: Generic (Solid sorbent referenced) | F90: 2011 USD | G90: 2011 | H90: USD | I90: Reference - Nat. Gas w/o seq | J90: Cost of capture, transport, storage | K90: 1 | L90: =[19]Baseline!$B$18* ((1+Inputs!$C$5) ^ (2022-G90)) -> 979.38998
A91: Simon et al. 2011 | B91: 2011 | C91: 10.1016/j.egypro.2011.02.196 | D91: Solid sorbent | E91: Generic (Solid sorbent referenced) | F91: 2011 USD | G91: 2011 | H91: USD | I91: Reference - Nat. Gas w/seq | J91: Cost of capture, transport, storage | K91: 1 | L91: =[19]Baseline!$B$19* ((1+Inputs!$C$5) ^ (2022-G91)) -> 361.42049
A92: Simon et al. 2011 | B92: 2011 | C92: 10.1016/j.egypro.2011.02.196 | D92: Solid sorbent | E92: Generic (Solid sorbent referenced) | F92: 2011 USD | G92: 2011 | H92: USD | I92: Pessimistic - Wind | J92: Cost of capture, transport, storage | K92: 1 | L92: =[19]Baseline!$B$42* ((1+Inputs!$C$5) ^ (2022-G92)) -> 1280.6053
A93: Simon et al. 2011 | B93: 2011 | C93: 10.1016/j.egypro.2011.02.196 | D93: Solid sorbent | E93: Generic (Solid sorbent referenced) | F93: 2011 USD | G93: 2011 | H93: USD | I93: Pessimistic - Geothermal | J93: Cost of capture, transport, storage | K93: 1 | L93: =[19]Baseline!$B$43* ((1+Inputs!$C$5) ^ (2022-G93)) -> 1299.8366
A94: Simon et al. 2011 | B94: 2011 | C94: 10.1016/j.egypro.2011.02.196 | D94: Solid sorbent | E94: Generic (Solid sorbent referenced) | F94: 2011 USD | G94: 2011 | H94: USD | I94: Pessimistic - Nat. Gas w/o seq | J94: Cost of capture, transport, storage | K94: 1 | L94: =[19]Baseline!$B$44* ((1+Inputs!$C$5) ^ (2022-G94)) -> 3412.5637
A95: Simon et al. 2011 | B95: 2011 | C95: 10.1016/j.egypro.2011.02.196 | D95: Solid sorbent | E95: Generic (Solid sorbent referenced) | F95: 2011 USD | G95: 2011 | H95: USD | I95: Pessimistic - Nat. Gas w/seq | J95: Cost of capture, transport, storage | K95: 1 | L95: =[19]Baseline!$B$45* ((1+Inputs!$C$5) ^ (2022-G95)) -> 1245.9465
A96: Simon et al. 2011 | B96: 2011 | C96: 10.1016/j.egypro.2011.02.196 | D96: Solid sorbent | E96: Generic (Solid sorbent referenced) | F96: 2011 USD | G96: 2011 | H96: USD | I96: Optimistic - Wind | J96: Cost of capture, transport, storage | K96: 1 | L96: =[19]Baseline!$B$29* ((1+Inputs!$C$5) ^ (2022-G96)) -> 261.61467
A97: ='Study Parameters'!A22 -> Simon et al. 2011 | B97: ='Study Parameters'!H22 -> 2011 | C97: ='Study Parameters'!E22 -> 10.1016/j.egypro.2011.02.196 | D97: Solid sorbent | E97: Generic (Solid sorbent referenced) | F97: ='Study Parameters'!I22 -> 2011 USD | G97: 2011 | H97: USD | I97: Optimistic - Geothermal | J97: ='Study Parameters'!L22 -> Cost of capture, transport, storage | K97: 1 | L97: =[19]Baseline!$B$30* ((1+Inputs!$C$5) ^ (2022-G97)) -> 304.70765
A98: Simon et al. 2011 | B98: 2011 | C98: 10.1016/j.egypro.2011.02.196 | D98: Solid sorbent | E98: Generic (Solid sorbent referenced) | F98: 2011 USD | G98: 2011 | H98: USD | I98: Optimistic - Nat. Gas w/o seq | J98: ='Study Parameters'!L22 -> Cost of capture, transport, storage | K98: 1 | L98: =[19]Baseline!$B$31* ((1+Inputs!$C$5) ^ (2022-G98)) -> 803.14144
A99: Simon et al. 2011 | B99: 2011 | C99: 10.1016/j.egypro.2011.02.196 | D99: Solid sorbent | E99: Generic (Solid sorbent referenced) | F99: 2011 USD | G99: 2011 | H99: USD | I99: Optimistic - Nat. Gas w/seq | J99: ='Study Parameters'!L22 -> Cost of capture, transport, storage | K99: 1 | L99: =[19]Baseline!$B$32* ((1+Inputs!$C$5) ^ (2022-G99)) -> 329.15418
A100: Küng et al. 2023 | B100: 2023 | C100: 10.1039/d3ee01008b | D100: Liquid solvent | E100: Amino acid salt solution | F100: 2022 USD | G100: 2022 | H100: USD | I100: =[20]baseline_output!$C2 -> Amino acid salt solution-1c | K100: =[20]baseline_output!$S2 -> 0.002294244 | L100: =[20]baseline_output!$BD2 -> 779.02844
...

Sheet Inflation
A1: Inflation, consumer prices (annual %) - United States | F1: FRED Graph Observations
A2: Inflation, consumer prices (annual %) - United States | Data (worldbank.org) | F2: Federal Reserve Economic Data
F3: Link: https://fred.stlouisfed.org
A4: Country Code | B4: Indicator Name | C4: Indicator Code | F4: Help: https://fredhelp.stlouisfed.org
A5: USA | B5: Inflation, consumer prices (annual %) | C5: FP.CPI.TOTL.ZG | F5: Economic Research Division
B6: 2008 | C6: 3.8391003 | F6: Federal Reserve Bank of St. Louis
B7: 2009 | C7: -0.35554627
B8: 2010 | C8: 1.6400434
B9: 2011 | C9: 3.1568416
B10: 2012 | C10: 2.0693373
B11: 2013 | C11: 1.4648327
B12: 2014 | C12: 1.622223
B13: 2015 | C13: 0.11862714
B14: 2016 | C14: 1.2615832
B15: 2017 | C15: 2.13011
B16: 2018 | C16: 2.4425833
B17: 2019 | C17: 1.8122101
B18: 2020 | C18: 1.2335844
... B21: 2023 | C21: 4.1163384
B22: Average | C22: =AVERAGEA(C6:C21) -> 2.4532829
A23: Country | B23: Currency | C23: 2023 | D23: 2022 | E23: 2021 | F23: 2020 | G23: 2019 | H23: 2018 | I23: 2017
A24: Euro Zone | B24: Euro | C24: 0.924 | D24: 0.951 | E24: 0.846 | F24: 0.877 | G24: 0.893 | H24: 0.848 | I24: 0.923
A25: To convert from foreign currency to U.S. dollars, divide the foreign currency amount by the applicable yearly average exchange rate in the table
A26: 1 Euro | B26: =1/G24 -> 1.1198208 | C26: USD in 2019
A27: Source | B27: Yearly average currency exchange rates | Internal Revenue Service (irs.gov)

Sheet USD_EUR
A1: FRED Graph Observations
A2: Federal Reserve Economic Data
A3: Link: https://fred.stlouisfed.org
A4: Help: https://fredhelp.stlouisfed.org
A5: Economic Research Division
A6: Federal Reserve Bank of St. Louis
A8: EXUSEU | B8: U.S. Dollars to Euro Spot Exchange Rate, U.S. Dollars to One Euro, Monthly, Not Seasonally Adjusted
A10: Frequency: Monthly
A11: observation_date | B11: EXUSEU
A12: 39448 | B12: 1.4728
A13: 39479 | B13: 1.4759
A14: 39508 | B14: 1.552
A15: 39539 | B15: 1.5754
A16: 39569 | B16: 1.5554
A17: 39600 | B17: 1.5562
A18: 39630 | B18: 1.5759
A19: 39661 | B19: 1.4955
A20: 39692 | B20: 1.4342
A21: 39722 | B21: 1.3266
A22: 39753 | B22: 1.2744
A23: 39783 | B23: 1.3511
... A211: 45505 | B211: 1.102
