Workbook

Sheet Inputs
A1: Parameter | B1: Year | C1: Value | D1: Unit
A2: Standard Values
A3: Current Year | C3: 2024
A4: Inflation | C4: =[1]Inputs!C5 -> 0.02
A5: WACC | C5: =[1]Inputs!C6 -> 0.07
A6: USD to EUR | C6: =[1]Inputs!C7 -> 0.9
A7: Electricity
A8: LCOE | B8: 2024 | C8: =[1]Inputs!C9 -> 64 | D8: $/MWh
A9: LCOE | B9: 2050 | C9: =[1]Inputs!C10 -> 11 | D9: $/MWh
A10: Jet Fuel A-1 Characteristics
A11: Emissions Intensity | B11: 2024 | C11: =[1]Inputs!C12 -> 88.7 | D11: gCO2/MJ
A12: Emissions Intensity | B12: 2050 | C12: =[1]Inputs!C13 -> 88.7 | D12: gCO2/MJ
A13: Energy Density | C13: =[1]Inputs!C14 -> 43.2 | D13: MJ/kg
A14: Energy Density | C14: =[1]Inputs!C15 -> 34.6896 | D14: MJ/l
A15: Volumetric Density | C15: =[1]Inputs!C16 -> 0.803 | D15: kg/l
A16: Jet Fuel A-1 Price | B16: 2024 | C16: =[1]Inputs!C17 -> 0.8 | D16: $/l
A17: Scenario Specific Values
A18: Jet Fuel A-1 Price | B18: 2050 | C18: =[1]Inputs!C19 -> 1.7 | D18: $/l
A19: IEA Reference
A20: Jet Fuel A-1 Price | B20: 2024 | C20: =[1]Inputs!C21 -> 0.32246154 | D20: $/l
A21: Jet Fuel A-1 Price | B21: 2050 | C21: =[1]Inputs!C22 -> 0.20923077 | D21: $/l
A22: EIA Reference
A23: Jet Fuel A-1 Price | B23: 2024 | C23: =[1]Inputs!C24 -> 1.0209014 | D23: $/l
A24: Jet Fuel A-1 Price | B24: 2050 | C24: =[1]Inputs!C25 -> 2.0095594 | D24: $/l
A25: EIA Low Oil Price Scenario
A26: Jet Fuel A-1 Price | B26: 2024 | C26: =[1]Inputs!C27 -> 0.48286833 | D26: $/l
A27: Jet Fuel A-1 Price | B27: 2050 | C27: =[1]Inputs!C28 -> 0.89646575 | D27: $/l
A28: EIA High Scenario
A29: Jet Fuel A-1 Price | B29: 2024 | C29: =[1]Inputs!C30 -> 1.8838713 | D29: $/l
A30: Jet Fuel A-1 Price | B30: 2050 | C30: =[1]Inputs!C31 -> 3.7893731 | D30: $/l
A31: Direct Air Capture
A32: LCOR | B32: 2024 | C32: =[1]Inputs!$C$33 -> 1371 | D32: $/tCO2
A33: LCOR | B33: 2050 | C33: =[1]Inputs!C34 -> 523 | D33: $/tCO2

Sheet Received Data Brazzola
A1: Year | B1: DACCU Climate neutrality | C1: DACCS Climate neutrality | D1: DACCU CO2neutrality | E1: DACCS CO2neutrality | F1: Unit
A2: 2020 | F2: €/tCO2 removed
A3: 2021 | B3: 238.12811 | C3: 0 | D3: 683.55019 | E3: 0 | F3: €/tCO2 removed
A4: 2022 | B4: 180.28715 | C4: 0 | D4: 539.2059 | E4: 0 | F4: €/tCO2 removed
A5: 2023 | B5: 157.90104 | C5: 0 | D5: 473.29344 | E5: 0 | F5: €/tCO2 removed
A6: 2024 | B6: 152.22467 | C6: 0 | D6: 432.43604 | E6: 0 | F6: €/tCO2 removed
A7: 2025 | B7: 141.77606 | C7: 0 | D7: 402.89261 | E7: 0 | F7: €/tCO2 removed
A8: 2026 | B8: 132.57425 | C8: 0 | D8: 380.52166 | E8: 0 | F8: €/tCO2 removed
A9: 2027 | B9: 126.27529 | C9: 0 | D9: 362.72424 | E9: 0 | F9: €/tCO2 removed
A10: 2028 | B10: 118.6048 | C10: 0 | D10: 348.04704 | E10: 0 | F10: €/tCO2 removed
A11: 2029 | B11: 108.309 | C11: 0 | D11: 335.60677 | E11: 0 | F11: €/tCO2 removed
A12: 2030 | B12: 108.19629 | C12: 0 | D12: 324.83483 | E12: 0 | F12: €/tCO2 removed
A13: 2031 | B13: 105.35672 | C13: 0 | D13: 315.45025 | E13: 0 | F13: €/tCO2 removed
A14: 2032 | B14: 100.74983 | C14: 0 | D14: 307.0821 | E14: 0 | F14: €/tCO2 removed
... A42: 2060 | B42: 82.565074 | C42: 0 | D42: 227.9341 | E42: 0 | F42: €/tCO2 removed

Sheet LCOE Corrected
A1: Year | B1: Unit | C1: DACCU CO2neutrality
A2: 2020 | B2: €/tCO2 removed | C2: ='Received Data Brazzola'!D3*Inputs!$C$8/30 -> 1458.2404
A3: 2021 | B3: €/tCO2 removed | C3: ='Received Data Brazzola'!D4*Inputs!$C$8/30 -> 1150.3059
A4: 2022 | B4: €/tCO2 removed | C4: ='Received Data Brazzola'!D5*Inputs!$C$8/30 -> 1009.6927
A5: 2023 | B5: €/tCO2 removed | C5: ='Received Data Brazzola'!D6*Inputs!$C$8/30 -> 922.53021
A6: 2024 | B6: €/tCO2 removed | C6: ='Received Data Brazzola'!D7*Inputs!$C$8/30 -> 859.50423
A7: 2025 | B7: €/tCO2 removed | C7: ='Received Data Brazzola'!D8*Inputs!$C$8/30 -> 811.77955
A8: 2026 | B8: €/tCO2 removed | C8: ='Received Data Brazzola'!D9*Inputs!$C$8/30 -> 773.81171
A9: 2027 | B9: €/tCO2 removed | C9: ='Received Data Brazzola'!D10*Inputs!$C$8/30 -> 742.50035
A10: 2028 | B10: €/tCO2 removed | C10: ='Received Data Brazzola'!D11*Inputs!$C$8/30 -> 715.96111
A11: 2029 | B11: €/tCO2 removed | C11: ='Received Data Brazzola'!D12*Inputs!$C$8/30 -> 692.98097
A12: 2030 | B12: €/tCO2 removed | C12: ='Received Data Brazzola'!D13*Inputs!$C$8/30 -> 672.96054
A13: 2031 | B13: €/tCO2 removed | C13: ='Received Data Brazzola'!D14*Inputs!$C$8/30 -> 655.10848
... A32: 2050 | B32: €/tCO2 removed | C32: ='Received Data Brazzola'!D33*Inputs!$C$8/30 -> 507.54963

Sheet CO2 Cost Corrected
A1: Year | B1: Unit | C1: DACCU CO2neutrality
A2: 2020 | B2: €/tCO2 removed | C2: ='LCOE Corrected'!C2*Inputs!$C$32/870 -> 2297.9857
A3: 2021 | B3: €/tCO2 removed | C3: ='LCOE Corrected'!C3*Inputs!$C$32/870 -> 1812.7235
A4: 2022 | B4: €/tCO2 removed | C4: ='LCOE Corrected'!C4*Inputs!$C$32/870 -> 1591.1364
A5: 2023 | B5: €/tCO2 removed | C5: ='LCOE Corrected'!C5*Inputs!$C$32/870 -> 1453.7804
A6: 2024 | B6: €/tCO2 removed | C6: ='LCOE Corrected'!C6*Inputs!$C$32/870 -> 1354.4601
A7: 2025 | B7: €/tCO2 removed | C7: ='LCOE Corrected'!C7*Inputs!$C$32/870 -> 1279.2526
A8: 2026 | B8: €/tCO2 removed | C8: ='LCOE Corrected'!C8*Inputs!$C$32/870 -> 1219.4205
A9: 2027 | B9: €/tCO2 removed | C9: ='LCOE Corrected'!C9*Inputs!$C$32/870 -> 1170.0781
A10: 2028 | B10: €/tCO2 removed | C10: ='LCOE Corrected'!C10*Inputs!$C$32/870 -> 1128.256
A11: 2029 | B11: €/tCO2 removed | C11: ='LCOE Corrected'!C11*Inputs!$C$32/870 -> 1092.0424
A12: 2030 | B12: €/tCO2 removed | C12: ='LCOE Corrected'!C12*Inputs!$C$32/870 -> 1060.493
A13: 2031 | B13: €/tCO2 removed | C13: ='LCOE Corrected'!C13*Inputs!$C$32/870 -> 1032.3606
... A32: 2050 | B32: €/tCO2 removed | C32: ='LCOE Corrected'!C32*Inputs!$C$32/870 -> 799.82822

Sheet WACC Corrected
A1: Year | B1: Unit
A2: 2020 | B2: ='CO2 Cost Corrected'!C2 -> 2297.9857
A3: 2021 | B3: ='CO2 Cost Corrected'!C3 -> 1812.7235
A4: 2022 | B4: ='CO2 Cost Corrected'!C4 -> 1591.1364
A5: 2023 | B5: ='CO2 Cost Corrected'!C5 -> 1453.7804
A6: 2024 | B6: ='CO2 Cost Corrected'!C6 -> 1354.4601
A7: 2025 | B7: ='CO2 Cost Corrected'!C7 -> 1279.2526
A8: 2026 | B8: ='CO2 Cost Corrected'!C8 -> 1219.4205
A9: 2027 | B9: ='CO2 Cost Corrected'!C9 -> 1170.0781
A10: 2028 | B10: ='CO2 Cost Corrected'!C10 -> 1128.256
A11: 2029 | B11: ='CO2 Cost Corrected'!C11 -> 1092.0424
A12: 2030 | B12: ='CO2 Cost Corrected'!C12 -> 1060.493
A13: 2031 | B13: ='CO2 Cost Corrected'!C13 -> 1032.3606
... A32: 2050 | B32: ='CO2 Cost Corrected'!C32 -> 799.82822

Sheet Outputs
A1: Abatement Cost ($2023/tCO2)
A2: 2024 | B2: ='WACC Corrected'!B6 -> 1354.4601
A3: 2050 | B3: ='WACC Corrected'!B32 -> 799.82822
