Workbook

Sheet Inputs
A1: Parameter | B1: Year | C1: Value | D1: Unit
A2: Standard Values
A3: Current Year | C3: 2024
A4: Inflation | C4: =[1]Inputs!C5 -> 0.02
A5: WACC | C5: =[1]Inputs!C6 -> 0.07
A6: USD to EUR | C6: =[1]Inputs!C7 -> 0.9
A7: Electricity
A8: LCOE | B8: 2024 | C8: =[1]Inputs!C9 -> 64 | D8: $/MWh
A9: LCOE | B9: 2050 | C9: =[1]Inputs!C10 -> 11 | D9: $/MWh
A10: Jet Fuel A-1 Characteristics
A11: Emissions Intensity | B11: 2024 | C11: =[1]Inputs!C12 -> 88.7 | D11: gCO2/MJ
A12: Emissions Intensity | B12: 2050 | C12: =[1]Inputs!C13 -> 88.7 | D12: gCO2/MJ
A13: Energy Density | C13: =[1]Inputs!C14 -> 43.2 | D13: MJ/kg
A14: Energy Density | C14: =[1]Inputs!C15 -> 34.6896 | D14: MJ/l
A15: Volumetric Density | C15: =[1]Inputs!C16 -> 0.803 | D15: kg/l
A16: Jet Fuel A-1 Price | B16: 2024 | C16: =[1]Inputs!C17 -> 0.8 | D16: $/l
A17: Scenario Specific Values
A18: Jet Fuel A-1 Price | B18: 2050 | C18: =[1]Inputs!C19 -> 0.8 | D18: $/l
A19: IEA Reference
A20: Jet Fuel A-1 Price | B20: 2024 | C20: =[1]Inputs!C21 -> 0.32246154 | D20: $/l
A21: Jet Fuel A-1 Price | B21: 2050 | C21: =[1]Inputs!C22 -> 0.20923077 | D21: $/l
A22: EIA Reference
A23: Jet Fuel A-1 Price | B23: 2024 | C23: =[1]Inputs!C24 -> 1.0209014 | D23: $/l
A24: Jet Fuel A-1 Price | B24: 2050 | C24: =[1]Inputs!C25 -> 2.0095594 | D24: $/l
A25: EIA Low Oil Price Scenario
A26: Jet Fuel A-1 Price | B26: 2024 | C26: =[1]Inputs!C27 -> 0.48286833 | D26: $/l
A27: Jet Fuel A-1 Price | B27: 2050 | C27: =[1]Inputs!C28 -> 0.89646575 | D27: $/l
A28: EIA High Scenario
A29: Jet Fuel A-1 Price | B29: 2024 | C29: =[1]Inputs!C30 -> 1.8838713 | D29: $/l
A30: Jet Fuel A-1 Price | B30: 2050 | C30: =[1]Inputs!C31 -> 3.7893731 | D30: $/l
A31: Direct Air Capture
A32: LCOR | B32: 2024 | C32: =[1]Inputs!C33 -> 1282 | D32: $/tCO2
A33: LCOR | B33: 2050 | C33: =[1]Inputs!C34 -> 480 | D33: $/tCO2

Sheet Study Parameters
A1: Key Parameters
A2: Parameter | B2: Year | C2: Value | D2: Source | E2: Note
A3: Discount Rate | B3: 2024 | C3: 0.06 | D3: Gray et al.
A4: Lifetime (years) | B4: 2024 | C4: 25 | D4: Gray et al. Table 4
A6: Process Parameters
A7: Parameter | B7: Year | C7: Value | D7: Unit | E7: Source | F7: Note
A8: Annual CO2 Capture | B8: 2024 | C8: 144.344 | D8: kt | E8: Gray et al. Box 1
A9: Annual H2 consumption | B9: 2024 | C9: 19849 | D9: t | E9: Gray et al. Box 1
A10: Annual Jet Fuel Output | B10: 2024 | C10: 372300 | D10: MWh | E10: Gray et al. Box 1
A11: Annual Jet Fuel Output | B11: 2024 | C11: 31312027 | D11: kg | E11: Gray et al. Box 1 | F11: mFT fuel considered
A12: Annual Jet Fuel Output | B12: 2024 | C12: =C11 / 10^6 -> 31.312027 | D12: kt | F12: Calculated
A13: Annual Electricity Consumption (PtX) | B13: 2024 | C13: 372.3 | D13: GWh
A14: Fuel Synthesis Capcity Factor | B14: 2024 | C14: 0.85 | E14: Gray et al. Table 4
A15: Annual Full Load Hours (FT) | B15: 2024 | C15: =8760 * C14 -> 7446 | D15: hours | E15: Gray et al. Table 4
A16: H2 Electricity Requirement | B16: 2024 | C16: =0.03333 / 0.7 -> 0.047614286 | D16: MWh/kgH2 | E16: Gray et al. Box 1 | F16: Calculated for 70% electrolyzer efficinecy
A17: Annual Electricity Consumption (H2) | B17: 2024 | C17: =(C22*8760/10^3) -> 438 | D17: GWh
A19: Plant Parameters
A20: Parameter | B20: Year | C20: Value | D20: Unit | E20: Source | F20: Note
A21: FT Synthesis Capacity | B21: 2024 | C21: 50 | D21: MW | E21: Gray et al. Table 4
A22: Electrolyser Capacity | B22: 2024 | C22: 50 | D22: MW | E22: Gray et al. Table 4 | F22: Calculated as the minimum capcaity needed at 100% load factor to produce required H2
A23: Electrolyser Cell Stack Lifetime | B23: 2024 | C23: 80000 | D23: hours
A24: Cell Stack Replacements | B24: 2024 | C24: =ROUNDUP((8760 *C4) / C23,0) - 1 -> 2 | F24: Calculated for 100% load factor (8760 hours over 25 year lifetime)
A26: Fuel Characteristics
A27: Parameter | B27: Year | C27: Value | D27: Unit | E27: Source | F27: Note
A28: Fuel LHV | B28: 2024 | C28: 11.89 | D28: kWh/kg | E28: Gray et al. Box 1
A29: Fuel LHV | B29: 2024 | C29: =C28 * 3.6 -> 42.804 | D29: MJ/kg | E29: Gray et al. Box 1
A30: Emissions Intensity | B30: 2024 | C30: =0.09*Inputs!C11 -> 7.983 | D30: gCO2/MJ | E30: Gray et al. | F30: Assumed intensity of electricity supply is 30gCO2eq/kWh (Norwegian grid)
A32: External Costs
A33: Parameter | B33: Year | C33: Value | D33: Unit | E33: Source | F33: Note
A34: Electricity Price | B34: 2024 | C34: 40 | D34: €/MWh | E34: Gray et al. Table 5
A35: Low CO2 Price | B35: 2024 | C35: 160 | D35: €/tCO2 | E35: Gray et al. | F35: Calculated as LCDACS by varying capacity factors of capture plant
A36: High CO2 Price | B36: 2024 | C36: 1300 | D36: €/tCO2 | E36: Gray et al. | F36: Calculated as LCDACS by varying capacity factors of capture plant
A37: Electrolyzer Stack Replacement Cost | B37: 2033 | C37: =0.35 * 'Cost Components'!B5 -> 140 | D37: M€
A38: Electrolyzer Stack Replacement Cost | B38: 2042 | C38: =0.3 *'Cost Components'!B5 -> 120 | D38: M€
A39: First Electrolyzer Stack Replacement Cost (Annualized) - 6% | B39: 2024 | C39: =PMT($C$3,$C$4,-C37) -> 10.951741 | D39: M€/year
A40: Second Electrolyzer Stack Replacement Cost (Annualized) - 6% | B40: 2024 | C40: =PMT($C$3,$C$4,-C38) -> 9.3872062 | D40: M€/year
A41: First Electrolyzer Stack Replacement Cost (Annualized) - 7% | B41: 2024 | C41: =PMT(Inputs!C5,$C$4,-C37) -> 12.013472 | D41: M€/year
A42: Second Electrolyzer Stack Replacement Cost (Annualized) - 7% | B42: 2024 | C42: =PMT(Inputs!C5,$C$4,-C38) -> 10.297262 | D42: M€/year

Sheet Cost Components
A1: Economic Assumptions 2024 Low CO2 Price | G1: Economic Assumptions 2024 High CO2 Price
A2: CAPEX | G2: CAPEX
A3: Component | B3: Value | C3: Unit | D3: Source | E3: Notes | G3: Component | H3: Value | I3: Unit | J3: Source | K3: Notes
A4: Fuel Synthesis | B4: =(7000000*'Study Parameters'!$C$21) / 10^6 -> 350 | C4: M€ | D4: Gray et al. Table 4 | G4: Fuel Synthesis | H4: =(7000000*'Study Parameters'!$C$21) / 10^6 -> 350 | I4: M€ | J4: Gray et al. Table 4
A5: Electrolyzer | B5: =(8000000 * 'Study Parameters'!$C$22) / 10^6 -> 400 | C5: M€ | D5: Gray et al. Table 4 | G5: Electrolyzer | H5: =(8000000 * 'Study Parameters'!$C$22) / 10^6 -> 400 | I5: M€ | J5: Gray et al. Table 4
A8: OPEX | G8: OPEX
A9: Component | B9: Value | C9: Unit | D9: Source | E9: Notes | G9: Component | H9: Value | I9: Unit | J9: Source | K9: Notes
A10: Fuel Synthesis | B10: =0.04*B4 -> 14 | C10: m€/year | D10: Gray et al. Table 4 | G10: Fuel Synthesis | H10: =0.04*H4 -> 14 | I10: M€/year | J10: Gray et al. Table 4
A11: Electrolyzer | B11: =0.03*B5 -> 12 | C11: M€/year | D11: Gray et al. Table 4 | G11: Electrolyzer | H11: =0.03*H5 -> 12 | I11: M€/year | J11: Gray et al. Table 4
A12: Electricity | B12: =('Study Parameters'!$C$17+'Study Parameters'!$C$13) * 'Study Parameters'!$C$34 * 10^3/10^6 -> 32.412 | C12: M€/year | E12: Calculated | G12: Electricity | H12: =('Study Parameters'!$C$17+'Study Parameters'!$C$13) * 'Study Parameters'!$C$34 * 10^3/10^6 -> 32.412 | I12: M€/year | K12: Calculated
A13: CO2 Cost | B13: =('Study Parameters'!$C$35*'Study Parameters'!$C$8 * 10^3) / 10^6 -> 23.09504 | C13: M€/year | E13: Calculated | G13: CO2 Cost | H13: =('Study Parameters'!$C$36*'Study Parameters'!$C$8 * 10^3) / 10^6 -> 187.6472 | I13: M€/year | K13: Calculated
A14: Cell Stack Replacement (Annualised) | B14: ='Study Parameters'!$C$39+'Study Parameters'!$C$40 -> 20.338947 | C14: M€/year | G14: Cell Stack Replacement (Annualised) | H14: ='Study Parameters'!$C$39+'Study Parameters'!$C$40 -> 20.338947 | I14: M€/year

Sheet Levelised Cost H2
A1: Baseline | E1: LCOE Corrected | I1: WACC Corrected
A2: Parameter | B2: Value | C2: Unit | E2: Parameter | F2: Value | G2: Unit | I2: Parameter | J2: Value | K2: Unit
A3: CAPEX | B3: ='Cost Components'!$B$5 -> 400 | C3: M€ | E3: CAPEX | F3: ='Cost Components'!$B$5 -> 400 | G3: M€ | I3: CAPEX | J3: ='Cost Components'!$B$5 -> 400 | K3: M€
A4: Annualized CAPEX | B4: =PMT('Study Parameters'!$C$3,'Study Parameters'!$C$4,-'Levelised Cost H2'!B3) -> 31.290687 | C4: M€/year | E4: Annualized CAPEX | F4: =PMT('Study Parameters'!$C$3,'Study Parameters'!$C$4,-'Levelised Cost H2'!F3) -> 31.290687 | G4: M€/year | I4: Annualized CAPEX | J4: =PMT(Inputs!$C$5,'Study Parameters'!$C$4,-'Levelised Cost H2'!J3) -> 34.324207 | K4: M€/year
A5: O&M Electrolysis | B5: ='Cost Components'!$B$11 -> 12 | C5: M€/year | E5: O&M Electrolysis | F5: ='Cost Components'!$B$11 -> 12 | G5: M€/year | I5: O&M Electrolysis | J5: ='Cost Components'!$B$11 -> 12 | K5: M€/year
A6: Electricity Cost | B6: =('Study Parameters'!$C$17*'Study Parameters'!$C$34 * 10^3)/10^6 -> 17.52 | C6: M€/year | E6: Electricity Cost | F6: =('Study Parameters'!$C$17* Inputs!$C$8*Inputs!$C$6 * 10^3)/10^6 -> 25.2288 | G6: M€/year | I6: Electricity Cost | J6: =('Study Parameters'!$C$17* Inputs!$C$8*Inputs!$C$6 * 10^3)/10^6 -> 25.2288 | K6: M€/year
A7: Annualized Stack Replacement Cost | B7: ='Cost Components'!$B$14 -> 20.338947 | C7: M€/year | E7: Annualized Stack Replacement Cost | F7: ='Cost Components'!$B$14 -> 20.338947 | G7: M€/year | I7: Annualized Stack Replacement Cost | J7: ='Study Parameters'!C41+'Study Parameters'!C42 -> 22.310734 | K7: M€/year
A8: H2 Production | B8: ='Study Parameters'!$C$9 * 10^3 * 0.03333 -> 661567.17 | C8: MWh/year | E8: H2 Production | F8: ='Study Parameters'!$C$9 * 10^3 * 0.03333 -> 661567.17 | G8: MWh/year | I8: H2 Production | J8: ='Study Parameters'!$C$9 * 10^3 * 0.03333 -> 661567.17 | K8: MWh/year
A10: Levelized Cost of H2 | B10: =(SUM(B4:B7) * 10^6)/B8 -> 122.66273 | C10: €/MWh | E10: Levelized Cost of H2 | F10: =(SUM(F4:F7) * 10^6)/F8 -> 134.31506 | G10: €/MWh | I10: Levelized Cost of H2 | J10: =(SUM(J4:J7) * 10^6)/J8 -> 141.88089 | K10: €/MWh

Sheet LCOF Baseline
A1: 2024 - Low CO2 Cost Scenario | E1: 2024 - High CO2 Cost Scenario
A2: Parameter | B2: Value | C2: Unit | E2: Parameter | F2: Value | G2: Unit
A3: FT CAPEX | B3: ='Cost Components'!$B$4 -> 350 | C3: M€ | E3: FT CAPEX | F3: ='Cost Components'!$B$4 -> 350 | G3: M€
A4: Annualized FT CAPEX | B4: =PMT('Study Parameters'!$C$3,'Study Parameters'!$C$4,-'LCOF Baseline'!B3) -> 27.379351 | C4: M€/year | E4: Annualized FT CAPEX | F4: =PMT('Study Parameters'!$C$3,'Study Parameters'!$C$4,-'LCOF Baseline'!F3) -> 27.379351 | G4: M€/year
A5: O&M FT | B5: ='Cost Components'!$B$10 -> 14 | C5: M€/year | E5: O&M FT | F5: ='Cost Components'!$B$10 -> 14 | G5: M€/year
A6: CO2 Consumption | B6: ='Study Parameters'!$C$8 -> 144.344 | C6: kt/year | E6: CO2 Consumption | F6: ='Study Parameters'!$C$8 -> 144.344 | G6: kt/year
A7: CO2 Cost | B7: ='Study Parameters'!C35 -> 160 | C7: €/tCO2 | E7: CO2 Cost | F7: ='Study Parameters'!C36 -> 1300 | G7: €/tCO2
A8: Annual CO2 Cost | B8: =B7*B6*10^3 / 10^6 -> 23.09504 | C8: M€/year | E8: Annual CO2 Cost | F8: =F7*F6*10^3 / 10^6 -> 187.6472 | G8: M€/year
A9: H2 Consumption | B9: ='Study Parameters'!$C$9 -> 19849 | C9: t/year | E9: H2 Consumption | F9: ='Study Parameters'!$C$9 -> 19849 | G9: t/year
A10: H2 Cost | B10: ='Levelised Cost H2'!$B$10 -> 122.66273 | C10: €/MWh | E10: H2 Cost | F10: ='Levelised Cost H2'!$B$10 -> 122.66273 | G10: €/MWh
A11: Annual H2 Cost | B11: =B10*B9 * 0.0333 * 10^3 / 10^6 -> 81.076592 | C11: M€/year | E11: Annual H2 Cost | F11: =F10*F9 * 0.0333 * 10^3 / 10^6 -> 81.076592 | G11: M€/year
A12: Fuel Production | B12: ='Study Parameters'!$C$10 -> 372300 | C12: MWh/year | E12: Fuel Production | F12: ='Study Parameters'!$C$10 -> 372300 | G12: MWh/year
A14: LCOF | B14: =(B4+B8+B11) * 10^6/ B12 -> 353.34672 | C14: €/MWh | E14: LCOF | F14: =(F4+F8+F11) * 10^6/ F12 -> 795.33479 | G14: €/MWh
A15: LCOF | B15: =B14*'Study Parameters'!$C$28/10^3 -> 4.2012925 | C15: €/kg | E15: LCOF | F15: =F14*'Study Parameters'!$C$28/10^3 -> 9.4565307 | G15: €/kg
A16: LCOF | B16: =B15 * Inputs!$C$15 -> 3.3736379 | C16: €/l | E16: LCOF | F16: =F15 * Inputs!$C$15 -> 7.5935941 | G16: €/l

Sheet LCOF LCOE Corrected
A1: 2024 - Low CO2 Cost Scenario | E1: 2024 - High CO2 Cost Scenario
A2: Parameter | B2: Value | C2: Unit | E2: Parameter | F2: Value | G2: Unit
A3: FT CAPEX | B3: ='Cost Components'!$B$4 -> 350 | C3: M€ | E3: FT CAPEX | F3: ='Cost Components'!$B$4 -> 350 | G3: M€
A4: Annualized FT CAPEX | B4: =PMT('Study Parameters'!$C$3,'Study Parameters'!$C$4,-'LCOF Baseline'!B3) -> 27.379351 | C4: M€/year | E4: Annualized FT CAPEX | F4: =PMT('Study Parameters'!$C$3,'Study Parameters'!$C$4,-'LCOF Baseline'!F3) -> 27.379351 | G4: M€/year
A5: O&M FT | B5: ='Cost Components'!$B$10 -> 14 | C5: M€/year | E5: O&M FT | F5: ='Cost Components'!$B$10 -> 14 | G5: M€/year
A6: CO2 Consumption | B6: ='Study Parameters'!$C$8 -> 144.344 | C6: kt/year | E6: CO2 Consumption | F6: ='Study Parameters'!$C$8 -> 144.344 | G6: kt/year
A7: CO2 Cost | B7: ='Study Parameters'!C35 -> 160 | C7: €/tCO2 | E7: CO2 Cost | F7: ='Study Parameters'!C36 -> 1300 | G7: €/tCO2
A8: Annual CO2 Cost | B8: =B7*B6*10^3 / 10^6 -> 23.09504 | C8: M€/year | E8: Annual CO2 Cost | F8: =F7*F6*10^3 / 10^6 -> 187.6472 | G8: M€/year
A9: H2 Consumption | B9: ='Study Parameters'!$C$9 -> 19849 | C9: t/year | E9: H2 Consumption | F9: ='Study Parameters'!$C$9 -> 19849 | G9: t/year
A10: H2 Cost | B10: ='Levelised Cost H2'!$F$10 -> 134.31506 | C10: €/MWh | E10: H2 Cost | F10: ='Levelised Cost H2'!$F$10 -> 134.31506 | G10: €/MWh
A11: Annual H2 Cost | B11: =B10*B9 * 0.0333 * 10^3 / 10^6 -> 88.778453 | C11: M€/year | E11: Annual H2 Cost | F11: =F10*F9 * 0.0333 * 10^3 / 10^6 -> 88.778453 | G11: M€/year
A12: Fuel Production | B12: ='Study Parameters'!$C$10 -> 372300 | C12: MWh/year | E12: Fuel Production | F12: ='Study Parameters'!$C$10 -> 372300 | G12: MWh/year
A14: LCOF | B14: =(B4+B8+B11) * 10^6/ B12 -> 374.03396 | C14: €/MWh | E14: LCOF | F14: =(F4+F8+F11) * 10^6/ F12 -> 816.02204 | G14: €/MWh
A15: LCOF | B15: =B14*'Study Parameters'!$C$28/10^3 -> 4.4472638 | C15: €/kg | E15: LCOF | F15: =F14*'Study Parameters'!$C$28/10^3 -> 9.702502 | G15: €/kg
A16: LCOF | B16: =B15 * Inputs!$C$15 -> 3.5711529 | C16: €/l | E16: LCOF | F16: =F15 * Inputs!$C$15 -> 7.7911091 | G16: €/l

Sheet LCOF DAC Corrected
A1: 2024 - Low CO2 Cost Scenario | E1: 2024 - High CO2 Cost Scenario
A2: Parameter | B2: Value | C2: Unit | E2: Parameter | F2: Value | G2: Unit
A3: FT CAPEX | B3: ='Cost Components'!$B$4 -> 350 | C3: M€ | E3: FT CAPEX | F3: ='Cost Components'!$B$4 -> 350 | G3: M€
A4: Annualized FT CAPEX | B4: =PMT('Study Parameters'!$C$3,'Study Parameters'!$C$4,-'LCOF Baseline'!B3) -> 27.379351 | C4: M€/year | E4: Annualized FT CAPEX | F4: =PMT('Study Parameters'!$C$3,'Study Parameters'!$C$4,-'LCOF Baseline'!F3) -> 27.379351 | G4: M€/year
A5: O&M FT | B5: ='Cost Components'!$B$10 -> 14 | C5: M€/year | E5: O&M FT | F5: ='Cost Components'!$B$10 -> 14 | G5: M€/year
A6: CO2 Consumption | B6: ='Study Parameters'!$C$8 -> 144.344 | C6: kt/year | E6: CO2 Consumption | F6: ='Study Parameters'!$C$8 -> 144.344 | G6: kt/year
A7: CO2 Cost | B7: =Inputs!C33 * Inputs!C6 -> 432 | C7: €/tCO2 | E7: CO2 Cost | F7: =Inputs!C32*Inputs!C6 -> 1153.8 | G7: €/tCO2
A8: Annual CO2 Cost | B8: =B7*B6*10^3 / 10^6 -> 62.356608 | C8: M€/year | E8: Annual CO2 Cost | F8: =F7*F6*10^3 / 10^6 -> 166.54411 | G8: M€/year
A9: H2 Consumption | B9: ='Study Parameters'!$C$9 -> 19849 | C9: t/year | E9: H2 Consumption | F9: ='Study Parameters'!$C$9 -> 19849 | G9: t/year
A10: H2 Cost | B10: ='Levelised Cost H2'!$F$10 -> 134.31506 | C10: €/MWh | E10: H2 Cost | F10: ='Levelised Cost H2'!$F$10 -> 134.31506 | G10: €/MWh
A11: Annual H2 Cost | B11: =B10*B9 * 0.0333 * 10^3 / 10^6 -> 88.778453 | C11: M€/year | E11: Annual H2 Cost | F11: =F10*F9 * 0.0333 * 10^3 / 10^6 -> 88.778453 | G11: M€/year
A12: Fuel Production | B12: ='Study Parameters'!$C$10 -> 372300 | C12: MWh/year | E12: Fuel Production | F12: ='Study Parameters'!$C$10 -> 372300 | G12: MWh/year
A14: LCOF | B14: =(B4+B8+B11) * 10^6/ B12 -> 479.49077 | C14: €/MWh | E14: LCOF | F14: =(F4+F8+F11) * 10^6/ F12 -> 759.33901 | G14: €/MWh
A15: LCOF | B15: =B14*'Study Parameters'!$C$28/10^3 -> 5.7011452 | C15: €/kg | E15: LCOF | F15: =F14*'Study Parameters'!$C$28/10^3 -> 9.0285408 | G15: €/kg
A16: LCOF | B16: =B15 * Inputs!$C$15 -> 4.5780196 | C16: €/l | E16: LCOF | F16: =F15 * Inputs!$C$15 -> 7.2499182 | G16: €/l

Sheet LCOF WACC Corrected
A1: 2024 - Low CO2 Cost Scenario | E1: 2024 - High CO2 Cost Scenario | I1: Cost Breakdowns | L1: Cost Breakdowns
A2: Parameter | B2: Value | C2: Unit | E2: Parameter | F2: Value | G2: Unit | I2: CO2 Cost | J2: =F8 -> 166.54411 | L2: CO2 Cost | M2: =B8 -> 62.356608
A3: FT CAPEX | B3: ='Cost Components'!$B$4 -> 350 | C3: M€ | E3: FT CAPEX | F3: ='Cost Components'!$B$4 -> 350 | G3: M€ | I3: Electricity | J3: ='Levelised Cost H2'!$J$6+'Cost Components'!$B$12 -> 57.6408 | L3: Electricity | M3: ='Levelised Cost H2'!$J$6+'Cost Components'!$B$12 -> 57.6408
A4: Annualized FT CAPEX | B4: =PMT(Inputs!$C$5,'Study Parameters'!$C$4,-'LCOF Baseline'!B3) -> 30.033681 | C4: M€/year | E4: Annualized FT CAPEX | F4: =PMT(Inputs!$C$5,'Study Parameters'!$C$4,-'LCOF Baseline'!F3) -> 30.033681 | G4: M€/year | I4: CAPEX | J4: =$F$4 -> 30.033681 | L4: CAPEX | M4: =$F$4 -> 30.033681
A5: O&M FT | B5: ='Cost Components'!$B$10 -> 14 | C5: M€/year | E5: O&M FT | F5: ='Cost Components'!$B$10 -> 14 | G5: M€/year | I5: Other OPEX | J5: =$F$5 -> 14 | L5: Other OPEX | M5: =$F$5 -> 14
A6: CO2 Consumption | B6: ='Study Parameters'!$C$8 -> 144.344 | C6: kt/year | E6: CO2 Consumption | F6: ='Study Parameters'!$C$8 -> 144.344 | G6: kt/year
A7: CO2 Cost | B7: =Inputs!C33 * Inputs!C6 -> 432 | C7: €/tCO2 | E7: CO2 Cost | F7: =Inputs!C32*Inputs!C6 -> 1153.8 | G7: €/tCO2 | I7: Contributions | L7: Contributions
A8: Annual CO2 Cost | B8: =B7*B6*10^3 / 10^6 -> 62.356608 | C8: M€/year | E8: Annual CO2 Cost | F8: =F7*F6*10^3 / 10^6 -> 166.54411 | G8: M€/year | I8: CO2 Cost | J8: =J2/SUM($J$2:$J$5) -> 0.62092679 | L8: CO2 Cost | M8: =M2/SUM($M$2:$M$5) -> 0.38015116
A9: H2 Consumption | B9: ='Study Parameters'!$C$9 -> 19849 | C9: t/year | E9: H2 Consumption | F9: ='Study Parameters'!$C$9 -> 19849 | G9: t/year | I9: Electricity | J9: =J3/SUM($J$2:$J$5) -> 0.21490233 | L9: Electricity | M9: =M3/SUM($M$2:$M$5) -> 0.35140168
A10: H2 Cost | B10: ='Levelised Cost H2'!$J$10 -> 141.88089 | C10: €/MWh | E10: H2 Cost | F10: ='Levelised Cost H2'!$J$10 -> 141.88089 | G10: €/MWh | I10: CAPEX | J10: =J4/SUM($J$2:$J$5) -> 0.11197464 | L10: CAPEX | M10: =M4/SUM($M$2:$M$5) -> 0.18309749
A11: Annual H2 Cost | B11: =B10*B9 * 0.0333 * 10^3 / 10^6 -> 93.779256 | C11: M€/year | E11: Annual H2 Cost | F11: =F10*F9 * 0.0333 * 10^3 / 10^6 -> 93.779256 | G11: M€/year | I11: Other OPEX | J11: =J5/SUM($J$2:$J$5) -> 0.052196233 | L11: Other OPEX | M11: =M5/SUM($M$2:$M$5) -> 0.085349674
A12: Fuel Production | B12: ='Study Parameters'!$C$10 -> 372300 | C12: MWh/year | E12: Fuel Production | F12: ='Study Parameters'!$C$10 -> 372300 | G12: MWh/year
A14: LCOF | B14: =(B4+B8+B11) * 10^6/ B12 -> 500.0525 | C14: €/MWh | E14: LCOF | F14: =(F4+F8+F11) * 10^6/ F12 -> 779.90074 | G14: €/MWh
A15: LCOF | B15: =B14*'Study Parameters'!$C$28/10^3 -> 5.9456242 | C15: €/kg | E15: LCOF | F15: =F14*'Study Parameters'!$C$28/10^3 -> 9.2730197 | G15: €/kg
A16: LCOF | B16: =B15 * Inputs!$C$15 -> 4.7743362 | C16: €/l | E16: LCOF | F16: =F15 * Inputs!$C$15 -> 7.4462349 | G16: €/l

Sheet Outputs
A1: Low CO2 Cost Scenario (2024 and 2050) | H1: 2024 - High CO2 Cost
A2: Parameter | B2: Unit | C2: Base case | D2: Electricity correction | E2: DAC correction | F2: WACC correction | H2: Parameter | I2: Unit | J2: Base case | K2: Electricity correction | L2: DAC correction | M2: WACC correction
A3: Syn-Fuel cost | B3: €/l | C3: ='LCOF Baseline'!B16 -> 3.3736379 | D3: ='LCOF LCOE Corrected'!B16 -> 3.5711529 | E3: ='LCOF DAC Corrected'!B16 -> 4.5780196 | F3: ='LCOF WACC Corrected'!B16 -> 4.7743362 | H3: Syn-Fuel cost | I3: €/l | J3: ='LCOF Baseline'!F16 -> 7.5935941 | K3: ='LCOF LCOE Corrected'!F16 -> 7.7911091 | L3: ='LCOF DAC Corrected'!F16 -> 7.2499182 | M3: ='LCOF WACC Corrected'!F16 -> 7.4462349
A4: Syn-Fuel cost | B4: $/l | C4: =C3/Inputs!$C$6 -> 3.7484865 | D4: =D3/Inputs!$C$6 -> 3.9679476 | E4: =E3/Inputs!$C$6 -> 5.0866885 | F4: =F3/Inputs!$C$6 -> 5.304818 | H4: Syn-Fuel cost | I4: $/l | J4: =J3/Inputs!$C$6 -> 8.4373268 | K4: =K3/Inputs!$C$6 -> 8.6567879 | L4: =L3/Inputs!$C$6 -> 8.0554647 | M4: =M3/Inputs!$C$6 -> 8.2735943
A5: Fossil Fuel cost | B5: $/l | C5: =Inputs!$C$18 -> 0.8 | D5: =Inputs!$C$18 -> 0.8 | E5: =Inputs!$C$18 -> 0.8 | F5: =Inputs!$C$18 -> 0.8 | H5: Fossil Fuel cost | I5: $/l | J5: =Inputs!$C$16 -> 0.8 | K5: =Inputs!$C$16 -> 0.8 | L5: =Inputs!$C$16 -> 0.8 | M5: =Inputs!$C$16 -> 0.8
A6: Syn-Fuel emissions | B6: gCO2eq/MJ | C6: ='Study Parameters'!$C$30 -> 7.983 | D6: ='Study Parameters'!$C$30 -> 7.983 | E6: ='Study Parameters'!$C$30 -> 7.983 | F6: ='Study Parameters'!$C$30 -> 7.983 | H6: Syn-Fuel emissions | I6: gCO2eq/MJ | J6: ='Study Parameters'!$C$30 -> 7.983 | K6: ='Study Parameters'!$C$30 -> 7.983 | L6: ='Study Parameters'!$C$30 -> 7.983 | M6: ='Study Parameters'!$C$30 -> 7.983
A7: Fossil Fuel emissions | B7: gCO2eq/MJ | C7: =Inputs!$C$11 -> 88.7 | D7: =Inputs!$C$11 -> 88.7 | E7: =Inputs!$C$11 -> 88.7 | F7: =Inputs!$C$11 -> 88.7 | H7: Fossil Fuel emissions | I7: gCO2eq/MJ | J7: =Inputs!$C$11 -> 88.7 | K7: =Inputs!$C$11 -> 88.7 | L7: =Inputs!$C$11 -> 88.7 | M7: =Inputs!$C$11 -> 88.7
A8: CO2 Abated | B8: gCO2eq/MJ | C8: =C7-C6 -> 80.717 | D8: =D7-D6 -> 80.717 | E8: =E7-E6 -> 80.717 | F8: =F7-F6 -> 80.717 | H8: CO2 Abated | I8: gCO2eq/MJ | J8: =J7-J6 -> 80.717 | K8: =K7-K6 -> 80.717 | L8: =L7-L6 -> 80.717 | M8: =M7-M6 -> 80.717
A9: CO2 Abated | B9: gCO2eq/l | C9: =C8*Inputs!$C$14 -> 2800.0404 | D9: =D8*Inputs!$C$14 -> 2800.0404 | E9: =E8*Inputs!$C$14 -> 2800.0404 | F9: =F8*Inputs!$C$14 -> 2800.0404 | H9: CO2 Abated | I9: gCO2eq/l | J9: =J8*Inputs!$C$14 -> 2800.0404 | K9: =K8*Inputs!$C$14 -> 2800.0404 | L9: =L8*Inputs!$C$14 -> 2800.0404 | M9: =M8*Inputs!$C$14 -> 2800.0404
A10: Abatement cost | B10: $/tCO2 | C10: =(C4-C5) / C9 * 10^6 -> 1053.0157 | D10: =(D4-D5) / D9 * 10^6 -> 1131.3935 | E10: =(E4-E5) / E9 * 10^6 -> 1530.9381 | F10: =(F4-F5) / F9 * 10^6 -> 1608.8403 | H10: Abatement cost | I10: $/tCO2 | J10: =(J4-J5) / J9 * 10^6 -> 2727.5773 | K10: =(K4-K5) / K9 * 10^6 -> 2805.9552 | L10: =(L4-L5) / L9 * 10^6 -> 2591.2 | M10: =(M4-M5) / M9 * 10^6 -> 2669.1023
A12: Full Abatement | H12: Full Abatement
A13: Parameter | B13: Unit | C13: Value | H13: Parameter | I13: Unit | J13: Value
A14: Residual Emissions | B14: gCO2eq/l | C14: =C6*Inputs!$C$14 -> 276.92708 | H14: Residual Emissions | I14: gCO2eq/l | J14: =J6*Inputs!$C$14 -> 276.92708
A15: Emissions Reduction Cost | B15: $/l | C15: =C14*Inputs!$C$33 * 10^-6 -> 0.132925 | H15: Emissions Reduction Cost | I15: $/l | J15: =J14*Inputs!$C$32 * 10^-6 -> 0.35502051
A16: Effective Synfuel Cost | B16: $/l | C16: =F4+C15 -> 5.437743 | H16: Effective Synfuel Cost | I16: $/l | J16: =M4+J15 -> 8.6286148
A17: Effective Abatement Cost | B17: $/tCO2 | C17: =(C16-C5) /C9 * 10^6 -> 1656.3129 | H17: Effective Abatement Cost | I17: $/tCO2 | J17: =(J16-J5) /J9 * 10^6 -> 2795.8935
