Workbook

Sheet Inputs
A1: Parameter | B1: Year | C1: Value | D1: Unit
A2: Standard Values
A3: Current Year | C3: 2024
A4: Inflation | C4: =[1]Inputs!C5 -> 0.02
A5: WACC | C5: =[1]Inputs!C6 -> 0.07
A6: USD to EUR | C6: =[1]Inputs!C7 -> 0.9
A7: Electricity
A8: LCOE | B8: 2024 | C8: =[1]Inputs!C9 -> 64 | D8: $/MWh
A9: LCOE | B9: 2050 | C9: =[1]Inputs!C10 -> 11 | D9: $/MWh
A10: Jet Fuel A-1 Characteristics
A11: Emissions Intensity | B11: 2024 | C11: =[1]Inputs!C12 -> 88.7 | D11: gCO2/MJ
A12: Emissions Intensity | B12: 2050 | C12: =[1]Inputs!C13 -> 88.7 | D12: gCO2/MJ
A13: Energy Density | C13: =[1]Inputs!C14 -> 43.2 | D13: MJ/kg
A14: Energy Density | C14: =[1]Inputs!C15 -> 34.6896 | D14: MJ/l
A15: Volumetric Density | C15: =[1]Inputs!C16 -> 0.803 | D15: kg/l
A16: Jet Fuel A-1 Price | B16: 2024 | C16: =[1]Inputs!C17 -> 0.8 | D16: $/l
A17: Scenario Specific Values
A18: Jet Fuel A-1 Price | B18: 2050 | C18: =[1]Inputs!C19 -> 1.7 | D18: $/l
A19: IEA Reference
A20: Jet Fuel A-1 Price | B20: 2024 | C20: =[1]Inputs!C21 -> 0.32246154 | D20: $/l
A21: Jet Fuel A-1 Price | B21: 2050 | C21: =[1]Inputs!C22 -> 0.20923077 | D21: $/l
A22: EIA Reference
A23: Jet Fuel A-1 Price | B23: 2024 | C23: =[1]Inputs!C24 -> 1.0209014 | D23: $/l
A24: Jet Fuel A-1 Price | B24: 2050 | C24: =[1]Inputs!C25 -> 2.0095594 | D24: $/l
A25: EIA Low Oil Price Scenario
A26: Jet Fuel A-1 Price | B26: 2024 | C26: =[1]Inputs!C27 -> 0.48286833 | D26: $/l
A27: Jet Fuel A-1 Price | B27: 2050 | C27: =[1]Inputs!C28 -> 0.89646575 | D27: $/l
A28: EIA High Scenario
A29: Jet Fuel A-1 Price | B29: 2024 | C29: =[1]Inputs!C30 -> 1.8838713 | D29: $/l
A30: Jet Fuel A-1 Price | B30: 2050 | C30: =[1]Inputs!C31 -> 3.7893731 | D30: $/l
A31: Direct Air Capture
A32: LCOR | B32: 2024 | C32: =[1]Inputs!C33 -> 1371 | D32: $/tCO2
A33: LCOR | B33: 2050 | C33: =[1]Inputs!C34 -> 523 | D33: $/tCO2

Sheet Study Parameters
A1: Key Parameters
A2: Parameter | B2: Year | C2: Value | D2: Source | E2: Note
A3: Plant Lifetime (years) | B3: Both | C3: 25 | D3: Marchese et. al.
A4: Discount Rate | B4: Both | C4: 0.075 | D4: Marchese et. al. | E4: Medium risk discount rate considered as low risk is 0%
A6: Plant Parameters
A7: Parameter | B7: Year | C7: Value | D7: Unit | E7: Source | F7: Note
A8: Annual Full Load Hours | B8: Both | C8: 8000 | D8: h | E8: Marchese et. al.
A10: Process Parameters
A11: Parameter | B11: Year | C11: Value | D11: Unit | E11: Source | F11: Note
A12: Fuel Production C.1 | B12: Both | C12: 8.7 | D12: t/h | E12: Marchese et. al.
A13: Fuel Production C.2 | B13: Both | C13: 3.5 | D13: t/h | E13: Marchese et. al.
A14: Fuel Production C.3 | B14: Both | C14: 4.8 | D14: t/h | E14: Marchese et. al.
A15: Fuel Production C.4 | B15: Both | C15: 6.9 | D15: t/h | E15: Marchese et. al.
A16: Fuel Production C.5 | B16: Both | C16: 6.8 | D16: t/h | E16: Marchese et. al.
A17: H2 Consumption | B17: Both
A18: CO2 Consumption | B18: Both | C18: 27 | D18: t/h | E18: Marchese et. al.
A19: Annual CO2 Consumption | B19: Both | C19: =C18*C8 -> 216000 | D19: t | F19: Calculated
A20: DAC Electricity Consumption | B20: Both | C20: 694 | D20: kWh/t | E20: Fasihi et. al. 2019, Table 2 | F20: K2CO3 process is considered as it is modelled here
A21: Annual DAC Electricity Consumption | B21: Both | C21: =(C20*C19) / 10^3 -> 149904 | D21: MWh
A22: Annual Process Electricity Consumption C.1 | B22: Both | C22: =SUM('Cost Components'!B23:B29) * 10^6 / SUM('Study Parameters'!C30:C35) / 4 -> 2384886.1 | D22: MWh
A23: Annual Process Electricity Consumption C.2 | B23: Both | C23: =SUM('Cost Components'!C23:C29) * 10^6/ SUM('Study Parameters'!C30:C35) / 4 -> 1650148.4 | D23: MWh
A24: Annual Process Electricity Consumption C.3 | B24: Both | C24: =SUM('Cost Components'!D23:D29) * 10^6 / SUM('Study Parameters'!C30:C35) / 3 -> 2555280.2 | D24: MWh
A25: Annual Process Electricity Consumption C.4 | B25: Both | C25: =SUM('Cost Components'!E23:E29) * 10^6 / SUM('Study Parameters'!C30:C35) / 4 -> 1758471.6 | D25: MWh
A26: Annual Process Electricity Consumption C.5 | B26: Both | C26: =SUM('Cost Components'!F23:F29) * 10^6 / SUM('Study Parameters'!C30:C35) / 4 -> 2222533.5 | D26: MWh
A28: External Costs
A29: Parameter | B29: Year | C29: Value | D29: Unit | E29: Source | F29: Note
A30: Electricity Price: Hydropower | B30: 2021 | C30: 41.05 | D30: €/MWh | E30: Marchese et. al.
A31: Electricity Price: Onshore Wind | B31: 2021 | C31: 59.39 | D31: €/MWh | E31: Marchese et. al.
A32: Electricity Price: Geothermal | B32: 2021 | C32: 63.76 | D32: €/MWh | E32: Marchese et. al.
A33: Electricity Price: Offshore Wind | B33: 2021 | C33: 100.44 | D33: €/MWh | E33: Marchese et. al.
A34: Electricity Price: CSP | B34: 2021 | C34: 158.95 | D34: €/MWh | E34: Marchese et. al.
A35: Electricity Price: Baseload (Wind + Solar) | B35: 2021 | C35: 210 | D35: €/MWh | E35: Marchese et. al.
A36: Electricity Price: Baseload | B36: 2050
A38: Fuel Characteristics
A39: Parameter | B39: Year | C39: Value | D39: Unit | E39: Source | F39: Note
A40: GHG Emissions | B40: Both | C40: 0 | D40: gCO2/MJ | E40: Marchese et. al. | F40: Process is considered to be carbon neutral with embedded CO2 captured via DAC

Sheet Cost Components
A1: 2021 | L1: 2050
A2: CAPEX | L2: CAPEX
A3: Component | B3: C.1 | C3: C.2 | D3: C.3 | E3: C.4 | F3: C.5 | G3: Unit | H3: Source | I3: Note | L3: Component | M3: C.1 | N3: C.2 | O3: C.3 | P3: C.4 | Q3: C.5 | R3: Unit | S3: Source | T3: Note
A4: Electrolysis | B4: 330 | C4: 283 | D4: 310 | E4: 261 | F4: 337 | G4: M€ | H4: Marchese et. al. Supplementary Information Table S.6 | L4: Other CAPEX | M4: =M12-M5 -> 428.2 | N4: =N12-N5 -> 309.4 | O4: =O12-O5 -> 321.6 | P4: =P12-P5 -> 339 | Q4: =Q12-Q5 -> 347 | R4: M€ | S4: Marchese et. al. Supplementary Information Table S.6
A5: DAC | B5: 734 | C5: 698 | D5: 707 | E5: 595 | F5: 535 | G5: M€ | H5: Marchese et. al. Supplementary Information Table S.6 | L5: DAC | M5: =B5 * 0.2 -> 146.8 | N5: =C5 * 0.2 -> 139.6 | O5: =D5 * 0.2 -> 141.4 | P5: =E5 * 0.2 -> 119 | Q5: =F5 * 0.2 -> 107 | R5: M€ | S5: Marchese et. al. Supplementary Information Table S.6
A6: Thermal Integration | B6: 416 | C6: 355 | D6: 347 | E6: 305 | F6: 306 | G6: M€ | H6: Marchese et. al. Supplementary Information Table S.6
A7: RWGS | B7: 115 | C7: 75 | D7: 82 | E7: 79 | F7: 96 | G7: M€ | H7: Marchese et. al. Supplementary Information Table S.6
A8: FT | B8: 223 | C8: 86 | D8: 118 | E8: 164 | F8: 169 | G8: M€ | H8: Marchese et. al. Supplementary Information Table S.6
A9: Total Syngas Compression | B9: 32 | C9: 15 | D9: 18 | E9: 22 | F9: 24 | G9: M€ | H9: Marchese et. al. Supplementary Information Table S.6
A10: Distillation | B10: 14.76 | C10: 7.8 | D10: 9.03 | E10: 9.62 | F10: 11.46 | G10: M€ | H10: Marchese et. al. Supplementary Information Table S.6
A11: Afterburn Combustor | B11: 6 | C11: 5.5 | D11: 3 | E11: 4.3 | F11: 4.2 | G11: M€ | H11: Marchese et. al. Supplementary Information Table S.6
A12: Total CAPEX | B12: =SUM(B4:B11) -> 1870.76 | C12: =SUM(C4:C11) -> 1525.3 | D12: =SUM(D4:D11) -> 1594.03 | E12: =SUM(E4:E11) -> 1439.92 | F12: =SUM(F4:F11) -> 1482.66 | G12: M€ | H12: Marchese et. al. Supplementary Information Table S.6 | L12: Total CAPEX | M12: 575 | N12: 449 | O12: 463 | P12: 458 | Q12: 454 | R12: M€ | S12: Marchese et. al. Supplementary Information Table S.6
A14: OPEX | L14: OPEX
A15: Component | B15: C.1 | C15: C.2 | D15: C.3 | E15: C.4 | F15: C.5 | G15: Unit | H15: Source | I15: Note | L15: Component | M15: C.1 | N15: C.2 | O15: C.3 | P15: C.4 | Q15: C.5 | R15: Unit | S15: Source | T15: Note
A16: Electrolysis | B16: 51.8 | C16: 26.2 | D16: 26.5 | E16: 22.4 | F16: 20.2 | G16: M€/year | H16: Marchese et. al. Supplementary Information Table S.7 | L16: Electricity | M16: =(60 * 'Study Parameters'!$C$22) / 10^6 -> 143.09317 | N16: =(60 * 'Study Parameters'!$C$23) / 10^6 -> 99.008902 | O16: =(60 * 'Study Parameters'!$C$24) / 10^6 -> 153.31681 | P16: =(60 * 'Study Parameters'!$C$25) / 10^6 -> 105.50829 | Q16: =(60 * 'Study Parameters'!$C$26) / 10^6 -> 133.35201 | R16: M€/year | S16: Marchese et. al. Supplementary Information Table S.7
A17: DAC | B17: 12.6 | C17: 10.7 | D17: 10.5 | E17: 9.2 | F17: 9.2 | G17: M€/year | H17: Marchese et. al. Supplementary Information Table S.7 | L17: DAC | M17: =B17/B5*M5 -> 2.52 | N17: =C17/C5*N5 -> 2.14 | O17: =D17/D5*O5 -> 2.1 | P17: =E17/E5*P5 -> 1.84 | Q17: =F17/F5*Q5 -> 1.84 | R17: M€/year | S17: Marchese et. al. Supplementary Information Table S.7
A18: Thermal Integration | B18: 13.6 | C18: 11.6 | D18: 12.8 | E18: 10.7 | F18: 13.9 | G18: M€/year | H18: Marchese et. al. Supplementary Information Table S.7 | L18: Other OPEX | M18: 129.5 | N18: 101.8 | O18: 104.6 | P18: 89 | Q18: 100 | R18: M€/year | S18: Marchese et. al. Supplementary Information Table S.7
A19: RWGS | B19: 9.7 | C19: 7.3 | D19: 7.8 | E19: 7.2 | F19: 7.8 | G19: M€/year | H19: Marchese et. al. Supplementary Information Table S.7
A20: FT | B20: 41.8 | C20: 46 | D20: 47 | E20: 39.5 | F20: 48.9 | G20: M€/year | H20: Marchese et. al. Supplementary Information Table S.7
A21: Total OPEX (non electric) | B21: =SUM(B16:B20) -> 129.5 | C21: =SUM(C16:C20) -> 101.8 | D21: =SUM(D16:D20) -> 104.6 | E21: =SUM(E16:E20) -> 89 | F21: =SUM(F16:F20) -> 100 | G21: M€/year | L21: Total OPEX (including electricity) | M21: =SUM(M16:M18) -> 275.11317 | N21: =SUM(N16:N18) -> 202.9489 | O21: =SUM(O16:O18) -> 260.01681 | P21: =SUM(P16:P18) -> 196.34829 | Q21: =SUM(Q16:Q18) -> 235.19201 | R21: M€/year
A22: Electricity
A23: Hydropower | B23: 364.92 | C23: 252.5 | D23: 293.2 | E23: 269.1 | F23: 340.1 | G23: M€/year | H23: Marchese et. al. Supplementary Information Table S.7
A24: Onshore Wind | B24: 411.51 | C24: 284.73 | D24: 330.7 | E24: 303.4 | F24: 383.5 | G24: M€/year | H24: Marchese et. al. Supplementary Information Table S.7
A25: PV | B25: 527.98 | C25: 365.32 | D25: 424.3 | E25: 389.3 | F25: 492 | G25: M€/year | H25: Marchese et. al. Supplementary Information Table S.7
A26: Geothermal | B26: 566.8 | C26: 392.18 | D26: 455.5 | E26: 417.9 | F26: 528.2 | G26: M€/year | H26: Marchese et. al. Supplementary Information Table S.7
A27: Offshore Wind | B27: 892.9 | C27: 617.81 | D27: 717.5 | E27: 658.4 | F27: 832.1 | G27: M€/year | H27: Marchese et. al. Supplementary Information Table S.7
A28: CSP | B28: 1413.11 | C28: 977.76 | D28: 1135.6 | E28: 1041.9 | F28: 1316.9 | G28: M€/year | H28: Marchese et. al. Supplementary Information Table S.7
A29: Baseload (Solar + Wind) | B29: 1866.94 | C29: 1291.77 | D29: 1500.2 | E29: 1376.6 | F29: 1739.9 | G29: M€/year | H29: Marchese et. al. Supplementary Information Table S.7
A31: Revenues | L31: Revenues
A32: Component | B32: C.1 | C32: C.2 | D32: C.3 | E32: C.4 | F32: C.5 | G32: Unit | H32: Source | I32: Note | L32: Component | M32: C.1 | N32: C.2 | O32: C.3 | P32: C.4 | Q32: C.5 | R32: Unit | S32: Source | T32: Note
A33: O2 Sale | B33: 28.5 | C33: 56.5 | D33: 45 | E33: 52.6 | F33: 62 | G33: M€/year | H33: Marchese et. al. Supplementary Information Table S.7
A34: FT C5-C11 | B34: 12.1 | C34: 37.1 | D34: 15.5 | E34: 21.6 | F34: 30.8 | G34: M€/year | H34: Marchese et. al. Supplementary Information Table S.7
A35: FT C11-C20 | B35: 16.2 | C35: 56.3 | D35: 20.5 | E35: 29 | F35: 42.4 | G35: M€/year | H35: Marchese et. al. Supplementary Information Table S.7
A36: Total Revenue | B36: =SUM(B33:B35) -> 56.8 | C36: =SUM(C33:C35) -> 149.9 | D36: =SUM(D33:D35) -> 81 | E36: =SUM(E33:E35) -> 103.2 | F36: =SUM(F33:F35) -> 135.2 | G36: M€/year | L36: Total Revenue | M36: 149.9 | N36: 81 | O36: 103.2 | P36: 135.2 | Q36: 133.7 | R36: M€/year
A38: 2021 Corrected | L38: 2050 Corrected
A39: Component | B39: C.1 | C39: C.2 | D39: C.3 | E39: C.4 | F39: C.5 | G39: Unit | L39: Component | M39: C.1 | N39: C.2 | O39: C.3 | P39: C.4 | Q39: C.5 | R39: Unit
A40: Electricity | B40: =(('Study Parameters'!C22-'Study Parameters'!C21) * Inputs!$C$8) / 10^6 -> 143.03886 | C40: =(('Study Parameters'!C23-'Study Parameters'!C21) * Inputs!$C$8) / 10^6 -> 96.015639 | D40: =(('Study Parameters'!C24-'Study Parameters'!C21) * Inputs!$C$8) / 10^6 -> 153.94408 | E40: =(('Study Parameters'!C25-'Study Parameters'!E21) * Inputs!$C$8) / 10^6 -> 112.54218 | F40: =(('Study Parameters'!C26-'Study Parameters'!F21) * Inputs!$C$8) / 10^6 -> 142.24214 | G40: M€/year | L40: Electricity | M40: =(Inputs!$C$9* 'Study Parameters'!$C$22) / 10^6 -> 26.233747 | N40: =(Inputs!C9 * 'Study Parameters'!$C$23) / 10^6 -> 18.151632 | O40: =(Inputs!C9 * 'Study Parameters'!$C$24) / 10^6 -> 28.108083 | P40: =(Inputs!C9 * 'Study Parameters'!$C$25) / 10^6 -> 19.343187 | Q40: =(Inputs!C9 * 'Study Parameters'!$C$26) / 10^6 -> 24.447868 | R40: M€/year
A41: CO2 Cost | B41: =(Inputs!$C$32*'Study Parameters'!$C$19) / 10^6 -> 296.136 | C41: =(Inputs!$C$32*'Study Parameters'!$C$19) / 10^6 -> 296.136 | D41: =(Inputs!$C$32*'Study Parameters'!$C$19) / 10^6 -> 296.136 | E41: =(Inputs!$C$32*'Study Parameters'!$C$19) / 10^6 -> 296.136 | F41: =(Inputs!$C$32*'Study Parameters'!$C$19) / 10^6 -> 296.136 | G41: M€/year | L41: Total OPEX (including electricity) | M41: =M21-M16+M40 -> 158.25375 | N41: =N21-N16+N40 -> 122.09163 | O41: =O21-O16+O40 -> 134.80808 | P41: =P21-P16+P40 -> 110.18319 | Q41: =Q21-Q16+Q40 -> 126.28787 | R41: M€/year
A42: CO2 Corrected CAPEX | B42: =B12-B5 -> 1136.76 | C42: =C12-C5 -> 827.3 | D42: =D12-D5 -> 887.03 | E42: =E12-E5 -> 844.92 | F42: =F12-F5 -> 947.66 | G42: M€ | L42: CO2 Cost | M42: =('Study Parameters'!$C$19*Inputs!$C$33) / 10^6 -> 112.968 | N42: =('Study Parameters'!$C$19*Inputs!$C$33) / 10^6 -> 112.968 | O42: =('Study Parameters'!$C$19*Inputs!$C$33) / 10^6 -> 112.968 | P42: =('Study Parameters'!$C$19*Inputs!$C$33) / 10^6 -> 112.968 | Q42: =('Study Parameters'!$C$19*Inputs!$C$33) / 10^6 -> 112.968 | R42: M€/year
A43: CO2 Corrected OPEX (non electric) | B43: =B21-B17 -> 116.9 | C43: =C21-C17 -> 91.1 | D43: =D21-D17 -> 94.1 | E43: =E21-E17 -> 79.8 | F43: =F21-F17 -> 90.8 | G43: M€/year | L43: CO2 Corrected CAPEX | M43: =M4 -> 428.2 | N43: =N4 -> 309.4 | O43: =O4 -> 321.6 | P43: =P4 -> 339 | Q43: =Q4 -> 347 | R43: M€
L44: CO2 Corrected OPEX (non electric) | M44: =M41-M17 -> 155.73375 | N44: =N41-N17 -> 119.95163 | O44: =O41-O17 -> 132.70808 | P44: =P41-P17 -> 108.34319 | Q44: =Q41-Q17 -> 124.44787 | R44: M€/year

Sheet Production Cost Baseline
A1: 2021
A2: Year | B2: 0 | C2: 1 | D2: 2 | E2: 3 | F2: 4 | G2: 5 | H2: 6 | I2: 7 | J2: 8 | K2: 9 | L2: 10 | M2: 11 | N2: 12 | O2: 13 | P2: 14 | Q2: 15 | R2: 16 | S2: 17 | T2: 18 | U2: 19 | V2: 20 | W2: 21 | X2: 22 | Y2: 23 | Z2: 24 | AA2: 25
A3: C.1 Hydropower
A4: Cost (€) | B4: ='Cost Components'!$B$12 * 10^6 -> 1870760000 | C4: =('Cost Components'!$B$21 + 'Cost Components'!$B$23) * 10^6 -> 494420000 | D4: =('Cost Components'!$B$21 + 'Cost Components'!$B$23) * 10^6 -> 494420000 | E4: =('Cost Components'!$B$21 + 'Cost Components'!$B$23) * 10^6 -> 494420000 | F4: =('Cost Components'!$B$21 + 'Cost Components'!$B$23) * 10^6 -> 494420000 | G4: =('Cost Components'!$B$21 + 'Cost Components'!$B$23) * 10^6 -> 494420000 | H4: =('Cost Components'!$B$21 + 'Cost Components'!$B$23) * 10^6 -> 494420000 | I4: =('Cost Components'!$B$21 + 'Cost Components'!$B$23) * 10^6 -> 494420000 | J4: =('Cost Components'!$B$21 + 'Cost Components'!$B$23) * 10^6 -> 494420000 | ... AA4: =('Cost Components'!$B$21 + 'Cost Components'!$B$23) * 10^6 -> 494420000
A5: Revenue (€) | B5: 0 | C5: ='Cost Components'!$B$36*10^6 -> 56800000 | D5: ='Cost Components'!$B$36*10^6 -> 56800000 | E5: ='Cost Components'!$B$36*10^6 -> 56800000 | F5: ='Cost Components'!$B$36*10^6 -> 56800000 | G5: ='Cost Components'!$B$36*10^6 -> 56800000 | H5: ='Cost Components'!$B$36*10^6 -> 56800000 | I5: ='Cost Components'!$B$36*10^6 -> 56800000 | J5: ='Cost Components'!$B$36*10^6 -> 56800000 | ... AA5: ='Cost Components'!$B$36*10^6 -> 56800000
A6: Free Cash Flow (€) | B6: =B4-B5 -> 1870760000 | C6: =C4-C5 -> 437620000 | D6: =D4-D5 -> 437620000 | E6: =E4-E5 -> 437620000 | F6: =F4-F5 -> 437620000 | G6: =G4-G5 -> 437620000 | H6: =H4-H5 -> 437620000 | I6: =I4-I5 -> 437620000 | ... AA6: =AA4-AA5 -> 437620000
A7: Discounted Cash Flow (€) | B7: =B6/(1+'Study Parameters'!$C$4) ^'Production Cost Baseline'!B$2 -> 1870760000 | C7: =C6/(1+'Study Parameters'!$C$4) ^'Production Cost Baseline'!C$2 -> 4.0708837e+08 | D7: =D6/(1+'Study Parameters'!$C$4) ^'Production Cost Baseline'!D$2 -> 3.7868686e+08 | E7: =E6/(1+'Study Parameters'!$C$4) ^'Production Cost Baseline'!E$2 -> 3.5226684e+08 | F7: =F6/(1+'Study Parameters'!$C$4) ^'Production Cost Baseline'!F$2 -> 3.2769009e+08 | G7: =G6/(1+'Study Parameters'!$C$4) ^'Production Cost Baseline'!G$2 -> 3.0482799e+08 | H7: =H6/(1+'Study Parameters'!$C$4) ^'Production Cost Baseline'!H$2 -> 2.8356092e+08 | I7: =I6/(1+'Study Parameters'!$C$4) ^'Production Cost Baseline'!I$2 -> 2.637776e+08 | ... AA7: =AA6/(1+'Study Parameters'!$C$4) ^'Production Cost Baseline'!AA$2 -> 71760516
A8: Fuel Production (kg) | B8: 0 | C8: ='Study Parameters'!$C$12*'Study Parameters'!$C$8 * 10^3 -> 69600000 | D8: ='Study Parameters'!$C$12*'Study Parameters'!$C$8 * 10^3 -> 69600000 | E8: ='Study Parameters'!$C$12*'Study Parameters'!$C$8 * 10^3 -> 69600000 | F8: ='Study Parameters'!$C$12*'Study Parameters'!$C$8 * 10^3 -> 69600000 | G8: ='Study Parameters'!$C$12*'Study Parameters'!$C$8 * 10^3 -> 69600000 | H8: ='Study Parameters'!$C$12*'Study Parameters'!$C$8 * 10^3 -> 69600000 | I8: ='Study Parameters'!$C$12*'Study Parameters'!$C$8 * 10^3 -> 69600000 | J8: ='Study Parameters'!$C$12*'Study Parameters'!$C$8 * 10^3 -> 69600000 | ... AA8: ='Study Parameters'!$C$12*'Study Parameters'!$C$8 * 10^3 -> 69600000
A9: Discounted Fuel Production (kg) | B9: 0 | C9: =C8/(1+'Study Parameters'!$C$4) ^'Production Cost Baseline'!C$2 -> 64744186 | D9: =D8/(1+'Study Parameters'!$C$4) ^'Production Cost Baseline'!D$2 -> 60227150 | E9: =E8/(1+'Study Parameters'!$C$4) ^'Production Cost Baseline'!E$2 -> 56025256 | F9: =F8/(1+'Study Parameters'!$C$4) ^'Production Cost Baseline'!F$2 -> 52116517 | G9: =G8/(1+'Study Parameters'!$C$4) ^'Production Cost Baseline'!G$2 -> 48480481 | H9: =H8/(1+'Study Parameters'!$C$4) ^'Production Cost Baseline'!H$2 -> 45098122 | I9: =I8/(1+'Study Parameters'!$C$4) ^'Production Cost Baseline'!I$2 -> 41951741 | J9: =J8/(1+'Study Parameters'!$C$4) ^'Production Cost Baseline'!J$2 -> 39024875 | ... AA9: =AA8/(1+'Study Parameters'!$C$4) ^'Production Cost Baseline'!AA$2 -> 11412943
A11: Production Cost of Fuel (€/kg) | B11: =SUM(B7:AA7) / SUM(C9:AA9) -> 8.6989531
A12: Production Cost of Fuel (€/l) | B12: =B11 * Inputs!$C$15 -> 6.9852593
A14: C.1 Baseload
A15: Cost (€) | B15: ='Cost Components'!$B$12 * 10^6 -> 1870760000 | C15: =('Cost Components'!$B$21 + 'Cost Components'!$B$29) * 10^6 -> 1996440000 | D15: =('Cost Components'!$B$21 + 'Cost Components'!$B$29) * 10^6 -> 1996440000 | E15: =('Cost Components'!$B$21 + 'Cost Components'!$B$29) * 10^6 -> 1996440000 | F15: =('Cost Components'!$B$21 + 'Cost Components'!$B$29) * 10^6 -> 1996440000 | G15: =('Cost Components'!$B$21 + 'Cost Components'!$B$29) * 10^6 -> 1996440000 | H15: =('Cost Components'!$B$21 + 'Cost Components'!$B$29) * 10^6 -> 1996440000 | I15: =('Cost Components'!$B$21 + 'Cost Components'!$B$29) * 10^6 -> 1996440000 | J15: =('Cost Components'!$B$21 + 'Cost Components'!$B$29) * 10^6 -> 1996440000 | ... AA15: =('Cost Components'!$B$21 + 'Cost Components'!$B$29) * 10^6 -> 1996440000
A16: Revenue (€) | B16: 0 | C16: ='Cost Components'!$B$36*10^6 -> 56800000 | D16: ='Cost Components'!$B$36*10^6 -> 56800000 | E16: ='Cost Components'!$B$36*10^6 -> 56800000 | F16: ='Cost Components'!$B$36*10^6 -> 56800000 | G16: ='Cost Components'!$B$36*10^6 -> 56800000 | H16: ='Cost Components'!$B$36*10^6 -> 56800000 | I16: ='Cost Components'!$B$36*10^6 -> 56800000 | J16: ='Cost Components'!$B$36*10^6 -> 56800000 | ... AA16: ='Cost Components'!$B$36*10^6 -> 56800000
A17: Free Cash Flow (€) | B17: =B15-B16 -> 1870760000 | C17: =C15-C16 -> 1939640000 | D17: =D15-D16 -> 1939640000 | E17: =E15-E16 -> 1939640000 | F17: =F15-F16 -> 1939640000 | G17: =G15-G16 -> 1939640000 | H17: =H15-H16 -> 1939640000 | I17: =I15-I16 -> 1939640000 | ... AA17: =AA15-AA16 -> 1939640000
A18: Discounted Cash Flow (€) | B18: =B17/(1+'Study Parameters'!$C$4) ^'Production Cost Baseline'!B$2 -> 1870760000 | C18: =C17/(1+'Study Parameters'!$C$4) ^'Production Cost Baseline'!C$2 -> 1.8043163e+09 | D18: =D17/(1+'Study Parameters'!$C$4) ^'Production Cost Baseline'!D$2 -> 1.6784337e+09 | E18: =E17/(1+'Study Parameters'!$C$4) ^'Production Cost Baseline'!E$2 -> 1.5613337e+09 | F18: =F17/(1+'Study Parameters'!$C$4) ^'Production Cost Baseline'!F$2 -> 1.4524035e+09 | G18: =G17/(1+'Study Parameters'!$C$4) ^'Production Cost Baseline'!G$2 -> 1.351073e+09 | H18: =H17/(1+'Study Parameters'!$C$4) ^'Production Cost Baseline'!H$2 -> 1.2568121e+09 | I18: =I17/(1+'Study Parameters'!$C$4) ^'Production Cost Baseline'!I$2 -> 1.1691275e+09 | ... AA18: =AA17/(1+'Study Parameters'!$C$4) ^'Production Cost Baseline'!AA$2 -> 3.1806034e+08
A19: Fuel Production (kg) | B19: 0 | C19: ='Study Parameters'!$C$12*'Study Parameters'!$C$8 * 10^3 -> 69600000 | D19: ='Study Parameters'!$C$12*'Study Parameters'!$C$8 * 10^3 -> 69600000 | E19: ='Study Parameters'!$C$12*'Study Parameters'!$C$8 * 10^3 -> 69600000 | F19: ='Study Parameters'!$C$12*'Study Parameters'!$C$8 * 10^3 -> 69600000 | G19: ='Study Parameters'!$C$12*'Study Parameters'!$C$8 * 10^3 -> 69600000 | H19: ='Study Parameters'!$C$12*'Study Parameters'!$C$8 * 10^3 -> 69600000 | I19: ='Study Parameters'!$C$12*'Study Parameters'!$C$8 * 10^3 -> 69600000 | J19: ='Study Parameters'!$C$12*'Study Parameters'!$C$8 * 10^3 -> 69600000 | ... AA19: ='Study Parameters'!$C$12*'Study Parameters'!$C$8 * 10^3 -> 69600000
A20: Discounted Fuel Production (kg) | B20: 0 | C20: =C19/(1+'Study Parameters'!$C$4) ^'Production Cost Baseline'!C$2 -> 64744186 | D20: =D19/(1+'Study Parameters'!$C$4) ^'Production Cost Baseline'!D$2 -> 60227150 | E20: =E19/(1+'Study Parameters'!$C$4) ^'Production Cost Baseline'!E$2 -> 56025256 | F20: =F19/(1+'Study Parameters'!$C$4) ^'Production Cost Baseline'!F$2 -> 52116517 | G20: =G19/(1+'Study Parameters'!$C$4) ^'Production Cost Baseline'!G$2 -> 48480481 | H20: =H19/(1+'Study Parameters'!$C$4) ^'Production Cost Baseline'!H$2 -> 45098122 | I20: =I19/(1+'Study Parameters'!$C$4) ^'Production Cost Baseline'!I$2 -> 41951741 | J20: =J19/(1+'Study Parameters'!$C$4) ^'Production Cost Baseline'!J$2 -> 39024875 | ... AA20: =AA19/(1+'Study Parameters'!$C$4) ^'Production Cost Baseline'!AA$2 -> 11412943
A22: Production Cost of Fuel (€/kg) | B22: =SUM(B18:AA18) / SUM(C20:AA20) -> 30.2797
A23: Production Cost of Fuel (€/l) | B23: =B22 * Inputs!$C$15 -> 24.314599
A25: C.2 Hydropower
A26: Cost (€) | B26: ='Cost Components'!$C$12 * 10^6 -> 1525300000 | C26: =('Cost Components'!$C$21 + 'Cost Components'!$C$23) * 10^6 -> 354300000 | D26: =('Cost Components'!$C$21 + 'Cost Components'!$C$23) * 10^6 -> 354300000 | E26: =('Cost Components'!$C$21 + 'Cost Components'!$C$23) * 10^6 -> 354300000 | F26: =('Cost Components'!$C$21 + 'Cost Components'!$C$23) * 10^6 -> 354300000 | G26: =('Cost Components'!$C$21 + 'Cost Components'!$C$23) * 10^6 -> 354300000 | H26: =('Cost Components'!$C$21 + 'Cost Components'!$C$23) * 10^6 -> 354300000 | I26: =('Cost Components'!$C$21 + 'Cost Components'!$C$23) * 10^6 -> 354300000 | J26: =('Cost Components'!$C$21 + 'Cost Components'!$C$23) * 10^6 -> 354300000 | ... AA26: =('Cost Components'!$C$21 + 'Cost Components'!$C$23) * 10^6 -> 354300000
A27: Revenue (€) | B27: 0 | C27: ='Cost Components'!$C$36*10^6 -> 1.499e+08 | D27: ='Cost Components'!$C$36*10^6 -> 1.499e+08 | E27: ='Cost Components'!$C$36*10^6 -> 1.499e+08 | F27: ='Cost Components'!$C$36*10^6 -> 1.499e+08 | G27: ='Cost Components'!$C$36*10^6 -> 1.499e+08 | H27: ='Cost Components'!$C$36*10^6 -> 1.499e+08 | I27: ='Cost Components'!$C$36*10^6 -> 1.499e+08 | J27: ='Cost Components'!$C$36*10^6 -> 1.499e+08 | ... AA27: ='Cost Components'!$C$36*10^6 -> 1.499e+08
A28: Free Cash Flow (€) | B28: =B26-B27 -> 1525300000 | C28: =C26-C27 -> 2.044e+08 | D28: =D26-D27 -> 2.044e+08 | E28: =E26-E27 -> 2.044e+08 | F28: =F26-F27 -> 2.044e+08 | G28: =G26-G27 -> 2.044e+08 | H28: =H26-H27 -> 2.044e+08 | I28: =I26-I27 -> 2.044e+08 | ... AA28: =AA26-AA27 -> 2.044e+08
A29: Discounted Cash Flow (€) | B29: =B28/(1+'Study Parameters'!$C$4) ^'Production Cost Baseline'!B$2 -> 1525300000 | C29: =C28/(1+'Study Parameters'!$C$4) ^'Production Cost Baseline'!C$2 -> 1.9013953e+08 | D29: =D28/(1+'Study Parameters'!$C$4) ^'Production Cost Baseline'!D$2 -> 1.7687399e+08 | E29: =E28/(1+'Study Parameters'!$C$4) ^'Production Cost Baseline'!E$2 -> 1.6453394e+08 | F29: =F28/(1+'Study Parameters'!$C$4) ^'Production Cost Baseline'!F$2 -> 1.5305483e+08 | G29: =G28/(1+'Study Parameters'!$C$4) ^'Production Cost Baseline'!G$2 -> 1.4237658e+08 | H29: =H28/(1+'Study Parameters'!$C$4) ^'Production Cost Baseline'!H$2 -> 1.3244333e+08 | I29: =I28/(1+'Study Parameters'!$C$4) ^'Production Cost Baseline'!I$2 -> 1.232031e+08 | ... AA29: =AA28/(1+'Study Parameters'!$C$4) ^'Production Cost Baseline'!AA$2 -> 33517320
A30: Fuel Production (kg) | B30: 0 | C30: ='Study Parameters'!$C$13*'Study Parameters'!$C$8 * 10^3 -> 28000000 | D30: ='Study Parameters'!$C$13*'Study Parameters'!$C$8 * 10^3 -> 28000000 | E30: ='Study Parameters'!$C$13*'Study Parameters'!$C$8 * 10^3 -> 28000000 | F30: ='Study Parameters'!$C$13*'Study Parameters'!$C$8 * 10^3 -> 28000000 | G30: ='Study Parameters'!$C$13*'Study Parameters'!$C$8 * 10^3 -> 28000000 | H30: ='Study Parameters'!$C$13*'Study Parameters'!$C$8 * 10^3 -> 28000000 | I30: ='Study Parameters'!$C$13*'Study Parameters'!$C$8 * 10^3 -> 28000000 | J30: ='Study Parameters'!$C$13*'Study Parameters'!$C$8 * 10^3 -> 28000000 | ... AA30: ='Study Parameters'!$C$13*'Study Parameters'!$C$8 * 10^3 -> 28000000
A31: Discounted Fuel Production (kg) | B31: 0 | C31: =C30/(1+'Study Parameters'!$C$4) ^'Production Cost Baseline'!C$2 -> 26046512 | D31: =D30/(1+'Study Parameters'!$C$4) ^'Production Cost Baseline'!D$2 -> 24229313 | E31: =E30/(1+'Study Parameters'!$C$4) ^'Production Cost Baseline'!E$2 -> 22538896 | F31: =F30/(1+'Study Parameters'!$C$4) ^'Production Cost Baseline'!F$2 -> 20966415 | G31: =G30/(1+'Study Parameters'!$C$4) ^'Production Cost Baseline'!G$2 -> 19503642 | H31: =H30/(1+'Study Parameters'!$C$4) ^'Production Cost Baseline'!H$2 -> 18142923 | I31: =I30/(1+'Study Parameters'!$C$4) ^'Production Cost Baseline'!I$2 -> 16877137 | J31: =J30/(1+'Study Parameters'!$C$4) ^'Production Cost Baseline'!J$2 -> 15699663 | ... AA31: =AA30/(1+'Study Parameters'!$C$4) ^'Production Cost Baseline'!AA$2 -> 4591413.7
A33: Production Cost of Fuel (€/kg) | B33: =SUM(B29:AA29) / SUM(C31:AA31) -> 12.186989
A34: Production Cost of Fuel (€/l) | B34: =B33 * Inputs!$C$15 -> 9.786152
A36: C.2 Baseload
A37: Cost (€) | B37: ='Cost Components'!$C$12 * 10^6 -> 1525300000 | C37: =('Cost Components'!$C$21 + 'Cost Components'!$C$29) * 10^6 -> 1393570000 | D37: =('Cost Components'!$C$21 + 'Cost Components'!$C$29) * 10^6 -> 1393570000 | E37: =('Cost Components'!$C$21 + 'Cost Components'!$C$29) * 10^6 -> 1393570000 | F37: =('Cost Components'!$C$21 + 'Cost Components'!$C$29) * 10^6 -> 1393570000 | G37: =('Cost Components'!$C$21 + 'Cost Components'!$C$29) * 10^6 -> 1393570000 | H37: =('Cost Components'!$C$21 + 'Cost Components'!$C$29) * 10^6 -> 1393570000 | I37: =('Cost Components'!$C$21 + 'Cost Components'!$C$29) * 10^6 -> 1393570000 | J37: =('Cost Components'!$C$21 + 'Cost Components'!$C$29) * 10^6 -> 1393570000 | ... AA37: =('Cost Components'!$C$21 + 'Cost Components'!$C$29) * 10^6 -> 1393570000
A38: Revenue (€) | B38: 0 | C38: ='Cost Components'!$C$36*10^6 -> 1.499e+08 | D38: ='Cost Components'!$C$36*10^6 -> 1.499e+08 | E38: ='Cost Components'!$C$36*10^6 -> 1.499e+08 | F38: ='Cost Components'!$C$36*10^6 -> 1.499e+08 | G38: ='Cost Components'!$C$36*10^6 -> 1.499e+08 | H38: ='Cost Components'!$C$36*10^6 -> 1.499e+08 | I38: ='Cost Components'!$C$36*10^6 -> 1.499e+08 | J38: ='Cost Components'!$C$36*10^6 -> 1.499e+08 | ... AA38: ='Cost Components'!$C$36*10^6 -> 1.499e+08
A39: Free Cash Flow (€) | B39: =B37-B38 -> 1525300000 | C39: =C37-C38 -> 1243670000 | D39: =D37-D38 -> 1243670000 | E39: =E37-E38 -> 1243670000 | F39: =F37-F38 -> 1243670000 | G39: =G37-G38 -> 1243670000 | H39: =H37-H38 -> 1243670000 | I39: =I37-I38 -> 1243670000 | ... AA39: =AA37-AA38 -> 1243670000
A40: Discounted Cash Flow (€) | B40: =B39/(1+'Study Parameters'!$C$4) ^'Production Cost Baseline'!B$2 -> 1525300000 | C40: =C39/(1+'Study Parameters'!$C$4) ^'Production Cost Baseline'!C$2 -> 1.1569023e+09 | D40: =D39/(1+'Study Parameters'!$C$4) ^'Production Cost Baseline'!D$2 -> 1.0761882e+09 | E40: =E39/(1+'Study Parameters'!$C$4) ^'Production Cost Baseline'!E$2 -> 1.0011053e+09 | F40: =F39/(1+'Study Parameters'!$C$4) ^'Production Cost Baseline'!F$2 -> 9.3126075e+08 | G40: =G39/(1+'Study Parameters'!$C$4) ^'Production Cost Baseline'!G$2 -> 8.6628907e+08 | H40: =H39/(1+'Study Parameters'!$C$4) ^'Production Cost Baseline'!H$2 -> 8.058503e+08 | I40: =I39/(1+'Study Parameters'!$C$4) ^'Production Cost Baseline'!I$2 -> 7.4962819e+08 | ... AA40: =AA39/(1+'Study Parameters'!$C$4) ^'Production Cost Baseline'!AA$2 -> 2.0393584e+08
A41: Fuel Production (kg) | B41: 0 | C41: ='Study Parameters'!$C$13*'Study Parameters'!$C$8 * 10^3 -> 28000000 | D41: ='Study Parameters'!$C$13*'Study Parameters'!$C$8 * 10^3 -> 28000000 | E41: ='Study Parameters'!$C$13*'Study Parameters'!$C$8 * 10^3 -> 28000000 | F41: ='Study Parameters'!$C$13*'Study Parameters'!$C$8 * 10^3 -> 28000000 | G41: ='Study Parameters'!$C$13*'Study Parameters'!$C$8 * 10^3 -> 28000000 | H41: ='Study Parameters'!$C$13*'Study Parameters'!$C$8 * 10^3 -> 28000000 | I41: ='Study Parameters'!$C$13*'Study Parameters'!$C$8 * 10^3 -> 28000000 | J41: ='Study Parameters'!$C$13*'Study Parameters'!$C$8 * 10^3 -> 28000000 | ... AA41: ='Study Parameters'!$C$13*'Study Parameters'!$C$8 * 10^3 -> 28000000
A42: Discounted Fuel Production (kg) | B42: 0 | C42: =C41/(1+'Study Parameters'!$C$4) ^'Production Cost Baseline'!C$2 -> 26046512 | D42: =D41/(1+'Study Parameters'!$C$4) ^'Production Cost Baseline'!D$2 -> 24229313 | E42: =E41/(1+'Study Parameters'!$C$4) ^'Production Cost Baseline'!E$2 -> 22538896 | F42: =F41/(1+'Study Parameters'!$C$4) ^'Production Cost Baseline'!F$2 -> 20966415 | G42: =G41/(1+'Study Parameters'!$C$4) ^'Production Cost Baseline'!G$2 -> 19503642 | H42: =H41/(1+'Study Parameters'!$C$4) ^'Production Cost Baseline'!H$2 -> 18142923 | I42: =I41/(1+'Study Parameters'!$C$4) ^'Production Cost Baseline'!I$2 -> 16877137 | J42: =J41/(1+'Study Parameters'!$C$4) ^'Production Cost Baseline'!J$2 -> 15699663 | ... AA42: =AA41/(1+'Study Parameters'!$C$4) ^'Production Cost Baseline'!AA$2 -> 4591413.7
A44: Production Cost of Fuel (€/kg) | B44: =SUM(B40:AA40) / SUM(C42:AA42) -> 49.303775
A45: Production Cost of Fuel (€/l) | B45: =B44 * Inputs!$C$15 -> 39.590931
A47: C.3 Hydropower
A48: Cost (€) | B48: ='Cost Components'!$D$12 * 10^6 -> 1594030000 | C48: =('Cost Components'!$D$21 + 'Cost Components'!$D$23) * 10^6 -> 3.978e+08 | D48: =('Cost Components'!$D$21 + 'Cost Components'!$D$23) * 10^6 -> 3.978e+08 | E48: =('Cost Components'!$D$21 + 'Cost Components'!$D$23) * 10^6 -> 3.978e+08 | F48: =('Cost Components'!$D$21 + 'Cost Components'!$D$23) * 10^6 -> 3.978e+08 | G48: =('Cost Components'!$D$21 + 'Cost Components'!$D$23) * 10^6 -> 3.978e+08 | H48: =('Cost Components'!$D$21 + 'Cost Components'!$D$23) * 10^6 -> 3.978e+08 | I48: =('Cost Components'!$D$21 + 'Cost Components'!$D$23) * 10^6 -> 3.978e+08 | J48: =('Cost Components'!$D$21 + 'Cost Components'!$D$23) * 10^6 -> 3.978e+08 | ... AA48: =('Cost Components'!$D$21 + 'Cost Components'!$D$23) * 10^6 -> 3.978e+08
A49: Revenue (€) | B49: 0 | C49: ='Cost Components'!$D$36*10^6 -> 81000000 | D49: ='Cost Components'!$D$36*10^6 -> 81000000 | E49: ='Cost Components'!$D$36*10^6 -> 81000000 | F49: ='Cost Components'!$D$36*10^6 -> 81000000 | G49: ='Cost Components'!$D$36*10^6 -> 81000000 | H49: ='Cost Components'!$D$36*10^6 -> 81000000 | I49: ='Cost Components'!$D$36*10^6 -> 81000000 | J49: ='Cost Components'!$D$36*10^6 -> 81000000 | ... AA49: ='Cost Components'!$D$36*10^6 -> 81000000
A50: Free Cash Flow (€) | B50: =B48-B49 -> 1594030000 | C50: =C48-C49 -> 3.168e+08 | D50: =D48-D49 -> 3.168e+08 | E50: =E48-E49 -> 3.168e+08 | F50: =F48-F49 -> 3.168e+08 | G50: =G48-G49 -> 3.168e+08 | H50: =H48-H49 -> 3.168e+08 | I50: =I48-I49 -> 3.168e+08 | ... AA50: =AA48-AA49 -> 3.168e+08
A51: Discounted Cash Flow (€) | B51: =B50/(1+'Study Parameters'!$C$4) ^'Production Cost Baseline'!B$2 -> 1594030000 | C51: =C50/(1+'Study Parameters'!$C$4) ^'Production Cost Baseline'!C$2 -> 2.9469767e+08 | D51: =D50/(1+'Study Parameters'!$C$4) ^'Production Cost Baseline'!D$2 -> 2.7413737e+08 | E51: =E50/(1+'Study Parameters'!$C$4) ^'Production Cost Baseline'!E$2 -> 2.5501151e+08 | F51: =F50/(1+'Study Parameters'!$C$4) ^'Production Cost Baseline'!F$2 -> 2.3722001e+08 | G51: =G50/(1+'Study Parameters'!$C$4) ^'Production Cost Baseline'!G$2 -> 2.2066977e+08 | H51: =H50/(1+'Study Parameters'!$C$4) ^'Production Cost Baseline'!H$2 -> 2.0527421e+08 | I51: =I50/(1+'Study Parameters'!$C$4) ^'Production Cost Baseline'!I$2 -> 1.9095275e+08 | ... AA51: =AA50/(1+'Study Parameters'!$C$4) ^'Production Cost Baseline'!AA$2 -> 51948566
A52: Fuel Production (kg) | B52: 0 | C52: ='Study Parameters'!$C$14*'Study Parameters'!$C$8 * 10^3 -> 38400000 | D52: ='Study Parameters'!$C$14*'Study Parameters'!$C$8 * 10^3 -> 38400000 | E52: ='Study Parameters'!$C$14*'Study Parameters'!$C$8 * 10^3 -> 38400000 | F52: ='Study Parameters'!$C$14*'Study Parameters'!$C$8 * 10^3 -> 38400000 | G52: ='Study Parameters'!$C$14*'Study Parameters'!$C$8 * 10^3 -> 38400000 | H52: ='Study Parameters'!$C$14*'Study Parameters'!$C$8 * 10^3 -> 38400000 | I52: ='Study Parameters'!$C$14*'Study Parameters'!$C$8 * 10^3 -> 38400000 | J52: ='Study Parameters'!$C$14*'Study Parameters'!$C$8 * 10^3 -> 38400000 | ... AA52: ='Study Parameters'!$C$14*'Study Parameters'!$C$8 * 10^3 -> 38400000
A53: Discounted Fuel Production (kg) | B53: 0 | C53: =C52/(1+'Study Parameters'!$C$4) ^'Production Cost Baseline'!C$2 -> 35720930 | D53: =D52/(1+'Study Parameters'!$C$4) ^'Production Cost Baseline'!D$2 -> 33228772 | E53: =E52/(1+'Study Parameters'!$C$4) ^'Production Cost Baseline'!E$2 -> 30910486 | F53: =F52/(1+'Study Parameters'!$C$4) ^'Production Cost Baseline'!F$2 -> 28753940 | G53: =G52/(1+'Study Parameters'!$C$4) ^'Production Cost Baseline'!G$2 -> 26747851 | H53: =H52/(1+'Study Parameters'!$C$4) ^'Production Cost Baseline'!H$2 -> 24881722 | I53: =I52/(1+'Study Parameters'!$C$4) ^'Production Cost Baseline'!I$2 -> 23145788 | J53: =J52/(1+'Study Parameters'!$C$4) ^'Production Cost Baseline'!J$2 -> 21530966 | ... AA53: =AA52/(1+'Study Parameters'!$C$4) ^'Production Cost Baseline'!AA$2 -> 6296795.9
A55: Production Cost of Fuel (€/kg) | B55: =SUM(B51:AA51) / SUM(C53:AA53) -> 11.973997
A56: Production Cost of Fuel (€/l) | B56: =B55 * Inputs!$C$15 -> 9.6151199
A58: C.3 Baseload
A59: Cost (€) | B59: ='Cost Components'!$D$12 * 10^6 -> 1594030000 | C59: =('Cost Components'!$D$21 + 'Cost Components'!$D$29) * 10^6 -> 1604800000 | D59: =('Cost Components'!$D$21 + 'Cost Components'!$D$29) * 10^6 -> 1604800000 | E59: =('Cost Components'!$D$21 + 'Cost Components'!$D$29) * 10^6 -> 1604800000 | F59: =('Cost Components'!$D$21 + 'Cost Components'!$D$29) * 10^6 -> 1604800000 | G59: =('Cost Components'!$D$21 + 'Cost Components'!$D$29) * 10^6 -> 1604800000 | H59: =('Cost Components'!$D$21 + 'Cost Components'!$D$29) * 10^6 -> 1604800000 | I59: =('Cost Components'!$D$21 + 'Cost Components'!$D$29) * 10^6 -> 1604800000 | J59: =('Cost Components'!$D$21 + 'Cost Components'!$D$29) * 10^6 -> 1604800000 | ... AA59: =('Cost Components'!$D$21 + 'Cost Components'!$D$29) * 10^6 -> 1604800000
A60: Revenue (€) | B60: 0 | C60: ='Cost Components'!$D$36*10^6 -> 81000000 | D60: ='Cost Components'!$D$36*10^6 -> 81000000 | E60: ='Cost Components'!$D$36*10^6 -> 81000000 | F60: ='Cost Components'!$D$36*10^6 -> 81000000 | G60: ='Cost Components'!$D$36*10^6 -> 81000000 | H60: ='Cost Components'!$D$36*10^6 -> 81000000 | I60: ='Cost Components'!$D$36*10^6 -> 81000000 | J60: ='Cost Components'!$D$36*10^6 -> 81000000 | ... AA60: ='Cost Components'!$D$36*10^6 -> 81000000
A61: Free Cash Flow (€) | B61: =B59-B60 -> 1594030000 | C61: =C59-C60 -> 1523800000 | D61: =D59-D60 -> 1523800000 | E61: =E59-E60 -> 1523800000 | F61: =F59-F60 -> 1523800000 | G61: =G59-G60 -> 1523800000 | H61: =H59-H60 -> 1523800000 | I61: =I59-I60 -> 1523800000 | ... AA61: =AA59-AA60 -> 1523800000
A62: Discounted Cash Flow (€) | B62: =B61/(1+'Study Parameters'!$C$4) ^'Production Cost Baseline'!B$2 -> 1594030000 | C62: =C61/(1+'Study Parameters'!$C$4) ^'Production Cost Baseline'!C$2 -> 1.4174884e+09 | D62: =D61/(1+'Study Parameters'!$C$4) ^'Production Cost Baseline'!D$2 -> 1.3185938e+09 | E62: =E61/(1+'Study Parameters'!$C$4) ^'Production Cost Baseline'!E$2 -> 1.2265989e+09 | F62: =F61/(1+'Study Parameters'!$C$4) ^'Production Cost Baseline'!F$2 -> 1.1410222e+09 | G62: =G61/(1+'Study Parameters'!$C$4) ^'Production Cost Baseline'!G$2 -> 1.061416e+09 | H62: =H61/(1+'Study Parameters'!$C$4) ^'Production Cost Baseline'!H$2 -> 9.8736376e+08 | I62: =I61/(1+'Study Parameters'!$C$4) ^'Production Cost Baseline'!I$2 -> 9.1847792e+08 | ... AA62: =AA61/(1+'Study Parameters'!$C$4) ^'Production Cost Baseline'!AA$2 -> 2.4987129e+08
A63: Fuel Production (kg) | B63: 0 | C63: ='Study Parameters'!$C$14*'Study Parameters'!$C$8 * 10^3 -> 38400000 | D63: ='Study Parameters'!$C$14*'Study Parameters'!$C$8 * 10^3 -> 38400000 | E63: ='Study Parameters'!$C$14*'Study Parameters'!$C$8 * 10^3 -> 38400000 | F63: ='Study Parameters'!$C$14*'Study Parameters'!$C$8 * 10^3 -> 38400000 | G63: ='Study Parameters'!$C$14*'Study Parameters'!$C$8 * 10^3 -> 38400000 | H63: ='Study Parameters'!$C$14*'Study Parameters'!$C$8 * 10^3 -> 38400000 | I63: ='Study Parameters'!$C$14*'Study Parameters'!$C$8 * 10^3 -> 38400000 | J63: ='Study Parameters'!$C$14*'Study Parameters'!$C$8 * 10^3 -> 38400000 | ... AA63: ='Study Parameters'!$C$14*'Study Parameters'!$C$8 * 10^3 -> 38400000
A64: Discounted Fuel Production (kg) | B64: 0 | C64: =C63/(1+'Study Parameters'!$C$4) ^'Production Cost Baseline'!C$2 -> 35720930 | D64: =D63/(1+'Study Parameters'!$C$4) ^'Production Cost Baseline'!D$2 -> 33228772 | E64: =E63/(1+'Study Parameters'!$C$4) ^'Production Cost Baseline'!E$2 -> 30910486 | F64: =F63/(1+'Study Parameters'!$C$4) ^'Production Cost Baseline'!F$2 -> 28753940 | G64: =G63/(1+'Study Parameters'!$C$4) ^'Production Cost Baseline'!G$2 -> 26747851 | H64: =H63/(1+'Study Parameters'!$C$4) ^'Production Cost Baseline'!H$2 -> 24881722 | I64: =I63/(1+'Study Parameters'!$C$4) ^'Production Cost Baseline'!I$2 -> 23145788 | J64: =J63/(1+'Study Parameters'!$C$4) ^'Production Cost Baseline'!J$2 -> 21530966 | ... AA64: =AA63/(1+'Study Parameters'!$C$4) ^'Production Cost Baseline'!AA$2 -> 6296795.9
A66: Production Cost of Fuel (€/kg) | B66: =SUM(B62:AA62) / SUM(C64:AA64) -> 43.406289
A67: Production Cost of Fuel (€/l) | B67: =B66 * Inputs!$C$15 -> 34.85525
A69: C.4 Hydropower
A70: Cost (€) | B70: ='Cost Components'!$E$12 * 10^6 -> 1.43992e+09 | C70: =('Cost Components'!$E$21 + 'Cost Components'!$E$23) * 10^6 -> 358100000 | D70: =('Cost Components'!$E$21 + 'Cost Components'!$E$23) * 10^6 -> 358100000 | E70: =('Cost Components'!$E$21 + 'Cost Components'!$E$23) * 10^6 -> 358100000 | F70: =('Cost Components'!$E$21 + 'Cost Components'!$E$23) * 10^6 -> 358100000 | G70: =('Cost Components'!$E$21 + 'Cost Components'!$E$23) * 10^6 -> 358100000 | H70: =('Cost Components'!$E$21 + 'Cost Components'!$E$23) * 10^6 -> 358100000 | I70: =('Cost Components'!$E$21 + 'Cost Components'!$E$23) * 10^6 -> 358100000 | J70: =('Cost Components'!$E$21 + 'Cost Components'!$E$23) * 10^6 -> 358100000 | ... AA70: =('Cost Components'!$E$21 + 'Cost Components'!$E$23) * 10^6 -> 358100000
A71: Revenue (€) | B71: 0 | C71: ='Cost Components'!$E$36*10^6 -> 103200000 | D71: ='Cost Components'!$E$36*10^6 -> 103200000 | E71: ='Cost Components'!$E$36*10^6 -> 103200000 | F71: ='Cost Components'!$E$36*10^6 -> 103200000 | G71: ='Cost Components'!$E$36*10^6 -> 103200000 | H71: ='Cost Components'!$E$36*10^6 -> 103200000 | I71: ='Cost Components'!$E$36*10^6 -> 103200000 | J71: ='Cost Components'!$E$36*10^6 -> 103200000 | ... AA71: ='Cost Components'!$E$36*10^6 -> 103200000
A72: Free Cash Flow (€) | B72: =B70-B71 -> 1.43992e+09 | C72: =C70-C71 -> 254900000 | D72: =D70-D71 -> 254900000 | E72: =E70-E71 -> 254900000 | F72: =F70-F71 -> 254900000 | G72: =G70-G71 -> 254900000 | H72: =H70-H71 -> 254900000 | I72: =I70-I71 -> 254900000 | ... AA72: =AA70-AA71 -> 254900000
A73: Discounted Cash Flow (€) | B73: =B72/(1+'Study Parameters'!$C$4) ^'Production Cost Baseline'!B$2 -> 1.43992e+09 | C73: =C72/(1+'Study Parameters'!$C$4) ^'Production Cost Baseline'!C$2 -> 2.3711628e+08 | D73: =D72/(1+'Study Parameters'!$C$4) ^'Production Cost Baseline'!D$2 -> 2.2057328e+08 | E73: =E72/(1+'Study Parameters'!$C$4) ^'Production Cost Baseline'!E$2 -> 2.0518445e+08 | F73: =F72/(1+'Study Parameters'!$C$4) ^'Production Cost Baseline'!F$2 -> 1.9086926e+08 | G73: =G72/(1+'Study Parameters'!$C$4) ^'Production Cost Baseline'!G$2 -> 1.775528e+08 | H73: =H72/(1+'Study Parameters'!$C$4) ^'Production Cost Baseline'!H$2 -> 1.6516539e+08 | I73: =I72/(1+'Study Parameters'!$C$4) ^'Production Cost Baseline'!I$2 -> 1.5364222e+08 | ... AA73: =AA72/(1+'Study Parameters'!$C$4) ^'Production Cost Baseline'!AA$2 -> 41798263
A74: Fuel Production (kg) | B74: 0 | C74: ='Study Parameters'!$C$15*'Study Parameters'!$C$8 * 10^3 -> 55200000 | D74: ='Study Parameters'!$C$15*'Study Parameters'!$C$8 * 10^3 -> 55200000 | E74: ='Study Parameters'!$C$15*'Study Parameters'!$C$8 * 10^3 -> 55200000 | F74: ='Study Parameters'!$C$15*'Study Parameters'!$C$8 * 10^3 -> 55200000 | G74: ='Study Parameters'!$C$15*'Study Parameters'!$C$8 * 10^3 -> 55200000 | H74: ='Study Parameters'!$C$15*'Study Parameters'!$C$8 * 10^3 -> 55200000 | I74: ='Study Parameters'!$C$15*'Study Parameters'!$C$8 * 10^3 -> 55200000 | J74: ='Study Parameters'!$C$15*'Study Parameters'!$C$8 * 10^3 -> 55200000 | ... AA74: ='Study Parameters'!$C$15*'Study Parameters'!$C$8 * 10^3 -> 55200000
A75: Discounted Fuel Production (kg) | B75: 0 | C75: =C74/(1+'Study Parameters'!$C$4) ^'Production Cost Baseline'!C$2 -> 51348837 | D75: =D74/(1+'Study Parameters'!$C$4) ^'Production Cost Baseline'!D$2 -> 47766360 | E75: =E74/(1+'Study Parameters'!$C$4) ^'Production Cost Baseline'!E$2 -> 44433823 | F75: =F74/(1+'Study Parameters'!$C$4) ^'Production Cost Baseline'!F$2 -> 41333789 | G75: =G74/(1+'Study Parameters'!$C$4) ^'Production Cost Baseline'!G$2 -> 38450037 | H75: =H74/(1+'Study Parameters'!$C$4) ^'Production Cost Baseline'!H$2 -> 35767476 | I75: =I74/(1+'Study Parameters'!$C$4) ^'Production Cost Baseline'!I$2 -> 33272071 | J75: =J74/(1+'Study Parameters'!$C$4) ^'Production Cost Baseline'!J$2 -> 30950763 | ... AA75: =AA74/(1+'Study Parameters'!$C$4) ^'Production Cost Baseline'!AA$2 -> 9051644.1
A77: Production Cost of Fuel (€/kg) | B77: =SUM(B73:AA73) / SUM(C75:AA75) -> 6.957902
A78: Production Cost of Fuel (€/l) | B78: =B77 * Inputs!$C$15 -> 5.5871953
A80: C.4 Baseload
A81: Cost (€) | B81: ='Cost Components'!$E$12 * 10^6 -> 1.43992e+09 | C81: =('Cost Components'!$E$21 + 'Cost Components'!$E$29) * 10^6 -> 1465600000 | D81: =('Cost Components'!$E$21 + 'Cost Components'!$E$29) * 10^6 -> 1465600000 | E81: =('Cost Components'!$E$21 + 'Cost Components'!$E$29) * 10^6 -> 1465600000 | F81: =('Cost Components'!$E$21 + 'Cost Components'!$E$29) * 10^6 -> 1465600000 | G81: =('Cost Components'!$E$21 + 'Cost Components'!$E$29) * 10^6 -> 1465600000 | H81: =('Cost Components'!$E$21 + 'Cost Components'!$E$29) * 10^6 -> 1465600000 | I81: =('Cost Components'!$E$21 + 'Cost Components'!$E$29) * 10^6 -> 1465600000 | J81: =('Cost Components'!$E$21 + 'Cost Components'!$E$29) * 10^6 -> 1465600000 | ... AA81: =('Cost Components'!$E$21 + 'Cost Components'!$E$29) * 10^6 -> 1465600000
A82: Revenue (€) | B82: 0 | C82: ='Cost Components'!$E$36*10^6 -> 103200000 | D82: ='Cost Components'!$E$36*10^6 -> 103200000 | E82: ='Cost Components'!$E$36*10^6 -> 103200000 | F82: ='Cost Components'!$E$36*10^6 -> 103200000 | G82: ='Cost Components'!$E$36*10^6 -> 103200000 | H82: ='Cost Components'!$E$36*10^6 -> 103200000 | I82: ='Cost Components'!$E$36*10^6 -> 103200000 | J82: ='Cost Components'!$E$36*10^6 -> 103200000 | ... AA82: ='Cost Components'!$E$36*10^6 -> 103200000
A83: Free Cash Flow (€) | B83: =B81-B82 -> 1.43992e+09 | C83: =C81-C82 -> 1362400000 | D83: =D81-D82 -> 1362400000 | E83: =E81-E82 -> 1362400000 | F83: =F81-F82 -> 1362400000 | G83: =G81-G82 -> 1362400000 | H83: =H81-H82 -> 1362400000 | I83: =I81-I82 -> 1362400000 | ... AA83: =AA81-AA82 -> 1362400000
A84: Discounted Cash Flow (€) | B84: =B83/(1+'Study Parameters'!$C$4) ^'Production Cost Baseline'!B$2 -> 1.43992e+09 | C84: =C83/(1+'Study Parameters'!$C$4) ^'Production Cost Baseline'!C$2 -> 1.2673488e+09 | D84: =D83/(1+'Study Parameters'!$C$4) ^'Production Cost Baseline'!D$2 -> 1.1789292e+09 | E84: =E83/(1+'Study Parameters'!$C$4) ^'Production Cost Baseline'!E$2 -> 1.0966783e+09 | F84: =F83/(1+'Study Parameters'!$C$4) ^'Production Cost Baseline'!F$2 -> 1.0201658e+09 | G84: =G83/(1+'Study Parameters'!$C$4) ^'Production Cost Baseline'!G$2 -> 9.4899148e+08 | H84: =H83/(1+'Study Parameters'!$C$4) ^'Production Cost Baseline'!H$2 -> 8.8278277e+08 | I84: =I83/(1+'Study Parameters'!$C$4) ^'Production Cost Baseline'!I$2 -> 8.2119328e+08 | ... AA84: =AA83/(1+'Study Parameters'!$C$4) ^'Production Cost Baseline'!AA$2 -> 2.2340507e+08
A85: Fuel Production (kg) | B85: 0 | C85: ='Study Parameters'!$C$15*'Study Parameters'!$C$8 * 10^3 -> 55200000 | D85: ='Study Parameters'!$C$15*'Study Parameters'!$C$8 * 10^3 -> 55200000 | E85: ='Study Parameters'!$C$15*'Study Parameters'!$C$8 * 10^3 -> 55200000 | F85: ='Study Parameters'!$C$15*'Study Parameters'!$C$8 * 10^3 -> 55200000 | G85: ='Study Parameters'!$C$15*'Study Parameters'!$C$8 * 10^3 -> 55200000 | H85: ='Study Parameters'!$C$15*'Study Parameters'!$C$8 * 10^3 -> 55200000 | I85: ='Study Parameters'!$C$15*'Study Parameters'!$C$8 * 10^3 -> 55200000 | J85: ='Study Parameters'!$C$15*'Study Parameters'!$C$8 * 10^3 -> 55200000 | ... AA85: ='Study Parameters'!$C$15*'Study Parameters'!$C$8 * 10^3 -> 55200000
A86: Discounted Fuel Production (kg) | B86: 0 | C86: =C85/(1+'Study Parameters'!$C$4) ^'Production Cost Baseline'!C$2 -> 51348837 | D86: =D85/(1+'Study Parameters'!$C$4) ^'Production Cost Baseline'!D$2 -> 47766360 | E86: =E85/(1+'Study Parameters'!$C$4) ^'Production Cost Baseline'!E$2 -> 44433823 | F86: =F85/(1+'Study Parameters'!$C$4) ^'Production Cost Baseline'!F$2 -> 41333789 | G86: =G85/(1+'Study Parameters'!$C$4) ^'Production Cost Baseline'!G$2 -> 38450037 | H86: =H85/(1+'Study Parameters'!$C$4) ^'Production Cost Baseline'!H$2 -> 35767476 | I86: =I85/(1+'Study Parameters'!$C$4) ^'Production Cost Baseline'!I$2 -> 33272071 | J86: =J85/(1+'Study Parameters'!$C$4) ^'Production Cost Baseline'!J$2 -> 30950763 | ... AA86: =AA85/(1+'Study Parameters'!$C$4) ^'Production Cost Baseline'!AA$2 -> 9051644.1
A88: Production Cost of Fuel (€/kg) | B88: =SUM(B84:AA84) / SUM(C86:AA86) -> 27.021308
A89: Production Cost of Fuel (€/l) | B89: =B88 * Inputs!$C$15 -> 21.69811
A91: C.5 Hydropower
A92: Cost (€) | B92: ='Cost Components'!$F$12 * 10^6 -> 1482660000 | C92: =('Cost Components'!$F$21 + 'Cost Components'!$F$23) * 10^6 -> 440100000 | D92: =('Cost Components'!$F$21 + 'Cost Components'!$F$23) * 10^6 -> 440100000 | E92: =('Cost Components'!$F$21 + 'Cost Components'!$F$23) * 10^6 -> 440100000 | F92: =('Cost Components'!$F$21 + 'Cost Components'!$F$23) * 10^6 -> 440100000 | G92: =('Cost Components'!$F$21 + 'Cost Components'!$F$23) * 10^6 -> 440100000 | H92: =('Cost Components'!$F$21 + 'Cost Components'!$F$23) * 10^6 -> 440100000 | I92: =('Cost Components'!$F$21 + 'Cost Components'!$F$23) * 10^6 -> 440100000 | J92: =('Cost Components'!$F$21 + 'Cost Components'!$F$23) * 10^6 -> 440100000 | ... AA92: =('Cost Components'!$F$21 + 'Cost Components'!$F$23) * 10^6 -> 440100000
A93: Revenue (€) | B93: 0 | C93: ='Cost Components'!$F$36*10^6 -> 135200000 | D93: ='Cost Components'!$F$36*10^6 -> 135200000 | E93: ='Cost Components'!$F$36*10^6 -> 135200000 | F93: ='Cost Components'!$F$36*10^6 -> 135200000 | G93: ='Cost Components'!$F$36*10^6 -> 135200000 | H93: ='Cost Components'!$F$36*10^6 -> 135200000 | I93: ='Cost Components'!$F$36*10^6 -> 135200000 | J93: ='Cost Components'!$F$36*10^6 -> 135200000 | ... AA93: ='Cost Components'!$F$36*10^6 -> 135200000
A94: Free Cash Flow (€) | B94: =B92-B93 -> 1482660000 | C94: =C92-C93 -> 304900000 | D94: =D92-D93 -> 304900000 | E94: =E92-E93 -> 304900000 | F94: =F92-F93 -> 304900000 | G94: =G92-G93 -> 304900000 | H94: =H92-H93 -> 304900000 | I94: =I92-I93 -> 304900000 | ... AA94: =AA92-AA93 -> 304900000
A95: Discounted Cash Flow (€) | B95: =B94/(1+'Study Parameters'!$C$4) ^'Production Cost Baseline'!B$2 -> 1482660000 | C95: =C94/(1+'Study Parameters'!$C$4) ^'Production Cost Baseline'!C$2 -> 2.8362791e+08 | D95: =D94/(1+'Study Parameters'!$C$4) ^'Production Cost Baseline'!D$2 -> 2.6383991e+08 | E95: =E94/(1+'Study Parameters'!$C$4) ^'Production Cost Baseline'!E$2 -> 2.4543248e+08 | F95: =F94/(1+'Study Parameters'!$C$4) ^'Production Cost Baseline'!F$2 -> 2.2830928e+08 | G95: =G94/(1+'Study Parameters'!$C$4) ^'Production Cost Baseline'!G$2 -> 2.1238073e+08 | H95: =H94/(1+'Study Parameters'!$C$4) ^'Production Cost Baseline'!H$2 -> 1.9756347e+08 | I95: =I94/(1+'Study Parameters'!$C$4) ^'Production Cost Baseline'!I$2 -> 1.8377997e+08 | ... AA95: =AA94/(1+'Study Parameters'!$C$4) ^'Production Cost Baseline'!AA$2 -> 49997216
A96: Fuel Production (kg) | B96: 0 | C96: ='Study Parameters'!$C$16*'Study Parameters'!$C$8 * 10^3 -> 54400000 | D96: ='Study Parameters'!$C$16*'Study Parameters'!$C$8 * 10^3 -> 54400000 | E96: ='Study Parameters'!$C$16*'Study Parameters'!$C$8 * 10^3 -> 54400000 | F96: ='Study Parameters'!$C$16*'Study Parameters'!$C$8 * 10^3 -> 54400000 | G96: ='Study Parameters'!$C$16*'Study Parameters'!$C$8 * 10^3 -> 54400000 | H96: ='Study Parameters'!$C$16*'Study Parameters'!$C$8 * 10^3 -> 54400000 | I96: ='Study Parameters'!$C$16*'Study Parameters'!$C$8 * 10^3 -> 54400000 | J96: ='Study Parameters'!$C$16*'Study Parameters'!$C$8 * 10^3 -> 54400000 | ... AA96: ='Study Parameters'!$C$16*'Study Parameters'!$C$8 * 10^3 -> 54400000
A97: Discounted Fuel Production (kg) | B97: 0 | C97: =C96/(1+'Study Parameters'!$C$4) ^'Production Cost Baseline'!C$2 -> 50604651 | D97: =D96/(1+'Study Parameters'!$C$4) ^'Production Cost Baseline'!D$2 -> 47074094 | E97: =E96/(1+'Study Parameters'!$C$4) ^'Production Cost Baseline'!E$2 -> 43789855 | F97: =F96/(1+'Study Parameters'!$C$4) ^'Production Cost Baseline'!F$2 -> 40734749 | G97: =G96/(1+'Study Parameters'!$C$4) ^'Production Cost Baseline'!G$2 -> 37892790 | H97: =H96/(1+'Study Parameters'!$C$4) ^'Production Cost Baseline'!H$2 -> 35249107 | I97: =I96/(1+'Study Parameters'!$C$4) ^'Production Cost Baseline'!I$2 -> 32789867 | J97: =J96/(1+'Study Parameters'!$C$4) ^'Production Cost Baseline'!J$2 -> 30502201 | ... AA97: =AA96/(1+'Study Parameters'!$C$4) ^'Production Cost Baseline'!AA$2 -> 8920460.9
A99: Production Cost of Fuel (€/kg) | B99: =SUM(B95:AA95) / SUM(C97:AA97) -> 8.049824
A100: Production Cost of Fuel (€/l) | B100: =B99 * Inputs!$C$15 -> 6.4640087
A102: C.5 Baseload
A103: Cost (€) | B103: ='Cost Components'!$F$12 * 10^6 -> 1482660000 | C103: =('Cost Components'!$F$21 + 'Cost Components'!$F$29) * 10^6 -> 1839900000 | D103: =('Cost Components'!$F$21 + 'Cost Components'!$F$29) * 10^6 -> 1839900000 | E103: =('Cost Components'!$F$21 + 'Cost Components'!$F$29) * 10^6 -> 1839900000 | F103: =('Cost Components'!$F$21 + 'Cost Components'!$F$29) * 10^6 -> 1839900000 | G103: =('Cost Components'!$F$21 + 'Cost Components'!$F$29) * 10^6 -> 1839900000 | H103: =('Cost Components'!$F$21 + 'Cost Components'!$F$29) * 10^6 -> 1839900000 | I103: =('Cost Components'!$F$21 + 'Cost Components'!$F$29) * 10^6 -> 1839900000 | J103: =('Cost Components'!$F$21 + 'Cost Components'!$F$29) * 10^6 -> 1839900000 | ... AA103: =('Cost Components'!$F$21 + 'Cost Components'!$F$29) * 10^6 -> 1839900000
A104: Revenue (€) | B104: 0 | C104: ='Cost Components'!$F$36*10^6 -> 135200000 | D104: ='Cost Components'!$F$36*10^6 -> 135200000 | E104: ='Cost Components'!$F$36*10^6 -> 135200000 | F104: ='Cost Components'!$F$36*10^6 -> 135200000 | G104: ='Cost Components'!$F$36*10^6 -> 135200000 | H104: ='Cost Components'!$F$36*10^6 -> 135200000 | I104: ='Cost Components'!$F$36*10^6 -> 135200000 | J104: ='Cost Components'!$F$36*10^6 -> 135200000 | ... AA104: ='Cost Components'!$F$36*10^6 -> 135200000
A105: Free Cash Flow (€) | B105: =B103-B104 -> 1482660000 | C105: =C103-C104 -> 1704700000 | D105: =D103-D104 -> 1704700000 | E105: =E103-E104 -> 1704700000 | F105: =F103-F104 -> 1704700000 | G105: =G103-G104 -> 1704700000 | H105: =H103-H104 -> 1704700000 | I105: =I103-I104 -> 1704700000 | ... AA105: =AA103-AA104 -> 1704700000
A106: Discounted Cash Flow (€) | B106: =B105/(1+'Study Parameters'!$C$4) ^'Production Cost Baseline'!B$2 -> 1482660000 | C106: =C105/(1+'Study Parameters'!$C$4) ^'Production Cost Baseline'!C$2 -> 1.5857674e+09 | D106: =D105/(1+'Study Parameters'!$C$4) ^'Production Cost Baseline'!D$2 -> 1.4751325e+09 | E106: =E105/(1+'Study Parameters'!$C$4) ^'Production Cost Baseline'!E$2 -> 1.3722163e+09 | F106: =F105/(1+'Study Parameters'!$C$4) ^'Production Cost Baseline'!F$2 -> 1.2764803e+09 | G106: =G105/(1+'Study Parameters'!$C$4) ^'Production Cost Baseline'!G$2 -> 1.1874235e+09 | H106: =H105/(1+'Study Parameters'!$C$4) ^'Production Cost Baseline'!H$2 -> 1.10458e+09 | I106: =I105/(1+'Study Parameters'!$C$4) ^'Production Cost Baseline'!I$2 -> 1.0275163e+09 | ... AA106: =AA105/(1+'Study Parameters'!$C$4) ^'Production Cost Baseline'!AA$2 -> 2.795351e+08
A107: Fuel Production (kg) | B107: 0 | C107: ='Study Parameters'!$C$16*'Study Parameters'!$C$8 * 10^3 -> 54400000 | D107: ='Study Parameters'!$C$16*'Study Parameters'!$C$8 * 10^3 -> 54400000 | E107: ='Study Parameters'!$C$16*'Study Parameters'!$C$8 * 10^3 -> 54400000 | F107: ='Study Parameters'!$C$16*'Study Parameters'!$C$8 * 10^3 -> 54400000 | G107: ='Study Parameters'!$C$16*'Study Parameters'!$C$8 * 10^3 -> 54400000 | H107: ='Study Parameters'!$C$16*'Study Parameters'!$C$8 * 10^3 -> 54400000 | I107: ='Study Parameters'!$C$16*'Study Parameters'!$C$8 * 10^3 -> 54400000 | J107: ='Study Parameters'!$C$16*'Study Parameters'!$C$8 * 10^3 -> 54400000 | ... AA107: ='Study Parameters'!$C$16*'Study Parameters'!$C$8 * 10^3 -> 54400000
A108: Discounted Fuel Production (kg) | B108: 0 | C108: =C107/(1+'Study Parameters'!$C$4) ^'Production Cost Baseline'!C$2 -> 50604651 | D108: =D107/(1+'Study Parameters'!$C$4) ^'Production Cost Baseline'!D$2 -> 47074094 | E108: =E107/(1+'Study Parameters'!$C$4) ^'Production Cost Baseline'!E$2 -> 43789855 | F108: =F107/(1+'Study Parameters'!$C$4) ^'Production Cost Baseline'!F$2 -> 40734749 | G108: =G107/(1+'Study Parameters'!$C$4) ^'Production Cost Baseline'!G$2 -> 37892790 | H108: =H107/(1+'Study Parameters'!$C$4) ^'Production Cost Baseline'!H$2 -> 35249107 | I108: =I107/(1+'Study Parameters'!$C$4) ^'Production Cost Baseline'!I$2 -> 32789867 | J108: =J107/(1+'Study Parameters'!$C$4) ^'Production Cost Baseline'!J$2 -> 30502201 | ... AA108: =AA107/(1+'Study Parameters'!$C$4) ^'Production Cost Baseline'!AA$2 -> 8920460.9
A110: Production Cost of Fuel (€/kg) | B110: =SUM(B106:AA106) / SUM(C108:AA108) -> 33.781442
A111: Production Cost of Fuel (€/l) | B111: =B110 * Inputs!$C$15 -> 27.126498
A113: 2050
A114: C.1 Baseload
A115: Cost (€) | B115: ='Cost Components'!$M$12 * 10^6 -> 575000000 | C115: ='Cost Components'!$M$21*10^6 -> 2.7511317e+08 | D115: ='Cost Components'!$M$21*10^6 -> 2.7511317e+08 | E115: ='Cost Components'!$M$21*10^6 -> 2.7511317e+08 | F115: ='Cost Components'!$M$21*10^6 -> 2.7511317e+08 | G115: ='Cost Components'!$M$21*10^6 -> 2.7511317e+08 | H115: ='Cost Components'!$M$21*10^6 -> 2.7511317e+08 | I115: ='Cost Components'!$M$21*10^6 -> 2.7511317e+08 | J115: ='Cost Components'!$M$21*10^6 -> 2.7511317e+08 | ... AA115: ='Cost Components'!$M$21*10^6 -> 2.7511317e+08
A116: Revenue (€) | B116: 0 | C116: ='Cost Components'!$M$36 * 10^6 -> 149900000 | D116: ='Cost Components'!$M$36 * 10^6 -> 149900000 | E116: ='Cost Components'!$M$36 * 10^6 -> 149900000 | F116: ='Cost Components'!$M$36 * 10^6 -> 149900000 | G116: ='Cost Components'!$M$36 * 10^6 -> 149900000 | H116: ='Cost Components'!$M$36 * 10^6 -> 149900000 | I116: ='Cost Components'!$M$36 * 10^6 -> 149900000 | J116: ='Cost Components'!$M$36 * 10^6 -> 149900000 | ... AA116: ='Cost Components'!$M$36 * 10^6 -> 149900000
A117: Free Cash Flow (€) | B117: =B115-B116 -> 575000000 | C117: =C115-C116 -> 1.2521317e+08 | D117: =D115-D116 -> 1.2521317e+08 | E117: =E115-E116 -> 1.2521317e+08 | F117: =F115-F116 -> 1.2521317e+08 | G117: =G115-G116 -> 1.2521317e+08 | H117: =H115-H116 -> 1.2521317e+08 | I117: =I115-I116 -> 1.2521317e+08 | ... AA117: =AA115-AA116 -> 1.2521317e+08
A118: Discounted Cash Flow (€) | B118: =B117/(1+'Study Parameters'!$C$4) ^'Production Cost Baseline'!B$2 -> 575000000 | C118: =C117/(1+'Study Parameters'!$C$4) ^'Production Cost Baseline'!C$2 -> 1.1647737e+08 | D118: =D117/(1+'Study Parameters'!$C$4) ^'Production Cost Baseline'!D$2 -> 1.0835104e+08 | E118: =E117/(1+'Study Parameters'!$C$4) ^'Production Cost Baseline'!E$2 -> 1.0079166e+08 | F118: =F117/(1+'Study Parameters'!$C$4) ^'Production Cost Baseline'!F$2 -> 93759686 | G118: =G117/(1+'Study Parameters'!$C$4) ^'Production Cost Baseline'!G$2 -> 87218313 | H118: =H117/(1+'Study Parameters'!$C$4) ^'Production Cost Baseline'!H$2 -> 81133314 | I118: =I117/(1+'Study Parameters'!$C$4) ^'Production Cost Baseline'!I$2 -> 75472850 | ... AA118: =AA117/(1+'Study Parameters'!$C$4) ^'Production Cost Baseline'!AA$2 -> 20532338
A119: Fuel Production (kg) | B119: 0 | C119: ='Study Parameters'!$C$12*'Study Parameters'!$C$8 * 10^3 -> 69600000 | D119: ='Study Parameters'!$C$12*'Study Parameters'!$C$8 * 10^3 -> 69600000 | E119: ='Study Parameters'!$C$12*'Study Parameters'!$C$8 * 10^3 -> 69600000 | F119: ='Study Parameters'!$C$12*'Study Parameters'!$C$8 * 10^3 -> 69600000 | G119: ='Study Parameters'!$C$12*'Study Parameters'!$C$8 * 10^3 -> 69600000 | H119: ='Study Parameters'!$C$12*'Study Parameters'!$C$8 * 10^3 -> 69600000 | I119: ='Study Parameters'!$C$12*'Study Parameters'!$C$8 * 10^3 -> 69600000 | J119: ='Study Parameters'!$C$12*'Study Parameters'!$C$8 * 10^3 -> 69600000 | ... AA119: ='Study Parameters'!$C$12*'Study Parameters'!$C$8 * 10^3 -> 69600000
A120: Discounted Fuel Production (kg) | B120: =B119/(1+'Study Parameters'!$C$4) ^'Production Cost Baseline'!B$2 -> 0 | C120: =C119/(1+'Study Parameters'!$C$4) ^'Production Cost Baseline'!C$2 -> 64744186 | D120: =D119/(1+'Study Parameters'!$C$4) ^'Production Cost Baseline'!D$2 -> 60227150 | E120: =E119/(1+'Study Parameters'!$C$4) ^'Production Cost Baseline'!E$2 -> 56025256 | F120: =F119/(1+'Study Parameters'!$C$4) ^'Production Cost Baseline'!F$2 -> 52116517 | G120: =G119/(1+'Study Parameters'!$C$4) ^'Production Cost Baseline'!G$2 -> 48480481 | H120: =H119/(1+'Study Parameters'!$C$4) ^'Production Cost Baseline'!H$2 -> 45098122 | I120: =I119/(1+'Study Parameters'!$C$4) ^'Production Cost Baseline'!I$2 -> 41951741 | ... AA120: =AA119/(1+'Study Parameters'!$C$4) ^'Production Cost Baseline'!AA$2 -> 11412943
...

Sheet LCOE Corrected Production Cost 
A1: 2021
A2: Year | B2: 0 | C2: 1 | D2: 2 | E2: 3 | F2: 4 | G2: 5 | H2: 6 | I2: 7 | J2: 8 | K2: 9 | L2: 10 | M2: 11 | N2: 12 | O2: 13 | P2: 14 | Q2: 15 | R2: 16 | S2: 17 | T2: 18 | U2: 19 | V2: 20 | W2: 21 | X2: 22 | Y2: 23 | Z2: 24 | AA2: 25
A3: C.1 Baseload
A4: Cost (€) | B4: ='Cost Components'!$B$12 * 10^6 -> 1870760000 | C4: =('Cost Components'!$B$21 + 'Cost Components'!$B$40) * 10^6 -> 2.7253886e+08 | D4: =('Cost Components'!$B$21 + 'Cost Components'!$B$40) * 10^6 -> 2.7253886e+08 | E4: =('Cost Components'!$B$21 + 'Cost Components'!$B$40) * 10^6 -> 2.7253886e+08 | F4: =('Cost Components'!$B$21 + 'Cost Components'!$B$40) * 10^6 -> 2.7253886e+08 | G4: =('Cost Components'!$B$21 + 'Cost Components'!$B$40) * 10^6 -> 2.7253886e+08 | H4: =('Cost Components'!$B$21 + 'Cost Components'!$B$40) * 10^6 -> 2.7253886e+08 | I4: =('Cost Components'!$B$21 + 'Cost Components'!$B$40) * 10^6 -> 2.7253886e+08 | J4: =('Cost Components'!$B$21 + 'Cost Components'!$B$40) * 10^6 -> 2.7253886e+08 | ... AA4: =('Cost Components'!$B$21 + 'Cost Components'!$B$40) * 10^6 -> 2.7253886e+08
A5: Revenue (€) | B5: 0 | C5: ='Cost Components'!$B$36*10^6 -> 56800000 | D5: ='Cost Components'!$B$36*10^6 -> 56800000 | E5: ='Cost Components'!$B$36*10^6 -> 56800000 | F5: ='Cost Components'!$B$36*10^6 -> 56800000 | G5: ='Cost Components'!$B$36*10^6 -> 56800000 | H5: ='Cost Components'!$B$36*10^6 -> 56800000 | I5: ='Cost Components'!$B$36*10^6 -> 56800000 | J5: ='Cost Components'!$B$36*10^6 -> 56800000 | ... AA5: ='Cost Components'!$B$36*10^6 -> 56800000
A6: Free Cash Flow (€) | B6: =B4-B5 -> 1870760000 | C6: =C4-C5 -> 2.1573886e+08 | D6: =D4-D5 -> 2.1573886e+08 | E6: =E4-E5 -> 2.1573886e+08 | F6: =F4-F5 -> 2.1573886e+08 | G6: =G4-G5 -> 2.1573886e+08 | H6: =H4-H5 -> 2.1573886e+08 | I6: =I4-I5 -> 2.1573886e+08 | ... AA6: =AA4-AA5 -> 2.1573886e+08
A7: Discounted Cash Flow (€) | B7: =B6/(1+'Study Parameters'!$C$4) ^'Production Cost Baseline'!B$2 -> 1870760000 | C7: =C6/(1+'Study Parameters'!$C$4) ^'Production Cost Baseline'!C$2 -> 2.0068731e+08 | D7: =D6/(1+'Study Parameters'!$C$4) ^'Production Cost Baseline'!D$2 -> 1.8668587e+08 | E7: =E6/(1+'Study Parameters'!$C$4) ^'Production Cost Baseline'!E$2 -> 1.7366127e+08 | F7: =F6/(1+'Study Parameters'!$C$4) ^'Production Cost Baseline'!F$2 -> 1.6154537e+08 | G7: =G6/(1+'Study Parameters'!$C$4) ^'Production Cost Baseline'!G$2 -> 1.5027476e+08 | H7: =H6/(1+'Study Parameters'!$C$4) ^'Production Cost Baseline'!H$2 -> 1.3979048e+08 | I7: =I6/(1+'Study Parameters'!$C$4) ^'Production Cost Baseline'!I$2 -> 1.3003765e+08 | ... AA7: =AA6/(1+'Study Parameters'!$C$4) ^'Production Cost Baseline'!AA$2 -> 35376655
A8: Fuel Production (kg) | B8: 0 | C8: ='Study Parameters'!$C$12*'Study Parameters'!$C$8 * 10^3 -> 69600000 | D8: ='Study Parameters'!$C$12*'Study Parameters'!$C$8 * 10^3 -> 69600000 | E8: ='Study Parameters'!$C$12*'Study Parameters'!$C$8 * 10^3 -> 69600000 | F8: ='Study Parameters'!$C$12*'Study Parameters'!$C$8 * 10^3 -> 69600000 | G8: ='Study Parameters'!$C$12*'Study Parameters'!$C$8 * 10^3 -> 69600000 | H8: ='Study Parameters'!$C$12*'Study Parameters'!$C$8 * 10^3 -> 69600000 | I8: ='Study Parameters'!$C$12*'Study Parameters'!$C$8 * 10^3 -> 69600000 | J8: ='Study Parameters'!$C$12*'Study Parameters'!$C$8 * 10^3 -> 69600000 | ... AA8: ='Study Parameters'!$C$12*'Study Parameters'!$C$8 * 10^3 -> 69600000
A9: Discounted Fuel Production (kg) | B9: 0 | C9: =C8/(1+'Study Parameters'!$C$4) ^'Production Cost Baseline'!C$2 -> 64744186 | D9: =D8/(1+'Study Parameters'!$C$4) ^'Production Cost Baseline'!D$2 -> 60227150 | E9: =E8/(1+'Study Parameters'!$C$4) ^'Production Cost Baseline'!E$2 -> 56025256 | F9: =F8/(1+'Study Parameters'!$C$4) ^'Production Cost Baseline'!F$2 -> 52116517 | G9: =G8/(1+'Study Parameters'!$C$4) ^'Production Cost Baseline'!G$2 -> 48480481 | H9: =H8/(1+'Study Parameters'!$C$4) ^'Production Cost Baseline'!H$2 -> 45098122 | I9: =I8/(1+'Study Parameters'!$C$4) ^'Production Cost Baseline'!I$2 -> 41951741 | J9: =J8/(1+'Study Parameters'!$C$4) ^'Production Cost Baseline'!J$2 -> 39024875 | ... AA9: =AA8/(1+'Study Parameters'!$C$4) ^'Production Cost Baseline'!AA$2 -> 11412943
A11: Production Cost of Fuel (€/kg) | B11: =SUM(B7:AA7) / SUM(C9:AA9) -> 5.5110056
A12: Production Cost of Fuel (€/l) | B12: =B11 * Inputs!$C$15 -> 4.4253375
A14: C.2 Baseload
A15: Cost (€) | B15: ='Cost Components'!$C$12 * 10^6 -> 1525300000 | C15: =('Cost Components'!$C$21 + 'Cost Components'!$C$40) * 10^6 -> 1.9781564e+08 | D15: =('Cost Components'!$C$21 + 'Cost Components'!$C$40) * 10^6 -> 1.9781564e+08 | E15: =('Cost Components'!$C$21 + 'Cost Components'!$C$40) * 10^6 -> 1.9781564e+08 | F15: =('Cost Components'!$C$21 + 'Cost Components'!$C$40) * 10^6 -> 1.9781564e+08 | G15: =('Cost Components'!$C$21 + 'Cost Components'!$C$40) * 10^6 -> 1.9781564e+08 | H15: =('Cost Components'!$C$21 + 'Cost Components'!$C$40) * 10^6 -> 1.9781564e+08 | I15: =('Cost Components'!$C$21 + 'Cost Components'!$C$40) * 10^6 -> 1.9781564e+08 | J15: =('Cost Components'!$C$21 + 'Cost Components'!$C$40) * 10^6 -> 1.9781564e+08 | ... AA15: =('Cost Components'!$C$21 + 'Cost Components'!$C$40) * 10^6 -> 1.9781564e+08
A16: Revenue (€) | B16: 0 | C16: ='Cost Components'!$C$36*10^6 -> 1.499e+08 | D16: ='Cost Components'!$C$36*10^6 -> 1.499e+08 | E16: ='Cost Components'!$C$36*10^6 -> 1.499e+08 | F16: ='Cost Components'!$C$36*10^6 -> 1.499e+08 | G16: ='Cost Components'!$C$36*10^6 -> 1.499e+08 | H16: ='Cost Components'!$C$36*10^6 -> 1.499e+08 | I16: ='Cost Components'!$C$36*10^6 -> 1.499e+08 | J16: ='Cost Components'!$C$36*10^6 -> 1.499e+08 | ... AA16: ='Cost Components'!$C$36*10^6 -> 1.499e+08
A17: Free Cash Flow (€) | B17: =B15-B16 -> 1525300000 | C17: =C15-C16 -> 47915639 | D17: =D15-D16 -> 47915639 | E17: =E15-E16 -> 47915639 | F17: =F15-F16 -> 47915639 | G17: =G15-G16 -> 47915639 | H17: =H15-H16 -> 47915639 | I17: =I15-I16 -> 47915639 | ... AA17: =AA15-AA16 -> 47915639
A18: Discounted Cash Flow (€) | B18: =B17/(1+'Study Parameters'!$C$4) ^'Production Cost Baseline'!B$2 -> 1525300000 | C18: =C17/(1+'Study Parameters'!$C$4) ^'Production Cost Baseline'!C$2 -> 44572688 | D18: =D17/(1+'Study Parameters'!$C$4) ^'Production Cost Baseline'!D$2 -> 41462965 | E18: =E17/(1+'Study Parameters'!$C$4) ^'Production Cost Baseline'!E$2 -> 38570200 | F18: =F17/(1+'Study Parameters'!$C$4) ^'Production Cost Baseline'!F$2 -> 35879256 | G18: =G17/(1+'Study Parameters'!$C$4) ^'Production Cost Baseline'!G$2 -> 33376052 | H18: =H17/(1+'Study Parameters'!$C$4) ^'Production Cost Baseline'!H$2 -> 31047490 | I18: =I17/(1+'Study Parameters'!$C$4) ^'Production Cost Baseline'!I$2 -> 28881386 | ... AA18: =AA17/(1+'Study Parameters'!$C$4) ^'Production Cost Baseline'!AA$2 -> 7857161.5
A19: Fuel Production (kg) | B19: 0 | C19: ='Study Parameters'!$C$13*'Study Parameters'!$C$8 * 10^3 -> 28000000 | D19: ='Study Parameters'!$C$13*'Study Parameters'!$C$8 * 10^3 -> 28000000 | E19: ='Study Parameters'!$C$13*'Study Parameters'!$C$8 * 10^3 -> 28000000 | F19: ='Study Parameters'!$C$13*'Study Parameters'!$C$8 * 10^3 -> 28000000 | G19: ='Study Parameters'!$C$13*'Study Parameters'!$C$8 * 10^3 -> 28000000 | H19: ='Study Parameters'!$C$13*'Study Parameters'!$C$8 * 10^3 -> 28000000 | I19: ='Study Parameters'!$C$13*'Study Parameters'!$C$8 * 10^3 -> 28000000 | J19: ='Study Parameters'!$C$13*'Study Parameters'!$C$8 * 10^3 -> 28000000 | ... AA19: ='Study Parameters'!$C$13*'Study Parameters'!$C$8 * 10^3 -> 28000000
A20: Discounted Fuel Production (kg) | B20: 0 | C20: =C19/(1+'Study Parameters'!$C$4) ^'Production Cost Baseline'!C$2 -> 26046512 | D20: =D19/(1+'Study Parameters'!$C$4) ^'Production Cost Baseline'!D$2 -> 24229313 | E20: =E19/(1+'Study Parameters'!$C$4) ^'Production Cost Baseline'!E$2 -> 22538896 | F20: =F19/(1+'Study Parameters'!$C$4) ^'Production Cost Baseline'!F$2 -> 20966415 | G20: =G19/(1+'Study Parameters'!$C$4) ^'Production Cost Baseline'!G$2 -> 19503642 | H20: =H19/(1+'Study Parameters'!$C$4) ^'Production Cost Baseline'!H$2 -> 18142923 | I20: =I19/(1+'Study Parameters'!$C$4) ^'Production Cost Baseline'!I$2 -> 16877137 | J20: =J19/(1+'Study Parameters'!$C$4) ^'Production Cost Baseline'!J$2 -> 15699663 | ... AA20: =AA19/(1+'Study Parameters'!$C$4) ^'Production Cost Baseline'!AA$2 -> 4591413.7
A22: Production Cost of Fuel (€/kg) | B22: =SUM(B18:AA18) / SUM(C20:AA20) -> 6.5982617
A23: Production Cost of Fuel (€/l) | B23: =B22 * Inputs!$C$15 -> 5.2984041
A25: C.3 Baseload
A26: Cost (€) | B26: ='Cost Components'!$D$12 * 10^6 -> 1594030000 | C26: =('Cost Components'!$D$21 + 'Cost Components'!$D$40) * 10^6 -> 2.5854408e+08 | D26: =('Cost Components'!$D$21 + 'Cost Components'!$D$40) * 10^6 -> 2.5854408e+08 | E26: =('Cost Components'!$D$21 + 'Cost Components'!$D$40) * 10^6 -> 2.5854408e+08 | F26: =('Cost Components'!$D$21 + 'Cost Components'!$D$40) * 10^6 -> 2.5854408e+08 | G26: =('Cost Components'!$D$21 + 'Cost Components'!$D$40) * 10^6 -> 2.5854408e+08 | H26: =('Cost Components'!$D$21 + 'Cost Components'!$D$40) * 10^6 -> 2.5854408e+08 | I26: =('Cost Components'!$D$21 + 'Cost Components'!$D$40) * 10^6 -> 2.5854408e+08 | J26: =('Cost Components'!$D$21 + 'Cost Components'!$D$40) * 10^6 -> 2.5854408e+08 | ... AA26: =('Cost Components'!$D$21 + 'Cost Components'!$D$40) * 10^6 -> 2.5854408e+08
A27: Revenue (€) | B27: 0 | C27: ='Cost Components'!$D$36*10^6 -> 81000000 | D27: ='Cost Components'!$D$36*10^6 -> 81000000 | E27: ='Cost Components'!$D$36*10^6 -> 81000000 | F27: ='Cost Components'!$D$36*10^6 -> 81000000 | G27: ='Cost Components'!$D$36*10^6 -> 81000000 | H27: ='Cost Components'!$D$36*10^6 -> 81000000 | I27: ='Cost Components'!$D$36*10^6 -> 81000000 | J27: ='Cost Components'!$D$36*10^6 -> 81000000 | ... AA27: ='Cost Components'!$D$36*10^6 -> 81000000
A28: Free Cash Flow (€) | B28: =B26-B27 -> 1594030000 | C28: =C26-C27 -> 1.7754408e+08 | D28: =D26-D27 -> 1.7754408e+08 | E28: =E26-E27 -> 1.7754408e+08 | F28: =F26-F27 -> 1.7754408e+08 | G28: =G26-G27 -> 1.7754408e+08 | H28: =H26-H27 -> 1.7754408e+08 | I28: =I26-I27 -> 1.7754408e+08 | ... AA28: =AA26-AA27 -> 1.7754408e+08
A29: Discounted Cash Flow (€) | B29: =B28/(1+'Study Parameters'!$C$4) ^'Production Cost Baseline'!B$2 -> 1594030000 | C29: =C28/(1+'Study Parameters'!$C$4) ^'Production Cost Baseline'!C$2 -> 1.6515728e+08 | D29: =D28/(1+'Study Parameters'!$C$4) ^'Production Cost Baseline'!D$2 -> 1.5363468e+08 | E29: =E28/(1+'Study Parameters'!$C$4) ^'Production Cost Baseline'!E$2 -> 1.4291598e+08 | F29: =F28/(1+'Study Parameters'!$C$4) ^'Production Cost Baseline'!F$2 -> 1.329451e+08 | G29: =G28/(1+'Study Parameters'!$C$4) ^'Production Cost Baseline'!G$2 -> 1.2366986e+08 | H29: =H28/(1+'Study Parameters'!$C$4) ^'Production Cost Baseline'!H$2 -> 1.1504173e+08 | I29: =I28/(1+'Study Parameters'!$C$4) ^'Production Cost Baseline'!I$2 -> 1.0701556e+08 | ... AA29: =AA28/(1+'Study Parameters'!$C$4) ^'Production Cost Baseline'!AA$2 -> 29113511
A30: Fuel Production (kg) | B30: 0 | C30: ='Study Parameters'!$C$14*'Study Parameters'!$C$8 * 10^3 -> 38400000 | D30: ='Study Parameters'!$C$14*'Study Parameters'!$C$8 * 10^3 -> 38400000 | E30: ='Study Parameters'!$C$14*'Study Parameters'!$C$8 * 10^3 -> 38400000 | F30: ='Study Parameters'!$C$14*'Study Parameters'!$C$8 * 10^3 -> 38400000 | G30: ='Study Parameters'!$C$14*'Study Parameters'!$C$8 * 10^3 -> 38400000 | H30: ='Study Parameters'!$C$14*'Study Parameters'!$C$8 * 10^3 -> 38400000 | I30: ='Study Parameters'!$C$14*'Study Parameters'!$C$8 * 10^3 -> 38400000 | J30: ='Study Parameters'!$C$14*'Study Parameters'!$C$8 * 10^3 -> 38400000 | ... AA30: ='Study Parameters'!$C$14*'Study Parameters'!$C$8 * 10^3 -> 38400000
A31: Discounted Fuel Production (kg) | B31: 0 | C31: =C30/(1+'Study Parameters'!$C$4) ^'Production Cost Baseline'!C$2 -> 35720930 | D31: =D30/(1+'Study Parameters'!$C$4) ^'Production Cost Baseline'!D$2 -> 33228772 | E31: =E30/(1+'Study Parameters'!$C$4) ^'Production Cost Baseline'!E$2 -> 30910486 | F31: =F30/(1+'Study Parameters'!$C$4) ^'Production Cost Baseline'!F$2 -> 28753940 | G31: =G30/(1+'Study Parameters'!$C$4) ^'Production Cost Baseline'!G$2 -> 26747851 | H31: =H30/(1+'Study Parameters'!$C$4) ^'Production Cost Baseline'!H$2 -> 24881722 | I31: =I30/(1+'Study Parameters'!$C$4) ^'Production Cost Baseline'!I$2 -> 23145788 | J31: =J30/(1+'Study Parameters'!$C$4) ^'Production Cost Baseline'!J$2 -> 21530966 | ... AA31: =AA30/(1+'Study Parameters'!$C$4) ^'Production Cost Baseline'!AA$2 -> 6296795.9
A33: Production Cost of Fuel (€/kg) | B33: =SUM(B29:AA29) / SUM(C31:AA31) -> 8.3475412
A34: Production Cost of Fuel (€/l) | B34: =B33 * Inputs!$C$15 -> 6.7030756
A36: C.4 Baseload
A37: Cost (€) | B37: ='Cost Components'!$E$12 * 10^6 -> 1.43992e+09 | C37: =('Cost Components'!$E$21 + 'Cost Components'!$E$40) * 10^6 -> 2.0154218e+08 | D37: =('Cost Components'!$E$21 + 'Cost Components'!$E$40) * 10^6 -> 2.0154218e+08 | E37: =('Cost Components'!$E$21 + 'Cost Components'!$E$40) * 10^6 -> 2.0154218e+08 | F37: =('Cost Components'!$E$21 + 'Cost Components'!$E$40) * 10^6 -> 2.0154218e+08 | G37: =('Cost Components'!$E$21 + 'Cost Components'!$E$40) * 10^6 -> 2.0154218e+08 | H37: =('Cost Components'!$E$21 + 'Cost Components'!$E$40) * 10^6 -> 2.0154218e+08 | I37: =('Cost Components'!$E$21 + 'Cost Components'!$E$40) * 10^6 -> 2.0154218e+08 | J37: =('Cost Components'!$E$21 + 'Cost Components'!$E$40) * 10^6 -> 2.0154218e+08 | ... AA37: =('Cost Components'!$E$21 + 'Cost Components'!$E$40) * 10^6 -> 2.0154218e+08
A38: Revenue (€) | B38: 0 | C38: ='Cost Components'!$E$36*10^6 -> 103200000 | D38: ='Cost Components'!$E$36*10^6 -> 103200000 | E38: ='Cost Components'!$E$36*10^6 -> 103200000 | F38: ='Cost Components'!$E$36*10^6 -> 103200000 | G38: ='Cost Components'!$E$36*10^6 -> 103200000 | H38: ='Cost Components'!$E$36*10^6 -> 103200000 | I38: ='Cost Components'!$E$36*10^6 -> 103200000 | J38: ='Cost Components'!$E$36*10^6 -> 103200000 | ... AA38: ='Cost Components'!$E$36*10^6 -> 103200000
A39: Free Cash Flow (€) | B39: =B37-B38 -> 1.43992e+09 | C39: =C37-C38 -> 98342180 | D39: =D37-D38 -> 98342180 | E39: =E37-E38 -> 98342180 | F39: =F37-F38 -> 98342180 | G39: =G37-G38 -> 98342180 | H39: =H37-H38 -> 98342180 | I39: =I37-I38 -> 98342180 | ... AA39: =AA37-AA38 -> 98342180
A40: Discounted Cash Flow (€) | B40: =B39/(1+'Study Parameters'!$C$4) ^'Production Cost Baseline'!B$2 -> 1.43992e+09 | C40: =C39/(1+'Study Parameters'!$C$4) ^'Production Cost Baseline'!C$2 -> 91481098 | D40: =D39/(1+'Study Parameters'!$C$4) ^'Production Cost Baseline'!D$2 -> 85098696 | E40: =E39/(1+'Study Parameters'!$C$4) ^'Production Cost Baseline'!E$2 -> 79161577 | F40: =F39/(1+'Study Parameters'!$C$4) ^'Production Cost Baseline'!F$2 -> 73638677 | G40: =G39/(1+'Study Parameters'!$C$4) ^'Production Cost Baseline'!G$2 -> 68501095 | H40: =H39/(1+'Study Parameters'!$C$4) ^'Production Cost Baseline'!H$2 -> 63721948 | I40: =I39/(1+'Study Parameters'!$C$4) ^'Production Cost Baseline'!I$2 -> 59276231 | ... AA40: =AA39/(1+'Study Parameters'!$C$4) ^'Production Cost Baseline'!AA$2 -> 16126058
A41: Fuel Production (kg) | B41: 0 | C41: ='Study Parameters'!$C$15*'Study Parameters'!$C$8 * 10^3 -> 55200000 | D41: ='Study Parameters'!$C$15*'Study Parameters'!$C$8 * 10^3 -> 55200000 | E41: ='Study Parameters'!$C$15*'Study Parameters'!$C$8 * 10^3 -> 55200000 | F41: ='Study Parameters'!$C$15*'Study Parameters'!$C$8 * 10^3 -> 55200000 | G41: ='Study Parameters'!$C$15*'Study Parameters'!$C$8 * 10^3 -> 55200000 | H41: ='Study Parameters'!$C$15*'Study Parameters'!$C$8 * 10^3 -> 55200000 | I41: ='Study Parameters'!$C$15*'Study Parameters'!$C$8 * 10^3 -> 55200000 | J41: ='Study Parameters'!$C$15*'Study Parameters'!$C$8 * 10^3 -> 55200000 | ... AA41: ='Study Parameters'!$C$15*'Study Parameters'!$C$8 * 10^3 -> 55200000
A42: Discounted Fuel Production (kg) | B42: 0 | C42: =C41/(1+'Study Parameters'!$C$4) ^'Production Cost Baseline'!C$2 -> 51348837 | D42: =D41/(1+'Study Parameters'!$C$4) ^'Production Cost Baseline'!D$2 -> 47766360 | E42: =E41/(1+'Study Parameters'!$C$4) ^'Production Cost Baseline'!E$2 -> 44433823 | F42: =F41/(1+'Study Parameters'!$C$4) ^'Production Cost Baseline'!F$2 -> 41333789 | G42: =G41/(1+'Study Parameters'!$C$4) ^'Production Cost Baseline'!G$2 -> 38450037 | H42: =H41/(1+'Study Parameters'!$C$4) ^'Production Cost Baseline'!H$2 -> 35767476 | I42: =I41/(1+'Study Parameters'!$C$4) ^'Production Cost Baseline'!I$2 -> 33272071 | J42: =J41/(1+'Study Parameters'!$C$4) ^'Production Cost Baseline'!J$2 -> 30950763 | ... AA42: =AA41/(1+'Study Parameters'!$C$4) ^'Production Cost Baseline'!AA$2 -> 9051644.1
A44: Production Cost of Fuel (€/kg) | B44: =SUM(B40:AA40) / SUM(C42:AA42) -> 4.1217096
A45: Production Cost of Fuel (€/l) | B45: =B44 * Inputs!$C$15 -> 3.3097328
A47: C.5 Baseload
A48: Cost (€) | B48: ='Cost Components'!$F$12 * 10^6 -> 1482660000 | C48: =('Cost Components'!$F$21 + 'Cost Components'!$F$40) * 10^6 -> 2.4224214e+08 | D48: =('Cost Components'!$F$21 + 'Cost Components'!$F$40) * 10^6 -> 2.4224214e+08 | E48: =('Cost Components'!$F$21 + 'Cost Components'!$F$40) * 10^6 -> 2.4224214e+08 | F48: =('Cost Components'!$F$21 + 'Cost Components'!$F$40) * 10^6 -> 2.4224214e+08 | G48: =('Cost Components'!$F$21 + 'Cost Components'!$F$40) * 10^6 -> 2.4224214e+08 | H48: =('Cost Components'!$F$21 + 'Cost Components'!$F$40) * 10^6 -> 2.4224214e+08 | I48: =('Cost Components'!$F$21 + 'Cost Components'!$F$40) * 10^6 -> 2.4224214e+08 | J48: =('Cost Components'!$F$21 + 'Cost Components'!$F$40) * 10^6 -> 2.4224214e+08 | ... AA48: =('Cost Components'!$F$21 + 'Cost Components'!$F$40) * 10^6 -> 2.4224214e+08
A49: Revenue (€) | B49: 0 | C49: ='Cost Components'!$F$36*10^6 -> 135200000 | D49: ='Cost Components'!$F$36*10^6 -> 135200000 | E49: ='Cost Components'!$F$36*10^6 -> 135200000 | F49: ='Cost Components'!$F$36*10^6 -> 135200000 | G49: ='Cost Components'!$F$36*10^6 -> 135200000 | H49: ='Cost Components'!$F$36*10^6 -> 135200000 | I49: ='Cost Components'!$F$36*10^6 -> 135200000 | J49: ='Cost Components'!$F$36*10^6 -> 135200000 | ... AA49: ='Cost Components'!$F$36*10^6 -> 135200000
A50: Free Cash Flow (€) | B50: =B48-B49 -> 1482660000 | C50: =C48-C49 -> 1.0704214e+08 | D50: =D48-D49 -> 1.0704214e+08 | E50: =E48-E49 -> 1.0704214e+08 | F50: =F48-F49 -> 1.0704214e+08 | G50: =G48-G49 -> 1.0704214e+08 | H50: =H48-H49 -> 1.0704214e+08 | I50: =I48-I49 -> 1.0704214e+08 | ... AA50: =AA48-AA49 -> 1.0704214e+08
A51: Discounted Cash Flow (€) | B51: =B50/(1+'Study Parameters'!$C$4) ^'Production Cost Baseline'!B$2 -> 1482660000 | C51: =C50/(1+'Study Parameters'!$C$4) ^'Production Cost Baseline'!C$2 -> 99574087 | D51: =D50/(1+'Study Parameters'!$C$4) ^'Production Cost Baseline'!D$2 -> 92627058 | E51: =E50/(1+'Study Parameters'!$C$4) ^'Production Cost Baseline'!E$2 -> 86164705 | F51: =F50/(1+'Study Parameters'!$C$4) ^'Production Cost Baseline'!F$2 -> 80153214 | G51: =G50/(1+'Study Parameters'!$C$4) ^'Production Cost Baseline'!G$2 -> 74561129 | H51: =H50/(1+'Study Parameters'!$C$4) ^'Production Cost Baseline'!H$2 -> 69359190 | I51: =I50/(1+'Study Parameters'!$C$4) ^'Production Cost Baseline'!I$2 -> 64520177 | ... AA51: =AA50/(1+'Study Parameters'!$C$4) ^'Production Cost Baseline'!AA$2 -> 17552670
A52: Fuel Production (kg) | B52: 0 | C52: ='Study Parameters'!$C$16*'Study Parameters'!$C$8 * 10^3 -> 54400000 | D52: ='Study Parameters'!$C$16*'Study Parameters'!$C$8 * 10^3 -> 54400000 | E52: ='Study Parameters'!$C$16*'Study Parameters'!$C$8 * 10^3 -> 54400000 | F52: ='Study Parameters'!$C$16*'Study Parameters'!$C$8 * 10^3 -> 54400000 | G52: ='Study Parameters'!$C$16*'Study Parameters'!$C$8 * 10^3 -> 54400000 | H52: ='Study Parameters'!$C$16*'Study Parameters'!$C$8 * 10^3 -> 54400000 | I52: ='Study Parameters'!$C$16*'Study Parameters'!$C$8 * 10^3 -> 54400000 | J52: ='Study Parameters'!$C$16*'Study Parameters'!$C$8 * 10^3 -> 54400000 | ... AA52: ='Study Parameters'!$C$16*'Study Parameters'!$C$8 * 10^3 -> 54400000
A53: Discounted Fuel Production (kg) | B53: 0 | C53: =C52/(1+'Study Parameters'!$C$4) ^'Production Cost Baseline'!C$2 -> 50604651 | D53: =D52/(1+'Study Parameters'!$C$4) ^'Production Cost Baseline'!D$2 -> 47074094 | E53: =E52/(1+'Study Parameters'!$C$4) ^'Production Cost Baseline'!E$2 -> 43789855 | F53: =F52/(1+'Study Parameters'!$C$4) ^'Production Cost Baseline'!F$2 -> 40734749 | G53: =G52/(1+'Study Parameters'!$C$4) ^'Production Cost Baseline'!G$2 -> 37892790 | H53: =H52/(1+'Study Parameters'!$C$4) ^'Production Cost Baseline'!H$2 -> 35249107 | I53: =I52/(1+'Study Parameters'!$C$4) ^'Production Cost Baseline'!I$2 -> 32789867 | J53: =J52/(1+'Study Parameters'!$C$4) ^'Production Cost Baseline'!J$2 -> 30502201 | ... AA53: =AA52/(1+'Study Parameters'!$C$4) ^'Production Cost Baseline'!AA$2 -> 8920460.9
A55: Production Cost of Fuel (€/kg) | B55: =SUM(B51:AA51) / SUM(C53:AA53) -> 4.412731
A56: Production Cost of Fuel (€/l) | B56: =B55 * Inputs!$C$15 -> 3.543423
A58: 2050
A59: C.1 Baseload
A60: Cost (€) | B60: ='Cost Components'!$M$12 * 10^6 -> 575000000 | C60: ='Cost Components'!$M$41*10^6 -> 1.5825375e+08 | D60: ='Cost Components'!$M$41*10^6 -> 1.5825375e+08 | E60: ='Cost Components'!$M$41*10^6 -> 1.5825375e+08 | F60: ='Cost Components'!$M$41*10^6 -> 1.5825375e+08 | G60: ='Cost Components'!$M$41*10^6 -> 1.5825375e+08 | H60: ='Cost Components'!$M$41*10^6 -> 1.5825375e+08 | I60: ='Cost Components'!$M$41*10^6 -> 1.5825375e+08 | J60: ='Cost Components'!$M$41*10^6 -> 1.5825375e+08 | ... AA60: ='Cost Components'!$M$41*10^6 -> 1.5825375e+08
A61: Revenue (€) | B61: 0 | C61: ='Cost Components'!$M$36 * 10^6 -> 149900000 | D61: ='Cost Components'!$M$36 * 10^6 -> 149900000 | E61: ='Cost Components'!$M$36 * 10^6 -> 149900000 | F61: ='Cost Components'!$M$36 * 10^6 -> 149900000 | G61: ='Cost Components'!$M$36 * 10^6 -> 149900000 | H61: ='Cost Components'!$M$36 * 10^6 -> 149900000 | I61: ='Cost Components'!$M$36 * 10^6 -> 149900000 | J61: ='Cost Components'!$M$36 * 10^6 -> 149900000 | ... AA61: ='Cost Components'!$M$36 * 10^6 -> 149900000
A62: Free Cash Flow (€) | B62: =B60-B61 -> 575000000 | C62: =C60-C61 -> 8353747.4 | D62: =D60-D61 -> 8353747.4 | E62: =E60-E61 -> 8353747.4 | F62: =F60-F61 -> 8353747.4 | G62: =G60-G61 -> 8353747.4 | H62: =H60-H61 -> 8353747.4 | I62: =I60-I61 -> 8353747.4 | ... AA62: =AA60-AA61 -> 8353747.4
A63: Discounted Cash Flow (€) | B63: =B62/(1+'Study Parameters'!$C$4) ^'Production Cost Baseline'!B$2 -> 575000000 | C63: =C62/(1+'Study Parameters'!$C$4) ^'Production Cost Baseline'!C$2 -> 7770927.8 | D63: =D62/(1+'Study Parameters'!$C$4) ^'Production Cost Baseline'!D$2 -> 7228770 | E63: =E62/(1+'Study Parameters'!$C$4) ^'Production Cost Baseline'!E$2 -> 6724437.2 | F63: =F62/(1+'Study Parameters'!$C$4) ^'Production Cost Baseline'!F$2 -> 6255290.5 | G63: =G62/(1+'Study Parameters'!$C$4) ^'Production Cost Baseline'!G$2 -> 5818874.8 | H63: =H62/(1+'Study Parameters'!$C$4) ^'Production Cost Baseline'!H$2 -> 5412906.8 | I63: =I62/(1+'Study Parameters'!$C$4) ^'Production Cost Baseline'!I$2 -> 5035262.2 | ... AA63: =AA62/(1+'Study Parameters'!$C$4) ^'Production Cost Baseline'!AA$2 -> 1369839.6
A64: Fuel Production (kg) | B64: 0 | C64: ='Study Parameters'!$C$12*'Study Parameters'!$C$8 * 10^3 -> 69600000 | D64: ='Study Parameters'!$C$12*'Study Parameters'!$C$8 * 10^3 -> 69600000 | E64: ='Study Parameters'!$C$12*'Study Parameters'!$C$8 * 10^3 -> 69600000 | F64: ='Study Parameters'!$C$12*'Study Parameters'!$C$8 * 10^3 -> 69600000 | G64: ='Study Parameters'!$C$12*'Study Parameters'!$C$8 * 10^3 -> 69600000 | H64: ='Study Parameters'!$C$12*'Study Parameters'!$C$8 * 10^3 -> 69600000 | I64: ='Study Parameters'!$C$12*'Study Parameters'!$C$8 * 10^3 -> 69600000 | J64: ='Study Parameters'!$C$12*'Study Parameters'!$C$8 * 10^3 -> 69600000 | ... AA64: ='Study Parameters'!$C$12*'Study Parameters'!$C$8 * 10^3 -> 69600000
A65: Discounted Fuel Production (kg) | B65: =B64/(1+'Study Parameters'!$C$4) ^'Production Cost Baseline'!B$2 -> 0 | C65: =C64/(1+'Study Parameters'!$C$4) ^'Production Cost Baseline'!C$2 -> 64744186 | D65: =D64/(1+'Study Parameters'!$C$4) ^'Production Cost Baseline'!D$2 -> 60227150 | E65: =E64/(1+'Study Parameters'!$C$4) ^'Production Cost Baseline'!E$2 -> 56025256 | F65: =F64/(1+'Study Parameters'!$C$4) ^'Production Cost Baseline'!F$2 -> 52116517 | G65: =G64/(1+'Study Parameters'!$C$4) ^'Production Cost Baseline'!G$2 -> 48480481 | H65: =H64/(1+'Study Parameters'!$C$4) ^'Production Cost Baseline'!H$2 -> 45098122 | I65: =I64/(1+'Study Parameters'!$C$4) ^'Production Cost Baseline'!I$2 -> 41951741 | ... AA65: =AA64/(1+'Study Parameters'!$C$4) ^'Production Cost Baseline'!AA$2 -> 11412943
A67: Production Cost of Fuel (€/kg) | B67: =SUM(B63:AA63) / SUM(C65:AA65) -> 0.8611693
A68: Production Cost of Fuel (€/l) | B68: =B67 * Inputs!$C$15 -> 0.69151895
A70: C.2 Baseload
A71: Cost (€) | B71: ='Cost Components'!$N$12 * 10^6 -> 449000000 | C71: ='Cost Components'!$N$41*10^6 -> 1.2209163e+08 | D71: ='Cost Components'!$N$41*10^6 -> 1.2209163e+08 | E71: ='Cost Components'!$N$41*10^6 -> 1.2209163e+08 | F71: ='Cost Components'!$N$41*10^6 -> 1.2209163e+08 | G71: ='Cost Components'!$N$41*10^6 -> 1.2209163e+08 | H71: ='Cost Components'!$N$41*10^6 -> 1.2209163e+08 | I71: ='Cost Components'!$N$41*10^6 -> 1.2209163e+08 | J71: ='Cost Components'!$N$41*10^6 -> 1.2209163e+08 | ... AA71: ='Cost Components'!$N$41*10^6 -> 1.2209163e+08
A72: Revenue (€) | B72: 0 | C72: ='Cost Components'!$N$36 * 10^6 -> 81000000 | D72: ='Cost Components'!$N$36 * 10^6 -> 81000000 | E72: ='Cost Components'!$N$36 * 10^6 -> 81000000 | F72: ='Cost Components'!$N$36 * 10^6 -> 81000000 | G72: ='Cost Components'!$N$36 * 10^6 -> 81000000 | H72: ='Cost Components'!$N$36 * 10^6 -> 81000000 | I72: ='Cost Components'!$N$36 * 10^6 -> 81000000 | J72: ='Cost Components'!$N$36 * 10^6 -> 81000000 | ... AA72: ='Cost Components'!$N$36 * 10^6 -> 81000000
A73: Free Cash Flow (€) | B73: =B71-B72 -> 449000000 | C73: =C71-C72 -> 41091632 | D73: =D71-D72 -> 41091632 | E73: =E71-E72 -> 41091632 | F73: =F71-F72 -> 41091632 | G73: =G71-G72 -> 41091632 | H73: =H71-H72 -> 41091632 | I73: =I71-I72 -> 41091632 | ... AA73: =AA71-AA72 -> 41091632
A74: Discounted Cash Flow (€) | B74: =B73/(1+'Study Parameters'!$C$4) ^'Production Cost Baseline'!B$2 -> 449000000 | C74: =C73/(1+'Study Parameters'!$C$4) ^'Production Cost Baseline'!C$2 -> 38224774 | D74: =D73/(1+'Study Parameters'!$C$4) ^'Production Cost Baseline'!D$2 -> 35557929 | E74: =E73/(1+'Study Parameters'!$C$4) ^'Production Cost Baseline'!E$2 -> 33077143 | F74: =F73/(1+'Study Parameters'!$C$4) ^'Production Cost Baseline'!F$2 -> 30769436 | G74: =G73/(1+'Study Parameters'!$C$4) ^'Production Cost Baseline'!G$2 -> 28622731 | H74: =H73/(1+'Study Parameters'!$C$4) ^'Production Cost Baseline'!H$2 -> 26625796 | I74: =I73/(1+'Study Parameters'!$C$4) ^'Production Cost Baseline'!I$2 -> 24768183 | ... AA74: =AA73/(1+'Study Parameters'!$C$4) ^'Production Cost Baseline'!AA$2 -> 6738167.2
A75: Fuel Production (kg) | B75: 0 | C75: ='Study Parameters'!$C$13*'Study Parameters'!$C$8 * 10^3 -> 28000000 | D75: ='Study Parameters'!$C$13*'Study Parameters'!$C$8 * 10^3 -> 28000000 | E75: ='Study Parameters'!$C$13*'Study Parameters'!$C$8 * 10^3 -> 28000000 | F75: ='Study Parameters'!$C$13*'Study Parameters'!$C$8 * 10^3 -> 28000000 | G75: ='Study Parameters'!$C$13*'Study Parameters'!$C$8 * 10^3 -> 28000000 | H75: ='Study Parameters'!$C$13*'Study Parameters'!$C$8 * 10^3 -> 28000000 | I75: ='Study Parameters'!$C$13*'Study Parameters'!$C$8 * 10^3 -> 28000000 | J75: ='Study Parameters'!$C$13*'Study Parameters'!$C$8 * 10^3 -> 28000000 | ... AA75: ='Study Parameters'!$C$13*'Study Parameters'!$C$8 * 10^3 -> 28000000
A76: Discounted Fuel Production (kg) | B76: =B75/(1+'Study Parameters'!$C$4) ^'Production Cost Baseline'!B$2 -> 0 | C76: =C75/(1+'Study Parameters'!$C$4) ^'Production Cost Baseline'!C$2 -> 26046512 | D76: =D75/(1+'Study Parameters'!$C$4) ^'Production Cost Baseline'!D$2 -> 24229313 | E76: =E75/(1+'Study Parameters'!$C$4) ^'Production Cost Baseline'!E$2 -> 22538896 | F76: =F75/(1+'Study Parameters'!$C$4) ^'Production Cost Baseline'!F$2 -> 20966415 | G76: =G75/(1+'Study Parameters'!$C$4) ^'Production Cost Baseline'!G$2 -> 19503642 | H76: =H75/(1+'Study Parameters'!$C$4) ^'Production Cost Baseline'!H$2 -> 18142923 | I76: =I75/(1+'Study Parameters'!$C$4) ^'Production Cost Baseline'!I$2 -> 16877137 | ... AA76: =AA75/(1+'Study Parameters'!$C$4) ^'Production Cost Baseline'!AA$2 -> 4591413.7
A78: Production Cost of Fuel (€/kg) | B78: =SUM(B74:AA74) / SUM(C76:AA76) -> 2.906133
A79: Production Cost of Fuel (€/l) | B79: =B78 * Inputs!$C$15 -> 2.3336248
A81: C.3 Baseload
A82: Cost (€) | B82: ='Cost Components'!$O$12 * 10^6 -> 463000000 | C82: ='Cost Components'!$O$41*10^6 -> 1.3480808e+08 | D82: ='Cost Components'!$O$41*10^6 -> 1.3480808e+08 | E82: ='Cost Components'!$O$41*10^6 -> 1.3480808e+08 | F82: ='Cost Components'!$O$41*10^6 -> 1.3480808e+08 | G82: ='Cost Components'!$O$41*10^6 -> 1.3480808e+08 | H82: ='Cost Components'!$O$41*10^6 -> 1.3480808e+08 | I82: ='Cost Components'!$O$41*10^6 -> 1.3480808e+08 | J82: ='Cost Components'!$O$41*10^6 -> 1.3480808e+08 | ... AA82: ='Cost Components'!$O$41*10^6 -> 1.3480808e+08
A83: Revenue (€) | B83: 0 | C83: ='Cost Components'!$O$36 * 10^6 -> 103200000 | D83: ='Cost Components'!$O$36 * 10^6 -> 103200000 | E83: ='Cost Components'!$O$36 * 10^6 -> 103200000 | F83: ='Cost Components'!$O$36 * 10^6 -> 103200000 | G83: ='Cost Components'!$O$36 * 10^6 -> 103200000 | H83: ='Cost Components'!$O$36 * 10^6 -> 103200000 | I83: ='Cost Components'!$O$36 * 10^6 -> 103200000 | J83: ='Cost Components'!$O$36 * 10^6 -> 103200000 | ... AA83: ='Cost Components'!$O$36 * 10^6 -> 103200000
A84: Free Cash Flow (€) | B84: =B82-B83 -> 463000000 | C84: =C82-C83 -> 31608083 | D84: =D82-D83 -> 31608083 | E84: =E82-E83 -> 31608083 | F84: =F82-F83 -> 31608083 | G84: =G82-G83 -> 31608083 | H84: =H82-H83 -> 31608083 | I84: =I82-I83 -> 31608083 | ... AA84: =AA82-AA83 -> 31608083
A85: Discounted Cash Flow (€) | B85: =B84/(1+'Study Parameters'!$C$4) ^'Production Cost Baseline'!B$2 -> 463000000 | C85: =C84/(1+'Study Parameters'!$C$4) ^'Production Cost Baseline'!C$2 -> 29402867 | D85: =D84/(1+'Study Parameters'!$C$4) ^'Production Cost Baseline'!D$2 -> 27351505 | E85: =E84/(1+'Study Parameters'!$C$4) ^'Production Cost Baseline'!E$2 -> 25443260 | F85: =F84/(1+'Study Parameters'!$C$4) ^'Production Cost Baseline'!F$2 -> 23668149 | G85: =G84/(1+'Study Parameters'!$C$4) ^'Production Cost Baseline'!G$2 -> 22016883 | H85: =H84/(1+'Study Parameters'!$C$4) ^'Production Cost Baseline'!H$2 -> 20480821 | I85: =I84/(1+'Study Parameters'!$C$4) ^'Production Cost Baseline'!I$2 -> 19051927 | ... AA85: =AA84/(1+'Study Parameters'!$C$4) ^'Production Cost Baseline'!AA$2 -> 5183063.7
A86: Fuel Production (kg) | B86: 0 | C86: ='Study Parameters'!$C$14*'Study Parameters'!$C$8 * 10^3 -> 38400000 | D86: ='Study Parameters'!$C$14*'Study Parameters'!$C$8 * 10^3 -> 38400000 | E86: ='Study Parameters'!$C$14*'Study Parameters'!$C$8 * 10^3 -> 38400000 | F86: ='Study Parameters'!$C$14*'Study Parameters'!$C$8 * 10^3 -> 38400000 | G86: ='Study Parameters'!$C$14*'Study Parameters'!$C$8 * 10^3 -> 38400000 | H86: ='Study Parameters'!$C$14*'Study Parameters'!$C$8 * 10^3 -> 38400000 | I86: ='Study Parameters'!$C$14*'Study Parameters'!$C$8 * 10^3 -> 38400000 | J86: ='Study Parameters'!$C$14*'Study Parameters'!$C$8 * 10^3 -> 38400000 | ... AA86: ='Study Parameters'!$C$14*'Study Parameters'!$C$8 * 10^3 -> 38400000
A87: Discounted Fuel Production (kg) | B87: =B86/(1+'Study Parameters'!$C$4) ^'Production Cost Baseline'!B$2 -> 0 | C87: =C86/(1+'Study Parameters'!$C$4) ^'Production Cost Baseline'!C$2 -> 35720930 | D87: =D86/(1+'Study Parameters'!$C$4) ^'Production Cost Baseline'!D$2 -> 33228772 | E87: =E86/(1+'Study Parameters'!$C$4) ^'Production Cost Baseline'!E$2 -> 30910486 | F87: =F86/(1+'Study Parameters'!$C$4) ^'Production Cost Baseline'!F$2 -> 28753940 | G87: =G86/(1+'Study Parameters'!$C$4) ^'Production Cost Baseline'!G$2 -> 26747851 | H87: =H86/(1+'Study Parameters'!$C$4) ^'Production Cost Baseline'!H$2 -> 24881722 | I87: =I86/(1+'Study Parameters'!$C$4) ^'Production Cost Baseline'!I$2 -> 23145788 | ... AA87: =AA86/(1+'Study Parameters'!$C$4) ^'Production Cost Baseline'!AA$2 -> 6296795.9
A89: Production Cost of Fuel (€/kg) | B89: =SUM(B85:AA85) / SUM(C87:AA87) -> 1.9047949
A90: Production Cost of Fuel (€/l) | B90: =B89 * Inputs!$C$15 -> 1.5295503
A92: C.4 Baseload
A93: Cost (€) | B93: ='Cost Components'!$P$12 * 10^6 -> 458000000 | C93: ='Cost Components'!$P$41*10^6 -> 1.1018319e+08 | D93: ='Cost Components'!$P$41*10^6 -> 1.1018319e+08 | E93: ='Cost Components'!$P$41*10^6 -> 1.1018319e+08 | F93: ='Cost Components'!$P$41*10^6 -> 1.1018319e+08 | G93: ='Cost Components'!$P$41*10^6 -> 1.1018319e+08 | H93: ='Cost Components'!$P$41*10^6 -> 1.1018319e+08 | I93: ='Cost Components'!$P$41*10^6 -> 1.1018319e+08 | J93: ='Cost Components'!$P$41*10^6 -> 1.1018319e+08 | ... AA93: ='Cost Components'!$P$41*10^6 -> 1.1018319e+08
A94: Revenue (€) | B94: 0 | C94: ='Cost Components'!$P$36 * 10^6 -> 135200000 | D94: ='Cost Components'!$P$36 * 10^6 -> 135200000 | E94: ='Cost Components'!$P$36 * 10^6 -> 135200000 | F94: ='Cost Components'!$P$36 * 10^6 -> 135200000 | G94: ='Cost Components'!$P$36 * 10^6 -> 135200000 | H94: ='Cost Components'!$P$36 * 10^6 -> 135200000 | I94: ='Cost Components'!$P$36 * 10^6 -> 135200000 | J94: ='Cost Components'!$P$36 * 10^6 -> 135200000 | ... AA94: ='Cost Components'!$P$36 * 10^6 -> 135200000
A95: Free Cash Flow (€) | B95: =B93-B94 -> 458000000 | C95: =C93-C94 -> -25016813 | D95: =D93-D94 -> -25016813 | E95: =E93-E94 -> -25016813 | F95: =F93-F94 -> -25016813 | G95: =G93-G94 -> -25016813 | H95: =H93-H94 -> -25016813 | I95: =I93-I94 -> -25016813 | ... AA95: =AA93-AA94 -> -25016813
A96: Discounted Cash Flow (€) | B96: =B95/(1+'Study Parameters'!$C$4) ^'Production Cost Baseline'!B$2 -> 458000000 | C96: =C95/(1+'Study Parameters'!$C$4) ^'Production Cost Baseline'!C$2 -> -23271454 | D96: =D95/(1+'Study Parameters'!$C$4) ^'Production Cost Baseline'!D$2 -> -21647864 | E96: =E95/(1+'Study Parameters'!$C$4) ^'Production Cost Baseline'!E$2 -> -20137548 | F96: =F95/(1+'Study Parameters'!$C$4) ^'Production Cost Baseline'!F$2 -> -18732603 | G96: =G95/(1+'Study Parameters'!$C$4) ^'Production Cost Baseline'!G$2 -> -17425677 | H96: =H95/(1+'Study Parameters'!$C$4) ^'Production Cost Baseline'!H$2 -> -16209932 | I96: =I95/(1+'Study Parameters'!$C$4) ^'Production Cost Baseline'!I$2 -> -15079006 | ... AA96: =AA95/(1+'Study Parameters'!$C$4) ^'Production Cost Baseline'!AA$2 -> -4102233.5
A97: Fuel Production (kg) | B97: 0 | C97: ='Study Parameters'!$C$15*'Study Parameters'!$C$8 * 10^3 -> 55200000 | D97: ='Study Parameters'!$C$15*'Study Parameters'!$C$8 * 10^3 -> 55200000 | E97: ='Study Parameters'!$C$15*'Study Parameters'!$C$8 * 10^3 -> 55200000 | F97: ='Study Parameters'!$C$15*'Study Parameters'!$C$8 * 10^3 -> 55200000 | G97: ='Study Parameters'!$C$15*'Study Parameters'!$C$8 * 10^3 -> 55200000 | H97: ='Study Parameters'!$C$15*'Study Parameters'!$C$8 * 10^3 -> 55200000 | I97: ='Study Parameters'!$C$15*'Study Parameters'!$C$8 * 10^3 -> 55200000 | J97: ='Study Parameters'!$C$15*'Study Parameters'!$C$8 * 10^3 -> 55200000 | ... AA97: ='Study Parameters'!$C$15*'Study Parameters'!$C$8 * 10^3 -> 55200000
A98: Discounted Fuel Production (kg) | B98: =B97/(1+'Study Parameters'!$C$4) ^'Production Cost Baseline'!B$2 -> 0 | C98: =C97/(1+'Study Parameters'!$C$4) ^'Production Cost Baseline'!C$2 -> 51348837 | D98: =D97/(1+'Study Parameters'!$C$4) ^'Production Cost Baseline'!D$2 -> 47766360 | E98: =E97/(1+'Study Parameters'!$C$4) ^'Production Cost Baseline'!E$2 -> 44433823 | F98: =F97/(1+'Study Parameters'!$C$4) ^'Production Cost Baseline'!F$2 -> 41333789 | G98: =G97/(1+'Study Parameters'!$C$4) ^'Production Cost Baseline'!G$2 -> 38450037 | H98: =H97/(1+'Study Parameters'!$C$4) ^'Production Cost Baseline'!H$2 -> 35767476 | I98: =I97/(1+'Study Parameters'!$C$4) ^'Production Cost Baseline'!I$2 -> 33272071 | ... AA98: =AA97/(1+'Study Parameters'!$C$4) ^'Production Cost Baseline'!AA$2 -> 9051644.1
A100: Production Cost of Fuel (€/kg) | B100: =SUM(B96:AA96) / SUM(C98:AA98) -> 0.29113541
A101: Production Cost of Fuel (€/l) | B101: =B100 * Inputs!$C$15 -> 0.23378174
A103: C.5 Baseload
A104: Cost (€) | B104: ='Cost Components'!$Q$12 * 10^6 -> 454000000 | C104: ='Cost Components'!$Q$41*10^6 -> 1.2628787e+08 | D104: ='Cost Components'!$Q$41*10^6 -> 1.2628787e+08 | E104: ='Cost Components'!$Q$41*10^6 -> 1.2628787e+08 | F104: ='Cost Components'!$Q$41*10^6 -> 1.2628787e+08 | G104: ='Cost Components'!$Q$41*10^6 -> 1.2628787e+08 | H104: ='Cost Components'!$Q$41*10^6 -> 1.2628787e+08 | I104: ='Cost Components'!$Q$41*10^6 -> 1.2628787e+08 | J104: ='Cost Components'!$Q$41*10^6 -> 1.2628787e+08 | ... AA104: ='Cost Components'!$Q$41*10^6 -> 1.2628787e+08
A105: Revenue (€) | B105: 0 | C105: ='Cost Components'!$Q$36 * 10^6 -> 1.337e+08 | D105: ='Cost Components'!$Q$36 * 10^6 -> 1.337e+08 | E105: ='Cost Components'!$Q$36 * 10^6 -> 1.337e+08 | F105: ='Cost Components'!$Q$36 * 10^6 -> 1.337e+08 | G105: ='Cost Components'!$Q$36 * 10^6 -> 1.337e+08 | H105: ='Cost Components'!$Q$36 * 10^6 -> 1.337e+08 | I105: ='Cost Components'!$Q$36 * 10^6 -> 1.337e+08 | J105: ='Cost Components'!$Q$36 * 10^6 -> 1.337e+08 | ... AA105: ='Cost Components'!$Q$36 * 10^6 -> 1.337e+08
A106: Free Cash Flow (€) | B106: =B104-B105 -> 454000000 | C106: =C104-C105 -> -7412131.5 | D106: =D104-D105 -> -7412131.5 | E106: =E104-E105 -> -7412131.5 | F106: =F104-F105 -> -7412131.5 | G106: =G104-G105 -> -7412131.5 | H106: =H104-H105 -> -7412131.5 | I106: =I104-I105 -> -7412131.5 | ... AA106: =AA104-AA105 -> -7412131.5
A107: Discounted Cash Flow (€) | B107: =B106/(1+'Study Parameters'!$C$4) ^'Production Cost Baseline'!B$2 -> 454000000 | C107: =C106/(1+'Study Parameters'!$C$4) ^'Production Cost Baseline'!C$2 -> -6895006.1 | D107: =D106/(1+'Study Parameters'!$C$4) ^'Production Cost Baseline'!D$2 -> -6413959.1 | E107: =E106/(1+'Study Parameters'!$C$4) ^'Production Cost Baseline'!E$2 -> -5966473.6 | F107: =F106/(1+'Study Parameters'!$C$4) ^'Production Cost Baseline'!F$2 -> -5550208 | G107: =G106/(1+'Study Parameters'!$C$4) ^'Production Cost Baseline'!G$2 -> -5162984.2 | H107: =H106/(1+'Study Parameters'!$C$4) ^'Production Cost Baseline'!H$2 -> -4802776 | I107: =I106/(1+'Study Parameters'!$C$4) ^'Production Cost Baseline'!I$2 -> -4467698.6 | ... AA107: =AA106/(1+'Study Parameters'!$C$4) ^'Production Cost Baseline'!AA$2 -> -1215434.4
A108: Fuel Production (kg) | B108: 0 | C108: ='Study Parameters'!$C$16*'Study Parameters'!$C$8 * 10^3 -> 54400000 | D108: ='Study Parameters'!$C$16*'Study Parameters'!$C$8 * 10^3 -> 54400000 | E108: ='Study Parameters'!$C$16*'Study Parameters'!$C$8 * 10^3 -> 54400000 | F108: ='Study Parameters'!$C$16*'Study Parameters'!$C$8 * 10^3 -> 54400000 | G108: ='Study Parameters'!$C$16*'Study Parameters'!$C$8 * 10^3 -> 54400000 | H108: ='Study Parameters'!$C$16*'Study Parameters'!$C$8 * 10^3 -> 54400000 | I108: ='Study Parameters'!$C$16*'Study Parameters'!$C$8 * 10^3 -> 54400000 | J108: ='Study Parameters'!$C$16*'Study Parameters'!$C$8 * 10^3 -> 54400000 | ... AA108: ='Study Parameters'!$C$16*'Study Parameters'!$C$8 * 10^3 -> 54400000
A109: Discounted Fuel Production (kg) | B109: =B108/(1+'Study Parameters'!$C$4) ^'Production Cost Baseline'!B$2 -> 0 | C109: =C108/(1+'Study Parameters'!$C$4) ^'Production Cost Baseline'!C$2 -> 50604651 | D109: =D108/(1+'Study Parameters'!$C$4) ^'Production Cost Baseline'!D$2 -> 47074094 | E109: =E108/(1+'Study Parameters'!$C$4) ^'Production Cost Baseline'!E$2 -> 43789855 | F109: =F108/(1+'Study Parameters'!$C$4) ^'Production Cost Baseline'!F$2 -> 40734749 | G109: =G108/(1+'Study Parameters'!$C$4) ^'Production Cost Baseline'!G$2 -> 37892790 | H109: =H108/(1+'Study Parameters'!$C$4) ^'Production Cost Baseline'!H$2 -> 35249107 | I109: =I108/(1+'Study Parameters'!$C$4) ^'Production Cost Baseline'!I$2 -> 32789867 | ... AA109: =AA108/(1+'Study Parameters'!$C$4) ^'Production Cost Baseline'!AA$2 -> 8920460.9
A111: Production Cost of Fuel (€/kg) | B111: =SUM(B107:AA107) / SUM(C109:AA109) -> 0.61243591
A112: Production Cost of Fuel (€/l) | B112: =B111 * Inputs!$C$15 -> 0.49178603

Sheet CO2 Corrected Production Cost
A1: 2021
A2: Year | B2: 0 | C2: 1 | D2: 2 | E2: 3 | F2: 4 | G2: 5 | H2: 6 | I2: 7 | J2: 8 | K2: 9 | L2: 10 | M2: 11 | N2: 12 | O2: 13 | P2: 14 | Q2: 15 | R2: 16 | S2: 17 | T2: 18 | U2: 19 | V2: 20 | W2: 21 | X2: 22 | Y2: 23 | Z2: 24 | AA2: 25
A3: C.1 Baseload
A4: Cost (€) | B4: ='Cost Components'!$B$42 * 10^6 -> 1136760000 | C4: =('Cost Components'!$B$43 + 'Cost Components'!$B$40 + 'Cost Components'!$B$41) * 10^6 -> 5.5607486e+08 | D4: =('Cost Components'!$B$43 + 'Cost Components'!$B$40 + 'Cost Components'!$B$41) * 10^6 -> 5.5607486e+08 | E4: =('Cost Components'!$B$43 + 'Cost Components'!$B$40 + 'Cost Components'!$B$41) * 10^6 -> 5.5607486e+08 | F4: =('Cost Components'!$B$43 + 'Cost Components'!$B$40 + 'Cost Components'!$B$41) * 10^6 -> 5.5607486e+08 | G4: =('Cost Components'!$B$43 + 'Cost Components'!$B$40 + 'Cost Components'!$B$41) * 10^6 -> 5.5607486e+08 | H4: =('Cost Components'!$B$43 + 'Cost Components'!$B$40 + 'Cost Components'!$B$41) * 10^6 -> 5.5607486e+08 | I4: =('Cost Components'!$B$43 + 'Cost Components'!$B$40 + 'Cost Components'!$B$41) * 10^6 -> 5.5607486e+08 | J4: =('Cost Components'!$B$43 + 'Cost Components'!$B$40 + 'Cost Components'!$B$41) * 10^6 -> 5.5607486e+08 | ... AA4: =('Cost Components'!$B$43 + 'Cost Components'!$B$40 + 'Cost Components'!$B$41) * 10^6 -> 5.5607486e+08
A5: Revenue (€) | B5: 0 | C5: ='Cost Components'!$B$36*10^6 -> 56800000 | D5: ='Cost Components'!$B$36*10^6 -> 56800000 | E5: ='Cost Components'!$B$36*10^6 -> 56800000 | F5: ='Cost Components'!$B$36*10^6 -> 56800000 | G5: ='Cost Components'!$B$36*10^6 -> 56800000 | H5: ='Cost Components'!$B$36*10^6 -> 56800000 | I5: ='Cost Components'!$B$36*10^6 -> 56800000 | J5: ='Cost Components'!$B$36*10^6 -> 56800000 | ... AA5: ='Cost Components'!$B$36*10^6 -> 56800000
A6: Free Cash Flow (€) | B6: =B4-B5 -> 1136760000 | C6: =C4-C5 -> 4.9927486e+08 | D6: =D4-D5 -> 4.9927486e+08 | E6: =E4-E5 -> 4.9927486e+08 | F6: =F4-F5 -> 4.9927486e+08 | G6: =G4-G5 -> 4.9927486e+08 | H6: =H4-H5 -> 4.9927486e+08 | I6: =I4-I5 -> 4.9927486e+08 | ... AA6: =AA4-AA5 -> 4.9927486e+08
A7: Discounted Cash Flow (€) | B7: =B6/(1+'Study Parameters'!$C$4) ^'Production Cost Baseline'!B$2 -> 1136760000 | C7: =C6/(1+'Study Parameters'!$C$4) ^'Production Cost Baseline'!C$2 -> 4.6444173e+08 | D7: =D6/(1+'Study Parameters'!$C$4) ^'Production Cost Baseline'!D$2 -> 4.3203882e+08 | E7: =E6/(1+'Study Parameters'!$C$4) ^'Production Cost Baseline'!E$2 -> 4.0189657e+08 | F7: =F6/(1+'Study Parameters'!$C$4) ^'Production Cost Baseline'!F$2 -> 3.7385728e+08 | G7: =G6/(1+'Study Parameters'!$C$4) ^'Production Cost Baseline'!G$2 -> 3.4777421e+08 | H7: =H6/(1+'Study Parameters'!$C$4) ^'Production Cost Baseline'!H$2 -> 3.2351089e+08 | I7: =I6/(1+'Study Parameters'!$C$4) ^'Production Cost Baseline'!I$2 -> 3.0094037e+08 | ... AA7: =AA6/(1+'Study Parameters'!$C$4) ^'Production Cost Baseline'!AA$2 -> 81870622
A8: Fuel Production (kg) | B8: 0 | C8: ='Study Parameters'!$C$12*'Study Parameters'!$C$8 * 10^3 -> 69600000 | D8: ='Study Parameters'!$C$12*'Study Parameters'!$C$8 * 10^3 -> 69600000 | E8: ='Study Parameters'!$C$12*'Study Parameters'!$C$8 * 10^3 -> 69600000 | F8: ='Study Parameters'!$C$12*'Study Parameters'!$C$8 * 10^3 -> 69600000 | G8: ='Study Parameters'!$C$12*'Study Parameters'!$C$8 * 10^3 -> 69600000 | H8: ='Study Parameters'!$C$12*'Study Parameters'!$C$8 * 10^3 -> 69600000 | I8: ='Study Parameters'!$C$12*'Study Parameters'!$C$8 * 10^3 -> 69600000 | J8: ='Study Parameters'!$C$12*'Study Parameters'!$C$8 * 10^3 -> 69600000 | ... AA8: ='Study Parameters'!$C$12*'Study Parameters'!$C$8 * 10^3 -> 69600000
A9: Discounted Fuel Production (kg) | B9: 0 | C9: =C8/(1+'Study Parameters'!$C$4) ^'Production Cost Baseline'!C$2 -> 64744186 | D9: =D8/(1+'Study Parameters'!$C$4) ^'Production Cost Baseline'!D$2 -> 60227150 | E9: =E8/(1+'Study Parameters'!$C$4) ^'Production Cost Baseline'!E$2 -> 56025256 | F9: =F8/(1+'Study Parameters'!$C$4) ^'Production Cost Baseline'!F$2 -> 52116517 | G9: =G8/(1+'Study Parameters'!$C$4) ^'Production Cost Baseline'!G$2 -> 48480481 | H9: =H8/(1+'Study Parameters'!$C$4) ^'Production Cost Baseline'!H$2 -> 45098122 | I9: =I8/(1+'Study Parameters'!$C$4) ^'Production Cost Baseline'!I$2 -> 41951741 | J9: =J8/(1+'Study Parameters'!$C$4) ^'Production Cost Baseline'!J$2 -> 39024875 | ... AA9: =AA8/(1+'Study Parameters'!$C$4) ^'Production Cost Baseline'!AA$2 -> 11412943
A11: Production Cost of Fuel (€/kg) | B11: =SUM(B7:AA7) / SUM(C9:AA9) -> 8.6387121
A12: Production Cost of Fuel (€/l) | B12: =B11 * Inputs!$C$15 -> 6.9368858
A14: C.2 Baseload
A15: Cost (€) | B15: ='Cost Components'!$C$42 * 10^6 -> 827300000 | C15: =('Cost Components'!$C$43 + 'Cost Components'!$C$40 + 'Cost Components'!$C$41) * 10^6 -> 4.8325164e+08 | D15: =('Cost Components'!$C$43 + 'Cost Components'!$C$40 + 'Cost Components'!$C$41) * 10^6 -> 4.8325164e+08 | E15: =('Cost Components'!$C$43 + 'Cost Components'!$C$40 + 'Cost Components'!$C$41) * 10^6 -> 4.8325164e+08 | F15: =('Cost Components'!$C$43 + 'Cost Components'!$C$40 + 'Cost Components'!$C$41) * 10^6 -> 4.8325164e+08 | G15: =('Cost Components'!$C$43 + 'Cost Components'!$C$40 + 'Cost Components'!$C$41) * 10^6 -> 4.8325164e+08 | H15: =('Cost Components'!$C$43 + 'Cost Components'!$C$40 + 'Cost Components'!$C$41) * 10^6 -> 4.8325164e+08 | I15: =('Cost Components'!$C$43 + 'Cost Components'!$C$40 + 'Cost Components'!$C$41) * 10^6 -> 4.8325164e+08 | J15: =('Cost Components'!$C$43 + 'Cost Components'!$C$40 + 'Cost Components'!$C$41) * 10^6 -> 4.8325164e+08 | ... AA15: =('Cost Components'!$C$43 + 'Cost Components'!$C$40 + 'Cost Components'!$C$41) * 10^6 -> 4.8325164e+08
A16: Revenue (€) | B16: 0 | C16: ='Cost Components'!$C$36*10^6 -> 1.499e+08 | D16: ='Cost Components'!$C$36*10^6 -> 1.499e+08 | E16: ='Cost Components'!$C$36*10^6 -> 1.499e+08 | F16: ='Cost Components'!$C$36*10^6 -> 1.499e+08 | G16: ='Cost Components'!$C$36*10^6 -> 1.499e+08 | H16: ='Cost Components'!$C$36*10^6 -> 1.499e+08 | I16: ='Cost Components'!$C$36*10^6 -> 1.499e+08 | J16: ='Cost Components'!$C$36*10^6 -> 1.499e+08 | ... AA16: ='Cost Components'!$C$36*10^6 -> 1.499e+08
A17: Free Cash Flow (€) | B17: =B15-B16 -> 827300000 | C17: =C15-C16 -> 3.3335164e+08 | D17: =D15-D16 -> 3.3335164e+08 | E17: =E15-E16 -> 3.3335164e+08 | F17: =F15-F16 -> 3.3335164e+08 | G17: =G15-G16 -> 3.3335164e+08 | H17: =H15-H16 -> 3.3335164e+08 | I17: =I15-I16 -> 3.3335164e+08 | ... AA17: =AA15-AA16 -> 3.3335164e+08
A18: Discounted Cash Flow (€) | B18: =B17/(1+'Study Parameters'!$C$4) ^'Production Cost Baseline'!B$2 -> 827300000 | C18: =C17/(1+'Study Parameters'!$C$4) ^'Production Cost Baseline'!C$2 -> 3.1009455e+08 | D18: =D17/(1+'Study Parameters'!$C$4) ^'Production Cost Baseline'!D$2 -> 2.8846004e+08 | E18: =E17/(1+'Study Parameters'!$C$4) ^'Production Cost Baseline'!E$2 -> 2.6833493e+08 | F18: =F17/(1+'Study Parameters'!$C$4) ^'Production Cost Baseline'!F$2 -> 2.4961388e+08 | G18: =G17/(1+'Study Parameters'!$C$4) ^'Production Cost Baseline'!G$2 -> 2.3219896e+08 | H18: =H17/(1+'Study Parameters'!$C$4) ^'Production Cost Baseline'!H$2 -> 2.1599903e+08 | I18: =I17/(1+'Study Parameters'!$C$4) ^'Production Cost Baseline'!I$2 -> 2.0092933e+08 | ... AA18: =AA17/(1+'Study Parameters'!$C$4) ^'Production Cost Baseline'!AA$2 -> 54662689
A19: Fuel Production (kg) | B19: 0 | C19: ='Study Parameters'!$C$13*'Study Parameters'!$C$8 * 10^3 -> 28000000 | D19: ='Study Parameters'!$C$13*'Study Parameters'!$C$8 * 10^3 -> 28000000 | E19: ='Study Parameters'!$C$13*'Study Parameters'!$C$8 * 10^3 -> 28000000 | F19: ='Study Parameters'!$C$13*'Study Parameters'!$C$8 * 10^3 -> 28000000 | G19: ='Study Parameters'!$C$13*'Study Parameters'!$C$8 * 10^3 -> 28000000 | H19: ='Study Parameters'!$C$13*'Study Parameters'!$C$8 * 10^3 -> 28000000 | I19: ='Study Parameters'!$C$13*'Study Parameters'!$C$8 * 10^3 -> 28000000 | J19: ='Study Parameters'!$C$13*'Study Parameters'!$C$8 * 10^3 -> 28000000 | ... AA19: ='Study Parameters'!$C$13*'Study Parameters'!$C$8 * 10^3 -> 28000000
A20: Discounted Fuel Production (kg) | B20: 0 | C20: =C19/(1+'Study Parameters'!$C$4) ^'Production Cost Baseline'!C$2 -> 26046512 | D20: =D19/(1+'Study Parameters'!$C$4) ^'Production Cost Baseline'!D$2 -> 24229313 | E20: =E19/(1+'Study Parameters'!$C$4) ^'Production Cost Baseline'!E$2 -> 22538896 | F20: =F19/(1+'Study Parameters'!$C$4) ^'Production Cost Baseline'!F$2 -> 20966415 | G20: =G19/(1+'Study Parameters'!$C$4) ^'Production Cost Baseline'!G$2 -> 19503642 | H20: =H19/(1+'Study Parameters'!$C$4) ^'Production Cost Baseline'!H$2 -> 18142923 | I20: =I19/(1+'Study Parameters'!$C$4) ^'Production Cost Baseline'!I$2 -> 16877137 | J20: =J19/(1+'Study Parameters'!$C$4) ^'Production Cost Baseline'!J$2 -> 15699663 | ... AA20: =AA19/(1+'Study Parameters'!$C$4) ^'Production Cost Baseline'!AA$2 -> 4591413.7
A22: Production Cost of Fuel (€/kg) | B22: =SUM(B18:AA18) / SUM(C20:AA20) -> 14.556046
A23: Production Cost of Fuel (€/l) | B23: =B22 * Inputs!$C$15 -> 11.688505
A25: C.3 Baseload
A26: Cost (€) | B26: ='Cost Components'!$D$42 * 10^6 -> 887030000 | C26: =('Cost Components'!$D$43 + 'Cost Components'!$D$40 + 'Cost Components'!$D$41) * 10^6 -> 5.4418008e+08 | D26: =('Cost Components'!$D$43 + 'Cost Components'!$D$40 + 'Cost Components'!$D$41) * 10^6 -> 5.4418008e+08 | E26: =('Cost Components'!$D$43 + 'Cost Components'!$D$40 + 'Cost Components'!$D$41) * 10^6 -> 5.4418008e+08 | F26: =('Cost Components'!$D$43 + 'Cost Components'!$D$40 + 'Cost Components'!$D$41) * 10^6 -> 5.4418008e+08 | G26: =('Cost Components'!$D$43 + 'Cost Components'!$D$40 + 'Cost Components'!$D$41) * 10^6 -> 5.4418008e+08 | H26: =('Cost Components'!$D$43 + 'Cost Components'!$D$40 + 'Cost Components'!$D$41) * 10^6 -> 5.4418008e+08 | I26: =('Cost Components'!$D$43 + 'Cost Components'!$D$40 + 'Cost Components'!$D$41) * 10^6 -> 5.4418008e+08 | J26: =('Cost Components'!$D$43 + 'Cost Components'!$D$40 + 'Cost Components'!$D$41) * 10^6 -> 5.4418008e+08 | ... AA26: =('Cost Components'!$D$43 + 'Cost Components'!$D$40 + 'Cost Components'!$D$41) * 10^6 -> 5.4418008e+08
A27: Revenue (€) | B27: 0 | C27: ='Cost Components'!$D$36*10^6 -> 81000000 | D27: ='Cost Components'!$D$36*10^6 -> 81000000 | E27: ='Cost Components'!$D$36*10^6 -> 81000000 | F27: ='Cost Components'!$D$36*10^6 -> 81000000 | G27: ='Cost Components'!$D$36*10^6 -> 81000000 | H27: ='Cost Components'!$D$36*10^6 -> 81000000 | I27: ='Cost Components'!$D$36*10^6 -> 81000000 | J27: ='Cost Components'!$D$36*10^6 -> 81000000 | ... AA27: ='Cost Components'!$D$36*10^6 -> 81000000
A28: Free Cash Flow (€) | B28: =B26-B27 -> 887030000 | C28: =C26-C27 -> 4.6318008e+08 | D28: =D26-D27 -> 4.6318008e+08 | E28: =E26-E27 -> 4.6318008e+08 | F28: =F26-F27 -> 4.6318008e+08 | G28: =G26-G27 -> 4.6318008e+08 | H28: =H26-H27 -> 4.6318008e+08 | I28: =I26-I27 -> 4.6318008e+08 | ... AA28: =AA26-AA27 -> 4.6318008e+08
A29: Discounted Cash Flow (€) | B29: =B28/(1+'Study Parameters'!$C$4) ^'Production Cost Baseline'!B$2 -> 887030000 | C29: =C28/(1+'Study Parameters'!$C$4) ^'Production Cost Baseline'!C$2 -> 4.3086519e+08 | D29: =D28/(1+'Study Parameters'!$C$4) ^'Production Cost Baseline'!D$2 -> 4.0080483e+08 | E29: =E28/(1+'Study Parameters'!$C$4) ^'Production Cost Baseline'!E$2 -> 3.728417e+08 | F29: =F28/(1+'Study Parameters'!$C$4) ^'Production Cost Baseline'!F$2 -> 3.4682949e+08 | G29: =G28/(1+'Study Parameters'!$C$4) ^'Production Cost Baseline'!G$2 -> 3.2263208e+08 | H29: =H28/(1+'Study Parameters'!$C$4) ^'Production Cost Baseline'!H$2 -> 3.0012287e+08 | I29: =I28/(1+'Study Parameters'!$C$4) ^'Production Cost Baseline'!I$2 -> 2.7918406e+08 | ... AA29: =AA28/(1+'Study Parameters'!$C$4) ^'Production Cost Baseline'!AA$2 -> 75951834
A30: Fuel Production (kg) | B30: 0 | C30: ='Study Parameters'!$C$14*'Study Parameters'!$C$8 * 10^3 -> 38400000 | D30: ='Study Parameters'!$C$14*'Study Parameters'!$C$8 * 10^3 -> 38400000 | E30: ='Study Parameters'!$C$14*'Study Parameters'!$C$8 * 10^3 -> 38400000 | F30: ='Study Parameters'!$C$14*'Study Parameters'!$C$8 * 10^3 -> 38400000 | G30: ='Study Parameters'!$C$14*'Study Parameters'!$C$8 * 10^3 -> 38400000 | H30: ='Study Parameters'!$C$14*'Study Parameters'!$C$8 * 10^3 -> 38400000 | I30: ='Study Parameters'!$C$14*'Study Parameters'!$C$8 * 10^3 -> 38400000 | J30: ='Study Parameters'!$C$14*'Study Parameters'!$C$8 * 10^3 -> 38400000 | ... AA30: ='Study Parameters'!$C$14*'Study Parameters'!$C$8 * 10^3 -> 38400000
A31: Discounted Fuel Production (kg) | B31: 0 | C31: =C30/(1+'Study Parameters'!$C$4) ^'Production Cost Baseline'!C$2 -> 35720930 | D31: =D30/(1+'Study Parameters'!$C$4) ^'Production Cost Baseline'!D$2 -> 33228772 | E31: =E30/(1+'Study Parameters'!$C$4) ^'Production Cost Baseline'!E$2 -> 30910486 | F31: =F30/(1+'Study Parameters'!$C$4) ^'Production Cost Baseline'!F$2 -> 28753940 | G31: =G30/(1+'Study Parameters'!$C$4) ^'Production Cost Baseline'!G$2 -> 26747851 | H31: =H30/(1+'Study Parameters'!$C$4) ^'Production Cost Baseline'!H$2 -> 24881722 | I31: =I30/(1+'Study Parameters'!$C$4) ^'Production Cost Baseline'!I$2 -> 23145788 | J31: =J30/(1+'Study Parameters'!$C$4) ^'Production Cost Baseline'!J$2 -> 21530966 | ... AA31: =AA30/(1+'Study Parameters'!$C$4) ^'Production Cost Baseline'!AA$2 -> 6296795.9
A33: Production Cost of Fuel (€/kg) | B33: =SUM(B29:AA29) / SUM(C31:AA31) -> 14.134274
A34: Production Cost of Fuel (€/l) | B34: =B33 * Inputs!$C$15 -> 11.349822
A36: C.4 Baseload
A37: Cost (€) | B37: ='Cost Components'!$E$42 * 10^6 -> 8.4492e+08 | C37: =('Cost Components'!$E$43 + 'Cost Components'!$E$40 + 'Cost Components'!$E$41) * 10^6 -> 4.8847818e+08 | D37: =('Cost Components'!$E$43 + 'Cost Components'!$E$40 + 'Cost Components'!$E$41) * 10^6 -> 4.8847818e+08 | E37: =('Cost Components'!$E$43 + 'Cost Components'!$E$40 + 'Cost Components'!$E$41) * 10^6 -> 4.8847818e+08 | F37: =('Cost Components'!$E$43 + 'Cost Components'!$E$40 + 'Cost Components'!$E$41) * 10^6 -> 4.8847818e+08 | G37: =('Cost Components'!$E$43 + 'Cost Components'!$E$40 + 'Cost Components'!$E$41) * 10^6 -> 4.8847818e+08 | H37: =('Cost Components'!$E$43 + 'Cost Components'!$E$40 + 'Cost Components'!$E$41) * 10^6 -> 4.8847818e+08 | I37: =('Cost Components'!$E$43 + 'Cost Components'!$E$40 + 'Cost Components'!$E$41) * 10^6 -> 4.8847818e+08 | J37: =('Cost Components'!$E$43 + 'Cost Components'!$E$40 + 'Cost Components'!$E$41) * 10^6 -> 4.8847818e+08 | ... AA37: =('Cost Components'!$E$43 + 'Cost Components'!$E$40 + 'Cost Components'!$E$41) * 10^6 -> 4.8847818e+08
A38: Revenue (€) | B38: 0 | C38: ='Cost Components'!$E$36*10^6 -> 103200000 | D38: ='Cost Components'!$E$36*10^6 -> 103200000 | E38: ='Cost Components'!$E$36*10^6 -> 103200000 | F38: ='Cost Components'!$E$36*10^6 -> 103200000 | G38: ='Cost Components'!$E$36*10^6 -> 103200000 | H38: ='Cost Components'!$E$36*10^6 -> 103200000 | I38: ='Cost Components'!$E$36*10^6 -> 103200000 | J38: ='Cost Components'!$E$36*10^6 -> 103200000 | ... AA38: ='Cost Components'!$E$36*10^6 -> 103200000
A39: Free Cash Flow (€) | B39: =B37-B38 -> 8.4492e+08 | C39: =C37-C38 -> 3.8527818e+08 | D39: =D37-D38 -> 3.8527818e+08 | E39: =E37-E38 -> 3.8527818e+08 | F39: =F37-F38 -> 3.8527818e+08 | G39: =G37-G38 -> 3.8527818e+08 | H39: =H37-H38 -> 3.8527818e+08 | I39: =I37-I38 -> 3.8527818e+08 | ... AA39: =AA37-AA38 -> 3.8527818e+08
A40: Discounted Cash Flow (€) | B40: =B39/(1+'Study Parameters'!$C$4) ^'Production Cost Baseline'!B$2 -> 8.4492e+08 | C40: =C39/(1+'Study Parameters'!$C$4) ^'Production Cost Baseline'!C$2 -> 3.5839831e+08 | D40: =D39/(1+'Study Parameters'!$C$4) ^'Production Cost Baseline'!D$2 -> 3.3339377e+08 | E40: =E39/(1+'Study Parameters'!$C$4) ^'Production Cost Baseline'!E$2 -> 3.1013374e+08 | F40: =F39/(1+'Study Parameters'!$C$4) ^'Production Cost Baseline'!F$2 -> 2.8849651e+08 | G40: =G39/(1+'Study Parameters'!$C$4) ^'Production Cost Baseline'!G$2 -> 2.6836884e+08 | H40: =H39/(1+'Study Parameters'!$C$4) ^'Production Cost Baseline'!H$2 -> 2.4964543e+08 | I40: =I39/(1+'Study Parameters'!$C$4) ^'Production Cost Baseline'!I$2 -> 2.3222831e+08 | ... AA40: =AA39/(1+'Study Parameters'!$C$4) ^'Production Cost Baseline'!AA$2 -> 63177554
A41: Fuel Production (kg) | B41: 0 | C41: ='Study Parameters'!$C$15*'Study Parameters'!$C$8 * 10^3 -> 55200000 | D41: ='Study Parameters'!$C$15*'Study Parameters'!$C$8 * 10^3 -> 55200000 | E41: ='Study Parameters'!$C$15*'Study Parameters'!$C$8 * 10^3 -> 55200000 | F41: ='Study Parameters'!$C$15*'Study Parameters'!$C$8 * 10^3 -> 55200000 | G41: ='Study Parameters'!$C$15*'Study Parameters'!$C$8 * 10^3 -> 55200000 | H41: ='Study Parameters'!$C$15*'Study Parameters'!$C$8 * 10^3 -> 55200000 | I41: ='Study Parameters'!$C$15*'Study Parameters'!$C$8 * 10^3 -> 55200000 | J41: ='Study Parameters'!$C$15*'Study Parameters'!$C$8 * 10^3 -> 55200000 | ... AA41: ='Study Parameters'!$C$15*'Study Parameters'!$C$8 * 10^3 -> 55200000
A42: Discounted Fuel Production (kg) | B42: 0 | C42: =C41/(1+'Study Parameters'!$C$4) ^'Production Cost Baseline'!C$2 -> 51348837 | D42: =D41/(1+'Study Parameters'!$C$4) ^'Production Cost Baseline'!D$2 -> 47766360 | E42: =E41/(1+'Study Parameters'!$C$4) ^'Production Cost Baseline'!E$2 -> 44433823 | F42: =F41/(1+'Study Parameters'!$C$4) ^'Production Cost Baseline'!F$2 -> 41333789 | G42: =G41/(1+'Study Parameters'!$C$4) ^'Production Cost Baseline'!G$2 -> 38450037 | H42: =H41/(1+'Study Parameters'!$C$4) ^'Production Cost Baseline'!H$2 -> 35767476 | I42: =I41/(1+'Study Parameters'!$C$4) ^'Production Cost Baseline'!I$2 -> 33272071 | J42: =J41/(1+'Study Parameters'!$C$4) ^'Production Cost Baseline'!J$2 -> 30950763 | ... AA42: =AA41/(1+'Study Parameters'!$C$4) ^'Production Cost Baseline'!AA$2 -> 9051644.1
A44: Production Cost of Fuel (€/kg) | B44: =SUM(B40:AA40) / SUM(C42:AA42) -> 8.3528355
A45: Production Cost of Fuel (€/l) | B45: =B44 * Inputs!$C$15 -> 6.7073269
A47: C.5 Baseload
A48: Cost (€) | B48: ='Cost Components'!$F$42 * 10^6 -> 9.4766e+08 | C48: =('Cost Components'!$F$43 + 'Cost Components'!$F$40 + 'Cost Components'!$F$41) * 10^6 -> 5.2917814e+08 | D48: =('Cost Components'!$F$43 + 'Cost Components'!$F$40 + 'Cost Components'!$F$41) * 10^6 -> 5.2917814e+08 | E48: =('Cost Components'!$F$43 + 'Cost Components'!$F$40 + 'Cost Components'!$F$41) * 10^6 -> 5.2917814e+08 | F48: =('Cost Components'!$F$43 + 'Cost Components'!$F$40 + 'Cost Components'!$F$41) * 10^6 -> 5.2917814e+08 | G48: =('Cost Components'!$F$43 + 'Cost Components'!$F$40 + 'Cost Components'!$F$41) * 10^6 -> 5.2917814e+08 | H48: =('Cost Components'!$F$43 + 'Cost Components'!$F$40 + 'Cost Components'!$F$41) * 10^6 -> 5.2917814e+08 | I48: =('Cost Components'!$F$43 + 'Cost Components'!$F$40 + 'Cost Components'!$F$41) * 10^6 -> 5.2917814e+08 | J48: =('Cost Components'!$F$43 + 'Cost Components'!$F$40 + 'Cost Components'!$F$41) * 10^6 -> 5.2917814e+08 | ... AA48: =('Cost Components'!$F$43 + 'Cost Components'!$F$40 + 'Cost Components'!$F$41) * 10^6 -> 5.2917814e+08
A49: Revenue (€) | B49: 0 | C49: ='Cost Components'!$F$36*10^6 -> 135200000 | D49: ='Cost Components'!$F$36*10^6 -> 135200000 | E49: ='Cost Components'!$F$36*10^6 -> 135200000 | F49: ='Cost Components'!$F$36*10^6 -> 135200000 | G49: ='Cost Components'!$F$36*10^6 -> 135200000 | H49: ='Cost Components'!$F$36*10^6 -> 135200000 | I49: ='Cost Components'!$F$36*10^6 -> 135200000 | J49: ='Cost Components'!$F$36*10^6 -> 135200000 | ... AA49: ='Cost Components'!$F$36*10^6 -> 135200000
A50: Free Cash Flow (€) | B50: =B48-B49 -> 9.4766e+08 | C50: =C48-C49 -> 3.9397814e+08 | D50: =D48-D49 -> 3.9397814e+08 | E50: =E48-E49 -> 3.9397814e+08 | F50: =F48-F49 -> 3.9397814e+08 | G50: =G48-G49 -> 3.9397814e+08 | H50: =H48-H49 -> 3.9397814e+08 | I50: =I48-I49 -> 3.9397814e+08 | ... AA50: =AA48-AA49 -> 3.9397814e+08
A51: Discounted Cash Flow (€) | B51: =B50/(1+'Study Parameters'!$C$4) ^'Production Cost Baseline'!B$2 -> 9.4766e+08 | C51: =C50/(1+'Study Parameters'!$C$4) ^'Production Cost Baseline'!C$2 -> 3.664913e+08 | D51: =D50/(1+'Study Parameters'!$C$4) ^'Production Cost Baseline'!D$2 -> 3.4092214e+08 | E51: =E50/(1+'Study Parameters'!$C$4) ^'Production Cost Baseline'!E$2 -> 3.1713687e+08 | F51: =F50/(1+'Study Parameters'!$C$4) ^'Production Cost Baseline'!F$2 -> 2.9501104e+08 | G51: =G50/(1+'Study Parameters'!$C$4) ^'Production Cost Baseline'!G$2 -> 2.7442888e+08 | H51: =H50/(1+'Study Parameters'!$C$4) ^'Production Cost Baseline'!H$2 -> 2.5528268e+08 | I51: =I50/(1+'Study Parameters'!$C$4) ^'Production Cost Baseline'!I$2 -> 2.3747226e+08 | ... AA51: =AA50/(1+'Study Parameters'!$C$4) ^'Production Cost Baseline'!AA$2 -> 64604166
A52: Fuel Production (kg) | B52: 0 | C52: ='Study Parameters'!$C$16*'Study Parameters'!$C$8 * 10^3 -> 54400000 | D52: ='Study Parameters'!$C$16*'Study Parameters'!$C$8 * 10^3 -> 54400000 | E52: ='Study Parameters'!$C$16*'Study Parameters'!$C$8 * 10^3 -> 54400000 | F52: ='Study Parameters'!$C$16*'Study Parameters'!$C$8 * 10^3 -> 54400000 | G52: ='Study Parameters'!$C$16*'Study Parameters'!$C$8 * 10^3 -> 54400000 | H52: ='Study Parameters'!$C$16*'Study Parameters'!$C$8 * 10^3 -> 54400000 | I52: ='Study Parameters'!$C$16*'Study Parameters'!$C$8 * 10^3 -> 54400000 | J52: ='Study Parameters'!$C$16*'Study Parameters'!$C$8 * 10^3 -> 54400000 | ... AA52: ='Study Parameters'!$C$16*'Study Parameters'!$C$8 * 10^3 -> 54400000
A53: Discounted Fuel Production (kg) | B53: 0 | C53: =C52/(1+'Study Parameters'!$C$4) ^'Production Cost Baseline'!C$2 -> 50604651 | D53: =D52/(1+'Study Parameters'!$C$4) ^'Production Cost Baseline'!D$2 -> 47074094 | E53: =E52/(1+'Study Parameters'!$C$4) ^'Production Cost Baseline'!E$2 -> 43789855 | F53: =F52/(1+'Study Parameters'!$C$4) ^'Production Cost Baseline'!F$2 -> 40734749 | G53: =G52/(1+'Study Parameters'!$C$4) ^'Production Cost Baseline'!G$2 -> 37892790 | H53: =H52/(1+'Study Parameters'!$C$4) ^'Production Cost Baseline'!H$2 -> 35249107 | I53: =I52/(1+'Study Parameters'!$C$4) ^'Production Cost Baseline'!I$2 -> 32789867 | J53: =J52/(1+'Study Parameters'!$C$4) ^'Production Cost Baseline'!J$2 -> 30502201 | ... AA53: =AA52/(1+'Study Parameters'!$C$4) ^'Production Cost Baseline'!AA$2 -> 8920460.9
A55: Production Cost of Fuel (€/kg) | B55: =SUM(B51:AA51) / SUM(C53:AA53) -> 8.805025
A56: Production Cost of Fuel (€/l) | B56: =B55 * Inputs!$C$15 -> 7.0704351
A58: 2050
A59: C.1 Baseload
A60: Cost (€) | B60: ='Cost Components'!$M$43 * 10^6 -> 428200000 | C60: =('Cost Components'!$M$44 + 'Cost Components'!$M$42)*10^6 -> 2.6870175e+08 | D60: =('Cost Components'!$M$44 + 'Cost Components'!$M$42)*10^6 -> 2.6870175e+08 | E60: =('Cost Components'!$M$44 + 'Cost Components'!$M$42)*10^6 -> 2.6870175e+08 | F60: =('Cost Components'!$M$44 + 'Cost Components'!$M$42)*10^6 -> 2.6870175e+08 | G60: =('Cost Components'!$M$44 + 'Cost Components'!$M$42)*10^6 -> 2.6870175e+08 | H60: =('Cost Components'!$M$44 + 'Cost Components'!$M$42)*10^6 -> 2.6870175e+08 | I60: =('Cost Components'!$M$44 + 'Cost Components'!$M$42)*10^6 -> 2.6870175e+08 | J60: =('Cost Components'!$M$44 + 'Cost Components'!$M$42)*10^6 -> 2.6870175e+08 | ... AA60: =('Cost Components'!$M$44 + 'Cost Components'!$M$42)*10^6 -> 2.6870175e+08
A61: Revenue (€) | B61: 0 | C61: ='Cost Components'!$M$36 * 10^6 -> 149900000 | D61: ='Cost Components'!$M$36 * 10^6 -> 149900000 | E61: ='Cost Components'!$M$36 * 10^6 -> 149900000 | F61: ='Cost Components'!$M$36 * 10^6 -> 149900000 | G61: ='Cost Components'!$M$36 * 10^6 -> 149900000 | H61: ='Cost Components'!$M$36 * 10^6 -> 149900000 | I61: ='Cost Components'!$M$36 * 10^6 -> 149900000 | J61: ='Cost Components'!$M$36 * 10^6 -> 149900000 | ... AA61: ='Cost Components'!$M$36 * 10^6 -> 149900000
A62: Free Cash Flow (€) | B62: =B60-B61 -> 428200000 | C62: =C60-C61 -> 1.1880175e+08 | D62: =D60-D61 -> 1.1880175e+08 | E62: =E60-E61 -> 1.1880175e+08 | F62: =F60-F61 -> 1.1880175e+08 | G62: =G60-G61 -> 1.1880175e+08 | H62: =H60-H61 -> 1.1880175e+08 | I62: =I60-I61 -> 1.1880175e+08 | ... AA62: =AA60-AA61 -> 1.1880175e+08
A63: Discounted Cash Flow (€) | B63: =B62/(1+'Study Parameters'!$C$4) ^'Production Cost Baseline'!B$2 -> 428200000 | C63: =C62/(1+'Study Parameters'!$C$4) ^'Production Cost Baseline'!C$2 -> 1.1051325e+08 | D63: =D62/(1+'Study Parameters'!$C$4) ^'Production Cost Baseline'!D$2 -> 1.0280303e+08 | E63: =E62/(1+'Study Parameters'!$C$4) ^'Production Cost Baseline'!E$2 -> 95630722 | F63: =F62/(1+'Study Parameters'!$C$4) ^'Production Cost Baseline'!F$2 -> 88958811 | G63: =G62/(1+'Study Parameters'!$C$4) ^'Production Cost Baseline'!G$2 -> 82752383 | H63: =H62/(1+'Study Parameters'!$C$4) ^'Production Cost Baseline'!H$2 -> 76978961 | I63: =I62/(1+'Study Parameters'!$C$4) ^'Production Cost Baseline'!I$2 -> 71608335 | ... AA63: =AA62/(1+'Study Parameters'!$C$4) ^'Production Cost Baseline'!AA$2 -> 19480999
A64: Fuel Production (kg) | B64: 0 | C64: ='Study Parameters'!$C$12*'Study Parameters'!$C$8 * 10^3 -> 69600000 | D64: ='Study Parameters'!$C$12*'Study Parameters'!$C$8 * 10^3 -> 69600000 | E64: ='Study Parameters'!$C$12*'Study Parameters'!$C$8 * 10^3 -> 69600000 | F64: ='Study Parameters'!$C$12*'Study Parameters'!$C$8 * 10^3 -> 69600000 | G64: ='Study Parameters'!$C$12*'Study Parameters'!$C$8 * 10^3 -> 69600000 | H64: ='Study Parameters'!$C$12*'Study Parameters'!$C$8 * 10^3 -> 69600000 | I64: ='Study Parameters'!$C$12*'Study Parameters'!$C$8 * 10^3 -> 69600000 | J64: ='Study Parameters'!$C$12*'Study Parameters'!$C$8 * 10^3 -> 69600000 | ... AA64: ='Study Parameters'!$C$12*'Study Parameters'!$C$8 * 10^3 -> 69600000
A65: Discounted Fuel Production (kg) | B65: =B64/(1+'Study Parameters'!$C$4) ^'Production Cost Baseline'!B$2 -> 0 | C65: =C64/(1+'Study Parameters'!$C$4) ^'Production Cost Baseline'!C$2 -> 64744186 | D65: =D64/(1+'Study Parameters'!$C$4) ^'Production Cost Baseline'!D$2 -> 60227150 | E65: =E64/(1+'Study Parameters'!$C$4) ^'Production Cost Baseline'!E$2 -> 56025256 | F65: =F64/(1+'Study Parameters'!$C$4) ^'Production Cost Baseline'!F$2 -> 52116517 | G65: =G64/(1+'Study Parameters'!$C$4) ^'Production Cost Baseline'!G$2 -> 48480481 | H65: =H64/(1+'Study Parameters'!$C$4) ^'Production Cost Baseline'!H$2 -> 45098122 | I65: =I64/(1+'Study Parameters'!$C$4) ^'Production Cost Baseline'!I$2 -> 41951741 | ... AA65: =AA64/(1+'Study Parameters'!$C$4) ^'Production Cost Baseline'!AA$2 -> 11412943
A67: Production Cost of Fuel (€/kg) | B67: =SUM(B63:AA63) / SUM(C65:AA65) -> 2.2588485
A68: Production Cost of Fuel (€/l) | B68: =B67 * Inputs!$C$15 -> 1.8138554
A70: C.2 Baseload
A71: Cost (€) | B71: ='Cost Components'!$N$43 * 10^6 -> 309400000 | C71: =('Cost Components'!$N$44 + 'Cost Components'!$N$42)*10^6 -> 2.3291963e+08 | D71: =('Cost Components'!$N$44 + 'Cost Components'!$N$42)*10^6 -> 2.3291963e+08 | E71: =('Cost Components'!$N$44 + 'Cost Components'!$N$42)*10^6 -> 2.3291963e+08 | F71: =('Cost Components'!$N$44 + 'Cost Components'!$N$42)*10^6 -> 2.3291963e+08 | G71: =('Cost Components'!$N$44 + 'Cost Components'!$N$42)*10^6 -> 2.3291963e+08 | H71: =('Cost Components'!$N$44 + 'Cost Components'!$N$42)*10^6 -> 2.3291963e+08 | I71: =('Cost Components'!$N$44 + 'Cost Components'!$N$42)*10^6 -> 2.3291963e+08 | J71: =('Cost Components'!$N$44 + 'Cost Components'!$N$42)*10^6 -> 2.3291963e+08 | ... AA71: =('Cost Components'!$N$44 + 'Cost Components'!$N$42)*10^6 -> 2.3291963e+08
A72: Revenue (€) | B72: 0 | C72: ='Cost Components'!$N$36 * 10^6 -> 81000000 | D72: ='Cost Components'!$N$36 * 10^6 -> 81000000 | E72: ='Cost Components'!$N$36 * 10^6 -> 81000000 | F72: ='Cost Components'!$N$36 * 10^6 -> 81000000 | G72: ='Cost Components'!$N$36 * 10^6 -> 81000000 | H72: ='Cost Components'!$N$36 * 10^6 -> 81000000 | I72: ='Cost Components'!$N$36 * 10^6 -> 81000000 | J72: ='Cost Components'!$N$36 * 10^6 -> 81000000 | ... AA72: ='Cost Components'!$N$36 * 10^6 -> 81000000
A73: Free Cash Flow (€) | B73: =B71-B72 -> 309400000 | C73: =C71-C72 -> 1.5191963e+08 | D73: =D71-D72 -> 1.5191963e+08 | E73: =E71-E72 -> 1.5191963e+08 | F73: =F71-F72 -> 1.5191963e+08 | G73: =G71-G72 -> 1.5191963e+08 | H73: =H71-H72 -> 1.5191963e+08 | I73: =I71-I72 -> 1.5191963e+08 | ... AA73: =AA71-AA72 -> 1.5191963e+08
A74: Discounted Cash Flow (€) | B74: =B73/(1+'Study Parameters'!$C$4) ^'Production Cost Baseline'!B$2 -> 309400000 | C74: =C73/(1+'Study Parameters'!$C$4) ^'Production Cost Baseline'!C$2 -> 1.4132059e+08 | D74: =D73/(1+'Study Parameters'!$C$4) ^'Production Cost Baseline'!D$2 -> 1.3146101e+08 | E74: =E73/(1+'Study Parameters'!$C$4) ^'Production Cost Baseline'!E$2 -> 1.2228931e+08 | F74: =F73/(1+'Study Parameters'!$C$4) ^'Production Cost Baseline'!F$2 -> 1.137575e+08 | G74: =G73/(1+'Study Parameters'!$C$4) ^'Production Cost Baseline'!G$2 -> 1.0582093e+08 | H74: =H73/(1+'Study Parameters'!$C$4) ^'Production Cost Baseline'!H$2 -> 98438075 | I74: =I73/(1+'Study Parameters'!$C$4) ^'Production Cost Baseline'!I$2 -> 91570303 | ... AA74: =AA73/(1+'Study Parameters'!$C$4) ^'Production Cost Baseline'!AA$2 -> 24911639
A75: Fuel Production (kg) | B75: 0 | C75: ='Study Parameters'!$C$13*'Study Parameters'!$C$8 * 10^3 -> 28000000 | D75: ='Study Parameters'!$C$13*'Study Parameters'!$C$8 * 10^3 -> 28000000 | E75: ='Study Parameters'!$C$13*'Study Parameters'!$C$8 * 10^3 -> 28000000 | F75: ='Study Parameters'!$C$13*'Study Parameters'!$C$8 * 10^3 -> 28000000 | G75: ='Study Parameters'!$C$13*'Study Parameters'!$C$8 * 10^3 -> 28000000 | H75: ='Study Parameters'!$C$13*'Study Parameters'!$C$8 * 10^3 -> 28000000 | I75: ='Study Parameters'!$C$13*'Study Parameters'!$C$8 * 10^3 -> 28000000 | J75: ='Study Parameters'!$C$13*'Study Parameters'!$C$8 * 10^3 -> 28000000 | ... AA75: ='Study Parameters'!$C$13*'Study Parameters'!$C$8 * 10^3 -> 28000000
A76: Discounted Fuel Production (kg) | B76: =B75/(1+'Study Parameters'!$C$4) ^'Production Cost Baseline'!B$2 -> 0 | C76: =C75/(1+'Study Parameters'!$C$4) ^'Production Cost Baseline'!C$2 -> 26046512 | D76: =D75/(1+'Study Parameters'!$C$4) ^'Production Cost Baseline'!D$2 -> 24229313 | E76: =E75/(1+'Study Parameters'!$C$4) ^'Production Cost Baseline'!E$2 -> 22538896 | F76: =F75/(1+'Study Parameters'!$C$4) ^'Production Cost Baseline'!F$2 -> 20966415 | G76: =G75/(1+'Study Parameters'!$C$4) ^'Production Cost Baseline'!G$2 -> 19503642 | H76: =H75/(1+'Study Parameters'!$C$4) ^'Production Cost Baseline'!H$2 -> 18142923 | I76: =I75/(1+'Study Parameters'!$C$4) ^'Production Cost Baseline'!I$2 -> 16877137 | ... AA76: =AA75/(1+'Study Parameters'!$C$4) ^'Production Cost Baseline'!AA$2 -> 4591413.7
A78: Production Cost of Fuel (€/kg) | B78: =SUM(B74:AA74) / SUM(C76:AA76) -> 6.4170041
A79: Production Cost of Fuel (€/l) | B79: =B78 * Inputs!$C$15 -> 5.1528543
A81: C.3 Baseload
A82: Cost (€) | B82: ='Cost Components'!$O$43 * 10^6 -> 321600000 | C82: =('Cost Components'!$O$44 + 'Cost Components'!$O$42)*10^6 -> 2.4567608e+08 | D82: =('Cost Components'!$O$44 + 'Cost Components'!$O$42)*10^6 -> 2.4567608e+08 | E82: =('Cost Components'!$O$44 + 'Cost Components'!$O$42)*10^6 -> 2.4567608e+08 | F82: =('Cost Components'!$O$44 + 'Cost Components'!$O$42)*10^6 -> 2.4567608e+08 | G82: =('Cost Components'!$O$44 + 'Cost Components'!$O$42)*10^6 -> 2.4567608e+08 | H82: =('Cost Components'!$O$44 + 'Cost Components'!$O$42)*10^6 -> 2.4567608e+08 | I82: =('Cost Components'!$O$44 + 'Cost Components'!$O$42)*10^6 -> 2.4567608e+08 | J82: =('Cost Components'!$O$44 + 'Cost Components'!$O$42)*10^6 -> 2.4567608e+08 | ... AA82: =('Cost Components'!$O$44 + 'Cost Components'!$O$42)*10^6 -> 2.4567608e+08
A83: Revenue (€) | B83: 0 | C83: ='Cost Components'!$O$36 * 10^6 -> 103200000 | D83: ='Cost Components'!$O$36 * 10^6 -> 103200000 | E83: ='Cost Components'!$O$36 * 10^6 -> 103200000 | F83: ='Cost Components'!$O$36 * 10^6 -> 103200000 | G83: ='Cost Components'!$O$36 * 10^6 -> 103200000 | H83: ='Cost Components'!$O$36 * 10^6 -> 103200000 | I83: ='Cost Components'!$O$36 * 10^6 -> 103200000 | J83: ='Cost Components'!$O$36 * 10^6 -> 103200000 | ... AA83: ='Cost Components'!$O$36 * 10^6 -> 103200000
A84: Free Cash Flow (€) | B84: =B82-B83 -> 321600000 | C84: =C82-C83 -> 1.4247608e+08 | D84: =D82-D83 -> 1.4247608e+08 | E84: =E82-E83 -> 1.4247608e+08 | F84: =F82-F83 -> 1.4247608e+08 | G84: =G82-G83 -> 1.4247608e+08 | H84: =H82-H83 -> 1.4247608e+08 | I84: =I82-I83 -> 1.4247608e+08 | ... AA84: =AA82-AA83 -> 1.4247608e+08
A85: Discounted Cash Flow (€) | B85: =B84/(1+'Study Parameters'!$C$4) ^'Production Cost Baseline'!B$2 -> 321600000 | C85: =C84/(1+'Study Parameters'!$C$4) ^'Production Cost Baseline'!C$2 -> 1.3253589e+08 | D85: =D84/(1+'Study Parameters'!$C$4) ^'Production Cost Baseline'!D$2 -> 1.232892e+08 | E85: =E84/(1+'Study Parameters'!$C$4) ^'Production Cost Baseline'!E$2 -> 1.1468763e+08 | F85: =F84/(1+'Study Parameters'!$C$4) ^'Production Cost Baseline'!F$2 -> 1.0668617e+08 | G85: =G84/(1+'Study Parameters'!$C$4) ^'Production Cost Baseline'!G$2 -> 99242945 | H85: =H84/(1+'Study Parameters'!$C$4) ^'Production Cost Baseline'!H$2 -> 92319019 | I85: =I84/(1+'Study Parameters'!$C$4) ^'Production Cost Baseline'!I$2 -> 85878157 | ... AA85: =AA84/(1+'Study Parameters'!$C$4) ^'Production Cost Baseline'!AA$2 -> 23363094
A86: Fuel Production (kg) | B86: 0 | C86: ='Study Parameters'!$C$14*'Study Parameters'!$C$8 * 10^3 -> 38400000 | D86: ='Study Parameters'!$C$14*'Study Parameters'!$C$8 * 10^3 -> 38400000 | E86: ='Study Parameters'!$C$14*'Study Parameters'!$C$8 * 10^3 -> 38400000 | F86: ='Study Parameters'!$C$14*'Study Parameters'!$C$8 * 10^3 -> 38400000 | G86: ='Study Parameters'!$C$14*'Study Parameters'!$C$8 * 10^3 -> 38400000 | H86: ='Study Parameters'!$C$14*'Study Parameters'!$C$8 * 10^3 -> 38400000 | I86: ='Study Parameters'!$C$14*'Study Parameters'!$C$8 * 10^3 -> 38400000 | J86: ='Study Parameters'!$C$14*'Study Parameters'!$C$8 * 10^3 -> 38400000 | ... AA86: ='Study Parameters'!$C$14*'Study Parameters'!$C$8 * 10^3 -> 38400000
A87: Discounted Fuel Production (kg) | B87: =B86/(1+'Study Parameters'!$C$4) ^'Production Cost Baseline'!B$2 -> 0 | C87: =C86/(1+'Study Parameters'!$C$4) ^'Production Cost Baseline'!C$2 -> 35720930 | D87: =D86/(1+'Study Parameters'!$C$4) ^'Production Cost Baseline'!D$2 -> 33228772 | E87: =E86/(1+'Study Parameters'!$C$4) ^'Production Cost Baseline'!E$2 -> 30910486 | F87: =F86/(1+'Study Parameters'!$C$4) ^'Production Cost Baseline'!F$2 -> 28753940 | G87: =G86/(1+'Study Parameters'!$C$4) ^'Production Cost Baseline'!G$2 -> 26747851 | H87: =H86/(1+'Study Parameters'!$C$4) ^'Production Cost Baseline'!H$2 -> 24881722 | I87: =I86/(1+'Study Parameters'!$C$4) ^'Production Cost Baseline'!I$2 -> 23145788 | ... AA87: =AA86/(1+'Study Parameters'!$C$4) ^'Production Cost Baseline'!AA$2 -> 6296795.9
A89: Production Cost of Fuel (€/kg) | B89: =SUM(B85:AA85) / SUM(C87:AA87) -> 4.4616415
A90: Production Cost of Fuel (€/l) | B90: =B89 * Inputs!$C$15 -> 3.5826981
A92: C.4 Baseload
A93: Cost (€) | B93: ='Cost Components'!$P$43 * 10^6 -> 339000000 | C93: =('Cost Components'!$P$44 + 'Cost Components'!$P$42)*10^6 -> 2.2131119e+08 | D93: =('Cost Components'!$P$44 + 'Cost Components'!$P$42)*10^6 -> 2.2131119e+08 | E93: =('Cost Components'!$P$44 + 'Cost Components'!$P$42)*10^6 -> 2.2131119e+08 | F93: =('Cost Components'!$P$44 + 'Cost Components'!$P$42)*10^6 -> 2.2131119e+08 | G93: =('Cost Components'!$P$44 + 'Cost Components'!$P$42)*10^6 -> 2.2131119e+08 | H93: =('Cost Components'!$P$44 + 'Cost Components'!$P$42)*10^6 -> 2.2131119e+08 | I93: =('Cost Components'!$P$44 + 'Cost Components'!$P$42)*10^6 -> 2.2131119e+08 | J93: =('Cost Components'!$P$44 + 'Cost Components'!$P$42)*10^6 -> 2.2131119e+08 | ... AA93: =('Cost Components'!$P$44 + 'Cost Components'!$P$42)*10^6 -> 2.2131119e+08
A94: Revenue (€) | B94: 0 | C94: ='Cost Components'!$P$36 * 10^6 -> 135200000 | D94: ='Cost Components'!$P$36 * 10^6 -> 135200000 | E94: ='Cost Components'!$P$36 * 10^6 -> 135200000 | F94: ='Cost Components'!$P$36 * 10^6 -> 135200000 | G94: ='Cost Components'!$P$36 * 10^6 -> 135200000 | H94: ='Cost Components'!$P$36 * 10^6 -> 135200000 | I94: ='Cost Components'!$P$36 * 10^6 -> 135200000 | J94: ='Cost Components'!$P$36 * 10^6 -> 135200000 | ... AA94: ='Cost Components'!$P$36 * 10^6 -> 135200000
A95: Free Cash Flow (€) | B95: =B93-B94 -> 339000000 | C95: =C93-C94 -> 86111187 | D95: =D93-D94 -> 86111187 | E95: =E93-E94 -> 86111187 | F95: =F93-F94 -> 86111187 | G95: =G93-G94 -> 86111187 | H95: =H93-H94 -> 86111187 | I95: =I93-I94 -> 86111187 | ... AA95: =AA93-AA94 -> 86111187
A96: Discounted Cash Flow (€) | B96: =B95/(1+'Study Parameters'!$C$4) ^'Production Cost Baseline'!B$2 -> 339000000 | C96: =C95/(1+'Study Parameters'!$C$4) ^'Production Cost Baseline'!C$2 -> 80103430 | D96: =D95/(1+'Study Parameters'!$C$4) ^'Production Cost Baseline'!D$2 -> 74514819 | E96: =E95/(1+'Study Parameters'!$C$4) ^'Production Cost Baseline'!E$2 -> 69316110 | F96: =F95/(1+'Study Parameters'!$C$4) ^'Production Cost Baseline'!F$2 -> 64480103 | G96: =G95/(1+'Study Parameters'!$C$4) ^'Production Cost Baseline'!G$2 -> 59981491 | H96: =H95/(1+'Study Parameters'!$C$4) ^'Production Cost Baseline'!H$2 -> 55796736 | I96: =I95/(1+'Study Parameters'!$C$4) ^'Production Cost Baseline'!I$2 -> 51903940 | ... AA96: =AA95/(1+'Study Parameters'!$C$4) ^'Production Cost Baseline'!AA$2 -> 14120432
A97: Fuel Production (kg) | B97: 0 | C97: ='Study Parameters'!$C$15*'Study Parameters'!$C$8 * 10^3 -> 55200000 | D97: ='Study Parameters'!$C$15*'Study Parameters'!$C$8 * 10^3 -> 55200000 | E97: ='Study Parameters'!$C$15*'Study Parameters'!$C$8 * 10^3 -> 55200000 | F97: ='Study Parameters'!$C$15*'Study Parameters'!$C$8 * 10^3 -> 55200000 | G97: ='Study Parameters'!$C$15*'Study Parameters'!$C$8 * 10^3 -> 55200000 | H97: ='Study Parameters'!$C$15*'Study Parameters'!$C$8 * 10^3 -> 55200000 | I97: ='Study Parameters'!$C$15*'Study Parameters'!$C$8 * 10^3 -> 55200000 | J97: ='Study Parameters'!$C$15*'Study Parameters'!$C$8 * 10^3 -> 55200000 | ... AA97: ='Study Parameters'!$C$15*'Study Parameters'!$C$8 * 10^3 -> 55200000
A98: Discounted Fuel Production (kg) | B98: =B97/(1+'Study Parameters'!$C$4) ^'Production Cost Baseline'!B$2 -> 0 | C98: =C97/(1+'Study Parameters'!$C$4) ^'Production Cost Baseline'!C$2 -> 51348837 | D98: =D97/(1+'Study Parameters'!$C$4) ^'Production Cost Baseline'!D$2 -> 47766360 | E98: =E97/(1+'Study Parameters'!$C$4) ^'Production Cost Baseline'!E$2 -> 44433823 | F98: =F97/(1+'Study Parameters'!$C$4) ^'Production Cost Baseline'!F$2 -> 41333789 | G98: =G97/(1+'Study Parameters'!$C$4) ^'Production Cost Baseline'!G$2 -> 38450037 | H98: =H97/(1+'Study Parameters'!$C$4) ^'Production Cost Baseline'!H$2 -> 35767476 | I98: =I97/(1+'Study Parameters'!$C$4) ^'Production Cost Baseline'!I$2 -> 33272071 | ... AA98: =AA97/(1+'Study Parameters'!$C$4) ^'Production Cost Baseline'!AA$2 -> 9051644.1
A100: Production Cost of Fuel (€/kg) | B100: =SUM(B96:AA96) / SUM(C98:AA98) -> 2.1109258
A101: Production Cost of Fuel (€/l) | B101: =B100 * Inputs!$C$15 -> 1.6950734
A103: C.5 Baseload
A104: Cost (€) | B104: ='Cost Components'!$Q$43 * 10^6 -> 347000000 | C104: =('Cost Components'!$Q$44 + 'Cost Components'!$Q$42)*10^6 -> 2.3741587e+08 | D104: =('Cost Components'!$Q$44 + 'Cost Components'!$Q$42)*10^6 -> 2.3741587e+08 | E104: =('Cost Components'!$Q$44 + 'Cost Components'!$Q$42)*10^6 -> 2.3741587e+08 | F104: =('Cost Components'!$Q$44 + 'Cost Components'!$Q$42)*10^6 -> 2.3741587e+08 | G104: =('Cost Components'!$Q$44 + 'Cost Components'!$Q$42)*10^6 -> 2.3741587e+08 | H104: =('Cost Components'!$Q$44 + 'Cost Components'!$Q$42)*10^6 -> 2.3741587e+08 | I104: =('Cost Components'!$Q$44 + 'Cost Components'!$Q$42)*10^6 -> 2.3741587e+08 | J104: =('Cost Components'!$Q$44 + 'Cost Components'!$Q$42)*10^6 -> 2.3741587e+08 | ... AA104: =('Cost Components'!$Q$44 + 'Cost Components'!$Q$42)*10^6 -> 2.3741587e+08
A105: Revenue (€) | B105: 0 | C105: ='Cost Components'!$Q$36 * 10^6 -> 1.337e+08 | D105: ='Cost Components'!$Q$36 * 10^6 -> 1.337e+08 | E105: ='Cost Components'!$Q$36 * 10^6 -> 1.337e+08 | F105: ='Cost Components'!$Q$36 * 10^6 -> 1.337e+08 | G105: ='Cost Components'!$Q$36 * 10^6 -> 1.337e+08 | H105: ='Cost Components'!$Q$36 * 10^6 -> 1.337e+08 | I105: ='Cost Components'!$Q$36 * 10^6 -> 1.337e+08 | J105: ='Cost Components'!$Q$36 * 10^6 -> 1.337e+08 | ... AA105: ='Cost Components'!$Q$36 * 10^6 -> 1.337e+08
A106: Free Cash Flow (€) | B106: =B104-B105 -> 347000000 | C106: =C104-C105 -> 1.0371587e+08 | D106: =D104-D105 -> 1.0371587e+08 | E106: =E104-E105 -> 1.0371587e+08 | F106: =F104-F105 -> 1.0371587e+08 | G106: =G104-G105 -> 1.0371587e+08 | H106: =H104-H105 -> 1.0371587e+08 | I106: =I104-I105 -> 1.0371587e+08 | ... AA106: =AA104-AA105 -> 1.0371587e+08
A107: Discounted Cash Flow (€) | B107: =B106/(1+'Study Parameters'!$C$4) ^'Production Cost Baseline'!B$2 -> 347000000 | C107: =C106/(1+'Study Parameters'!$C$4) ^'Production Cost Baseline'!C$2 -> 96479878 | D107: =D106/(1+'Study Parameters'!$C$4) ^'Production Cost Baseline'!D$2 -> 89748723 | E107: =E106/(1+'Study Parameters'!$C$4) ^'Production Cost Baseline'!E$2 -> 83487185 | F107: =F106/(1+'Study Parameters'!$C$4) ^'Production Cost Baseline'!F$2 -> 77662497 | G107: =G106/(1+'Study Parameters'!$C$4) ^'Production Cost Baseline'!G$2 -> 72244184 | H107: =H106/(1+'Study Parameters'!$C$4) ^'Production Cost Baseline'!H$2 -> 67203892 | I107: =I106/(1+'Study Parameters'!$C$4) ^'Production Cost Baseline'!I$2 -> 62515248 | ... AA107: =AA106/(1+'Study Parameters'!$C$4) ^'Production Cost Baseline'!AA$2 -> 17007231
A108: Fuel Production (kg) | B108: 0 | C108: ='Study Parameters'!$C$16*'Study Parameters'!$C$8 * 10^3 -> 54400000 | D108: ='Study Parameters'!$C$16*'Study Parameters'!$C$8 * 10^3 -> 54400000 | E108: ='Study Parameters'!$C$16*'Study Parameters'!$C$8 * 10^3 -> 54400000 | F108: ='Study Parameters'!$C$16*'Study Parameters'!$C$8 * 10^3 -> 54400000 | G108: ='Study Parameters'!$C$16*'Study Parameters'!$C$8 * 10^3 -> 54400000 | H108: ='Study Parameters'!$C$16*'Study Parameters'!$C$8 * 10^3 -> 54400000 | I108: ='Study Parameters'!$C$16*'Study Parameters'!$C$8 * 10^3 -> 54400000 | J108: ='Study Parameters'!$C$16*'Study Parameters'!$C$8 * 10^3 -> 54400000 | ... AA108: ='Study Parameters'!$C$16*'Study Parameters'!$C$8 * 10^3 -> 54400000
A109: Discounted Fuel Production (kg) | B109: =B108/(1+'Study Parameters'!$C$4) ^'Production Cost Baseline'!B$2 -> 0 | C109: =C108/(1+'Study Parameters'!$C$4) ^'Production Cost Baseline'!C$2 -> 50604651 | D109: =D108/(1+'Study Parameters'!$C$4) ^'Production Cost Baseline'!D$2 -> 47074094 | E109: =E108/(1+'Study Parameters'!$C$4) ^'Production Cost Baseline'!E$2 -> 43789855 | F109: =F108/(1+'Study Parameters'!$C$4) ^'Production Cost Baseline'!F$2 -> 40734749 | G109: =G108/(1+'Study Parameters'!$C$4) ^'Production Cost Baseline'!G$2 -> 37892790 | H109: =H108/(1+'Study Parameters'!$C$4) ^'Production Cost Baseline'!H$2 -> 35249107 | I109: =I108/(1+'Study Parameters'!$C$4) ^'Production Cost Baseline'!I$2 -> 32789867 | ... AA109: =AA108/(1+'Study Parameters'!$C$4) ^'Production Cost Baseline'!AA$2 -> 8920460.9
A111: Production Cost of Fuel (€/kg) | B111: =SUM(B107:AA107) / SUM(C109:AA109) -> 2.4787771
A112: Production Cost of Fuel (€/l) | B112: =B111 * Inputs!$C$15 -> 1.990458

Sheet WACC Corrected Production Cost
A1: 2021
A2: Year | B2: 0 | C2: 1 | D2: 2 | E2: 3 | F2: 4 | G2: 5 | H2: 6 | I2: 7 | J2: 8 | K2: 9 | L2: 10 | M2: 11 | N2: 12 | O2: 13 | P2: 14 | Q2: 15 | R2: 16 | S2: 17 | T2: 18 | U2: 19 | V2: 20 | W2: 21 | X2: 22 | Y2: 23 | Z2: 24 | AA2: 25
A3: C.1 Baseload
A4: Cost (€) | B4: ='Cost Components'!$B$42 * 10^6 -> 1136760000 | C4: =('Cost Components'!$B$43 + 'Cost Components'!$B$40 + 'Cost Components'!$B$41) * 10^6 -> 5.5607486e+08 | D4: =('Cost Components'!$B$43 + 'Cost Components'!$B$40 + 'Cost Components'!$B$41) * 10^6 -> 5.5607486e+08 | E4: =('Cost Components'!$B$43 + 'Cost Components'!$B$40 + 'Cost Components'!$B$41) * 10^6 -> 5.5607486e+08 | F4: =('Cost Components'!$B$43 + 'Cost Components'!$B$40 + 'Cost Components'!$B$41) * 10^6 -> 5.5607486e+08 | G4: =('Cost Components'!$B$43 + 'Cost Components'!$B$40 + 'Cost Components'!$B$41) * 10^6 -> 5.5607486e+08 | H4: =('Cost Components'!$B$43 + 'Cost Components'!$B$40 + 'Cost Components'!$B$41) * 10^6 -> 5.5607486e+08 | I4: =('Cost Components'!$B$43 + 'Cost Components'!$B$40 + 'Cost Components'!$B$41) * 10^6 -> 5.5607486e+08 | J4: =('Cost Components'!$B$43 + 'Cost Components'!$B$40 + 'Cost Components'!$B$41) * 10^6 -> 5.5607486e+08 | ... AA4: =('Cost Components'!$B$43 + 'Cost Components'!$B$40 + 'Cost Components'!$B$41) * 10^6 -> 5.5607486e+08
A5: Revenue (€) | B5: 0 | C5: ='Cost Components'!$B$36*10^6 -> 56800000 | D5: ='Cost Components'!$B$36*10^6 -> 56800000 | E5: ='Cost Components'!$B$36*10^6 -> 56800000 | F5: ='Cost Components'!$B$36*10^6 -> 56800000 | G5: ='Cost Components'!$B$36*10^6 -> 56800000 | H5: ='Cost Components'!$B$36*10^6 -> 56800000 | I5: ='Cost Components'!$B$36*10^6 -> 56800000 | J5: ='Cost Components'!$B$36*10^6 -> 56800000 | ... AA5: ='Cost Components'!$B$36*10^6 -> 56800000
A6: Free Cash Flow (€) | B6: =B4-B5 -> 1136760000 | C6: =C4-C5 -> 4.9927486e+08 | D6: =D4-D5 -> 4.9927486e+08 | E6: =E4-E5 -> 4.9927486e+08 | F6: =F4-F5 -> 4.9927486e+08 | G6: =G4-G5 -> 4.9927486e+08 | H6: =H4-H5 -> 4.9927486e+08 | I6: =I4-I5 -> 4.9927486e+08 | ... AA6: =AA4-AA5 -> 4.9927486e+08
A7: Discounted Cash Flow (€) | B7: =B6/(1+Inputs!$C$5) ^'Production Cost Baseline'!B$2 -> 1136760000 | C7: =C6/(1+Inputs!$C$5) ^'Production Cost Baseline'!C$2 -> 4.6661201e+08 | D7: =D6/(1+Inputs!$C$5) ^'Production Cost Baseline'!D$2 -> 4.36086e+08 | E7: =E6/(1+Inputs!$C$5) ^'Production Cost Baseline'!E$2 -> 4.07557e+08 | F7: =F6/(1+Inputs!$C$5) ^'Production Cost Baseline'!F$2 -> 3.808944e+08 | G7: =G6/(1+Inputs!$C$5) ^'Production Cost Baseline'!G$2 -> 3.5597607e+08 | H7: =H6/(1+Inputs!$C$5) ^'Production Cost Baseline'!H$2 -> 3.3268792e+08 | I7: =I6/(1+Inputs!$C$5) ^'Production Cost Baseline'!I$2 -> 3.1092329e+08 | ... AA7: =AA6/(1+Inputs!$C$5) ^'Production Cost Baseline'!AA$2 -> 91990982
A8: Fuel Production (kg) | B8: 0 | C8: ='Study Parameters'!$C$12*'Study Parameters'!$C$8 * 10^3 -> 69600000 | D8: ='Study Parameters'!$C$12*'Study Parameters'!$C$8 * 10^3 -> 69600000 | E8: ='Study Parameters'!$C$12*'Study Parameters'!$C$8 * 10^3 -> 69600000 | F8: ='Study Parameters'!$C$12*'Study Parameters'!$C$8 * 10^3 -> 69600000 | G8: ='Study Parameters'!$C$12*'Study Parameters'!$C$8 * 10^3 -> 69600000 | H8: ='Study Parameters'!$C$12*'Study Parameters'!$C$8 * 10^3 -> 69600000 | I8: ='Study Parameters'!$C$12*'Study Parameters'!$C$8 * 10^3 -> 69600000 | J8: ='Study Parameters'!$C$12*'Study Parameters'!$C$8 * 10^3 -> 69600000 | ... AA8: ='Study Parameters'!$C$12*'Study Parameters'!$C$8 * 10^3 -> 69600000
A9: Discounted Fuel Production (kg) | B9: 0 | C9: =C8/(1+Inputs!$C$5) ^'Production Cost Baseline'!C$2 -> 65046729 | D9: =D8/(1+Inputs!$C$5) ^'Production Cost Baseline'!D$2 -> 60791335 | E9: =E8/(1+Inputs!$C$5) ^'Production Cost Baseline'!E$2 -> 56814332 | F9: =F8/(1+Inputs!$C$5) ^'Production Cost Baseline'!F$2 -> 53097507 | G9: =G8/(1+Inputs!$C$5) ^'Production Cost Baseline'!G$2 -> 49623838 | H9: =H8/(1+Inputs!$C$5) ^'Production Cost Baseline'!H$2 -> 46377419 | I9: =I8/(1+Inputs!$C$5) ^'Production Cost Baseline'!I$2 -> 43343382 | J9: =J8/(1+Inputs!$C$5) ^'Production Cost Baseline'!J$2 -> 40507834 | ... AA9: =AA8/(1+Inputs!$C$5) ^'Production Cost Baseline'!AA$2 -> 12823743
A11: Production Cost of Fuel (€/kg) | B11: =SUM(B7:AA7) / SUM(C9:AA9) -> 8.5750118
A12: Production Cost of Fuel (€/l) | B12: =B11 * Inputs!$C$15 -> 6.8857345
A14: C.2 Baseload
A15: Cost (€) | B15: ='Cost Components'!$C$42 * 10^6 -> 827300000 | C15: =('Cost Components'!$C$43 + 'Cost Components'!$C$40 + 'Cost Components'!$C$41) * 10^6 -> 4.8325164e+08 | D15: =('Cost Components'!$C$43 + 'Cost Components'!$C$40 + 'Cost Components'!$C$41) * 10^6 -> 4.8325164e+08 | E15: =('Cost Components'!$C$43 + 'Cost Components'!$C$40 + 'Cost Components'!$C$41) * 10^6 -> 4.8325164e+08 | F15: =('Cost Components'!$C$43 + 'Cost Components'!$C$40 + 'Cost Components'!$C$41) * 10^6 -> 4.8325164e+08 | G15: =('Cost Components'!$C$43 + 'Cost Components'!$C$40 + 'Cost Components'!$C$41) * 10^6 -> 4.8325164e+08 | H15: =('Cost Components'!$C$43 + 'Cost Components'!$C$40 + 'Cost Components'!$C$41) * 10^6 -> 4.8325164e+08 | I15: =('Cost Components'!$C$43 + 'Cost Components'!$C$40 + 'Cost Components'!$C$41) * 10^6 -> 4.8325164e+08 | J15: =('Cost Components'!$C$43 + 'Cost Components'!$C$40 + 'Cost Components'!$C$41) * 10^6 -> 4.8325164e+08 | ... AA15: =('Cost Components'!$C$43 + 'Cost Components'!$C$40 + 'Cost Components'!$C$41) * 10^6 -> 4.8325164e+08
A16: Revenue (€) | B16: 0 | C16: ='Cost Components'!$C$36*10^6 -> 1.499e+08 | D16: ='Cost Components'!$C$36*10^6 -> 1.499e+08 | E16: ='Cost Components'!$C$36*10^6 -> 1.499e+08 | F16: ='Cost Components'!$C$36*10^6 -> 1.499e+08 | G16: ='Cost Components'!$C$36*10^6 -> 1.499e+08 | H16: ='Cost Components'!$C$36*10^6 -> 1.499e+08 | I16: ='Cost Components'!$C$36*10^6 -> 1.499e+08 | J16: ='Cost Components'!$C$36*10^6 -> 1.499e+08 | ... AA16: ='Cost Components'!$C$36*10^6 -> 1.499e+08
A17: Free Cash Flow (€) | B17: =B15-B16 -> 827300000 | C17: =C15-C16 -> 3.3335164e+08 | D17: =D15-D16 -> 3.3335164e+08 | E17: =E15-E16 -> 3.3335164e+08 | F17: =F15-F16 -> 3.3335164e+08 | G17: =G15-G16 -> 3.3335164e+08 | H17: =H15-H16 -> 3.3335164e+08 | I17: =I15-I16 -> 3.3335164e+08 | ... AA17: =AA15-AA16 -> 3.3335164e+08
A18: Discounted Cash Flow (€) | B18: =B17/(1+Inputs!$C$5) ^'Production Cost Baseline'!B$2 -> 827300000 | C18: =C17/(1+Inputs!$C$5) ^'Production Cost Baseline'!C$2 -> 3.1154359e+08 | D18: =D17/(1+Inputs!$C$5) ^'Production Cost Baseline'!D$2 -> 2.9116223e+08 | E18: =E17/(1+Inputs!$C$5) ^'Production Cost Baseline'!E$2 -> 2.7211424e+08 | F18: =F17/(1+Inputs!$C$5) ^'Production Cost Baseline'!F$2 -> 2.5431237e+08 | G18: =G17/(1+Inputs!$C$5) ^'Production Cost Baseline'!G$2 -> 2.3767511e+08 | H18: =H17/(1+Inputs!$C$5) ^'Production Cost Baseline'!H$2 -> 2.2212627e+08 | I18: =I17/(1+Inputs!$C$5) ^'Production Cost Baseline'!I$2 -> 2.0759465e+08 | ... AA18: =AA17/(1+Inputs!$C$5) ^'Production Cost Baseline'!AA$2 -> 61419765
A19: Fuel Production (kg) | B19: 0 | C19: ='Study Parameters'!$C$13*'Study Parameters'!$C$8 * 10^3 -> 28000000 | D19: ='Study Parameters'!$C$13*'Study Parameters'!$C$8 * 10^3 -> 28000000 | E19: ='Study Parameters'!$C$13*'Study Parameters'!$C$8 * 10^3 -> 28000000 | F19: ='Study Parameters'!$C$13*'Study Parameters'!$C$8 * 10^3 -> 28000000 | G19: ='Study Parameters'!$C$13*'Study Parameters'!$C$8 * 10^3 -> 28000000 | H19: ='Study Parameters'!$C$13*'Study Parameters'!$C$8 * 10^3 -> 28000000 | I19: ='Study Parameters'!$C$13*'Study Parameters'!$C$8 * 10^3 -> 28000000 | J19: ='Study Parameters'!$C$13*'Study Parameters'!$C$8 * 10^3 -> 28000000 | ... AA19: ='Study Parameters'!$C$13*'Study Parameters'!$C$8 * 10^3 -> 28000000
A20: Discounted Fuel Production (kg) | B20: 0 | C20: =C19/(1+Inputs!$C$5) ^'Production Cost Baseline'!C$2 -> 26168224 | D20: =D19/(1+Inputs!$C$5) ^'Production Cost Baseline'!D$2 -> 24456284 | E20: =E19/(1+Inputs!$C$5) ^'Production Cost Baseline'!E$2 -> 22856341 | F20: =F19/(1+Inputs!$C$5) ^'Production Cost Baseline'!F$2 -> 21361066 | G20: =G19/(1+Inputs!$C$5) ^'Production Cost Baseline'!G$2 -> 19963613 | H20: =H19/(1+Inputs!$C$5) ^'Production Cost Baseline'!H$2 -> 18657582 | I20: =I19/(1+Inputs!$C$5) ^'Production Cost Baseline'!I$2 -> 17436993 | J20: =J19/(1+Inputs!$C$5) ^'Production Cost Baseline'!J$2 -> 16296255 | ... AA20: =AA19/(1+Inputs!$C$5) ^'Production Cost Baseline'!AA$2 -> 5158977
A22: Production Cost of Fuel (€/kg) | B22: =SUM(B18:AA18) / SUM(C20:AA20) -> 14.44081
A23: Production Cost of Fuel (€/l) | B23: =B22 * Inputs!$C$15 -> 11.59597
A25: C.3 Baseload
A26: Cost (€) | B26: ='Cost Components'!$D$42 * 10^6 -> 887030000 | C26: =('Cost Components'!$D$43 + 'Cost Components'!$D$40 + 'Cost Components'!$D$41) * 10^6 -> 5.4418008e+08 | D26: =('Cost Components'!$D$43 + 'Cost Components'!$D$40 + 'Cost Components'!$D$41) * 10^6 -> 5.4418008e+08 | E26: =('Cost Components'!$D$43 + 'Cost Components'!$D$40 + 'Cost Components'!$D$41) * 10^6 -> 5.4418008e+08 | F26: =('Cost Components'!$D$43 + 'Cost Components'!$D$40 + 'Cost Components'!$D$41) * 10^6 -> 5.4418008e+08 | G26: =('Cost Components'!$D$43 + 'Cost Components'!$D$40 + 'Cost Components'!$D$41) * 10^6 -> 5.4418008e+08 | H26: =('Cost Components'!$D$43 + 'Cost Components'!$D$40 + 'Cost Components'!$D$41) * 10^6 -> 5.4418008e+08 | I26: =('Cost Components'!$D$43 + 'Cost Components'!$D$40 + 'Cost Components'!$D$41) * 10^6 -> 5.4418008e+08 | J26: =('Cost Components'!$D$43 + 'Cost Components'!$D$40 + 'Cost Components'!$D$41) * 10^6 -> 5.4418008e+08 | ... AA26: =('Cost Components'!$D$43 + 'Cost Components'!$D$40 + 'Cost Components'!$D$41) * 10^6 -> 5.4418008e+08
A27: Revenue (€) | B27: 0 | C27: ='Cost Components'!$D$36*10^6 -> 81000000 | D27: ='Cost Components'!$D$36*10^6 -> 81000000 | E27: ='Cost Components'!$D$36*10^6 -> 81000000 | F27: ='Cost Components'!$D$36*10^6 -> 81000000 | G27: ='Cost Components'!$D$36*10^6 -> 81000000 | H27: ='Cost Components'!$D$36*10^6 -> 81000000 | I27: ='Cost Components'!$D$36*10^6 -> 81000000 | J27: ='Cost Components'!$D$36*10^6 -> 81000000 | ... AA27: ='Cost Components'!$D$36*10^6 -> 81000000
A28: Free Cash Flow (€) | B28: =B26-B27 -> 887030000 | C28: =C26-C27 -> 4.6318008e+08 | D28: =D26-D27 -> 4.6318008e+08 | E28: =E26-E27 -> 4.6318008e+08 | F28: =F26-F27 -> 4.6318008e+08 | G28: =G26-G27 -> 4.6318008e+08 | H28: =H26-H27 -> 4.6318008e+08 | I28: =I26-I27 -> 4.6318008e+08 | ... AA28: =AA26-AA27 -> 4.6318008e+08
A29: Discounted Cash Flow (€) | B29: =B28/(1+Inputs!$C$5) ^'Production Cost Baseline'!B$2 -> 887030000 | C29: =C28/(1+Inputs!$C$5) ^'Production Cost Baseline'!C$2 -> 4.3287858e+08 | D29: =D28/(1+Inputs!$C$5) ^'Production Cost Baseline'!D$2 -> 4.0455942e+08 | E29: =E28/(1+Inputs!$C$5) ^'Production Cost Baseline'!E$2 -> 3.7809291e+08 | F29: =F28/(1+Inputs!$C$5) ^'Production Cost Baseline'!F$2 -> 3.5335786e+08 | G29: =G28/(1+Inputs!$C$5) ^'Production Cost Baseline'!G$2 -> 3.3024099e+08 | H29: =H28/(1+Inputs!$C$5) ^'Production Cost Baseline'!H$2 -> 3.0863644e+08 | I29: =I28/(1+Inputs!$C$5) ^'Production Cost Baseline'!I$2 -> 2.8844527e+08 | ... AA29: =AA28/(1+Inputs!$C$5) ^'Production Cost Baseline'!AA$2 -> 85340549
A30: Fuel Production (kg) | B30: 0 | C30: ='Study Parameters'!$C$14*'Study Parameters'!$C$8 * 10^3 -> 38400000 | D30: ='Study Parameters'!$C$14*'Study Parameters'!$C$8 * 10^3 -> 38400000 | E30: ='Study Parameters'!$C$14*'Study Parameters'!$C$8 * 10^3 -> 38400000 | F30: ='Study Parameters'!$C$14*'Study Parameters'!$C$8 * 10^3 -> 38400000 | G30: ='Study Parameters'!$C$14*'Study Parameters'!$C$8 * 10^3 -> 38400000 | H30: ='Study Parameters'!$C$14*'Study Parameters'!$C$8 * 10^3 -> 38400000 | I30: ='Study Parameters'!$C$14*'Study Parameters'!$C$8 * 10^3 -> 38400000 | J30: ='Study Parameters'!$C$14*'Study Parameters'!$C$8 * 10^3 -> 38400000 | ... AA30: ='Study Parameters'!$C$14*'Study Parameters'!$C$8 * 10^3 -> 38400000
A31: Discounted Fuel Production (kg) | B31: 0 | C31: =C30/(1+Inputs!$C$5) ^'Production Cost Baseline'!C$2 -> 35887850 | D31: =D30/(1+Inputs!$C$5) ^'Production Cost Baseline'!D$2 -> 33540047 | E31: =E30/(1+Inputs!$C$5) ^'Production Cost Baseline'!E$2 -> 31345838 | F31: =F30/(1+Inputs!$C$5) ^'Production Cost Baseline'!F$2 -> 29295176 | G31: =G30/(1+Inputs!$C$5) ^'Production Cost Baseline'!G$2 -> 27378669 | H31: =H30/(1+Inputs!$C$5) ^'Production Cost Baseline'!H$2 -> 25587541 | I31: =I30/(1+Inputs!$C$5) ^'Production Cost Baseline'!I$2 -> 23913590 | J31: =J30/(1+Inputs!$C$5) ^'Production Cost Baseline'!J$2 -> 22349150 | ... AA31: =AA30/(1+Inputs!$C$5) ^'Production Cost Baseline'!AA$2 -> 7075168.4
A33: Production Cost of Fuel (€/kg) | B33: =SUM(B29:AA29) / SUM(C31:AA31) -> 14.044182
A34: Production Cost of Fuel (€/l) | B34: =B33 * Inputs!$C$15 -> 11.277478
A36: C.4 Baseload
A37: Cost (€) | B37: ='Cost Components'!$E$42 * 10^6 -> 8.4492e+08 | C37: =('Cost Components'!$E$43 + 'Cost Components'!$E$40 + 'Cost Components'!$E$41) * 10^6 -> 4.8847818e+08 | D37: =('Cost Components'!$E$43 + 'Cost Components'!$E$40 + 'Cost Components'!$E$41) * 10^6 -> 4.8847818e+08 | E37: =('Cost Components'!$E$43 + 'Cost Components'!$E$40 + 'Cost Components'!$E$41) * 10^6 -> 4.8847818e+08 | F37: =('Cost Components'!$E$43 + 'Cost Components'!$E$40 + 'Cost Components'!$E$41) * 10^6 -> 4.8847818e+08 | G37: =('Cost Components'!$E$43 + 'Cost Components'!$E$40 + 'Cost Components'!$E$41) * 10^6 -> 4.8847818e+08 | H37: =('Cost Components'!$E$43 + 'Cost Components'!$E$40 + 'Cost Components'!$E$41) * 10^6 -> 4.8847818e+08 | I37: =('Cost Components'!$E$43 + 'Cost Components'!$E$40 + 'Cost Components'!$E$41) * 10^6 -> 4.8847818e+08 | J37: =('Cost Components'!$E$43 + 'Cost Components'!$E$40 + 'Cost Components'!$E$41) * 10^6 -> 4.8847818e+08 | ... AA37: =('Cost Components'!$E$43 + 'Cost Components'!$E$40 + 'Cost Components'!$E$41) * 10^6 -> 4.8847818e+08
A38: Revenue (€) | B38: 0 | C38: ='Cost Components'!$E$36*10^6 -> 103200000 | D38: ='Cost Components'!$E$36*10^6 -> 103200000 | E38: ='Cost Components'!$E$36*10^6 -> 103200000 | F38: ='Cost Components'!$E$36*10^6 -> 103200000 | G38: ='Cost Components'!$E$36*10^6 -> 103200000 | H38: ='Cost Components'!$E$36*10^6 -> 103200000 | I38: ='Cost Components'!$E$36*10^6 -> 103200000 | J38: ='Cost Components'!$E$36*10^6 -> 103200000 | ... AA38: ='Cost Components'!$E$36*10^6 -> 103200000
A39: Free Cash Flow (€) | B39: =B37-B38 -> 8.4492e+08 | C39: =C37-C38 -> 3.8527818e+08 | D39: =D37-D38 -> 3.8527818e+08 | E39: =E37-E38 -> 3.8527818e+08 | F39: =F37-F38 -> 3.8527818e+08 | G39: =G37-G38 -> 3.8527818e+08 | H39: =H37-H38 -> 3.8527818e+08 | I39: =I37-I38 -> 3.8527818e+08 | ... AA39: =AA37-AA38 -> 3.8527818e+08
A40: Discounted Cash Flow (€) | B40: =B39/(1+Inputs!$C$5) ^'Production Cost Baseline'!B$2 -> 8.4492e+08 | C40: =C39/(1+Inputs!$C$5) ^'Production Cost Baseline'!C$2 -> 3.6007307e+08 | D40: =D39/(1+Inputs!$C$5) ^'Production Cost Baseline'!D$2 -> 3.3651688e+08 | E40: =E39/(1+Inputs!$C$5) ^'Production Cost Baseline'!E$2 -> 3.1450176e+08 | F40: =F39/(1+Inputs!$C$5) ^'Production Cost Baseline'!F$2 -> 2.9392688e+08 | G40: =G39/(1+Inputs!$C$5) ^'Production Cost Baseline'!G$2 -> 2.7469802e+08 | H40: =H39/(1+Inputs!$C$5) ^'Production Cost Baseline'!H$2 -> 2.5672712e+08 | I40: =I39/(1+Inputs!$C$5) ^'Production Cost Baseline'!I$2 -> 2.3993189e+08 | ... AA40: =AA39/(1+Inputs!$C$5) ^'Production Cost Baseline'!AA$2 -> 70987188
A41: Fuel Production (kg) | B41: 0 | C41: ='Study Parameters'!$C$15*'Study Parameters'!$C$8 * 10^3 -> 55200000 | D41: ='Study Parameters'!$C$15*'Study Parameters'!$C$8 * 10^3 -> 55200000 | E41: ='Study Parameters'!$C$15*'Study Parameters'!$C$8 * 10^3 -> 55200000 | F41: ='Study Parameters'!$C$15*'Study Parameters'!$C$8 * 10^3 -> 55200000 | G41: ='Study Parameters'!$C$15*'Study Parameters'!$C$8 * 10^3 -> 55200000 | H41: ='Study Parameters'!$C$15*'Study Parameters'!$C$8 * 10^3 -> 55200000 | I41: ='Study Parameters'!$C$15*'Study Parameters'!$C$8 * 10^3 -> 55200000 | J41: ='Study Parameters'!$C$15*'Study Parameters'!$C$8 * 10^3 -> 55200000 | ... AA41: ='Study Parameters'!$C$15*'Study Parameters'!$C$8 * 10^3 -> 55200000
A42: Discounted Fuel Production (kg) | B42: 0 | C42: =C41/(1+Inputs!$C$5) ^'Production Cost Baseline'!C$2 -> 51588785 | D42: =D41/(1+Inputs!$C$5) ^'Production Cost Baseline'!D$2 -> 48213818 | E42: =E41/(1+Inputs!$C$5) ^'Production Cost Baseline'!E$2 -> 45059643 | F42: =F41/(1+Inputs!$C$5) ^'Production Cost Baseline'!F$2 -> 42111816 | G42: =G41/(1+Inputs!$C$5) ^'Production Cost Baseline'!G$2 -> 39356837 | H42: =H41/(1+Inputs!$C$5) ^'Production Cost Baseline'!H$2 -> 36782091 | I42: =I41/(1+Inputs!$C$5) ^'Production Cost Baseline'!I$2 -> 34375786 | J42: =J41/(1+Inputs!$C$5) ^'Production Cost Baseline'!J$2 -> 32126903 | ... AA42: =AA41/(1+Inputs!$C$5) ^'Production Cost Baseline'!AA$2 -> 10170555
A44: Production Cost of Fuel (€/kg) | B44: =SUM(B40:AA40) / SUM(C42:AA42) -> 8.2931377
A45: Production Cost of Fuel (€/l) | B45: =B44 * Inputs!$C$15 -> 6.6593896
A47: C.5 Baseload
A48: Cost (€) | B48: ='Cost Components'!$F$42 * 10^6 -> 9.4766e+08 | C48: =('Cost Components'!$F$43 + 'Cost Components'!$F$40 + 'Cost Components'!$F$41) * 10^6 -> 5.2917814e+08 | D48: =('Cost Components'!$F$43 + 'Cost Components'!$F$40 + 'Cost Components'!$F$41) * 10^6 -> 5.2917814e+08 | E48: =('Cost Components'!$F$43 + 'Cost Components'!$F$40 + 'Cost Components'!$F$41) * 10^6 -> 5.2917814e+08 | F48: =('Cost Components'!$F$43 + 'Cost Components'!$F$40 + 'Cost Components'!$F$41) * 10^6 -> 5.2917814e+08 | G48: =('Cost Components'!$F$43 + 'Cost Components'!$F$40 + 'Cost Components'!$F$41) * 10^6 -> 5.2917814e+08 | H48: =('Cost Components'!$F$43 + 'Cost Components'!$F$40 + 'Cost Components'!$F$41) * 10^6 -> 5.2917814e+08 | I48: =('Cost Components'!$F$43 + 'Cost Components'!$F$40 + 'Cost Components'!$F$41) * 10^6 -> 5.2917814e+08 | J48: =('Cost Components'!$F$43 + 'Cost Components'!$F$40 + 'Cost Components'!$F$41) * 10^6 -> 5.2917814e+08 | ... AA48: =('Cost Components'!$F$43 + 'Cost Components'!$F$40 + 'Cost Components'!$F$41) * 10^6 -> 5.2917814e+08
A49: Revenue (€) | B49: 0 | C49: ='Cost Components'!$F$36*10^6 -> 135200000 | D49: ='Cost Components'!$F$36*10^6 -> 135200000 | E49: ='Cost Components'!$F$36*10^6 -> 135200000 | F49: ='Cost Components'!$F$36*10^6 -> 135200000 | G49: ='Cost Components'!$F$36*10^6 -> 135200000 | H49: ='Cost Components'!$F$36*10^6 -> 135200000 | I49: ='Cost Components'!$F$36*10^6 -> 135200000 | J49: ='Cost Components'!$F$36*10^6 -> 135200000 | ... AA49: ='Cost Components'!$F$36*10^6 -> 135200000
A50: Free Cash Flow (€) | B50: =B48-B49 -> 9.4766e+08 | C50: =C48-C49 -> 3.9397814e+08 | D50: =D48-D49 -> 3.9397814e+08 | E50: =E48-E49 -> 3.9397814e+08 | F50: =F48-F49 -> 3.9397814e+08 | G50: =G48-G49 -> 3.9397814e+08 | H50: =H48-H49 -> 3.9397814e+08 | I50: =I48-I49 -> 3.9397814e+08 | ... AA50: =AA48-AA49 -> 3.9397814e+08
A51: Discounted Cash Flow (€) | B51: =B50/(1+Inputs!$C$5) ^'Production Cost Baseline'!B$2 -> 9.4766e+08 | C51: =C50/(1+Inputs!$C$5) ^'Production Cost Baseline'!C$2 -> 3.6820387e+08 | D51: =D50/(1+Inputs!$C$5) ^'Production Cost Baseline'!D$2 -> 3.4411577e+08 | E51: =E50/(1+Inputs!$C$5) ^'Production Cost Baseline'!E$2 -> 3.2160352e+08 | F51: =F50/(1+Inputs!$C$5) ^'Production Cost Baseline'!F$2 -> 3.0056404e+08 | G51: =G50/(1+Inputs!$C$5) ^'Production Cost Baseline'!G$2 -> 2.8090097e+08 | H51: =H50/(1+Inputs!$C$5) ^'Production Cost Baseline'!H$2 -> 2.6252427e+08 | I51: =I50/(1+Inputs!$C$5) ^'Production Cost Baseline'!I$2 -> 2.4534979e+08 | ... AA51: =AA50/(1+Inputs!$C$5) ^'Production Cost Baseline'!AA$2 -> 72590149
A52: Fuel Production (kg) | B52: 0 | C52: ='Study Parameters'!$C$16*'Study Parameters'!$C$8 * 10^3 -> 54400000 | D52: ='Study Parameters'!$C$16*'Study Parameters'!$C$8 * 10^3 -> 54400000 | E52: ='Study Parameters'!$C$16*'Study Parameters'!$C$8 * 10^3 -> 54400000 | F52: ='Study Parameters'!$C$16*'Study Parameters'!$C$8 * 10^3 -> 54400000 | G52: ='Study Parameters'!$C$16*'Study Parameters'!$C$8 * 10^3 -> 54400000 | H52: ='Study Parameters'!$C$16*'Study Parameters'!$C$8 * 10^3 -> 54400000 | I52: ='Study Parameters'!$C$16*'Study Parameters'!$C$8 * 10^3 -> 54400000 | J52: ='Study Parameters'!$C$16*'Study Parameters'!$C$8 * 10^3 -> 54400000 | ... AA52: ='Study Parameters'!$C$16*'Study Parameters'!$C$8 * 10^3 -> 54400000
A53: Discounted Fuel Production (kg) | B53: 0 | C53: =C52/(1+Inputs!$C$5) ^'Production Cost Baseline'!C$2 -> 50841121 | D53: =D52/(1+Inputs!$C$5) ^'Production Cost Baseline'!D$2 -> 47515067 | E53: =E52/(1+Inputs!$C$5) ^'Production Cost Baseline'!E$2 -> 44406605 | F53: =F52/(1+Inputs!$C$5) ^'Production Cost Baseline'!F$2 -> 41501500 | G53: =G52/(1+Inputs!$C$5) ^'Production Cost Baseline'!G$2 -> 38786448 | H53: =H52/(1+Inputs!$C$5) ^'Production Cost Baseline'!H$2 -> 36249017 | I53: =I52/(1+Inputs!$C$5) ^'Production Cost Baseline'!I$2 -> 33877586 | J53: =J52/(1+Inputs!$C$5) ^'Production Cost Baseline'!J$2 -> 31661295 | ... AA53: =AA52/(1+Inputs!$C$5) ^'Production Cost Baseline'!AA$2 -> 10023155
A55: Production Cost of Fuel (€/kg) | B55: =SUM(B51:AA51) / SUM(C53:AA53) -> 8.7370834
A56: Production Cost of Fuel (€/l) | B56: =B55 * Inputs!$C$15 -> 7.015878
A58: 2050
A59: C.1 Baseload
A60: Cost (€) | B60: ='Cost Components'!$M$43 * 10^6 -> 428200000 | C60: =('Cost Components'!$M$44 + 'Cost Components'!$M$42)*10^6 -> 2.6870175e+08 | D60: =('Cost Components'!$M$44 + 'Cost Components'!$M$42)*10^6 -> 2.6870175e+08 | E60: =('Cost Components'!$M$44 + 'Cost Components'!$M$42)*10^6 -> 2.6870175e+08 | F60: =('Cost Components'!$M$44 + 'Cost Components'!$M$42)*10^6 -> 2.6870175e+08 | G60: =('Cost Components'!$M$44 + 'Cost Components'!$M$42)*10^6 -> 2.6870175e+08 | H60: =('Cost Components'!$M$44 + 'Cost Components'!$M$42)*10^6 -> 2.6870175e+08 | I60: =('Cost Components'!$M$44 + 'Cost Components'!$M$42)*10^6 -> 2.6870175e+08 | J60: =('Cost Components'!$M$44 + 'Cost Components'!$M$42)*10^6 -> 2.6870175e+08 | ... AA60: =('Cost Components'!$M$44 + 'Cost Components'!$M$42)*10^6 -> 2.6870175e+08
A61: Revenue (€) | B61: 0 | C61: ='Cost Components'!$M$36 * 10^6 -> 149900000 | D61: ='Cost Components'!$M$36 * 10^6 -> 149900000 | E61: ='Cost Components'!$M$36 * 10^6 -> 149900000 | F61: ='Cost Components'!$M$36 * 10^6 -> 149900000 | G61: ='Cost Components'!$M$36 * 10^6 -> 149900000 | H61: ='Cost Components'!$M$36 * 10^6 -> 149900000 | I61: ='Cost Components'!$M$36 * 10^6 -> 149900000 | J61: ='Cost Components'!$M$36 * 10^6 -> 149900000 | ... AA61: ='Cost Components'!$M$36 * 10^6 -> 149900000
A62: Free Cash Flow (€) | B62: =B60-B61 -> 428200000 | C62: =C60-C61 -> 1.1880175e+08 | D62: =D60-D61 -> 1.1880175e+08 | E62: =E60-E61 -> 1.1880175e+08 | F62: =F60-F61 -> 1.1880175e+08 | G62: =G60-G61 -> 1.1880175e+08 | H62: =H60-H61 -> 1.1880175e+08 | I62: =I60-I61 -> 1.1880175e+08 | ... AA62: =AA60-AA61 -> 1.1880175e+08
A63: Discounted Cash Flow (€) | B63: =B62/(1+Inputs!$C$5) ^'Production Cost Baseline'!B$2 -> 428200000 | C63: =C62/(1+Inputs!$C$5) ^'Production Cost Baseline'!C$2 -> 1.1102967e+08 | D63: =D62/(1+Inputs!$C$5) ^'Production Cost Baseline'!D$2 -> 1.0376605e+08 | E63: =E62/(1+Inputs!$C$5) ^'Production Cost Baseline'!E$2 -> 96977614 | F63: =F62/(1+Inputs!$C$5) ^'Production Cost Baseline'!F$2 -> 90633284 | G63: =G62/(1+Inputs!$C$5) ^'Production Cost Baseline'!G$2 -> 84704004 | H63: =H62/(1+Inputs!$C$5) ^'Production Cost Baseline'!H$2 -> 79162621 | I63: =I62/(1+Inputs!$C$5) ^'Production Cost Baseline'!I$2 -> 73983758 | ... AA63: =AA62/(1+Inputs!$C$5) ^'Production Cost Baseline'!AA$2 -> 21889124
A64: Fuel Production (kg) | B64: 0 | C64: ='Study Parameters'!$C$12*'Study Parameters'!$C$8 * 10^3 -> 69600000 | D64: ='Study Parameters'!$C$12*'Study Parameters'!$C$8 * 10^3 -> 69600000 | E64: ='Study Parameters'!$C$12*'Study Parameters'!$C$8 * 10^3 -> 69600000 | F64: ='Study Parameters'!$C$12*'Study Parameters'!$C$8 * 10^3 -> 69600000 | G64: ='Study Parameters'!$C$12*'Study Parameters'!$C$8 * 10^3 -> 69600000 | H64: ='Study Parameters'!$C$12*'Study Parameters'!$C$8 * 10^3 -> 69600000 | I64: ='Study Parameters'!$C$12*'Study Parameters'!$C$8 * 10^3 -> 69600000 | J64: ='Study Parameters'!$C$12*'Study Parameters'!$C$8 * 10^3 -> 69600000 | ... AA64: ='Study Parameters'!$C$12*'Study Parameters'!$C$8 * 10^3 -> 69600000
A65: Discounted Fuel Production (kg) | B65: =B64/(1+Inputs!$C$5) ^'Production Cost Baseline'!B$2 -> 0 | C65: =C64/(1+Inputs!$C$5) ^'Production Cost Baseline'!C$2 -> 65046729 | D65: =D64/(1+Inputs!$C$5) ^'Production Cost Baseline'!D$2 -> 60791335 | E65: =E64/(1+Inputs!$C$5) ^'Production Cost Baseline'!E$2 -> 56814332 | F65: =F64/(1+Inputs!$C$5) ^'Production Cost Baseline'!F$2 -> 53097507 | G65: =G64/(1+Inputs!$C$5) ^'Production Cost Baseline'!G$2 -> 49623838 | H65: =H64/(1+Inputs!$C$5) ^'Production Cost Baseline'!H$2 -> 46377419 | I65: =I64/(1+Inputs!$C$5) ^'Production Cost Baseline'!I$2 -> 43343382 | ... AA65: =AA64/(1+Inputs!$C$5) ^'Production Cost Baseline'!AA$2 -> 12823743
A67: Production Cost of Fuel (€/kg) | B67: =SUM(B63:AA63) / SUM(C65:AA65) -> 2.2348536
A68: Production Cost of Fuel (€/l) | B68: =B67 * Inputs!$C$15 -> 1.7945874
A70: C.2 Baseload
A71: Cost (€) | B71: ='Cost Components'!$N$43 * 10^6 -> 309400000 | C71: =('Cost Components'!$N$44 + 'Cost Components'!$N$42)*10^6 -> 2.3291963e+08 | D71: =('Cost Components'!$N$44 + 'Cost Components'!$N$42)*10^6 -> 2.3291963e+08 | E71: =('Cost Components'!$N$44 + 'Cost Components'!$N$42)*10^6 -> 2.3291963e+08 | F71: =('Cost Components'!$N$44 + 'Cost Components'!$N$42)*10^6 -> 2.3291963e+08 | G71: =('Cost Components'!$N$44 + 'Cost Components'!$N$42)*10^6 -> 2.3291963e+08 | H71: =('Cost Components'!$N$44 + 'Cost Components'!$N$42)*10^6 -> 2.3291963e+08 | I71: =('Cost Components'!$N$44 + 'Cost Components'!$N$42)*10^6 -> 2.3291963e+08 | J71: =('Cost Components'!$N$44 + 'Cost Components'!$N$42)*10^6 -> 2.3291963e+08 | ... AA71: =('Cost Components'!$N$44 + 'Cost Components'!$N$42)*10^6 -> 2.3291963e+08
A72: Revenue (€) | B72: 0 | C72: ='Cost Components'!$N$36 * 10^6 -> 81000000 | D72: ='Cost Components'!$N$36 * 10^6 -> 81000000 | E72: ='Cost Components'!$N$36 * 10^6 -> 81000000 | F72: ='Cost Components'!$N$36 * 10^6 -> 81000000 | G72: ='Cost Components'!$N$36 * 10^6 -> 81000000 | H72: ='Cost Components'!$N$36 * 10^6 -> 81000000 | I72: ='Cost Components'!$N$36 * 10^6 -> 81000000 | J72: ='Cost Components'!$N$36 * 10^6 -> 81000000 | ... AA72: ='Cost Components'!$N$36 * 10^6 -> 81000000
A73: Free Cash Flow (€) | B73: =B71-B72 -> 309400000 | C73: =C71-C72 -> 1.5191963e+08 | D73: =D71-D72 -> 1.5191963e+08 | E73: =E71-E72 -> 1.5191963e+08 | F73: =F71-F72 -> 1.5191963e+08 | G73: =G71-G72 -> 1.5191963e+08 | H73: =H71-H72 -> 1.5191963e+08 | I73: =I71-I72 -> 1.5191963e+08 | ... AA73: =AA71-AA72 -> 1.5191963e+08
A74: Discounted Cash Flow (€) | B74: =B73/(1+Inputs!$C$5) ^'Production Cost Baseline'!B$2 -> 309400000 | C74: =C73/(1+Inputs!$C$5) ^'Production Cost Baseline'!C$2 -> 1.4198096e+08 | D74: =D73/(1+Inputs!$C$5) ^'Production Cost Baseline'!D$2 -> 1.3269249e+08 | E74: =E73/(1+Inputs!$C$5) ^'Production Cost Baseline'!E$2 -> 1.2401167e+08 | F74: =F73/(1+Inputs!$C$5) ^'Production Cost Baseline'!F$2 -> 1.1589876e+08 | G74: =G73/(1+Inputs!$C$5) ^'Production Cost Baseline'!G$2 -> 1.083166e+08 | H74: =H73/(1+Inputs!$C$5) ^'Production Cost Baseline'!H$2 -> 1.0123047e+08 | I74: =I73/(1+Inputs!$C$5) ^'Production Cost Baseline'!I$2 -> 94607912 | ... AA74: =AA73/(1+Inputs!$C$5) ^'Production Cost Baseline'!AA$2 -> 27991067
A75: Fuel Production (kg) | B75: 0 | C75: ='Study Parameters'!$C$13*'Study Parameters'!$C$8 * 10^3 -> 28000000 | D75: ='Study Parameters'!$C$13*'Study Parameters'!$C$8 * 10^3 -> 28000000 | E75: ='Study Parameters'!$C$13*'Study Parameters'!$C$8 * 10^3 -> 28000000 | F75: ='Study Parameters'!$C$13*'Study Parameters'!$C$8 * 10^3 -> 28000000 | G75: ='Study Parameters'!$C$13*'Study Parameters'!$C$8 * 10^3 -> 28000000 | H75: ='Study Parameters'!$C$13*'Study Parameters'!$C$8 * 10^3 -> 28000000 | I75: ='Study Parameters'!$C$13*'Study Parameters'!$C$8 * 10^3 -> 28000000 | J75: ='Study Parameters'!$C$13*'Study Parameters'!$C$8 * 10^3 -> 28000000 | ... AA75: ='Study Parameters'!$C$13*'Study Parameters'!$C$8 * 10^3 -> 28000000
A76: Discounted Fuel Production (kg) | B76: =B75/(1+Inputs!$C$5) ^'Production Cost Baseline'!B$2 -> 0 | C76: =C75/(1+Inputs!$C$5) ^'Production Cost Baseline'!C$2 -> 26168224 | D76: =D75/(1+Inputs!$C$5) ^'Production Cost Baseline'!D$2 -> 24456284 | E76: =E75/(1+Inputs!$C$5) ^'Production Cost Baseline'!E$2 -> 22856341 | F76: =F75/(1+Inputs!$C$5) ^'Production Cost Baseline'!F$2 -> 21361066 | G76: =G75/(1+Inputs!$C$5) ^'Production Cost Baseline'!G$2 -> 19963613 | H76: =H75/(1+Inputs!$C$5) ^'Production Cost Baseline'!H$2 -> 18657582 | I76: =I75/(1+Inputs!$C$5) ^'Production Cost Baseline'!I$2 -> 17436993 | ... AA76: =AA75/(1+Inputs!$C$5) ^'Production Cost Baseline'!AA$2 -> 5158977
A78: Production Cost of Fuel (€/kg) | B78: =SUM(B74:AA74) / SUM(C76:AA76) -> 6.3739074
A79: Production Cost of Fuel (€/l) | B79: =B78 * Inputs!$C$15 -> 5.1182476
A81: C.3 Baseload
A82: Cost (€) | B82: ='Cost Components'!$O$43 * 10^6 -> 321600000 | C82: =('Cost Components'!$O$44 + 'Cost Components'!$O$42)*10^6 -> 2.4567608e+08 | D82: =('Cost Components'!$O$44 + 'Cost Components'!$O$42)*10^6 -> 2.4567608e+08 | E82: =('Cost Components'!$O$44 + 'Cost Components'!$O$42)*10^6 -> 2.4567608e+08 | F82: =('Cost Components'!$O$44 + 'Cost Components'!$O$42)*10^6 -> 2.4567608e+08 | G82: =('Cost Components'!$O$44 + 'Cost Components'!$O$42)*10^6 -> 2.4567608e+08 | H82: =('Cost Components'!$O$44 + 'Cost Components'!$O$42)*10^6 -> 2.4567608e+08 | I82: =('Cost Components'!$O$44 + 'Cost Components'!$O$42)*10^6 -> 2.4567608e+08 | J82: =('Cost Components'!$O$44 + 'Cost Components'!$O$42)*10^6 -> 2.4567608e+08 | ... AA82: =('Cost Components'!$O$44 + 'Cost Components'!$O$42)*10^6 -> 2.4567608e+08
A83: Revenue (€) | B83: 0 | C83: ='Cost Components'!$O$36 * 10^6 -> 103200000 | D83: ='Cost Components'!$O$36 * 10^6 -> 103200000 | E83: ='Cost Components'!$O$36 * 10^6 -> 103200000 | F83: ='Cost Components'!$O$36 * 10^6 -> 103200000 | G83: ='Cost Components'!$O$36 * 10^6 -> 103200000 | H83: ='Cost Components'!$O$36 * 10^6 -> 103200000 | I83: ='Cost Components'!$O$36 * 10^6 -> 103200000 | J83: ='Cost Components'!$O$36 * 10^6 -> 103200000 | ... AA83: ='Cost Components'!$O$36 * 10^6 -> 103200000
A84: Free Cash Flow (€) | B84: =B82-B83 -> 321600000 | C84: =C82-C83 -> 1.4247608e+08 | D84: =D82-D83 -> 1.4247608e+08 | E84: =E82-E83 -> 1.4247608e+08 | F84: =F82-F83 -> 1.4247608e+08 | G84: =G82-G83 -> 1.4247608e+08 | H84: =H82-H83 -> 1.4247608e+08 | I84: =I82-I83 -> 1.4247608e+08 | ... AA84: =AA82-AA83 -> 1.4247608e+08
A85: Discounted Cash Flow (€) | B85: =B84/(1+Inputs!$C$5) ^'Production Cost Baseline'!B$2 -> 321600000 | C85: =C84/(1+Inputs!$C$5) ^'Production Cost Baseline'!C$2 -> 1.3315522e+08 | D85: =D84/(1+Inputs!$C$5) ^'Production Cost Baseline'!D$2 -> 1.2444413e+08 | E85: =E84/(1+Inputs!$C$5) ^'Production Cost Baseline'!E$2 -> 1.1630292e+08 | F85: =F84/(1+Inputs!$C$5) ^'Production Cost Baseline'!F$2 -> 1.0869432e+08 | G85: =G84/(1+Inputs!$C$5) ^'Production Cost Baseline'!G$2 -> 1.0158348e+08 | H85: =H84/(1+Inputs!$C$5) ^'Production Cost Baseline'!H$2 -> 94937830 | I85: =I84/(1+Inputs!$C$5) ^'Production Cost Baseline'!I$2 -> 88726944 | ... AA85: =AA84/(1+Inputs!$C$5) ^'Production Cost Baseline'!AA$2 -> 26251101
A86: Fuel Production (kg) | B86: 0 | C86: ='Study Parameters'!$C$14*'Study Parameters'!$C$8 * 10^3 -> 38400000 | D86: ='Study Parameters'!$C$14*'Study Parameters'!$C$8 * 10^3 -> 38400000 | E86: ='Study Parameters'!$C$14*'Study Parameters'!$C$8 * 10^3 -> 38400000 | F86: ='Study Parameters'!$C$14*'Study Parameters'!$C$8 * 10^3 -> 38400000 | G86: ='Study Parameters'!$C$14*'Study Parameters'!$C$8 * 10^3 -> 38400000 | H86: ='Study Parameters'!$C$14*'Study Parameters'!$C$8 * 10^3 -> 38400000 | I86: ='Study Parameters'!$C$14*'Study Parameters'!$C$8 * 10^3 -> 38400000 | J86: ='Study Parameters'!$C$14*'Study Parameters'!$C$8 * 10^3 -> 38400000 | ... AA86: ='Study Parameters'!$C$14*'Study Parameters'!$C$8 * 10^3 -> 38400000
A87: Discounted Fuel Production (kg) | B87: =B86/(1+Inputs!$C$5) ^'Production Cost Baseline'!B$2 -> 0 | C87: =C86/(1+Inputs!$C$5) ^'Production Cost Baseline'!C$2 -> 35887850 | D87: =D86/(1+Inputs!$C$5) ^'Production Cost Baseline'!D$2 -> 33540047 | E87: =E86/(1+Inputs!$C$5) ^'Production Cost Baseline'!E$2 -> 31345838 | F87: =F86/(1+Inputs!$C$5) ^'Production Cost Baseline'!F$2 -> 29295176 | G87: =G86/(1+Inputs!$C$5) ^'Production Cost Baseline'!G$2 -> 27378669 | H87: =H86/(1+Inputs!$C$5) ^'Production Cost Baseline'!H$2 -> 25587541 | I87: =I86/(1+Inputs!$C$5) ^'Production Cost Baseline'!I$2 -> 23913590 | ... AA87: =AA86/(1+Inputs!$C$5) ^'Production Cost Baseline'!AA$2 -> 7075168.4
A89: Production Cost of Fuel (€/kg) | B89: =SUM(B85:AA85) / SUM(C87:AA87) -> 4.4289777
A90: Production Cost of Fuel (€/l) | B90: =B89 * Inputs!$C$15 -> 3.5564691
A92: C.4 Baseload
A93: Cost (€) | B93: ='Cost Components'!$P$43 * 10^6 -> 339000000 | C93: =('Cost Components'!$P$44 + 'Cost Components'!$P$42)*10^6 -> 2.2131119e+08 | D93: =('Cost Components'!$P$44 + 'Cost Components'!$P$42)*10^6 -> 2.2131119e+08 | E93: =('Cost Components'!$P$44 + 'Cost Components'!$P$42)*10^6 -> 2.2131119e+08 | F93: =('Cost Components'!$P$44 + 'Cost Components'!$P$42)*10^6 -> 2.2131119e+08 | G93: =('Cost Components'!$P$44 + 'Cost Components'!$P$42)*10^6 -> 2.2131119e+08 | H93: =('Cost Components'!$P$44 + 'Cost Components'!$P$42)*10^6 -> 2.2131119e+08 | I93: =('Cost Components'!$P$44 + 'Cost Components'!$P$42)*10^6 -> 2.2131119e+08 | J93: =('Cost Components'!$P$44 + 'Cost Components'!$P$42)*10^6 -> 2.2131119e+08 | ... AA93: =('Cost Components'!$P$44 + 'Cost Components'!$P$42)*10^6 -> 2.2131119e+08
A94: Revenue (€) | B94: 0 | C94: ='Cost Components'!$P$36 * 10^6 -> 135200000 | D94: ='Cost Components'!$P$36 * 10^6 -> 135200000 | E94: ='Cost Components'!$P$36 * 10^6 -> 135200000 | F94: ='Cost Components'!$P$36 * 10^6 -> 135200000 | G94: ='Cost Components'!$P$36 * 10^6 -> 135200000 | H94: ='Cost Components'!$P$36 * 10^6 -> 135200000 | I94: ='Cost Components'!$P$36 * 10^6 -> 135200000 | J94: ='Cost Components'!$P$36 * 10^6 -> 135200000 | ... AA94: ='Cost Components'!$P$36 * 10^6 -> 135200000
A95: Free Cash Flow (€) | B95: =B93-B94 -> 339000000 | C95: =C93-C94 -> 86111187 | D95: =D93-D94 -> 86111187 | E95: =E93-E94 -> 86111187 | F95: =F93-F94 -> 86111187 | G95: =G93-G94 -> 86111187 | H95: =H93-H94 -> 86111187 | I95: =I93-I94 -> 86111187 | ... AA95: =AA93-AA94 -> 86111187
A96: Discounted Cash Flow (€) | B96: =B95/(1+Inputs!$C$5) ^'Production Cost Baseline'!B$2 -> 339000000 | C96: =C95/(1+Inputs!$C$5) ^'Production Cost Baseline'!C$2 -> 80477745 | D96: =D95/(1+Inputs!$C$5) ^'Production Cost Baseline'!D$2 -> 75212846 | E96: =E95/(1+Inputs!$C$5) ^'Production Cost Baseline'!E$2 -> 70292379 | F96: =F95/(1+Inputs!$C$5) ^'Production Cost Baseline'!F$2 -> 65693812 | G96: =G95/(1+Inputs!$C$5) ^'Production Cost Baseline'!G$2 -> 61396086 | H96: =H95/(1+Inputs!$C$5) ^'Production Cost Baseline'!H$2 -> 57379520 | I96: =I95/(1+Inputs!$C$5) ^'Production Cost Baseline'!I$2 -> 53625720 | ... AA96: =AA95/(1+Inputs!$C$5) ^'Production Cost Baseline'!AA$2 -> 15865915
A97: Fuel Production (kg) | B97: 0 | C97: ='Study Parameters'!$C$15*'Study Parameters'!$C$8 * 10^3 -> 55200000 | D97: ='Study Parameters'!$C$15*'Study Parameters'!$C$8 * 10^3 -> 55200000 | E97: ='Study Parameters'!$C$15*'Study Parameters'!$C$8 * 10^3 -> 55200000 | F97: ='Study Parameters'!$C$15*'Study Parameters'!$C$8 * 10^3 -> 55200000 | G97: ='Study Parameters'!$C$15*'Study Parameters'!$C$8 * 10^3 -> 55200000 | H97: ='Study Parameters'!$C$15*'Study Parameters'!$C$8 * 10^3 -> 55200000 | I97: ='Study Parameters'!$C$15*'Study Parameters'!$C$8 * 10^3 -> 55200000 | J97: ='Study Parameters'!$C$15*'Study Parameters'!$C$8 * 10^3 -> 55200000 | ... AA97: ='Study Parameters'!$C$15*'Study Parameters'!$C$8 * 10^3 -> 55200000
A98: Discounted Fuel Production (kg) | B98: =B97/(1+Inputs!$C$5) ^'Production Cost Baseline'!B$2 -> 0 | C98: =C97/(1+Inputs!$C$5) ^'Production Cost Baseline'!C$2 -> 51588785 | D98: =D97/(1+Inputs!$C$5) ^'Production Cost Baseline'!D$2 -> 48213818 | E98: =E97/(1+Inputs!$C$5) ^'Production Cost Baseline'!E$2 -> 45059643 | F98: =F97/(1+Inputs!$C$5) ^'Production Cost Baseline'!F$2 -> 42111816 | G98: =G97/(1+Inputs!$C$5) ^'Production Cost Baseline'!G$2 -> 39356837 | H98: =H97/(1+Inputs!$C$5) ^'Production Cost Baseline'!H$2 -> 36782091 | I98: =I97/(1+Inputs!$C$5) ^'Production Cost Baseline'!I$2 -> 34375786 | ... AA98: =AA97/(1+Inputs!$C$5) ^'Production Cost Baseline'!AA$2 -> 10170555
A100: Production Cost of Fuel (€/kg) | B100: =SUM(B96:AA96) / SUM(C98:AA98) -> 2.0869738
A101: Production Cost of Fuel (€/l) | B101: =B100 * Inputs!$C$15 -> 1.6758399
A103: C.5 Baseload
A104: Cost (€) | B104: ='Cost Components'!$Q$43 * 10^6 -> 347000000 | C104: =('Cost Components'!$Q$44 + 'Cost Components'!$Q$42)*10^6 -> 2.3741587e+08 | D104: =('Cost Components'!$Q$44 + 'Cost Components'!$Q$42)*10^6 -> 2.3741587e+08 | E104: =('Cost Components'!$Q$44 + 'Cost Components'!$Q$42)*10^6 -> 2.3741587e+08 | F104: =('Cost Components'!$Q$44 + 'Cost Components'!$Q$42)*10^6 -> 2.3741587e+08 | G104: =('Cost Components'!$Q$44 + 'Cost Components'!$Q$42)*10^6 -> 2.3741587e+08 | H104: =('Cost Components'!$Q$44 + 'Cost Components'!$Q$42)*10^6 -> 2.3741587e+08 | I104: =('Cost Components'!$Q$44 + 'Cost Components'!$Q$42)*10^6 -> 2.3741587e+08 | J104: =('Cost Components'!$Q$44 + 'Cost Components'!$Q$42)*10^6 -> 2.3741587e+08 | ... AA104: =('Cost Components'!$Q$44 + 'Cost Components'!$Q$42)*10^6 -> 2.3741587e+08
A105: Revenue (€) | B105: 0 | C105: ='Cost Components'!$Q$36 * 10^6 -> 1.337e+08 | D105: ='Cost Components'!$Q$36 * 10^6 -> 1.337e+08 | E105: ='Cost Components'!$Q$36 * 10^6 -> 1.337e+08 | F105: ='Cost Components'!$Q$36 * 10^6 -> 1.337e+08 | G105: ='Cost Components'!$Q$36 * 10^6 -> 1.337e+08 | H105: ='Cost Components'!$Q$36 * 10^6 -> 1.337e+08 | I105: ='Cost Components'!$Q$36 * 10^6 -> 1.337e+08 | J105: ='Cost Components'!$Q$36 * 10^6 -> 1.337e+08 | ... AA105: ='Cost Components'!$Q$36 * 10^6 -> 1.337e+08
A106: Free Cash Flow (€) | B106: =B104-B105 -> 347000000 | C106: =C104-C105 -> 1.0371587e+08 | D106: =D104-D105 -> 1.0371587e+08 | E106: =E104-E105 -> 1.0371587e+08 | F106: =F104-F105 -> 1.0371587e+08 | G106: =G104-G105 -> 1.0371587e+08 | H106: =H104-H105 -> 1.0371587e+08 | I106: =I104-I105 -> 1.0371587e+08 | ... AA106: =AA104-AA105 -> 1.0371587e+08
A107: Discounted Cash Flow (€) | B107: =B106/(1+Inputs!$C$5) ^'Production Cost Baseline'!B$2 -> 347000000 | C107: =C106/(1+Inputs!$C$5) ^'Production Cost Baseline'!C$2 -> 96930718 | D107: =D106/(1+Inputs!$C$5) ^'Production Cost Baseline'!D$2 -> 90589456 | E107: =E106/(1+Inputs!$C$5) ^'Production Cost Baseline'!E$2 -> 84663043 | F107: =F106/(1+Inputs!$C$5) ^'Production Cost Baseline'!F$2 -> 79124339 | G107: =G106/(1+Inputs!$C$5) ^'Production Cost Baseline'!G$2 -> 73947981 | H107: =H106/(1+Inputs!$C$5) ^'Production Cost Baseline'!H$2 -> 69110262 | I107: =I106/(1+Inputs!$C$5) ^'Production Cost Baseline'!I$2 -> 64589030 | ... AA107: =AA106/(1+Inputs!$C$5) ^'Production Cost Baseline'!AA$2 -> 19109563
A108: Fuel Production (kg) | B108: 0 | C108: ='Study Parameters'!$C$16*'Study Parameters'!$C$8 * 10^3 -> 54400000 | D108: ='Study Parameters'!$C$16*'Study Parameters'!$C$8 * 10^3 -> 54400000 | E108: ='Study Parameters'!$C$16*'Study Parameters'!$C$8 * 10^3 -> 54400000 | F108: ='Study Parameters'!$C$16*'Study Parameters'!$C$8 * 10^3 -> 54400000 | G108: ='Study Parameters'!$C$16*'Study Parameters'!$C$8 * 10^3 -> 54400000 | H108: ='Study Parameters'!$C$16*'Study Parameters'!$C$8 * 10^3 -> 54400000 | I108: ='Study Parameters'!$C$16*'Study Parameters'!$C$8 * 10^3 -> 54400000 | J108: ='Study Parameters'!$C$16*'Study Parameters'!$C$8 * 10^3 -> 54400000 | ... AA108: ='Study Parameters'!$C$16*'Study Parameters'!$C$8 * 10^3 -> 54400000
A109: Discounted Fuel Production (kg) | B109: =B108/(1+Inputs!$C$5) ^'Production Cost Baseline'!B$2 -> 0 | C109: =C108/(1+Inputs!$C$5) ^'Production Cost Baseline'!C$2 -> 50841121 | D109: =D108/(1+Inputs!$C$5) ^'Production Cost Baseline'!D$2 -> 47515067 | E109: =E108/(1+Inputs!$C$5) ^'Production Cost Baseline'!E$2 -> 44406605 | F109: =F108/(1+Inputs!$C$5) ^'Production Cost Baseline'!F$2 -> 41501500 | G109: =G108/(1+Inputs!$C$5) ^'Production Cost Baseline'!G$2 -> 38786448 | H109: =H108/(1+Inputs!$C$5) ^'Production Cost Baseline'!H$2 -> 36249017 | I109: =I108/(1+Inputs!$C$5) ^'Production Cost Baseline'!I$2 -> 33877586 | ... AA109: =AA108/(1+Inputs!$C$5) ^'Production Cost Baseline'!AA$2 -> 10023155
A111: Production Cost of Fuel (€/kg) | B111: =SUM(B107:AA107) / SUM(C109:AA109) -> 2.4538992
A112: Production Cost of Fuel (€/l) | B112: =B111 * Inputs!$C$15 -> 1.9704811

Sheet Cost Breakdown
A1: Year | B1: 0 | C1: 1 | D1: 2 | E1: 3 | F1: 4 | G1: 5 | H1: 6 | I1: 7 | J1: 8 | K1: 9 | L1: 10 | M1: 11 | N1: 12 | O1: 13 | P1: 14 | Q1: 15 | R1: 16 | S1: 17 | T1: 18 | U1: 19 | V1: 20 | W1: 21 | X1: 22 | Y1: 23 | Z1: 24 | AA1: 25
A2: 2024
A3: CO2 | B3: 0 | C3: =('Cost Components'!$B$41) / (1+Inputs!$C$5)^'Cost Breakdown'!C1 -> 276.76262 | D3: =('Cost Components'!$B$41) / (1+Inputs!$C$5)^'Cost Breakdown'!D1 -> 258.65665 | E3: =('Cost Components'!$B$41) / (1+Inputs!$C$5)^'Cost Breakdown'!E1 -> 241.73519 | F3: =('Cost Components'!$B$41) / (1+Inputs!$C$5)^'Cost Breakdown'!F1 -> 225.92074 | G3: =('Cost Components'!$B$41) / (1+Inputs!$C$5)^'Cost Breakdown'!G1 -> 211.14088 | H3: =('Cost Components'!$B$41) / (1+Inputs!$C$5)^'Cost Breakdown'!H1 -> 197.32792 | I3: =('Cost Components'!$B$41) / (1+Inputs!$C$5)^'Cost Breakdown'!I1 -> 184.41862 | J3: =('Cost Components'!$B$41) / (1+Inputs!$C$5)^'Cost Breakdown'!J1 -> 172.35385 | ... AA3: =('Cost Components'!$B$41) / (1+Inputs!$C$5)^'Cost Breakdown'!AA1 -> 54.562814
A4: Electricity | B4: 0 | C4: =('Cost Components'!$B$40) / (1+Inputs!$C$5)^'Cost Breakdown'!C1 -> 133.68117 | D4: =('Cost Components'!$B$40) / (1+Inputs!$C$5)^'Cost Breakdown'!D1 -> 124.93568 | E4: =('Cost Components'!$B$40) / (1+Inputs!$C$5)^'Cost Breakdown'!E1 -> 116.76231 | F4: =('Cost Components'!$B$40) / (1+Inputs!$C$5)^'Cost Breakdown'!F1 -> 109.12366 | G4: =('Cost Components'!$B$40) / (1+Inputs!$C$5)^'Cost Breakdown'!G1 -> 101.98473 | H4: =('Cost Components'!$B$40) / (1+Inputs!$C$5)^'Cost Breakdown'!H1 -> 95.312829 | I4: =('Cost Components'!$B$40) / (1+Inputs!$C$5)^'Cost Breakdown'!I1 -> 89.077411 | J4: =('Cost Components'!$B$40) / (1+Inputs!$C$5)^'Cost Breakdown'!J1 -> 83.249917 | ... AA4: =('Cost Components'!$B$40) / (1+Inputs!$C$5)^'Cost Breakdown'!AA1 -> 26.354792
A5: CAPEX | B5: ='Cost Components'!B12 -> 1870.76 | C5: 0 | D5: 0 | E5: 0 | F5: 0 | G5: 0 | H5: 0 | I5: 0 | J5: 0 | K5: 0 | L5: 0 | M5: 0 | N5: 0 | O5: 0 | P5: 0 | Q5: 0 | R5: 0 | S5: 0 | T5: 0 | U5: 0 | V5: 0 | W5: 0 | X5: 0 | Y5: 0 | Z5: 0 | AA5: 0
A6: OPEX | B6: 0 | C6: =('Cost Components'!$B$21)/ (1+Inputs!$C$5)^'Cost Breakdown'!C1 -> 121.02804 | D6: =('Cost Components'!$B$21)/ (1+Inputs!$C$5)^'Cost Breakdown'!D1 -> 113.11032 | E6: =('Cost Components'!$B$21)/ (1+Inputs!$C$5)^'Cost Breakdown'!E1 -> 105.71058 | F6: =('Cost Components'!$B$21)/ (1+Inputs!$C$5)^'Cost Breakdown'!F1 -> 98.79493 | G6: =('Cost Components'!$B$21)/ (1+Inputs!$C$5)^'Cost Breakdown'!G1 -> 92.33171 | H6: =('Cost Components'!$B$21)/ (1+Inputs!$C$5)^'Cost Breakdown'!H1 -> 86.291318 | I6: =('Cost Components'!$B$21)/ (1+Inputs!$C$5)^'Cost Breakdown'!I1 -> 80.646092 | J6: =('Cost Components'!$B$21)/ (1+Inputs!$C$5)^'Cost Breakdown'!J1 -> 75.370179 | ... AA6: =('Cost Components'!$B$21)/ (1+Inputs!$C$5)^'Cost Breakdown'!AA1 -> 23.860268
A8: Contributions
A9: CO2 | B9: =SUM(B3:AA3) / SUM($B$3:$AA$6) -> 0.40610761
A10: Electricity | B10: =SUM(B4:AA4) / SUM($B$3:$AA$6) -> 0.19615706
A11: CAPEX | B11: =SUM(B5:AA5) / SUM($B$3:$AA$6) -> 0.22014484
A12: OPEX | B12: =SUM(B6:AA6) / SUM($B$3:$AA$6) -> 0.17759048
A14: 2050
A15: CO2 | B15: 0 | C15: =('Cost Components'!$M$42) / (1+Inputs!$C$5)^'Cost Breakdown'!C1 -> 105.57757 | D15: =('Cost Components'!$M$42) / (1+Inputs!$C$5)^'Cost Breakdown'!D1 -> 98.670626 | E15: =('Cost Components'!$M$42) / (1+Inputs!$C$5)^'Cost Breakdown'!E1 -> 92.215539 | F15: =('Cost Components'!$M$42) / (1+Inputs!$C$5)^'Cost Breakdown'!F1 -> 86.182746 | G15: =('Cost Components'!$M$42) / (1+Inputs!$C$5)^'Cost Breakdown'!G1 -> 80.544623 | H15: =('Cost Components'!$M$42) / (1+Inputs!$C$5)^'Cost Breakdown'!H1 -> 75.275348 | I15: =('Cost Components'!$M$42) / (1+Inputs!$C$5)^'Cost Breakdown'!I1 -> 70.350793 | J15: =('Cost Components'!$M$42) / (1+Inputs!$C$5)^'Cost Breakdown'!J1 -> 65.748405 | ... AA15: =('Cost Components'!$M$42) / (1+Inputs!$C$5)^'Cost Breakdown'!AA1 -> 20.814261
A16: Electricity | B16: 0 | C16: =('Cost Components'!$M$40) / (1+Inputs!$C$5)^'Cost Breakdown'!C1 -> 24.517521 | D16: =('Cost Components'!$M$40) / (1+Inputs!$C$5)^'Cost Breakdown'!D1 -> 22.913571 | E16: =('Cost Components'!$M$40) / (1+Inputs!$C$5)^'Cost Breakdown'!E1 -> 21.414552 | F16: =('Cost Components'!$M$40) / (1+Inputs!$C$5)^'Cost Breakdown'!F1 -> 20.0136 | G16: =('Cost Components'!$M$40) / (1+Inputs!$C$5)^'Cost Breakdown'!G1 -> 18.704299 | H16: =('Cost Components'!$M$40) / (1+Inputs!$C$5)^'Cost Breakdown'!H1 -> 17.480654 | I16: =('Cost Components'!$M$40) / (1+Inputs!$C$5)^'Cost Breakdown'!I1 -> 16.337059 | J16: =('Cost Components'!$M$40) / (1+Inputs!$C$5)^'Cost Breakdown'!J1 -> 15.26828 | ... AA16: =('Cost Components'!$M$40) / (1+Inputs!$C$5)^'Cost Breakdown'!AA1 -> 4.8335464
A17: CAPEX | B17: ='Cost Components'!M12 -> 575 | C17: 0 | D17: 0 | E17: 0 | F17: 0 | G17: 0 | H17: 0 | I17: 0 | J17: 0 | K17: 0 | L17: 0 | M17: 0 | N17: 0 | O17: 0 | P17: 0 | Q17: 0 | R17: 0 | S17: 0 | T17: 0 | U17: 0 | V17: 0 | W17: 0 | X17: 0 | Y17: 0 | Z17: 0 | AA17: 0
A18: OPEX | B18: 0 | C18: =('Cost Components'!$M$18)/ (1+Inputs!$C$5)^'Cost Breakdown'!C1 -> 121.02804 | D18: =('Cost Components'!$M$18)/ (1+Inputs!$C$5)^'Cost Breakdown'!D1 -> 113.11032 | E18: =('Cost Components'!$M$18)/ (1+Inputs!$C$5)^'Cost Breakdown'!E1 -> 105.71058 | F18: =('Cost Components'!$M$18)/ (1+Inputs!$C$5)^'Cost Breakdown'!F1 -> 98.79493 | G18: =('Cost Components'!$M$18)/ (1+Inputs!$C$5)^'Cost Breakdown'!G1 -> 92.33171 | H18: =('Cost Components'!$M$18)/ (1+Inputs!$C$5)^'Cost Breakdown'!H1 -> 86.291318 | I18: =('Cost Components'!$M$18)/ (1+Inputs!$C$5)^'Cost Breakdown'!I1 -> 80.646092 | J18: =('Cost Components'!$M$18)/ (1+Inputs!$C$5)^'Cost Breakdown'!J1 -> 75.370179 | ... AA18: =('Cost Components'!$M$18)/ (1+Inputs!$C$5)^'Cost Breakdown'!AA1 -> 23.860268
A20: Contributions
A21: CO2 | B21: =SUM(B15:AA15) / SUM($B$15:$AA$18) -> 0.35519748
A22: Electricity | B22: =SUM(B16:AA16) / SUM($B$15:$AA$18) -> 0.082484961
A23: CAPEX | B23: =SUM(B17:AA17) / SUM($B$15:$AA$18) -> 0.15513965
A24: OPEX | B24: =SUM(B18:AA18) / SUM($B$15:$AA$18) -> 0.40717791

Sheet Outputs
A1: 2024 C.1 | H1: 2024 C.2 | O1: 2024 C.3 | V1: 2024 C.4 | AC1: 2024 C.5
A2: Parameter | B2: Unit | C2: Base Case | D2: LCOE Corrected | E2: CO2 Cost Corrected | F2: WACC Corrected | H2: Parameter | I2: Unit | J2: Base Case | K2: LCOE Corrected | L2: CO2 Cost Corrected | M2: WACC Corrected | O2: Parameter | P2: Unit | Q2: Base Case | R2: LCOE Corrected | S2: CO2 Cost Corrected | T2: WACC Corrected | V2: Parameter | W2: Unit | X2: Base Case | Y2: LCOE Corrected | Z2: CO2 Cost Corrected | AA2: WACC Corrected | AC2: Parameter | AD2: Unit | AE2: Base Case | AF2: LCOE Corrected | AG2: CO2 Cost Corrected | AH2: WACC Corrected
A3: Syn-Fuel cost | B3: €/l | C3: ='Production Cost Baseline'!B12 -> 6.9852593 | D3: ='LCOE Corrected Production Cost '!B12 -> 4.4253375 | E3: ='CO2 Corrected Production Cost'!B12 -> 6.9368858 | F3: ='WACC Corrected Production Cost'!B12 -> 6.8857345 | H3: Syn-Fuel cost | I3: €/l | J3: ='Production Cost Baseline'!B34 -> 9.786152 | K3: ='LCOE Corrected Production Cost '!B23 -> 5.2984041 | L3: ='CO2 Corrected Production Cost'!B23 -> 11.688505 | M3: ='WACC Corrected Production Cost'!B23 -> 11.59597 | O3: Syn-Fuel cost | P3: €/l | Q3: ='Production Cost Baseline'!B56 -> 9.6151199 | R3: ='LCOE Corrected Production Cost '!B34 -> 6.7030756 | S3: ='CO2 Corrected Production Cost'!B34 -> 11.349822 | T3: ='WACC Corrected Production Cost'!B34 -> 11.277478 | V3: Syn-Fuel cost | W3: €/l | X3: ='Production Cost Baseline'!B78 -> 5.5871953 | Y3: ='LCOE Corrected Production Cost '!B45 -> 3.3097328 | Z3: ='CO2 Corrected Production Cost'!B45 -> 6.7073269 | AA3: ='WACC Corrected Production Cost'!B45 -> 6.6593896 | AC3: Syn-Fuel cost | AD3: €/l | AE3: ='Production Cost Baseline'!B100 -> 6.4640087 | AF3: ='LCOE Corrected Production Cost '!B56 -> 3.543423 | AG3: ='CO2 Corrected Production Cost'!B56 -> 7.0704351 | AH3: ='WACC Corrected Production Cost'!B56 -> 7.015878
A4: Syn-Fuel cost | B4: $/l | C4: =C3*Inputs!$C$6 -> 6.2867334 | D4: =D3*Inputs!$C$6 -> 3.9828038 | E4: =E3*Inputs!$C$6 -> 6.2431972 | F4: =F3*Inputs!$C$6 -> 6.197161 | H4: Syn-Fuel cost | I4: $/l | J4: =J3*Inputs!$C$6 -> 8.8075368 | K4: =K3*Inputs!$C$6 -> 4.7685637 | L4: =L3*Inputs!$C$6 -> 10.519654 | M4: =M3*Inputs!$C$6 -> 10.436373 | O4: Syn-Fuel cost | P4: $/l | Q4: =Q3*Inputs!$C$6 -> 8.653608 | R4: =R3*Inputs!$C$6 -> 6.032768 | S4: =S3*Inputs!$C$6 -> 10.21484 | T4: =T3*Inputs!$C$6 -> 10.14973 | V4: Syn-Fuel cost | W4: $/l | X4: =X3*Inputs!$C$6 -> 5.0284758 | Y4: =Y3*Inputs!$C$6 -> 2.9787595 | Z4: =Z3*Inputs!$C$6 -> 6.0365942 | AA4: =AA3*Inputs!$C$6 -> 5.9934506 | AC4: Syn-Fuel cost | AD4: $/l | AE4: =AE3*Inputs!$C$6 -> 5.8176078 | AF4: =AF3*Inputs!$C$6 -> 3.1890807 | AG4: =AG3*Inputs!$C$6 -> 6.3633916 | AH4: =AH3*Inputs!$C$6 -> 6.3142902
A5: Fossil Fuel cost | B5: $/l | C5: =Inputs!$C$16 -> 0.8 | D5: =Inputs!$C$16 -> 0.8 | E5: =Inputs!$C$16 -> 0.8 | F5: =Inputs!$C$16 -> 0.8 | H5: Fossil Fuel cost | I5: $/l | J5: =Inputs!$C$16 -> 0.8 | K5: =Inputs!$C$16 -> 0.8 | L5: =Inputs!$C$16 -> 0.8 | M5: =Inputs!$C$16 -> 0.8 | O5: Fossil Fuel cost | P5: $/l | Q5: =Inputs!$C$16 -> 0.8 | R5: =Inputs!$C$16 -> 0.8 | S5: =Inputs!$C$16 -> 0.8 | T5: =Inputs!$C$16 -> 0.8 | V5: Fossil Fuel cost | W5: $/l | X5: =Inputs!$C$16 -> 0.8 | Y5: =Inputs!$C$16 -> 0.8 | Z5: =Inputs!$C$16 -> 0.8 | AA5: =Inputs!$C$16 -> 0.8 | AC5: Fossil Fuel cost | AD5: $/l | AE5: =Inputs!$C$16 -> 0.8 | AF5: =Inputs!$C$16 -> 0.8 | AG5: =Inputs!$C$16 -> 0.8 | AH5: =Inputs!$C$16 -> 0.8
A6: Syn-Fuel emissions | B6: gCO2eq/MJ | C6: ='Study Parameters'!$C$40 -> 0 | D6: ='Study Parameters'!$C$40 -> 0 | E6: ='Study Parameters'!$C$40 -> 0 | F6: ='Study Parameters'!$C$40 -> 0 | H6: Syn-Fuel emissions | I6: gCO2eq/MJ | J6: ='Study Parameters'!$C$40 -> 0 | K6: ='Study Parameters'!$C$40 -> 0 | L6: ='Study Parameters'!$C$40 -> 0 | M6: ='Study Parameters'!$C$40 -> 0 | O6: Syn-Fuel emissions | P6: gCO2eq/MJ | Q6: ='Study Parameters'!$C$40 -> 0 | R6: ='Study Parameters'!$C$40 -> 0 | S6: ='Study Parameters'!$C$40 -> 0 | T6: ='Study Parameters'!$C$40 -> 0 | V6: Syn-Fuel emissions | W6: gCO2eq/MJ | X6: ='Study Parameters'!$C$40 -> 0 | Y6: ='Study Parameters'!$C$40 -> 0 | Z6: ='Study Parameters'!$C$40 -> 0 | AA6: ='Study Parameters'!$C$40 -> 0 | AC6: Syn-Fuel emissions | AD6: gCO2eq/MJ | AE6: ='Study Parameters'!$C$40 -> 0 | AF6: ='Study Parameters'!$C$40 -> 0 | AG6: ='Study Parameters'!$C$40 -> 0 | AH6: ='Study Parameters'!$C$40 -> 0
A7: Fossil Fuel emissions | B7: gCO2eq/MJ | C7: =Inputs!$C$11 -> 88.7 | D7: =Inputs!$C$11 -> 88.7 | E7: =Inputs!$C$11 -> 88.7 | F7: =Inputs!$C$11 -> 88.7 | H7: Fossil Fuel emissions | I7: gCO2eq/MJ | J7: =Inputs!$C$11 -> 88.7 | K7: =Inputs!$C$11 -> 88.7 | L7: =Inputs!$C$11 -> 88.7 | M7: =Inputs!$C$11 -> 88.7 | O7: Fossil Fuel emissions | P7: gCO2eq/MJ | Q7: =Inputs!$C$11 -> 88.7 | R7: =Inputs!$C$11 -> 88.7 | S7: =Inputs!$C$11 -> 88.7 | T7: =Inputs!$C$11 -> 88.7 | V7: Fossil Fuel emissions | W7: gCO2eq/MJ | X7: =Inputs!$C$11 -> 88.7 | Y7: =Inputs!$C$11 -> 88.7 | Z7: =Inputs!$C$11 -> 88.7 | AA7: =Inputs!$C$11 -> 88.7 | AC7: Fossil Fuel emissions | AD7: gCO2eq/MJ | AE7: =Inputs!$C$11 -> 88.7 | AF7: =Inputs!$C$11 -> 88.7 | AG7: =Inputs!$C$11 -> 88.7 | AH7: =Inputs!$C$11 -> 88.7
A8: CO2 Abated | B8: gCO2eq/MJ | C8: =C7-C6 -> 88.7 | D8: =D7-D6 -> 88.7 | E8: =E7-E6 -> 88.7 | F8: =F7-F6 -> 88.7 | H8: CO2 Abated | I8: gCO2eq/MJ | J8: =J7-J6 -> 88.7 | K8: =K7-K6 -> 88.7 | L8: =L7-L6 -> 88.7 | M8: =M7-M6 -> 88.7 | O8: CO2 Abated | P8: gCO2eq/MJ | Q8: =Q7-Q6 -> 88.7 | R8: =R7-R6 -> 88.7 | S8: =S7-S6 -> 88.7 | T8: =T7-T6 -> 88.7 | V8: CO2 Abated | W8: gCO2eq/MJ | X8: =X7-X6 -> 88.7 | Y8: =Y7-Y6 -> 88.7 | Z8: =Z7-Z6 -> 88.7 | AA8: =AA7-AA6 -> 88.7 | AC8: CO2 Abated | AD8: gCO2eq/MJ | AE8: =AE7-AE6 -> 88.7 | AF8: =AF7-AF6 -> 88.7 | AG8: =AG7-AG6 -> 88.7 | AH8: =AH7-AH6 -> 88.7
A9: CO2 Abated | B9: gCO2eq/l | C9: =C8*Inputs!$C$14 -> 3076.9675 | D9: =D8*Inputs!$C$14 -> 3076.9675 | E9: =E8*Inputs!$C$14 -> 3076.9675 | F9: =F8*Inputs!$C$14 -> 3076.9675 | H9: CO2 Abated | I9: gCO2eq/l | J9: =J8*Inputs!$C$14 -> 3076.9675 | K9: =K8*Inputs!$C$14 -> 3076.9675 | L9: =L8*Inputs!$C$14 -> 3076.9675 | M9: =M8*Inputs!$C$14 -> 3076.9675 | O9: CO2 Abated | P9: gCO2eq/l | Q9: =Q8*Inputs!$C$14 -> 3076.9675 | R9: =R8*Inputs!$C$14 -> 3076.9675 | S9: =S8*Inputs!$C$14 -> 3076.9675 | T9: =T8*Inputs!$C$14 -> 3076.9675 | V9: CO2 Abated | W9: gCO2eq/l | X9: =X8*Inputs!$C$14 -> 3076.9675 | Y9: =Y8*Inputs!$C$14 -> 3076.9675 | Z9: =Z8*Inputs!$C$14 -> 3076.9675 | AA9: =AA8*Inputs!$C$14 -> 3076.9675 | AC9: CO2 Abated | AD9: gCO2eq/l | AE9: =AE8*Inputs!$C$14 -> 3076.9675 | AF9: =AF8*Inputs!$C$14 -> 3076.9675 | AG9: =AG8*Inputs!$C$14 -> 3076.9675 | AH9: =AH8*Inputs!$C$14 -> 3076.9675
A10: Abatement cost | B10: $/tCO2 | C10: =(C4-C5) / C9 * 10^6 -> 1783.1626 | D10: =(D4-D5) / D9 * 10^6 -> 1034.3963 | E10: =(E4-E5) / E9 * 10^6 -> 1769.0135 | F10: =(F4-F5) / F9 * 10^6 -> 1754.052 | H10: Abatement cost | I10: $/tCO2 | J10: =(J4-J5) / J9 * 10^6 -> 2602.4119 | K10: =(K4-K5) / K9 * 10^6 -> 1289.7646 | L10: =(L4-L5) / L9 * 10^6 -> 3158.842 | M10: =(M4-M5) / M9 * 10^6 -> 3131.7761 | O10: Abatement cost | P10: $/tCO2 | Q10: =(Q4-Q5) / Q9 * 10^6 -> 2552.3857 | R10: =(R4-R5) / R9 * 10^6 -> 1700.625 | S10: =(S4-S5) / S9 * 10^6 -> 3059.7788 | T10: =(T4-T5) / T9 * 10^6 -> 3038.6184 | V10: Abatement cost | W10: $/tCO2 | X10: =(X4-X5) / X9 * 10^6 -> 1374.2348 | Y10: =(Y4-Y5) / Y9 * 10^6 -> 708.08662 | Z10: =(Z4-Z5) / Z9 * 10^6 -> 1701.8685 | AA10: =(AA4-AA5) / AA9 * 10^6 -> 1687.8471 | AC10: Abatement cost | AD10: $/tCO2 | AE10: =(AE4-AE5) / AE9 * 10^6 -> 1630.699 | AF10: =(AF4-AF5) / AF9 * 10^6 -> 776.44002 | AG10: =(AG4-AG5) / AG9 * 10^6 -> 1808.0761 | AH10: =(AH4-AH5) / AH9 * 10^6 -> 1792.1184
A12: 2050 C.1 | H12: 2050 C.2 | O12: 2050 C.3 | V12: 2050 C.4 | AC12: 2050 C.5
A13: Parameter | B13: Unit | C13: Base Case | D13: LCOE Corrected | E13: CO2 Cost Corrected | F13: WACC Corrected | H13: Parameter | I13: Unit | J13: Base Case | K13: LCOE Corrected | L13: CO2 Cost Corrected | M13: WACC Corrected | O13: Parameter | P13: Unit | Q13: Base Case | R13: LCOE Corrected | S13: CO2 Cost Corrected | T13: WACC Corrected | V13: Parameter | W13: Unit | X13: Base Case | Y13: LCOE Corrected | Z13: CO2 Cost Corrected | AA13: WACC Corrected | AC13: Parameter | AD13: Unit | AE13: Base Case | AF13: LCOE Corrected | AG13: CO2 Cost Corrected | AH13: WACC Corrected
A14: Syn-Fuel cost | B14: €/l | C14: ='Production Cost Baseline'!B123 -> 2.0397677 | D14: ='LCOE Corrected Production Cost '!B68 -> 0.69151895 | E14: ='CO2 Corrected Production Cost'!B68 -> 1.8138554 | F14: ='WACC Corrected Production Cost'!B68 -> 1.7945874 | H14: Syn-Fuel cost | I14: €/l | J14: ='Production Cost Baseline'!B134 -> 4.6524958 | K14: ='LCOE Corrected Production Cost '!B79 -> 2.3336248 | L14: ='CO2 Corrected Production Cost'!B79 -> 5.1528543 | M14: ='WACC Corrected Production Cost'!B79 -> 5.1182476 | O14: Syn-Fuel cost | P14: €/l | Q14: ='Production Cost Baseline'!B145 -> 4.1478475 | R14: ='LCOE Corrected Production Cost '!B90 -> 1.5295503 | S14: ='CO2 Corrected Production Cost'!B90 -> 3.5826981 | T14: ='WACC Corrected Production Cost'!B90 -> 3.5564691 | V14: Syn-Fuel cost | W14: €/l | X14: ='Production Cost Baseline'!B156 -> 1.4872343 | Y14: ='LCOE Corrected Production Cost '!B101 -> 0.23378174 | Z14: ='CO2 Corrected Production Cost'!B101 -> 1.6950734 | AA14: ='WACC Corrected Production Cost'!B101 -> 1.6758399 | AC14: Syn-Fuel cost | AD14: €/l | AE14: ='Production Cost Baseline'!B167 -> 2.0993233 | AF14: ='LCOE Corrected Production Cost '!B112 -> 0.49178603 | AG14: ='CO2 Corrected Production Cost'!B112 -> 1.990458 | AH14: ='WACC Corrected Production Cost'!B112 -> 1.9704811
