Workbook

Sheet Inputs
A1: Parameter | B1: Year | C1: Value | D1: Unit
A2: Standard Values
A3: Current Year | C3: =[1]Inputs!C4 -> 2024
A4: Inflation | C4: =[1]Inputs!C5 -> 0.02
A5: WACC | C5: =[1]Inputs!C6 -> 0.07
A6: USD to EUR | C6: =[1]Inputs!C7 -> 0.9
A7: Electricity
A8: LCOE | B8: 2024 | C8: =[1]Inputs!C9 -> 64 | D8: $/MWh
A9: LCOE | B9: 2050 | C9: =[1]Inputs!C10 -> 11 | D9: $/MWh
A10: Jet Fuel A-1 Characteristics
A11: Emissions Intensity | B11: 2024 | C11: =[1]Inputs!C12 -> 88.7 | D11: gCO2/MJ
A12: Emissions Intensity | B12: 2050 | C12: =[1]Inputs!C13 -> 88.7 | D12: gCO2/MJ
A13: Energy Density | C13: =[1]Inputs!C14 -> 43.2 | D13: MJ/kg
A14: Energy Density | C14: =[1]Inputs!C15 -> 34.6896 | D14: MJ/l
A15: Volumetric Density | C15: =[1]Inputs!C16 -> 0.803 | D15: kg/l
A16: Jet Fuel A-1 Price | B16: 2024 | C16: =[1]Inputs!C17 -> 0.8 | D16: $/l
A17: Scenario Specific Values
A18: Jet Fuel A-1 Price | B18: 2050 | C18: =[1]Inputs!C19 -> 0.8 | D18: $/l
A19: IEA Reference
A20: Jet Fuel A-1 Price | B20: 2024 | C20: =[1]Inputs!C21 -> 0.32246154 | D20: $/l
A21: Jet Fuel A-1 Price | B21: 2050 | C21: =[1]Inputs!C22 -> 0.20923077 | D21: $/l
A22: EIA Reference
A23: Jet Fuel A-1 Price | B23: 2024 | C23: =[1]Inputs!C24 -> 1.0209014 | D23: $/l
A24: Jet Fuel A-1 Price | B24: 2050 | C24: =[1]Inputs!C25 -> 2.0095594 | D24: $/l
A25: EIA Low Oil Price Scenario
A26: Jet Fuel A-1 Price | B26: 2024 | C26: =[1]Inputs!C27 -> 0.48286833 | D26: $/l
A27: Jet Fuel A-1 Price | B27: 2050 | C27: =[1]Inputs!C28 -> 0.89646575 | D27: $/l
A28: EIA High Scenario
A29: Jet Fuel A-1 Price | B29: 2024 | C29: =[1]Inputs!C30 -> 1.8838713 | D29: $/l
A30: Jet Fuel A-1 Price | B30: 2050 | C30: =[1]Inputs!C31 -> 3.7893731 | D30: $/l
A31: Direct Air Capture
A32: LCOR | B32: 2024 | C32: =[1]Inputs!C33 -> 1282 | D32: $/tCO2
A33: LCOR | B33: 2050 | C33: =[1]Inputs!C34 -> 480 | D33: $/tCO2

Sheet Base LCOF
A1: WACC_source | B1: 0.06 | C1: 0.06 | D1: 0.06 | E1: 0.06 | F1: 0.06 | G1: 0.06 | H1: 0.06 | I1: 0.06 | J1: 0.06 | K1: -
A2: WACC_alternative | B2: 0.06 | C2: 0.06 | D2: 0.06 | E2: 0.06 | F2: 0.06 | G2: 0.06 | H2: 0.06 | I2: 0.06 | J2: 0.06 | K2: -
A3: LCOE_alternative | B3: 9.3710341 | C3: 5.2586511 | D3: 2.969201 | E3: 5.9593963 | F3: 3.6109404 | G3: 2.969201 | H3: 4.7585019 | I3: 3.330479 | J3: 2.969201 | K3: ct/kWh
B4: 11.1 | C4: 11.1 | D4: 11.1 | E4: 7.5 | F4: 7.5 | G4: 7.5 | H4: 3.9 | I4: 3.9 | J4: 3.9 | L4: Note: this is the standard LCOE curve
A5: DAC_source | B5: 460 | C5: 460 | D5: 460 | E5: 135 | F5: 135 | G5: 135 | H5: 80 | I5: 80 | J5: 80 | K5: €/tCO2
A6: DAC_alternative | B6: 460 | C6: 460 | D6: 460 | E6: 135 | F6: 135 | G6: 135 | H6: 80 | I6: 80 | J6: 80 | K6: €/tCO2 | L6: Average between SS and LS DAC
B7: 731.19867 | C7: 731.19867 | D7: 731.19867 | E7: 449.5681 | F7: 449.5681 | G7: 449.5681 | H7: 298.29332 | I7: 298.29332 | J7: 298.29332 | L7: Note: this is modelled DAC cost
A8: Levelized cost of electricity [ct/kWh]
B10: 2020 | E10: 2035 | H10: 2050
B11: Offshore | C11: Onshore | D11: Hydro | E11: Offshore | F11: Onshore | G11: Hydro | H11: Offshore | I11: Onshore | J11: Hydro | N11: 2020 Offshore | O11: 2020 Onshore
A12: Capex generation | B12: 5.6892159 | C12: 4.0867761 | D12: 2.1299153 | E12: 3.5557599 | F12: 2.8062529 | G12: 2.1299153 | H12: 2.9335019 | I12: 2.5882915 | J12: 2.1299153 | K12: ct/kWh | M12: CAPEX | N12: 3200 | O12: 1500
A13: Opex generation | B13: 2.1818182 | C13: 1.171875 | D13: 0.83928571 | E13: 1.3636364 | F13: 0.8046875 | G13: 0.83928571 | H13: 1.125 | I13: 0.7421875 | J13: 0.83928571 | K13: ct/kWh | M13: Loadhours | N13: 4400 | O13: 3200
A14: Offshore grid fee | B14: 1.5 | C14: 0 | D14: 0 | E14: 1.04 | F14: 0 | G14: 0 | H14: 0.7 | I14: 0 | J14: 0 | K14: ct/kWh | M14: UCRF | N14: =B23 -> 0.078226718 | O14: =C23 -> 0.087184557
M15: Annualized CAPEX | N15: =N12*N14/N13 -> 0.056892159 | O15: =O12*O14/O13 -> 0.040867761 | P15: €/kWh
A16: BC | B16: 1.377431 | C16: 0.80426429 | D16: 0.37115013 | E16: 1.3238642 | F16: 1.1857743 | G16: 0.37115013 | H16: 1.292708 | I16: 1.020797 | J16: 0.37115013 | K16: ct/kWh | N16: =N15*100 -> 5.6892159 | O16: =O15*100 -> 4.0867761 | P16: ct/kWh
A17: WC | B17: 1.4414975 | C17: 0.91149953 | D17: 0.49486684 | E17: 1.3602703 | F17: 1.3812724 | G17: 0.49486684 | H17: 1.352834 | I17: 1.1569032 | J17: 0.49486684 | K17: ct/kWh
A19: LCOE | B19: =SUM(B12:B14) -> 9.3710341 | C19: =SUM(C12:C14) -> 5.2586511 | D19: =SUM(D12:D14) -> 2.969201 | E19: =SUM(E12:E14) -> 5.9593963 | F19: =SUM(F12:F14) -> 3.6109404 | G19: =SUM(G12:G14) -> 2.969201 | H19: =SUM(H12:H14) -> 4.7585019 | I19: =SUM(I12:I14) -> 3.330479 | J19: =SUM(J12:J14) -> 2.969201 | K19: ct/kWh
A20: LCOE | B20: =B19*10 -> 93.710341 | C20: =C19*10 -> 52.586511 | D20: =D19*10 -> 29.69201 | E20: =E19*10 -> 59.593963 | F20: =F19*10 -> 36.109404 | G20: =G19*10 -> 29.69201 | H20: =H19*10 -> 47.585019 | I20: =I19*10 -> 33.30479 | J20: =J19*10 -> 29.69201 | K20: €/MWh
A22: Lifetime | B22: 25 | C22: 20 | D22: 50 | E22: 25 | F22: 20 | G22: 50 | H22: 25 | I22: 20 | J22: 50 | K22: years | M22: WACC
A23: UCRF | B23: =(B$1*(1+B$1)^B22)/((1+B$1)^B22-1) -> 0.078226718 | C23: =(C$1*(1+C$1)^C22)/((1+C$1)^C22-1) -> 0.087184557 | D23: =(D$1*(1+D$1)^D22)/((1+D$1)^D22-1) -> 0.063444286 | E23: =(E$1*(1+E$1)^E22)/((1+E$1)^E22-1) -> 0.078226718 | F23: =(F$1*(1+F$1)^F22)/((1+F$1)^F22-1) -> 0.087184557 | G23: =(G$1*(1+G$1)^G22)/((1+G$1)^G22-1) -> 0.063444286 | H23: =(H$1*(1+H$1)^H22)/((1+H$1)^H22-1) -> 0.078226718 | I23: =(I$1*(1+I$1)^I22)/((1+I$1)^I22-1) -> 0.087184557 | J23: =(J$1*(1+J$1)^J22)/((1+J$1)^J22-1) -> 0.063444286 | K23: - | M23: WACC
A25: UCRF_alternative | B25: =(B$2*(1+B$2)^B22)/((1+B$2)^B22-1) -> 0.078226718 | C25: =(C$2*(1+C$2)^C22)/((1+C$2)^C22-1) -> 0.087184557 | D25: =(D$2*(1+D$2)^D22)/((1+D$2)^D22-1) -> 0.063444286 | E25: =(E$2*(1+E$2)^E22)/((1+E$2)^E22-1) -> 0.078226718 | F25: =(F$2*(1+F$2)^F22)/((1+F$2)^F22-1) -> 0.087184557 | G25: =(G$2*(1+G$2)^G22)/((1+G$2)^G22-1) -> 0.063444286 | H25: =(H$2*(1+H$2)^H22)/((1+H$2)^H22-1) -> 0.078226718 | I25: =(I$2*(1+I$2)^I22)/((1+I$2)^I22-1) -> 0.087184557 | J25: =(J$2*(1+J$2)^J22)/((1+J$2)^J22-1) -> 0.063444286 | K25: - | M25: WACC
A26: Capex generation_alternative | B26: =B12/B23*B25 -> 5.6892159 | C26: =C12/C23*C25 -> 4.0867761 | D26: =D12/D23*D25 -> 2.1299153 | E26: =E12/E23*E25 -> 3.5557599 | F26: =F12/F23*F25 -> 2.8062529 | G26: =G12/G23*G25 -> 2.1299153 | H26: =H12/H23*H25 -> 2.9335019 | I26: =I12/I23*I25 -> 2.5882915 | J26: =J12/J23*J25 -> 2.1299153 | K26: ct/kWh | M26: WACC
A27: LCOE_alternative | B27: =B19-B12+B26 -> 9.3710341 | C27: =C19-C12+C26 -> 5.2586511 | D27: =D19-D12+D26 -> 2.969201 | E27: =E19-E12+E26 -> 5.9593963 | F27: =F19-F12+F26 -> 3.6109404 | G27: =G19-G12+G26 -> 2.969201 | H27: =H19-H12+H26 -> 4.7585019 | I27: =I19-I12+I26 -> 3.330479 | J27: =J19-J12+J26 -> 2.969201 | K27: ct/kWh
A29: Levelized cost of hydrogen [ct/kWh]
B31: 2020 | E31: 2035 | H31: 2050
B32: Offshore | C32: Onshore | D32: Hydro | E32: Offshore | F32: Onshore | G32: Hydro | H32: Offshore | I32: Onshore | J32: Hydro
A33: Capex electrolysis | B33: 3.0462118 | C33: 4.1885412 | D33: 1.9147617 | E33: 1.3931149 | F33: 1.915533 | G33: 0.87567222 | H33: 0.81260441 | I33: 1.1173311 | J33: 0.51077992 | K33: ct/kWh
A34: Opex electrolysis | B34: 1.1682243 | C34: 1.6063084 | D34: 0.73431242 | E34: 0.53426052 | F34: 0.73460821 | G34: 0.3358209 | H34: 0.31163435 | I34: 0.42849723 | J34: 0.19588445 | K34: ct/kWh
A35: Electricity cost | B35: 14.596626 | C35: 8.1910453 | D35: 4.6249237 | E35: 8.8946213 | F35: 5.3894633 | G35: 4.4316433 | H35: 6.5907229 | I35: 4.6128518 | J35: 4.1124668 | K35: ct/kWh
A36: Storage cost | B36: 2.9792732 | C36: 2.9792732 | D36: 2.9792732 | E36: 2.3792732 | F36: 2.3792732 | G36: 2.3792732 | H36: 1.9792732 | I36: 1.9792732 | J36: 1.9792732 | K36: ct/kWh
A37: Liquefaction cost | B37: 3.7938486 | C37: 3.7938486 | D37: 3.7938486 | E37: 2.1404261 | F37: 2.1404261 | G37: 2.1404261 | H37: 1.4308452 | I37: 1.4308452 | J37: 1.4308452 | K37: ct/kWh
A38: Distribution cost | B38: 0.225 | C38: 0.225 | D38: 0.225 | E38: 0.195 | F38: 0.195 | G38: 0.195 | H38: 0.1875 | I38: 0.1875 | J38: 0.1875 | K38: ct/kWh
A40: BC | B40: 5.0944468 | C40: 4.5421905 | D40: 2.3451036 | E40: 4.0195481 | F40: 3.9103357 | G40: 2.0092187 | H40: 3.0022965 | I40: 2.7698807 | J40: 1.3897171 | K40: ct/kWh
A41: WC | B41: 6.2445545 | C41: 5.9119403 | D41: 3.4038153 | E41: 4.7428356 | F41: 5.0150862 | G41: 2.5555799 | H41: 4.1084781 | I41: 4.0463644 | J41: 2.3824229 | K41: ct/kWh
A43: LCOH | B43: =SUM(B33:B38) -> 25.809184 | C43: =SUM(C33:C38) -> 20.984017 | D43: =SUM(D33:D38) -> 14.27212 | E43: =SUM(E33:E38) -> 15.536696 | F43: =SUM(F33:F38) -> 12.754304 | G43: =SUM(G33:G38) -> 10.357836 | H43: =SUM(H33:H38) -> 11.31258 | I43: =SUM(I33:I38) -> 9.7562986 | J43: =SUM(J33:J38) -> 8.4167496 | K43: ct/kWh
A45: Electricity consumption | B45: =B35/B19 -> 1.5576324 | C45: =C35/C19 -> 1.5576324 | D45: =D35/D19 -> 1.5576324 | E45: =E35/E19 -> 1.4925373 | F45: =F35/F19 -> 1.4925373 | G45: =G35/G19 -> 1.4925373 | H45: =H35/H19 -> 1.3850416 | I45: =I35/I19 -> 1.3850416 | J45: =J35/J19 -> 1.3850416 | K45: kWh_el/kWh_fuel | M45: LCOE
A47: Lifetime | B47: 25 | C47: 25 | D47: 25 | E47: 25 | F47: 25 | G47: 25 | H47: 25 | I47: 25 | J47: 25 | K47: years | M47: WACC
A48: UCRF | B48: =(B$1*(1+B$1)^B47)/((1+B$1)^B47-1) -> 0.078226718 | C48: =(C$1*(1+C$1)^C47)/((1+C$1)^C47-1) -> 0.078226718 | D48: =(D$1*(1+D$1)^D47)/((1+D$1)^D47-1) -> 0.078226718 | E48: =(E$1*(1+E$1)^E47)/((1+E$1)^E47-1) -> 0.078226718 | F48: =(F$1*(1+F$1)^F47)/((1+F$1)^F47-1) -> 0.078226718 | G48: =(G$1*(1+G$1)^G47)/((1+G$1)^G47-1) -> 0.078226718 | H48: =(H$1*(1+H$1)^H47)/((1+H$1)^H47-1) -> 0.078226718 | I48: =(I$1*(1+I$1)^I47)/((1+I$1)^I47-1) -> 0.078226718 | J48: =(J$1*(1+J$1)^J47)/((1+J$1)^J47-1) -> 0.078226718 | K48: - | M48: WACC
A50: UCRF_alternative | B50: =(B$2*(1+B$2)^B47)/((1+B$2)^B47-1) -> 0.078226718 | C50: =(C$2*(1+C$2)^C47)/((1+C$2)^C47-1) -> 0.078226718 | D50: =(D$2*(1+D$2)^D47)/((1+D$2)^D47-1) -> 0.078226718 | E50: =(E$2*(1+E$2)^E47)/((1+E$2)^E47-1) -> 0.078226718 | F50: =(F$2*(1+F$2)^F47)/((1+F$2)^F47-1) -> 0.078226718 | G50: =(G$2*(1+G$2)^G47)/((1+G$2)^G47-1) -> 0.078226718 | H50: =(H$2*(1+H$2)^H47)/((1+H$2)^H47-1) -> 0.078226718 | I50: =(I$2*(1+I$2)^I47)/((1+I$2)^I47-1) -> 0.078226718 | J50: =(J$2*(1+J$2)^J47)/((1+J$2)^J47-1) -> 0.078226718 | K50: - | M50: WACC
A51: Electricity cost_alternative | B51: =B45*B3 -> 14.596626 | C51: =C45*C3 -> 8.1910453 | D51: =D45*D3 -> 4.6249237 | E51: =E45*E3 -> 8.8946213 | F51: =F45*F3 -> 5.3894633 | G51: =G45*G3 -> 4.4316433 | H51: =H45*H3 -> 6.5907229 | I51: =I45*I3 -> 4.6128518 | J51: =J45*J3 -> 4.1124668 | K51: ct/kWh | M51: LCOE
A52: Capex electrolysis_alternative | B52: =B33/B48*B50 -> 3.0462118 | C52: =C33/C48*C50 -> 4.1885412 | D52: =D33/D48*D50 -> 1.9147617 | E52: =E33/E48*E50 -> 1.3931149 | F52: =F33/F48*F50 -> 1.915533 | G52: =G33/G48*G50 -> 0.87567222 | H52: =H33/H48*H50 -> 0.81260441 | I52: =I33/I48*I50 -> 1.1173311 | J52: =J33/J48*J50 -> 0.51077992 | K52: ct/kWh | M52: WACC
A53: LCOH_alternative | B53: =B43-B33+B52-B35+B51 -> 25.809184 | C53: =C43-C33+C52-C35+C51 -> 20.984017 | D53: =D43-D33+D52-D35+D51 -> 14.27212 | E53: =E43-E33+E52-E35+E51 -> 15.536696 | F53: =F43-F33+F52-F35+F51 -> 12.754304 | G53: =G43-G33+G52-G35+G51 -> 10.357836 | H53: =H43-H33+H52-H35+H51 -> 11.31258 | I53: =I43-I33+I52-I35+I51 -> 9.7562986 | J53: =J43-J33+J52-J35+J51 -> 8.4167496 | K53: ct/kWh
A55: Levelized cost of ammonia [ct/kWh]
B57: 2020 | E57: 2035 | H57: 2050
B58: Offshore | C58: Onshore | D58: Hydro | E58: Offshore | F58: Onshore | G58: Hydro | H58: Offshore | I58: Onshore | J58: Hydro
A59: Electrolysis & storage cost | B59: 5.8617929 | C59: 7.6454453 | D59: 4.0951278 | E59: 3.2806198 | F59: 4.0963321 | G59: 2.4726761 | H59: 2.374201 | I59: 2.8500063 | J59: 1.9029271 | K59: ct/kWh
A60: Electricity cost electrolysis | B60: 16.47373 | C60: 9.2444014 | D60: 5.2196819 | E60: 10.038456 | F60: 6.0825401 | G60: 5.001546 | H60: 7.4382799 | I60: 5.2060576 | J60: 4.6413238 | K60: ct/kWh
A61: Capex synthesis | B61: 0.90398361 | C61: 0.90398361 | D61: 0.90398361 | E61: 0.90398361 | F61: 0.90398361 | G61: 0.90398361 | H61: 0.90398361 | I61: 0.90398361 | J61: 0.90398361 | K61: ct/kWh
A62: Opex synthesis | B62: 0.62215909 | C62: 0.62215909 | D62: 0.62215909 | E62: 0.62215909 | F62: 0.62215909 | G62: 0.62215909 | H62: 0.62215909 | I62: 0.62215909 | J62: 0.62215909 | K62: ct/kWh
A63: Electricity costs synthesis | B63: 0.1375 | C63: 0.1375 | D63: 0.1375 | E63: 0.1375 | F63: 0.1375 | G63: 0.1375 | H63: 0.1375 | I63: 0.1375 | J63: 0.325 | K63: ct/kWh
A64: Storage cost | B64: 0.325 | C64: 0.325 | D64: 0.325 | E64: 0.325 | F64: 0.325 | G64: 0.325 | H64: 0.325 | I64: 0.325 | J64: 0.325 | K64: ct/kWh
A65: Distribution cost | B65: 0.0625 | C65: 0.0625 | D65: 0.0625 | E65: 0.04625 | F65: 0.04625 | G65: 0.04625 | H65: 0.0375 | I65: 0.0375 | J65: 0.0375 | K65: ct/kWh
A67: BC | B67: 5.6659076 | C67: 5.0426319 | D67: 2.563003 | E67: 4.1720267 | F67: 4.0487697 | G67: 1.903172 | H67: 3.3808903 | I67: 3.1185862 | J67: 1.5609356 | K67: ct/kWh
A68: WC | B68: 6.9639174 | C68: 6.5885295 | D68: 3.7578634 | E68: 5.3391657 | F68: 5.6464272 | G68: 2.8706322 | H68: 4.2165748 | I68: 4.1464734 | J68: 2.2685515 | K68: ct/kWh
A70: LCOA | B70: =SUM(B59:B65) -> 24.386666 | C70: =SUM(C59:C65) -> 18.940989 | D70: =SUM(D59:D65) -> 11.365952 | E70: =SUM(E59:E65) -> 15.353969 | F70: =SUM(F59:F65) -> 12.213765 | G70: =SUM(G59:G65) -> 9.5091148 | H70: =SUM(H59:H65) -> 11.838624 | I70: =SUM(I59:I65) -> 10.082207 | J70: =SUM(J59:J65) -> 8.7578936 | K70: ct/kWh
N71: eAmmonia
A72: Electricity consumption | B72: =(B60+B63)/B19 -> 1.7726144 | C72: =(C60+C63)/C19 -> 1.784089 | D72: =(D60+D63)/D19 -> 1.8042503 | E72: =(E60+E63)/E19 -> 1.7075482 | F72: =(F60+F63)/F19 -> 1.7225541 | G72: =(G60+G63)/G19 -> 1.7307841 | H72: =(H60+H63)/H19 -> 1.5920514 | I72: =(I60+I63)/I19 -> 1.6044411 | J72: =(J60+J63)/J19 -> 1.6726129 | K72: kWh_el/kWh_fuel | M72: LCOE | N72: 738 | O72: kWh_el/t_fuel
N73: 5.28 | O73: kWh_fuel/kg_fuel
A74: Lifetime | B74: 30 | C74: 30 | D74: 30 | E74: 30 | F74: 30 | G74: 30 | H74: 30 | I74: 30 | J74: 30 | K74: years | M74: WACC | N74: =N73/1000 -> 0.00528 | O74: kWh_fuel/t_fuel
A75: UCRF | B75: =(B$1*(1+B$1)^B74)/((1+B$1)^B74-1) -> 0.072648911 | C75: =(C$1*(1+C$1)^C74)/((1+C$1)^C74-1) -> 0.072648911 | D75: =(D$1*(1+D$1)^D74)/((1+D$1)^D74-1) -> 0.072648911 | E75: =(E$1*(1+E$1)^E74)/((1+E$1)^E74-1) -> 0.072648911 | F75: =(F$1*(1+F$1)^F74)/((1+F$1)^F74-1) -> 0.072648911 | G75: =(G$1*(1+G$1)^G74)/((1+G$1)^G74-1) -> 0.072648911 | H75: =(H$1*(1+H$1)^H74)/((1+H$1)^H74-1) -> 0.072648911 | I75: =(I$1*(1+I$1)^I74)/((1+I$1)^I74-1) -> 0.072648911 | J75: =(J$1*(1+J$1)^J74)/((1+J$1)^J74-1) -> 0.072648911 | K75: - | M75: WACC | N75: 0.99 | O75: Efficiency
N76: =N72/N74*0.99 -> 138375 | O76: kWh_el/kWh_fuel
A77: UCRF_alternative | B77: =(B$2*(1+B$2)^B74)/((1+B$2)^B74-1) -> 0.072648911 | C77: =(C$2*(1+C$2)^C74)/((1+C$2)^C74-1) -> 0.072648911 | D77: =(D$2*(1+D$2)^D74)/((1+D$2)^D74-1) -> 0.072648911 | E77: =(E$2*(1+E$2)^E74)/((1+E$2)^E74-1) -> 0.072648911 | F77: =(F$2*(1+F$2)^F74)/((1+F$2)^F74-1) -> 0.072648911 | G77: =(G$2*(1+G$2)^G74)/((1+G$2)^G74-1) -> 0.072648911 | H77: =(H$2*(1+H$2)^H74)/((1+H$2)^H74-1) -> 0.072648911 | I77: =(I$2*(1+I$2)^I74)/((1+I$2)^I74-1) -> 0.072648911 | J77: =(J$2*(1+J$2)^J74)/((1+J$2)^J74-1) -> 0.072648911 | K77: - | M77: WACC
A78: Electricity cost_alternative | B78: =B72*B3 -> 16.61123 | C78: =C72*C3 -> 9.3819014 | D78: =D72*D3 -> 5.3571819 | E78: =E72*E3 -> 10.175956 | F78: =F72*F3 -> 6.2200401 | G78: =G72*G3 -> 5.139046 | H78: =H72*H3 -> 7.5757799 | I78: =I72*I3 -> 5.3435576 | J78: =J72*J3 -> 4.9663238 | K78: ct/kWh | M78: LCOE
A79: Capex electrolysis_alternative | B79: =B61/B75*B77 -> 0.90398361 | C79: =C61/C75*C77 -> 0.90398361 | D79: =D61/D75*D77 -> 0.90398361 | E79: =E61/E75*E77 -> 0.90398361 | F79: =F61/F75*F77 -> 0.90398361 | G79: =G61/G75*G77 -> 0.90398361 | H79: =H61/H75*H77 -> 0.90398361 | I79: =I61/I75*I77 -> 0.90398361 | J79: =J61/J75*J77 -> 0.90398361 | K79: ct/kWh | M79: WACC
A80: LCOA_alternative | B80: =B70-B60-B63+B79-B61+B78 -> 24.386666 | C80: =C70-C60-C63+C79-C61+C78 -> 18.940989 | D80: =D70-D60-D63+D79-D61+D78 -> 11.365952 | E80: =E70-E60-E63+E79-E61+E78 -> 15.353969 | F80: =F70-F60-F63+F79-F61+F78 -> 12.213765 | G80: =G70-G60-G63+G79-G61+G78 -> 9.5091148 | H80: =H70-H60-H63+H79-H61+H78 -> 11.838624 | I80: =I70-I60-I63+I79-I61+I78 -> 10.082207 | J80: =J70-J60-J63+J79-J61+J78 -> 8.7578936 | K80: ct/kWh | M80: WACC
A82: Levelized cost of e-fuel [ct/kWh]
B84: 2020 | E84: 2035 | H84: 2050
B85: Offshore | C85: Onshore | D85: Hydro | E85: Offshore | F85: Onshore | G85: Hydro | H85: Offshore | I85: Onshore | J85: Hydro
A86: Electrolysis & storage cost | B86: 6.4923365 | C86: 8.4678535 | D86: 4.5356341 | E86: 3.6335107 | F86: 4.5369679 | G86: 2.7386579 | H86: 2.6295899 | I86: 3.1565768 | J86: 2.1076219 | K86: ct/kWh
A87: Electricity cost electrolysis | B87: 18.245783 | C87: 10.238807 | D87: 5.7811547 | E87: 11.118277 | F87: 6.7368292 | G87: 5.5395542 | H87: 8.2384036 | I87: 5.7660648 | J87: 5.1405835 | K87: ct/kWh
A88: Capex synthesis | B88: 0.78226718 | C88: 0.78226718 | D88: 0.78226718 | E88: 0.51336284 | F88: 0.51336284 | G88: 0.51336284 | H88: 0.39113359 | I88: 0.39113359 | J88: 0.39113359 | K88: ct/kWh
A89: Opex synthesis | B89: 0.35 | C89: 0.35 | D89: 0.35 | E89: 0.2296875 | F89: 0.2296875 | G89: 0.2296875 | H89: 0.175 | I89: 0.175 | J89: 0.175 | K89: ct/kWh
A90: Electricity costs synthesis | B90: 0.12375 | C90: 0.12375 | D90: 0.12375 | E90: 0.12375 | F90: 0.12375 | G90: 0.12375 | H90: 0.12375 | I90: 0.12375 | J90: 0.12375 | K90: ct/kWh
A91: CO2 cost | B91: 15.686 | C91: 15.686 | D91: 15.686 | E91: 4.6035 | F91: 4.6035 | G91: 4.6035 | H91: 2.728 | I91: 2.728 | J91: 2.728 | K91: ct/kWh
A92: Storage costs | B92: 0.04 | C92: 0.04 | D92: 0.04 | E92: 0.04 | F92: 0.04 | G92: 0.04 | H92: 0.04 | I92: 0.04 | J92: 0.04 | K92: ct/kWh
A93: Distribution cost | B93: 0.0375 | C93: 0.0375 | D93: 0.0375 | E93: 0.02125 | F93: 0.02125 | G93: 0.02125 | H93: 0.0125 | I93: 0.0125 | J93: 0.0125 | K93: ct/kWh
A95: BC | B95: 9.4671086 | C95: 8.7767882 | D95: 6.0304296 | E95: 6.14035 | F95: 6.0038345 | G95: 3.6274383 | H95: 4.8195291 | I95: 4.5290093 | J95: 2.8038048 | K95: ct/kWh
A96: WC | B96: 10.904743 | C96: 10.488975 | D96: 7.3538193 | E96: 7.6241064 | F96: 7.9644196 | G96: 4.8900367 | H96: 6.0281736 | I96: 5.9505315 | J96: 3.8706046 | K96: ct/kWh
A98: LCOEF | B98: =SUM(B86:B93) -> 41.757637 | C98: =SUM(C86:C93) -> 35.726177 | D98: =SUM(D86:D93) -> 27.336306 | E98: =SUM(E86:E93) -> 20.283338 | F98: =SUM(F86:F93) -> 16.805347 | G98: =SUM(G86:G93) -> 13.809762 | H98: =SUM(H86:H93) -> 14.338377 | I98: =SUM(I86:I93) -> 12.393025 | J98: =SUM(J86:J93) -> 10.718589 | K98: ct/kWh
A100: Electricity consumption | B100: =(B87+B90)/B19 -> 1.9602461 | C100: =(C87+C90)/C19 -> 1.9705731 | D100: =(D87+D90)/D19 -> 1.9887184 | E100: =(E87+E90)/E19 -> 1.8864372 | F100: =(F87+F90)/F19 -> 1.8999425 | G100: =(G87+G90)/G19 -> 1.9073495 | H100: =(H87+H90)/H19 -> 1.757308 | I100: =(I87+I90)/I19 -> 1.7684588 | J100: =(J87+J90)/J19 -> 1.7729798 | K100: kWh_el/kWh_fuel
A102: Lifetime | B102: 25 | C102: 25 | D102: 25 | E102: 25 | F102: 25 | G102: 25 | H102: 25 | I102: 25 | J102: 25 | K102: years
A103: UCRF | B103: =(B$1*(1+B$1)^B102)/((1+B$1)^B102-1) -> 0.078226718 | C103: =(C$1*(1+C$1)^C102)/((1+C$1)^C102-1) -> 0.078226718 | D103: =(D$1*(1+D$1)^D102)/((1+D$1)^D102-1) -> 0.078226718 | E103: =(E$1*(1+E$1)^E102)/((1+E$1)^E102-1) -> 0.078226718 | F103: =(F$1*(1+F$1)^F102)/((1+F$1)^F102-1) -> 0.078226718 | G103: =(G$1*(1+G$1)^G102)/((1+G$1)^G102-1) -> 0.078226718 | H103: =(H$1*(1+H$1)^H102)/((1+H$1)^H102-1) -> 0.078226718 | I103: =(I$1*(1+I$1)^I102)/((1+I$1)^I102-1) -> 0.078226718 | J103: =(J$1*(1+J$1)^J102)/((1+J$1)^J102-1) -> 0.078226718 | K103: -
A105: UCRF_alternative | B105: =(B$2*(1+B$2)^B102)/((1+B$2)^B102-1) -> 0.078226718 | C105: =(C$2*(1+C$2)^C102)/((1+C$2)^C102-1) -> 0.078226718 | D105: =(D$2*(1+D$2)^D102)/((1+D$2)^D102-1) -> 0.078226718 | E105: =(E$2*(1+E$2)^E102)/((1+E$2)^E102-1) -> 0.078226718 | F105: =(F$2*(1+F$2)^F102)/((1+F$2)^F102-1) -> 0.078226718 | G105: =(G$2*(1+G$2)^G102)/((1+G$2)^G102-1) -> 0.078226718 | H105: =(H$2*(1+H$2)^H102)/((1+H$2)^H102-1) -> 0.078226718 | I105: =(I$2*(1+I$2)^I102)/((1+I$2)^I102-1) -> 0.078226718 | J105: =(J$2*(1+J$2)^J102)/((1+J$2)^J102-1) -> 0.078226718 | K105: -
A106: Electricity cost_alternative | B106: =B100*B3 -> 18.369533 | C106: =C100*C3 -> 10.362557 | D106: =D100*D3 -> 5.9049047 | E106: =E100*E3 -> 11.242027 | F106: =F100*F3 -> 6.8605792 | G106: =G100*G3 -> 5.6633042 | H106: =H100*H3 -> 8.3621536 | I106: =I100*I3 -> 5.8898148 | J106: =J100*J3 -> 5.2643335 | K106: ct/kWh
A107: Capex electrolysis_alternative | B107: =B88/B103*B105 -> 0.78226718 | C107: =C88/C103*C105 -> 0.78226718 | D107: =D88/D103*D105 -> 0.78226718 | E107: =E88/E103*E105 -> 0.51336284 | F107: =F88/F103*F105 -> 0.51336284 | G107: =G88/G103*G105 -> 0.51336284 | H107: =H88/H103*H105 -> 0.39113359 | I107: =I88/I103*I105 -> 0.39113359 | J107: =J88/J103*J105 -> 0.39113359 | K107: ct/kWh
A109: CO2 cost_alternative | B109: =B91/B5*B6 -> 15.686 | C109: =C91/C5*C6 -> 15.686 | D109: =D91/D5*D6 -> 15.686 | E109: =E91/E5*E6 -> 4.6035 | F109: =F91/F5*F6 -> 4.6035 | G109: =G91/G5*G6 -> 4.6035 | H109: =H91/H5*H6 -> 2.728 | I109: =I91/I5*I6 -> 2.728 | J109: =J91/J5*J6 -> 2.728 | K109: ct/kWh
A111: LCOEF_alternative | B111: =B98-B87-B90+B106-B88+B107-B91+B109 -> 41.757637 | C111: =C98-C87-C90+C106-C88+C107-C91+C109 -> 35.726177 | D111: =D98-D87-D90+D106-D88+D107-D91+D109 -> 27.336306 | E111: =E98-E87-E90+E106-E88+E107-E91+E109 -> 20.283338 | F111: =F98-F87-F90+F106-F88+F107-F91+F109 -> 16.805347 | G111: =G98-G87-G90+G106-G88+G107-G91+G109 -> 13.809762 | H111: =H98-H87-H90+H106-H88+H107-H91+H109 -> 14.338377 | I111: =I98-I87-I90+I106-I88+I107-I91+I109 -> 12.393025 | J111: =J98-J87-J90+J106-J88+J107-J91+J109 -> 10.718589 | K111: ct/kWh
A112: LCOEF_alternative | B112: =B111/3.6 -> 11.599343 | C112: =C111/3.6 -> 9.9239381 | D112: =D111/3.6 -> 7.5934183 | E112: =E111/3.6 -> 5.6342605 | F112: =F111/3.6 -> 4.6681521 | G112: =G111/3.6 -> 3.8360451 | H112: =H111/3.6 -> 3.9828825 | I112: =I111/3.6 -> 3.442507 | J112: =J111/3.6 -> 2.9773858 | K112: ct/MJ
A113: LCOEF_alternative | B113: =B112*Inputs!$C$14 / 100 -> 4.0237659 | C113: =C112*Inputs!$C$14 / 100 -> 3.4425744 | D113: =D112*Inputs!$C$14 / 100 -> 2.6341264 | E113: =E112*Inputs!$C$14 / 100 -> 1.9545024 | F113: =F112*Inputs!$C$14 / 100 -> 1.6193633 | G113: =G112*Inputs!$C$14 / 100 -> 1.3307087 | H113: =H112*Inputs!$C$14 / 100 -> 1.381646 | I113: =I112*Inputs!$C$14 / 100 -> 1.1941919 | J113: =J112*Inputs!$C$14 / 100 -> 1.0328432 | K113: €/l

Sheet LCOE Corrected LCOF
A1: WACC_source | B1: 0.06 | C1: 0.06 | D1: 0.06 | E1: 0.06 | F1: 0.06 | G1: 0.06 | H1: 0.06 | I1: 0.06 | J1: 0.06 | K1: -
A2: WACC_alternative | B2: 0.06 | C2: 0.06 | D2: 0.06 | E2: 0.06 | F2: 0.06 | G2: 0.06 | H2: 0.06 | I2: 0.06 | J2: 0.06 | K2: -
A3: LCOE_alternative | B3: =Inputs!$C$8*Inputs!$C$6 / 10 -> 5.76 | C3: =Inputs!$C$8*Inputs!$C$6 / 10 -> 5.76 | D3: =Inputs!$C$8*Inputs!$C$6 / 10 -> 5.76 | E3: 5.9593963 | F3: 3.6109404 | G3: 2.969201 | H3: =Inputs!$C$9*Inputs!$C$6 / 10 -> 0.99 | I3: =Inputs!$C$9*Inputs!$C$6 / 10 -> 0.99 | J3: =Inputs!$C$9*Inputs!$C$6 / 10 -> 0.99 | K3: ct/kWh
B4: 11.1 | C4: 11.1 | D4: 11.1 | E4: 7.5 | F4: 7.5 | G4: 7.5 | H4: 3.9 | I4: 3.9 | J4: 3.9 | L4: Note: this is the standard LCOE curve
A5: DAC_source | B5: 460 | C5: 460 | D5: 460 | E5: 135 | F5: 135 | G5: 135 | H5: 80 | I5: 80 | J5: 80 | K5: €/tCO2
A6: DAC_alternative | B6: 460 | C6: 460 | D6: 460 | E6: 135 | F6: 135 | G6: 135 | H6: 80 | I6: 80 | J6: 80 | K6: €/tCO2 | L6: Average between SS and LS DAC
B7: 731.19867 | C7: 731.19867 | D7: 731.19867 | E7: 449.5681 | F7: 449.5681 | G7: 449.5681 | H7: 298.29332 | I7: 298.29332 | J7: 298.29332 | L7: Note: this is modelled DAC cost
A8: Levelized cost of electricity [ct/kWh]
B10: 2020 | E10: 2035 | H10: 2050
B11: Offshore | C11: Onshore | D11: Hydro | E11: Offshore | F11: Onshore | G11: Hydro | H11: Offshore | I11: Onshore | J11: Hydro | N11: 2020 Offshore | O11: 2020 Onshore
A12: Capex generation | B12: 5.6892159 | C12: 4.0867761 | D12: 2.1299153 | E12: 3.5557599 | F12: 2.8062529 | G12: 2.1299153 | H12: 2.9335019 | I12: 2.5882915 | J12: 2.1299153 | K12: ct/kWh | M12: CAPEX | N12: 3200 | O12: 1500
A13: Opex generation | B13: 2.1818182 | C13: 1.171875 | D13: 0.83928571 | E13: 1.3636364 | F13: 0.8046875 | G13: 0.83928571 | H13: 1.125 | I13: 0.7421875 | J13: 0.83928571 | K13: ct/kWh | M13: Loadhours | N13: 4400 | O13: 3200
A14: Offshore grid fee | B14: 1.5 | C14: 0 | D14: 0 | E14: 1.04 | F14: 0 | G14: 0 | H14: 0.7 | I14: 0 | J14: 0 | K14: ct/kWh | M14: UCRF | N14: =B23 -> 0.078226718 | O14: =C23 -> 0.087184557
M15: Annualized CAPEX | N15: =N12*N14/N13 -> 0.056892159 | O15: =O12*O14/O13 -> 0.040867761 | P15: €/kWh
A16: BC | B16: 1.377431 | C16: 0.80426429 | D16: 0.37115013 | E16: 1.3238642 | F16: 1.1857743 | G16: 0.37115013 | H16: 1.292708 | I16: 1.020797 | J16: 0.37115013 | K16: ct/kWh | N16: =N15*100 -> 5.6892159 | O16: =O15*100 -> 4.0867761 | P16: ct/kWh
A17: WC | B17: 1.4414975 | C17: 0.91149953 | D17: 0.49486684 | E17: 1.3602703 | F17: 1.3812724 | G17: 0.49486684 | H17: 1.352834 | I17: 1.1569032 | J17: 0.49486684 | K17: ct/kWh
A19: LCOE | B19: =SUM(B12:B14) -> 9.3710341 | C19: =SUM(C12:C14) -> 5.2586511 | D19: =SUM(D12:D14) -> 2.969201 | E19: =SUM(E12:E14) -> 5.9593963 | F19: =SUM(F12:F14) -> 3.6109404 | G19: =SUM(G12:G14) -> 2.969201 | H19: =SUM(H12:H14) -> 4.7585019 | I19: =SUM(I12:I14) -> 3.330479 | J19: =SUM(J12:J14) -> 2.969201 | K19: ct/kWh
A20: LCOE | B20: =B19*10 -> 93.710341 | C20: =C19*10 -> 52.586511 | D20: =D19*10 -> 29.69201 | E20: =E19*10 -> 59.593963 | F20: =F19*10 -> 36.109404 | G20: =G19*10 -> 29.69201 | H20: =H19*10 -> 47.585019 | I20: =I19*10 -> 33.30479 | J20: =J19*10 -> 29.69201 | K20: €/MWh
A22: Lifetime | B22: 25 | C22: 20 | D22: 50 | E22: 25 | F22: 20 | G22: 50 | H22: 25 | I22: 20 | J22: 50 | K22: years | M22: WACC
A23: UCRF | B23: =(B$1*(1+B$1)^B22)/((1+B$1)^B22-1) -> 0.078226718 | C23: =(C$1*(1+C$1)^C22)/((1+C$1)^C22-1) -> 0.087184557 | D23: =(D$1*(1+D$1)^D22)/((1+D$1)^D22-1) -> 0.063444286 | E23: =(E$1*(1+E$1)^E22)/((1+E$1)^E22-1) -> 0.078226718 | F23: =(F$1*(1+F$1)^F22)/((1+F$1)^F22-1) -> 0.087184557 | G23: =(G$1*(1+G$1)^G22)/((1+G$1)^G22-1) -> 0.063444286 | H23: =(H$1*(1+H$1)^H22)/((1+H$1)^H22-1) -> 0.078226718 | I23: =(I$1*(1+I$1)^I22)/((1+I$1)^I22-1) -> 0.087184557 | J23: =(J$1*(1+J$1)^J22)/((1+J$1)^J22-1) -> 0.063444286 | K23: - | M23: WACC
A25: UCRF_alternative | B25: =(B$2*(1+B$2)^B22)/((1+B$2)^B22-1) -> 0.078226718 | C25: =(C$2*(1+C$2)^C22)/((1+C$2)^C22-1) -> 0.087184557 | D25: =(D$2*(1+D$2)^D22)/((1+D$2)^D22-1) -> 0.063444286 | E25: =(E$2*(1+E$2)^E22)/((1+E$2)^E22-1) -> 0.078226718 | F25: =(F$2*(1+F$2)^F22)/((1+F$2)^F22-1) -> 0.087184557 | G25: =(G$2*(1+G$2)^G22)/((1+G$2)^G22-1) -> 0.063444286 | H25: =(H$2*(1+H$2)^H22)/((1+H$2)^H22-1) -> 0.078226718 | I25: =(I$2*(1+I$2)^I22)/((1+I$2)^I22-1) -> 0.087184557 | J25: =(J$2*(1+J$2)^J22)/((1+J$2)^J22-1) -> 0.063444286 | K25: - | M25: WACC
A26: Capex generation_alternative | B26: =B12/B23*B25 -> 5.6892159 | C26: =C12/C23*C25 -> 4.0867761 | D26: =D12/D23*D25 -> 2.1299153 | E26: =E12/E23*E25 -> 3.5557599 | F26: =F12/F23*F25 -> 2.8062529 | G26: =G12/G23*G25 -> 2.1299153 | H26: =H12/H23*H25 -> 2.9335019 | I26: =I12/I23*I25 -> 2.5882915 | J26: =J12/J23*J25 -> 2.1299153 | K26: ct/kWh | M26: WACC
A27: LCOE_alternative | B27: =B19-B12+B26 -> 9.3710341 | C27: =C19-C12+C26 -> 5.2586511 | D27: =D19-D12+D26 -> 2.969201 | E27: =E19-E12+E26 -> 5.9593963 | F27: =F19-F12+F26 -> 3.6109404 | G27: =G19-G12+G26 -> 2.969201 | H27: =H19-H12+H26 -> 4.7585019 | I27: =I19-I12+I26 -> 3.330479 | J27: =J19-J12+J26 -> 2.969201 | K27: ct/kWh
A29: Levelized cost of hydrogen [ct/kWh]
B31: 2020 | E31: 2035 | H31: 2050
B32: Offshore | C32: Onshore | D32: Hydro | E32: Offshore | F32: Onshore | G32: Hydro | H32: Offshore | I32: Onshore | J32: Hydro
A33: Capex electrolysis | B33: 3.0462118 | C33: 4.1885412 | D33: 1.9147617 | E33: 1.3931149 | F33: 1.915533 | G33: 0.87567222 | H33: 0.81260441 | I33: 1.1173311 | J33: 0.51077992 | K33: ct/kWh
A34: Opex electrolysis | B34: 1.1682243 | C34: 1.6063084 | D34: 0.73431242 | E34: 0.53426052 | F34: 0.73460821 | G34: 0.3358209 | H34: 0.31163435 | I34: 0.42849723 | J34: 0.19588445 | K34: ct/kWh
A35: Electricity cost | B35: 14.596626 | C35: 8.1910453 | D35: 4.6249237 | E35: 8.8946213 | F35: 5.3894633 | G35: 4.4316433 | H35: 6.5907229 | I35: 4.6128518 | J35: 4.1124668 | K35: ct/kWh
A36: Storage cost | B36: 2.9792732 | C36: 2.9792732 | D36: 2.9792732 | E36: 2.3792732 | F36: 2.3792732 | G36: 2.3792732 | H36: 1.9792732 | I36: 1.9792732 | J36: 1.9792732 | K36: ct/kWh
A37: Liquefaction cost | B37: 3.7938486 | C37: 3.7938486 | D37: 3.7938486 | E37: 2.1404261 | F37: 2.1404261 | G37: 2.1404261 | H37: 1.4308452 | I37: 1.4308452 | J37: 1.4308452 | K37: ct/kWh
A38: Distribution cost | B38: 0.225 | C38: 0.225 | D38: 0.225 | E38: 0.195 | F38: 0.195 | G38: 0.195 | H38: 0.1875 | I38: 0.1875 | J38: 0.1875 | K38: ct/kWh
A40: BC | B40: 5.0944468 | C40: 4.5421905 | D40: 2.3451036 | E40: 4.0195481 | F40: 3.9103357 | G40: 2.0092187 | H40: 3.0022965 | I40: 2.7698807 | J40: 1.3897171 | K40: ct/kWh
A41: WC | B41: 6.2445545 | C41: 5.9119403 | D41: 3.4038153 | E41: 4.7428356 | F41: 5.0150862 | G41: 2.5555799 | H41: 4.1084781 | I41: 4.0463644 | J41: 2.3824229 | K41: ct/kWh
A43: LCOH | B43: =SUM(B33:B38) -> 25.809184 | C43: =SUM(C33:C38) -> 20.984017 | D43: =SUM(D33:D38) -> 14.27212 | E43: =SUM(E33:E38) -> 15.536696 | F43: =SUM(F33:F38) -> 12.754304 | G43: =SUM(G33:G38) -> 10.357836 | H43: =SUM(H33:H38) -> 11.31258 | I43: =SUM(I33:I38) -> 9.7562986 | J43: =SUM(J33:J38) -> 8.4167496 | K43: ct/kWh
A45: Electricity consumption | B45: =B35/B19 -> 1.5576324 | C45: =C35/C19 -> 1.5576324 | D45: =D35/D19 -> 1.5576324 | E45: =E35/E19 -> 1.4925373 | F45: =F35/F19 -> 1.4925373 | G45: =G35/G19 -> 1.4925373 | H45: =H35/H19 -> 1.3850416 | I45: =I35/I19 -> 1.3850416 | J45: =J35/J19 -> 1.3850416 | K45: kWh_el/kWh_fuel | M45: LCOE
A47: Lifetime | B47: 25 | C47: 25 | D47: 25 | E47: 25 | F47: 25 | G47: 25 | H47: 25 | I47: 25 | J47: 25 | K47: years | M47: WACC
A48: UCRF | B48: =(B$1*(1+B$1)^B47)/((1+B$1)^B47-1) -> 0.078226718 | C48: =(C$1*(1+C$1)^C47)/((1+C$1)^C47-1) -> 0.078226718 | D48: =(D$1*(1+D$1)^D47)/((1+D$1)^D47-1) -> 0.078226718 | E48: =(E$1*(1+E$1)^E47)/((1+E$1)^E47-1) -> 0.078226718 | F48: =(F$1*(1+F$1)^F47)/((1+F$1)^F47-1) -> 0.078226718 | G48: =(G$1*(1+G$1)^G47)/((1+G$1)^G47-1) -> 0.078226718 | H48: =(H$1*(1+H$1)^H47)/((1+H$1)^H47-1) -> 0.078226718 | I48: =(I$1*(1+I$1)^I47)/((1+I$1)^I47-1) -> 0.078226718 | J48: =(J$1*(1+J$1)^J47)/((1+J$1)^J47-1) -> 0.078226718 | K48: - | M48: WACC
A50: UCRF_alternative | B50: =(B$2*(1+B$2)^B47)/((1+B$2)^B47-1) -> 0.078226718 | C50: =(C$2*(1+C$2)^C47)/((1+C$2)^C47-1) -> 0.078226718 | D50: =(D$2*(1+D$2)^D47)/((1+D$2)^D47-1) -> 0.078226718 | E50: =(E$2*(1+E$2)^E47)/((1+E$2)^E47-1) -> 0.078226718 | F50: =(F$2*(1+F$2)^F47)/((1+F$2)^F47-1) -> 0.078226718 | G50: =(G$2*(1+G$2)^G47)/((1+G$2)^G47-1) -> 0.078226718 | H50: =(H$2*(1+H$2)^H47)/((1+H$2)^H47-1) -> 0.078226718 | I50: =(I$2*(1+I$2)^I47)/((1+I$2)^I47-1) -> 0.078226718 | J50: =(J$2*(1+J$2)^J47)/((1+J$2)^J47-1) -> 0.078226718 | K50: - | M50: WACC
A51: Electricity cost_alternative | B51: =B45*B3 -> 8.9719626 | C51: =C45*C3 -> 8.9719626 | D51: =D45*D3 -> 8.9719626 | E51: =E45*E3 -> 8.8946213 | F51: =F45*F3 -> 5.3894633 | G51: =G45*G3 -> 4.4316433 | H51: =H45*H3 -> 1.3711911 | I51: =I45*I3 -> 1.3711911 | J51: =J45*J3 -> 1.3711911 | K51: ct/kWh | M51: LCOE
A52: Capex electrolysis_alternative | B52: =B33/B48*B50 -> 3.0462118 | C52: =C33/C48*C50 -> 4.1885412 | D52: =D33/D48*D50 -> 1.9147617 | E52: =E33/E48*E50 -> 1.3931149 | F52: =F33/F48*F50 -> 1.915533 | G52: =G33/G48*G50 -> 0.87567222 | H52: =H33/H48*H50 -> 0.81260441 | I52: =I33/I48*I50 -> 1.1173311 | J52: =J33/J48*J50 -> 0.51077992 | K52: ct/kWh | M52: WACC
A53: LCOH_alternative | B53: =B43-B33+B52-B35+B51 -> 20.18452 | C53: =C43-C33+C52-C35+C51 -> 21.764934 | D53: =D43-D33+D52-D35+D51 -> 18.619159 | E53: =E43-E33+E52-E35+E51 -> 15.536696 | F53: =F43-F33+F52-F35+F51 -> 12.754304 | G53: =G43-G33+G52-G35+G51 -> 10.357836 | H53: =H43-H33+H52-H35+H51 -> 6.0930483 | I53: =I43-I33+I52-I35+I51 -> 6.5146378 | J53: =J43-J33+J52-J35+J51 -> 5.6754739 | K53: ct/kWh
A55: Levelized cost of ammonia [ct/kWh]
B57: 2020 | E57: 2035 | H57: 2050
B58: Offshore | C58: Onshore | D58: Hydro | E58: Offshore | F58: Onshore | G58: Hydro | H58: Offshore | I58: Onshore | J58: Hydro
A59: Electrolysis & storage cost | B59: 5.8617929 | C59: 7.6454453 | D59: 4.0951278 | E59: 3.2806198 | F59: 4.0963321 | G59: 2.4726761 | H59: 2.374201 | I59: 2.8500063 | J59: 1.9029271 | K59: ct/kWh
A60: Electricity cost electrolysis | B60: 16.47373 | C60: 9.2444014 | D60: 5.2196819 | E60: 10.038456 | F60: 6.0825401 | G60: 5.001546 | H60: 7.4382799 | I60: 5.2060576 | J60: 4.6413238 | K60: ct/kWh
A61: Capex synthesis | B61: 0.90398361 | C61: 0.90398361 | D61: 0.90398361 | E61: 0.90398361 | F61: 0.90398361 | G61: 0.90398361 | H61: 0.90398361 | I61: 0.90398361 | J61: 0.90398361 | K61: ct/kWh
A62: Opex synthesis | B62: 0.62215909 | C62: 0.62215909 | D62: 0.62215909 | E62: 0.62215909 | F62: 0.62215909 | G62: 0.62215909 | H62: 0.62215909 | I62: 0.62215909 | J62: 0.62215909 | K62: ct/kWh
A63: Electricity costs synthesis | B63: 0.1375 | C63: 0.1375 | D63: 0.1375 | E63: 0.1375 | F63: 0.1375 | G63: 0.1375 | H63: 0.1375 | I63: 0.1375 | J63: 0.325 | K63: ct/kWh
A64: Storage cost | B64: 0.325 | C64: 0.325 | D64: 0.325 | E64: 0.325 | F64: 0.325 | G64: 0.325 | H64: 0.325 | I64: 0.325 | J64: 0.325 | K64: ct/kWh
A65: Distribution cost | B65: 0.0625 | C65: 0.0625 | D65: 0.0625 | E65: 0.04625 | F65: 0.04625 | G65: 0.04625 | H65: 0.0375 | I65: 0.0375 | J65: 0.0375 | K65: ct/kWh
A67: BC | B67: 5.6659076 | C67: 5.0426319 | D67: 2.563003 | E67: 4.1720267 | F67: 4.0487697 | G67: 1.903172 | H67: 3.3808903 | I67: 3.1185862 | J67: 1.5609356 | K67: ct/kWh
A68: WC | B68: 6.9639174 | C68: 6.5885295 | D68: 3.7578634 | E68: 5.3391657 | F68: 5.6464272 | G68: 2.8706322 | H68: 4.2165748 | I68: 4.1464734 | J68: 2.2685515 | K68: ct/kWh
A70: LCOA | B70: =SUM(B59:B65) -> 24.386666 | C70: =SUM(C59:C65) -> 18.940989 | D70: =SUM(D59:D65) -> 11.365952 | E70: =SUM(E59:E65) -> 15.353969 | F70: =SUM(F59:F65) -> 12.213765 | G70: =SUM(G59:G65) -> 9.5091148 | H70: =SUM(H59:H65) -> 11.838624 | I70: =SUM(I59:I65) -> 10.082207 | J70: =SUM(J59:J65) -> 8.7578936 | K70: ct/kWh
N71: eAmmonia
A72: Electricity consumption | B72: =(B60+B63)/B19 -> 1.7726144 | C72: =(C60+C63)/C19 -> 1.784089 | D72: =(D60+D63)/D19 -> 1.8042503 | E72: =(E60+E63)/E19 -> 1.7075482 | F72: =(F60+F63)/F19 -> 1.7225541 | G72: =(G60+G63)/G19 -> 1.7307841 | H72: =(H60+H63)/H19 -> 1.5920514 | I72: =(I60+I63)/I19 -> 1.6044411 | J72: =(J60+J63)/J19 -> 1.6726129 | K72: kWh_el/kWh_fuel | M72: LCOE | N72: 738 | O72: kWh_el/t_fuel
N73: 5.28 | O73: kWh_fuel/kg_fuel
A74: Lifetime | B74: 30 | C74: 30 | D74: 30 | E74: 30 | F74: 30 | G74: 30 | H74: 30 | I74: 30 | J74: 30 | K74: years | M74: WACC | N74: =N73/1000 -> 0.00528 | O74: kWh_fuel/t_fuel
A75: UCRF | B75: =(B$1*(1+B$1)^B74)/((1+B$1)^B74-1) -> 0.072648911 | C75: =(C$1*(1+C$1)^C74)/((1+C$1)^C74-1) -> 0.072648911 | D75: =(D$1*(1+D$1)^D74)/((1+D$1)^D74-1) -> 0.072648911 | E75: =(E$1*(1+E$1)^E74)/((1+E$1)^E74-1) -> 0.072648911 | F75: =(F$1*(1+F$1)^F74)/((1+F$1)^F74-1) -> 0.072648911 | G75: =(G$1*(1+G$1)^G74)/((1+G$1)^G74-1) -> 0.072648911 | H75: =(H$1*(1+H$1)^H74)/((1+H$1)^H74-1) -> 0.072648911 | I75: =(I$1*(1+I$1)^I74)/((1+I$1)^I74-1) -> 0.072648911 | J75: =(J$1*(1+J$1)^J74)/((1+J$1)^J74-1) -> 0.072648911 | K75: - | M75: WACC | N75: 0.99 | O75: Efficiency
N76: =N72/N74*0.99 -> 138375 | O76: kWh_el/kWh_fuel
A77: UCRF_alternative | B77: =(B$2*(1+B$2)^B74)/((1+B$2)^B74-1) -> 0.072648911 | C77: =(C$2*(1+C$2)^C74)/((1+C$2)^C74-1) -> 0.072648911 | D77: =(D$2*(1+D$2)^D74)/((1+D$2)^D74-1) -> 0.072648911 | E77: =(E$2*(1+E$2)^E74)/((1+E$2)^E74-1) -> 0.072648911 | F77: =(F$2*(1+F$2)^F74)/((1+F$2)^F74-1) -> 0.072648911 | G77: =(G$2*(1+G$2)^G74)/((1+G$2)^G74-1) -> 0.072648911 | H77: =(H$2*(1+H$2)^H74)/((1+H$2)^H74-1) -> 0.072648911 | I77: =(I$2*(1+I$2)^I74)/((1+I$2)^I74-1) -> 0.072648911 | J77: =(J$2*(1+J$2)^J74)/((1+J$2)^J74-1) -> 0.072648911 | K77: - | M77: WACC
A78: Electricity cost_alternative | B78: =B72*B3 -> 10.210259 | C78: =C72*C3 -> 10.276352 | D78: =D72*D3 -> 10.392482 | E78: =E72*E3 -> 10.175956 | F78: =F72*F3 -> 6.2200401 | G78: =G72*G3 -> 5.139046 | H78: =H72*H3 -> 1.5761309 | I78: =I72*I3 -> 1.5883967 | J78: =J72*J3 -> 1.6558867 | K78: ct/kWh | M78: LCOE
A79: Capex electrolysis_alternative | B79: =B61/B75*B77 -> 0.90398361 | C79: =C61/C75*C77 -> 0.90398361 | D79: =D61/D75*D77 -> 0.90398361 | E79: =E61/E75*E77 -> 0.90398361 | F79: =F61/F75*F77 -> 0.90398361 | G79: =G61/G75*G77 -> 0.90398361 | H79: =H61/H75*H77 -> 0.90398361 | I79: =I61/I75*I77 -> 0.90398361 | J79: =J61/J75*J77 -> 0.90398361 | K79: ct/kWh | M79: WACC
A80: LCOA_alternative | B80: =B70-B60-B63+B79-B61+B78 -> 17.985695 | C80: =C70-C60-C63+C79-C61+C78 -> 19.83544 | D80: =D70-D60-D63+D79-D61+D78 -> 16.401252 | E80: =E70-E60-E63+E79-E61+E78 -> 15.353969 | F80: =F70-F60-F63+F79-F61+F78 -> 12.213765 | G80: =G70-G60-G63+G79-G61+G78 -> 9.5091148 | H80: =H70-H60-H63+H79-H61+H78 -> 5.8389746 | I80: =I70-I60-I63+I79-I61+I78 -> 6.3270457 | J80: =J70-J60-J63+J79-J61+J78 -> 5.4474565 | K80: ct/kWh | M80: WACC
A82: Levelized cost of e-fuel [ct/kWh]
B84: 2020 | E84: 2035 | H84: 2050
B85: Offshore | C85: Onshore | D85: Hydro | E85: Offshore | F85: Onshore | G85: Hydro | H85: Offshore | I85: Onshore | J85: Hydro
A86: Electrolysis & storage cost | B86: 6.4923365 | C86: 8.4678535 | D86: 4.5356341 | E86: 3.6335107 | F86: 4.5369679 | G86: 2.7386579 | H86: 2.6295899 | I86: 3.1565768 | J86: 2.1076219 | K86: ct/kWh
A87: Electricity cost electrolysis | B87: 18.245783 | C87: 10.238807 | D87: 5.7811547 | E87: 11.118277 | F87: 6.7368292 | G87: 5.5395542 | H87: 8.2384036 | I87: 5.7660648 | J87: 5.1405835 | K87: ct/kWh
A88: Capex synthesis | B88: 0.78226718 | C88: 0.78226718 | D88: 0.78226718 | E88: 0.51336284 | F88: 0.51336284 | G88: 0.51336284 | H88: 0.39113359 | I88: 0.39113359 | J88: 0.39113359 | K88: ct/kWh
A89: Opex synthesis | B89: 0.35 | C89: 0.35 | D89: 0.35 | E89: 0.2296875 | F89: 0.2296875 | G89: 0.2296875 | H89: 0.175 | I89: 0.175 | J89: 0.175 | K89: ct/kWh
A90: Electricity costs synthesis | B90: 0.12375 | C90: 0.12375 | D90: 0.12375 | E90: 0.12375 | F90: 0.12375 | G90: 0.12375 | H90: 0.12375 | I90: 0.12375 | J90: 0.12375 | K90: ct/kWh
A91: CO2 cost | B91: 15.686 | C91: 15.686 | D91: 15.686 | E91: 4.6035 | F91: 4.6035 | G91: 4.6035 | H91: 2.728 | I91: 2.728 | J91: 2.728 | K91: ct/kWh
A92: Storage costs | B92: 0.04 | C92: 0.04 | D92: 0.04 | E92: 0.04 | F92: 0.04 | G92: 0.04 | H92: 0.04 | I92: 0.04 | J92: 0.04 | K92: ct/kWh
A93: Distribution cost | B93: 0.0375 | C93: 0.0375 | D93: 0.0375 | E93: 0.02125 | F93: 0.02125 | G93: 0.02125 | H93: 0.0125 | I93: 0.0125 | J93: 0.0125 | K93: ct/kWh
A95: BC | B95: 9.4671086 | C95: 8.7767882 | D95: 6.0304296 | E95: 6.14035 | F95: 6.0038345 | G95: 3.6274383 | H95: 4.8195291 | I95: 4.5290093 | J95: 2.8038048 | K95: ct/kWh
A96: WC | B96: 10.904743 | C96: 10.488975 | D96: 7.3538193 | E96: 7.6241064 | F96: 7.9644196 | G96: 4.8900367 | H96: 6.0281736 | I96: 5.9505315 | J96: 3.8706046 | K96: ct/kWh
A98: LCOEF | B98: =SUM(B86:B93) -> 41.757637 | C98: =SUM(C86:C93) -> 35.726177 | D98: =SUM(D86:D93) -> 27.336306 | E98: =SUM(E86:E93) -> 20.283338 | F98: =SUM(F86:F93) -> 16.805347 | G98: =SUM(G86:G93) -> 13.809762 | H98: =SUM(H86:H93) -> 14.338377 | I98: =SUM(I86:I93) -> 12.393025 | J98: =SUM(J86:J93) -> 10.718589 | K98: ct/kWh
A100: Electricity consumption | B100: =(B87+B90)/B19 -> 1.9602461 | C100: =(C87+C90)/C19 -> 1.9705731 | D100: =(D87+D90)/D19 -> 1.9887184 | E100: =(E87+E90)/E19 -> 1.8864372 | F100: =(F87+F90)/F19 -> 1.8999425 | G100: =(G87+G90)/G19 -> 1.9073495 | H100: =(H87+H90)/H19 -> 1.757308 | I100: =(I87+I90)/I19 -> 1.7684588 | J100: =(J87+J90)/J19 -> 1.7729798 | K100: kWh_el/kWh_fuel
A102: Lifetime | B102: 25 | C102: 25 | D102: 25 | E102: 25 | F102: 25 | G102: 25 | H102: 25 | I102: 25 | J102: 25 | K102: years
A103: UCRF | B103: =(B$1*(1+B$1)^B102)/((1+B$1)^B102-1) -> 0.078226718 | C103: =(C$1*(1+C$1)^C102)/((1+C$1)^C102-1) -> 0.078226718 | D103: =(D$1*(1+D$1)^D102)/((1+D$1)^D102-1) -> 0.078226718 | E103: =(E$1*(1+E$1)^E102)/((1+E$1)^E102-1) -> 0.078226718 | F103: =(F$1*(1+F$1)^F102)/((1+F$1)^F102-1) -> 0.078226718 | G103: =(G$1*(1+G$1)^G102)/((1+G$1)^G102-1) -> 0.078226718 | H103: =(H$1*(1+H$1)^H102)/((1+H$1)^H102-1) -> 0.078226718 | I103: =(I$1*(1+I$1)^I102)/((1+I$1)^I102-1) -> 0.078226718 | J103: =(J$1*(1+J$1)^J102)/((1+J$1)^J102-1) -> 0.078226718 | K103: -
A105: UCRF_alternative | B105: =(B$2*(1+B$2)^B102)/((1+B$2)^B102-1) -> 0.078226718 | C105: =(C$2*(1+C$2)^C102)/((1+C$2)^C102-1) -> 0.078226718 | D105: =(D$2*(1+D$2)^D102)/((1+D$2)^D102-1) -> 0.078226718 | E105: =(E$2*(1+E$2)^E102)/((1+E$2)^E102-1) -> 0.078226718 | F105: =(F$2*(1+F$2)^F102)/((1+F$2)^F102-1) -> 0.078226718 | G105: =(G$2*(1+G$2)^G102)/((1+G$2)^G102-1) -> 0.078226718 | H105: =(H$2*(1+H$2)^H102)/((1+H$2)^H102-1) -> 0.078226718 | I105: =(I$2*(1+I$2)^I102)/((1+I$2)^I102-1) -> 0.078226718 | J105: =(J$2*(1+J$2)^J102)/((1+J$2)^J102-1) -> 0.078226718 | K105: -
A106: Electricity cost_alternative | B106: =B100*B3 -> 11.291017 | C106: =C100*C3 -> 11.350501 | D106: =D100*D3 -> 11.455018 | E106: =E100*E3 -> 11.242027 | F106: =F100*F3 -> 6.8605792 | G106: =G100*G3 -> 5.6633042 | H106: =H100*H3 -> 1.7397349 | I106: =I100*I3 -> 1.7507742 | J106: =J100*J3 -> 1.75525 | K106: ct/kWh
A107: Capex electrolysis_alternative | B107: =B88/B103*B105 -> 0.78226718 | C107: =C88/C103*C105 -> 0.78226718 | D107: =D88/D103*D105 -> 0.78226718 | E107: =E88/E103*E105 -> 0.51336284 | F107: =F88/F103*F105 -> 0.51336284 | G107: =G88/G103*G105 -> 0.51336284 | H107: =H88/H103*H105 -> 0.39113359 | I107: =I88/I103*I105 -> 0.39113359 | J107: =J88/J103*J105 -> 0.39113359 | K107: ct/kWh
A109: CO2 cost_alternative | B109: =B91/B5*B6 -> 15.686 | C109: =C91/C5*C6 -> 15.686 | D109: =D91/D5*D6 -> 15.686 | E109: =E91/E5*E6 -> 4.6035 | F109: =F91/F5*F6 -> 4.6035 | G109: =G91/G5*G6 -> 4.6035 | H109: =H91/H5*H6 -> 2.728 | I109: =I91/I5*I6 -> 2.728 | J109: =J91/J5*J6 -> 2.728 | K109: ct/kWh
A111: LCOEF_alternative | B111: =B98-B87-B90+B106-B88+B107-B91+B109 -> 34.679121 | C111: =C98-C87-C90+C106-C88+C107-C91+C109 -> 36.714122 | D111: =D98-D87-D90+D106-D88+D107-D91+D109 -> 32.886419 | E111: =E98-E87-E90+E106-E88+E107-E91+E109 -> 20.283338 | F111: =F98-F87-F90+F106-F88+F107-F91+F109 -> 16.805347 | G111: =G98-G87-G90+G106-G88+G107-G91+G109 -> 13.809762 | H111: =H98-H87-H90+H106-H88+H107-H91+H109 -> 7.7159584 | I111: =I98-I87-I90+I106-I88+I107-I91+I109 -> 8.2539846 | J111: =J98-J87-J90+J106-J88+J107-J91+J109 -> 7.2095055 | K111: ct/kWh
A112: LCOEF_alternative | B112: =B111/3.6 -> 9.6330892 | C112: =C111/3.6 -> 10.198367 | D112: =D111/3.6 -> 9.1351164 | E112: =E111/3.6 -> 5.6342605 | F112: =F111/3.6 -> 4.6681521 | G112: =G111/3.6 -> 3.8360451 | H112: =H111/3.6 -> 2.1433218 | I112: =I111/3.6 -> 2.2927735 | J112: =J111/3.6 -> 2.0026404 | K112: ct/MJ
A113: LCOEF_alternative | B113: =B112*Inputs!$C$14 / 100 -> 3.3416801 | C113: =C112*Inputs!$C$14 / 100 -> 3.5377728 | D113: =D112*Inputs!$C$14 / 100 -> 3.1689353 | E113: =E112*Inputs!$C$14 / 100 -> 1.9545024 | F113: =F112*Inputs!$C$14 / 100 -> 1.6193633 | G113: =G112*Inputs!$C$14 / 100 -> 1.3307087 | H113: =H112*Inputs!$C$14 / 100 -> 0.74350976 | I113: =I112*Inputs!$C$14 / 100 -> 0.79535396 | J113: =J112*Inputs!$C$14 / 100 -> 0.69470795 | K113: €/l

Sheet CO2 Price Corrected LCOF
A1: WACC_source | B1: 0.06 | C1: 0.06 | D1: 0.06 | E1: 0.06 | F1: 0.06 | G1: 0.06 | H1: 0.06 | I1: 0.06 | J1: 0.06 | K1: -
A2: WACC_alternative | B2: 0.06 | C2: 0.06 | D2: 0.06 | E2: 0.06 | F2: 0.06 | G2: 0.06 | H2: 0.06 | I2: 0.06 | J2: 0.06 | K2: -
A3: LCOE_alternative | B3: =Inputs!$C$8*Inputs!$C$6 / 10 -> 5.76 | C3: =Inputs!$C$8*Inputs!$C$6 / 10 -> 5.76 | D3: =Inputs!$C$8*Inputs!$C$6 / 10 -> 5.76 | E3: 5.9593963 | F3: 3.6109404 | G3: 2.969201 | H3: =Inputs!$C$9*Inputs!$C$6 / 10 -> 0.99 | I3: =Inputs!$C$9*Inputs!$C$6 / 10 -> 0.99 | J3: =Inputs!$C$9*Inputs!$C$6 / 10 -> 0.99 | K3: ct/kWh
B4: 11.1 | C4: 11.1 | D4: 11.1 | E4: 7.5 | F4: 7.5 | G4: 7.5 | H4: 3.9 | I4: 3.9 | J4: 3.9 | L4: Note: this is the standard LCOE curve
A5: DAC_source | B5: 460 | C5: 460 | D5: 460 | E5: 135 | F5: 135 | G5: 135 | H5: 80 | I5: 80 | J5: 80 | K5: €/tCO2
A6: DAC_alternative | B6: =Inputs!$C$32*Inputs!$C$6 -> 1153.8 | C6: =Inputs!$C$32*Inputs!$C$6 -> 1153.8 | D6: =Inputs!$C$32*Inputs!$C$6 -> 1153.8 | E6: 135 | F6: 135 | G6: 135 | H6: =Inputs!$C$33*Inputs!$C$6 -> 432 | I6: =Inputs!$C$33*Inputs!$C$6 -> 432 | J6: =Inputs!$C$33*Inputs!$C$6 -> 432 | K6: €/tCO2 | L6: Average between SS and LS DAC
B7: 731.19867 | C7: 731.19867 | D7: 731.19867 | E7: 449.5681 | F7: 449.5681 | G7: 449.5681 | H7: 298.29332 | I7: 298.29332 | J7: 298.29332 | L7: Note: this is modelled DAC cost
A8: Levelized cost of electricity [ct/kWh]
B10: 2020 | E10: 2035 | H10: 2050
B11: Offshore | C11: Onshore | D11: Hydro | E11: Offshore | F11: Onshore | G11: Hydro | H11: Offshore | I11: Onshore | J11: Hydro | N11: 2020 Offshore | O11: 2020 Onshore
A12: Capex generation | B12: 5.6892159 | C12: 4.0867761 | D12: 2.1299153 | E12: 3.5557599 | F12: 2.8062529 | G12: 2.1299153 | H12: 2.9335019 | I12: 2.5882915 | J12: 2.1299153 | K12: ct/kWh | M12: CAPEX | N12: 3200 | O12: 1500
A13: Opex generation | B13: 2.1818182 | C13: 1.171875 | D13: 0.83928571 | E13: 1.3636364 | F13: 0.8046875 | G13: 0.83928571 | H13: 1.125 | I13: 0.7421875 | J13: 0.83928571 | K13: ct/kWh | M13: Loadhours | N13: 4400 | O13: 3200
A14: Offshore grid fee | B14: 1.5 | C14: 0 | D14: 0 | E14: 1.04 | F14: 0 | G14: 0 | H14: 0.7 | I14: 0 | J14: 0 | K14: ct/kWh | M14: UCRF | N14: =B23 -> 0.078226718 | O14: =C23 -> 0.087184557
M15: Annualized CAPEX | N15: =N12*N14/N13 -> 0.056892159 | O15: =O12*O14/O13 -> 0.040867761 | P15: €/kWh
A16: BC | B16: 1.377431 | C16: 0.80426429 | D16: 0.37115013 | E16: 1.3238642 | F16: 1.1857743 | G16: 0.37115013 | H16: 1.292708 | I16: 1.020797 | J16: 0.37115013 | K16: ct/kWh | N16: =N15*100 -> 5.6892159 | O16: =O15*100 -> 4.0867761 | P16: ct/kWh
A17: WC | B17: 1.4414975 | C17: 0.91149953 | D17: 0.49486684 | E17: 1.3602703 | F17: 1.3812724 | G17: 0.49486684 | H17: 1.352834 | I17: 1.1569032 | J17: 0.49486684 | K17: ct/kWh
A19: LCOE | B19: =SUM(B12:B14) -> 9.3710341 | C19: =SUM(C12:C14) -> 5.2586511 | D19: =SUM(D12:D14) -> 2.969201 | E19: =SUM(E12:E14) -> 5.9593963 | F19: =SUM(F12:F14) -> 3.6109404 | G19: =SUM(G12:G14) -> 2.969201 | H19: =SUM(H12:H14) -> 4.7585019 | I19: =SUM(I12:I14) -> 3.330479 | J19: =SUM(J12:J14) -> 2.969201 | K19: ct/kWh
A20: LCOE | B20: =B19*10 -> 93.710341 | C20: =C19*10 -> 52.586511 | D20: =D19*10 -> 29.69201 | E20: =E19*10 -> 59.593963 | F20: =F19*10 -> 36.109404 | G20: =G19*10 -> 29.69201 | H20: =H19*10 -> 47.585019 | I20: =I19*10 -> 33.30479 | J20: =J19*10 -> 29.69201 | K20: €/MWh
A22: Lifetime | B22: 25 | C22: 20 | D22: 50 | E22: 25 | F22: 20 | G22: 50 | H22: 25 | I22: 20 | J22: 50 | K22: years | M22: WACC
A23: UCRF | B23: =(B$1*(1+B$1)^B22)/((1+B$1)^B22-1) -> 0.078226718 | C23: =(C$1*(1+C$1)^C22)/((1+C$1)^C22-1) -> 0.087184557 | D23: =(D$1*(1+D$1)^D22)/((1+D$1)^D22-1) -> 0.063444286 | E23: =(E$1*(1+E$1)^E22)/((1+E$1)^E22-1) -> 0.078226718 | F23: =(F$1*(1+F$1)^F22)/((1+F$1)^F22-1) -> 0.087184557 | G23: =(G$1*(1+G$1)^G22)/((1+G$1)^G22-1) -> 0.063444286 | H23: =(H$1*(1+H$1)^H22)/((1+H$1)^H22-1) -> 0.078226718 | I23: =(I$1*(1+I$1)^I22)/((1+I$1)^I22-1) -> 0.087184557 | J23: =(J$1*(1+J$1)^J22)/((1+J$1)^J22-1) -> 0.063444286 | K23: - | M23: WACC
A25: UCRF_alternative | B25: =(B$2*(1+B$2)^B22)/((1+B$2)^B22-1) -> 0.078226718 | C25: =(C$2*(1+C$2)^C22)/((1+C$2)^C22-1) -> 0.087184557 | D25: =(D$2*(1+D$2)^D22)/((1+D$2)^D22-1) -> 0.063444286 | E25: =(E$2*(1+E$2)^E22)/((1+E$2)^E22-1) -> 0.078226718 | F25: =(F$2*(1+F$2)^F22)/((1+F$2)^F22-1) -> 0.087184557 | G25: =(G$2*(1+G$2)^G22)/((1+G$2)^G22-1) -> 0.063444286 | H25: =(H$2*(1+H$2)^H22)/((1+H$2)^H22-1) -> 0.078226718 | I25: =(I$2*(1+I$2)^I22)/((1+I$2)^I22-1) -> 0.087184557 | J25: =(J$2*(1+J$2)^J22)/((1+J$2)^J22-1) -> 0.063444286 | K25: - | M25: WACC
A26: Capex generation_alternative | B26: =B12/B23*B25 -> 5.6892159 | C26: =C12/C23*C25 -> 4.0867761 | D26: =D12/D23*D25 -> 2.1299153 | E26: =E12/E23*E25 -> 3.5557599 | F26: =F12/F23*F25 -> 2.8062529 | G26: =G12/G23*G25 -> 2.1299153 | H26: =H12/H23*H25 -> 2.9335019 | I26: =I12/I23*I25 -> 2.5882915 | J26: =J12/J23*J25 -> 2.1299153 | K26: ct/kWh | M26: WACC
A27: LCOE_alternative | B27: =B19-B12+B26 -> 9.3710341 | C27: =C19-C12+C26 -> 5.2586511 | D27: =D19-D12+D26 -> 2.969201 | E27: =E19-E12+E26 -> 5.9593963 | F27: =F19-F12+F26 -> 3.6109404 | G27: =G19-G12+G26 -> 2.969201 | H27: =H19-H12+H26 -> 4.7585019 | I27: =I19-I12+I26 -> 3.330479 | J27: =J19-J12+J26 -> 2.969201 | K27: ct/kWh
A29: Levelized cost of hydrogen [ct/kWh]
B31: 2020 | E31: 2035 | H31: 2050
B32: Offshore | C32: Onshore | D32: Hydro | E32: Offshore | F32: Onshore | G32: Hydro | H32: Offshore | I32: Onshore | J32: Hydro
A33: Capex electrolysis | B33: 3.0462118 | C33: 4.1885412 | D33: 1.9147617 | E33: 1.3931149 | F33: 1.915533 | G33: 0.87567222 | H33: 0.81260441 | I33: 1.1173311 | J33: 0.51077992 | K33: ct/kWh
A34: Opex electrolysis | B34: 1.1682243 | C34: 1.6063084 | D34: 0.73431242 | E34: 0.53426052 | F34: 0.73460821 | G34: 0.3358209 | H34: 0.31163435 | I34: 0.42849723 | J34: 0.19588445 | K34: ct/kWh
A35: Electricity cost | B35: 14.596626 | C35: 8.1910453 | D35: 4.6249237 | E35: 8.8946213 | F35: 5.3894633 | G35: 4.4316433 | H35: 6.5907229 | I35: 4.6128518 | J35: 4.1124668 | K35: ct/kWh
A36: Storage cost | B36: 2.9792732 | C36: 2.9792732 | D36: 2.9792732 | E36: 2.3792732 | F36: 2.3792732 | G36: 2.3792732 | H36: 1.9792732 | I36: 1.9792732 | J36: 1.9792732 | K36: ct/kWh
A37: Liquefaction cost | B37: 3.7938486 | C37: 3.7938486 | D37: 3.7938486 | E37: 2.1404261 | F37: 2.1404261 | G37: 2.1404261 | H37: 1.4308452 | I37: 1.4308452 | J37: 1.4308452 | K37: ct/kWh
A38: Distribution cost | B38: 0.225 | C38: 0.225 | D38: 0.225 | E38: 0.195 | F38: 0.195 | G38: 0.195 | H38: 0.1875 | I38: 0.1875 | J38: 0.1875 | K38: ct/kWh
A40: BC | B40: 5.0944468 | C40: 4.5421905 | D40: 2.3451036 | E40: 4.0195481 | F40: 3.9103357 | G40: 2.0092187 | H40: 3.0022965 | I40: 2.7698807 | J40: 1.3897171 | K40: ct/kWh
A41: WC | B41: 6.2445545 | C41: 5.9119403 | D41: 3.4038153 | E41: 4.7428356 | F41: 5.0150862 | G41: 2.5555799 | H41: 4.1084781 | I41: 4.0463644 | J41: 2.3824229 | K41: ct/kWh
A43: LCOH | B43: =SUM(B33:B38) -> 25.809184 | C43: =SUM(C33:C38) -> 20.984017 | D43: =SUM(D33:D38) -> 14.27212 | E43: =SUM(E33:E38) -> 15.536696 | F43: =SUM(F33:F38) -> 12.754304 | G43: =SUM(G33:G38) -> 10.357836 | H43: =SUM(H33:H38) -> 11.31258 | I43: =SUM(I33:I38) -> 9.7562986 | J43: =SUM(J33:J38) -> 8.4167496 | K43: ct/kWh
A45: Electricity consumption | B45: =B35/B19 -> 1.5576324 | C45: =C35/C19 -> 1.5576324 | D45: =D35/D19 -> 1.5576324 | E45: =E35/E19 -> 1.4925373 | F45: =F35/F19 -> 1.4925373 | G45: =G35/G19 -> 1.4925373 | H45: =H35/H19 -> 1.3850416 | I45: =I35/I19 -> 1.3850416 | J45: =J35/J19 -> 1.3850416 | K45: kWh_el/kWh_fuel | M45: LCOE
A47: Lifetime | B47: 25 | C47: 25 | D47: 25 | E47: 25 | F47: 25 | G47: 25 | H47: 25 | I47: 25 | J47: 25 | K47: years | M47: WACC
A48: UCRF | B48: =(B$1*(1+B$1)^B47)/((1+B$1)^B47-1) -> 0.078226718 | C48: =(C$1*(1+C$1)^C47)/((1+C$1)^C47-1) -> 0.078226718 | D48: =(D$1*(1+D$1)^D47)/((1+D$1)^D47-1) -> 0.078226718 | E48: =(E$1*(1+E$1)^E47)/((1+E$1)^E47-1) -> 0.078226718 | F48: =(F$1*(1+F$1)^F47)/((1+F$1)^F47-1) -> 0.078226718 | G48: =(G$1*(1+G$1)^G47)/((1+G$1)^G47-1) -> 0.078226718 | H48: =(H$1*(1+H$1)^H47)/((1+H$1)^H47-1) -> 0.078226718 | I48: =(I$1*(1+I$1)^I47)/((1+I$1)^I47-1) -> 0.078226718 | J48: =(J$1*(1+J$1)^J47)/((1+J$1)^J47-1) -> 0.078226718 | K48: - | M48: WACC
A50: UCRF_alternative | B50: =(B$2*(1+B$2)^B47)/((1+B$2)^B47-1) -> 0.078226718 | C50: =(C$2*(1+C$2)^C47)/((1+C$2)^C47-1) -> 0.078226718 | D50: =(D$2*(1+D$2)^D47)/((1+D$2)^D47-1) -> 0.078226718 | E50: =(E$2*(1+E$2)^E47)/((1+E$2)^E47-1) -> 0.078226718 | F50: =(F$2*(1+F$2)^F47)/((1+F$2)^F47-1) -> 0.078226718 | G50: =(G$2*(1+G$2)^G47)/((1+G$2)^G47-1) -> 0.078226718 | H50: =(H$2*(1+H$2)^H47)/((1+H$2)^H47-1) -> 0.078226718 | I50: =(I$2*(1+I$2)^I47)/((1+I$2)^I47-1) -> 0.078226718 | J50: =(J$2*(1+J$2)^J47)/((1+J$2)^J47-1) -> 0.078226718 | K50: - | M50: WACC
A51: Electricity cost_alternative | B51: =B45*B3 -> 8.9719626 | C51: =C45*C3 -> 8.9719626 | D51: =D45*D3 -> 8.9719626 | E51: =E45*E3 -> 8.8946213 | F51: =F45*F3 -> 5.3894633 | G51: =G45*G3 -> 4.4316433 | H51: =H45*H3 -> 1.3711911 | I51: =I45*I3 -> 1.3711911 | J51: =J45*J3 -> 1.3711911 | K51: ct/kWh | M51: LCOE
A52: Capex electrolysis_alternative | B52: =B33/B48*B50 -> 3.0462118 | C52: =C33/C48*C50 -> 4.1885412 | D52: =D33/D48*D50 -> 1.9147617 | E52: =E33/E48*E50 -> 1.3931149 | F52: =F33/F48*F50 -> 1.915533 | G52: =G33/G48*G50 -> 0.87567222 | H52: =H33/H48*H50 -> 0.81260441 | I52: =I33/I48*I50 -> 1.1173311 | J52: =J33/J48*J50 -> 0.51077992 | K52: ct/kWh | M52: WACC
A53: LCOH_alternative | B53: =B43-B33+B52-B35+B51 -> 20.18452 | C53: =C43-C33+C52-C35+C51 -> 21.764934 | D53: =D43-D33+D52-D35+D51 -> 18.619159 | E53: =E43-E33+E52-E35+E51 -> 15.536696 | F53: =F43-F33+F52-F35+F51 -> 12.754304 | G53: =G43-G33+G52-G35+G51 -> 10.357836 | H53: =H43-H33+H52-H35+H51 -> 6.0930483 | I53: =I43-I33+I52-I35+I51 -> 6.5146378 | J53: =J43-J33+J52-J35+J51 -> 5.6754739 | K53: ct/kWh
A55: Levelized cost of ammonia [ct/kWh]
B57: 2020 | E57: 2035 | H57: 2050
B58: Offshore | C58: Onshore | D58: Hydro | E58: Offshore | F58: Onshore | G58: Hydro | H58: Offshore | I58: Onshore | J58: Hydro
A59: Electrolysis & storage cost | B59: 5.8617929 | C59: 7.6454453 | D59: 4.0951278 | E59: 3.2806198 | F59: 4.0963321 | G59: 2.4726761 | H59: 2.374201 | I59: 2.8500063 | J59: 1.9029271 | K59: ct/kWh
A60: Electricity cost electrolysis | B60: 16.47373 | C60: 9.2444014 | D60: 5.2196819 | E60: 10.038456 | F60: 6.0825401 | G60: 5.001546 | H60: 7.4382799 | I60: 5.2060576 | J60: 4.6413238 | K60: ct/kWh
A61: Capex synthesis | B61: 0.90398361 | C61: 0.90398361 | D61: 0.90398361 | E61: 0.90398361 | F61: 0.90398361 | G61: 0.90398361 | H61: 0.90398361 | I61: 0.90398361 | J61: 0.90398361 | K61: ct/kWh
A62: Opex synthesis | B62: 0.62215909 | C62: 0.62215909 | D62: 0.62215909 | E62: 0.62215909 | F62: 0.62215909 | G62: 0.62215909 | H62: 0.62215909 | I62: 0.62215909 | J62: 0.62215909 | K62: ct/kWh
A63: Electricity costs synthesis | B63: 0.1375 | C63: 0.1375 | D63: 0.1375 | E63: 0.1375 | F63: 0.1375 | G63: 0.1375 | H63: 0.1375 | I63: 0.1375 | J63: 0.325 | K63: ct/kWh
A64: Storage cost | B64: 0.325 | C64: 0.325 | D64: 0.325 | E64: 0.325 | F64: 0.325 | G64: 0.325 | H64: 0.325 | I64: 0.325 | J64: 0.325 | K64: ct/kWh
A65: Distribution cost | B65: 0.0625 | C65: 0.0625 | D65: 0.0625 | E65: 0.04625 | F65: 0.04625 | G65: 0.04625 | H65: 0.0375 | I65: 0.0375 | J65: 0.0375 | K65: ct/kWh
A67: BC | B67: 5.6659076 | C67: 5.0426319 | D67: 2.563003 | E67: 4.1720267 | F67: 4.0487697 | G67: 1.903172 | H67: 3.3808903 | I67: 3.1185862 | J67: 1.5609356 | K67: ct/kWh
A68: WC | B68: 6.9639174 | C68: 6.5885295 | D68: 3.7578634 | E68: 5.3391657 | F68: 5.6464272 | G68: 2.8706322 | H68: 4.2165748 | I68: 4.1464734 | J68: 2.2685515 | K68: ct/kWh
A70: LCOA | B70: =SUM(B59:B65) -> 24.386666 | C70: =SUM(C59:C65) -> 18.940989 | D70: =SUM(D59:D65) -> 11.365952 | E70: =SUM(E59:E65) -> 15.353969 | F70: =SUM(F59:F65) -> 12.213765 | G70: =SUM(G59:G65) -> 9.5091148 | H70: =SUM(H59:H65) -> 11.838624 | I70: =SUM(I59:I65) -> 10.082207 | J70: =SUM(J59:J65) -> 8.7578936 | K70: ct/kWh
N71: eAmmonia
A72: Electricity consumption | B72: =(B60+B63)/B19 -> 1.7726144 | C72: =(C60+C63)/C19 -> 1.784089 | D72: =(D60+D63)/D19 -> 1.8042503 | E72: =(E60+E63)/E19 -> 1.7075482 | F72: =(F60+F63)/F19 -> 1.7225541 | G72: =(G60+G63)/G19 -> 1.7307841 | H72: =(H60+H63)/H19 -> 1.5920514 | I72: =(I60+I63)/I19 -> 1.6044411 | J72: =(J60+J63)/J19 -> 1.6726129 | K72: kWh_el/kWh_fuel | M72: LCOE | N72: 738 | O72: kWh_el/t_fuel
N73: 5.28 | O73: kWh_fuel/kg_fuel
A74: Lifetime | B74: 30 | C74: 30 | D74: 30 | E74: 30 | F74: 30 | G74: 30 | H74: 30 | I74: 30 | J74: 30 | K74: years | M74: WACC | N74: =N73/1000 -> 0.00528 | O74: kWh_fuel/t_fuel
A75: UCRF | B75: =(B$1*(1+B$1)^B74)/((1+B$1)^B74-1) -> 0.072648911 | C75: =(C$1*(1+C$1)^C74)/((1+C$1)^C74-1) -> 0.072648911 | D75: =(D$1*(1+D$1)^D74)/((1+D$1)^D74-1) -> 0.072648911 | E75: =(E$1*(1+E$1)^E74)/((1+E$1)^E74-1) -> 0.072648911 | F75: =(F$1*(1+F$1)^F74)/((1+F$1)^F74-1) -> 0.072648911 | G75: =(G$1*(1+G$1)^G74)/((1+G$1)^G74-1) -> 0.072648911 | H75: =(H$1*(1+H$1)^H74)/((1+H$1)^H74-1) -> 0.072648911 | I75: =(I$1*(1+I$1)^I74)/((1+I$1)^I74-1) -> 0.072648911 | J75: =(J$1*(1+J$1)^J74)/((1+J$1)^J74-1) -> 0.072648911 | K75: - | M75: WACC | N75: 0.99 | O75: Efficiency
N76: =N72/N74*0.99 -> 138375 | O76: kWh_el/kWh_fuel
A77: UCRF_alternative | B77: =(B$2*(1+B$2)^B74)/((1+B$2)^B74-1) -> 0.072648911 | C77: =(C$2*(1+C$2)^C74)/((1+C$2)^C74-1) -> 0.072648911 | D77: =(D$2*(1+D$2)^D74)/((1+D$2)^D74-1) -> 0.072648911 | E77: =(E$2*(1+E$2)^E74)/((1+E$2)^E74-1) -> 0.072648911 | F77: =(F$2*(1+F$2)^F74)/((1+F$2)^F74-1) -> 0.072648911 | G77: =(G$2*(1+G$2)^G74)/((1+G$2)^G74-1) -> 0.072648911 | H77: =(H$2*(1+H$2)^H74)/((1+H$2)^H74-1) -> 0.072648911 | I77: =(I$2*(1+I$2)^I74)/((1+I$2)^I74-1) -> 0.072648911 | J77: =(J$2*(1+J$2)^J74)/((1+J$2)^J74-1) -> 0.072648911 | K77: - | M77: WACC
A78: Electricity cost_alternative | B78: =B72*B3 -> 10.210259 | C78: =C72*C3 -> 10.276352 | D78: =D72*D3 -> 10.392482 | E78: =E72*E3 -> 10.175956 | F78: =F72*F3 -> 6.2200401 | G78: =G72*G3 -> 5.139046 | H78: =H72*H3 -> 1.5761309 | I78: =I72*I3 -> 1.5883967 | J78: =J72*J3 -> 1.6558867 | K78: ct/kWh | M78: LCOE
A79: Capex electrolysis_alternative | B79: =B61/B75*B77 -> 0.90398361 | C79: =C61/C75*C77 -> 0.90398361 | D79: =D61/D75*D77 -> 0.90398361 | E79: =E61/E75*E77 -> 0.90398361 | F79: =F61/F75*F77 -> 0.90398361 | G79: =G61/G75*G77 -> 0.90398361 | H79: =H61/H75*H77 -> 0.90398361 | I79: =I61/I75*I77 -> 0.90398361 | J79: =J61/J75*J77 -> 0.90398361 | K79: ct/kWh | M79: WACC
A80: LCOA_alternative | B80: =B70-B60-B63+B79-B61+B78 -> 17.985695 | C80: =C70-C60-C63+C79-C61+C78 -> 19.83544 | D80: =D70-D60-D63+D79-D61+D78 -> 16.401252 | E80: =E70-E60-E63+E79-E61+E78 -> 15.353969 | F80: =F70-F60-F63+F79-F61+F78 -> 12.213765 | G80: =G70-G60-G63+G79-G61+G78 -> 9.5091148 | H80: =H70-H60-H63+H79-H61+H78 -> 5.8389746 | I80: =I70-I60-I63+I79-I61+I78 -> 6.3270457 | J80: =J70-J60-J63+J79-J61+J78 -> 5.4474565 | K80: ct/kWh | M80: WACC
A82: Levelized cost of e-fuel [ct/kWh]
B84: 2020 | E84: 2035 | H84: 2050
B85: Offshore | C85: Onshore | D85: Hydro | E85: Offshore | F85: Onshore | G85: Hydro | H85: Offshore | I85: Onshore | J85: Hydro
A86: Electrolysis & storage cost | B86: 6.4923365 | C86: 8.4678535 | D86: 4.5356341 | E86: 3.6335107 | F86: 4.5369679 | G86: 2.7386579 | H86: 2.6295899 | I86: 3.1565768 | J86: 2.1076219 | K86: ct/kWh
A87: Electricity cost electrolysis | B87: 18.245783 | C87: 10.238807 | D87: 5.7811547 | E87: 11.118277 | F87: 6.7368292 | G87: 5.5395542 | H87: 8.2384036 | I87: 5.7660648 | J87: 5.1405835 | K87: ct/kWh
A88: Capex synthesis | B88: 0.78226718 | C88: 0.78226718 | D88: 0.78226718 | E88: 0.51336284 | F88: 0.51336284 | G88: 0.51336284 | H88: 0.39113359 | I88: 0.39113359 | J88: 0.39113359 | K88: ct/kWh
A89: Opex synthesis | B89: 0.35 | C89: 0.35 | D89: 0.35 | E89: 0.2296875 | F89: 0.2296875 | G89: 0.2296875 | H89: 0.175 | I89: 0.175 | J89: 0.175 | K89: ct/kWh
A90: Electricity costs synthesis | B90: 0.12375 | C90: 0.12375 | D90: 0.12375 | E90: 0.12375 | F90: 0.12375 | G90: 0.12375 | H90: 0.12375 | I90: 0.12375 | J90: 0.12375 | K90: ct/kWh
A91: CO2 cost | B91: 15.686 | C91: 15.686 | D91: 15.686 | E91: 4.6035 | F91: 4.6035 | G91: 4.6035 | H91: 2.728 | I91: 2.728 | J91: 2.728 | K91: ct/kWh
A92: Storage costs | B92: 0.04 | C92: 0.04 | D92: 0.04 | E92: 0.04 | F92: 0.04 | G92: 0.04 | H92: 0.04 | I92: 0.04 | J92: 0.04 | K92: ct/kWh
A93: Distribution cost | B93: 0.0375 | C93: 0.0375 | D93: 0.0375 | E93: 0.02125 | F93: 0.02125 | G93: 0.02125 | H93: 0.0125 | I93: 0.0125 | J93: 0.0125 | K93: ct/kWh
A95: BC | B95: 9.4671086 | C95: 8.7767882 | D95: 6.0304296 | E95: 6.14035 | F95: 6.0038345 | G95: 3.6274383 | H95: 4.8195291 | I95: 4.5290093 | J95: 2.8038048 | K95: ct/kWh
A96: WC | B96: 10.904743 | C96: 10.488975 | D96: 7.3538193 | E96: 7.6241064 | F96: 7.9644196 | G96: 4.8900367 | H96: 6.0281736 | I96: 5.9505315 | J96: 3.8706046 | K96: ct/kWh
A98: LCOEF | B98: =SUM(B86:B93) -> 41.757637 | C98: =SUM(C86:C93) -> 35.726177 | D98: =SUM(D86:D93) -> 27.336306 | E98: =SUM(E86:E93) -> 20.283338 | F98: =SUM(F86:F93) -> 16.805347 | G98: =SUM(G86:G93) -> 13.809762 | H98: =SUM(H86:H93) -> 14.338377 | I98: =SUM(I86:I93) -> 12.393025 | J98: =SUM(J86:J93) -> 10.718589 | K98: ct/kWh
A100: Electricity consumption | B100: =(B87+B90)/B19 -> 1.9602461 | C100: =(C87+C90)/C19 -> 1.9705731 | D100: =(D87+D90)/D19 -> 1.9887184 | E100: =(E87+E90)/E19 -> 1.8864372 | F100: =(F87+F90)/F19 -> 1.8999425 | G100: =(G87+G90)/G19 -> 1.9073495 | H100: =(H87+H90)/H19 -> 1.757308 | I100: =(I87+I90)/I19 -> 1.7684588 | J100: =(J87+J90)/J19 -> 1.7729798 | K100: kWh_el/kWh_fuel
A102: Lifetime | B102: 25 | C102: 25 | D102: 25 | E102: 25 | F102: 25 | G102: 25 | H102: 25 | I102: 25 | J102: 25 | K102: years
A103: UCRF | B103: =(B$1*(1+B$1)^B102)/((1+B$1)^B102-1) -> 0.078226718 | C103: =(C$1*(1+C$1)^C102)/((1+C$1)^C102-1) -> 0.078226718 | D103: =(D$1*(1+D$1)^D102)/((1+D$1)^D102-1) -> 0.078226718 | E103: =(E$1*(1+E$1)^E102)/((1+E$1)^E102-1) -> 0.078226718 | F103: =(F$1*(1+F$1)^F102)/((1+F$1)^F102-1) -> 0.078226718 | G103: =(G$1*(1+G$1)^G102)/((1+G$1)^G102-1) -> 0.078226718 | H103: =(H$1*(1+H$1)^H102)/((1+H$1)^H102-1) -> 0.078226718 | I103: =(I$1*(1+I$1)^I102)/((1+I$1)^I102-1) -> 0.078226718 | J103: =(J$1*(1+J$1)^J102)/((1+J$1)^J102-1) -> 0.078226718 | K103: -
A105: UCRF_alternative | B105: =(B$2*(1+B$2)^B102)/((1+B$2)^B102-1) -> 0.078226718 | C105: =(C$2*(1+C$2)^C102)/((1+C$2)^C102-1) -> 0.078226718 | D105: =(D$2*(1+D$2)^D102)/((1+D$2)^D102-1) -> 0.078226718 | E105: =(E$2*(1+E$2)^E102)/((1+E$2)^E102-1) -> 0.078226718 | F105: =(F$2*(1+F$2)^F102)/((1+F$2)^F102-1) -> 0.078226718 | G105: =(G$2*(1+G$2)^G102)/((1+G$2)^G102-1) -> 0.078226718 | H105: =(H$2*(1+H$2)^H102)/((1+H$2)^H102-1) -> 0.078226718 | I105: =(I$2*(1+I$2)^I102)/((1+I$2)^I102-1) -> 0.078226718 | J105: =(J$2*(1+J$2)^J102)/((1+J$2)^J102-1) -> 0.078226718 | K105: -
A106: Electricity cost_alternative | B106: =B100*B3 -> 11.291017 | C106: =C100*C3 -> 11.350501 | D106: =D100*D3 -> 11.455018 | E106: =E100*E3 -> 11.242027 | F106: =F100*F3 -> 6.8605792 | G106: =G100*G3 -> 5.6633042 | H106: =H100*H3 -> 1.7397349 | I106: =I100*I3 -> 1.7507742 | J106: =J100*J3 -> 1.75525 | K106: ct/kWh
A107: Capex electrolysis_alternative | B107: =B88/B103*B105 -> 0.78226718 | C107: =C88/C103*C105 -> 0.78226718 | D107: =D88/D103*D105 -> 0.78226718 | E107: =E88/E103*E105 -> 0.51336284 | F107: =F88/F103*F105 -> 0.51336284 | G107: =G88/G103*G105 -> 0.51336284 | H107: =H88/H103*H105 -> 0.39113359 | I107: =I88/I103*I105 -> 0.39113359 | J107: =J88/J103*J105 -> 0.39113359 | K107: ct/kWh
A109: CO2 cost_alternative | B109: =B91/B5*B6 -> 39.34458 | C109: =C91/C5*C6 -> 39.34458 | D109: =D91/D5*D6 -> 39.34458 | E109: =E91/E5*E6 -> 4.6035 | F109: =F91/F5*F6 -> 4.6035 | G109: =G91/G5*G6 -> 4.6035 | H109: =H91/H5*H6 -> 14.7312 | I109: =I91/I5*I6 -> 14.7312 | J109: =J91/J5*J6 -> 14.7312 | K109: ct/kWh
A111: LCOEF_alternative | B111: =B98-B87-B90+B106-B88+B107-B91+B109 -> 58.337701 | C111: =C98-C87-C90+C106-C88+C107-C91+C109 -> 60.372702 | D111: =D98-D87-D90+D106-D88+D107-D91+D109 -> 56.544999 | E111: =E98-E87-E90+E106-E88+E107-E91+E109 -> 20.283338 | F111: =F98-F87-F90+F106-F88+F107-F91+F109 -> 16.805347 | G111: =G98-G87-G90+G106-G88+G107-G91+G109 -> 13.809762 | H111: =H98-H87-H90+H106-H88+H107-H91+H109 -> 19.719158 | I111: =I98-I87-I90+I106-I88+I107-I91+I109 -> 20.257185 | J111: =J98-J87-J90+J106-J88+J107-J91+J109 -> 19.212706 | K111: ct/kWh
A112: LCOEF_alternative | B112: =B111/3.6 -> 16.204917 | C112: =C111/3.6 -> 16.770195 | D112: =D111/3.6 -> 15.706944 | E112: =E111/3.6 -> 5.6342605 | F112: =F111/3.6 -> 4.6681521 | G112: =G111/3.6 -> 3.8360451 | H112: =H111/3.6 -> 5.477544 | I112: =I111/3.6 -> 5.6269957 | J112: =J111/3.6 -> 5.3368626 | K112: ct/MJ
A113: LCOEF_alternative | B113: =B112*Inputs!$C$14 / 100 -> 5.6214209 | C113: =C112*Inputs!$C$14 / 100 -> 5.8175136 | D113: =D112*Inputs!$C$14 / 100 -> 5.4486761 | E113: =E112*Inputs!$C$14 / 100 -> 1.9545024 | F113: =F112*Inputs!$C$14 / 100 -> 1.6193633 | G113: =G112*Inputs!$C$14 / 100 -> 1.3307087 | H113: =H112*Inputs!$C$14 / 100 -> 1.9001381 | I113: =I112*Inputs!$C$14 / 100 -> 1.9519823 | J113: =J112*Inputs!$C$14 / 100 -> 1.8513363 | K113: €/l

Sheet WACC Corrected LCOF
A1: WACC_source | B1: 0.06 | C1: 0.06 | D1: 0.06 | E1: 0.06 | F1: 0.06 | G1: 0.06 | H1: 0.06 | I1: 0.06 | J1: 0.06 | K1: -
A2: WACC_alternative | B2: =Inputs!$C$5 -> 0.07 | C2: =Inputs!$C$5 -> 0.07 | D2: =Inputs!$C$5 -> 0.07 | E2: =Inputs!$C$5 -> 0.07 | F2: =Inputs!$C$5 -> 0.07 | G2: =Inputs!$C$5 -> 0.07 | H2: =Inputs!$C$5 -> 0.07 | I2: =Inputs!$C$5 -> 0.07 | J2: =Inputs!$C$5 -> 0.07 | K2: -
A3: LCOE_alternative | B3: =Inputs!$C$8*Inputs!$C$6 / 10 -> 5.76 | C3: =Inputs!$C$8*Inputs!$C$6 / 10 -> 5.76 | D3: =Inputs!$C$8*Inputs!$C$6 / 10 -> 5.76 | E3: 5.9593963 | F3: 3.6109404 | G3: 2.969201 | H3: =Inputs!$C$9*Inputs!$C$6 / 10 -> 0.99 | I3: =Inputs!$C$9*Inputs!$C$6 / 10 -> 0.99 | J3: =Inputs!$C$9*Inputs!$C$6 / 10 -> 0.99 | K3: ct/kWh
B4: 11.1 | C4: 11.1 | D4: 11.1 | E4: 7.5 | F4: 7.5 | G4: 7.5 | H4: 3.9 | I4: 3.9 | J4: 3.9 | L4: Note: this is the standard LCOE curve
A5: DAC_source | B5: 460 | C5: 460 | D5: 460 | E5: 135 | F5: 135 | G5: 135 | H5: 80 | I5: 80 | J5: 80 | K5: €/tCO2
A6: DAC_alternative | B6: =Inputs!$C$32*Inputs!$C$6 -> 1153.8 | C6: =Inputs!$C$32*Inputs!$C$6 -> 1153.8 | D6: =Inputs!$C$32*Inputs!$C$6 -> 1153.8 | E6: 135 | F6: 135 | G6: 135 | H6: =Inputs!$C$33*Inputs!$C$6 -> 432 | I6: =Inputs!$C$33*Inputs!$C$6 -> 432 | J6: =Inputs!$C$33*Inputs!$C$6 -> 432 | K6: €/tCO2 | L6: Average between SS and LS DAC
B7: 731.19867 | C7: 731.19867 | D7: 731.19867 | E7: 449.5681 | F7: 449.5681 | G7: 449.5681 | H7: 298.29332 | I7: 298.29332 | J7: 298.29332 | L7: Note: this is modelled DAC cost
A8: Levelized cost of electricity [ct/kWh]
B10: 2020 | E10: 2035 | H10: 2050
B11: Offshore | C11: Onshore | D11: Hydro | E11: Offshore | F11: Onshore | G11: Hydro | H11: Offshore | I11: Onshore | J11: Hydro | N11: 2020 Offshore | O11: 2020 Onshore
A12: Capex generation | B12: 5.6892159 | C12: 4.0867761 | D12: 2.1299153 | E12: 3.5557599 | F12: 2.8062529 | G12: 2.1299153 | H12: 2.9335019 | I12: 2.5882915 | J12: 2.1299153 | K12: ct/kWh | M12: CAPEX | N12: 3200 | O12: 1500
A13: Opex generation | B13: 2.1818182 | C13: 1.171875 | D13: 0.83928571 | E13: 1.3636364 | F13: 0.8046875 | G13: 0.83928571 | H13: 1.125 | I13: 0.7421875 | J13: 0.83928571 | K13: ct/kWh | M13: Loadhours | N13: 4400 | O13: 3200
A14: Offshore grid fee | B14: 1.5 | C14: 0 | D14: 0 | E14: 1.04 | F14: 0 | G14: 0 | H14: 0.7 | I14: 0 | J14: 0 | K14: ct/kWh | M14: UCRF | N14: =B23 -> 0.078226718 | O14: =C23 -> 0.087184557
M15: Annualized CAPEX | N15: =N12*N14/N13 -> 0.056892159 | O15: =O12*O14/O13 -> 0.040867761 | P15: €/kWh
A16: BC | B16: 1.377431 | C16: 0.80426429 | D16: 0.37115013 | E16: 1.3238642 | F16: 1.1857743 | G16: 0.37115013 | H16: 1.292708 | I16: 1.020797 | J16: 0.37115013 | K16: ct/kWh | N16: =N15*100 -> 5.6892159 | O16: =O15*100 -> 4.0867761 | P16: ct/kWh
A17: WC | B17: 1.4414975 | C17: 0.91149953 | D17: 0.49486684 | E17: 1.3602703 | F17: 1.3812724 | G17: 0.49486684 | H17: 1.352834 | I17: 1.1569032 | J17: 0.49486684 | K17: ct/kWh
A19: LCOE | B19: =SUM(B12:B14) -> 9.3710341 | C19: =SUM(C12:C14) -> 5.2586511 | D19: =SUM(D12:D14) -> 2.969201 | E19: =SUM(E12:E14) -> 5.9593963 | F19: =SUM(F12:F14) -> 3.6109404 | G19: =SUM(G12:G14) -> 2.969201 | H19: =SUM(H12:H14) -> 4.7585019 | I19: =SUM(I12:I14) -> 3.330479 | J19: =SUM(J12:J14) -> 2.969201 | K19: ct/kWh
A20: LCOE | B20: =B19*10 -> 93.710341 | C20: =C19*10 -> 52.586511 | D20: =D19*10 -> 29.69201 | E20: =E19*10 -> 59.593963 | F20: =F19*10 -> 36.109404 | G20: =G19*10 -> 29.69201 | H20: =H19*10 -> 47.585019 | I20: =I19*10 -> 33.30479 | J20: =J19*10 -> 29.69201 | K20: €/MWh
A22: Lifetime | B22: 25 | C22: 20 | D22: 50 | E22: 25 | F22: 20 | G22: 50 | H22: 25 | I22: 20 | J22: 50 | K22: years | M22: WACC
A23: UCRF | B23: =(B$1*(1+B$1)^B22)/((1+B$1)^B22-1) -> 0.078226718 | C23: =(C$1*(1+C$1)^C22)/((1+C$1)^C22-1) -> 0.087184557 | D23: =(D$1*(1+D$1)^D22)/((1+D$1)^D22-1) -> 0.063444286 | E23: =(E$1*(1+E$1)^E22)/((1+E$1)^E22-1) -> 0.078226718 | F23: =(F$1*(1+F$1)^F22)/((1+F$1)^F22-1) -> 0.087184557 | G23: =(G$1*(1+G$1)^G22)/((1+G$1)^G22-1) -> 0.063444286 | H23: =(H$1*(1+H$1)^H22)/((1+H$1)^H22-1) -> 0.078226718 | I23: =(I$1*(1+I$1)^I22)/((1+I$1)^I22-1) -> 0.087184557 | J23: =(J$1*(1+J$1)^J22)/((1+J$1)^J22-1) -> 0.063444286 | K23: - | M23: WACC
A25: UCRF_alternative | B25: =(B$2*(1+B$2)^B22)/((1+B$2)^B22-1) -> 0.085810517 | C25: =(C$2*(1+C$2)^C22)/((1+C$2)^C22-1) -> 0.094392926 | D25: =(D$2*(1+D$2)^D22)/((1+D$2)^D22-1) -> 0.07245985 | E25: =(E$2*(1+E$2)^E22)/((1+E$2)^E22-1) -> 0.085810517 | F25: =(F$2*(1+F$2)^F22)/((1+F$2)^F22-1) -> 0.094392926 | G25: =(G$2*(1+G$2)^G22)/((1+G$2)^G22-1) -> 0.07245985 | H25: =(H$2*(1+H$2)^H22)/((1+H$2)^H22-1) -> 0.085810517 | I25: =(I$2*(1+I$2)^I22)/((1+I$2)^I22-1) -> 0.094392926 | J25: =(J$2*(1+J$2)^J22)/((1+J$2)^J22-1) -> 0.07245985 | K25: - | M25: WACC
A26: Capex generation_alternative | B26: =B12/B23*B25 -> 6.2407649 | C26: =C12/C23*C25 -> 4.4246684 | D26: =D12/D23*D25 -> 2.4325807 | E26: =E12/E23*E25 -> 3.9004781 | F26: =F12/F23*F25 -> 3.0382723 | G26: =G12/G23*G25 -> 2.4325807 | H26: =H12/H23*H25 -> 3.2178944 | I26: =I12/I23*I25 -> 2.80229 | J26: =J12/J23*J25 -> 2.4325807 | K26: ct/kWh | M26: WACC
A27: LCOE_alternative | B27: =B19-B12+B26 -> 9.9225831 | C27: =C19-C12+C26 -> 5.5965434 | D27: =D19-D12+D26 -> 3.2718664 | E27: =E19-E12+E26 -> 6.3041144 | F27: =F19-F12+F26 -> 3.8429598 | G27: =G19-G12+G26 -> 3.2718664 | H27: =H19-H12+H26 -> 5.0428944 | I27: =I19-I12+I26 -> 3.5444775 | J27: =J19-J12+J26 -> 3.2718664 | K27: ct/kWh
A29: Levelized cost of hydrogen [ct/kWh]
B31: 2020 | E31: 2035 | H31: 2050
B32: Offshore | C32: Onshore | D32: Hydro | E32: Offshore | F32: Onshore | G32: Hydro | H32: Offshore | I32: Onshore | J32: Hydro
A33: Capex electrolysis | B33: 3.0462118 | C33: 4.1885412 | D33: 1.9147617 | E33: 1.3931149 | F33: 1.915533 | G33: 0.87567222 | H33: 0.81260441 | I33: 1.1173311 | J33: 0.51077992 | K33: ct/kWh
A34: Opex electrolysis | B34: 1.1682243 | C34: 1.6063084 | D34: 0.73431242 | E34: 0.53426052 | F34: 0.73460821 | G34: 0.3358209 | H34: 0.31163435 | I34: 0.42849723 | J34: 0.19588445 | K34: ct/kWh
A35: Electricity cost | B35: 14.596626 | C35: 8.1910453 | D35: 4.6249237 | E35: 8.8946213 | F35: 5.3894633 | G35: 4.4316433 | H35: 6.5907229 | I35: 4.6128518 | J35: 4.1124668 | K35: ct/kWh
A36: Storage cost | B36: 2.9792732 | C36: 2.9792732 | D36: 2.9792732 | E36: 2.3792732 | F36: 2.3792732 | G36: 2.3792732 | H36: 1.9792732 | I36: 1.9792732 | J36: 1.9792732 | K36: ct/kWh
A37: Liquefaction cost | B37: 3.7938486 | C37: 3.7938486 | D37: 3.7938486 | E37: 2.1404261 | F37: 2.1404261 | G37: 2.1404261 | H37: 1.4308452 | I37: 1.4308452 | J37: 1.4308452 | K37: ct/kWh
A38: Distribution cost | B38: 0.225 | C38: 0.225 | D38: 0.225 | E38: 0.195 | F38: 0.195 | G38: 0.195 | H38: 0.1875 | I38: 0.1875 | J38: 0.1875 | K38: ct/kWh
A40: BC | B40: 5.0944468 | C40: 4.5421905 | D40: 2.3451036 | E40: 4.0195481 | F40: 3.9103357 | G40: 2.0092187 | H40: 3.0022965 | I40: 2.7698807 | J40: 1.3897171 | K40: ct/kWh
A41: WC | B41: 6.2445545 | C41: 5.9119403 | D41: 3.4038153 | E41: 4.7428356 | F41: 5.0150862 | G41: 2.5555799 | H41: 4.1084781 | I41: 4.0463644 | J41: 2.3824229 | K41: ct/kWh
A43: LCOH | B43: =SUM(B33:B38) -> 25.809184 | C43: =SUM(C33:C38) -> 20.984017 | D43: =SUM(D33:D38) -> 14.27212 | E43: =SUM(E33:E38) -> 15.536696 | F43: =SUM(F33:F38) -> 12.754304 | G43: =SUM(G33:G38) -> 10.357836 | H43: =SUM(H33:H38) -> 11.31258 | I43: =SUM(I33:I38) -> 9.7562986 | J43: =SUM(J33:J38) -> 8.4167496 | K43: ct/kWh
A45: Electricity consumption | B45: =B35/B19 -> 1.5576324 | C45: =C35/C19 -> 1.5576324 | D45: =D35/D19 -> 1.5576324 | E45: =E35/E19 -> 1.4925373 | F45: =F35/F19 -> 1.4925373 | G45: =G35/G19 -> 1.4925373 | H45: =H35/H19 -> 1.3850416 | I45: =I35/I19 -> 1.3850416 | J45: =J35/J19 -> 1.3850416 | K45: kWh_el/kWh_fuel | M45: LCOE
A47: Lifetime | B47: 25 | C47: 25 | D47: 25 | E47: 25 | F47: 25 | G47: 25 | H47: 25 | I47: 25 | J47: 25 | K47: years | M47: WACC
A48: UCRF | B48: =(B$1*(1+B$1)^B47)/((1+B$1)^B47-1) -> 0.078226718 | C48: =(C$1*(1+C$1)^C47)/((1+C$1)^C47-1) -> 0.078226718 | D48: =(D$1*(1+D$1)^D47)/((1+D$1)^D47-1) -> 0.078226718 | E48: =(E$1*(1+E$1)^E47)/((1+E$1)^E47-1) -> 0.078226718 | F48: =(F$1*(1+F$1)^F47)/((1+F$1)^F47-1) -> 0.078226718 | G48: =(G$1*(1+G$1)^G47)/((1+G$1)^G47-1) -> 0.078226718 | H48: =(H$1*(1+H$1)^H47)/((1+H$1)^H47-1) -> 0.078226718 | I48: =(I$1*(1+I$1)^I47)/((1+I$1)^I47-1) -> 0.078226718 | J48: =(J$1*(1+J$1)^J47)/((1+J$1)^J47-1) -> 0.078226718 | K48: - | M48: WACC
A50: UCRF_alternative | B50: =(B$2*(1+B$2)^B47)/((1+B$2)^B47-1) -> 0.085810517 | C50: =(C$2*(1+C$2)^C47)/((1+C$2)^C47-1) -> 0.085810517 | D50: =(D$2*(1+D$2)^D47)/((1+D$2)^D47-1) -> 0.085810517 | E50: =(E$2*(1+E$2)^E47)/((1+E$2)^E47-1) -> 0.085810517 | F50: =(F$2*(1+F$2)^F47)/((1+F$2)^F47-1) -> 0.085810517 | G50: =(G$2*(1+G$2)^G47)/((1+G$2)^G47-1) -> 0.085810517 | H50: =(H$2*(1+H$2)^H47)/((1+H$2)^H47-1) -> 0.085810517 | I50: =(I$2*(1+I$2)^I47)/((1+I$2)^I47-1) -> 0.085810517 | J50: =(J$2*(1+J$2)^J47)/((1+J$2)^J47-1) -> 0.085810517 | K50: - | M50: WACC
A51: Electricity cost_alternative | B51: =B45*B3 -> 8.9719626 | C51: =C45*C3 -> 8.9719626 | D51: =D45*D3 -> 8.9719626 | E51: =E45*E3 -> 8.8946213 | F51: =F45*F3 -> 5.3894633 | G51: =G45*G3 -> 4.4316433 | H51: =H45*H3 -> 1.3711911 | I51: =I45*I3 -> 1.3711911 | J51: =J45*J3 -> 1.3711911 | K51: ct/kWh | M51: LCOE
A52: Capex electrolysis_alternative | B52: =B33/B48*B50 -> 3.341531 | C52: =C33/C48*C50 -> 4.5946052 | D52: =D33/D48*D50 -> 2.1003909 | E52: =E33/E48*E50 -> 1.5281724 | F52: =F33/F48*F50 -> 2.101237 | G52: =G33/G48*G50 -> 0.96056549 | H52: =H33/H48*H50 -> 0.89138349 | I52: =I33/I48*I50 -> 1.2256523 | J52: =J33/J48*J50 -> 0.56029819 | K52: ct/kWh | M52: WACC
A53: LCOH_alternative | B53: =B43-B33+B52-B35+B51 -> 20.47984 | C53: =C43-C33+C52-C35+C51 -> 22.170998 | D53: =D43-D33+D52-D35+D51 -> 18.804788 | E53: =E43-E33+E52-E35+E51 -> 15.671753 | F53: =F43-F33+F52-F35+F51 -> 12.940008 | G53: =G43-G33+G52-G35+G51 -> 10.442729 | H53: =H43-H33+H52-H35+H51 -> 6.1718274 | I53: =I43-I33+I52-I35+I51 -> 6.6229591 | J53: =J43-J33+J52-J35+J51 -> 5.7249922 | K53: ct/kWh
A55: Levelized cost of ammonia [ct/kWh]
B57: 2020 | E57: 2035 | H57: 2050
B58: Offshore | C58: Onshore | D58: Hydro | E58: Offshore | F58: Onshore | G58: Hydro | H58: Offshore | I58: Onshore | J58: Hydro
A59: Electrolysis & storage cost | B59: 5.8617929 | C59: 7.6454453 | D59: 4.0951278 | E59: 3.2806198 | F59: 4.0963321 | G59: 2.4726761 | H59: 2.374201 | I59: 2.8500063 | J59: 1.9029271 | K59: ct/kWh
A60: Electricity cost electrolysis | B60: 16.47373 | C60: 9.2444014 | D60: 5.2196819 | E60: 10.038456 | F60: 6.0825401 | G60: 5.001546 | H60: 7.4382799 | I60: 5.2060576 | J60: 4.6413238 | K60: ct/kWh
A61: Capex synthesis | B61: 0.90398361 | C61: 0.90398361 | D61: 0.90398361 | E61: 0.90398361 | F61: 0.90398361 | G61: 0.90398361 | H61: 0.90398361 | I61: 0.90398361 | J61: 0.90398361 | K61: ct/kWh
A62: Opex synthesis | B62: 0.62215909 | C62: 0.62215909 | D62: 0.62215909 | E62: 0.62215909 | F62: 0.62215909 | G62: 0.62215909 | H62: 0.62215909 | I62: 0.62215909 | J62: 0.62215909 | K62: ct/kWh
A63: Electricity costs synthesis | B63: 0.1375 | C63: 0.1375 | D63: 0.1375 | E63: 0.1375 | F63: 0.1375 | G63: 0.1375 | H63: 0.1375 | I63: 0.1375 | J63: 0.325 | K63: ct/kWh
A64: Storage cost | B64: 0.325 | C64: 0.325 | D64: 0.325 | E64: 0.325 | F64: 0.325 | G64: 0.325 | H64: 0.325 | I64: 0.325 | J64: 0.325 | K64: ct/kWh
A65: Distribution cost | B65: 0.0625 | C65: 0.0625 | D65: 0.0625 | E65: 0.04625 | F65: 0.04625 | G65: 0.04625 | H65: 0.0375 | I65: 0.0375 | J65: 0.0375 | K65: ct/kWh
A67: BC | B67: 5.6659076 | C67: 5.0426319 | D67: 2.563003 | E67: 4.1720267 | F67: 4.0487697 | G67: 1.903172 | H67: 3.3808903 | I67: 3.1185862 | J67: 1.5609356 | K67: ct/kWh
A68: WC | B68: 6.9639174 | C68: 6.5885295 | D68: 3.7578634 | E68: 5.3391657 | F68: 5.6464272 | G68: 2.8706322 | H68: 4.2165748 | I68: 4.1464734 | J68: 2.2685515 | K68: ct/kWh
A70: LCOA | B70: =SUM(B59:B65) -> 24.386666 | C70: =SUM(C59:C65) -> 18.940989 | D70: =SUM(D59:D65) -> 11.365952 | E70: =SUM(E59:E65) -> 15.353969 | F70: =SUM(F59:F65) -> 12.213765 | G70: =SUM(G59:G65) -> 9.5091148 | H70: =SUM(H59:H65) -> 11.838624 | I70: =SUM(I59:I65) -> 10.082207 | J70: =SUM(J59:J65) -> 8.7578936 | K70: ct/kWh
N71: eAmmonia
A72: Electricity consumption | B72: =(B60+B63)/B19 -> 1.7726144 | C72: =(C60+C63)/C19 -> 1.784089 | D72: =(D60+D63)/D19 -> 1.8042503 | E72: =(E60+E63)/E19 -> 1.7075482 | F72: =(F60+F63)/F19 -> 1.7225541 | G72: =(G60+G63)/G19 -> 1.7307841 | H72: =(H60+H63)/H19 -> 1.5920514 | I72: =(I60+I63)/I19 -> 1.6044411 | J72: =(J60+J63)/J19 -> 1.6726129 | K72: kWh_el/kWh_fuel | M72: LCOE | N72: 738 | O72: kWh_el/t_fuel
N73: 5.28 | O73: kWh_fuel/kg_fuel
A74: Lifetime | B74: 30 | C74: 30 | D74: 30 | E74: 30 | F74: 30 | G74: 30 | H74: 30 | I74: 30 | J74: 30 | K74: years | M74: WACC | N74: =N73/1000 -> 0.00528 | O74: kWh_fuel/t_fuel
A75: UCRF | B75: =(B$1*(1+B$1)^B74)/((1+B$1)^B74-1) -> 0.072648911 | C75: =(C$1*(1+C$1)^C74)/((1+C$1)^C74-1) -> 0.072648911 | D75: =(D$1*(1+D$1)^D74)/((1+D$1)^D74-1) -> 0.072648911 | E75: =(E$1*(1+E$1)^E74)/((1+E$1)^E74-1) -> 0.072648911 | F75: =(F$1*(1+F$1)^F74)/((1+F$1)^F74-1) -> 0.072648911 | G75: =(G$1*(1+G$1)^G74)/((1+G$1)^G74-1) -> 0.072648911 | H75: =(H$1*(1+H$1)^H74)/((1+H$1)^H74-1) -> 0.072648911 | I75: =(I$1*(1+I$1)^I74)/((1+I$1)^I74-1) -> 0.072648911 | J75: =(J$1*(1+J$1)^J74)/((1+J$1)^J74-1) -> 0.072648911 | K75: - | M75: WACC | N75: 0.99 | O75: Efficiency
N76: =N72/N74*0.99 -> 138375 | O76: kWh_el/kWh_fuel
A77: UCRF_alternative | B77: =(B$2*(1+B$2)^B74)/((1+B$2)^B74-1) -> 0.080586404 | C77: =(C$2*(1+C$2)^C74)/((1+C$2)^C74-1) -> 0.080586404 | D77: =(D$2*(1+D$2)^D74)/((1+D$2)^D74-1) -> 0.080586404 | E77: =(E$2*(1+E$2)^E74)/((1+E$2)^E74-1) -> 0.080586404 | F77: =(F$2*(1+F$2)^F74)/((1+F$2)^F74-1) -> 0.080586404 | G77: =(G$2*(1+G$2)^G74)/((1+G$2)^G74-1) -> 0.080586404 | H77: =(H$2*(1+H$2)^H74)/((1+H$2)^H74-1) -> 0.080586404 | I77: =(I$2*(1+I$2)^I74)/((1+I$2)^I74-1) -> 0.080586404 | J77: =(J$2*(1+J$2)^J74)/((1+J$2)^J74-1) -> 0.080586404 | K77: - | M77: WACC
A78: Electricity cost_alternative | B78: =B72*B3 -> 10.210259 | C78: =C72*C3 -> 10.276352 | D78: =D72*D3 -> 10.392482 | E78: =E72*E3 -> 10.175956 | F78: =F72*F3 -> 6.2200401 | G78: =G72*G3 -> 5.139046 | H78: =H72*H3 -> 1.5761309 | I78: =I72*I3 -> 1.5883967 | J78: =J72*J3 -> 1.6558867 | K78: ct/kWh | M78: LCOE
A79: Capex electrolysis_alternative | B79: =B61/B75*B77 -> 1.0027513 | C79: =C61/C75*C77 -> 1.0027513 | D79: =D61/D75*D77 -> 1.0027513 | E79: =E61/E75*E77 -> 1.0027513 | F79: =F61/F75*F77 -> 1.0027513 | G79: =G61/G75*G77 -> 1.0027513 | H79: =H61/H75*H77 -> 1.0027513 | I79: =I61/I75*I77 -> 1.0027513 | J79: =J61/J75*J77 -> 1.0027513 | K79: ct/kWh | M79: WACC
A80: LCOA_alternative | B80: =B70-B60-B63+B79-B61+B78 -> 18.084462 | C80: =C70-C60-C63+C79-C61+C78 -> 19.934208 | D80: =D70-D60-D63+D79-D61+D78 -> 16.50002 | E80: =E70-E60-E63+E79-E61+E78 -> 15.452736 | F80: =F70-F60-F63+F79-F61+F78 -> 12.312533 | G80: =G70-G60-G63+G79-G61+G78 -> 9.6078824 | H80: =H70-H60-H63+H79-H61+H78 -> 5.9377422 | I80: =I70-I60-I63+I79-I61+I78 -> 6.4258134 | J80: =J70-J60-J63+J79-J61+J78 -> 5.5462242 | K80: ct/kWh | M80: WACC
A82: Levelized cost of e-fuel [ct/kWh]
B84: 2020 | E84: 2035 | H84: 2050
B85: Offshore | C85: Onshore | D85: Hydro | E85: Offshore | F85: Onshore | G85: Hydro | H85: Offshore | I85: Onshore | J85: Hydro
A86: Electrolysis & storage cost | B86: 6.4923365 | C86: 8.4678535 | D86: 4.5356341 | E86: 3.6335107 | F86: 4.5369679 | G86: 2.7386579 | H86: 2.6295899 | I86: 3.1565768 | J86: 2.1076219 | K86: ct/kWh
A87: Electricity cost electrolysis | B87: 18.245783 | C87: 10.238807 | D87: 5.7811547 | E87: 11.118277 | F87: 6.7368292 | G87: 5.5395542 | H87: 8.2384036 | I87: 5.7660648 | J87: 5.1405835 | K87: ct/kWh
A88: Capex synthesis | B88: 0.78226718 | C88: 0.78226718 | D88: 0.78226718 | E88: 0.51336284 | F88: 0.51336284 | G88: 0.51336284 | H88: 0.39113359 | I88: 0.39113359 | J88: 0.39113359 | K88: ct/kWh
A89: Opex synthesis | B89: 0.35 | C89: 0.35 | D89: 0.35 | E89: 0.2296875 | F89: 0.2296875 | G89: 0.2296875 | H89: 0.175 | I89: 0.175 | J89: 0.175 | K89: ct/kWh
A90: Electricity costs synthesis | B90: 0.12375 | C90: 0.12375 | D90: 0.12375 | E90: 0.12375 | F90: 0.12375 | G90: 0.12375 | H90: 0.12375 | I90: 0.12375 | J90: 0.12375 | K90: ct/kWh
A91: CO2 cost | B91: 15.686 | C91: 15.686 | D91: 15.686 | E91: 4.6035 | F91: 4.6035 | G91: 4.6035 | H91: 2.728 | I91: 2.728 | J91: 2.728 | K91: ct/kWh
A92: Storage costs | B92: 0.04 | C92: 0.04 | D92: 0.04 | E92: 0.04 | F92: 0.04 | G92: 0.04 | H92: 0.04 | I92: 0.04 | J92: 0.04 | K92: ct/kWh
A93: Distribution cost | B93: 0.0375 | C93: 0.0375 | D93: 0.0375 | E93: 0.02125 | F93: 0.02125 | G93: 0.02125 | H93: 0.0125 | I93: 0.0125 | J93: 0.0125 | K93: ct/kWh
A95: BC | B95: 9.4671086 | C95: 8.7767882 | D95: 6.0304296 | E95: 6.14035 | F95: 6.0038345 | G95: 3.6274383 | H95: 4.8195291 | I95: 4.5290093 | J95: 2.8038048 | K95: ct/kWh
A96: WC | B96: 10.904743 | C96: 10.488975 | D96: 7.3538193 | E96: 7.6241064 | F96: 7.9644196 | G96: 4.8900367 | H96: 6.0281736 | I96: 5.9505315 | J96: 3.8706046 | K96: ct/kWh
A98: LCOEF | B98: =SUM(B86:B93) -> 41.757637 | C98: =SUM(C86:C93) -> 35.726177 | D98: =SUM(D86:D93) -> 27.336306 | E98: =SUM(E86:E93) -> 20.283338 | F98: =SUM(F86:F93) -> 16.805347 | G98: =SUM(G86:G93) -> 13.809762 | H98: =SUM(H86:H93) -> 14.338377 | I98: =SUM(I86:I93) -> 12.393025 | J98: =SUM(J86:J93) -> 10.718589 | K98: ct/kWh
A100: Electricity consumption | B100: =(B87+B90)/B19 -> 1.9602461 | C100: =(C87+C90)/C19 -> 1.9705731 | D100: =(D87+D90)/D19 -> 1.9887184 | E100: =(E87+E90)/E19 -> 1.8864372 | F100: =(F87+F90)/F19 -> 1.8999425 | G100: =(G87+G90)/G19 -> 1.9073495 | H100: =(H87+H90)/H19 -> 1.757308 | I100: =(I87+I90)/I19 -> 1.7684588 | J100: =(J87+J90)/J19 -> 1.7729798 | K100: kWh_el/kWh_fuel
A102: Lifetime | B102: 25 | C102: 25 | D102: 25 | E102: 25 | F102: 25 | G102: 25 | H102: 25 | I102: 25 | J102: 25 | K102: years
A103: UCRF | B103: =(B$1*(1+B$1)^B102)/((1+B$1)^B102-1) -> 0.078226718 | C103: =(C$1*(1+C$1)^C102)/((1+C$1)^C102-1) -> 0.078226718 | D103: =(D$1*(1+D$1)^D102)/((1+D$1)^D102-1) -> 0.078226718 | E103: =(E$1*(1+E$1)^E102)/((1+E$1)^E102-1) -> 0.078226718 | F103: =(F$1*(1+F$1)^F102)/((1+F$1)^F102-1) -> 0.078226718 | G103: =(G$1*(1+G$1)^G102)/((1+G$1)^G102-1) -> 0.078226718 | H103: =(H$1*(1+H$1)^H102)/((1+H$1)^H102-1) -> 0.078226718 | I103: =(I$1*(1+I$1)^I102)/((1+I$1)^I102-1) -> 0.078226718 | J103: =(J$1*(1+J$1)^J102)/((1+J$1)^J102-1) -> 0.078226718 | K103: -
A105: UCRF_alternative | B105: =(B$2*(1+B$2)^B102)/((1+B$2)^B102-1) -> 0.085810517 | C105: =(C$2*(1+C$2)^C102)/((1+C$2)^C102-1) -> 0.085810517 | D105: =(D$2*(1+D$2)^D102)/((1+D$2)^D102-1) -> 0.085810517 | E105: =(E$2*(1+E$2)^E102)/((1+E$2)^E102-1) -> 0.085810517 | F105: =(F$2*(1+F$2)^F102)/((1+F$2)^F102-1) -> 0.085810517 | G105: =(G$2*(1+G$2)^G102)/((1+G$2)^G102-1) -> 0.085810517 | H105: =(H$2*(1+H$2)^H102)/((1+H$2)^H102-1) -> 0.085810517 | I105: =(I$2*(1+I$2)^I102)/((1+I$2)^I102-1) -> 0.085810517 | J105: =(J$2*(1+J$2)^J102)/((1+J$2)^J102-1) -> 0.085810517 | K105: -
A106: Electricity cost_alternative | B106: =B100*B3 -> 11.291017 | C106: =C100*C3 -> 11.350501 | D106: =D100*D3 -> 11.455018 | E106: =E100*E3 -> 11.242027 | F106: =F100*F3 -> 6.8605792 | G106: =G100*G3 -> 5.6633042 | H106: =H100*H3 -> 1.7397349 | I106: =I100*I3 -> 1.7507742 | J106: =J100*J3 -> 1.75525 | K106: ct/kWh
A107: Capex electrolysis_alternative | B107: =B88/B103*B105 -> 0.85810517 | C107: =C88/C103*C105 -> 0.85810517 | D107: =D88/D103*D105 -> 0.85810517 | E107: =E88/E103*E105 -> 0.56313152 | F107: =F88/F103*F105 -> 0.56313152 | G107: =G88/G103*G105 -> 0.56313152 | H107: =H88/H103*H105 -> 0.42905259 | I107: =I88/I103*I105 -> 0.42905259 | J107: =J88/J103*J105 -> 0.42905259 | K107: ct/kWh
A109: CO2 cost_alternative | B109: =B91/B5*B6 -> 39.34458 | C109: =C91/C5*C6 -> 39.34458 | D109: =D91/D5*D6 -> 39.34458 | E109: =E91/E5*E6 -> 4.6035 | F109: =F91/F5*F6 -> 4.6035 | G109: =G91/G5*G6 -> 4.6035 | H109: =H91/H5*H6 -> 14.7312 | I109: =I91/I5*I6 -> 14.7312 | J109: =J91/J5*J6 -> 14.7312 | K109: ct/kWh
A111: LCOEF_alternative | B111: =B98-B87-B90+B106-B88+B107-B91+B109 -> 58.413539 | C111: =C98-C87-C90+C106-C88+C107-C91+C109 -> 60.44854 | D111: =D98-D87-D90+D106-D88+D107-D91+D109 -> 56.620837 | E111: =E98-E87-E90+E106-E88+E107-E91+E109 -> 20.333106 | F111: =F98-F87-F90+F106-F88+F107-F91+F109 -> 16.855116 | G111: =G98-G87-G90+G106-G88+G107-G91+G109 -> 13.859531 | H111: =H98-H87-H90+H106-H88+H107-H91+H109 -> 19.757077 | I111: =I98-I87-I90+I106-I88+I107-I91+I109 -> 20.295104 | J111: =J98-J87-J90+J106-J88+J107-J91+J109 -> 19.250625 | K111: ct/kWh
A112: LCOEF_alternative | B112: =B111/3.6 -> 16.225983 | C112: =C111/3.6 -> 16.791261 | D112: =D111/3.6 -> 15.72801 | E112: =E111/3.6 -> 5.6480851 | F112: =F111/3.6 -> 4.6819767 | G112: =G111/3.6 -> 3.8498697 | H112: =H111/3.6 -> 5.4880771 | I112: =I111/3.6 -> 5.6375288 | J112: =J111/3.6 -> 5.3473957 | K112: ct/MJ
A113: LCOEF_alternative | B113: =B112*Inputs!$C$14 / 100 -> 5.6287286 | C113: =C112*Inputs!$C$14 / 100 -> 5.8248213 | D113: =D112*Inputs!$C$14 / 100 -> 5.4559839 | E113: =E112*Inputs!$C$14 / 100 -> 1.9592981 | F113: =F112*Inputs!$C$14 / 100 -> 1.624159 | G113: =G112*Inputs!$C$14 / 100 -> 1.3355044 | H113: =H112*Inputs!$C$14 / 100 -> 1.903792 | I113: =I112*Inputs!$C$14 / 100 -> 1.9556362 | J113: =J112*Inputs!$C$14 / 100 -> 1.8549902 | K113: €/l

Sheet Outputs
A1: 2024 | H1: 2050
A2: Parameter | B2: Unit | C2: Base Case | D2: LCOE Corrected | E2: CO2 Cost Corrected | F2: WACC Corrected | H2: Parameter | I2: Unit | J2: Base Case | K2: LCOE Corrected | L2: CO2 Cost Corrected | M2: WACC Corrected
A3: Syn-Fuel cost | B3: €/l | C3: =AVERAGE('Base LCOF'!B113:D113) -> 3.3668222 | D3: ='LCOE Corrected LCOF'!B113 -> 3.3416801 | E3: =AVERAGE('CO2 Price Corrected LCOF'!B113:D113) -> 5.6292035 | F3: =AVERAGE('WACC Corrected LCOF'!B113:D113) -> 5.6365113 | H3: Syn-Fuel cost | I3: €/l | J3: =AVERAGE('Base LCOF'!H113:J113) -> 1.2028937 | K3: =AVERAGE('LCOE Corrected LCOF'!H113:J113) -> 0.74452389 | L3: =AVERAGE('CO2 Price Corrected LCOF'!H113:J113) -> 1.9011522 | M3: =AVERAGE('WACC Corrected LCOF'!H113:J113) -> 1.9048061
A4: Syn-Fuel cost | B4: $/l | C4: =C3/Inputs!$C$6 -> 3.7409136 | D4: =D3/Inputs!$C$6 -> 3.7129779 | E4: =E3/Inputs!$C$6 -> 6.2546706 | F4: =F3/Inputs!$C$6 -> 6.2627903 | H4: Syn-Fuel cost | I4: $/l | J4: =J3/Inputs!$C$6 -> 1.3365486 | K4: =K3/Inputs!$C$6 -> 0.82724876 | L4: =L3/Inputs!$C$6 -> 2.1123914 | M4: =M3/Inputs!$C$6 -> 2.1164512
A5: Fossil Fuel cost | B5: $/l | C5: =Inputs!$C$16 -> 0.8 | D5: =Inputs!$C$16 -> 0.8 | E5: =Inputs!$C$16 -> 0.8 | F5: =Inputs!$C$16 -> 0.8 | H5: Fossil Fuel cost | I5: $/l | J5: =Inputs!$C$18 -> 0.8 | K5: =Inputs!$C$18 -> 0.8 | L5: =Inputs!$C$18 -> 0.8 | M5: =Inputs!$C$18 -> 0.8
A6: Syn-Fuel emissions | B6: gCO2eq/MJ | C6: 13.4 | D6: 13.4 | E6: 13.4 | F6: 13.4 | H6: Syn-Fuel emissions | I6: gCO2eq/MJ | J6: 13.4 | K6: 13.4 | L6: 13.4 | M6: 13.4
A7: Fossil Fuel emissions | B7: gCO2eq/MJ | C7: =Inputs!$C$11 -> 88.7 | D7: =Inputs!$C$11 -> 88.7 | E7: =Inputs!$C$11 -> 88.7 | F7: =Inputs!$C$11 -> 88.7 | H7: Fossil Fuel emissions | I7: gCO2eq/MJ | J7: =Inputs!$C$11 -> 88.7 | K7: =Inputs!$C$11 -> 88.7 | L7: =Inputs!$C$11 -> 88.7 | M7: =Inputs!$C$11 -> 88.7
A8: CO2 Abated | B8: gCO2eq/MJ | C8: =C7-C6 -> 75.3 | D8: =D7-D6 -> 75.3 | E8: =E7-E6 -> 75.3 | F8: =F7-F6 -> 75.3 | H8: CO2 Abated | I8: gCO2eq/MJ | J8: =J7-J6 -> 75.3 | K8: =K7-K6 -> 75.3 | L8: =L7-L6 -> 75.3 | M8: =M7-M6 -> 75.3
A9: CO2 Abated | B9: gCO2eq/l | C9: =C8 * Inputs!$C$14 -> 2612.1269 | D9: =D8*Inputs!$C$14 -> 2612.1269 | E9: =E8*Inputs!$C$14 -> 2612.1269 | F9: =F8*Inputs!$C$14 -> 2612.1269 | H9: CO2 Abated | I9: gCO2eq/l | J9: =J8 * Inputs!$C$14 -> 2612.1269 | K9: =K8 * Inputs!$C$14 -> 2612.1269 | L9: =L8 * Inputs!$C$14 -> 2612.1269 | M9: =M8 * Inputs!$C$14 -> 2612.1269
A10: Abatement cost | B10: $/tCO2 | C10: =(C4-C5) / C9 * 10^6 -> 1125.8694 | D10: =(D4-D5) / D9 * 10^6 -> 1115.1747 | E10: =(E4-E5) / E9 * 10^6 -> 2088.2104 | F10: =(F4-F5) / F9 * 10^6 -> 2091.3189 | H10: Abatement cost | I10: $/tCO2 | J10: =(J4-J5) / J9 * 10^6 -> 205.40678 | K10: =(K4-K5) / K9 * 10^6 -> 10.431639 | L10: =(L4-L5) / L9 * 10^6 -> 502.42252 | M10: =(M4-M5) / M9 * 10^6 -> 503.97676
A12: Full Abatement | H12: Full Abatement
A13: Parameter | B13: Unit | C13: Value | H13: Parameter | I13: Unit | J13: Value
A14: Residual Emissions | B14: gCO2eq/l | C14: =C6*Inputs!$C$14 -> 464.84064 | H14: Residual Emissions | I14: gCO2eq/l | J14: =J6*Inputs!$C$14 -> 464.84064
A15: Emissions Reduction Cost | B15: $/l | C15: =C14*Inputs!$C$32 * 10^-6 -> 0.5959257 | H15: Emissions Reduction Cost | I15: $/l | J15: =J14*Inputs!$C$32 * 10^-6 -> 0.5959257
A16: Effective Synfuel Cost | B16: $/l | C16: =F4+C15 -> 6.858716 | H16: Effective Synfuel Cost | I16: $/l | J16: =M4+J15 -> 2.7123769
A17: Effective Abatement Cost | B17: $/tCO2 | C17: =(C16-C5) /C9 * 10^6 -> 2319.457 | H17: Effective Abatement Cost | I17: $/tCO2 | J17: =(J16-J5) /J9 * 10^6 -> 732.11487
