Workbook

Sheet Legend
A1: Scenario Name | B1: Details | C1: Notes
A2: C-P-N | B2: Current - PEM - Nuclear
A3: C-P-R | B3: Current - PEM - Renewable | C3: Very high battery CAPEX, scenario is omitted
A4: C-P-N/R | B4: Current - PEM - Nuclear/Renewable
A5: C-S-N/R | B5: Current - SOEC- Nuclear/Renewable
A6: F-P-N | B6: 2050 - PEM - Nuclear
A7: F-P-R | B7: 2050 - PEM - Renewables
A8: F-P-N/R | B8: 2050 - PEM - Nuclear/Renewables
A9: F-S-N/R | B9: 2050 - SOEC - Nuclear/Renewables

Sheet Inputs
A1: Parameter | B1: Year | C1: Value | D1: Unit
A2: Standard Values
A3: Current Year | C3: 2024
A4: Inflation | C4: =[1]Inputs!C5 -> 0.02
A5: WACC | C5: =[1]Inputs!C6 -> 0.07
A6: USD to EUR | C6: =[1]Inputs!C7 -> 0.9
A7: Electricity
A8: LCOE | B8: 2024 | C8: =[1]Inputs!C9 -> 64 | D8: $/MWh
A9: LCOE | B9: 2050 | C9: =[1]Inputs!C10 -> 11 | D9: $/MWh
A10: Jet Fuel A-1 Characteristics
A11: Emissions Intensity | B11: 2024 | C11: =[1]Inputs!C12 -> 88.7 | D11: gCO2/MJ
A12: Emissions Intensity | B12: 2050 | C12: =[1]Inputs!C13 -> 88.7 | D12: gCO2/MJ
A13: Energy Density | C13: =[1]Inputs!C14 -> 43.2 | D13: MJ/kg
A14: Energy Density | C14: =[1]Inputs!C15 -> 34.6896 | D14: MJ/l
A15: Volumetric Density | C15: =[1]Inputs!C16 -> 0.803 | D15: kg/l
A16: Jet Fuel A-1 Price | B16: 2024 | C16: =[1]Inputs!C17 -> 0.8 | D16: $/l
A17: Scenario Specific Values
A18: Jet Fuel A-1 Price | B18: 2050 | C18: =[1]Inputs!C19 -> 1.7 | D18: $/l
A19: IEA Reference
A20: Jet Fuel A-1 Price | B20: 2024 | C20: =[1]Inputs!C21 -> 0.32246154 | D20: $/l
A21: Jet Fuel A-1 Price | B21: 2050 | C21: =[1]Inputs!C22 -> 0.20923077 | D21: $/l
A22: EIA Reference
A23: Jet Fuel A-1 Price | B23: 2024 | C23: =[1]Inputs!C24 -> 1.0209014 | D23: $/l
A24: Jet Fuel A-1 Price | B24: 2050 | C24: =[1]Inputs!C25 -> 2.0095594 | D24: $/l
A25: EIA Low Oil Price Scenario
A26: Jet Fuel A-1 Price | B26: 2024 | C26: =[1]Inputs!C27 -> 0.48286833 | D26: $/l
A27: Jet Fuel A-1 Price | B27: 2050 | C27: =[1]Inputs!C28 -> 0.89646575 | D27: $/l
A28: EIA High Scenario
A29: Jet Fuel A-1 Price | B29: 2024 | C29: =[1]Inputs!C30 -> 1.8838713 | D29: $/l
A30: Jet Fuel A-1 Price | B30: 2050 | C30: =[1]Inputs!C31 -> 3.7893731 | D30: $/l
A31: Direct Air Capture
A32: LCOR | B32: 2024 | C32: =[1]Inputs!C33 -> 1371 | D32: $/tCO2
A33: LCOR | B33: 2050 | C33: =[1]Inputs!C34 -> 523 | D33: $/tCO2

Sheet Study Parameters
A1: Key Parameters
A2: Parameter | B2: Year | C2: Value | D2: Source | E2: Note
A3: Discount Rate | B3: Both | C3: 0.08 | D3: Peacock et. al.
A4: Lifetime (years) | B4: Both | C4: 30 | D4: Peacock et. al.
A6: Process Parameters
A7: Parameter | B7: Year | C7: Value | D7: Unit | E7: Source | F7: Note
A8: Annual Jet Fuel Production | B8: Both | C8: 0.99 | D8: Mbbl | E8: Peacock et. al.
A9: Annual Jet Fuel Production | B9: Both | C9: =C8*159 * 10^6 -> 157410000 | D9: l | F9: Calculated (1 barrel = 159 litres)
A10: Annual CO2 Consumption | B10: Both | C10: 1 | D10: Mt | E10: Peacock et. al.
A11: Annual H2 consumption | B11: Both | C11: 94 | D11: kt | E11: Peacock et. al. | G11: =C10*10^9 / C9*0.8 -> 5.0822692
A12: Annual Diesel Production | B12: Both | C12: 0.66 | D12: Mbbl | E12: Peacock et. al.
A13: Annual Diesel Production | B13: Both | C13: =C12*159 * 10^6 -> 1.0494e+08 | D13: l | F13: Calculated (1 barrel = 159 litres)
A14: DAC Heat | B14: 2024 | C14: 1200 | D14: kWh/tCO2 | E14: Peacock et. al. Table 2
A15: DAC Heat | B15: 2050 | C15: 1100 | D15: kWh/tCO2 | E15: Peacock et. al. Table 2
A16: DAC Electricity | B16: 2024 | C16: 250 | D16: kWh/tCO2 | E16: Peacock et. al. Table 2
A17: DAC Electricity | B17: 2050 | C17: 182 | D17: kWh/tCO2 | E17: Peacock et. al. Table 2
A18: Electrolyzer Electricity Consumption | B18: 2024 | C18: 55.6 | D18: kWh/kg H2 | E18: Peacock et. al. Table 3
A19: Electrolyzer Electricity Consumption | B19: 2050 | C19: 47.5 | D19: kWh/kg H2 | E19: Peacock et. al. Table 3
A22: Plant Parameters
A23: Parameter | B23: Year | C23: Value | D23: Unit | E23: Source | F23: Note
A24: Installed Battery Capacity | B24: 2024 | C24: 18956 | D24: MWh | E24: Peacock et. al. Table 6
A25: Installed Battery Capacity | B25: 2050 | C25: 16474 | D25: MWh | E25: Peacock et. al. Table 6
A26: Number of cycles per day | B26: Both | C26: 2
A27: No. of cycles before replacement | B27: 2024 | C27: 2750
A28: No. of cycles before replacement | B28: 2050 | C28: 3500
A29: No. of replacements (Battery) | B29: 2024 | C29: =_xlfn.CEILING.MATH($C$4 / (($C$27/C26) / (365)),1) - 1 -> 7 | E29: Peacock et. al. Table 6
A30: No. of replacements (Battery) | B30: 2050 | C30: =_xlfn.CEILING.MATH($C$4 / (($C$28/C26) / (365)),1) - 1 -> 6 | E30: Peacock et. al. Table 6
A31: PEM Replacement period (years) | B31: 2024 | C31: 10 | E31: Peacock et. al. Table 3
A32: PEM Replacement period (years) | B32: 2050 | C32: 12 | E32: Peacock et. al. Table 3
A33: SOEC Replacement period (years) | B33: 2024 | C33: 6 | E33: Peacock et. al. Table 5
A34: SOEC Replacement period (years) | B34: 2050 | C34: 10 | E34: Peacock et. al. Table 5
A35: No. or replacements (PEM) | B35: 2024 | C35: =C4/C31 - 1 -> 2 | E35: Peacock et. al. Table 3
A36: No. or replacements (PEM) | B36: 2050 | C36: =_xlfn.CEILING.MATH(C4/C32 - 1,1) -> 2 | E36: Peacock et. al. Table 3
A37: No. or replacements (SOEC) | B37: 2024 | C37: =C4/C33 - 1 -> 4 | E37: Peacock et. al. Table 5
A38: No. or replacements (SOEC) | B38: 2050 | C38: =C4/C34 - 1 -> 2 | E38: Peacock et. al. Table 5
A40: Cost Parameters
A41: Parameter | B41: Year | C41: Value | D41: Unit | E41: Source | F41: Note
A42: Diesel Revenue | B42: Both | C42: 122 | D42: M€ | E42: Peacock et. al.
A43: Thermal Energy Cost (C-P-R Scenario) | B43: 2024 | C43: 28.5 | D43: $/MWh | E43: Peacock et. al. Table 1
A44: Thermal Energy Cost (F-P-R Scenario) | B44: 2050 | C44: 14.2 | D44: $/MWh | E44: Peacock et. al. Table 1
A45: DAC CAPEX | B45: 2024 | C45: 524 | D45: $/tCO2 | E45: Peacock et. al. Table 2
A46: DAC CAPEX | B46: 2050 | C46: 200 | D46: $/tCO2 | E46: Peacock et. al. Table 2
A47: PEM CAPEX | B47: 2024 | C47: 772 | D47: $/kW | E47: Peacock et. al. Table 3
A48: PEM CAPEX | B48: 2050 | C48: 400 | D48: $/kW | E48: Peacock et. al. Table 3
A49: PEM Stack Replacement Cost | B49: 2024 | C49: 0.35 | E49: Peacock et. al. Table 3
A50: PEM Stack Replacement Cost | B50: 2050 | C50: 0.3 | E50: Peacock et. al. Table 3
A51: SOEC CAPEX | B51: 2024 | C51: 1452 | D51: $/kW | E51: Peacock et. al. Table 5
A52: SOEC CAPEX | B52: 2050 | C52: 400 | D52: $/kW | E52: Peacock et. al. Table 5
A53: SOEC Stack Replacement Cost | B53: 2024 | C53: 0.5 | E53: Peacock et. al. Table 5
A54: SOEC Stack Replacement Cost | B54: 2050 | C54: 0.4 | E54: Peacock et. al. Table 5
A55: Battery CAPEX | B55: 2024 | C55: 350 | D55: $/kWh | E55: Peacock et. al. Table 6
A56: Battery CAPEX | B56: 2050 | C56: 90 | D56: $/kWh | E56: Peacock et. al. Table 6
A57: Battery Replacement CAPEX | B57: 2024 | C57: 145 | D57: $/kWh | E57: Peacock et. al. Table 6
A58: Battery Replacement CAPEX | B58: 2050 | C58: 37 | D58: $/kWh | E58: Peacock et. al. Table 6
A59: Electricity Price Nuclear | B59: 2024 | C59: 118 | D59: $/MWh | E59: Peacock et. al. Table 1
A60: Electricity Price Nuclear | B60: 2050 | C60: 50 | D60: $/MWh | E60: Peacock et. al. Table 1
A61: Electricity Price Nuclear/Renewables | B61: 2024 | C61: 79.8 | D61: $/MWh | E61: Peacock et. al. Table 1
A62: Electricity Price Nuclear/Renewables | B62: 2050 | C62: 38 | D62: $/MWh | E62: Peacock et. al. Table 1
A64: Fuel Characteristics
A65: Parameter | B65: Year | C65: Value | D65: Unit | E65: Source | F65: Note
A66: Emissions Intensity | B66: Both | C66: =0.07 * Inputs!C11 -> 6.209 | D66: gCO2/MJ | E66: Peacock et. al. | F66: 93% savings assumed by study
A68: Scenario Specific Parameters
A69: Parameter | B69: Year | C69: Scenario | D69: Value | E69: Unit | F69: Source | G69: Note
A70: Annual Electricity Consumption | B70: 2024 | C70: C-P-N | D70: ='Cost Components'!B12 * 10^6 / 'Study Parameters'!C59 -> 5932203.4 | E70: MWh | G70: Calculated from annual opex and electricity price
B71: 2050 | C71: F-P-N | D71: ='Cost Components'!T12*10^6 / 'Study Parameters'!C60 -> 5060000 | E71: MWh
B72: 2024 | C72: C-P-N/R | D72: ='Cost Components'!H12 * 10^6/'Study Parameters'!C61 -> 6390977.4 | E72: MWh
B73: 2050 | C73: F-P-N/R | D73: ='Cost Components'!Z12 * 10^6 /'Study Parameters'!C62 -> 4842105.3 | E73: MWh
B74: 2024 | C74: C-S-N/R | D74: ='Cost Components'!N12 * 10^6 /'Study Parameters'!C61 -> 4761904.8 | E74: MWh
B75: 2050 | C75: F-S-N/R | D75: ='Cost Components'!AF12 * 10^6 / 'Study Parameters'!C62 -> 4078947.4 | E75: MWh
A76: Annual Electricity Consumption (Without DAC) | B76: 2024 | C76: C-P-N | D76: =D70-$C$16 * 10^3 -> 5682203.4 | E76: MWh
B77: 2050 | C77: F-P-N | D77: =D71-$C$17 * 10^3 -> 4878000 | E77: MWh
B78: 2024 | C78: C-P-N/R | D78: =D72-$C$16 * 10^3 -> 6140977.4 | E78: MWh
B79: 2050 | C79: F-P-N/R | D79: =D73-$C$17 * 10^3 -> 4660105.3 | E79: MWh
B80: 2024 | C80: C-S-N/R | D80: =D74-$C$16 * 10^3 -> 4511904.8 | E80: MWh
B81: 2050 | C81: F-S-N/R | D81: =D75-$C$17 * 10^3 -> 3896947.4 | E81: MWh

Sheet NPV DAC CAPEX
A1: Year | B1: 0 | C1: 1 | D1: 2 | E1: 3 | F1: 4 | G1: 5 | H1: 6 | I1: 7 | J1: 8 | K1: 9 | L1: 10 | M1: 11 | N1: 12 | O1: 13 | P1: 14 | Q1: 15 | R1: 16 | S1: 17 | T1: 18 | U1: 19 | V1: 20 | W1: 21 | X1: 22 | Y1: 23 | Z1: 24 | AA1: 25 | AB1: 26 | AC1: 27 | AD1: 28 | AE1: 29 | AF1: 30
A2: 2024
A3: Cost (€) | B3: 524 | C3: 524 | D3: 524 | E3: 524 | F3: 524 | G3: 524 | H3: 524 | I3: 524 | J3: 524 | K3: 524 | L3: 524 | M3: 524 | N3: 524 | O3: 524 | P3: 524 | Q3: 524 | R3: 524 | S3: 524 | T3: 524 | U3: 524 | V3: 524 | W3: 524 | X3: 524 | Y3: 524 | Z3: 524 | AA3: 524 | AB3: 524 | AC3: 524 | AD3: 524 | AE3: 524 | AF3: 524
A4: Discounted Cost (€) | B4: =B3/(1+'Study Parameters'!$C$3)^'NPV DAC CAPEX'!B1 -> 524 | C4: =C3/(1+'Study Parameters'!$C$3)^'NPV DAC CAPEX'!C1 -> 485.18519 | D4: =D3/(1+'Study Parameters'!$C$3)^'NPV DAC CAPEX'!D1 -> 449.24554 | E4: =E3/(1+'Study Parameters'!$C$3)^'NPV DAC CAPEX'!E1 -> 415.96809 | F4: =F3/(1+'Study Parameters'!$C$3)^'NPV DAC CAPEX'!F1 -> 385.15564 | G4: =G3/(1+'Study Parameters'!$C$3)^'NPV DAC CAPEX'!G1 -> 356.6256 | H4: =H3/(1+'Study Parameters'!$C$3)^'NPV DAC CAPEX'!H1 -> 330.20888 | I4: =I3/(1+'Study Parameters'!$C$3)^'NPV DAC CAPEX'!I1 -> 305.74897 | ... AF4: =AF3/(1+'Study Parameters'!$C$3)^'NPV DAC CAPEX'!AF1 -> 52.073722
A6: 2050
A7: Cost (€) | B7: 200 | C7: 200 | D7: 200 | E7: 200 | F7: 200 | G7: 200 | H7: 200 | I7: 200 | J7: 200 | K7: 200 | L7: 200 | M7: 200 | N7: 200 | O7: 200 | P7: 200 | Q7: 200 | R7: 200 | S7: 200 | T7: 200 | U7: 200 | V7: 200 | W7: 200 | X7: 200 | Y7: 200 | Z7: 200 | AA7: 200 | AB7: 200 | AC7: 200 | AD7: 200 | AE7: 200 | AF7: 200
A8: Discounted Cost (€) | B8: =B7/(1+'Study Parameters'!$C$3)^'NPV DAC CAPEX'!B1 -> 200 | C8: =C7/(1+'Study Parameters'!$C$3)^'NPV DAC CAPEX'!C1 -> 185.18519 | D8: =D7/(1+'Study Parameters'!$C$3)^'NPV DAC CAPEX'!D1 -> 171.46776 | E8: =E7/(1+'Study Parameters'!$C$3)^'NPV DAC CAPEX'!E1 -> 158.76645 | F8: =F7/(1+'Study Parameters'!$C$3)^'NPV DAC CAPEX'!F1 -> 147.00597 | G8: =G7/(1+'Study Parameters'!$C$3)^'NPV DAC CAPEX'!G1 -> 136.11664 | H8: =H7/(1+'Study Parameters'!$C$3)^'NPV DAC CAPEX'!H1 -> 126.03393 | I8: =I7/(1+'Study Parameters'!$C$3)^'NPV DAC CAPEX'!I1 -> 116.69808 | ... AF8: =AF7/(1+'Study Parameters'!$C$3)^'NPV DAC CAPEX'!AF1 -> 19.875467
A10: 2024
A11: CO2 Removed | B11: 0 | C11: =10^6 -> 1000000 | D11: =10^6 -> 1000000 | E11: =10^6 -> 1000000 | F11: =10^6 -> 1000000 | G11: =10^6 -> 1000000 | H11: =10^6 -> 1000000 | I11: =10^6 -> 1000000 | J11: =10^6 -> 1000000 | ... AF11: =10^6 -> 1000000
A12: CO2 Removed (Discounted) | B12: =B11/(1+'Study Parameters'!$C$3)^'NPV DAC CAPEX'!B1 -> 0 | C12: =C11/(1+'Study Parameters'!$C$3)^'NPV DAC CAPEX'!C1 -> 925925.93 | D12: =D11/(1+'Study Parameters'!$C$3)^'NPV DAC CAPEX'!D1 -> 857338.82 | E12: =E11/(1+'Study Parameters'!$C$3)^'NPV DAC CAPEX'!E1 -> 793832.24 | F12: =F11/(1+'Study Parameters'!$C$3)^'NPV DAC CAPEX'!F1 -> 735029.85 | G12: =G11/(1+'Study Parameters'!$C$3)^'NPV DAC CAPEX'!G1 -> 680583.2 | H12: =H11/(1+'Study Parameters'!$C$3)^'NPV DAC CAPEX'!H1 -> 630169.63 | I12: =I11/(1+'Study Parameters'!$C$3)^'NPV DAC CAPEX'!I1 -> 583490.4 | ... AF12: =AF11/(1+'Study Parameters'!$C$3)^'NPV DAC CAPEX'!AF1 -> 99377.333
A14: LCOR | B14: =(SUM(B4:AF4) * 10^6) / SUM(B12:AF12) -> 570.54558

Sheet Cost Components
A1: Economic Assumptions C-P-N | G1: Economic Assumptions C-P-N/R | M1: Economic Assumptions C-S-N/R | S1: Economic Assumptions F-P-N | Y1: Economic Assumptions F-P-N/R | AE1: Economic Assumptions F-S-N/R
A2: CAPEX | G2: CAPEX | M2: CAPEX | S2: CAPEX | Y2: CAPEX | AE2: CAPEX
A3: Component | B3: Value | C3: Unit | D3: Source | E3: Notes | G3: Component | H3: Value | I3: Unit | J3: Source | K3: Notes | M3: Component | N3: Value | O3: Unit | P3: Source | Q3: Notes | S3: Component | T3: Value | U3: Unit | V3: Source | W3: Notes | Y3: Component | Z3: Value | AA3: Unit | AB3: Source | AC3: Notes | AE3: Component | AF3: Value | AG3: Unit | AH3: Source | AI3: Notes
A4: PEM | B4: 480 | C4: M€ | D4: Peacock et. al. Figure 7 | G4: PEM | H4: 480 | I4: M€ | J4: Peacock et. al. Figure 7 | M4: SOE | N4: 750 | O4: M€ | P4: Peacock et. al. Figure 7 | S4: PEM | T4: 230 | U4: M€ | V4: Peacock et. al. Figure 7 | Y4: PEM | Z4: 230 | AA4: M€ | AB4: Peacock et. al. Figure 7 | AE4: SOEC | AF4: 175 | AG4: M€ | AH4: Peacock et. al. Figure 7
A5: DAC | B5: =SUM('NPV DAC CAPEX'!$B$4:$AF$4) -> 6423.0785 | C5: M€ | D5: Peacock et. al. Figure 7 | G5: DAC | H5: =SUM('NPV DAC CAPEX'!$B$4:$AF$4) -> 6423.0785 | I5: M€ | J5: Peacock et. al. Figure 7 | M5: DAC | N5: =SUM('NPV DAC CAPEX'!$B$4:$AF$4) -> 6423.0785 | O5: M€ | P5: Peacock et. al. Figure 7 | S5: DAC | T5: =SUM('NPV DAC CAPEX'!$B$8:$AF$8) -> 2451.5567 | U5: M€ | V5: Peacock et. al. Figure 7 | Y5: DAC | Z5: =SUM('NPV DAC CAPEX'!$B$8:$AF$8) -> 2451.5567 | AA5: M€ | AB5: Peacock et. al. Figure 7 | AE5: DAC | AF5: =SUM('NPV DAC CAPEX'!$B$8:$AF$8) -> 2451.5567 | AG5: M€ | AH5: Peacock et. al. Figure 7
A6: FT | B6: 620 | C6: M€ | D6: Peacock et. al. Figure 7 | G6: FT | H6: 620 | I6: M€ | J6: Peacock et. al. Figure 7 | M6: FT | N6: 620 | O6: M€ | P6: Peacock et. al. Figure 7 | S6: FT | T6: 620 | U6: M€ | V6: Peacock et. al. Figure 7 | Y6: FT | Z6: 620 | AA6: M€ | AB6: Peacock et. al. Figure 7 | AE6: FT | AF6: 620 | AG6: M€ | AH6: Peacock et. al. Figure 7
A7: PEM Stack Replacement | B7: 177 | C7: M€ | G7: PEM Stack Replacement | H7: 177 | I7: M€ | M7: SOE Stack Replacement | N7: ='Study Parameters'!C53*'Cost Components'!N4 -> 375 | O7: M€ | S7: PEM Stack Replacement | T7: ='Study Parameters'!$C$50*'Cost Components'!T4 -> 69 | U7: M€ | W7: Calculated | Y7: PEM Stack Replacement | Z7: ='Study Parameters'!$C$50*'Cost Components'!Z4 -> 69 | AA7: M€ | AC7: Calculated | AE7: SOEC Stack Replacement | AF7: ='Study Parameters'!C54*'Cost Components'!AF4 -> 70 | AG7: M€ | AI7: Calculated
A8: Total CAPEX | B8: =SUM(B4:B6) -> 7523.0785 | C8: M€ | G8: Total CAPEX | H8: =SUM(H4:H6) -> 7523.0785 | I8: M€ | M8: Total CAPEX | N8: =SUM(N4:N6) -> 7793.0785 | O8: M€ | S8: Total CAPEX | T8: =SUM(T4:T6) -> 3301.5567 | U8: M€ | Y8: Total CAPEX | Z8: =SUM(Z4:Z6) -> 3301.5567 | AA8: M€ | AE8: Total CAPEX | AF8: =SUM(AF4:AF6) -> 3246.5567 | AG8: M€
A10: OPEX | G10: OPEX | M10: OPEX | S10: OPEX | Y10: OPEX | AE10: OPEX
A11: Component | B11: Value | C11: Unit | D11: Source | E11: Notes | G11: Component | H11: Value | I11: Unit | J11: Source | K11: Notes | M11: Component | N11: Value | O11: Unit | P11: Source | Q11: Notes | S11: Component | T11: Value | U11: Unit | V11: Source | W11: Notes | Y11: Component | Z11: Value | AA11: Unit | AB11: Source | AC11: Notes | AE11: Component | AF11: Value | AG11: Unit | AH11: Source | AI11: Notes
A12: Electricity | B12: 700 | C12: M€/year | D12: Peacock et. al. Figure 9 | G12: Electricity | H12: 510 | I12: M€/year | J12: Peacock et. al. Figure 9 | M12: Electricity | N12: 380 | O12: M€/year | P12: Peacock et. al. Figure 9 | S12: Electricity | T12: 253 | U12: M€/year | V12: Peacock et. al. Figure 9 | Y12: Electricity | Z12: 184 | AA12: M€/year | AB12: Peacock et. al. Figure 9 | AE12: Electricity | AF12: 155 | AG12: M€/year | AH12: Peacock et. al. Figure 9
A13: Heat | B13: 44.2 | C13: M€/year | D13: Peacock et. al. Figure 9 | G13: Heat | H13: 44.2 | I13: M€/year | J13: Peacock et. al. Figure 9 | M13: Heat | N13: 55 | O13: M€/year | P13: Peacock et. al. Figure 9 | S13: Heat | T13: 25 | U13: M€/year | V13: Peacock et. al. Figure 9 | Y13: Heat | Z13: 25 | AA13: M€/year | AB13: Peacock et. al. Figure 9 | AE13: Heat | AF13: 27 | AG13: M€/year | AH13: Peacock et. al. Figure 9
A14: Water | B14: 14.7 | C14: M€/year | D14: Peacock et. al. Figure 9 | G14: Water | H14: 14.7 | I14: M€/year | J14: Peacock et. al. Figure 9 | M14: Water | N14: 9.8 | O14: M€/year | P14: Peacock et. al. Figure 9 | S14: Water | T14: 25 | U14: M€/year | V14: Peacock et. al. Figure 9 | Y14: Water | Z14: 26 | AA14: M€/year | AB14: Peacock et. al. Figure 9 | AE14: Water | AF14: 6 | AG14: M€/year | AH14: Peacock et. al. Figure 9
A15: Fixed Costs | B15: 121.6 | C15: M€/year | D15: Peacock et. al. Figure 9 | G15: Fixed Costs | H15: 121.6 | I15: M€/year | J15: Peacock et. al. Figure 9 | M15: Fixed Costs | N15: 141 | O15: M€/year | P15: Peacock et. al. Figure 9 | S15: Fixed Costs | T15: 90 | U15: M€/year | V15: Peacock et. al. Figure 9 | Y15: Fixed Costs | Z15: 90 | AA15: M€/year | AB15: Peacock et. al. Figure 9 | AE15: Fixed Costs | AF15: 90 | AG15: M€/year | AH15: Peacock et. al. Figure 9
A16: Total OPEX | B16: =SUM(B12:B15) -> 880.5 | G16: Total OPEX | H16: =SUM(H12:H15) -> 690.5 | M16: Total OPEX | N16: =SUM(N12:N15) -> 585.8 | S16: Total OPEX | T16: =SUM(T12:T15) -> 393 | Y16: Total OPEX | Z16: =SUM(Z12:Z15) -> 325 | AE16: Total OPEX | AF16: =SUM(AF12:AF15) -> 278
A18: Corrected Assumptions C-P-N | G18: Corrected Assumptions C-P-N/R | M18: Corrected Assumptions C-S-N/R | S18: Corrected Assumptions F-P-N | Y18: Corrected Assumptions F-P-N/R | AE18: Corrected Assumptions F-S-N/R
A19: OPEX | G19: OPEX | M19: OPEX | S19: OPEX | Y19: OPEX | AE19: OPEX
A20: Component | B20: Value | C20: Unit | D20: Source | E20: Notes | G20: Component | H20: Value | I20: Unit | J20: Source | K20: Notes | M20: Component | N20: Value | O20: Unit | P20: Source | Q20: Notes | S20: Component | T20: Value | U20: Unit | V20: Source | W20: Notes | Y20: Component | Z20: Value | AA20: Unit | AB20: Source | AC20: Notes | AE20: Component | AF20: Value | AG20: Unit | AH20: Source | AI20: Notes
A21: Electricity | B21: =Inputs!$C$8/'Study Parameters'!$C$59 * 'Cost Components'!B12 -> 379.66102 | C21: M€/year | E21: Grid Price considered | G21: Electricity | H21: =Inputs!$C$8/'Study Parameters'!$C$61 * 'Cost Components'!H12 -> 409.02256 | I21: M€/year | K21: Grid Price considered | M21: Electricity | N21: =Inputs!$C$8/'Study Parameters'!$C$61 * 'Cost Components'!N12 -> 304.7619 | O21: M€/year | Q21: Grid Price considered | S21: Electricity | T21: =Inputs!$C$9/'Study Parameters'!$C$60 * 'Cost Components'!T12 -> 55.66 | U21: M€/year | W21: Grid Price considered | Y21: Electricity | Z21: =Inputs!$C$9/'Study Parameters'!$C$62 * 'Cost Components'!Z12 -> 53.263158 | AA21: M€/year | AC21: Grid Price considered | AE21: Electricity | AF21: =Inputs!$C$9/'Study Parameters'!$C$62 * 'Cost Components'!AF12 -> 44.868421 | AG21: M€/year | AI21: Grid Price considered
A22: LCOE Corrected OPEX | B22: =B16-B12+B21 -> 560.16102 | C22: M€/year | G22: LCOE Corrected OPEX | H22: =H16-H12+H21 -> 589.52256 | I22: M€/year | M22: LCOE Corrected OPEX | N22: =N16-N12+N21 -> 510.5619 | O22: M€/year | S22: LCOE Corrected OPEX | T22: =T16-T12+T21 -> 195.66 | U22: M€/year | Y22: LCOE Corrected OPEX | Z22: =Z16-Z12+Z21 -> 194.26316 | AA22: M€/year | AE22: LCOE Corrected OPEX | AF22: =AF16-AF12+AF21 -> 167.86842 | AG22: M€/year
A23: CO2 Corrected CAPEX | B23: =B8-B5 -> 1100 | C23: M€ | E23: DAC CAPEX neglected | G23: CO2 Corrected CAPEX | H23: =H8-H5 -> 1100 | I23: M€ | K23: DAC CAPEX neglected | M23: CO2 Corrected CAPEX | N23: =N8-N5 -> 1370 | O23: M€ | Q23: DAC CAPEX neglected | S23: CO2 Corrected CAPEX | T23: =T8-T5 -> 850 | U23: M€ | W23: DAC CAPEX neglected | Y23: CO2 Corrected CAPEX | Z23: =Z8-Z5 -> 850 | AA23: M€ | AC23: DAC CAPEX neglected | AE23: CO2 Corrected CAPEX | AF23: =AF8-AF5 -> 795 | AG23: M€ | AI23: DAC CAPEX neglected
A24: CO2 Cost | B24: =(Inputs!$C$32*'Study Parameters'!$C$10*10^6) / 10^6 -> 1371 | C24: M€/year | G24: CO2 Cost | H24: =(Inputs!$C$32*'Study Parameters'!$C$10*10^6) / 10^6 -> 1371 | I24: M€/year | M24: CO2 Cost | N24: =(Inputs!$C$32*'Study Parameters'!$C$10*10^6) / 10^6 -> 1371 | O24: M€/year | S24: CO2 Cost | T24: =(Inputs!$C$33*'Study Parameters'!$C$10*10^6) / 10^6 -> 523 | U24: M€/year | Y24: CO2 Cost | Z24: =(Inputs!$C$33*'Study Parameters'!$C$10*10^6) / 10^6 -> 523 | AA24: M€/year | AE24: CO2 Cost | AF24: =(Inputs!$C$33*'Study Parameters'!$C$10*10^6) / 10^6 -> 523 | AG24: M€/year
A25: Electricity | B25: =(Inputs!$C$8*'Study Parameters'!D76) / 10^6 -> 363.66102 | C25: M€/year | E25: DAC Electricity requirements subtracted | G25: Electricity | H25: =(Inputs!$C$8*'Study Parameters'!D72) / 10^6 -> 409.02256 | I25: M€/year | K25: DAC Electricity requirements subtracted | M25: Electricity | N25: =(Inputs!$C$8*'Study Parameters'!D74) / 10^6 -> 304.7619 | O25: M€/year | Q25: DAC Electricity requirements subtracted | S25: Electricity | T25: =(Inputs!$C$8*'Study Parameters'!D71) / 10^6 -> 323.84 | U25: M€/year | W25: DAC Electricity requirements subtracted | Y25: Electricity | Z25: =(Inputs!$C$8*'Study Parameters'!D79) / 10^6 -> 298.24674 | AA25: M€/year | AC25: DAC Electricity requirements subtracted | AE25: Electricity | AF25: =(Inputs!$C$8*'Study Parameters'!D81) / 10^6 -> 249.40463 | AG25: M€/year | AI25: DAC Electricity requirements subtracted
A26: CO2 Corrected OPEX | B26: =B16-B12 - B13 - B14+B25+B24 -> 1856.261 | C26: M€/year | E26: DAC heat requirements subtracted | G26: CO2 Corrected OPEX | H26: =H16-H12 - H13 - H14+H25+H24 -> 1901.6226 | I26: M€/year | K26: DAC heat requirements subtracted | M26: CO2 Corrected OPEX | N26: =N16-N12 - N13 - N14+N25+N24 -> 1816.7619 | O26: M€/year | Q26: DAC heat requirements subtracted | S26: CO2 Corrected OPEX | T26: =T16-T12 - T13 - T14+T25+T24 -> 936.84 | U26: M€/year | W26: DAC heat requirements subtracted | Y26: CO2 Corrected OPEX | Z26: =Z16-Z12 - Z13 - Z14+Z25+Z24 -> 911.24674 | AA26: M€/year | AC26: DAC heat requirements subtracted | AE26: CO2 Corrected OPEX | AF26: =AF16-AF12 - AF13 - AF14+AF25+AF24 -> 862.40463 | AG26: M€/year | AI26: DAC heat requirements subtracted

Sheet LCOF Baseline
A1: C-P-N
A2: Year | B2: 0 | C2: 1 | D2: 2 | E2: 3 | F2: 4 | G2: 5 | H2: 6 | I2: 7 | J2: 8 | K2: 9 | L2: 10 | M2: 11 | N2: 12 | O2: 13 | P2: 14 | Q2: 15 | R2: 16 | S2: 17 | T2: 18 | U2: 19 | V2: 20 | W2: 21 | X2: 22 | Y2: 23 | Z2: 24 | AA2: 25 | AB2: 26 | AC2: 27 | AD2: 28 | AE2: 29 | AF2: 30
A3: Cost (€) | B3: ='Cost Components'!B8*10^6 -> 7.5230785e+09 | C3: ='Cost Components'!$B$16 * 10^6 -> 8.805e+08 | D3: ='Cost Components'!$B$16 * 10^6 -> 8.805e+08 | E3: ='Cost Components'!$B$16 * 10^6 -> 8.805e+08 | F3: ='Cost Components'!$B$16 * 10^6 -> 8.805e+08 | G3: ='Cost Components'!$B$16 * 10^6 -> 8.805e+08 | H3: ='Cost Components'!$B$16 * 10^6 -> 8.805e+08 | I3: ='Cost Components'!$B$16 * 10^6 -> 8.805e+08 | J3: ='Cost Components'!$B$16 * 10^6 -> 8.805e+08 | K3: ='Cost Components'!$B$16 * 10^6 -> 8.805e+08 | L3: ='Cost Components'!$B$16 * 10^6 + 'Cost Components'!$B$7*10^6 -> 1.0575e+09 | M3: ='Cost Components'!$B$16 * 10^6 -> 8.805e+08 | N3: ='Cost Components'!$B$16 * 10^6 -> 8.805e+08 | O3: ='Cost Components'!$B$16 * 10^6 -> 8.805e+08 | P3: ='Cost Components'!$B$16 * 10^6 -> 8.805e+08 | Q3: ='Cost Components'!$B$16 * 10^6 -> 8.805e+08 | R3: ='Cost Components'!$B$16 * 10^6 -> 8.805e+08 | S3: ='Cost Components'!$B$16 * 10^6 -> 8.805e+08 | T3: ='Cost Components'!$B$16 * 10^6 -> 8.805e+08 | U3: ='Cost Components'!$B$16 * 10^6 -> 8.805e+08 | V3: ='Cost Components'!$B$16 * 10^6 + 'Cost Components'!$B$7*10^6 -> 1.0575e+09 | W3: ='Cost Components'!$B$16 * 10^6 -> 8.805e+08 | X3: ='Cost Components'!$B$16 * 10^6 -> 8.805e+08 | Y3: ='Cost Components'!$B$16 * 10^6 -> 8.805e+08 | Z3: ='Cost Components'!$B$16 * 10^6 -> 8.805e+08 | AA3: ='Cost Components'!$B$16 * 10^6 -> 8.805e+08 | AB3: ='Cost Components'!$B$16 * 10^6 -> 8.805e+08 | AC3: ='Cost Components'!$B$16 * 10^6 -> 8.805e+08 | AD3: ='Cost Components'!$B$16 * 10^6 -> 8.805e+08 | ... AF3: ='Cost Components'!$B$16 * 10^6 -> 8.805e+08
A4: Discounted Cost (€) | B4: =B3/(1+'Study Parameters'!$C$3) ^ 'LCOF Baseline'!B2 -> 7.5230785e+09 | C4: =C3/(1+'Study Parameters'!$C$3) ^ 'LCOF Baseline'!C2 -> 8.1527778e+08 | D4: =D3/(1+'Study Parameters'!$C$3) ^ 'LCOF Baseline'!D2 -> 7.5488683e+08 | E4: =E3/(1+'Study Parameters'!$C$3) ^ 'LCOF Baseline'!E2 -> 6.9896929e+08 | F4: =F3/(1+'Study Parameters'!$C$3) ^ 'LCOF Baseline'!F2 -> 6.4719379e+08 | G4: =G3/(1+'Study Parameters'!$C$3) ^ 'LCOF Baseline'!G2 -> 5.992535e+08 | H4: =H3/(1+'Study Parameters'!$C$3) ^ 'LCOF Baseline'!H2 -> 5.5486436e+08 | I4: =I3/(1+'Study Parameters'!$C$3) ^ 'LCOF Baseline'!I2 -> 5.1376329e+08 | ... AF4: =AF3/(1+'Study Parameters'!$C$3) ^ 'LCOF Baseline'!AF2 -> 87501741
A5: Revenue (€) | B5: 0 | C5: ='Study Parameters'!$C$42*10^6 -> 122000000 | D5: ='Study Parameters'!$C$42*10^6 -> 122000000 | E5: ='Study Parameters'!$C$42*10^6 -> 122000000 | F5: ='Study Parameters'!$C$42*10^6 -> 122000000 | G5: ='Study Parameters'!$C$42*10^6 -> 122000000 | H5: ='Study Parameters'!$C$42*10^6 -> 122000000 | I5: ='Study Parameters'!$C$42*10^6 -> 122000000 | J5: ='Study Parameters'!$C$42*10^6 -> 122000000 | ... AF5: ='Study Parameters'!$C$42*10^6 -> 122000000
A6: Discounted Revenue (€) | B6: 0 | C6: =C5/(1+'Study Parameters'!$C$3) ^'LCOF Baseline'!C2 -> 1.1296296e+08 | D6: =D5/(1+'Study Parameters'!$C$3) ^'LCOF Baseline'!D2 -> 1.0459534e+08 | E6: =E5/(1+'Study Parameters'!$C$3) ^'LCOF Baseline'!E2 -> 96847533 | F6: =F5/(1+'Study Parameters'!$C$3) ^'LCOF Baseline'!F2 -> 89673642 | G6: =G5/(1+'Study Parameters'!$C$3) ^'LCOF Baseline'!G2 -> 83031150 | H6: =H5/(1+'Study Parameters'!$C$3) ^'LCOF Baseline'!H2 -> 76880694 | I6: =I5/(1+'Study Parameters'!$C$3) ^'LCOF Baseline'!I2 -> 71185828 | J6: =J5/(1+'Study Parameters'!$C$3) ^'LCOF Baseline'!J2 -> 65912804 | ... AF6: =AF5/(1+'Study Parameters'!$C$3) ^'LCOF Baseline'!AF2 -> 12124035
A7: Production (l) | B7: 0 | C7: ='Study Parameters'!$C$9 -> 157410000 | D7: ='Study Parameters'!$C$9 -> 157410000 | E7: ='Study Parameters'!$C$9 -> 157410000 | F7: ='Study Parameters'!$C$9 -> 157410000 | G7: ='Study Parameters'!$C$9 -> 157410000 | H7: ='Study Parameters'!$C$9 -> 157410000 | I7: ='Study Parameters'!$C$9 -> 157410000 | J7: ='Study Parameters'!$C$9 -> 157410000 | ... AF7: ='Study Parameters'!$C$9 -> 157410000
A8: Discounted Production (l) | B8: 0 | C8: =C7/(1+'Study Parameters'!$C$3) ^ 'LCOF Baseline'!C2 -> 145750000 | D8: =D7/(1+'Study Parameters'!$C$3) ^ 'LCOF Baseline'!D2 -> 1.349537e+08 | E8: =E7/(1+'Study Parameters'!$C$3) ^ 'LCOF Baseline'!E2 -> 1.2495713e+08 | F8: =F7/(1+'Study Parameters'!$C$3) ^ 'LCOF Baseline'!F2 -> 1.1570105e+08 | G8: =G7/(1+'Study Parameters'!$C$3) ^ 'LCOF Baseline'!G2 -> 1.071306e+08 | H8: =H7/(1+'Study Parameters'!$C$3) ^ 'LCOF Baseline'!H2 -> 99195001 | I8: =I7/(1+'Study Parameters'!$C$3) ^ 'LCOF Baseline'!I2 -> 91847223 | J8: =J7/(1+'Study Parameters'!$C$3) ^ 'LCOF Baseline'!J2 -> 85043725 | ... AF8: =AF7/(1+'Study Parameters'!$C$3) ^ 'LCOF Baseline'!AF2 -> 15642986
A10: Levelised Cost of Fuel (€/l) | B10: =(SUM(B4:AF4) - SUM(B6:AF6)) / SUM(B8:AF8) -> 9.1316404
A12: C-P-N/R
A13: Year | B13: 0 | C13: 1 | D13: 2 | E13: 3 | F13: 4 | G13: 5 | H13: 6 | I13: 7 | J13: 8 | K13: 9 | L13: 10 | M13: 11 | N13: 12 | O13: 13 | P13: 14 | Q13: 15 | R13: 16 | S13: 17 | T13: 18 | U13: 19 | V13: 20 | W13: 21 | X13: 22 | Y13: 23 | Z13: 24 | AA13: 25 | AB13: 26 | AC13: 27 | AD13: 28 | AE13: 29 | AF13: 30
A14: Cost (€) | B14: ='Cost Components'!H8*10^6 -> 7.5230785e+09 | C14: ='Cost Components'!$H$16*10^6 -> 6.905e+08 | D14: ='Cost Components'!$H$16*10^6 -> 6.905e+08 | E14: ='Cost Components'!$H$16*10^6 -> 6.905e+08 | F14: ='Cost Components'!$H$16*10^6 -> 6.905e+08 | G14: ='Cost Components'!$H$16*10^6 -> 6.905e+08 | H14: ='Cost Components'!$H$16*10^6 -> 6.905e+08 | I14: ='Cost Components'!$H$16*10^6 -> 6.905e+08 | J14: ='Cost Components'!$H$16*10^6 -> 6.905e+08 | K14: ='Cost Components'!$H$16*10^6 -> 6.905e+08 | L14: ='Cost Components'!$H$16*10^6 + 'Cost Components'!$H$7 * 10^6 -> 8.675e+08 | M14: ='Cost Components'!$H$16*10^6 -> 6.905e+08 | N14: ='Cost Components'!$H$16*10^6 -> 6.905e+08 | O14: ='Cost Components'!$H$16*10^6 -> 6.905e+08 | P14: ='Cost Components'!$H$16*10^6 -> 6.905e+08 | Q14: ='Cost Components'!$H$16*10^6 -> 6.905e+08 | R14: ='Cost Components'!$H$16*10^6 -> 6.905e+08 | S14: ='Cost Components'!$H$16*10^6 -> 6.905e+08 | T14: ='Cost Components'!$H$16*10^6 -> 6.905e+08 | U14: ='Cost Components'!$H$16*10^6 -> 6.905e+08 | V14: ='Cost Components'!$H$16*10^6 + 'Cost Components'!$H$7 * 10^6 -> 8.675e+08 | W14: ='Cost Components'!$H$16*10^6 -> 6.905e+08 | X14: ='Cost Components'!$H$16*10^6 -> 6.905e+08 | Y14: ='Cost Components'!$H$16*10^6 -> 6.905e+08 | Z14: ='Cost Components'!$H$16*10^6 -> 6.905e+08 | AA14: ='Cost Components'!$H$16*10^6 -> 6.905e+08 | AB14: ='Cost Components'!$H$16*10^6 -> 6.905e+08 | AC14: ='Cost Components'!$H$16*10^6 -> 6.905e+08 | AD14: ='Cost Components'!$H$16*10^6 -> 6.905e+08 | ... AF14: ='Cost Components'!$H$16*10^6 -> 6.905e+08
A15: Discounted Cost (€) | B15: =B14/(1+'Study Parameters'!$C$3) ^'LCOF Baseline'!B$13 -> 7.5230785e+09 | C15: =C14/(1+'Study Parameters'!$C$3) ^'LCOF Baseline'!C$13 -> 6.3935185e+08 | D15: =D14/(1+'Study Parameters'!$C$3) ^'LCOF Baseline'!D$13 -> 5.9199246e+08 | E15: =E14/(1+'Study Parameters'!$C$3) ^'LCOF Baseline'!E$13 -> 5.4814116e+08 | F15: =F14/(1+'Study Parameters'!$C$3) ^'LCOF Baseline'!F$13 -> 5.0753811e+08 | G15: =G14/(1+'Study Parameters'!$C$3) ^'LCOF Baseline'!G$13 -> 4.699427e+08 | H15: =H14/(1+'Study Parameters'!$C$3) ^'LCOF Baseline'!H$13 -> 4.3513213e+08 | I15: =I14/(1+'Study Parameters'!$C$3) ^'LCOF Baseline'!I$13 -> 4.0290012e+08 | ... AF15: =AF14/(1+'Study Parameters'!$C$3) ^'LCOF Baseline'!AF$13 -> 68620048
A16: Revenue (€) | B16: 0 | C16: ='Study Parameters'!$C$42 * 10^6 -> 122000000 | D16: ='Study Parameters'!$C$42 * 10^6 -> 122000000 | E16: ='Study Parameters'!$C$42 * 10^6 -> 122000000 | F16: ='Study Parameters'!$C$42 * 10^6 -> 122000000 | G16: ='Study Parameters'!$C$42 * 10^6 -> 122000000 | H16: ='Study Parameters'!$C$42 * 10^6 -> 122000000 | I16: ='Study Parameters'!$C$42 * 10^6 -> 122000000 | J16: ='Study Parameters'!$C$42 * 10^6 -> 122000000 | ... AF16: ='Study Parameters'!$C$42 * 10^6 -> 122000000
A17: Discounted Revenue (€) | B17: 0 | C17: =C16/(1+'Study Parameters'!$C$3) ^'LCOF Baseline'!C$13 -> 1.1296296e+08 | D17: =D16/(1+'Study Parameters'!$C$3) ^'LCOF Baseline'!D$13 -> 1.0459534e+08 | E17: =E16/(1+'Study Parameters'!$C$3) ^'LCOF Baseline'!E$13 -> 96847533 | F17: =F16/(1+'Study Parameters'!$C$3) ^'LCOF Baseline'!F$13 -> 89673642 | G17: =G16/(1+'Study Parameters'!$C$3) ^'LCOF Baseline'!G$13 -> 83031150 | H17: =H16/(1+'Study Parameters'!$C$3) ^'LCOF Baseline'!H$13 -> 76880694 | I17: =I16/(1+'Study Parameters'!$C$3) ^'LCOF Baseline'!I$13 -> 71185828 | J17: =J16/(1+'Study Parameters'!$C$3) ^'LCOF Baseline'!J$13 -> 65912804 | ... AF17: =AF16/(1+'Study Parameters'!$C$3) ^'LCOF Baseline'!AF$13 -> 12124035
A18: Production (l) | B18: 0 | C18: ='Study Parameters'!$C$9 -> 157410000 | D18: ='Study Parameters'!$C$9 -> 157410000 | E18: ='Study Parameters'!$C$9 -> 157410000 | F18: ='Study Parameters'!$C$9 -> 157410000 | G18: ='Study Parameters'!$C$9 -> 157410000 | H18: ='Study Parameters'!$C$9 -> 157410000 | I18: ='Study Parameters'!$C$9 -> 157410000 | J18: ='Study Parameters'!$C$9 -> 157410000 | ... AF18: ='Study Parameters'!$C$9 -> 157410000
A19: Discounted Production (l) | B19: 0 | C19: =C18/(1+'Study Parameters'!$C$3) ^'LCOF Baseline'!C$13 -> 145750000 | D19: =D18/(1+'Study Parameters'!$C$3) ^'LCOF Baseline'!D$13 -> 1.349537e+08 | E19: =E18/(1+'Study Parameters'!$C$3) ^'LCOF Baseline'!E$13 -> 1.2495713e+08 | F19: =F18/(1+'Study Parameters'!$C$3) ^'LCOF Baseline'!F$13 -> 1.1570105e+08 | G19: =G18/(1+'Study Parameters'!$C$3) ^'LCOF Baseline'!G$13 -> 1.071306e+08 | H19: =H18/(1+'Study Parameters'!$C$3) ^'LCOF Baseline'!H$13 -> 99195001 | I19: =I18/(1+'Study Parameters'!$C$3) ^'LCOF Baseline'!I$13 -> 91847223 | J19: =J18/(1+'Study Parameters'!$C$3) ^'LCOF Baseline'!J$13 -> 85043725 | ... AF19: =AF18/(1+'Study Parameters'!$C$3) ^'LCOF Baseline'!AF$13 -> 15642986
A21: Levelised Cost of Fuel (€/l) | B21: =(SUM(B15:AF15) - SUM(B17:AF17)) / SUM(B19:AF19) -> 7.9246015
A23: C-S-N/R
A24: Year | B24: 0 | C24: 1 | D24: 2 | E24: 3 | F24: 4 | G24: 5 | H24: 6 | I24: 7 | J24: 8 | K24: 9 | L24: 10 | M24: 11 | N24: 12 | O24: 13 | P24: 14 | Q24: 15 | R24: 16 | S24: 17 | T24: 18 | U24: 19 | V24: 20 | W24: 21 | X24: 22 | Y24: 23 | Z24: 24 | AA24: 25 | AB24: 26 | AC24: 27 | AD24: 28 | AE24: 29 | AF24: 30
A25: Cost (€) | B25: ='Cost Components'!N8 * 10^6 -> 7.7930785e+09 | C25: ='Cost Components'!$N$16 * 10^6 -> 585800000 | D25: ='Cost Components'!$N$16 * 10^6 -> 585800000 | E25: ='Cost Components'!$N$16 * 10^6 -> 585800000 | F25: ='Cost Components'!$N$16 * 10^6 -> 585800000 | G25: ='Cost Components'!$N$16 * 10^6 -> 585800000 | H25: ='Cost Components'!$N$16 * 10^6 -> 585800000 | I25: ='Cost Components'!$N$16 * 10^6 + 'Cost Components'!$N$7 * 10^6 -> 960800000 | J25: ='Cost Components'!$N$16 * 10^6 -> 585800000 | K25: ='Cost Components'!$N$16 * 10^6 -> 585800000 | L25: ='Cost Components'!$N$16 * 10^6 -> 585800000 | M25: ='Cost Components'!$N$16 * 10^6 -> 585800000 | N25: ='Cost Components'!$N$16 * 10^6 -> 585800000 | O25: ='Cost Components'!$N$16 * 10^6 + 'Cost Components'!$N$7 * 10^6 -> 960800000 | P25: ='Cost Components'!$N$16 * 10^6 -> 585800000 | Q25: ='Cost Components'!$N$16 * 10^6 -> 585800000 | R25: ='Cost Components'!$N$16 * 10^6 -> 585800000 | S25: ='Cost Components'!$N$16 * 10^6 -> 585800000 | T25: ='Cost Components'!$N$16 * 10^6 -> 585800000 | U25: ='Cost Components'!$N$16 * 10^6 + 'Cost Components'!$N$7 * 10^6 -> 960800000 | V25: ='Cost Components'!$N$16 * 10^6 -> 585800000 | W25: ='Cost Components'!$N$16 * 10^6 -> 585800000 | X25: ='Cost Components'!$N$16 * 10^6 -> 585800000 | Y25: ='Cost Components'!$N$16 * 10^6 -> 585800000 | Z25: ='Cost Components'!$N$16 * 10^6 -> 585800000 | AA25: ='Cost Components'!$N$16 * 10^6 + 'Cost Components'!$N$7 * 10^6 -> 960800000 | AB25: ='Cost Components'!$N$16 * 10^6 -> 585800000 | AC25: ='Cost Components'!$N$16 * 10^6 -> 585800000 | AD25: ='Cost Components'!$N$16 * 10^6 -> 585800000 | AE25: ='Cost Components'!$N$16 * 10^6 -> 585800000 | AF25: ='Cost Components'!$N$16 * 10^6 -> 585800000
A26: Discounted Cost (€) | B26: =B25/(1+'Study Parameters'!$C$3)^'LCOF Baseline'!B$24 -> 7.7930785e+09 | C26: =C25/(1+'Study Parameters'!$C$3)^'LCOF Baseline'!C$24 -> 5.4240741e+08 | D26: =D25/(1+'Study Parameters'!$C$3)^'LCOF Baseline'!D$24 -> 5.0222908e+08 | E26: =E25/(1+'Study Parameters'!$C$3)^'LCOF Baseline'!E$24 -> 4.6502693e+08 | F26: =F25/(1+'Study Parameters'!$C$3)^'LCOF Baseline'!F$24 -> 4.3058049e+08 | G26: =G25/(1+'Study Parameters'!$C$3)^'LCOF Baseline'!G$24 -> 3.9868564e+08 | H26: =H25/(1+'Study Parameters'!$C$3)^'LCOF Baseline'!H$24 -> 3.6915337e+08 | I26: =I25/(1+'Study Parameters'!$C$3)^'LCOF Baseline'!I$24 -> 5.6061757e+08 | ... AF26: =AF25/(1+'Study Parameters'!$C$3)^'LCOF Baseline'!AF$24 -> 58215241
A27: Revenue (€) | B27: 0 | C27: ='Study Parameters'!$C$42 * 10^6 -> 122000000 | D27: ='Study Parameters'!$C$42 * 10^6 -> 122000000 | E27: ='Study Parameters'!$C$42 * 10^6 -> 122000000 | F27: ='Study Parameters'!$C$42 * 10^6 -> 122000000 | G27: ='Study Parameters'!$C$42 * 10^6 -> 122000000 | H27: ='Study Parameters'!$C$42 * 10^6 -> 122000000 | I27: ='Study Parameters'!$C$42 * 10^6 -> 122000000 | J27: ='Study Parameters'!$C$42 * 10^6 -> 122000000 | ... AF27: ='Study Parameters'!$C$42 * 10^6 -> 122000000
A28: Discounted Revenue (€) | B28: 0 | C28: =C27/(1+'Study Parameters'!$C$3)^'LCOF Baseline'!C$24 -> 1.1296296e+08 | D28: =D27/(1+'Study Parameters'!$C$3)^'LCOF Baseline'!D$24 -> 1.0459534e+08 | E28: =E27/(1+'Study Parameters'!$C$3)^'LCOF Baseline'!E$24 -> 96847533 | F28: =F27/(1+'Study Parameters'!$C$3)^'LCOF Baseline'!F$24 -> 89673642 | G28: =G27/(1+'Study Parameters'!$C$3)^'LCOF Baseline'!G$24 -> 83031150 | H28: =H27/(1+'Study Parameters'!$C$3)^'LCOF Baseline'!H$24 -> 76880694 | I28: =I27/(1+'Study Parameters'!$C$3)^'LCOF Baseline'!I$24 -> 71185828 | J28: =J27/(1+'Study Parameters'!$C$3)^'LCOF Baseline'!J$24 -> 65912804 | ... AF28: =AF27/(1+'Study Parameters'!$C$3)^'LCOF Baseline'!AF$24 -> 12124035
A29: Production (l) | B29: 0 | C29: ='Study Parameters'!$C$9 -> 157410000 | D29: ='Study Parameters'!$C$9 -> 157410000 | E29: ='Study Parameters'!$C$9 -> 157410000 | F29: ='Study Parameters'!$C$9 -> 157410000 | G29: ='Study Parameters'!$C$9 -> 157410000 | H29: ='Study Parameters'!$C$9 -> 157410000 | I29: ='Study Parameters'!$C$9 -> 157410000 | J29: ='Study Parameters'!$C$9 -> 157410000 | ... AF29: ='Study Parameters'!$C$9 -> 157410000
A30: Discounted Production (l) | B30: 0 | C30: =C29/(1+'Study Parameters'!$C$3)^'LCOF Baseline'!C$24 -> 145750000 | D30: =D29/(1+'Study Parameters'!$C$3)^'LCOF Baseline'!D$24 -> 1.349537e+08 | E30: =E29/(1+'Study Parameters'!$C$3)^'LCOF Baseline'!E$24 -> 1.2495713e+08 | F30: =F29/(1+'Study Parameters'!$C$3)^'LCOF Baseline'!F$24 -> 1.1570105e+08 | G30: =G29/(1+'Study Parameters'!$C$3)^'LCOF Baseline'!G$24 -> 1.071306e+08 | H30: =H29/(1+'Study Parameters'!$C$3)^'LCOF Baseline'!H$24 -> 99195001 | I30: =I29/(1+'Study Parameters'!$C$3)^'LCOF Baseline'!I$24 -> 91847223 | J30: =J29/(1+'Study Parameters'!$C$3)^'LCOF Baseline'!J$24 -> 85043725 | ... AF30: =AF29/(1+'Study Parameters'!$C$3)^'LCOF Baseline'!AF$24 -> 15642986
A32: Levelised Cost of Fuel (€/l) | B32: =(SUM(B26:AF26) - SUM(B28:AF28)) / SUM(B30:AF30) -> 7.6253466
A34: F-P-N
A35: Year | B35: 0 | C35: 1 | D35: 2 | E35: 3 | F35: 4 | G35: 5 | H35: 6 | I35: 7 | J35: 8 | K35: 9 | L35: 10 | M35: 11 | N35: 12 | O35: 13 | P35: 14 | Q35: 15 | R35: 16 | S35: 17 | T35: 18 | U35: 19 | V35: 20 | W35: 21 | X35: 22 | Y35: 23 | Z35: 24 | AA35: 25 | AB35: 26 | AC35: 27 | AD35: 28 | AE35: 29 | AF35: 30
A36: Cost (€) | B36: ='Cost Components'!T8 * 10^6 -> 3.3015567e+09 | C36: ='Cost Components'!$T$16 * 10^6 -> 393000000 | D36: ='Cost Components'!$T$16 * 10^6 -> 393000000 | E36: ='Cost Components'!$T$16 * 10^6 -> 393000000 | F36: ='Cost Components'!$T$16 * 10^6 -> 393000000 | G36: ='Cost Components'!$T$16 * 10^6 -> 393000000 | H36: ='Cost Components'!$T$16 * 10^6 -> 393000000 | I36: ='Cost Components'!$T$16 * 10^6 -> 393000000 | J36: ='Cost Components'!$T$16 * 10^6 -> 393000000 | ... M36: ='Cost Components'!$T$16 * 10^6 -> 393000000 | N36: ='Cost Components'!$T$16 * 10^6 + 'Cost Components'!$T$7 * 10^6 -> 462000000 | O36: ='Cost Components'!$T$16 * 10^6 -> 393000000 | P36: ='Cost Components'!$T$16 * 10^6 -> 393000000 | Q36: ='Cost Components'!$T$16 * 10^6 -> 393000000 | R36: ='Cost Components'!$T$16 * 10^6 -> 393000000 | S36: ='Cost Components'!$T$16 * 10^6 -> 393000000 | T36: ='Cost Components'!$T$16 * 10^6 -> 393000000 | U36: ='Cost Components'!$T$16 * 10^6 -> 393000000 | V36: ='Cost Components'!$T$16 * 10^6 -> 393000000 | ... Y36: ='Cost Components'!$T$16 * 10^6 -> 393000000 | Z36: ='Cost Components'!$T$16 * 10^6 + 'Cost Components'!$T$7 * 10^6 -> 462000000 | AA36: ='Cost Components'!$T$16 * 10^6 -> 393000000 | AB36: ='Cost Components'!$T$16 * 10^6 -> 393000000 | AC36: ='Cost Components'!$T$16 * 10^6 -> 393000000 | AD36: ='Cost Components'!$T$16 * 10^6 -> 393000000 | AE36: ='Cost Components'!$T$16 * 10^6 -> 393000000 | AF36: ='Cost Components'!$T$16 * 10^6 -> 393000000
A37: Discounted Cost (€) | B37: =B36/(1+'Study Parameters'!$C$3)^'LCOF Baseline'!B$35 -> 3.3015567e+09 | C37: =C36/(1+'Study Parameters'!$C$3)^'LCOF Baseline'!C$35 -> 3.6388889e+08 | D37: =D36/(1+'Study Parameters'!$C$3)^'LCOF Baseline'!D$35 -> 3.3693416e+08 | E37: =E36/(1+'Study Parameters'!$C$3)^'LCOF Baseline'!E$35 -> 3.1197607e+08 | F37: =F36/(1+'Study Parameters'!$C$3)^'LCOF Baseline'!F$35 -> 2.8886673e+08 | G37: =G36/(1+'Study Parameters'!$C$3)^'LCOF Baseline'!G$35 -> 2.674692e+08 | H37: =H36/(1+'Study Parameters'!$C$3)^'LCOF Baseline'!H$35 -> 2.4765666e+08 | I37: =I36/(1+'Study Parameters'!$C$3)^'LCOF Baseline'!I$35 -> 2.2931173e+08 | ... AF37: =AF36/(1+'Study Parameters'!$C$3)^'LCOF Baseline'!AF$35 -> 39055292
A38: Revenue (€) | B38: 0 | C38: ='Study Parameters'!$C$42 * 10^6 -> 122000000 | D38: ='Study Parameters'!$C$42 * 10^6 -> 122000000 | E38: ='Study Parameters'!$C$42 * 10^6 -> 122000000 | F38: ='Study Parameters'!$C$42 * 10^6 -> 122000000 | G38: ='Study Parameters'!$C$42 * 10^6 -> 122000000 | H38: ='Study Parameters'!$C$42 * 10^6 -> 122000000 | I38: ='Study Parameters'!$C$42 * 10^6 -> 122000000 | J38: ='Study Parameters'!$C$42 * 10^6 -> 122000000 | ... AF38: ='Study Parameters'!$C$42 * 10^6 -> 122000000
A39: Discounted Revenue (€) | B39: 0 | C39: =C38/(1+'Study Parameters'!$C$3)^'LCOF Baseline'!C$35 -> 1.1296296e+08 | D39: =D38/(1+'Study Parameters'!$C$3)^'LCOF Baseline'!D$35 -> 1.0459534e+08 | E39: =E38/(1+'Study Parameters'!$C$3)^'LCOF Baseline'!E$35 -> 96847533 | F39: =F38/(1+'Study Parameters'!$C$3)^'LCOF Baseline'!F$35 -> 89673642 | G39: =G38/(1+'Study Parameters'!$C$3)^'LCOF Baseline'!G$35 -> 83031150 | H39: =H38/(1+'Study Parameters'!$C$3)^'LCOF Baseline'!H$35 -> 76880694 | I39: =I38/(1+'Study Parameters'!$C$3)^'LCOF Baseline'!I$35 -> 71185828 | J39: =J38/(1+'Study Parameters'!$C$3)^'LCOF Baseline'!J$35 -> 65912804 | ... AF39: =AF38/(1+'Study Parameters'!$C$3)^'LCOF Baseline'!AF$35 -> 12124035
A40: Production (l) | B40: 0 | C40: ='Study Parameters'!$C$9 -> 157410000 | D40: ='Study Parameters'!$C$9 -> 157410000 | E40: ='Study Parameters'!$C$9 -> 157410000 | F40: ='Study Parameters'!$C$9 -> 157410000 | G40: ='Study Parameters'!$C$9 -> 157410000 | H40: ='Study Parameters'!$C$9 -> 157410000 | I40: ='Study Parameters'!$C$9 -> 157410000 | J40: ='Study Parameters'!$C$9 -> 157410000 | ... AF40: ='Study Parameters'!$C$9 -> 157410000
A41: Discounted Production (l) | B41: 0 | C41: =C40/(1+'Study Parameters'!$C$3)^'LCOF Baseline'!C$35 -> 145750000 | D41: =D40/(1+'Study Parameters'!$C$3)^'LCOF Baseline'!D$35 -> 1.349537e+08 | E41: =E40/(1+'Study Parameters'!$C$3)^'LCOF Baseline'!E$35 -> 1.2495713e+08 | F41: =F40/(1+'Study Parameters'!$C$3)^'LCOF Baseline'!F$35 -> 1.1570105e+08 | G41: =G40/(1+'Study Parameters'!$C$3)^'LCOF Baseline'!G$35 -> 1.071306e+08 | H41: =H40/(1+'Study Parameters'!$C$3)^'LCOF Baseline'!H$35 -> 99195001 | I41: =I40/(1+'Study Parameters'!$C$3)^'LCOF Baseline'!I$35 -> 91847223 | J41: =J40/(1+'Study Parameters'!$C$3)^'LCOF Baseline'!J$35 -> 85043725 | ... AF41: =AF40/(1+'Study Parameters'!$C$3)^'LCOF Baseline'!AF$35 -> 15642986
A43: Levelised Cost of Fuel (€/l) | B43: =(SUM(B37:AF37) - SUM(B39:AF39)) / SUM(B41:AF41) -> 3.6063103
A45: F-P-N/R
A46: Year | B46: 0 | C46: 1 | D46: 2 | E46: 3 | F46: 4 | G46: 5 | H46: 6 | I46: 7 | J46: 8 | K46: 9 | L46: 10 | M46: 11 | N46: 12 | O46: 13 | P46: 14 | Q46: 15 | R46: 16 | S46: 17 | T46: 18 | U46: 19 | V46: 20 | W46: 21 | X46: 22 | Y46: 23 | Z46: 24 | AA46: 25 | AB46: 26 | AC46: 27 | AD46: 28 | AE46: 29 | AF46: 30
A47: Cost (€) | B47: ='Cost Components'!T8 * 10^6 -> 3.3015567e+09 | C47: ='Cost Components'!$Z$16 * 10^6 -> 325000000 | D47: ='Cost Components'!$Z$16 * 10^6 -> 325000000 | E47: ='Cost Components'!$Z$16 * 10^6 -> 325000000 | F47: ='Cost Components'!$Z$16 * 10^6 -> 325000000 | G47: ='Cost Components'!$Z$16 * 10^6 -> 325000000 | H47: ='Cost Components'!$Z$16 * 10^6 -> 325000000 | I47: ='Cost Components'!$Z$16 * 10^6 -> 325000000 | J47: ='Cost Components'!$Z$16 * 10^6 -> 325000000 | ... M47: ='Cost Components'!$Z$16 * 10^6 -> 325000000 | N47: ='Cost Components'!$Z$16 * 10^6 + 'Cost Components'!$Z$7 * 10^6 -> 394000000 | O47: ='Cost Components'!$Z$16 * 10^6 -> 325000000 | P47: ='Cost Components'!$Z$16 * 10^6 -> 325000000 | Q47: ='Cost Components'!$Z$16 * 10^6 -> 325000000 | R47: ='Cost Components'!$Z$16 * 10^6 -> 325000000 | S47: ='Cost Components'!$Z$16 * 10^6 -> 325000000 | T47: ='Cost Components'!$Z$16 * 10^6 -> 325000000 | U47: ='Cost Components'!$Z$16 * 10^6 -> 325000000 | V47: ='Cost Components'!$Z$16 * 10^6 -> 325000000 | ... Y47: ='Cost Components'!$Z$16 * 10^6 -> 325000000 | Z47: ='Cost Components'!$Z$16 * 10^6 + 'Cost Components'!$Z$7 * 10^6 -> 394000000 | AA47: ='Cost Components'!$Z$16 * 10^6 -> 325000000 | AB47: ='Cost Components'!$Z$16 * 10^6 -> 325000000 | AC47: ='Cost Components'!$Z$16 * 10^6 -> 325000000 | AD47: ='Cost Components'!$Z$16 * 10^6 -> 325000000 | AE47: ='Cost Components'!$Z$16 * 10^6 -> 325000000 | AF47: ='Cost Components'!$Z$16 * 10^6 -> 325000000
A48: Discounted Cost (€) | B48: =B47/(1+'Study Parameters'!$C$3)^'LCOF Baseline'!B$46 -> 3.3015567e+09 | C48: =C47/(1+'Study Parameters'!$C$3)^'LCOF Baseline'!C$46 -> 3.0092593e+08 | D48: =D47/(1+'Study Parameters'!$C$3)^'LCOF Baseline'!D$46 -> 2.7863512e+08 | E48: =E47/(1+'Study Parameters'!$C$3)^'LCOF Baseline'!E$46 -> 2.5799548e+08 | F48: =F47/(1+'Study Parameters'!$C$3)^'LCOF Baseline'!F$46 -> 2.388847e+08 | G48: =G47/(1+'Study Parameters'!$C$3)^'LCOF Baseline'!G$46 -> 2.2118954e+08 | H48: =H47/(1+'Study Parameters'!$C$3)^'LCOF Baseline'!H$46 -> 2.0480513e+08 | I48: =I47/(1+'Study Parameters'!$C$3)^'LCOF Baseline'!I$46 -> 1.8963438e+08 | ... AF48: =AF47/(1+'Study Parameters'!$C$3)^'LCOF Baseline'!AF$46 -> 32297633
A49: Revenue (€) | B49: 0 | C49: ='Study Parameters'!$C$42 * 10^6 -> 122000000 | D49: ='Study Parameters'!$C$42 * 10^6 -> 122000000 | E49: ='Study Parameters'!$C$42 * 10^6 -> 122000000 | F49: ='Study Parameters'!$C$42 * 10^6 -> 122000000 | G49: ='Study Parameters'!$C$42 * 10^6 -> 122000000 | H49: ='Study Parameters'!$C$42 * 10^6 -> 122000000 | I49: ='Study Parameters'!$C$42 * 10^6 -> 122000000 | J49: ='Study Parameters'!$C$42 * 10^6 -> 122000000 | ... AF49: ='Study Parameters'!$C$42 * 10^6 -> 122000000
A50: Discounted Revenue (€) | B50: 0 | C50: =C49/(1+'Study Parameters'!$C$3)^'LCOF Baseline'!C$46 -> 1.1296296e+08 | D50: =D49/(1+'Study Parameters'!$C$3)^'LCOF Baseline'!D$46 -> 1.0459534e+08 | E50: =E49/(1+'Study Parameters'!$C$3)^'LCOF Baseline'!E$46 -> 96847533 | F50: =F49/(1+'Study Parameters'!$C$3)^'LCOF Baseline'!F$46 -> 89673642 | G50: =G49/(1+'Study Parameters'!$C$3)^'LCOF Baseline'!G$46 -> 83031150 | H50: =H49/(1+'Study Parameters'!$C$3)^'LCOF Baseline'!H$46 -> 76880694 | I50: =I49/(1+'Study Parameters'!$C$3)^'LCOF Baseline'!I$46 -> 71185828 | J50: =J49/(1+'Study Parameters'!$C$3)^'LCOF Baseline'!J$46 -> 65912804 | ... AF50: =AF49/(1+'Study Parameters'!$C$3)^'LCOF Baseline'!AF$46 -> 12124035
A51: Production (l) | B51: 0 | C51: ='Study Parameters'!$C$9 -> 157410000 | D51: ='Study Parameters'!$C$9 -> 157410000 | E51: ='Study Parameters'!$C$9 -> 157410000 | F51: ='Study Parameters'!$C$9 -> 157410000 | G51: ='Study Parameters'!$C$9 -> 157410000 | H51: ='Study Parameters'!$C$9 -> 157410000 | I51: ='Study Parameters'!$C$9 -> 157410000 | J51: ='Study Parameters'!$C$9 -> 157410000 | ... AF51: ='Study Parameters'!$C$9 -> 157410000
A52: Discounted Production (l) | B52: 0 | C52: =C51/(1+'Study Parameters'!$C$3)^'LCOF Baseline'!C$46 -> 145750000 | D52: =D51/(1+'Study Parameters'!$C$3)^'LCOF Baseline'!D$46 -> 1.349537e+08 | E52: =E51/(1+'Study Parameters'!$C$3)^'LCOF Baseline'!E$46 -> 1.2495713e+08 | F52: =F51/(1+'Study Parameters'!$C$3)^'LCOF Baseline'!F$46 -> 1.1570105e+08 | G52: =G51/(1+'Study Parameters'!$C$3)^'LCOF Baseline'!G$46 -> 1.071306e+08 | H52: =H51/(1+'Study Parameters'!$C$3)^'LCOF Baseline'!H$46 -> 99195001 | I52: =I51/(1+'Study Parameters'!$C$3)^'LCOF Baseline'!I$46 -> 91847223 | J52: =J51/(1+'Study Parameters'!$C$3)^'LCOF Baseline'!J$46 -> 85043725 | ... AF52: =AF51/(1+'Study Parameters'!$C$3)^'LCOF Baseline'!AF$46 -> 15642986
A54: Levelised Cost of Fuel (€/l) | B54: =(SUM(B48:AF48) - SUM(B50:AF50)) / SUM(B52:AF52) -> 3.1743174
A56: F-S-N/R
A57: Year | B57: 0 | C57: 1 | D57: 2 | E57: 3 | F57: 4 | G57: 5 | H57: 6 | I57: 7 | J57: 8 | K57: 9 | L57: 10 | M57: 11 | N57: 12 | O57: 13 | P57: 14 | Q57: 15 | R57: 16 | S57: 17 | T57: 18 | U57: 19 | V57: 20 | W57: 21 | X57: 22 | Y57: 23 | Z57: 24 | AA57: 25 | AB57: 26 | AC57: 27 | AD57: 28 | AE57: 29 | AF57: 30
A58: Cost (€) | B58: ='Cost Components'!$AF$8*10^6 -> 3.2465567e+09 | C58: ='Cost Components'!$AF$16*10^6 -> 278000000 | D58: ='Cost Components'!$AF$16*10^6 -> 278000000 | E58: ='Cost Components'!$AF$16*10^6 -> 278000000 | F58: ='Cost Components'!$AF$16*10^6 -> 278000000 | G58: ='Cost Components'!$AF$16*10^6 -> 278000000 | H58: ='Cost Components'!$AF$16*10^6 -> 278000000 | I58: ='Cost Components'!$AF$16*10^6 -> 278000000 | J58: ='Cost Components'!$AF$16*10^6 -> 278000000 | K58: ='Cost Components'!$AF$16*10^6 -> 278000000 | L58: ='Cost Components'!$AF$16*10^6 + 'Cost Components'!$AF$7 * 10^6 -> 348000000 | M58: ='Cost Components'!$AF$16*10^6 -> 278000000 | N58: ='Cost Components'!$AF$16*10^6 -> 278000000 | O58: ='Cost Components'!$AF$16*10^6 -> 278000000 | P58: ='Cost Components'!$AF$16*10^6 -> 278000000 | Q58: ='Cost Components'!$AF$16*10^6 -> 278000000 | R58: ='Cost Components'!$AF$16*10^6 -> 278000000 | S58: ='Cost Components'!$AF$16*10^6 -> 278000000 | T58: ='Cost Components'!$AF$16*10^6 -> 278000000 | U58: ='Cost Components'!$AF$16*10^6 -> 278000000 | V58: ='Cost Components'!$AF$16*10^6 + 'Cost Components'!$AF$7 * 10^6 -> 348000000 | W58: ='Cost Components'!$AF$16*10^6 -> 278000000 | X58: ='Cost Components'!$AF$16*10^6 -> 278000000 | Y58: ='Cost Components'!$AF$16*10^6 -> 278000000 | Z58: ='Cost Components'!$AF$16*10^6 -> 278000000 | AA58: ='Cost Components'!$AF$16*10^6 -> 278000000 | AB58: ='Cost Components'!$AF$16*10^6 -> 278000000 | AC58: ='Cost Components'!$AF$16*10^6 -> 278000000 | AD58: ='Cost Components'!$AF$16*10^6 -> 278000000 | ... AF58: ='Cost Components'!$AF$16*10^6 -> 278000000
A59: Discounted Cost (€) | B59: =B58/(1+'Study Parameters'!$C$3)^'LCOF Baseline'!B$57 -> 3.2465567e+09 | C59: =C58/(1+'Study Parameters'!$C$3)^'LCOF Baseline'!C$57 -> 2.5740741e+08 | D59: =D58/(1+'Study Parameters'!$C$3)^'LCOF Baseline'!D$57 -> 2.3834019e+08 | E59: =E58/(1+'Study Parameters'!$C$3)^'LCOF Baseline'!E$57 -> 2.2068536e+08 | F59: =F58/(1+'Study Parameters'!$C$3)^'LCOF Baseline'!F$57 -> 2.043383e+08 | G59: =G58/(1+'Study Parameters'!$C$3)^'LCOF Baseline'!G$57 -> 1.8920213e+08 | H59: =H58/(1+'Study Parameters'!$C$3)^'LCOF Baseline'!H$57 -> 1.7518716e+08 | I59: =I58/(1+'Study Parameters'!$C$3)^'LCOF Baseline'!I$57 -> 1.6221033e+08 | ... AF59: =AF58/(1+'Study Parameters'!$C$3)^'LCOF Baseline'!AF$57 -> 27626898
A60: Revenue (€) | B60: 0 | C60: ='Study Parameters'!$C$42 * 10^6 -> 122000000 | D60: ='Study Parameters'!$C$42 * 10^6 -> 122000000 | E60: ='Study Parameters'!$C$42 * 10^6 -> 122000000 | F60: ='Study Parameters'!$C$42 * 10^6 -> 122000000 | G60: ='Study Parameters'!$C$42 * 10^6 -> 122000000 | H60: ='Study Parameters'!$C$42 * 10^6 -> 122000000 | I60: ='Study Parameters'!$C$42 * 10^6 -> 122000000 | J60: ='Study Parameters'!$C$42 * 10^6 -> 122000000 | ... AF60: ='Study Parameters'!$C$42 * 10^6 -> 122000000
A61: Discounted Revenue (€) | B61: 0 | C61: =C60/(1+'Study Parameters'!$C$3)^'LCOF Baseline'!C$57 -> 1.1296296e+08 | D61: =D60/(1+'Study Parameters'!$C$3)^'LCOF Baseline'!D$57 -> 1.0459534e+08 | E61: =E60/(1+'Study Parameters'!$C$3)^'LCOF Baseline'!E$57 -> 96847533 | F61: =F60/(1+'Study Parameters'!$C$3)^'LCOF Baseline'!F$57 -> 89673642 | G61: =G60/(1+'Study Parameters'!$C$3)^'LCOF Baseline'!G$57 -> 83031150 | H61: =H60/(1+'Study Parameters'!$C$3)^'LCOF Baseline'!H$57 -> 76880694 | I61: =I60/(1+'Study Parameters'!$C$3)^'LCOF Baseline'!I$57 -> 71185828 | J61: =J60/(1+'Study Parameters'!$C$3)^'LCOF Baseline'!J$57 -> 65912804 | ... AF61: =AF60/(1+'Study Parameters'!$C$3)^'LCOF Baseline'!AF$57 -> 12124035
A62: Production (l) | B62: 0 | C62: ='Study Parameters'!$C$9 -> 157410000 | D62: ='Study Parameters'!$C$9 -> 157410000 | E62: ='Study Parameters'!$C$9 -> 157410000 | F62: ='Study Parameters'!$C$9 -> 157410000 | G62: ='Study Parameters'!$C$9 -> 157410000 | H62: ='Study Parameters'!$C$9 -> 157410000 | I62: ='Study Parameters'!$C$9 -> 157410000 | J62: ='Study Parameters'!$C$9 -> 157410000 | ... AF62: ='Study Parameters'!$C$9 -> 157410000
A63: Discounted Production (l) | B63: 0 | C63: =C62/(1+'Study Parameters'!$C$3)^'LCOF Baseline'!C$57 -> 145750000 | D63: =D62/(1+'Study Parameters'!$C$3)^'LCOF Baseline'!D$57 -> 1.349537e+08 | E63: =E62/(1+'Study Parameters'!$C$3)^'LCOF Baseline'!E$57 -> 1.2495713e+08 | F63: =F62/(1+'Study Parameters'!$C$3)^'LCOF Baseline'!F$57 -> 1.1570105e+08 | G63: =G62/(1+'Study Parameters'!$C$3)^'LCOF Baseline'!G$57 -> 1.071306e+08 | H63: =H62/(1+'Study Parameters'!$C$3)^'LCOF Baseline'!H$57 -> 99195001 | I63: =I62/(1+'Study Parameters'!$C$3)^'LCOF Baseline'!I$57 -> 91847223 | J63: =J62/(1+'Study Parameters'!$C$3)^'LCOF Baseline'!J$57 -> 85043725 | ... AF63: =AF62/(1+'Study Parameters'!$C$3)^'LCOF Baseline'!AF$57 -> 15642986
A65: Levelised Cost of Fuel (€/l) | B65: =(SUM(B59:AF59) - SUM(B61:AF61)) / SUM(B63:AF63) -> 2.8498662

Sheet LCOF LCOE Corrected
A1: C-P-N
A2: Year | B2: 0 | C2: 1 | D2: 2 | E2: 3 | F2: 4 | G2: 5 | H2: 6 | I2: 7 | J2: 8 | K2: 9 | L2: 10 | M2: 11 | N2: 12 | O2: 13 | P2: 14 | Q2: 15 | R2: 16 | S2: 17 | T2: 18 | U2: 19 | V2: 20 | W2: 21 | X2: 22 | Y2: 23 | Z2: 24 | AA2: 25 | AB2: 26 | AC2: 27 | AD2: 28 | AE2: 29 | AF2: 30
A3: Cost (€) | B3: ='Cost Components'!B8*10^6 -> 7.5230785e+09 | C3: ='Cost Components'!$B$22 * 10^6 -> 5.6016102e+08 | D3: ='Cost Components'!$B$22 * 10^6 -> 5.6016102e+08 | E3: ='Cost Components'!$B$22 * 10^6 -> 5.6016102e+08 | F3: ='Cost Components'!$B$22 * 10^6 -> 5.6016102e+08 | G3: ='Cost Components'!$B$22 * 10^6 -> 5.6016102e+08 | H3: ='Cost Components'!$B$22 * 10^6 -> 5.6016102e+08 | I3: ='Cost Components'!$B$22 * 10^6 -> 5.6016102e+08 | J3: ='Cost Components'!$B$22 * 10^6 -> 5.6016102e+08 | K3: ='Cost Components'!$B$22 * 10^6 -> 5.6016102e+08 | L3: ='Cost Components'!$B$22 * 10^6 + 'Cost Components'!$B$7*10^6 -> 7.3716102e+08 | M3: ='Cost Components'!$B$22 * 10^6 -> 5.6016102e+08 | N3: ='Cost Components'!$B$22 * 10^6 -> 5.6016102e+08 | O3: ='Cost Components'!$B$22 * 10^6 -> 5.6016102e+08 | P3: ='Cost Components'!$B$22 * 10^6 -> 5.6016102e+08 | Q3: ='Cost Components'!$B$22 * 10^6 -> 5.6016102e+08 | R3: ='Cost Components'!$B$22 * 10^6 -> 5.6016102e+08 | S3: ='Cost Components'!$B$22 * 10^6 -> 5.6016102e+08 | T3: ='Cost Components'!$B$22 * 10^6 -> 5.6016102e+08 | U3: ='Cost Components'!$B$22 * 10^6 -> 5.6016102e+08 | V3: ='Cost Components'!$B$22 * 10^6 + 'Cost Components'!$B$7*10^6 -> 7.3716102e+08 | W3: ='Cost Components'!$B$16 * 10^6 -> 8.805e+08 | X3: ='Cost Components'!$B$16 * 10^6 -> 8.805e+08 | Y3: ='Cost Components'!$B$16 * 10^6 -> 8.805e+08 | Z3: ='Cost Components'!$B$16 * 10^6 -> 8.805e+08 | AA3: ='Cost Components'!$B$16 * 10^6 -> 8.805e+08 | AB3: ='Cost Components'!$B$16 * 10^6 -> 8.805e+08 | AC3: ='Cost Components'!$B$16 * 10^6 -> 8.805e+08 | AD3: ='Cost Components'!$B$16 * 10^6 -> 8.805e+08 | ... AF3: ='Cost Components'!$B$16 * 10^6 -> 8.805e+08
A4: Discounted Cost (€) | B4: =B3/(1+'Study Parameters'!$C$3) ^ 'LCOF Baseline'!B2 -> 7.5230785e+09 | C4: =C3/(1+'Study Parameters'!$C$3) ^ 'LCOF Baseline'!C2 -> 5.1866761e+08 | D4: =D3/(1+'Study Parameters'!$C$3) ^ 'LCOF Baseline'!D2 -> 4.8024779e+08 | E4: =E3/(1+'Study Parameters'!$C$3) ^ 'LCOF Baseline'!E2 -> 4.4467388e+08 | F4: =F3/(1+'Study Parameters'!$C$3) ^ 'LCOF Baseline'!F2 -> 4.1173507e+08 | G4: =G3/(1+'Study Parameters'!$C$3) ^ 'LCOF Baseline'!G2 -> 3.8123618e+08 | H4: =H3/(1+'Study Parameters'!$C$3) ^ 'LCOF Baseline'!H2 -> 3.5299646e+08 | I4: =I3/(1+'Study Parameters'!$C$3) ^ 'LCOF Baseline'!I2 -> 3.2684857e+08 | ... AF4: =AF3/(1+'Study Parameters'!$C$3) ^ 'LCOF Baseline'!AF2 -> 87501741
A5: Revenue (€) | B5: 0 | C5: ='Study Parameters'!$C$42*10^6 -> 122000000 | D5: ='Study Parameters'!$C$42*10^6 -> 122000000 | E5: ='Study Parameters'!$C$42*10^6 -> 122000000 | F5: ='Study Parameters'!$C$42*10^6 -> 122000000 | G5: ='Study Parameters'!$C$42*10^6 -> 122000000 | H5: ='Study Parameters'!$C$42*10^6 -> 122000000 | I5: ='Study Parameters'!$C$42*10^6 -> 122000000 | J5: ='Study Parameters'!$C$42*10^6 -> 122000000 | ... AF5: ='Study Parameters'!$C$42*10^6 -> 122000000
A6: Discounted Revenue (€) | B6: 0 | C6: =C5/(1+'Study Parameters'!$C$3) ^'LCOF Baseline'!C2 -> 1.1296296e+08 | D6: =D5/(1+'Study Parameters'!$C$3) ^'LCOF Baseline'!D2 -> 1.0459534e+08 | E6: =E5/(1+'Study Parameters'!$C$3) ^'LCOF Baseline'!E2 -> 96847533 | F6: =F5/(1+'Study Parameters'!$C$3) ^'LCOF Baseline'!F2 -> 89673642 | G6: =G5/(1+'Study Parameters'!$C$3) ^'LCOF Baseline'!G2 -> 83031150 | H6: =H5/(1+'Study Parameters'!$C$3) ^'LCOF Baseline'!H2 -> 76880694 | I6: =I5/(1+'Study Parameters'!$C$3) ^'LCOF Baseline'!I2 -> 71185828 | J6: =J5/(1+'Study Parameters'!$C$3) ^'LCOF Baseline'!J2 -> 65912804 | ... AF6: =AF5/(1+'Study Parameters'!$C$3) ^'LCOF Baseline'!AF2 -> 12124035
A7: Production (l) | B7: 0 | C7: ='Study Parameters'!$C$9 -> 157410000 | D7: ='Study Parameters'!$C$9 -> 157410000 | E7: ='Study Parameters'!$C$9 -> 157410000 | F7: ='Study Parameters'!$C$9 -> 157410000 | G7: ='Study Parameters'!$C$9 -> 157410000 | H7: ='Study Parameters'!$C$9 -> 157410000 | I7: ='Study Parameters'!$C$9 -> 157410000 | J7: ='Study Parameters'!$C$9 -> 157410000 | ... AF7: ='Study Parameters'!$C$9 -> 157410000
A8: Discounted Production (l) | B8: 0 | C8: =C7/(1+'Study Parameters'!$C$3) ^ 'LCOF Baseline'!C2 -> 145750000 | D8: =D7/(1+'Study Parameters'!$C$3) ^ 'LCOF Baseline'!D2 -> 1.349537e+08 | E8: =E7/(1+'Study Parameters'!$C$3) ^ 'LCOF Baseline'!E2 -> 1.2495713e+08 | F8: =F7/(1+'Study Parameters'!$C$3) ^ 'LCOF Baseline'!F2 -> 1.1570105e+08 | G8: =G7/(1+'Study Parameters'!$C$3) ^ 'LCOF Baseline'!G2 -> 1.071306e+08 | H8: =H7/(1+'Study Parameters'!$C$3) ^ 'LCOF Baseline'!H2 -> 99195001 | I8: =I7/(1+'Study Parameters'!$C$3) ^ 'LCOF Baseline'!I2 -> 91847223 | J8: =J7/(1+'Study Parameters'!$C$3) ^ 'LCOF Baseline'!J2 -> 85043725 | ... AF8: =AF7/(1+'Study Parameters'!$C$3) ^ 'LCOF Baseline'!AF2 -> 15642986
A10: Levelised Cost of Fuel (€/l) | B10: =(SUM(B4:AF4) - SUM(B6:AF6)) / SUM(B8:AF8) -> 7.3568211
A12: C-P-N/R
A13: Year | B13: 0 | C13: 1 | D13: 2 | E13: 3 | F13: 4 | G13: 5 | H13: 6 | I13: 7 | J13: 8 | K13: 9 | L13: 10 | M13: 11 | N13: 12 | O13: 13 | P13: 14 | Q13: 15 | R13: 16 | S13: 17 | T13: 18 | U13: 19 | V13: 20 | W13: 21 | X13: 22 | Y13: 23 | Z13: 24 | AA13: 25 | AB13: 26 | AC13: 27 | AD13: 28 | AE13: 29 | AF13: 30
A14: Cost (€) | B14: ='Cost Components'!H8*10^6 -> 7.5230785e+09 | C14: ='Cost Components'!$H$22*10^6 -> 5.8952256e+08 | D14: ='Cost Components'!$H$22*10^6 -> 5.8952256e+08 | E14: ='Cost Components'!$H$22*10^6 -> 5.8952256e+08 | F14: ='Cost Components'!$H$22*10^6 -> 5.8952256e+08 | G14: ='Cost Components'!$H$22*10^6 -> 5.8952256e+08 | H14: ='Cost Components'!$H$22*10^6 -> 5.8952256e+08 | I14: ='Cost Components'!$H$22*10^6 -> 5.8952256e+08 | J14: ='Cost Components'!$H$22*10^6 -> 5.8952256e+08 | K14: ='Cost Components'!$H$22*10^6 -> 5.8952256e+08 | L14: ='Cost Components'!$H$22*10^6 + 'Cost Components'!$H$7 * 10^6 -> 7.6652256e+08 | M14: ='Cost Components'!$H$22*10^6 -> 5.8952256e+08 | N14: ='Cost Components'!$H$22*10^6 -> 5.8952256e+08 | O14: ='Cost Components'!$H$22*10^6 -> 5.8952256e+08 | P14: ='Cost Components'!$H$22*10^6 -> 5.8952256e+08 | Q14: ='Cost Components'!$H$22*10^6 -> 5.8952256e+08 | R14: ='Cost Components'!$H$22*10^6 -> 5.8952256e+08 | S14: ='Cost Components'!$H$22*10^6 -> 5.8952256e+08 | T14: ='Cost Components'!$H$22*10^6 -> 5.8952256e+08 | U14: ='Cost Components'!$H$22*10^6 -> 5.8952256e+08 | V14: ='Cost Components'!$H$22*10^6 + 'Cost Components'!$H$7 * 10^6 -> 7.6652256e+08 | W14: ='Cost Components'!$H$22*10^6 -> 5.8952256e+08 | X14: ='Cost Components'!$H$22*10^6 -> 5.8952256e+08 | Y14: ='Cost Components'!$H$22*10^6 -> 5.8952256e+08 | Z14: ='Cost Components'!$H$22*10^6 -> 5.8952256e+08 | AA14: ='Cost Components'!$H$22*10^6 -> 5.8952256e+08 | AB14: ='Cost Components'!$H$22*10^6 -> 5.8952256e+08 | AC14: ='Cost Components'!$H$22*10^6 -> 5.8952256e+08 | AD14: ='Cost Components'!$H$22*10^6 -> 5.8952256e+08 | ... AF14: ='Cost Components'!$H$22*10^6 -> 5.8952256e+08
A15: Discounted Cost (€) | B15: =B14/(1+'Study Parameters'!$C$3) ^'LCOF Baseline'!B$13 -> 7.5230785e+09 | C15: =C14/(1+'Study Parameters'!$C$3) ^'LCOF Baseline'!C$13 -> 5.4585422e+08 | D15: =D14/(1+'Study Parameters'!$C$3) ^'LCOF Baseline'!D$13 -> 5.0542057e+08 | E15: =E14/(1+'Study Parameters'!$C$3) ^'LCOF Baseline'!E$13 -> 4.6798201e+08 | F15: =F14/(1+'Study Parameters'!$C$3) ^'LCOF Baseline'!F$13 -> 4.3331668e+08 | G15: =G14/(1+'Study Parameters'!$C$3) ^'LCOF Baseline'!G$13 -> 4.0121915e+08 | H15: =H14/(1+'Study Parameters'!$C$3) ^'LCOF Baseline'!H$13 -> 3.7149921e+08 | I15: =I14/(1+'Study Parameters'!$C$3) ^'LCOF Baseline'!I$13 -> 3.4398075e+08 | ... AF15: =AF14/(1+'Study Parameters'!$C$3) ^'LCOF Baseline'!AF$13 -> 58585179
A16: Revenue (€) | B16: 0 | C16: ='Study Parameters'!$C$42 * 10^6 -> 122000000 | D16: ='Study Parameters'!$C$42 * 10^6 -> 122000000 | E16: ='Study Parameters'!$C$42 * 10^6 -> 122000000 | F16: ='Study Parameters'!$C$42 * 10^6 -> 122000000 | G16: ='Study Parameters'!$C$42 * 10^6 -> 122000000 | H16: ='Study Parameters'!$C$42 * 10^6 -> 122000000 | I16: ='Study Parameters'!$C$42 * 10^6 -> 122000000 | J16: ='Study Parameters'!$C$42 * 10^6 -> 122000000 | ... AF16: ='Study Parameters'!$C$42 * 10^6 -> 122000000
A17: Discounted Revenue (€) | B17: 0 | C17: =C16/(1+'Study Parameters'!$C$3) ^'LCOF Baseline'!C$13 -> 1.1296296e+08 | D17: =D16/(1+'Study Parameters'!$C$3) ^'LCOF Baseline'!D$13 -> 1.0459534e+08 | E17: =E16/(1+'Study Parameters'!$C$3) ^'LCOF Baseline'!E$13 -> 96847533 | F17: =F16/(1+'Study Parameters'!$C$3) ^'LCOF Baseline'!F$13 -> 89673642 | G17: =G16/(1+'Study Parameters'!$C$3) ^'LCOF Baseline'!G$13 -> 83031150 | H17: =H16/(1+'Study Parameters'!$C$3) ^'LCOF Baseline'!H$13 -> 76880694 | I17: =I16/(1+'Study Parameters'!$C$3) ^'LCOF Baseline'!I$13 -> 71185828 | J17: =J16/(1+'Study Parameters'!$C$3) ^'LCOF Baseline'!J$13 -> 65912804 | ... AF17: =AF16/(1+'Study Parameters'!$C$3) ^'LCOF Baseline'!AF$13 -> 12124035
A18: Production (l) | B18: 0 | C18: ='Study Parameters'!$C$9 -> 157410000 | D18: ='Study Parameters'!$C$9 -> 157410000 | E18: ='Study Parameters'!$C$9 -> 157410000 | F18: ='Study Parameters'!$C$9 -> 157410000 | G18: ='Study Parameters'!$C$9 -> 157410000 | H18: ='Study Parameters'!$C$9 -> 157410000 | I18: ='Study Parameters'!$C$9 -> 157410000 | J18: ='Study Parameters'!$C$9 -> 157410000 | ... AF18: ='Study Parameters'!$C$9 -> 157410000
A19: Discounted Production (l) | B19: 0 | C19: =C18/(1+'Study Parameters'!$C$3) ^'LCOF Baseline'!C$13 -> 145750000 | D19: =D18/(1+'Study Parameters'!$C$3) ^'LCOF Baseline'!D$13 -> 1.349537e+08 | E19: =E18/(1+'Study Parameters'!$C$3) ^'LCOF Baseline'!E$13 -> 1.2495713e+08 | F19: =F18/(1+'Study Parameters'!$C$3) ^'LCOF Baseline'!F$13 -> 1.1570105e+08 | G19: =G18/(1+'Study Parameters'!$C$3) ^'LCOF Baseline'!G$13 -> 1.071306e+08 | H19: =H18/(1+'Study Parameters'!$C$3) ^'LCOF Baseline'!H$13 -> 99195001 | I19: =I18/(1+'Study Parameters'!$C$3) ^'LCOF Baseline'!I$13 -> 91847223 | J19: =J18/(1+'Study Parameters'!$C$3) ^'LCOF Baseline'!J$13 -> 85043725 | ... AF19: =AF18/(1+'Study Parameters'!$C$3) ^'LCOF Baseline'!AF$13 -> 15642986
A21: Levelised Cost of Fuel (€/l) | B21: =(SUM(B15:AF15) - SUM(B17:AF17)) / SUM(B19:AF19) -> 7.2831083
A23: C-S-N/R
A24: Year | B24: 0 | C24: 1 | D24: 2 | E24: 3 | F24: 4 | G24: 5 | H24: 6 | I24: 7 | J24: 8 | K24: 9 | L24: 10 | M24: 11 | N24: 12 | O24: 13 | P24: 14 | Q24: 15 | R24: 16 | S24: 17 | T24: 18 | U24: 19 | V24: 20 | W24: 21 | X24: 22 | Y24: 23 | Z24: 24 | AA24: 25 | AB24: 26 | AC24: 27 | AD24: 28 | AE24: 29 | AF24: 30
A25: Cost (€) | B25: ='Cost Components'!N8 * 10^6 -> 7.7930785e+09 | C25: ='Cost Components'!$N$22 * 10^6 -> 5.105619e+08 | D25: ='Cost Components'!$N$22 * 10^6 -> 5.105619e+08 | E25: ='Cost Components'!$N$22 * 10^6 -> 5.105619e+08 | F25: ='Cost Components'!$N$22 * 10^6 -> 5.105619e+08 | G25: ='Cost Components'!$N$22 * 10^6 -> 5.105619e+08 | H25: ='Cost Components'!$N$22 * 10^6 -> 5.105619e+08 | I25: ='Cost Components'!$N$22 * 10^6 + 'Cost Components'!$N$7 * 10^6 -> 8.855619e+08 | J25: ='Cost Components'!$N$22 * 10^6 -> 5.105619e+08 | K25: ='Cost Components'!$N$22 * 10^6 -> 5.105619e+08 | L25: ='Cost Components'!$N$22 * 10^6 -> 5.105619e+08 | M25: ='Cost Components'!$N$22 * 10^6 -> 5.105619e+08 | N25: ='Cost Components'!$N$22 * 10^6 -> 5.105619e+08 | O25: ='Cost Components'!$N$22 * 10^6 + 'Cost Components'!$N$7 * 10^6 -> 8.855619e+08 | P25: ='Cost Components'!$N$22 * 10^6 -> 5.105619e+08 | Q25: ='Cost Components'!$N$22 * 10^6 -> 5.105619e+08 | R25: ='Cost Components'!$N$22 * 10^6 -> 5.105619e+08 | S25: ='Cost Components'!$N$22 * 10^6 -> 5.105619e+08 | T25: ='Cost Components'!$N$22 * 10^6 -> 5.105619e+08 | U25: ='Cost Components'!$N$22 * 10^6 + 'Cost Components'!$N$7 * 10^6 -> 8.855619e+08 | V25: ='Cost Components'!$N$22 * 10^6 -> 5.105619e+08 | W25: ='Cost Components'!$N$22 * 10^6 -> 5.105619e+08 | X25: ='Cost Components'!$N$22 * 10^6 -> 5.105619e+08 | Y25: ='Cost Components'!$N$22 * 10^6 -> 5.105619e+08 | Z25: ='Cost Components'!$N$22 * 10^6 -> 5.105619e+08 | AA25: ='Cost Components'!$N$22 * 10^6 + 'Cost Components'!$N$7 * 10^6 -> 8.855619e+08 | AB25: ='Cost Components'!$N$22 * 10^6 -> 5.105619e+08 | AC25: ='Cost Components'!$N$22 * 10^6 -> 5.105619e+08 | AD25: ='Cost Components'!$N$22 * 10^6 -> 5.105619e+08 | AE25: ='Cost Components'!$N$22 * 10^6 -> 5.105619e+08 | AF25: ='Cost Components'!$N$22 * 10^6 -> 5.105619e+08
A26: Discounted Cost (€) | B26: =B25/(1+'Study Parameters'!$C$3)^'LCOF Baseline'!B$24 -> 7.7930785e+09 | C26: =C25/(1+'Study Parameters'!$C$3)^'LCOF Baseline'!C$24 -> 4.727425e+08 | D26: =D25/(1+'Study Parameters'!$C$3)^'LCOF Baseline'!D$24 -> 4.3772454e+08 | E26: =E25/(1+'Study Parameters'!$C$3)^'LCOF Baseline'!E$24 -> 4.053005e+08 | F26: =F25/(1+'Study Parameters'!$C$3)^'LCOF Baseline'!F$24 -> 3.7527824e+08 | G26: =G25/(1+'Study Parameters'!$C$3)^'LCOF Baseline'!G$24 -> 3.4747985e+08 | H26: =H25/(1+'Study Parameters'!$C$3)^'LCOF Baseline'!H$24 -> 3.2174061e+08 | I26: =I25/(1+'Study Parameters'!$C$3)^'LCOF Baseline'!I$24 -> 5.1671687e+08 | ... AF26: =AF25/(1+'Study Parameters'!$C$3)^'LCOF Baseline'!AF$24 -> 50738280
A27: Revenue (€) | B27: 0 | C27: ='Study Parameters'!$C$42 * 10^6 -> 122000000 | D27: ='Study Parameters'!$C$42 * 10^6 -> 122000000 | E27: ='Study Parameters'!$C$42 * 10^6 -> 122000000 | F27: ='Study Parameters'!$C$42 * 10^6 -> 122000000 | G27: ='Study Parameters'!$C$42 * 10^6 -> 122000000 | H27: ='Study Parameters'!$C$42 * 10^6 -> 122000000 | I27: ='Study Parameters'!$C$42 * 10^6 -> 122000000 | J27: ='Study Parameters'!$C$42 * 10^6 -> 122000000 | ... AF27: ='Study Parameters'!$C$42 * 10^6 -> 122000000
A28: Discounted Revenue (€) | B28: 0 | C28: =C27/(1+'Study Parameters'!$C$3)^'LCOF Baseline'!C$24 -> 1.1296296e+08 | D28: =D27/(1+'Study Parameters'!$C$3)^'LCOF Baseline'!D$24 -> 1.0459534e+08 | E28: =E27/(1+'Study Parameters'!$C$3)^'LCOF Baseline'!E$24 -> 96847533 | F28: =F27/(1+'Study Parameters'!$C$3)^'LCOF Baseline'!F$24 -> 89673642 | G28: =G27/(1+'Study Parameters'!$C$3)^'LCOF Baseline'!G$24 -> 83031150 | H28: =H27/(1+'Study Parameters'!$C$3)^'LCOF Baseline'!H$24 -> 76880694 | I28: =I27/(1+'Study Parameters'!$C$3)^'LCOF Baseline'!I$24 -> 71185828 | J28: =J27/(1+'Study Parameters'!$C$3)^'LCOF Baseline'!J$24 -> 65912804 | ... AF28: =AF27/(1+'Study Parameters'!$C$3)^'LCOF Baseline'!AF$24 -> 12124035
A29: Production (l) | B29: 0 | C29: ='Study Parameters'!$C$9 -> 157410000 | D29: ='Study Parameters'!$C$9 -> 157410000 | E29: ='Study Parameters'!$C$9 -> 157410000 | F29: ='Study Parameters'!$C$9 -> 157410000 | G29: ='Study Parameters'!$C$9 -> 157410000 | H29: ='Study Parameters'!$C$9 -> 157410000 | I29: ='Study Parameters'!$C$9 -> 157410000 | J29: ='Study Parameters'!$C$9 -> 157410000 | ... AF29: ='Study Parameters'!$C$9 -> 157410000
A30: Discounted Production (l) | B30: 0 | C30: =C29/(1+'Study Parameters'!$C$3)^'LCOF Baseline'!C$24 -> 145750000 | D30: =D29/(1+'Study Parameters'!$C$3)^'LCOF Baseline'!D$24 -> 1.349537e+08 | E30: =E29/(1+'Study Parameters'!$C$3)^'LCOF Baseline'!E$24 -> 1.2495713e+08 | F30: =F29/(1+'Study Parameters'!$C$3)^'LCOF Baseline'!F$24 -> 1.1570105e+08 | G30: =G29/(1+'Study Parameters'!$C$3)^'LCOF Baseline'!G$24 -> 1.071306e+08 | H30: =H29/(1+'Study Parameters'!$C$3)^'LCOF Baseline'!H$24 -> 99195001 | I30: =I29/(1+'Study Parameters'!$C$3)^'LCOF Baseline'!I$24 -> 91847223 | J30: =J29/(1+'Study Parameters'!$C$3)^'LCOF Baseline'!J$24 -> 85043725 | ... AF30: =AF29/(1+'Study Parameters'!$C$3)^'LCOF Baseline'!AF$24 -> 15642986
A32: Levelised Cost of Fuel (€/l) | B32: =(SUM(B26:AF26) - SUM(B28:AF28)) / SUM(B30:AF30) -> 7.1473713
A34: F-P-N
A35: Year | B35: 0 | C35: 1 | D35: 2 | E35: 3 | F35: 4 | G35: 5 | H35: 6 | I35: 7 | J35: 8 | K35: 9 | L35: 10 | M35: 11 | N35: 12 | O35: 13 | P35: 14 | Q35: 15 | R35: 16 | S35: 17 | T35: 18 | U35: 19 | V35: 20 | W35: 21 | X35: 22 | Y35: 23 | Z35: 24 | AA35: 25 | AB35: 26 | AC35: 27 | AD35: 28 | AE35: 29 | AF35: 30
A36: Cost (€) | B36: ='Cost Components'!T8 * 10^6 -> 3.3015567e+09 | C36: ='Cost Components'!$T$22 * 10^6 -> 195660000 | D36: ='Cost Components'!$T$22 * 10^6 -> 195660000 | E36: ='Cost Components'!$T$22 * 10^6 -> 195660000 | F36: ='Cost Components'!$T$22 * 10^6 -> 195660000 | G36: ='Cost Components'!$T$22 * 10^6 -> 195660000 | H36: ='Cost Components'!$T$22 * 10^6 -> 195660000 | I36: ='Cost Components'!$T$22 * 10^6 -> 195660000 | J36: ='Cost Components'!$T$22 * 10^6 -> 195660000 | ... M36: ='Cost Components'!$T$22 * 10^6 -> 195660000 | N36: ='Cost Components'!$T$22 * 10^6 + 'Cost Components'!$T$7 * 10^6 -> 264660000 | O36: ='Cost Components'!$T$22 * 10^6 -> 195660000 | P36: ='Cost Components'!$T$22 * 10^6 -> 195660000 | Q36: ='Cost Components'!$T$22 * 10^6 -> 195660000 | R36: ='Cost Components'!$T$22 * 10^6 -> 195660000 | S36: ='Cost Components'!$T$22 * 10^6 -> 195660000 | T36: ='Cost Components'!$T$22 * 10^6 -> 195660000 | U36: ='Cost Components'!$T$22 * 10^6 -> 195660000 | V36: ='Cost Components'!$T$22 * 10^6 -> 195660000 | ... Y36: ='Cost Components'!$T$22 * 10^6 -> 195660000 | Z36: ='Cost Components'!$T$22 * 10^6 + 'Cost Components'!$T$7 * 10^6 -> 264660000 | AA36: ='Cost Components'!$T$22 * 10^6 -> 195660000 | AB36: ='Cost Components'!$T$22 * 10^6 -> 195660000 | AC36: ='Cost Components'!$T$22 * 10^6 -> 195660000 | AD36: ='Cost Components'!$T$22 * 10^6 -> 195660000 | AE36: ='Cost Components'!$T$22 * 10^6 -> 195660000 | AF36: ='Cost Components'!$T$22 * 10^6 -> 195660000
A37: Discounted Cost (€) | B37: =B36/(1+'Study Parameters'!$C$3)^'LCOF Baseline'!B$35 -> 3.3015567e+09 | C37: =C36/(1+'Study Parameters'!$C$3)^'LCOF Baseline'!C$35 -> 1.8116667e+08 | D37: =D36/(1+'Study Parameters'!$C$3)^'LCOF Baseline'!D$35 -> 1.6774691e+08 | E37: =E36/(1+'Study Parameters'!$C$3)^'LCOF Baseline'!E$35 -> 1.5532122e+08 | F37: =F36/(1+'Study Parameters'!$C$3)^'LCOF Baseline'!F$35 -> 1.4381594e+08 | G37: =G36/(1+'Study Parameters'!$C$3)^'LCOF Baseline'!G$35 -> 1.3316291e+08 | H37: =H36/(1+'Study Parameters'!$C$3)^'LCOF Baseline'!H$35 -> 1.2329899e+08 | I37: =I36/(1+'Study Parameters'!$C$3)^'LCOF Baseline'!I$35 -> 1.1416573e+08 | ... AF37: =AF36/(1+'Study Parameters'!$C$3)^'LCOF Baseline'!AF$35 -> 19444169
A38: Revenue (€) | B38: 0 | C38: ='Study Parameters'!$C$42 * 10^6 -> 122000000 | D38: ='Study Parameters'!$C$42 * 10^6 -> 122000000 | E38: ='Study Parameters'!$C$42 * 10^6 -> 122000000 | F38: ='Study Parameters'!$C$42 * 10^6 -> 122000000 | G38: ='Study Parameters'!$C$42 * 10^6 -> 122000000 | H38: ='Study Parameters'!$C$42 * 10^6 -> 122000000 | I38: ='Study Parameters'!$C$42 * 10^6 -> 122000000 | J38: ='Study Parameters'!$C$42 * 10^6 -> 122000000 | ... AF38: ='Study Parameters'!$C$42 * 10^6 -> 122000000
A39: Discounted Revenue (€) | B39: 0 | C39: =C38/(1+'Study Parameters'!$C$3)^'LCOF Baseline'!C$35 -> 1.1296296e+08 | D39: =D38/(1+'Study Parameters'!$C$3)^'LCOF Baseline'!D$35 -> 1.0459534e+08 | E39: =E38/(1+'Study Parameters'!$C$3)^'LCOF Baseline'!E$35 -> 96847533 | F39: =F38/(1+'Study Parameters'!$C$3)^'LCOF Baseline'!F$35 -> 89673642 | G39: =G38/(1+'Study Parameters'!$C$3)^'LCOF Baseline'!G$35 -> 83031150 | H39: =H38/(1+'Study Parameters'!$C$3)^'LCOF Baseline'!H$35 -> 76880694 | I39: =I38/(1+'Study Parameters'!$C$3)^'LCOF Baseline'!I$35 -> 71185828 | J39: =J38/(1+'Study Parameters'!$C$3)^'LCOF Baseline'!J$35 -> 65912804 | ... AF39: =AF38/(1+'Study Parameters'!$C$3)^'LCOF Baseline'!AF$35 -> 12124035
A40: Production (l) | B40: 0 | C40: ='Study Parameters'!$C$9 -> 157410000 | D40: ='Study Parameters'!$C$9 -> 157410000 | E40: ='Study Parameters'!$C$9 -> 157410000 | F40: ='Study Parameters'!$C$9 -> 157410000 | G40: ='Study Parameters'!$C$9 -> 157410000 | H40: ='Study Parameters'!$C$9 -> 157410000 | I40: ='Study Parameters'!$C$9 -> 157410000 | J40: ='Study Parameters'!$C$9 -> 157410000 | ... AF40: ='Study Parameters'!$C$9 -> 157410000
A41: Discounted Production (l) | B41: 0 | C41: =C40/(1+'Study Parameters'!$C$3)^'LCOF Baseline'!C$35 -> 145750000 | D41: =D40/(1+'Study Parameters'!$C$3)^'LCOF Baseline'!D$35 -> 1.349537e+08 | E41: =E40/(1+'Study Parameters'!$C$3)^'LCOF Baseline'!E$35 -> 1.2495713e+08 | F41: =F40/(1+'Study Parameters'!$C$3)^'LCOF Baseline'!F$35 -> 1.1570105e+08 | G41: =G40/(1+'Study Parameters'!$C$3)^'LCOF Baseline'!G$35 -> 1.071306e+08 | H41: =H40/(1+'Study Parameters'!$C$3)^'LCOF Baseline'!H$35 -> 99195001 | I41: =I40/(1+'Study Parameters'!$C$3)^'LCOF Baseline'!I$35 -> 91847223 | J41: =J40/(1+'Study Parameters'!$C$3)^'LCOF Baseline'!J$35 -> 85043725 | ... AF41: =AF40/(1+'Study Parameters'!$C$3)^'LCOF Baseline'!AF$35 -> 15642986
A43: Levelised Cost of Fuel (€/l) | B43: =(SUM(B37:AF37) - SUM(B39:AF39)) / SUM(B41:AF41) -> 2.3526415
A45: F-P-N/R
A46: Year | B46: 0 | C46: 1 | D46: 2 | E46: 3 | F46: 4 | G46: 5 | H46: 6 | I46: 7 | J46: 8 | K46: 9 | L46: 10 | M46: 11 | N46: 12 | O46: 13 | P46: 14 | Q46: 15 | R46: 16 | S46: 17 | T46: 18 | U46: 19 | V46: 20 | W46: 21 | X46: 22 | Y46: 23 | Z46: 24 | AA46: 25 | AB46: 26 | AC46: 27 | AD46: 28 | AE46: 29 | AF46: 30
A47: Cost (€) | B47: ='Cost Components'!T8 * 10^6 -> 3.3015567e+09 | C47: ='Cost Components'!$Z$22 * 10^6 -> 1.9426316e+08 | D47: ='Cost Components'!$Z$22 * 10^6 -> 1.9426316e+08 | E47: ='Cost Components'!$Z$22 * 10^6 -> 1.9426316e+08 | F47: ='Cost Components'!$Z$22 * 10^6 -> 1.9426316e+08 | G47: ='Cost Components'!$Z$22 * 10^6 -> 1.9426316e+08 | H47: ='Cost Components'!$Z$22 * 10^6 -> 1.9426316e+08 | I47: ='Cost Components'!$Z$22 * 10^6 -> 1.9426316e+08 | J47: ='Cost Components'!$Z$22 * 10^6 -> 1.9426316e+08 | ... M47: ='Cost Components'!$Z$22 * 10^6 -> 1.9426316e+08 | N47: ='Cost Components'!$Z$22* 10^6 + 'Cost Components'!$Z$7 * 10^6 -> 2.6326316e+08 | O47: ='Cost Components'!$Z$22 * 10^6 -> 1.9426316e+08 | P47: ='Cost Components'!$Z$22 * 10^6 -> 1.9426316e+08 | Q47: ='Cost Components'!$Z$22 * 10^6 -> 1.9426316e+08 | R47: ='Cost Components'!$Z$22 * 10^6 -> 1.9426316e+08 | S47: ='Cost Components'!$Z$22 * 10^6 -> 1.9426316e+08 | T47: ='Cost Components'!$Z$22 * 10^6 -> 1.9426316e+08 | U47: ='Cost Components'!$Z$22 * 10^6 -> 1.9426316e+08 | V47: ='Cost Components'!$Z$22 * 10^6 -> 1.9426316e+08 | ... Y47: ='Cost Components'!$Z$22 * 10^6 -> 1.9426316e+08 | Z47: ='Cost Components'!$Z$22 * 10^6 + 'Cost Components'!$Z$7 * 10^6 -> 2.6326316e+08 | AA47: ='Cost Components'!$Z$22 * 10^6 -> 1.9426316e+08 | AB47: ='Cost Components'!$Z$22 * 10^6 -> 1.9426316e+08 | AC47: ='Cost Components'!$Z$22 * 10^6 -> 1.9426316e+08 | AD47: ='Cost Components'!$Z$22 * 10^6 -> 1.9426316e+08 | AE47: ='Cost Components'!$Z$22 * 10^6 -> 1.9426316e+08 | AF47: ='Cost Components'!$Z$22 * 10^6 -> 1.9426316e+08
A48: Discounted Cost (€) | B48: =B47/(1+'Study Parameters'!$C$3)^'LCOF Baseline'!B$46 -> 3.3015567e+09 | C48: =C47/(1+'Study Parameters'!$C$3)^'LCOF Baseline'!C$46 -> 1.7987329e+08 | D48: =D47/(1+'Study Parameters'!$C$3)^'LCOF Baseline'!D$46 -> 1.6654935e+08 | E48: =E47/(1+'Study Parameters'!$C$3)^'LCOF Baseline'!E$46 -> 1.5421236e+08 | F48: =F47/(1+'Study Parameters'!$C$3)^'LCOF Baseline'!F$46 -> 1.4278922e+08 | G48: =G47/(1+'Study Parameters'!$C$3)^'LCOF Baseline'!G$46 -> 1.3221224e+08 | H48: =H47/(1+'Study Parameters'!$C$3)^'LCOF Baseline'!H$46 -> 1.2241874e+08 | I48: =I47/(1+'Study Parameters'!$C$3)^'LCOF Baseline'!I$46 -> 1.1335069e+08 | ... AF48: =AF47/(1+'Study Parameters'!$C$3)^'LCOF Baseline'!AF$46 -> 19305354
A49: Revenue (€) | B49: 0 | C49: ='Study Parameters'!$C$42 * 10^6 -> 122000000 | D49: ='Study Parameters'!$C$42 * 10^6 -> 122000000 | E49: ='Study Parameters'!$C$42 * 10^6 -> 122000000 | F49: ='Study Parameters'!$C$42 * 10^6 -> 122000000 | G49: ='Study Parameters'!$C$42 * 10^6 -> 122000000 | H49: ='Study Parameters'!$C$42 * 10^6 -> 122000000 | I49: ='Study Parameters'!$C$42 * 10^6 -> 122000000 | J49: ='Study Parameters'!$C$42 * 10^6 -> 122000000 | ... AF49: ='Study Parameters'!$C$42 * 10^6 -> 122000000
A50: Discounted Revenue (€) | B50: 0 | C50: =C49/(1+'Study Parameters'!$C$3)^'LCOF Baseline'!C$46 -> 1.1296296e+08 | D50: =D49/(1+'Study Parameters'!$C$3)^'LCOF Baseline'!D$46 -> 1.0459534e+08 | E50: =E49/(1+'Study Parameters'!$C$3)^'LCOF Baseline'!E$46 -> 96847533 | F50: =F49/(1+'Study Parameters'!$C$3)^'LCOF Baseline'!F$46 -> 89673642 | G50: =G49/(1+'Study Parameters'!$C$3)^'LCOF Baseline'!G$46 -> 83031150 | H50: =H49/(1+'Study Parameters'!$C$3)^'LCOF Baseline'!H$46 -> 76880694 | I50: =I49/(1+'Study Parameters'!$C$3)^'LCOF Baseline'!I$46 -> 71185828 | J50: =J49/(1+'Study Parameters'!$C$3)^'LCOF Baseline'!J$46 -> 65912804 | ... AF50: =AF49/(1+'Study Parameters'!$C$3)^'LCOF Baseline'!AF$46 -> 12124035
A51: Production (l) | B51: 0 | C51: ='Study Parameters'!$C$9 -> 157410000 | D51: ='Study Parameters'!$C$9 -> 157410000 | E51: ='Study Parameters'!$C$9 -> 157410000 | F51: ='Study Parameters'!$C$9 -> 157410000 | G51: ='Study Parameters'!$C$9 -> 157410000 | H51: ='Study Parameters'!$C$9 -> 157410000 | I51: ='Study Parameters'!$C$9 -> 157410000 | J51: ='Study Parameters'!$C$9 -> 157410000 | ... AF51: ='Study Parameters'!$C$9 -> 157410000
A52: Discounted Production (l) | B52: 0 | C52: =C51/(1+'Study Parameters'!$C$3)^'LCOF Baseline'!C$46 -> 145750000 | D52: =D51/(1+'Study Parameters'!$C$3)^'LCOF Baseline'!D$46 -> 1.349537e+08 | E52: =E51/(1+'Study Parameters'!$C$3)^'LCOF Baseline'!E$46 -> 1.2495713e+08 | F52: =F51/(1+'Study Parameters'!$C$3)^'LCOF Baseline'!F$46 -> 1.1570105e+08 | G52: =G51/(1+'Study Parameters'!$C$3)^'LCOF Baseline'!G$46 -> 1.071306e+08 | H52: =H51/(1+'Study Parameters'!$C$3)^'LCOF Baseline'!H$46 -> 99195001 | I52: =I51/(1+'Study Parameters'!$C$3)^'LCOF Baseline'!I$46 -> 91847223 | J52: =J51/(1+'Study Parameters'!$C$3)^'LCOF Baseline'!J$46 -> 85043725 | ... AF52: =AF51/(1+'Study Parameters'!$C$3)^'LCOF Baseline'!AF$46 -> 15642986
A54: Levelised Cost of Fuel (€/l) | B54: =(SUM(B48:AF48) - SUM(B50:AF50)) / SUM(B52:AF52) -> 2.3437676
A56: F-S-N/R
A57: Year | B57: 0 | C57: 1 | D57: 2 | E57: 3 | F57: 4 | G57: 5 | H57: 6 | I57: 7 | J57: 8 | K57: 9 | L57: 10 | M57: 11 | N57: 12 | O57: 13 | P57: 14 | Q57: 15 | R57: 16 | S57: 17 | T57: 18 | U57: 19 | V57: 20 | W57: 21 | X57: 22 | Y57: 23 | Z57: 24 | AA57: 25 | AB57: 26 | AC57: 27 | AD57: 28 | AE57: 29 | AF57: 30
A58: Cost (€) | B58: ='Cost Components'!$AF$8*10^6 -> 3.2465567e+09 | C58: ='Cost Components'!$AF$22*10^6 -> 1.6786842e+08 | D58: ='Cost Components'!$AF$22*10^6 -> 1.6786842e+08 | E58: ='Cost Components'!$AF$22*10^6 -> 1.6786842e+08 | F58: ='Cost Components'!$AF$22*10^6 -> 1.6786842e+08 | G58: ='Cost Components'!$AF$22*10^6 -> 1.6786842e+08 | H58: ='Cost Components'!$AF$22*10^6 -> 1.6786842e+08 | I58: ='Cost Components'!$AF$22*10^6 -> 1.6786842e+08 | J58: ='Cost Components'!$AF$22*10^6 -> 1.6786842e+08 | K58: ='Cost Components'!$AF$22*10^6 -> 1.6786842e+08 | L58: ='Cost Components'!$AF$22*10^6 + 'Cost Components'!$AF$7 * 10^6 -> 2.3786842e+08 | M58: ='Cost Components'!$AF$22*10^6 -> 1.6786842e+08 | N58: ='Cost Components'!$AF$22*10^6 -> 1.6786842e+08 | O58: ='Cost Components'!$AF$22*10^6 -> 1.6786842e+08 | P58: ='Cost Components'!$AF$22*10^6 -> 1.6786842e+08 | Q58: ='Cost Components'!$AF$22*10^6 -> 1.6786842e+08 | R58: ='Cost Components'!$AF$22*10^6 -> 1.6786842e+08 | S58: ='Cost Components'!$AF$22*10^6 -> 1.6786842e+08 | T58: ='Cost Components'!$AF$22*10^6 -> 1.6786842e+08 | U58: ='Cost Components'!$AF$22*10^6 -> 1.6786842e+08 | V58: ='Cost Components'!$AF$22*10^6 + 'Cost Components'!$AF$7 * 10^6 -> 2.3786842e+08 | W58: ='Cost Components'!$AF$22*10^6 -> 1.6786842e+08 | X58: ='Cost Components'!$AF$22*10^6 -> 1.6786842e+08 | Y58: ='Cost Components'!$AF$22*10^6 -> 1.6786842e+08 | Z58: ='Cost Components'!$AF$22*10^6 -> 1.6786842e+08 | AA58: ='Cost Components'!$AF$22*10^6 -> 1.6786842e+08 | AB58: ='Cost Components'!$AF$22*10^6 -> 1.6786842e+08 | AC58: ='Cost Components'!$AF$22*10^6 -> 1.6786842e+08 | AD58: ='Cost Components'!$AF$22*10^6 -> 1.6786842e+08 | ... AF58: ='Cost Components'!$AF$22*10^6 -> 1.6786842e+08
A59: Discounted Cost (€) | B59: =B58/(1+'Study Parameters'!$C$3)^'LCOF Baseline'!B$57 -> 3.2465567e+09 | C59: =C58/(1+'Study Parameters'!$C$3)^'LCOF Baseline'!C$57 -> 1.5543372e+08 | D59: =D58/(1+'Study Parameters'!$C$3)^'LCOF Baseline'!D$57 -> 1.4392011e+08 | E59: =E58/(1+'Study Parameters'!$C$3)^'LCOF Baseline'!E$57 -> 1.3325936e+08 | F59: =F58/(1+'Study Parameters'!$C$3)^'LCOF Baseline'!F$57 -> 1.233883e+08 | G59: =G58/(1+'Study Parameters'!$C$3)^'LCOF Baseline'!G$57 -> 1.1424843e+08 | H59: =H58/(1+'Study Parameters'!$C$3)^'LCOF Baseline'!H$57 -> 1.0578558e+08 | I59: =I58/(1+'Study Parameters'!$C$3)^'LCOF Baseline'!I$57 -> 97949611 | ... AF59: =AF58/(1+'Study Parameters'!$C$3)^'LCOF Baseline'!AF$57 -> 16682316
A60: Revenue (€) | B60: 0 | C60: ='Study Parameters'!$C$42 * 10^6 -> 122000000 | D60: ='Study Parameters'!$C$42 * 10^6 -> 122000000 | E60: ='Study Parameters'!$C$42 * 10^6 -> 122000000 | F60: ='Study Parameters'!$C$42 * 10^6 -> 122000000 | G60: ='Study Parameters'!$C$42 * 10^6 -> 122000000 | H60: ='Study Parameters'!$C$42 * 10^6 -> 122000000 | I60: ='Study Parameters'!$C$42 * 10^6 -> 122000000 | J60: ='Study Parameters'!$C$42 * 10^6 -> 122000000 | ... AF60: ='Study Parameters'!$C$42 * 10^6 -> 122000000
A61: Discounted Revenue (€) | B61: 0 | C61: =C60/(1+'Study Parameters'!$C$3)^'LCOF Baseline'!C$57 -> 1.1296296e+08 | D61: =D60/(1+'Study Parameters'!$C$3)^'LCOF Baseline'!D$57 -> 1.0459534e+08 | E61: =E60/(1+'Study Parameters'!$C$3)^'LCOF Baseline'!E$57 -> 96847533 | F61: =F60/(1+'Study Parameters'!$C$3)^'LCOF Baseline'!F$57 -> 89673642 | G61: =G60/(1+'Study Parameters'!$C$3)^'LCOF Baseline'!G$57 -> 83031150 | H61: =H60/(1+'Study Parameters'!$C$3)^'LCOF Baseline'!H$57 -> 76880694 | I61: =I60/(1+'Study Parameters'!$C$3)^'LCOF Baseline'!I$57 -> 71185828 | J61: =J60/(1+'Study Parameters'!$C$3)^'LCOF Baseline'!J$57 -> 65912804 | ... AF61: =AF60/(1+'Study Parameters'!$C$3)^'LCOF Baseline'!AF$57 -> 12124035
A62: Production (l) | B62: 0 | C62: ='Study Parameters'!$C$9 -> 157410000 | D62: ='Study Parameters'!$C$9 -> 157410000 | E62: ='Study Parameters'!$C$9 -> 157410000 | F62: ='Study Parameters'!$C$9 -> 157410000 | G62: ='Study Parameters'!$C$9 -> 157410000 | H62: ='Study Parameters'!$C$9 -> 157410000 | I62: ='Study Parameters'!$C$9 -> 157410000 | J62: ='Study Parameters'!$C$9 -> 157410000 | ... AF62: ='Study Parameters'!$C$9 -> 157410000
A63: Discounted Production (l) | B63: 0 | C63: =C62/(1+'Study Parameters'!$C$3)^'LCOF Baseline'!C$57 -> 145750000 | D63: =D62/(1+'Study Parameters'!$C$3)^'LCOF Baseline'!D$57 -> 1.349537e+08 | E63: =E62/(1+'Study Parameters'!$C$3)^'LCOF Baseline'!E$57 -> 1.2495713e+08 | F63: =F62/(1+'Study Parameters'!$C$3)^'LCOF Baseline'!F$57 -> 1.1570105e+08 | G63: =G62/(1+'Study Parameters'!$C$3)^'LCOF Baseline'!G$57 -> 1.071306e+08 | H63: =H62/(1+'Study Parameters'!$C$3)^'LCOF Baseline'!H$57 -> 99195001 | I63: =I62/(1+'Study Parameters'!$C$3)^'LCOF Baseline'!I$57 -> 91847223 | J63: =J62/(1+'Study Parameters'!$C$3)^'LCOF Baseline'!J$57 -> 85043725 | ... AF63: =AF62/(1+'Study Parameters'!$C$3)^'LCOF Baseline'!AF$57 -> 15642986
A65: Levelised Cost of Fuel (€/l) | B65: =(SUM(B59:AF59) - SUM(B61:AF61)) / SUM(B63:AF63) -> 2.1502183

Sheet LCOF CO2 Cost Corrected
A1: C-P-N
A2: Year | B2: 0 | C2: 1 | D2: 2 | E2: 3 | F2: 4 | G2: 5 | H2: 6 | I2: 7 | J2: 8 | K2: 9 | L2: 10 | M2: 11 | N2: 12 | O2: 13 | P2: 14 | Q2: 15 | R2: 16 | S2: 17 | T2: 18 | U2: 19 | V2: 20 | W2: 21 | X2: 22 | Y2: 23 | Z2: 24 | AA2: 25 | AB2: 26 | AC2: 27 | AD2: 28 | AE2: 29 | AF2: 30
A3: Cost (€) | B3: ='Cost Components'!B23*10^6 -> 1100000000 | C3: ='Cost Components'!$B$26 * 10^6 -> 1.856261e+09 | D3: ='Cost Components'!$B$26 * 10^6 -> 1.856261e+09 | E3: ='Cost Components'!$B$26 * 10^6 -> 1.856261e+09 | F3: ='Cost Components'!$B$26 * 10^6 -> 1.856261e+09 | G3: ='Cost Components'!$B$26 * 10^6 -> 1.856261e+09 | H3: ='Cost Components'!$B$26 * 10^6 -> 1.856261e+09 | I3: ='Cost Components'!$B$26 * 10^6 -> 1.856261e+09 | J3: ='Cost Components'!$B$26 * 10^6 -> 1.856261e+09 | K3: ='Cost Components'!$B$26 * 10^6 -> 1.856261e+09 | L3: ='Cost Components'!$B$26 * 10^6 + 'Cost Components'!$B$7*10^6 -> 2.033261e+09 | M3: ='Cost Components'!$B$26 * 10^6 -> 1.856261e+09 | N3: ='Cost Components'!$B$26 * 10^6 -> 1.856261e+09 | O3: ='Cost Components'!$B$26 * 10^6 -> 1.856261e+09 | P3: ='Cost Components'!$B$26 * 10^6 -> 1.856261e+09 | Q3: ='Cost Components'!$B$26 * 10^6 -> 1.856261e+09 | R3: ='Cost Components'!$B$26 * 10^6 -> 1.856261e+09 | S3: ='Cost Components'!$B$26 * 10^6 -> 1.856261e+09 | T3: ='Cost Components'!$B$26 * 10^6 -> 1.856261e+09 | U3: ='Cost Components'!$B$26 * 10^6 -> 1.856261e+09 | V3: ='Cost Components'!$B$26 * 10^6 + 'Cost Components'!$B$7*10^6 -> 2.033261e+09 | W3: ='Cost Components'!$B$26 * 10^6 -> 1.856261e+09 | X3: ='Cost Components'!$B$26 * 10^6 -> 1.856261e+09 | Y3: ='Cost Components'!$B$26 * 10^6 -> 1.856261e+09 | Z3: ='Cost Components'!$B$26 * 10^6 -> 1.856261e+09 | AA3: ='Cost Components'!$B$26 * 10^6 -> 1.856261e+09 | AB3: ='Cost Components'!$B$26 * 10^6 -> 1.856261e+09 | AC3: ='Cost Components'!$B$26 * 10^6 -> 1.856261e+09 | AD3: ='Cost Components'!$B$26 * 10^6 -> 1.856261e+09 | ... AF3: ='Cost Components'!$B$26 * 10^6 -> 1.856261e+09
A4: Discounted Cost (€) | B4: =B3/(1+'Study Parameters'!$C$3) ^ 'LCOF Baseline'!B2 -> 1100000000 | C4: =C3/(1+'Study Parameters'!$C$3) ^ 'LCOF Baseline'!C2 -> 1.7187602e+09 | D4: =D3/(1+'Study Parameters'!$C$3) ^ 'LCOF Baseline'!D2 -> 1.5914446e+09 | E4: =E3/(1+'Study Parameters'!$C$3) ^ 'LCOF Baseline'!E2 -> 1.4735598e+09 | F4: =F3/(1+'Study Parameters'!$C$3) ^ 'LCOF Baseline'!F2 -> 1.3644073e+09 | G4: =G3/(1+'Study Parameters'!$C$3) ^ 'LCOF Baseline'!G2 -> 1.2633401e+09 | H4: =H3/(1+'Study Parameters'!$C$3) ^ 'LCOF Baseline'!H2 -> 1.1697593e+09 | I4: =I3/(1+'Study Parameters'!$C$3) ^ 'LCOF Baseline'!I2 -> 1.0831105e+09 | ... AF4: =AF3/(1+'Study Parameters'!$C$3) ^ 'LCOF Baseline'!AF2 -> 1.8447027e+08
A5: Revenue (€) | B5: 0 | C5: ='Study Parameters'!$C$42*10^6 -> 122000000 | D5: ='Study Parameters'!$C$42*10^6 -> 122000000 | E5: ='Study Parameters'!$C$42*10^6 -> 122000000 | F5: ='Study Parameters'!$C$42*10^6 -> 122000000 | G5: ='Study Parameters'!$C$42*10^6 -> 122000000 | H5: ='Study Parameters'!$C$42*10^6 -> 122000000 | I5: ='Study Parameters'!$C$42*10^6 -> 122000000 | J5: ='Study Parameters'!$C$42*10^6 -> 122000000 | ... AF5: ='Study Parameters'!$C$42*10^6 -> 122000000
A6: Discounted Revenue (€) | B6: 0 | C6: =C5/(1+'Study Parameters'!$C$3) ^'LCOF Baseline'!C2 -> 1.1296296e+08 | D6: =D5/(1+'Study Parameters'!$C$3) ^'LCOF Baseline'!D2 -> 1.0459534e+08 | E6: =E5/(1+'Study Parameters'!$C$3) ^'LCOF Baseline'!E2 -> 96847533 | F6: =F5/(1+'Study Parameters'!$C$3) ^'LCOF Baseline'!F2 -> 89673642 | G6: =G5/(1+'Study Parameters'!$C$3) ^'LCOF Baseline'!G2 -> 83031150 | H6: =H5/(1+'Study Parameters'!$C$3) ^'LCOF Baseline'!H2 -> 76880694 | I6: =I5/(1+'Study Parameters'!$C$3) ^'LCOF Baseline'!I2 -> 71185828 | J6: =J5/(1+'Study Parameters'!$C$3) ^'LCOF Baseline'!J2 -> 65912804 | ... AF6: =AF5/(1+'Study Parameters'!$C$3) ^'LCOF Baseline'!AF2 -> 12124035
A7: Production (l) | B7: 0 | C7: ='Study Parameters'!$C$9 -> 157410000 | D7: ='Study Parameters'!$C$9 -> 157410000 | E7: ='Study Parameters'!$C$9 -> 157410000 | F7: ='Study Parameters'!$C$9 -> 157410000 | G7: ='Study Parameters'!$C$9 -> 157410000 | H7: ='Study Parameters'!$C$9 -> 157410000 | I7: ='Study Parameters'!$C$9 -> 157410000 | J7: ='Study Parameters'!$C$9 -> 157410000 | ... AF7: ='Study Parameters'!$C$9 -> 157410000
A8: Discounted Production (l) | B8: 0 | C8: =C7/(1+'Study Parameters'!$C$3) ^ 'LCOF Baseline'!C2 -> 145750000 | D8: =D7/(1+'Study Parameters'!$C$3) ^ 'LCOF Baseline'!D2 -> 1.349537e+08 | E8: =E7/(1+'Study Parameters'!$C$3) ^ 'LCOF Baseline'!E2 -> 1.2495713e+08 | F8: =F7/(1+'Study Parameters'!$C$3) ^ 'LCOF Baseline'!F2 -> 1.1570105e+08 | G8: =G7/(1+'Study Parameters'!$C$3) ^ 'LCOF Baseline'!G2 -> 1.071306e+08 | H8: =H7/(1+'Study Parameters'!$C$3) ^ 'LCOF Baseline'!H2 -> 99195001 | I8: =I7/(1+'Study Parameters'!$C$3) ^ 'LCOF Baseline'!I2 -> 91847223 | J8: =J7/(1+'Study Parameters'!$C$3) ^ 'LCOF Baseline'!J2 -> 85043725 | ... AF8: =AF7/(1+'Study Parameters'!$C$3) ^ 'LCOF Baseline'!AF2 -> 15642986
A10: Levelised Cost of Fuel (€/l) | B10: =(SUM(B4:AF4) - SUM(B6:AF6)) / SUM(B8:AF8) -> 11.705908
A12: C-P-N/R
A13: Year | B13: 0 | C13: 1 | D13: 2 | E13: 3 | F13: 4 | G13: 5 | H13: 6 | I13: 7 | J13: 8 | K13: 9 | L13: 10 | M13: 11 | N13: 12 | O13: 13 | P13: 14 | Q13: 15 | R13: 16 | S13: 17 | T13: 18 | U13: 19 | V13: 20 | W13: 21 | X13: 22 | Y13: 23 | Z13: 24 | AA13: 25 | AB13: 26 | AC13: 27 | AD13: 28 | AE13: 29 | AF13: 30
A14: Cost (€) | B14: ='Cost Components'!H23*10^6 -> 1100000000 | C14: ='Cost Components'!$H$26*10^6 -> 1.9016226e+09 | D14: ='Cost Components'!$H$26*10^6 -> 1.9016226e+09 | E14: ='Cost Components'!$H$26*10^6 -> 1.9016226e+09 | F14: ='Cost Components'!$H$26*10^6 -> 1.9016226e+09 | G14: ='Cost Components'!$H$26*10^6 -> 1.9016226e+09 | H14: ='Cost Components'!$H$26*10^6 -> 1.9016226e+09 | I14: ='Cost Components'!$H$26*10^6 -> 1.9016226e+09 | J14: ='Cost Components'!$H$26*10^6 -> 1.9016226e+09 | K14: ='Cost Components'!$H$26*10^6 -> 1.9016226e+09 | L14: ='Cost Components'!$H$26*10^6 + 'Cost Components'!$H$7 * 10^6 -> 2.0786226e+09 | M14: ='Cost Components'!$H$26*10^6 -> 1.9016226e+09 | N14: ='Cost Components'!$H$26*10^6 -> 1.9016226e+09 | O14: ='Cost Components'!$H$26*10^6 -> 1.9016226e+09 | P14: ='Cost Components'!$H$26*10^6 -> 1.9016226e+09 | Q14: ='Cost Components'!$H$26*10^6 -> 1.9016226e+09 | R14: ='Cost Components'!$H$26*10^6 -> 1.9016226e+09 | S14: ='Cost Components'!$H$26*10^6 -> 1.9016226e+09 | T14: ='Cost Components'!$H$26*10^6 -> 1.9016226e+09 | U14: ='Cost Components'!$H$26*10^6 -> 1.9016226e+09 | V14: ='Cost Components'!$H$26*10^6 + 'Cost Components'!$H$7 * 10^6 -> 2.0786226e+09 | W14: ='Cost Components'!$H$26*10^6 -> 1.9016226e+09 | X14: ='Cost Components'!$H$26*10^6 -> 1.9016226e+09 | Y14: ='Cost Components'!$H$26*10^6 -> 1.9016226e+09 | Z14: ='Cost Components'!$H$26*10^6 -> 1.9016226e+09 | AA14: ='Cost Components'!$H$26*10^6 -> 1.9016226e+09 | AB14: ='Cost Components'!$H$26*10^6 -> 1.9016226e+09 | AC14: ='Cost Components'!$H$26*10^6 -> 1.9016226e+09 | AD14: ='Cost Components'!$H$26*10^6 -> 1.9016226e+09 | ... AF14: ='Cost Components'!$H$26*10^6 -> 1.9016226e+09
A15: Discounted Cost (€) | B15: =B14/(1+'Study Parameters'!$C$3) ^'LCOF Baseline'!B$13 -> 1100000000 | C15: =C14/(1+'Study Parameters'!$C$3) ^'LCOF Baseline'!C$13 -> 1.7607616e+09 | D15: =D14/(1+'Study Parameters'!$C$3) ^'LCOF Baseline'!D$13 -> 1.6303348e+09 | E15: =E14/(1+'Study Parameters'!$C$3) ^'LCOF Baseline'!E$13 -> 1.5095693e+09 | F15: =F14/(1+'Study Parameters'!$C$3) ^'LCOF Baseline'!F$13 -> 1.3977493e+09 | G15: =G14/(1+'Study Parameters'!$C$3) ^'LCOF Baseline'!G$13 -> 1.2942124e+09 | H15: =H14/(1+'Study Parameters'!$C$3) ^'LCOF Baseline'!H$13 -> 1.1983448e+09 | I15: =I14/(1+'Study Parameters'!$C$3) ^'LCOF Baseline'!I$13 -> 1.1095785e+09 | ... AF15: =AF14/(1+'Study Parameters'!$C$3) ^'LCOF Baseline'!AF$13 -> 1.8897818e+08
A16: Revenue (€) | B16: 0 | C16: ='Study Parameters'!$C$42 * 10^6 -> 122000000 | D16: ='Study Parameters'!$C$42 * 10^6 -> 122000000 | E16: ='Study Parameters'!$C$42 * 10^6 -> 122000000 | F16: ='Study Parameters'!$C$42 * 10^6 -> 122000000 | G16: ='Study Parameters'!$C$42 * 10^6 -> 122000000 | H16: ='Study Parameters'!$C$42 * 10^6 -> 122000000 | I16: ='Study Parameters'!$C$42 * 10^6 -> 122000000 | J16: ='Study Parameters'!$C$42 * 10^6 -> 122000000 | ... AF16: ='Study Parameters'!$C$42 * 10^6 -> 122000000
A17: Discounted Revenue (€) | B17: 0 | C17: =C16/(1+'Study Parameters'!$C$3) ^'LCOF Baseline'!C$13 -> 1.1296296e+08 | D17: =D16/(1+'Study Parameters'!$C$3) ^'LCOF Baseline'!D$13 -> 1.0459534e+08 | E17: =E16/(1+'Study Parameters'!$C$3) ^'LCOF Baseline'!E$13 -> 96847533 | F17: =F16/(1+'Study Parameters'!$C$3) ^'LCOF Baseline'!F$13 -> 89673642 | G17: =G16/(1+'Study Parameters'!$C$3) ^'LCOF Baseline'!G$13 -> 83031150 | H17: =H16/(1+'Study Parameters'!$C$3) ^'LCOF Baseline'!H$13 -> 76880694 | I17: =I16/(1+'Study Parameters'!$C$3) ^'LCOF Baseline'!I$13 -> 71185828 | J17: =J16/(1+'Study Parameters'!$C$3) ^'LCOF Baseline'!J$13 -> 65912804 | ... AF17: =AF16/(1+'Study Parameters'!$C$3) ^'LCOF Baseline'!AF$13 -> 12124035
A18: Production (l) | B18: 0 | C18: ='Study Parameters'!$C$9 -> 157410000 | D18: ='Study Parameters'!$C$9 -> 157410000 | E18: ='Study Parameters'!$C$9 -> 157410000 | F18: ='Study Parameters'!$C$9 -> 157410000 | G18: ='Study Parameters'!$C$9 -> 157410000 | H18: ='Study Parameters'!$C$9 -> 157410000 | I18: ='Study Parameters'!$C$9 -> 157410000 | J18: ='Study Parameters'!$C$9 -> 157410000 | ... AF18: ='Study Parameters'!$C$9 -> 157410000
A19: Discounted Production (l) | B19: 0 | C19: =C18/(1+'Study Parameters'!$C$3) ^'LCOF Baseline'!C$13 -> 145750000 | D19: =D18/(1+'Study Parameters'!$C$3) ^'LCOF Baseline'!D$13 -> 1.349537e+08 | E19: =E18/(1+'Study Parameters'!$C$3) ^'LCOF Baseline'!E$13 -> 1.2495713e+08 | F19: =F18/(1+'Study Parameters'!$C$3) ^'LCOF Baseline'!F$13 -> 1.1570105e+08 | G19: =G18/(1+'Study Parameters'!$C$3) ^'LCOF Baseline'!G$13 -> 1.071306e+08 | H19: =H18/(1+'Study Parameters'!$C$3) ^'LCOF Baseline'!H$13 -> 99195001 | I19: =I18/(1+'Study Parameters'!$C$3) ^'LCOF Baseline'!I$13 -> 91847223 | J19: =J18/(1+'Study Parameters'!$C$3) ^'LCOF Baseline'!J$13 -> 85043725 | ... AF19: =AF18/(1+'Study Parameters'!$C$3) ^'LCOF Baseline'!AF$13 -> 15642986
A21: Levelised Cost of Fuel (€/l) | B21: =(SUM(B15:AF15) - SUM(B17:AF17)) / SUM(B19:AF19) -> 11.994082
A23: C-S-N/R
A24: Year | B24: 0 | C24: 1 | D24: 2 | E24: 3 | F24: 4 | G24: 5 | H24: 6 | I24: 7 | J24: 8 | K24: 9 | L24: 10 | M24: 11 | N24: 12 | O24: 13 | P24: 14 | Q24: 15 | R24: 16 | S24: 17 | T24: 18 | U24: 19 | V24: 20 | W24: 21 | X24: 22 | Y24: 23 | Z24: 24 | AA24: 25 | AB24: 26 | AC24: 27 | AD24: 28 | AE24: 29 | AF24: 30
A25: Cost (€) | B25: ='Cost Components'!N23*10^6 -> 1370000000 | C25: ='Cost Components'!$N$26 * 10^6 -> 1.8167619e+09 | D25: ='Cost Components'!$N$26 * 10^6 -> 1.8167619e+09 | E25: ='Cost Components'!$N$26 * 10^6 -> 1.8167619e+09 | F25: ='Cost Components'!$N$26 * 10^6 -> 1.8167619e+09 | G25: ='Cost Components'!$N$26 * 10^6 -> 1.8167619e+09 | H25: ='Cost Components'!$N$26 * 10^6 -> 1.8167619e+09 | I25: ='Cost Components'!$N$26 * 10^6 + 'Cost Components'!$N$7 * 10^6 -> 2.1917619e+09 | J25: ='Cost Components'!$N$26 * 10^6 -> 1.8167619e+09 | K25: ='Cost Components'!$N$26 * 10^6 -> 1.8167619e+09 | L25: ='Cost Components'!$N$26 * 10^6 -> 1.8167619e+09 | M25: ='Cost Components'!$N$26 * 10^6 -> 1.8167619e+09 | N25: ='Cost Components'!$N$26 * 10^6 -> 1.8167619e+09 | O25: ='Cost Components'!$N$26 * 10^6 + 'Cost Components'!$N$7 * 10^6 -> 2.1917619e+09 | P25: ='Cost Components'!$N$26 * 10^6 -> 1.8167619e+09 | Q25: ='Cost Components'!$N$26 * 10^6 -> 1.8167619e+09 | R25: ='Cost Components'!$N$26 * 10^6 -> 1.8167619e+09 | S25: ='Cost Components'!$N$26 * 10^6 -> 1.8167619e+09 | T25: ='Cost Components'!$N$26 * 10^6 -> 1.8167619e+09 | U25: ='Cost Components'!$N$26 * 10^6 + 'Cost Components'!$N$7 * 10^6 -> 2.1917619e+09 | V25: ='Cost Components'!$N$26 * 10^6 -> 1.8167619e+09 | W25: ='Cost Components'!$N$26 * 10^6 -> 1.8167619e+09 | X25: ='Cost Components'!$N$26 * 10^6 -> 1.8167619e+09 | Y25: ='Cost Components'!$N$26 * 10^6 -> 1.8167619e+09 | Z25: ='Cost Components'!$N$26 * 10^6 -> 1.8167619e+09 | AA25: ='Cost Components'!$N$26* 10^6 + 'Cost Components'!$N$7 * 10^6 -> 2.1917619e+09 | AB25: ='Cost Components'!$N$26 * 10^6 -> 1.8167619e+09 | AC25: ='Cost Components'!$N$26 * 10^6 -> 1.8167619e+09 | AD25: ='Cost Components'!$N$26 * 10^6 -> 1.8167619e+09 | AE25: ='Cost Components'!$N$26 * 10^6 -> 1.8167619e+09 | AF25: ='Cost Components'!$N$26 * 10^6 -> 1.8167619e+09
A26: Discounted Cost (€) | B26: =B25/(1+'Study Parameters'!$C$3)^'LCOF Baseline'!B$24 -> 1370000000 | C26: =C25/(1+'Study Parameters'!$C$3)^'LCOF Baseline'!C$24 -> 1.6821869e+09 | D26: =D25/(1+'Study Parameters'!$C$3)^'LCOF Baseline'!D$24 -> 1.5575805e+09 | E26: =E25/(1+'Study Parameters'!$C$3)^'LCOF Baseline'!E$24 -> 1.4422042e+09 | F26: =F25/(1+'Study Parameters'!$C$3)^'LCOF Baseline'!F$24 -> 1.3353742e+09 | G26: =G25/(1+'Study Parameters'!$C$3)^'LCOF Baseline'!G$24 -> 1.2364576e+09 | H26: =H25/(1+'Study Parameters'!$C$3)^'LCOF Baseline'!H$24 -> 1.1448682e+09 | I26: =I25/(1+'Study Parameters'!$C$3)^'LCOF Baseline'!I$24 -> 1.278872e+09 | ... AF26: =AF25/(1+'Study Parameters'!$C$3)^'LCOF Baseline'!AF$24 -> 1.8054495e+08
A27: Revenue (€) | B27: 0 | C27: ='Study Parameters'!$C$42 * 10^6 -> 122000000 | D27: ='Study Parameters'!$C$42 * 10^6 -> 122000000 | E27: ='Study Parameters'!$C$42 * 10^6 -> 122000000 | F27: ='Study Parameters'!$C$42 * 10^6 -> 122000000 | G27: ='Study Parameters'!$C$42 * 10^6 -> 122000000 | H27: ='Study Parameters'!$C$42 * 10^6 -> 122000000 | I27: ='Study Parameters'!$C$42 * 10^6 -> 122000000 | J27: ='Study Parameters'!$C$42 * 10^6 -> 122000000 | ... AF27: ='Study Parameters'!$C$42 * 10^6 -> 122000000
A28: Discounted Revenue (€) | B28: 0 | C28: =C27/(1+'Study Parameters'!$C$3)^'LCOF Baseline'!C$24 -> 1.1296296e+08 | D28: =D27/(1+'Study Parameters'!$C$3)^'LCOF Baseline'!D$24 -> 1.0459534e+08 | E28: =E27/(1+'Study Parameters'!$C$3)^'LCOF Baseline'!E$24 -> 96847533 | F28: =F27/(1+'Study Parameters'!$C$3)^'LCOF Baseline'!F$24 -> 89673642 | G28: =G27/(1+'Study Parameters'!$C$3)^'LCOF Baseline'!G$24 -> 83031150 | H28: =H27/(1+'Study Parameters'!$C$3)^'LCOF Baseline'!H$24 -> 76880694 | I28: =I27/(1+'Study Parameters'!$C$3)^'LCOF Baseline'!I$24 -> 71185828 | J28: =J27/(1+'Study Parameters'!$C$3)^'LCOF Baseline'!J$24 -> 65912804 | ... AF28: =AF27/(1+'Study Parameters'!$C$3)^'LCOF Baseline'!AF$24 -> 12124035
A29: Production (l) | B29: 0 | C29: ='Study Parameters'!$C$9 -> 157410000 | D29: ='Study Parameters'!$C$9 -> 157410000 | E29: ='Study Parameters'!$C$9 -> 157410000 | F29: ='Study Parameters'!$C$9 -> 157410000 | G29: ='Study Parameters'!$C$9 -> 157410000 | H29: ='Study Parameters'!$C$9 -> 157410000 | I29: ='Study Parameters'!$C$9 -> 157410000 | J29: ='Study Parameters'!$C$9 -> 157410000 | ... AF29: ='Study Parameters'!$C$9 -> 157410000
A30: Discounted Production (l) | B30: 0 | C30: =C29/(1+'Study Parameters'!$C$3)^'LCOF Baseline'!C$24 -> 145750000 | D30: =D29/(1+'Study Parameters'!$C$3)^'LCOF Baseline'!D$24 -> 1.349537e+08 | E30: =E29/(1+'Study Parameters'!$C$3)^'LCOF Baseline'!E$24 -> 1.2495713e+08 | F30: =F29/(1+'Study Parameters'!$C$3)^'LCOF Baseline'!F$24 -> 1.1570105e+08 | G30: =G29/(1+'Study Parameters'!$C$3)^'LCOF Baseline'!G$24 -> 1.071306e+08 | H30: =H29/(1+'Study Parameters'!$C$3)^'LCOF Baseline'!H$24 -> 99195001 | I30: =I29/(1+'Study Parameters'!$C$3)^'LCOF Baseline'!I$24 -> 91847223 | J30: =J29/(1+'Study Parameters'!$C$3)^'LCOF Baseline'!J$24 -> 85043725 | ... AF30: =AF29/(1+'Study Parameters'!$C$3)^'LCOF Baseline'!AF$24 -> 15642986
A32: Levelised Cost of Fuel (€/l) | B32: =(SUM(B26:AF26) - SUM(B28:AF28)) / SUM(B30:AF30) -> 11.820864
A34: F-P-N
A35: Year | B35: 0 | C35: 1 | D35: 2 | E35: 3 | F35: 4 | G35: 5 | H35: 6 | I35: 7 | J35: 8 | K35: 9 | L35: 10 | M35: 11 | N35: 12 | O35: 13 | P35: 14 | Q35: 15 | R35: 16 | S35: 17 | T35: 18 | U35: 19 | V35: 20 | W35: 21 | X35: 22 | Y35: 23 | Z35: 24 | AA35: 25 | AB35: 26 | AC35: 27 | AD35: 28 | AE35: 29 | AF35: 30
A36: Cost (€) | B36: ='Cost Components'!T23 * 10^6 -> 850000000 | C36: ='Cost Components'!$T$26 * 10^6 -> 9.3684e+08 | D36: ='Cost Components'!$T$26 * 10^6 -> 9.3684e+08 | E36: ='Cost Components'!$T$26 * 10^6 -> 9.3684e+08 | F36: ='Cost Components'!$T$26 * 10^6 -> 9.3684e+08 | G36: ='Cost Components'!$T$26 * 10^6 -> 9.3684e+08 | H36: ='Cost Components'!$T$26 * 10^6 -> 9.3684e+08 | I36: ='Cost Components'!$T$26 * 10^6 -> 9.3684e+08 | J36: ='Cost Components'!$T$26 * 10^6 -> 9.3684e+08 | ... M36: ='Cost Components'!$T$26 * 10^6 -> 9.3684e+08 | N36: ='Cost Components'!$T$26 * 10^6 + 'Cost Components'!$T$7 * 10^6 -> 1.00584e+09 | O36: ='Cost Components'!$T$26 * 10^6 -> 9.3684e+08 | P36: ='Cost Components'!$T$26 * 10^6 -> 9.3684e+08 | Q36: ='Cost Components'!$T$26 * 10^6 -> 9.3684e+08 | R36: ='Cost Components'!$T$26 * 10^6 -> 9.3684e+08 | S36: ='Cost Components'!$T$26 * 10^6 -> 9.3684e+08 | T36: ='Cost Components'!$T$26 * 10^6 -> 9.3684e+08 | U36: ='Cost Components'!$T$26 * 10^6 -> 9.3684e+08 | V36: ='Cost Components'!$T$26 * 10^6 -> 9.3684e+08 | ... Y36: ='Cost Components'!$T$26 * 10^6 -> 9.3684e+08 | Z36: ='Cost Components'!$T$26 * 10^6 + 'Cost Components'!$T$7 * 10^6 -> 1.00584e+09 | AA36: ='Cost Components'!$T$26 * 10^6 -> 9.3684e+08 | AB36: ='Cost Components'!$T$26 * 10^6 -> 9.3684e+08 | AC36: ='Cost Components'!$T$26 * 10^6 -> 9.3684e+08 | AD36: ='Cost Components'!$T$26 * 10^6 -> 9.3684e+08 | AE36: ='Cost Components'!$T$26 * 10^6 -> 9.3684e+08 | AF36: ='Cost Components'!$T$26 * 10^6 -> 9.3684e+08
A37: Discounted Cost (€) | B37: =B36/(1+'Study Parameters'!$C$3)^'LCOF Baseline'!B$35 -> 850000000 | C37: =C36/(1+'Study Parameters'!$C$3)^'LCOF Baseline'!C$35 -> 8.6744444e+08 | D37: =D36/(1+'Study Parameters'!$C$3)^'LCOF Baseline'!D$35 -> 8.031893e+08 | E37: =E36/(1+'Study Parameters'!$C$3)^'LCOF Baseline'!E$35 -> 7.436938e+08 | F37: =F36/(1+'Study Parameters'!$C$3)^'LCOF Baseline'!F$35 -> 6.8860537e+08 | G37: =G36/(1+'Study Parameters'!$C$3)^'LCOF Baseline'!G$35 -> 6.3759756e+08 | H37: =H36/(1+'Study Parameters'!$C$3)^'LCOF Baseline'!H$35 -> 5.9036811e+08 | I37: =I36/(1+'Study Parameters'!$C$3)^'LCOF Baseline'!I$35 -> 5.4663714e+08 | ... AF37: =AF36/(1+'Study Parameters'!$C$3)^'LCOF Baseline'!AF$35 -> 93100660
A38: Revenue (€) | B38: 0 | C38: ='Study Parameters'!$C$42 * 10^6 -> 122000000 | D38: ='Study Parameters'!$C$42 * 10^6 -> 122000000 | E38: ='Study Parameters'!$C$42 * 10^6 -> 122000000 | F38: ='Study Parameters'!$C$42 * 10^6 -> 122000000 | G38: ='Study Parameters'!$C$42 * 10^6 -> 122000000 | H38: ='Study Parameters'!$C$42 * 10^6 -> 122000000 | I38: ='Study Parameters'!$C$42 * 10^6 -> 122000000 | J38: ='Study Parameters'!$C$42 * 10^6 -> 122000000 | ... AF38: ='Study Parameters'!$C$42 * 10^6 -> 122000000
A39: Discounted Revenue (€) | B39: 0 | C39: =C38/(1+'Study Parameters'!$C$3)^'LCOF Baseline'!C$35 -> 1.1296296e+08 | D39: =D38/(1+'Study Parameters'!$C$3)^'LCOF Baseline'!D$35 -> 1.0459534e+08 | E39: =E38/(1+'Study Parameters'!$C$3)^'LCOF Baseline'!E$35 -> 96847533 | F39: =F38/(1+'Study Parameters'!$C$3)^'LCOF Baseline'!F$35 -> 89673642 | G39: =G38/(1+'Study Parameters'!$C$3)^'LCOF Baseline'!G$35 -> 83031150 | H39: =H38/(1+'Study Parameters'!$C$3)^'LCOF Baseline'!H$35 -> 76880694 | I39: =I38/(1+'Study Parameters'!$C$3)^'LCOF Baseline'!I$35 -> 71185828 | J39: =J38/(1+'Study Parameters'!$C$3)^'LCOF Baseline'!J$35 -> 65912804 | ... AF39: =AF38/(1+'Study Parameters'!$C$3)^'LCOF Baseline'!AF$35 -> 12124035
A40: Production (l) | B40: 0 | C40: ='Study Parameters'!$C$9 -> 157410000 | D40: ='Study Parameters'!$C$9 -> 157410000 | E40: ='Study Parameters'!$C$9 -> 157410000 | F40: ='Study Parameters'!$C$9 -> 157410000 | G40: ='Study Parameters'!$C$9 -> 157410000 | H40: ='Study Parameters'!$C$9 -> 157410000 | I40: ='Study Parameters'!$C$9 -> 157410000 | J40: ='Study Parameters'!$C$9 -> 157410000 | ... AF40: ='Study Parameters'!$C$9 -> 157410000
A41: Discounted Production (l) | B41: 0 | C41: =C40/(1+'Study Parameters'!$C$3)^'LCOF Baseline'!C$35 -> 145750000 | D41: =D40/(1+'Study Parameters'!$C$3)^'LCOF Baseline'!D$35 -> 1.349537e+08 | E41: =E40/(1+'Study Parameters'!$C$3)^'LCOF Baseline'!E$35 -> 1.2495713e+08 | F41: =F40/(1+'Study Parameters'!$C$3)^'LCOF Baseline'!F$35 -> 1.1570105e+08 | G41: =G40/(1+'Study Parameters'!$C$3)^'LCOF Baseline'!G$35 -> 1.071306e+08 | H41: =H40/(1+'Study Parameters'!$C$3)^'LCOF Baseline'!H$35 -> 99195001 | I41: =I40/(1+'Study Parameters'!$C$3)^'LCOF Baseline'!I$35 -> 91847223 | J41: =J40/(1+'Study Parameters'!$C$3)^'LCOF Baseline'!J$35 -> 85043725 | ... AF41: =AF40/(1+'Study Parameters'!$C$3)^'LCOF Baseline'!AF$35 -> 15642986
A43: Levelised Cost of Fuel (€/l) | B43: =(SUM(B37:AF37) - SUM(B39:AF39)) / SUM(B41:AF41) -> 5.6778084
A45: F-P-N/R
A46: Year | B46: 0 | C46: 1 | D46: 2 | E46: 3 | F46: 4 | G46: 5 | H46: 6 | I46: 7 | J46: 8 | K46: 9 | L46: 10 | M46: 11 | N46: 12 | O46: 13 | P46: 14 | Q46: 15 | R46: 16 | S46: 17 | T46: 18 | U46: 19 | V46: 20 | W46: 21 | X46: 22 | Y46: 23 | Z46: 24 | AA46: 25 | AB46: 26 | AC46: 27 | AD46: 28 | AE46: 29 | AF46: 30
A47: Cost (€) | B47: ='Cost Components'!Z23 * 10^6 -> 850000000 | C47: ='Cost Components'!$Z$26 * 10^6 -> 9.1124674e+08 | D47: ='Cost Components'!$Z$26 * 10^6 -> 9.1124674e+08 | E47: ='Cost Components'!$Z$26 * 10^6 -> 9.1124674e+08 | F47: ='Cost Components'!$Z$26 * 10^6 -> 9.1124674e+08 | G47: ='Cost Components'!$Z$26 * 10^6 -> 9.1124674e+08 | H47: ='Cost Components'!$Z$26 * 10^6 -> 9.1124674e+08 | I47: ='Cost Components'!$Z$26 * 10^6 -> 9.1124674e+08 | J47: ='Cost Components'!$Z$26 * 10^6 -> 9.1124674e+08 | ... M47: ='Cost Components'!$Z$26 * 10^6 -> 9.1124674e+08 | N47: ='Cost Components'!$Z$26* 10^6 + 'Cost Components'!$Z$7 * 10^6 -> 9.8024674e+08 | O47: ='Cost Components'!$Z$26 * 10^6 -> 9.1124674e+08 | P47: ='Cost Components'!$Z$26 * 10^6 -> 9.1124674e+08 | Q47: ='Cost Components'!$Z$26 * 10^6 -> 9.1124674e+08 | R47: ='Cost Components'!$Z$26 * 10^6 -> 9.1124674e+08 | S47: ='Cost Components'!$Z$26 * 10^6 -> 9.1124674e+08 | T47: ='Cost Components'!$Z$26 * 10^6 -> 9.1124674e+08 | U47: ='Cost Components'!$Z$26 * 10^6 -> 9.1124674e+08 | V47: ='Cost Components'!$Z$26 * 10^6 -> 9.1124674e+08 | ... Y47: ='Cost Components'!$Z$26 * 10^6 -> 9.1124674e+08 | Z47: ='Cost Components'!$Z$26 * 10^6 + 'Cost Components'!$Z$7 * 10^6 -> 9.8024674e+08 | AA47: ='Cost Components'!$Z$26 * 10^6 -> 9.1124674e+08 | AB47: ='Cost Components'!$Z$26 * 10^6 -> 9.1124674e+08 | AC47: ='Cost Components'!$Z$26 * 10^6 -> 9.1124674e+08 | AD47: ='Cost Components'!$Z$26 * 10^6 -> 9.1124674e+08 | AE47: ='Cost Components'!$Z$26 * 10^6 -> 9.1124674e+08 | AF47: ='Cost Components'!$Z$26 * 10^6 -> 9.1124674e+08
A48: Discounted Cost (€) | B48: =B47/(1+'Study Parameters'!$C$3)^'LCOF Baseline'!B$46 -> 850000000 | C48: =C47/(1+'Study Parameters'!$C$3)^'LCOF Baseline'!C$46 -> 8.4374698e+08 | D48: =D47/(1+'Study Parameters'!$C$3)^'LCOF Baseline'!D$46 -> 7.812472e+08 | E48: =E47/(1+'Study Parameters'!$C$3)^'LCOF Baseline'!E$46 -> 7.2337704e+08 | F48: =F47/(1+'Study Parameters'!$C$3)^'LCOF Baseline'!F$46 -> 6.6979355e+08 | G48: =G47/(1+'Study Parameters'!$C$3)^'LCOF Baseline'!G$46 -> 6.2017922e+08 | H48: =H47/(1+'Study Parameters'!$C$3)^'LCOF Baseline'!H$46 -> 5.7424002e+08 | I48: =I47/(1+'Study Parameters'!$C$3)^'LCOF Baseline'!I$46 -> 5.3170372e+08 | ... AF48: =AF47/(1+'Study Parameters'!$C$3)^'LCOF Baseline'!AF$46 -> 90557270
A49: Revenue (€) | B49: 0 | C49: ='Study Parameters'!$C$42 * 10^6 -> 122000000 | D49: ='Study Parameters'!$C$42 * 10^6 -> 122000000 | E49: ='Study Parameters'!$C$42 * 10^6 -> 122000000 | F49: ='Study Parameters'!$C$42 * 10^6 -> 122000000 | G49: ='Study Parameters'!$C$42 * 10^6 -> 122000000 | H49: ='Study Parameters'!$C$42 * 10^6 -> 122000000 | I49: ='Study Parameters'!$C$42 * 10^6 -> 122000000 | J49: ='Study Parameters'!$C$42 * 10^6 -> 122000000 | ... AF49: ='Study Parameters'!$C$42 * 10^6 -> 122000000
A50: Discounted Revenue (€) | B50: 0 | C50: =C49/(1+'Study Parameters'!$C$3)^'LCOF Baseline'!C$46 -> 1.1296296e+08 | D50: =D49/(1+'Study Parameters'!$C$3)^'LCOF Baseline'!D$46 -> 1.0459534e+08 | E50: =E49/(1+'Study Parameters'!$C$3)^'LCOF Baseline'!E$46 -> 96847533 | F50: =F49/(1+'Study Parameters'!$C$3)^'LCOF Baseline'!F$46 -> 89673642 | G50: =G49/(1+'Study Parameters'!$C$3)^'LCOF Baseline'!G$46 -> 83031150 | H50: =H49/(1+'Study Parameters'!$C$3)^'LCOF Baseline'!H$46 -> 76880694 | I50: =I49/(1+'Study Parameters'!$C$3)^'LCOF Baseline'!I$46 -> 71185828 | J50: =J49/(1+'Study Parameters'!$C$3)^'LCOF Baseline'!J$46 -> 65912804 | ... AF50: =AF49/(1+'Study Parameters'!$C$3)^'LCOF Baseline'!AF$46 -> 12124035
A51: Production (l) | B51: 0 | C51: ='Study Parameters'!$C$9 -> 157410000 | D51: ='Study Parameters'!$C$9 -> 157410000 | E51: ='Study Parameters'!$C$9 -> 157410000 | F51: ='Study Parameters'!$C$9 -> 157410000 | G51: ='Study Parameters'!$C$9 -> 157410000 | H51: ='Study Parameters'!$C$9 -> 157410000 | I51: ='Study Parameters'!$C$9 -> 157410000 | J51: ='Study Parameters'!$C$9 -> 157410000 | ... AF51: ='Study Parameters'!$C$9 -> 157410000
A52: Discounted Production (l) | B52: 0 | C52: =C51/(1+'Study Parameters'!$C$3)^'LCOF Baseline'!C$46 -> 145750000 | D52: =D51/(1+'Study Parameters'!$C$3)^'LCOF Baseline'!D$46 -> 1.349537e+08 | E52: =E51/(1+'Study Parameters'!$C$3)^'LCOF Baseline'!E$46 -> 1.2495713e+08 | F52: =F51/(1+'Study Parameters'!$C$3)^'LCOF Baseline'!F$46 -> 1.1570105e+08 | G52: =G51/(1+'Study Parameters'!$C$3)^'LCOF Baseline'!G$46 -> 1.071306e+08 | H52: =H51/(1+'Study Parameters'!$C$3)^'LCOF Baseline'!H$46 -> 99195001 | I52: =I51/(1+'Study Parameters'!$C$3)^'LCOF Baseline'!I$46 -> 91847223 | J52: =J51/(1+'Study Parameters'!$C$3)^'LCOF Baseline'!J$46 -> 85043725 | ... AF52: =AF51/(1+'Study Parameters'!$C$3)^'LCOF Baseline'!AF$46 -> 15642986
A54: Levelised Cost of Fuel (€/l) | B54: =(SUM(B48:AF48) - SUM(B50:AF50)) / SUM(B52:AF52) -> 5.5152186
A56: F-S-N/R
A57: Year | B57: 0 | C57: 1 | D57: 2 | E57: 3 | F57: 4 | G57: 5 | H57: 6 | I57: 7 | J57: 8 | K57: 9 | L57: 10 | M57: 11 | N57: 12 | O57: 13 | P57: 14 | Q57: 15 | R57: 16 | S57: 17 | T57: 18 | U57: 19 | V57: 20 | W57: 21 | X57: 22 | Y57: 23 | Z57: 24 | AA57: 25 | AB57: 26 | AC57: 27 | AD57: 28 | AE57: 29 | AF57: 30
A58: Cost (€) | B58: ='Cost Components'!$AF$23*10^6 -> 795000000 | C58: ='Cost Components'!$AF$26*10^6 -> 8.6240463e+08 | D58: ='Cost Components'!$AF$26*10^6 -> 8.6240463e+08 | E58: ='Cost Components'!$AF$26*10^6 -> 8.6240463e+08 | F58: ='Cost Components'!$AF$26*10^6 -> 8.6240463e+08 | G58: ='Cost Components'!$AF$26*10^6 -> 8.6240463e+08 | H58: ='Cost Components'!$AF$26*10^6 -> 8.6240463e+08 | I58: ='Cost Components'!$AF$26*10^6 -> 8.6240463e+08 | J58: ='Cost Components'!$AF$26*10^6 -> 8.6240463e+08 | K58: ='Cost Components'!$AF$26*10^6 -> 8.6240463e+08 | L58: ='Cost Components'!$AF$26*10^6 + 'Cost Components'!$AF$7 * 10^6 -> 9.3240463e+08 | M58: ='Cost Components'!$AF$26*10^6 -> 8.6240463e+08 | N58: ='Cost Components'!$AF$26*10^6 -> 8.6240463e+08 | O58: ='Cost Components'!$AF$26*10^6 -> 8.6240463e+08 | P58: ='Cost Components'!$AF$26*10^6 -> 8.6240463e+08 | Q58: ='Cost Components'!$AF$26*10^6 -> 8.6240463e+08 | R58: ='Cost Components'!$AF$26*10^6 -> 8.6240463e+08 | S58: ='Cost Components'!$AF$26*10^6 -> 8.6240463e+08 | T58: ='Cost Components'!$AF$26*10^6 -> 8.6240463e+08 | U58: ='Cost Components'!$AF$26*10^6 -> 8.6240463e+08 | V58: ='Cost Components'!$AF$26*10^6 + 'Cost Components'!$AF$7 * 10^6 -> 9.3240463e+08 | W58: ='Cost Components'!$AF$26*10^6 -> 8.6240463e+08 | X58: ='Cost Components'!$AF$26*10^6 -> 8.6240463e+08 | Y58: ='Cost Components'!$AF$26*10^6 -> 8.6240463e+08 | Z58: ='Cost Components'!$AF$26*10^6 -> 8.6240463e+08 | AA58: ='Cost Components'!$AF$26*10^6 -> 8.6240463e+08 | AB58: ='Cost Components'!$AF$26*10^6 -> 8.6240463e+08 | AC58: ='Cost Components'!$AF$26*10^6 -> 8.6240463e+08 | AD58: ='Cost Components'!$AF$26*10^6 -> 8.6240463e+08 | ... AF58: ='Cost Components'!$AF$26*10^6 -> 8.6240463e+08
A59: Discounted Cost (€) | B59: =B58/(1+'Study Parameters'!$C$3)^'LCOF Baseline'!B$57 -> 795000000 | C59: =C58/(1+'Study Parameters'!$C$3)^'LCOF Baseline'!C$57 -> 7.9852281e+08 | D59: =D58/(1+'Study Parameters'!$C$3)^'LCOF Baseline'!D$57 -> 7.3937297e+08 | E59: =E58/(1+'Study Parameters'!$C$3)^'LCOF Baseline'!E$57 -> 6.846046e+08 | F59: =F58/(1+'Study Parameters'!$C$3)^'LCOF Baseline'!F$57 -> 6.3389315e+08 | G59: =G58/(1+'Study Parameters'!$C$3)^'LCOF Baseline'!G$57 -> 5.869381e+08 | H59: =H58/(1+'Study Parameters'!$C$3)^'LCOF Baseline'!H$57 -> 5.434612e+08 | I59: =I58/(1+'Study Parameters'!$C$3)^'LCOF Baseline'!I$57 -> 5.0320482e+08 | ... AF59: =AF58/(1+'Study Parameters'!$C$3)^'LCOF Baseline'!AF$57 -> 85703472
A60: Revenue (€) | B60: 0 | C60: ='Study Parameters'!$C$42 * 10^6 -> 122000000 | D60: ='Study Parameters'!$C$42 * 10^6 -> 122000000 | E60: ='Study Parameters'!$C$42 * 10^6 -> 122000000 | F60: ='Study Parameters'!$C$42 * 10^6 -> 122000000 | G60: ='Study Parameters'!$C$42 * 10^6 -> 122000000 | H60: ='Study Parameters'!$C$42 * 10^6 -> 122000000 | I60: ='Study Parameters'!$C$42 * 10^6 -> 122000000 | J60: ='Study Parameters'!$C$42 * 10^6 -> 122000000 | ... AF60: ='Study Parameters'!$C$42 * 10^6 -> 122000000
A61: Discounted Revenue (€) | B61: 0 | C61: =C60/(1+'Study Parameters'!$C$3)^'LCOF Baseline'!C$57 -> 1.1296296e+08 | D61: =D60/(1+'Study Parameters'!$C$3)^'LCOF Baseline'!D$57 -> 1.0459534e+08 | E61: =E60/(1+'Study Parameters'!$C$3)^'LCOF Baseline'!E$57 -> 96847533 | F61: =F60/(1+'Study Parameters'!$C$3)^'LCOF Baseline'!F$57 -> 89673642 | G61: =G60/(1+'Study Parameters'!$C$3)^'LCOF Baseline'!G$57 -> 83031150 | H61: =H60/(1+'Study Parameters'!$C$3)^'LCOF Baseline'!H$57 -> 76880694 | I61: =I60/(1+'Study Parameters'!$C$3)^'LCOF Baseline'!I$57 -> 71185828 | J61: =J60/(1+'Study Parameters'!$C$3)^'LCOF Baseline'!J$57 -> 65912804 | ... AF61: =AF60/(1+'Study Parameters'!$C$3)^'LCOF Baseline'!AF$57 -> 12124035
A62: Production (l) | B62: 0 | C62: ='Study Parameters'!$C$9 -> 157410000 | D62: ='Study Parameters'!$C$9 -> 157410000 | E62: ='Study Parameters'!$C$9 -> 157410000 | F62: ='Study Parameters'!$C$9 -> 157410000 | G62: ='Study Parameters'!$C$9 -> 157410000 | H62: ='Study Parameters'!$C$9 -> 157410000 | I62: ='Study Parameters'!$C$9 -> 157410000 | J62: ='Study Parameters'!$C$9 -> 157410000 | ... AF62: ='Study Parameters'!$C$9 -> 157410000
A63: Discounted Production (l) | B63: 0 | C63: =C62/(1+'Study Parameters'!$C$3)^'LCOF Baseline'!C$57 -> 145750000 | D63: =D62/(1+'Study Parameters'!$C$3)^'LCOF Baseline'!D$57 -> 1.349537e+08 | E63: =E62/(1+'Study Parameters'!$C$3)^'LCOF Baseline'!E$57 -> 1.2495713e+08 | F63: =F62/(1+'Study Parameters'!$C$3)^'LCOF Baseline'!F$57 -> 1.1570105e+08 | G63: =G62/(1+'Study Parameters'!$C$3)^'LCOF Baseline'!G$57 -> 1.071306e+08 | H63: =H62/(1+'Study Parameters'!$C$3)^'LCOF Baseline'!H$57 -> 99195001 | I63: =I62/(1+'Study Parameters'!$C$3)^'LCOF Baseline'!I$57 -> 91847223 | J63: =J62/(1+'Study Parameters'!$C$3)^'LCOF Baseline'!J$57 -> 85043725 | ... AF63: =AF62/(1+'Study Parameters'!$C$3)^'LCOF Baseline'!AF$57 -> 15642986
A65: Levelised Cost of Fuel (€/l) | B65: =(SUM(B59:AF59) - SUM(B61:AF61)) / SUM(B63:AF63) -> 5.1790648

Sheet LCOF WACC Corrected 
A1: C-P-N
A2: Year | B2: 0 | C2: 1 | D2: 2 | E2: 3 | F2: 4 | G2: 5 | H2: 6 | I2: 7 | J2: 8 | K2: 9 | L2: 10 | M2: 11 | N2: 12 | O2: 13 | P2: 14 | Q2: 15 | R2: 16 | S2: 17 | T2: 18 | U2: 19 | V2: 20 | W2: 21 | X2: 22 | Y2: 23 | Z2: 24 | AA2: 25 | AB2: 26 | AC2: 27 | AD2: 28 | AE2: 29 | AF2: 30
A3: Cost (€) | B3: ='Cost Components'!B23*10^6 -> 1100000000 | C3: ='Cost Components'!$B$26 * 10^6 -> 1.856261e+09 | D3: ='Cost Components'!$B$26 * 10^6 -> 1.856261e+09 | E3: ='Cost Components'!$B$26 * 10^6 -> 1.856261e+09 | F3: ='Cost Components'!$B$26 * 10^6 -> 1.856261e+09 | G3: ='Cost Components'!$B$26 * 10^6 -> 1.856261e+09 | H3: ='Cost Components'!$B$26 * 10^6 -> 1.856261e+09 | I3: ='Cost Components'!$B$26 * 10^6 -> 1.856261e+09 | J3: ='Cost Components'!$B$26 * 10^6 -> 1.856261e+09 | K3: ='Cost Components'!$B$26 * 10^6 -> 1.856261e+09 | L3: ='Cost Components'!$B$26 * 10^6 + 'Cost Components'!$B$7*10^6 -> 2.033261e+09 | M3: ='Cost Components'!$B$26 * 10^6 -> 1.856261e+09 | N3: ='Cost Components'!$B$26 * 10^6 -> 1.856261e+09 | O3: ='Cost Components'!$B$26 * 10^6 -> 1.856261e+09 | P3: ='Cost Components'!$B$26 * 10^6 -> 1.856261e+09 | Q3: ='Cost Components'!$B$26 * 10^6 -> 1.856261e+09 | R3: ='Cost Components'!$B$26 * 10^6 -> 1.856261e+09 | S3: ='Cost Components'!$B$26 * 10^6 -> 1.856261e+09 | T3: ='Cost Components'!$B$26 * 10^6 -> 1.856261e+09 | U3: ='Cost Components'!$B$26 * 10^6 -> 1.856261e+09 | V3: ='Cost Components'!$B$26 * 10^6 + 'Cost Components'!$B$7*10^6 -> 2.033261e+09 | W3: ='Cost Components'!$B$26 * 10^6 -> 1.856261e+09 | X3: ='Cost Components'!$B$26 * 10^6 -> 1.856261e+09 | Y3: ='Cost Components'!$B$26 * 10^6 -> 1.856261e+09 | Z3: ='Cost Components'!$B$26 * 10^6 -> 1.856261e+09 | AA3: ='Cost Components'!$B$26 * 10^6 -> 1.856261e+09 | AB3: ='Cost Components'!$B$26 * 10^6 -> 1.856261e+09 | AC3: ='Cost Components'!$B$26 * 10^6 -> 1.856261e+09 | AD3: ='Cost Components'!$B$26 * 10^6 -> 1.856261e+09 | ... AF3: ='Cost Components'!$B$26 * 10^6 -> 1.856261e+09
A4: Discounted Cost (€) | B4: =B3/(1+Inputs!$C$5) ^ 'LCOF Baseline'!B2 -> 1100000000 | C4: =C3/(1+Inputs!$C$5) ^ 'LCOF Baseline'!C2 -> 1.7348234e+09 | D4: =D3/(1+Inputs!$C$5) ^ 'LCOF Baseline'!D2 -> 1.6213303e+09 | E4: =E3/(1+Inputs!$C$5) ^ 'LCOF Baseline'!E2 -> 1.5152619e+09 | F4: =F3/(1+Inputs!$C$5) ^ 'LCOF Baseline'!F2 -> 1.4161326e+09 | G4: =G3/(1+Inputs!$C$5) ^ 'LCOF Baseline'!G2 -> 1.3234885e+09 | H4: =H3/(1+Inputs!$C$5) ^ 'LCOF Baseline'!H2 -> 1.2369051e+09 | I4: =I3/(1+Inputs!$C$5) ^ 'LCOF Baseline'!I2 -> 1.1559861e+09 | ... AF4: =AF3/(1+Inputs!$C$5) ^ 'LCOF Baseline'!AF2 -> 2.4385166e+08
A5: Revenue (€) | B5: 0 | C5: ='Study Parameters'!$C$42*10^6 -> 122000000 | D5: ='Study Parameters'!$C$42*10^6 -> 122000000 | E5: ='Study Parameters'!$C$42*10^6 -> 122000000 | F5: ='Study Parameters'!$C$42*10^6 -> 122000000 | G5: ='Study Parameters'!$C$42*10^6 -> 122000000 | H5: ='Study Parameters'!$C$42*10^6 -> 122000000 | I5: ='Study Parameters'!$C$42*10^6 -> 122000000 | J5: ='Study Parameters'!$C$42*10^6 -> 122000000 | ... AF5: ='Study Parameters'!$C$42*10^6 -> 122000000
A6: Discounted Revenue (€) | B6: 0 | C6: =C5/(1+Inputs!$C$5) ^'LCOF Baseline'!C2 -> 1.1401869e+08 | D6: =D5/(1+Inputs!$C$5) ^'LCOF Baseline'!D2 -> 1.0655952e+08 | E6: =E5/(1+Inputs!$C$5) ^'LCOF Baseline'!E2 -> 99588341 | F6: =F5/(1+Inputs!$C$5) ^'LCOF Baseline'!F2 -> 93073216 | G6: =G5/(1+Inputs!$C$5) ^'LCOF Baseline'!G2 -> 86984314 | H6: =H5/(1+Inputs!$C$5) ^'LCOF Baseline'!H2 -> 81293751 | I6: =I5/(1+Inputs!$C$5) ^'LCOF Baseline'!I2 -> 75975469 | J6: =J5/(1+Inputs!$C$5) ^'LCOF Baseline'!J2 -> 71005111 | ... AF6: =AF5/(1+Inputs!$C$5) ^'LCOF Baseline'!AF2 -> 16026788
A7: Production (l) | B7: 0 | C7: ='Study Parameters'!$C$9 -> 157410000 | D7: ='Study Parameters'!$C$9 -> 157410000 | E7: ='Study Parameters'!$C$9 -> 157410000 | F7: ='Study Parameters'!$C$9 -> 157410000 | G7: ='Study Parameters'!$C$9 -> 157410000 | H7: ='Study Parameters'!$C$9 -> 157410000 | I7: ='Study Parameters'!$C$9 -> 157410000 | J7: ='Study Parameters'!$C$9 -> 157410000 | ... AF7: ='Study Parameters'!$C$9 -> 157410000
A8: Discounted Production (l) | B8: 0 | C8: =C7/(1+Inputs!$C$5) ^ 'LCOF Baseline'!C2 -> 1.4711215e+08 | D8: =D7/(1+Inputs!$C$5) ^ 'LCOF Baseline'!D2 -> 1.3748799e+08 | E8: =E7/(1+Inputs!$C$5) ^ 'LCOF Baseline'!E2 -> 1.2849345e+08 | F8: =F7/(1+Inputs!$C$5) ^ 'LCOF Baseline'!F2 -> 1.2008734e+08 | G8: =G7/(1+Inputs!$C$5) ^ 'LCOF Baseline'!G2 -> 1.1223115e+08 | H8: =H7/(1+Inputs!$C$5) ^ 'LCOF Baseline'!H2 -> 1.0488893e+08 | I8: =I7/(1+Inputs!$C$5) ^ 'LCOF Baseline'!I2 -> 98027037 | J8: =J7/(1+Inputs!$C$5) ^ 'LCOF Baseline'!J2 -> 91614053 | ... AF8: =AF7/(1+Inputs!$C$5) ^ 'LCOF Baseline'!AF2 -> 20678498
A10: Levelised Cost of Fuel (€/l) | B10: =(SUM(B4:AF4) - SUM(B6:AF6)) / SUM(B8:AF8) -> 11.650105
A12: C-P-N/R
A13: Year | B13: 0 | C13: 1 | D13: 2 | E13: 3 | F13: 4 | G13: 5 | H13: 6 | I13: 7 | J13: 8 | K13: 9 | L13: 10 | M13: 11 | N13: 12 | O13: 13 | P13: 14 | Q13: 15 | R13: 16 | S13: 17 | T13: 18 | U13: 19 | V13: 20 | W13: 21 | X13: 22 | Y13: 23 | Z13: 24 | AA13: 25 | AB13: 26 | AC13: 27 | AD13: 28 | AE13: 29 | AF13: 30
A14: Cost (€) | B14: ='Cost Components'!H23*10^6 -> 1100000000 | C14: ='Cost Components'!$H$26*10^6 -> 1.9016226e+09 | D14: ='Cost Components'!$H$26*10^6 -> 1.9016226e+09 | E14: ='Cost Components'!$H$26*10^6 -> 1.9016226e+09 | F14: ='Cost Components'!$H$26*10^6 -> 1.9016226e+09 | G14: ='Cost Components'!$H$26*10^6 -> 1.9016226e+09 | H14: ='Cost Components'!$H$26*10^6 -> 1.9016226e+09 | I14: ='Cost Components'!$H$26*10^6 -> 1.9016226e+09 | J14: ='Cost Components'!$H$26*10^6 -> 1.9016226e+09 | K14: ='Cost Components'!$H$26*10^6 -> 1.9016226e+09 | L14: ='Cost Components'!$H$26*10^6 + 'Cost Components'!$H$7 * 10^6 -> 2.0786226e+09 | M14: ='Cost Components'!$H$26*10^6 -> 1.9016226e+09 | N14: ='Cost Components'!$H$26*10^6 -> 1.9016226e+09 | O14: ='Cost Components'!$H$26*10^6 -> 1.9016226e+09 | P14: ='Cost Components'!$H$26*10^6 -> 1.9016226e+09 | Q14: ='Cost Components'!$H$26*10^6 -> 1.9016226e+09 | R14: ='Cost Components'!$H$26*10^6 -> 1.9016226e+09 | S14: ='Cost Components'!$H$26*10^6 -> 1.9016226e+09 | T14: ='Cost Components'!$H$26*10^6 -> 1.9016226e+09 | U14: ='Cost Components'!$H$26*10^6 -> 1.9016226e+09 | V14: ='Cost Components'!$H$26*10^6 + 'Cost Components'!$H$7 * 10^6 -> 2.0786226e+09 | W14: ='Cost Components'!$H$26*10^6 -> 1.9016226e+09 | X14: ='Cost Components'!$H$26*10^6 -> 1.9016226e+09 | Y14: ='Cost Components'!$H$26*10^6 -> 1.9016226e+09 | Z14: ='Cost Components'!$H$26*10^6 -> 1.9016226e+09 | AA14: ='Cost Components'!$H$26*10^6 -> 1.9016226e+09 | AB14: ='Cost Components'!$H$26*10^6 -> 1.9016226e+09 | AC14: ='Cost Components'!$H$26*10^6 -> 1.9016226e+09 | AD14: ='Cost Components'!$H$26*10^6 -> 1.9016226e+09 | ... AF14: ='Cost Components'!$H$26*10^6 -> 1.9016226e+09
A15: Discounted Cost (€) | B15: =B14/(1+Inputs!$C$5) ^'LCOF Baseline'!B$13 -> 1100000000 | C15: =C14/(1+Inputs!$C$5) ^'LCOF Baseline'!C$13 -> 1.7772173e+09 | D15: =D14/(1+Inputs!$C$5) ^'LCOF Baseline'!D$13 -> 1.6609508e+09 | E15: =E14/(1+Inputs!$C$5) ^'LCOF Baseline'!E$13 -> 1.5522905e+09 | F15: =F14/(1+Inputs!$C$5) ^'LCOF Baseline'!F$13 -> 1.4507387e+09 | G15: =G14/(1+Inputs!$C$5) ^'LCOF Baseline'!G$13 -> 1.3558306e+09 | H15: =H14/(1+Inputs!$C$5) ^'LCOF Baseline'!H$13 -> 1.2671314e+09 | I15: =I14/(1+Inputs!$C$5) ^'LCOF Baseline'!I$13 -> 1.184235e+09 | ... AF15: =AF14/(1+Inputs!$C$5) ^'LCOF Baseline'!AF$13 -> 2.4981067e+08
A16: Revenue (€) | B16: 0 | C16: ='Study Parameters'!$C$42 * 10^6 -> 122000000 | D16: ='Study Parameters'!$C$42 * 10^6 -> 122000000 | E16: ='Study Parameters'!$C$42 * 10^6 -> 122000000 | F16: ='Study Parameters'!$C$42 * 10^6 -> 122000000 | G16: ='Study Parameters'!$C$42 * 10^6 -> 122000000 | H16: ='Study Parameters'!$C$42 * 10^6 -> 122000000 | I16: ='Study Parameters'!$C$42 * 10^6 -> 122000000 | J16: ='Study Parameters'!$C$42 * 10^6 -> 122000000 | ... AF16: ='Study Parameters'!$C$42 * 10^6 -> 122000000
A17: Discounted Revenue (€) | B17: 0 | C17: =C16/(1+Inputs!$C$5) ^'LCOF Baseline'!C$13 -> 1.1401869e+08 | D17: =D16/(1+Inputs!$C$5) ^'LCOF Baseline'!D$13 -> 1.0655952e+08 | E17: =E16/(1+Inputs!$C$5) ^'LCOF Baseline'!E$13 -> 99588341 | F17: =F16/(1+Inputs!$C$5) ^'LCOF Baseline'!F$13 -> 93073216 | G17: =G16/(1+Inputs!$C$5) ^'LCOF Baseline'!G$13 -> 86984314 | H17: =H16/(1+Inputs!$C$5) ^'LCOF Baseline'!H$13 -> 81293751 | I17: =I16/(1+Inputs!$C$5) ^'LCOF Baseline'!I$13 -> 75975469 | J17: =J16/(1+Inputs!$C$5) ^'LCOF Baseline'!J$13 -> 71005111 | ... AF17: =AF16/(1+Inputs!$C$5) ^'LCOF Baseline'!AF$13 -> 16026788
A18: Production (l) | B18: 0 | C18: ='Study Parameters'!$C$9 -> 157410000 | D18: ='Study Parameters'!$C$9 -> 157410000 | E18: ='Study Parameters'!$C$9 -> 157410000 | F18: ='Study Parameters'!$C$9 -> 157410000 | G18: ='Study Parameters'!$C$9 -> 157410000 | H18: ='Study Parameters'!$C$9 -> 157410000 | I18: ='Study Parameters'!$C$9 -> 157410000 | J18: ='Study Parameters'!$C$9 -> 157410000 | ... AF18: ='Study Parameters'!$C$9 -> 157410000
A19: Discounted Production (l) | B19: 0 | C19: =C18/(1+Inputs!$C$5) ^'LCOF Baseline'!C$13 -> 1.4711215e+08 | D19: =D18/(1+Inputs!$C$5) ^'LCOF Baseline'!D$13 -> 1.3748799e+08 | E19: =E18/(1+Inputs!$C$5) ^'LCOF Baseline'!E$13 -> 1.2849345e+08 | F19: =F18/(1+Inputs!$C$5) ^'LCOF Baseline'!F$13 -> 1.2008734e+08 | G19: =G18/(1+Inputs!$C$5) ^'LCOF Baseline'!G$13 -> 1.1223115e+08 | H19: =H18/(1+Inputs!$C$5) ^'LCOF Baseline'!H$13 -> 1.0488893e+08 | I19: =I18/(1+Inputs!$C$5) ^'LCOF Baseline'!I$13 -> 98027037 | J19: =J18/(1+Inputs!$C$5) ^'LCOF Baseline'!J$13 -> 91614053 | ... AF19: =AF18/(1+Inputs!$C$5) ^'LCOF Baseline'!AF$13 -> 20678498
A21: Levelised Cost of Fuel (€/l) | B21: =(SUM(B15:AF15) - SUM(B17:AF17)) / SUM(B19:AF19) -> 11.93828
A23: C-S-N/R
A24: Year | B24: 0 | C24: 1 | D24: 2 | E24: 3 | F24: 4 | G24: 5 | H24: 6 | I24: 7 | J24: 8 | K24: 9 | L24: 10 | M24: 11 | N24: 12 | O24: 13 | P24: 14 | Q24: 15 | R24: 16 | S24: 17 | T24: 18 | U24: 19 | V24: 20 | W24: 21 | X24: 22 | Y24: 23 | Z24: 24 | AA24: 25 | AB24: 26 | AC24: 27 | AD24: 28 | AE24: 29 | AF24: 30
A25: Cost (€) | B25: ='Cost Components'!N23*10^6 -> 1370000000 | C25: ='Cost Components'!$N$26 * 10^6 -> 1.8167619e+09 | D25: ='Cost Components'!$N$26 * 10^6 -> 1.8167619e+09 | E25: ='Cost Components'!$N$26 * 10^6 -> 1.8167619e+09 | F25: ='Cost Components'!$N$26 * 10^6 -> 1.8167619e+09 | G25: ='Cost Components'!$N$26 * 10^6 -> 1.8167619e+09 | H25: ='Cost Components'!$N$26 * 10^6 -> 1.8167619e+09 | I25: ='Cost Components'!$N$26 * 10^6 + 'Cost Components'!$N$7 * 10^6 -> 2.1917619e+09 | J25: ='Cost Components'!$N$26 * 10^6 -> 1.8167619e+09 | K25: ='Cost Components'!$N$26 * 10^6 -> 1.8167619e+09 | L25: ='Cost Components'!$N$26 * 10^6 -> 1.8167619e+09 | M25: ='Cost Components'!$N$26 * 10^6 -> 1.8167619e+09 | N25: ='Cost Components'!$N$26 * 10^6 -> 1.8167619e+09 | O25: ='Cost Components'!$N$26 * 10^6 + 'Cost Components'!$N$7 * 10^6 -> 2.1917619e+09 | P25: ='Cost Components'!$N$26 * 10^6 -> 1.8167619e+09 | Q25: ='Cost Components'!$N$26 * 10^6 -> 1.8167619e+09 | R25: ='Cost Components'!$N$26 * 10^6 -> 1.8167619e+09 | S25: ='Cost Components'!$N$26 * 10^6 -> 1.8167619e+09 | T25: ='Cost Components'!$N$26 * 10^6 -> 1.8167619e+09 | U25: ='Cost Components'!$N$26 * 10^6 + 'Cost Components'!$N$7 * 10^6 -> 2.1917619e+09 | V25: ='Cost Components'!$N$26 * 10^6 -> 1.8167619e+09 | W25: ='Cost Components'!$N$26 * 10^6 -> 1.8167619e+09 | X25: ='Cost Components'!$N$26 * 10^6 -> 1.8167619e+09 | Y25: ='Cost Components'!$N$26 * 10^6 -> 1.8167619e+09 | Z25: ='Cost Components'!$N$26 * 10^6 -> 1.8167619e+09 | AA25: ='Cost Components'!$N$26* 10^6 + 'Cost Components'!$N$7 * 10^6 -> 2.1917619e+09 | AB25: ='Cost Components'!$N$26 * 10^6 -> 1.8167619e+09 | AC25: ='Cost Components'!$N$26 * 10^6 -> 1.8167619e+09 | AD25: ='Cost Components'!$N$26 * 10^6 -> 1.8167619e+09 | AE25: ='Cost Components'!$N$26 * 10^6 -> 1.8167619e+09 | AF25: ='Cost Components'!$N$26 * 10^6 -> 1.8167619e+09
A26: Discounted Cost (€) | B26: =B25/(1+Inputs!$C$5)^'LCOF Baseline'!B$24 -> 1370000000 | C26: =C25/(1+Inputs!$C$5)^'LCOF Baseline'!C$24 -> 1.6979083e+09 | D26: =D25/(1+Inputs!$C$5)^'LCOF Baseline'!D$24 -> 1.5868302e+09 | E26: =E25/(1+Inputs!$C$5)^'LCOF Baseline'!E$24 -> 1.4830189e+09 | F26: =F25/(1+Inputs!$C$5)^'LCOF Baseline'!F$24 -> 1.385999e+09 | G26: =G25/(1+Inputs!$C$5)^'LCOF Baseline'!G$24 -> 1.2953261e+09 | H26: =H25/(1+Inputs!$C$5)^'LCOF Baseline'!H$24 -> 1.2105852e+09 | I26: =I25/(1+Inputs!$C$5)^'LCOF Baseline'!I$24 -> 1.3649192e+09 | ... AF26: =AF25/(1+Inputs!$C$5)^'LCOF Baseline'!AF$24 -> 2.3866277e+08
A27: Revenue (€) | B27: 0 | C27: ='Study Parameters'!$C$42 * 10^6 -> 122000000 | D27: ='Study Parameters'!$C$42 * 10^6 -> 122000000 | E27: ='Study Parameters'!$C$42 * 10^6 -> 122000000 | F27: ='Study Parameters'!$C$42 * 10^6 -> 122000000 | G27: ='Study Parameters'!$C$42 * 10^6 -> 122000000 | H27: ='Study Parameters'!$C$42 * 10^6 -> 122000000 | I27: ='Study Parameters'!$C$42 * 10^6 -> 122000000 | J27: ='Study Parameters'!$C$42 * 10^6 -> 122000000 | ... AF27: ='Study Parameters'!$C$42 * 10^6 -> 122000000
A28: Discounted Revenue (€) | B28: 0 | C28: =C27/(1+Inputs!$C$5)^'LCOF Baseline'!C$24 -> 1.1401869e+08 | D28: =D27/(1+Inputs!$C$5)^'LCOF Baseline'!D$24 -> 1.0655952e+08 | E28: =E27/(1+Inputs!$C$5)^'LCOF Baseline'!E$24 -> 99588341 | F28: =F27/(1+Inputs!$C$5)^'LCOF Baseline'!F$24 -> 93073216 | G28: =G27/(1+Inputs!$C$5)^'LCOF Baseline'!G$24 -> 86984314 | H28: =H27/(1+Inputs!$C$5)^'LCOF Baseline'!H$24 -> 81293751 | I28: =I27/(1+Inputs!$C$5)^'LCOF Baseline'!I$24 -> 75975469 | J28: =J27/(1+Inputs!$C$5)^'LCOF Baseline'!J$24 -> 71005111 | ... AF28: =AF27/(1+Inputs!$C$5)^'LCOF Baseline'!AF$24 -> 16026788
A29: Production (l) | B29: 0 | C29: ='Study Parameters'!$C$9 -> 157410000 | D29: ='Study Parameters'!$C$9 -> 157410000 | E29: ='Study Parameters'!$C$9 -> 157410000 | F29: ='Study Parameters'!$C$9 -> 157410000 | G29: ='Study Parameters'!$C$9 -> 157410000 | H29: ='Study Parameters'!$C$9 -> 157410000 | I29: ='Study Parameters'!$C$9 -> 157410000 | J29: ='Study Parameters'!$C$9 -> 157410000 | ... AF29: ='Study Parameters'!$C$9 -> 157410000
A30: Discounted Production (l) | B30: 0 | C30: =C29/(1+Inputs!$C$5)^'LCOF Baseline'!C$24 -> 1.4711215e+08 | D30: =D29/(1+Inputs!$C$5)^'LCOF Baseline'!D$24 -> 1.3748799e+08 | E30: =E29/(1+Inputs!$C$5)^'LCOF Baseline'!E$24 -> 1.2849345e+08 | F30: =F29/(1+Inputs!$C$5)^'LCOF Baseline'!F$24 -> 1.2008734e+08 | G30: =G29/(1+Inputs!$C$5)^'LCOF Baseline'!G$24 -> 1.1223115e+08 | H30: =H29/(1+Inputs!$C$5)^'LCOF Baseline'!H$24 -> 1.0488893e+08 | I30: =I29/(1+Inputs!$C$5)^'LCOF Baseline'!I$24 -> 98027037 | J30: =J29/(1+Inputs!$C$5)^'LCOF Baseline'!J$24 -> 91614053 | ... AF30: =AF29/(1+Inputs!$C$5)^'LCOF Baseline'!AF$24 -> 20678498
A32: Levelised Cost of Fuel (€/l) | B32: =(SUM(B26:AF26) - SUM(B28:AF28)) / SUM(B30:AF30) -> 11.7556
A34: F-P-N
A35: Year | B35: 0 | C35: 1 | D35: 2 | E35: 3 | F35: 4 | G35: 5 | H35: 6 | I35: 7 | J35: 8 | K35: 9 | L35: 10 | M35: 11 | N35: 12 | O35: 13 | P35: 14 | Q35: 15 | R35: 16 | S35: 17 | T35: 18 | U35: 19 | V35: 20 | W35: 21 | X35: 22 | Y35: 23 | Z35: 24 | AA35: 25 | AB35: 26 | AC35: 27 | AD35: 28 | AE35: 29 | AF35: 30
A36: Cost (€) | B36: ='Cost Components'!T23 * 10^6 -> 850000000 | C36: ='Cost Components'!$T$26 * 10^6 -> 9.3684e+08 | D36: ='Cost Components'!$T$26 * 10^6 -> 9.3684e+08 | E36: ='Cost Components'!$T$26 * 10^6 -> 9.3684e+08 | F36: ='Cost Components'!$T$26 * 10^6 -> 9.3684e+08 | G36: ='Cost Components'!$T$26 * 10^6 -> 9.3684e+08 | H36: ='Cost Components'!$T$26 * 10^6 -> 9.3684e+08 | I36: ='Cost Components'!$T$26 * 10^6 -> 9.3684e+08 | J36: ='Cost Components'!$T$26 * 10^6 -> 9.3684e+08 | ... M36: ='Cost Components'!$T$26 * 10^6 -> 9.3684e+08 | N36: ='Cost Components'!$T$26 * 10^6 + 'Cost Components'!$T$7 * 10^6 -> 1.00584e+09 | O36: ='Cost Components'!$T$26 * 10^6 -> 9.3684e+08 | P36: ='Cost Components'!$T$26 * 10^6 -> 9.3684e+08 | Q36: ='Cost Components'!$T$26 * 10^6 -> 9.3684e+08 | R36: ='Cost Components'!$T$26 * 10^6 -> 9.3684e+08 | S36: ='Cost Components'!$T$26 * 10^6 -> 9.3684e+08 | T36: ='Cost Components'!$T$26 * 10^6 -> 9.3684e+08 | U36: ='Cost Components'!$T$26 * 10^6 -> 9.3684e+08 | V36: ='Cost Components'!$T$26 * 10^6 -> 9.3684e+08 | ... Y36: ='Cost Components'!$T$26 * 10^6 -> 9.3684e+08 | Z36: ='Cost Components'!$T$26 * 10^6 + 'Cost Components'!$T$7 * 10^6 -> 1.00584e+09 | AA36: ='Cost Components'!$T$26 * 10^6 -> 9.3684e+08 | AB36: ='Cost Components'!$T$26 * 10^6 -> 9.3684e+08 | AC36: ='Cost Components'!$T$26 * 10^6 -> 9.3684e+08 | AD36: ='Cost Components'!$T$26 * 10^6 -> 9.3684e+08 | AE36: ='Cost Components'!$T$26 * 10^6 -> 9.3684e+08 | AF36: ='Cost Components'!$T$26 * 10^6 -> 9.3684e+08
A37: Discounted Cost (€) | B37: =B36/(1+Inputs!$C$5)^'LCOF Baseline'!B$35 -> 850000000 | C37: =C36/(1+Inputs!$C$5)^'LCOF Baseline'!C$35 -> 8.755514e+08 | D37: =D36/(1+Inputs!$C$5)^'LCOF Baseline'!D$35 -> 8.1827234e+08 | E37: =E36/(1+Inputs!$C$5)^'LCOF Baseline'!E$35 -> 7.647405e+08 | F37: =F36/(1+Inputs!$C$5)^'LCOF Baseline'!F$35 -> 7.1471075e+08 | G37: =G36/(1+Inputs!$C$5)^'LCOF Baseline'!G$35 -> 6.6795397e+08 | H37: =H36/(1+Inputs!$C$5)^'LCOF Baseline'!H$35 -> 6.2425605e+08 | I37: =I36/(1+Inputs!$C$5)^'LCOF Baseline'!I$35 -> 5.8341687e+08 | ... AF37: =AF36/(1+Inputs!$C$5)^'LCOF Baseline'!AF$35 -> 1.2306997e+08
A38: Revenue (€) | B38: 0 | C38: ='Study Parameters'!$C$42 * 10^6 -> 122000000 | D38: ='Study Parameters'!$C$42 * 10^6 -> 122000000 | E38: ='Study Parameters'!$C$42 * 10^6 -> 122000000 | F38: ='Study Parameters'!$C$42 * 10^6 -> 122000000 | G38: ='Study Parameters'!$C$42 * 10^6 -> 122000000 | H38: ='Study Parameters'!$C$42 * 10^6 -> 122000000 | I38: ='Study Parameters'!$C$42 * 10^6 -> 122000000 | J38: ='Study Parameters'!$C$42 * 10^6 -> 122000000 | ... AF38: ='Study Parameters'!$C$42 * 10^6 -> 122000000
A39: Discounted Revenue (€) | B39: 0 | C39: =C38/(1+Inputs!$C$5)^'LCOF Baseline'!C$35 -> 1.1401869e+08 | D39: =D38/(1+Inputs!$C$5)^'LCOF Baseline'!D$35 -> 1.0655952e+08 | E39: =E38/(1+Inputs!$C$5)^'LCOF Baseline'!E$35 -> 99588341 | F39: =F38/(1+Inputs!$C$5)^'LCOF Baseline'!F$35 -> 93073216 | G39: =G38/(1+Inputs!$C$5)^'LCOF Baseline'!G$35 -> 86984314 | H39: =H38/(1+Inputs!$C$5)^'LCOF Baseline'!H$35 -> 81293751 | I39: =I38/(1+Inputs!$C$5)^'LCOF Baseline'!I$35 -> 75975469 | J39: =J38/(1+Inputs!$C$5)^'LCOF Baseline'!J$35 -> 71005111 | ... AF39: =AF38/(1+Inputs!$C$5)^'LCOF Baseline'!AF$35 -> 16026788
A40: Production (l) | B40: 0 | C40: ='Study Parameters'!$C$9 -> 157410000 | D40: ='Study Parameters'!$C$9 -> 157410000 | E40: ='Study Parameters'!$C$9 -> 157410000 | F40: ='Study Parameters'!$C$9 -> 157410000 | G40: ='Study Parameters'!$C$9 -> 157410000 | H40: ='Study Parameters'!$C$9 -> 157410000 | I40: ='Study Parameters'!$C$9 -> 157410000 | J40: ='Study Parameters'!$C$9 -> 157410000 | ... AF40: ='Study Parameters'!$C$9 -> 157410000
A41: Discounted Production (l) | B41: 0 | C41: =C40/(1+Inputs!$C$5)^'LCOF Baseline'!C$35 -> 1.4711215e+08 | D41: =D40/(1+Inputs!$C$5)^'LCOF Baseline'!D$35 -> 1.3748799e+08 | E41: =E40/(1+Inputs!$C$5)^'LCOF Baseline'!E$35 -> 1.2849345e+08 | F41: =F40/(1+Inputs!$C$5)^'LCOF Baseline'!F$35 -> 1.2008734e+08 | G41: =G40/(1+Inputs!$C$5)^'LCOF Baseline'!G$35 -> 1.1223115e+08 | H41: =H40/(1+Inputs!$C$5)^'LCOF Baseline'!H$35 -> 1.0488893e+08 | I41: =I40/(1+Inputs!$C$5)^'LCOF Baseline'!I$35 -> 98027037 | J41: =J40/(1+Inputs!$C$5)^'LCOF Baseline'!J$35 -> 91614053 | ... AF41: =AF40/(1+Inputs!$C$5)^'LCOF Baseline'!AF$35 -> 20678498
A43: Levelised Cost of Fuel (€/l) | B43: =(SUM(B37:AF37) - SUM(B39:AF39)) / SUM(B41:AF41) -> 5.6343535
A45: F-P-N/R
A46: Year | B46: 0 | C46: 1 | D46: 2 | E46: 3 | F46: 4 | G46: 5 | H46: 6 | I46: 7 | J46: 8 | K46: 9 | L46: 10 | M46: 11 | N46: 12 | O46: 13 | P46: 14 | Q46: 15 | R46: 16 | S46: 17 | T46: 18 | U46: 19 | V46: 20 | W46: 21 | X46: 22 | Y46: 23 | Z46: 24 | AA46: 25 | AB46: 26 | AC46: 27 | AD46: 28 | AE46: 29 | AF46: 30
A47: Cost (€) | B47: ='Cost Components'!Z23 * 10^6 -> 850000000 | C47: ='Cost Components'!$Z$26 * 10^6 -> 9.1124674e+08 | D47: ='Cost Components'!$Z$26 * 10^6 -> 9.1124674e+08 | E47: ='Cost Components'!$Z$26 * 10^6 -> 9.1124674e+08 | F47: ='Cost Components'!$Z$26 * 10^6 -> 9.1124674e+08 | G47: ='Cost Components'!$Z$26 * 10^6 -> 9.1124674e+08 | H47: ='Cost Components'!$Z$26 * 10^6 -> 9.1124674e+08 | I47: ='Cost Components'!$Z$26 * 10^6 -> 9.1124674e+08 | J47: ='Cost Components'!$Z$26 * 10^6 -> 9.1124674e+08 | ... M47: ='Cost Components'!$Z$26 * 10^6 -> 9.1124674e+08 | N47: ='Cost Components'!$Z$26* 10^6 + 'Cost Components'!$Z$7 * 10^6 -> 9.8024674e+08 | O47: ='Cost Components'!$Z$26 * 10^6 -> 9.1124674e+08 | P47: ='Cost Components'!$Z$26 * 10^6 -> 9.1124674e+08 | Q47: ='Cost Components'!$Z$26 * 10^6 -> 9.1124674e+08 | R47: ='Cost Components'!$Z$26 * 10^6 -> 9.1124674e+08 | S47: ='Cost Components'!$Z$26 * 10^6 -> 9.1124674e+08 | T47: ='Cost Components'!$Z$26 * 10^6 -> 9.1124674e+08 | U47: ='Cost Components'!$Z$26 * 10^6 -> 9.1124674e+08 | V47: ='Cost Components'!$Z$26 * 10^6 -> 9.1124674e+08 | ... Y47: ='Cost Components'!$Z$26 * 10^6 -> 9.1124674e+08 | Z47: ='Cost Components'!$Z$26 * 10^6 + 'Cost Components'!$Z$7 * 10^6 -> 9.8024674e+08 | AA47: ='Cost Components'!$Z$26 * 10^6 -> 9.1124674e+08 | AB47: ='Cost Components'!$Z$26 * 10^6 -> 9.1124674e+08 | AC47: ='Cost Components'!$Z$26 * 10^6 -> 9.1124674e+08 | AD47: ='Cost Components'!$Z$26 * 10^6 -> 9.1124674e+08 | AE47: ='Cost Components'!$Z$26 * 10^6 -> 9.1124674e+08 | AF47: ='Cost Components'!$Z$26 * 10^6 -> 9.1124674e+08
A48: Discounted Cost (€) | B48: =B47/(1+Inputs!$C$5)^'LCOF Baseline'!B$46 -> 850000000 | C48: =C47/(1+Inputs!$C$5)^'LCOF Baseline'!C$46 -> 8.5163246e+08 | D48: =D47/(1+Inputs!$C$5)^'LCOF Baseline'!D$46 -> 7.9591819e+08 | E48: =E47/(1+Inputs!$C$5)^'LCOF Baseline'!E$46 -> 7.4384878e+08 | F48: =F47/(1+Inputs!$C$5)^'LCOF Baseline'!F$46 -> 6.9518577e+08 | G48: =G47/(1+Inputs!$C$5)^'LCOF Baseline'!G$46 -> 6.4970633e+08 | H48: =H47/(1+Inputs!$C$5)^'LCOF Baseline'!H$46 -> 6.0720218e+08 | I48: =I47/(1+Inputs!$C$5)^'LCOF Baseline'!I$46 -> 5.6747867e+08 | ... AF48: =AF47/(1+Inputs!$C$5)^'LCOF Baseline'!AF$46 -> 1.1970786e+08
A49: Revenue (€) | B49: 0 | C49: ='Study Parameters'!$C$42 * 10^6 -> 122000000 | D49: ='Study Parameters'!$C$42 * 10^6 -> 122000000 | E49: ='Study Parameters'!$C$42 * 10^6 -> 122000000 | F49: ='Study Parameters'!$C$42 * 10^6 -> 122000000 | G49: ='Study Parameters'!$C$42 * 10^6 -> 122000000 | H49: ='Study Parameters'!$C$42 * 10^6 -> 122000000 | I49: ='Study Parameters'!$C$42 * 10^6 -> 122000000 | J49: ='Study Parameters'!$C$42 * 10^6 -> 122000000 | ... AF49: ='Study Parameters'!$C$42 * 10^6 -> 122000000
A50: Discounted Revenue (€) | B50: 0 | C50: =C49/(1+Inputs!$C$5)^'LCOF Baseline'!C$46 -> 1.1401869e+08 | D50: =D49/(1+Inputs!$C$5)^'LCOF Baseline'!D$46 -> 1.0655952e+08 | E50: =E49/(1+Inputs!$C$5)^'LCOF Baseline'!E$46 -> 99588341 | F50: =F49/(1+Inputs!$C$5)^'LCOF Baseline'!F$46 -> 93073216 | G50: =G49/(1+Inputs!$C$5)^'LCOF Baseline'!G$46 -> 86984314 | H50: =H49/(1+Inputs!$C$5)^'LCOF Baseline'!H$46 -> 81293751 | I50: =I49/(1+Inputs!$C$5)^'LCOF Baseline'!I$46 -> 75975469 | J50: =J49/(1+Inputs!$C$5)^'LCOF Baseline'!J$46 -> 71005111 | ... AF50: =AF49/(1+Inputs!$C$5)^'LCOF Baseline'!AF$46 -> 16026788
A51: Production (l) | B51: 0 | C51: ='Study Parameters'!$C$9 -> 157410000 | D51: ='Study Parameters'!$C$9 -> 157410000 | E51: ='Study Parameters'!$C$9 -> 157410000 | F51: ='Study Parameters'!$C$9 -> 157410000 | G51: ='Study Parameters'!$C$9 -> 157410000 | H51: ='Study Parameters'!$C$9 -> 157410000 | I51: ='Study Parameters'!$C$9 -> 157410000 | J51: ='Study Parameters'!$C$9 -> 157410000 | ... AF51: ='Study Parameters'!$C$9 -> 157410000
A52: Discounted Production (l) | B52: 0 | C52: =C51/(1+Inputs!$C$5)^'LCOF Baseline'!C$46 -> 1.4711215e+08 | D52: =D51/(1+Inputs!$C$5)^'LCOF Baseline'!D$46 -> 1.3748799e+08 | E52: =E51/(1+Inputs!$C$5)^'LCOF Baseline'!E$46 -> 1.2849345e+08 | F52: =F51/(1+Inputs!$C$5)^'LCOF Baseline'!F$46 -> 1.2008734e+08 | G52: =G51/(1+Inputs!$C$5)^'LCOF Baseline'!G$46 -> 1.1223115e+08 | H52: =H51/(1+Inputs!$C$5)^'LCOF Baseline'!H$46 -> 1.0488893e+08 | I52: =I51/(1+Inputs!$C$5)^'LCOF Baseline'!I$46 -> 98027037 | J52: =J51/(1+Inputs!$C$5)^'LCOF Baseline'!J$46 -> 91614053 | ... AF52: =AF51/(1+Inputs!$C$5)^'LCOF Baseline'!AF$46 -> 20678498
A54: Levelised Cost of Fuel (€/l) | B54: =(SUM(B48:AF48) - SUM(B50:AF50)) / SUM(B52:AF52) -> 5.4717637
A56: F-S-N/R
A57: Year | B57: 0 | C57: 1 | D57: 2 | E57: 3 | F57: 4 | G57: 5 | H57: 6 | I57: 7 | J57: 8 | K57: 9 | L57: 10 | M57: 11 | N57: 12 | O57: 13 | P57: 14 | Q57: 15 | R57: 16 | S57: 17 | T57: 18 | U57: 19 | V57: 20 | W57: 21 | X57: 22 | Y57: 23 | Z57: 24 | AA57: 25 | AB57: 26 | AC57: 27 | AD57: 28 | AE57: 29 | AF57: 30
A58: Cost (€) | B58: ='Cost Components'!$AF$23*10^6 -> 795000000 | C58: ='Cost Components'!$AF$26*10^6 -> 8.6240463e+08 | D58: ='Cost Components'!$AF$26*10^6 -> 8.6240463e+08 | E58: ='Cost Components'!$AF$26*10^6 -> 8.6240463e+08 | F58: ='Cost Components'!$AF$26*10^6 -> 8.6240463e+08 | G58: ='Cost Components'!$AF$26*10^6 -> 8.6240463e+08 | H58: ='Cost Components'!$AF$26*10^6 -> 8.6240463e+08 | I58: ='Cost Components'!$AF$26*10^6 -> 8.6240463e+08 | J58: ='Cost Components'!$AF$26*10^6 -> 8.6240463e+08 | K58: ='Cost Components'!$AF$26*10^6 -> 8.6240463e+08 | L58: ='Cost Components'!$AF$26*10^6 + 'Cost Components'!$AF$7 * 10^6 -> 9.3240463e+08 | M58: ='Cost Components'!$AF$26*10^6 -> 8.6240463e+08 | N58: ='Cost Components'!$AF$26*10^6 -> 8.6240463e+08 | O58: ='Cost Components'!$AF$26*10^6 -> 8.6240463e+08 | P58: ='Cost Components'!$AF$26*10^6 -> 8.6240463e+08 | Q58: ='Cost Components'!$AF$26*10^6 -> 8.6240463e+08 | R58: ='Cost Components'!$AF$26*10^6 -> 8.6240463e+08 | S58: ='Cost Components'!$AF$26*10^6 -> 8.6240463e+08 | T58: ='Cost Components'!$AF$26*10^6 -> 8.6240463e+08 | U58: ='Cost Components'!$AF$26*10^6 -> 8.6240463e+08 | V58: ='Cost Components'!$AF$26*10^6 + 'Cost Components'!$AF$7 * 10^6 -> 9.3240463e+08 | W58: ='Cost Components'!$AF$26*10^6 -> 8.6240463e+08 | X58: ='Cost Components'!$AF$26*10^6 -> 8.6240463e+08 | Y58: ='Cost Components'!$AF$26*10^6 -> 8.6240463e+08 | Z58: ='Cost Components'!$AF$26*10^6 -> 8.6240463e+08 | AA58: ='Cost Components'!$AF$26*10^6 -> 8.6240463e+08 | AB58: ='Cost Components'!$AF$26*10^6 -> 8.6240463e+08 | AC58: ='Cost Components'!$AF$26*10^6 -> 8.6240463e+08 | AD58: ='Cost Components'!$AF$26*10^6 -> 8.6240463e+08 | ... AF58: ='Cost Components'!$AF$26*10^6 -> 8.6240463e+08
A59: Discounted Cost (€) | B59: =B58/(1+Inputs!$C$5)^'LCOF Baseline'!B$57 -> 795000000 | C59: =C58/(1+Inputs!$C$5)^'LCOF Baseline'!C$57 -> 8.0598564e+08 | D59: =D58/(1+Inputs!$C$5)^'LCOF Baseline'!D$57 -> 7.532576e+08 | E59: =E58/(1+Inputs!$C$5)^'LCOF Baseline'!E$57 -> 7.0397907e+08 | F59: =F58/(1+Inputs!$C$5)^'LCOF Baseline'!F$57 -> 6.5792436e+08 | G59: =G58/(1+Inputs!$C$5)^'LCOF Baseline'!G$57 -> 6.1488258e+08 | H59: =H58/(1+Inputs!$C$5)^'LCOF Baseline'!H$57 -> 5.7465662e+08 | I59: =I58/(1+Inputs!$C$5)^'LCOF Baseline'!I$57 -> 5.3706226e+08 | ... AF59: =AF58/(1+Inputs!$C$5)^'LCOF Baseline'!AF$57 -> 1.1329161e+08
A60: Revenue (€) | B60: 0 | C60: ='Study Parameters'!$C$42 * 10^6 -> 122000000 | D60: ='Study Parameters'!$C$42 * 10^6 -> 122000000 | E60: ='Study Parameters'!$C$42 * 10^6 -> 122000000 | F60: ='Study Parameters'!$C$42 * 10^6 -> 122000000 | G60: ='Study Parameters'!$C$42 * 10^6 -> 122000000 | H60: ='Study Parameters'!$C$42 * 10^6 -> 122000000 | I60: ='Study Parameters'!$C$42 * 10^6 -> 122000000 | J60: ='Study Parameters'!$C$42 * 10^6 -> 122000000 | ... AF60: ='Study Parameters'!$C$42 * 10^6 -> 122000000
A61: Discounted Revenue (€) | B61: 0 | C61: =C60/(1+Inputs!$C$5)^'LCOF Baseline'!C$57 -> 1.1401869e+08 | D61: =D60/(1+Inputs!$C$5)^'LCOF Baseline'!D$57 -> 1.0655952e+08 | E61: =E60/(1+Inputs!$C$5)^'LCOF Baseline'!E$57 -> 99588341 | F61: =F60/(1+Inputs!$C$5)^'LCOF Baseline'!F$57 -> 93073216 | G61: =G60/(1+Inputs!$C$5)^'LCOF Baseline'!G$57 -> 86984314 | H61: =H60/(1+Inputs!$C$5)^'LCOF Baseline'!H$57 -> 81293751 | I61: =I60/(1+Inputs!$C$5)^'LCOF Baseline'!I$57 -> 75975469 | J61: =J60/(1+Inputs!$C$5)^'LCOF Baseline'!J$57 -> 71005111 | ... AF61: =AF60/(1+Inputs!$C$5)^'LCOF Baseline'!AF$57 -> 16026788
A62: Production (l) | B62: 0 | C62: ='Study Parameters'!$C$9 -> 157410000 | D62: ='Study Parameters'!$C$9 -> 157410000 | E62: ='Study Parameters'!$C$9 -> 157410000 | F62: ='Study Parameters'!$C$9 -> 157410000 | G62: ='Study Parameters'!$C$9 -> 157410000 | H62: ='Study Parameters'!$C$9 -> 157410000 | I62: ='Study Parameters'!$C$9 -> 157410000 | J62: ='Study Parameters'!$C$9 -> 157410000 | ... AF62: ='Study Parameters'!$C$9 -> 157410000
A63: Discounted Production (l) | B63: 0 | C63: =C62/(1+Inputs!$C$5)^'LCOF Baseline'!C$57 -> 1.4711215e+08 | D63: =D62/(1+Inputs!$C$5)^'LCOF Baseline'!D$57 -> 1.3748799e+08 | E63: =E62/(1+Inputs!$C$5)^'LCOF Baseline'!E$57 -> 1.2849345e+08 | F63: =F62/(1+Inputs!$C$5)^'LCOF Baseline'!F$57 -> 1.2008734e+08 | G63: =G62/(1+Inputs!$C$5)^'LCOF Baseline'!G$57 -> 1.1223115e+08 | H63: =H62/(1+Inputs!$C$5)^'LCOF Baseline'!H$57 -> 1.0488893e+08 | I63: =I62/(1+Inputs!$C$5)^'LCOF Baseline'!I$57 -> 98027037 | J63: =J62/(1+Inputs!$C$5)^'LCOF Baseline'!J$57 -> 91614053 | ... AF63: =AF62/(1+Inputs!$C$5)^'LCOF Baseline'!AF$57 -> 20678498
A65: Levelised Cost of Fuel (€/l) | B65: =(SUM(B59:AF59) - SUM(B61:AF61)) / SUM(B63:AF63) -> 5.13815

Sheet Cost Breakdowns
A1: Year | B1: 0 | C1: 1 | D1: 2 | E1: 3 | F1: 4 | G1: 5 | H1: 6 | I1: 7 | J1: 8 | K1: 9 | L1: 10 | M1: 11 | N1: 12 | O1: 13 | P1: 14 | Q1: 15 | R1: 16 | S1: 17 | T1: 18 | U1: 19 | V1: 20 | W1: 21 | X1: 22 | Y1: 23 | Z1: 24 | AA1: 25 | AB1: 26 | AC1: 27 | AD1: 28 | AE1: 29 | AF1: 30
A2: 2024 C-P-N/R
A3: CO2 | B3: 0 | C3: =('Cost Components'!$B$24 * 10^6) / (1+Inputs!$C$5) ^ 'Cost Breakdowns'!C1 -> 1.2813084e+09 | D3: =('Cost Components'!$B$24 * 10^6) / (1+Inputs!$C$5) ^ 'Cost Breakdowns'!D1 -> 1.1974845e+09 | E3: =('Cost Components'!$B$24 * 10^6) / (1+Inputs!$C$5) ^ 'Cost Breakdowns'!E1 -> 1.1191444e+09 | F3: =('Cost Components'!$B$24 * 10^6) / (1+Inputs!$C$5) ^ 'Cost Breakdowns'!F1 -> 1.0459293e+09 | G3: =('Cost Components'!$B$24 * 10^6) / (1+Inputs!$C$5) ^ 'Cost Breakdowns'!G1 -> 9.7750405e+08 | H3: =('Cost Components'!$B$24 * 10^6) / (1+Inputs!$C$5) ^ 'Cost Breakdowns'!H1 -> 9.1355519e+08 | I3: =('Cost Components'!$B$24 * 10^6) / (1+Inputs!$C$5) ^ 'Cost Breakdowns'!I1 -> 8.537899e+08 | J3: =('Cost Components'!$B$24 * 10^6) / (1+Inputs!$C$5) ^ 'Cost Breakdowns'!J1 -> 7.9793448e+08 | ... AF3: =('Cost Components'!$B$24 * 10^6) / (1+Inputs!$C$5) ^ 'Cost Breakdowns'!AF1 -> 1.8010432e+08
A4: Electricity | B4: 0 | C4: =('Cost Components'!$H$25* 10^6) / (1+ Inputs!$C$5) ^'Cost Breakdowns'!C1 -> 3.8226407e+08 | D4: =('Cost Components'!$H$25* 10^6) / (1+ Inputs!$C$5) ^'Cost Breakdowns'!D1 -> 3.5725614e+08 | E4: =('Cost Components'!$H$25* 10^6) / (1+ Inputs!$C$5) ^'Cost Breakdowns'!E1 -> 3.3388424e+08 | F4: =('Cost Components'!$H$25* 10^6) / (1+ Inputs!$C$5) ^'Cost Breakdowns'!F1 -> 3.1204135e+08 | G4: =('Cost Components'!$H$25* 10^6) / (1+ Inputs!$C$5) ^'Cost Breakdowns'!G1 -> 2.9162743e+08 | H4: =('Cost Components'!$H$25* 10^6) / (1+ Inputs!$C$5) ^'Cost Breakdowns'!H1 -> 2.72549e+08 | I4: =('Cost Components'!$H$25* 10^6) / (1+ Inputs!$C$5) ^'Cost Breakdowns'!I1 -> 2.5471869e+08 | J4: =('Cost Components'!$H$25* 10^6) / (1+ Inputs!$C$5) ^'Cost Breakdowns'!J1 -> 2.3805485e+08 | ... AF4: =('Cost Components'!$H$25* 10^6) / (1+ Inputs!$C$5) ^'Cost Breakdowns'!AF1 -> 53732114
A5: CAPEX | B5: ='Cost Components'!B23 * 10^6 -> 1100000000 | C5: 0 | D5: 0 | E5: 0 | F5: 0 | G5: 0 | H5: 0 | I5: 0 | J5: 0 | K5: 0 | L5: 0 | M5: 0 | N5: 0 | O5: 0 | P5: 0 | Q5: 0 | R5: 0 | S5: 0 | T5: 0 | U5: 0 | V5: 0 | W5: 0 | X5: 0 | Y5: 0 | Z5: 0 | AA5: 0 | AB5: 0 | AC5: 0 | AD5: 0 | AE5: 0 | AF5: 0
A6: Other OPEX | B6: 0 | C6: =(('Cost Components'!$H$16-'Cost Components'!$H$12) * 10^6) / (1+Inputs!$C$5) ^'Cost Breakdowns'!C1 -> 1.6869159e+08 | D6: =(('Cost Components'!$H$16-'Cost Components'!$H$12) * 10^6) / (1+Inputs!$C$5) ^'Cost Breakdowns'!D1 -> 1.5765569e+08 | E6: =(('Cost Components'!$H$16-'Cost Components'!$H$12) * 10^6) / (1+Inputs!$C$5) ^'Cost Breakdowns'!E1 -> 1.4734177e+08 | F6: =(('Cost Components'!$H$16-'Cost Components'!$H$12) * 10^6) / (1+Inputs!$C$5) ^'Cost Breakdowns'!F1 -> 1.3770259e+08 | G6: =(('Cost Components'!$H$16-'Cost Components'!$H$12) * 10^6) / (1+Inputs!$C$5) ^'Cost Breakdowns'!G1 -> 1.2869401e+08 | H6: =(('Cost Components'!$H$16-'Cost Components'!$H$12) * 10^6) / (1+Inputs!$C$5) ^'Cost Breakdowns'!H1 -> 1.2027477e+08 | I6: =(('Cost Components'!$H$16-'Cost Components'!$H$12) * 10^6) / (1+Inputs!$C$5) ^'Cost Breakdowns'!I1 -> 1.1240633e+08 | J6: =(('Cost Components'!$H$16-'Cost Components'!$H$12) * 10^6) / (1+Inputs!$C$5) ^'Cost Breakdowns'!J1 -> 1.0505264e+08 | ... AF6: =(('Cost Components'!$H$16-'Cost Components'!$H$12) * 10^6) / (1+Inputs!$C$5) ^'Cost Breakdowns'!AF1 -> 23711765
A8: Contributions
A9: CO2 | B9: =SUM(B3:AF3) / SUM($B$3:$AF$6) -> 0.66905216
A10: Electricity | B10: =SUM(B4:AF4) / SUM($B$3:$AF$6) -> 0.19960425
A11: CAPEX | B11: =SUM(B5:AF5) / SUM($B$3:$AF$6) -> 0.04325905
A12: Other OPEX | B12: =SUM(B6:AF6) / SUM($B$3:$AF$6) -> 0.088084547
A14: 2050 F-P-N/R
A15: CO2 | B15: 0 | C15: =('Cost Components'!$Z$24 * 10^6) / (1+Inputs!$C$5) ^ 'Cost Breakdowns'!C1 -> 4.8878505e+08 | D15: =('Cost Components'!$Z$24 * 10^6) / (1+Inputs!$C$5) ^ 'Cost Breakdowns'!D1 -> 4.5680845e+08 | E15: =('Cost Components'!$Z$24 * 10^6) / (1+Inputs!$C$5) ^ 'Cost Breakdowns'!E1 -> 4.2692379e+08 | F15: =('Cost Components'!$Z$24 * 10^6) / (1+Inputs!$C$5) ^ 'Cost Breakdowns'!F1 -> 3.989942e+08 | G15: =('Cost Components'!$Z$24 * 10^6) / (1+Inputs!$C$5) ^ 'Cost Breakdowns'!G1 -> 3.7289177e+08 | H15: =('Cost Components'!$Z$24 * 10^6) / (1+Inputs!$C$5) ^ 'Cost Breakdowns'!H1 -> 3.4849698e+08 | I15: =('Cost Components'!$Z$24 * 10^6) / (1+Inputs!$C$5) ^ 'Cost Breakdowns'!I1 -> 3.2569812e+08 | J15: =('Cost Components'!$Z$24 * 10^6) / (1+Inputs!$C$5) ^ 'Cost Breakdowns'!J1 -> 3.0439076e+08 | ... AF15: =('Cost Components'!$Z$24 * 10^6) / (1+Inputs!$C$5) ^ 'Cost Breakdowns'!AF1 -> 68705002
A16: Electricity | B16: 0 | C16: =('Cost Components'!$Z$25 * 10^6) / (1+ Inputs!$C$5) ^'Cost Breakdowns'!C1 -> 2.7873527e+08 | D16: =('Cost Components'!$Z$25 * 10^6) / (1+ Inputs!$C$5) ^'Cost Breakdowns'!D1 -> 2.6050025e+08 | E16: =('Cost Components'!$Z$25 * 10^6) / (1+ Inputs!$C$5) ^'Cost Breakdowns'!E1 -> 2.4345818e+08 | F16: =('Cost Components'!$Z$25 * 10^6) / (1+ Inputs!$C$5) ^'Cost Breakdowns'!F1 -> 2.2753101e+08 | G16: =('Cost Components'!$Z$25 * 10^6) / (1+ Inputs!$C$5) ^'Cost Breakdowns'!G1 -> 2.126458e+08 | H16: =('Cost Components'!$Z$25 * 10^6) / (1+ Inputs!$C$5) ^'Cost Breakdowns'!H1 -> 1.9873439e+08 | I16: =('Cost Components'!$Z$25 * 10^6) / (1+ Inputs!$C$5) ^'Cost Breakdowns'!I1 -> 1.8573308e+08 | J16: =('Cost Components'!$Z$25 * 10^6) / (1+ Inputs!$C$5) ^'Cost Breakdowns'!J1 -> 1.7358232e+08 | ... AF16: =('Cost Components'!$Z$25 * 10^6) / (1+ Inputs!$C$5) ^'Cost Breakdowns'!AF1 -> 39179814
A17: CAPEX | B17: ='Cost Components'!Z23 * 10^6 -> 850000000 | C17: 0 | D17: 0 | E17: 0 | F17: 0 | G17: 0 | H17: 0 | I17: 0 | J17: 0 | K17: 0 | L17: 0 | M17: 0 | N17: 0 | O17: 0 | P17: 0 | Q17: 0 | R17: 0 | S17: 0 | T17: 0 | U17: 0 | V17: 0 | W17: 0 | X17: 0 | Y17: 0 | Z17: 0 | AA17: 0 | AB17: 0 | AC17: 0 | AD17: 0 | AE17: 0 | AF17: 0
A18: Other OPEX | B18: 0 | C18: =(('Cost Components'!$Z$16-'Cost Components'!$Z$12) * 10^6) / (1+Inputs!$C$5) ^'Cost Breakdowns'!C1 -> 1.317757e+08 | D18: =(('Cost Components'!$Z$16-'Cost Components'!$Z$12) * 10^6) / (1+Inputs!$C$5) ^'Cost Breakdowns'!D1 -> 1.2315486e+08 | E18: =(('Cost Components'!$Z$16-'Cost Components'!$Z$12) * 10^6) / (1+Inputs!$C$5) ^'Cost Breakdowns'!E1 -> 1.15098e+08 | F18: =(('Cost Components'!$Z$16-'Cost Components'!$Z$12) * 10^6) / (1+Inputs!$C$5) ^'Cost Breakdowns'!F1 -> 1.0756822e+08 | G18: =(('Cost Components'!$Z$16-'Cost Components'!$Z$12) * 10^6) / (1+Inputs!$C$5) ^'Cost Breakdowns'!G1 -> 1.0053105e+08 | H18: =(('Cost Components'!$Z$16-'Cost Components'!$Z$12) * 10^6) / (1+Inputs!$C$5) ^'Cost Breakdowns'!H1 -> 93954254 | I18: =(('Cost Components'!$Z$16-'Cost Components'!$Z$12) * 10^6) / (1+Inputs!$C$5) ^'Cost Breakdowns'!I1 -> 87807714 | J18: =(('Cost Components'!$Z$16-'Cost Components'!$Z$12) * 10^6) / (1+Inputs!$C$5) ^'Cost Breakdowns'!J1 -> 82063284 | ... AF18: =(('Cost Components'!$Z$16-'Cost Components'!$Z$12) * 10^6) / (1+Inputs!$C$5) ^'Cost Breakdowns'!AF1 -> 18522764
A20: Contributions
A21: CO2 | B21: =SUM(B15:AF15) / SUM($B$15:$AF$18) -> 0.5073999
A22: Electricity | B22: =SUM(B16:AF16) / SUM($B$15:$AF$18) -> 0.2893506
A23: CAPEX | B23: =SUM(B17:AF17) / SUM($B$15:$AF$18) -> 0.066455264
A24: Other OPEX | B24: =SUM(B18:AF18) / SUM($B$15:$AF$18) -> 0.13679424

Sheet Outputs
A1: 2024 - C-P-N | H1: 2024 - C-P-N/R | O1: 2024 - C-S-N/R
A2: Parameter | B2: Unit | C2: Base Case | D2: LCOE Corrected | E2: CO2 Cost Corrected | F2: WACC Corrected | H2: Parameter | I2: Unit | J2: Base Case | K2: LCOE Corrected | L2: CO2 Cost Corrected | M2: WACC Corrected | O2: Parameter | P2: Unit | Q2: Base Case | R2: LCOE Corrected | S2: CO2 Cost Corrected | T2: WACC Corrected
A3: Syn-Fuel cost | B3: €/l | C3: ='LCOF Baseline'!B10 -> 9.1316404 | D3: ='LCOF LCOE Corrected'!B10 -> 7.3568211 | E3: ='LCOF CO2 Cost Corrected'!B10 -> 11.705908 | F3: ='LCOF WACC Corrected '!B10 -> 11.650105 | H3: Syn-Fuel cost | I3: €/l | J3: ='LCOF Baseline'!B21 -> 7.9246015 | K3: ='LCOF LCOE Corrected'!B21 -> 7.2831083 | L3: ='LCOF CO2 Cost Corrected'!B21 -> 11.994082 | M3: ='LCOF WACC Corrected '!B21 -> 11.93828 | O3: Syn-Fuel cost | P3: €/l | Q3: ='LCOF Baseline'!B32 -> 7.6253466 | R3: ='LCOF LCOE Corrected'!B32 -> 7.1473713 | S3: ='LCOF CO2 Cost Corrected'!B32 -> 11.820864 | T3: ='LCOF WACC Corrected '!B32 -> 11.7556
A4: Syn-Fuel cost | B4: $/l | C4: =C3/Inputs!$C$6 -> 10.146267 | D4: =D3/Inputs!$C$6 -> 8.1742457 | E4: =E3/Inputs!$C$6 -> 13.006564 | F4: =F3/Inputs!$C$6 -> 12.944562 | H4: Syn-Fuel cost | I4: $/l | J4: =J3/Inputs!$C$6 -> 8.8051127 | K4: =K3/Inputs!$C$6 -> 8.0923425 | L4: =L3/Inputs!$C$6 -> 13.326758 | M4: =M3/Inputs!$C$6 -> 13.264755 | O4: Syn-Fuel cost | P4: $/l | Q4: =Q3/Inputs!$C$6 -> 8.4726073 | R4: =R3/Inputs!$C$6 -> 7.9415236 | S4: =S3/Inputs!$C$6 -> 13.134293 | T4: =T3/Inputs!$C$6 -> 13.061777
A5: Fossil Fuel cost | B5: $/l | C5: =Inputs!$C$16 -> 0.8 | D5: =Inputs!$C$16 -> 0.8 | E5: =Inputs!$C$16 -> 0.8 | F5: =Inputs!$C$16 -> 0.8 | H5: Fossil Fuel cost | I5: $/l | J5: =Inputs!$C$16 -> 0.8 | K5: =Inputs!$C$16 -> 0.8 | L5: =Inputs!$C$16 -> 0.8 | M5: =Inputs!$C$16 -> 0.8 | O5: Fossil Fuel cost | P5: $/l | Q5: =Inputs!$C$16 -> 0.8 | R5: =Inputs!$C$16 -> 0.8 | S5: =Inputs!$C$16 -> 0.8 | T5: =Inputs!$C$16 -> 0.8
A6: Syn-Fuel emissions | B6: gCO2eq/MJ | C6: =0.07 *Inputs!$C$11 -> 6.209 | D6: =0.07 *Inputs!$C$11 -> 6.209 | E6: =0.07 *Inputs!$C$11 -> 6.209 | F6: =0.07 *Inputs!$C$11 -> 6.209 | H6: Syn-Fuel emissions | I6: gCO2eq/MJ | J6: =0.07 *Inputs!$C$11 -> 6.209 | K6: =0.07 *Inputs!$C$11 -> 6.209 | L6: =0.07 *Inputs!$C$11 -> 6.209 | M6: =0.07 *Inputs!$C$11 -> 6.209 | O6: Syn-Fuel emissions | P6: gCO2eq/MJ | Q6: =0.07 *Inputs!$C$11 -> 6.209 | R6: =0.07 *Inputs!$C$11 -> 6.209 | S6: =0.07 *Inputs!$C$11 -> 6.209 | T6: =0.07 *Inputs!$C$11 -> 6.209
A7: Fossil Fuel emissions | B7: gCO2eq/MJ | C7: =Inputs!$C$11 -> 88.7 | D7: =Inputs!$C$11 -> 88.7 | E7: =Inputs!$C$11 -> 88.7 | F7: =Inputs!$C$11 -> 88.7 | H7: Fossil Fuel emissions | I7: gCO2eq/MJ | J7: =Inputs!$C$11 -> 88.7 | K7: =Inputs!$C$11 -> 88.7 | L7: =Inputs!$C$11 -> 88.7 | M7: =Inputs!$C$11 -> 88.7 | O7: Fossil Fuel emissions | P7: gCO2eq/MJ | Q7: =Inputs!$C$11 -> 88.7 | R7: =Inputs!$C$11 -> 88.7 | S7: =Inputs!$C$11 -> 88.7 | T7: =Inputs!$C$11 -> 88.7
A8: CO2 Abated | B8: gCO2eq/MJ | C8: =C7-C6 -> 82.491 | D8: =D7-D6 -> 82.491 | E8: =E7-E6 -> 82.491 | F8: =F7-F6 -> 82.491 | H8: CO2 Abated | I8: gCO2eq/MJ | J8: =J7-J6 -> 82.491 | K8: =K7-K6 -> 82.491 | L8: =L7-L6 -> 82.491 | M8: =M7-M6 -> 82.491 | O8: CO2 Abated | P8: gCO2eq/MJ | Q8: =Q7-Q6 -> 82.491 | R8: =R7-R6 -> 82.491 | S8: =S7-S6 -> 82.491 | T8: =T7-T6 -> 82.491
A9: CO2 Abated | B9: gCO2eq/l | C9: =C8*Inputs!$C$14 -> 2861.5798 | D9: =D8*Inputs!$C$14 -> 2861.5798 | E9: =E8*Inputs!$C$14 -> 2861.5798 | F9: =F8*Inputs!$C$14 -> 2861.5798 | H9: CO2 Abated | I9: gCO2eq/l | J9: =J8*Inputs!$C$14 -> 2861.5798 | K9: =K8*Inputs!$C$14 -> 2861.5798 | L9: =L8*Inputs!$C$14 -> 2861.5798 | M9: =M8*Inputs!$C$14 -> 2861.5798 | O9: CO2 Abated | P9: gCO2eq/l | Q9: =Q8*Inputs!$C$14 -> 2861.5798 | R9: =R8*Inputs!$C$14 -> 2861.5798 | S9: =S8*Inputs!$C$14 -> 2861.5798 | T9: =T8*Inputs!$C$14 -> 2861.5798
A10: Abatement cost | B10: $/tCO2 | C10: =(C4-C5) / C9 * 10^6 -> 3266.1214 | D10: =(D4-D5) / D9 * 10^6 -> 2576.9841 | E10: =(E4-E5) / E9 * 10^6 -> 4265.6732 | F10: =(F4-F5) / F9 * 10^6 -> 4244.0059 | H10: Abatement cost | I10: $/tCO2 | J10: =(J4-J5) / J9 * 10^6 -> 2797.4452 | K10: =(K4-K5) / K9 * 10^6 -> 2548.3625 | L10: =(L4-L5) / L9 * 10^6 -> 4377.5673 | M10: =(M4-M5) / M9 * 10^6 -> 4355.9 | O10: Abatement cost | P10: $/tCO2 | Q10: =(Q4-Q5) / Q9 * 10^6 -> 2681.2488 | R10: =(R4-R5) / R9 * 10^6 -> 2495.6577 | S10: =(S4-S5) / S9 * 10^6 -> 4310.3089 | T10: =(T4-T5) / T9 * 10^6 -> 4284.9678
A13: 2050 - F-P-N | H13: 2050 - F-P-N/R | O13: 2050 - F-S-N/R
A14: Parameter | B14: Unit | C14: Base Case | D14: LCOE Corrected | E14: CO2 Cost Corrected | F14: WACC Corrected | H14: Parameter | I14: Unit | J14: Base Case | K14: LCOE Corrected | L14: CO2 Cost Corrected | M14: WACC Corrected | O14: Parameter | P14: Unit | Q14: Base Case | R14: LCOE Corrected | S14: CO2 Cost Corrected | T14: WACC Corrected
A15: Syn-Fuel cost | B15: €/l | C15: ='LCOF Baseline'!B43 -> 3.6063103 | D15: ='LCOF LCOE Corrected'!B43 -> 2.3526415 | E15: ='LCOF CO2 Cost Corrected'!B43 -> 5.6778084 | F15: ='LCOF WACC Corrected '!B43 -> 5.6343535 | H15: Syn-Fuel cost | I15: €/l | J15: ='LCOF Baseline'!B54 -> 3.1743174 | K15: ='LCOF LCOE Corrected'!B54 -> 2.3437676 | L15: ='LCOF CO2 Cost Corrected'!B54 -> 5.5152186 | M15: ='LCOF WACC Corrected '!B54 -> 5.4717637 | O15: Syn-Fuel cost | P15: €/l | Q15: ='LCOF Baseline'!B65 -> 2.8498662 | R15: ='LCOF LCOE Corrected'!B65 -> 2.1502183 | S15: ='LCOF CO2 Cost Corrected'!B65 -> 5.1790648 | T15: ='LCOF WACC Corrected '!B65 -> 5.13815
A16: Syn-Fuel cost | B16: $/l | C16: =C15/Inputs!$C$6 -> 4.0070115 | D16: =D15/Inputs!$C$6 -> 2.6140462 | E16: =E15/Inputs!$C$6 -> 6.308676 | F16: =F15/Inputs!$C$6 -> 6.2603928 | H16: Syn-Fuel cost | I16: $/l | J16: =J15/Inputs!$C$6 -> 3.5270194 | K16: =K15/Inputs!$C$6 -> 2.6041863 | L16: =L15/Inputs!$C$6 -> 6.1280206 | M16: =M15/Inputs!$C$6 -> 6.0797374 | O16: Syn-Fuel cost | P16: $/l | Q16: =Q15/Inputs!$C$6 -> 3.166518 | R16: =R15/Inputs!$C$6 -> 2.3891314 | S16: =S15/Inputs!$C$6 -> 5.7545164 | T16: =T15/Inputs!$C$6 -> 5.7090556
A17: Fossil Fuel cost | B17: $/l | C17: =Inputs!$C$18 -> 1.7 | D17: =Inputs!$C$18 -> 1.7 | E17: =Inputs!$C$18 -> 1.7 | F17: =Inputs!$C$18 -> 1.7 | H17: Fossil Fuel cost | I17: $/l | J17: =Inputs!$C$18 -> 1.7 | K17: =Inputs!$C$18 -> 1.7 | L17: =Inputs!$C$18 -> 1.7 | M17: =Inputs!$C$18 -> 1.7 | O17: Fossil Fuel cost | P17: $/l | Q17: =Inputs!$C$18 -> 1.7 | R17: =Inputs!$C$18 -> 1.7 | S17: =Inputs!$C$18 -> 1.7 | T17: =Inputs!$C$18 -> 1.7
A18: Syn-Fuel emissions | B18: gCO2eq/MJ | C18: =0.07 *Inputs!$C$11 -> 6.209 | D18: =0.07 *Inputs!$C$11 -> 6.209 | E18: =0.07 *Inputs!$C$11 -> 6.209 | F18: =0.07 *Inputs!$C$11 -> 6.209 | H18: Syn-Fuel emissions | I18: gCO2eq/MJ | J18: =0.07 *Inputs!$C$11 -> 6.209 | K18: =0.07 *Inputs!$C$11 -> 6.209 | L18: =0.07 *Inputs!$C$11 -> 6.209 | M18: =0.07 *Inputs!$C$11 -> 6.209 | O18: Syn-Fuel emissions | P18: gCO2eq/MJ | Q18: =0.07 *Inputs!$C$11 -> 6.209 | R18: =0.07 *Inputs!$C$11 -> 6.209 | S18: =0.07 *Inputs!$C$11 -> 6.209 | T18: =0.07 *Inputs!$C$11 -> 6.209
A19: Fossil Fuel emissions | B19: gCO2eq/MJ | C19: =Inputs!$C$11 -> 88.7 | D19: =Inputs!$C$11 -> 88.7 | E19: =Inputs!$C$11 -> 88.7 | F19: =Inputs!$C$11 -> 88.7 | H19: Fossil Fuel emissions | I19: gCO2eq/MJ | J19: =Inputs!$C$11 -> 88.7 | K19: =Inputs!$C$11 -> 88.7 | L19: =Inputs!$C$11 -> 88.7 | M19: =Inputs!$C$11 -> 88.7 | O19: Fossil Fuel emissions | P19: gCO2eq/MJ | Q19: =Inputs!$C$11 -> 88.7 | R19: =Inputs!$C$11 -> 88.7 | S19: =Inputs!$C$11 -> 88.7 | T19: =Inputs!$C$11 -> 88.7
A20: CO2 Abated | B20: gCO2eq/MJ | C20: =C19-C18 -> 82.491 | D20: =D19-D18 -> 82.491 | E20: =E19-E18 -> 82.491 | F20: =F19-F18 -> 82.491 | H20: CO2 Abated | I20: gCO2eq/MJ | J20: =J19-J18 -> 82.491 | K20: =K19-K18 -> 82.491 | L20: =L19-L18 -> 82.491 | M20: =M19-M18 -> 82.491 | O20: CO2 Abated | P20: gCO2eq/MJ | Q20: =Q19-Q18 -> 82.491 | R20: =R19-R18 -> 82.491 | S20: =S19-S18 -> 82.491 | T20: =T19-T18 -> 82.491
A21: CO2 Abated | B21: gCO2eq/l | C21: =C20*Inputs!$C$14 -> 2861.5798 | D21: =D20*Inputs!$C$14 -> 2861.5798 | E21: =E20*Inputs!$C$14 -> 2861.5798 | F21: =F20*Inputs!$C$14 -> 2861.5798 | H21: CO2 Abated | I21: gCO2eq/l | J21: =J20*Inputs!$C$14 -> 2861.5798 | K21: =K20*Inputs!$C$14 -> 2861.5798 | L21: =L20*Inputs!$C$14 -> 2861.5798 | M21: =M20*Inputs!$C$14 -> 2861.5798 | O21: CO2 Abated | P21: gCO2eq/l | Q21: =Q20*Inputs!$C$14 -> 2861.5798 | R21: =R20*Inputs!$C$14 -> 2861.5798 | S21: =S20*Inputs!$C$14 -> 2861.5798 | T21: =T20*Inputs!$C$14 -> 2861.5798
A22: Abatement cost | B22: $/tCO2 | C22: =(C16-C17) / C21 * 10^6 -> 806.20204 | D22: =(D16-D17) / D21 * 10^6 -> 319.42012 | E22: =(E16-E17) / E21 * 10^6 -> 1610.5356 | F22: =(F16-F17) / F21 * 10^6 -> 1593.6626 | H22: Abatement cost | I22: $/tCO2 | J22: =(J16-J17) / J21 * 10^6 -> 638.46529 | K22: =(K16-K17) / K21 * 10^6 -> 315.97451 | L22: =(L16-L17) / L21 * 10^6 -> 1547.4042 | M22: =(M16-M17) / M21 * 10^6 -> 1530.5313 | O22: Abatement cost | P22: $/tCO2 | Q22: =(Q16-Q17) / Q21 * 10^6 -> 512.48545 | R22: =(R16-R17) / R21 * 10^6 -> 240.82202 | S22: =(S16-S17) / S21 * 10^6 -> 1416.8804 | T22: =(T16-T17) / T21 * 10^6 -> 1400.9938
A24: Full Abatement -2024 -C-P-N | H24: Full Abatement -2024 -C-P-N/R | O24: Full Abatement -2024 -C-S-N/R
A25: Parameter | B25: Unit | C25: Value | H25: Parameter | I25: Unit | J25: Value | O25: Parameter | P25: Unit | Q25: Value
A26: Residual Emissions | B26: gCO2eq/l | C26: =F6*Inputs!$C$14 -> 215.38773 | H26: Residual Emissions | I26: gCO2eq/l | J26: =M6*Inputs!$C$14 -> 215.38773 | O26: Residual Emissions | P26: gCO2eq/l | Q26: =T6*Inputs!$C$14 -> 215.38773
A27: Emissions Reduction Cost | B27: $/l | C27: =C26*Inputs!$C$32 * 10^-6 -> 0.29529657 | H27: Emissions Reduction Cost | I27: $/l | J27: =J26*Inputs!$C$32 * 10^-6 -> 0.29529657 | O27: Emissions Reduction Cost | P27: $/l | Q27: =Q26*Inputs!$C$32 * 10^-6 -> 0.29529657
A28: Effective Synfuel Cost | B28: $/l | C28: =F4+C27 -> 13.239858 | H28: Effective Synfuel Cost | I28: $/l | J28: =M4+J27 -> 13.560052 | O28: Effective Synfuel Cost | P28: $/l | Q28: =T4+Q27 -> 13.357074
A29: Effective Abatement Cost | B29: $/tCO2 | C29: =(C28-C17) /C21 * 10^6 -> 4032.6879 | H29: Effective Abatement Cost | I29: $/tCO2 | J29: =(J28-J17) /J21 * 10^6 -> 4144.5819 | O29: Effective Abatement Cost | P29: $/tCO2 | Q29: =(Q28-Q17) /Q21 * 10^6 -> 4073.6498
A31: Full Abatement -2050 -C-P-N | H31: Full Abatement -2050 -C-P-N/R | O31: Full Abatement -2050 -C-S-N/R
A32: Parameter | B32: Unit | C32: Value | H32: Parameter | I32: Unit | J32: Value | O32: Parameter | P32: Unit | Q32: Value
A33: Residual Emissions | B33: gCO2eq/l | C33: =F18*Inputs!$C$14 -> 215.38773 | H33: Residual Emissions | I33: gCO2eq/l | J33: =M18*Inputs!$C$14 -> 215.38773 | O33: Residual Emissions | P33: gCO2eq/l | Q33: =T18*Inputs!$C$14 -> 215.38773
A34: Emissions Reduction Cost | B34: $/l | C34: =C33*Inputs!$C$33 * 10^-6 -> 0.11264778 | H34: Emissions Reduction Cost | I34: $/l | J34: =J33*Inputs!$C$33 * 10^-6 -> 0.11264778 | O34: Emissions Reduction Cost | P34: $/l | Q34: =Q33*Inputs!$C$33 * 10^-6 -> 0.11264778
A35: Effective Synfuel Cost | B35: $/l | C35: =F16+C34 -> 6.3730405 | H35: Effective Synfuel Cost | I35: $/l | J35: =M16+J34 -> 6.1923852 | O35: Effective Synfuel Cost | P35: $/l | Q35: =T16+Q34 -> 5.8217034
A36: Effective Abatement Cost | B36: $/tCO2 | C36: =(C35-C17) /C21 * 10^6 -> 1633.0282 | H36: Effective Abatement Cost | I36: $/tCO2 | J36: =(J35-J17) /J21 * 10^6 -> 1569.8969 | O36: Effective Abatement Cost | P36: $/tCO2 | Q36: =(Q35-Q17) /Q21 * 10^6 -> 1440.3594
