Workbook

Sheet Inputs
A1: Parameter | B1: Year | C1: Value | D1: Unit
A2: Standard Values
A3: Current Year | C3: =[1]Inputs!C4 -> 2024
A4: Inflation | C4: =[1]Inputs!C5 -> 0.02
A5: WACC | C5: =[1]Inputs!C6 -> 0.07
A6: USD to EUR | C6: =[1]Inputs!C7 -> 0.9
A7: Electricity
A8: LCOE | B8: 2024 | C8: =[1]Inputs!C9 -> 64 | D8: $/MWh
A9: LCOE | B9: 2050 | C9: =[1]Inputs!C10 -> 11 | D9: $/MWh
A10: Jet Fuel A-1 Characteristics
A11: Emissions Intensity | B11: 2024 | C11: =[1]Inputs!C12 -> 88.7 | D11: gCO2/MJ
A12: Emissions Intensity | B12: 2050 | C12: =[1]Inputs!C13 -> 88.7 | D12: gCO2/MJ
A13: Energy Density | C13: =[1]Inputs!C14 -> 43.2 | D13: MJ/kg
A14: Energy Density | C14: =[1]Inputs!C15 -> 34.6896 | D14: MJ/l
A15: Volumetric Density | C15: =[1]Inputs!C16 -> 0.803 | D15: kg/l
A16: Jet Fuel A-1 Price | B16: 2024 | C16: =[1]Inputs!C17 -> 0.8 | D16: $/l
A17: Scenario Specific Values
A18: Jet Fuel A-1 Price | B18: 2050 | C18: =[1]Inputs!C19 -> 0.8 | D18: $/l
A19: Reference
A20: Jet Fuel A-1 Price | B20: 2024 | C20: =[1]Inputs!C21 -> 0.32246154 | D20: $/l
A21: Jet Fuel A-1 Price | B21: 2050 | C21: =[1]Inputs!C22 -> 0.20923077 | D21: $/l
A22: EIA Reference
A23: Jet Fuel A-1 Price | B23: 2024 | C23: =[1]Inputs!C24 -> 1.0209014 | D23: $/l
A24: Jet Fuel A-1 Price | B24: 2050 | C24: =[1]Inputs!C25 -> 2.0095594 | D24: $/l
A25: EIA Low Oil Price Scenario
A26: Jet Fuel A-1 Price | B26: 2024 | C26: =[1]Inputs!C27 -> 0.48286833 | D26: $/l
A27: Jet Fuel A-1 Price | B27: 2050 | C27: =[1]Inputs!C28 -> 0.89646575 | D27: $/l
A28: EIA High Scenario
A29: Jet Fuel A-1 Price | B29: 2024 | C29: =[1]Inputs!C30 -> 1.8838713 | D29: $/l
A30: Jet Fuel A-1 Price | B30: 2050 | C30: =[1]Inputs!C31 -> 3.7893731 | D30: $/l
A31: Direct Air Capture
A32: LCOR | B32: 2024 | C32: =[1]Inputs!C33 -> 1282 | D32: $/tCO2
A33: LCOR | B33: 2050 | C33: =[1]Inputs!$C$34 -> 480 | D33: $/tCO2

Sheet Study Parameters
A1: Key Parameters
A2: Parameter | B2: Year | C2: Value | D2: Unit | E2: Source | F2: Notes
A3: Plant Lifetime | B3: Both | C3: 30 | D3: years | E3: E-Fuels: A technoeconomic assessment of European domestic production and imports towards 2050 – Update, Concawe Table 130
A4: Discount Rate | B4: Both | C4: 0.08 | E4: E-Fuels: A technoeconomic assessment of European domestic production and imports towards 2050 – Update, Concawe
A6: Plant Parameters
A7: Parameter | B7: Year | C7: Value | D7: Unit | E7: Source | F7: Notes
A8: Electrolyser Capacity | B8: 2020 | C8: 1026333 | D8: Nm3/h | E8: E-Fuels: A technoeconomic assessment of European domestic production and imports towards 2050 – Update, Concawe Table 123
A9: Electrolyser Capacity | B9: 2050 | C9: 1065000 | D9: Nm3/h | E9: E-Fuels: A technoeconomic assessment of European domestic production and imports towards 2050 – Update, Concawe Table 125
A10: H2 Storage Capacity | B10: 2020 | C10: 150.2 | D10: Million Nm3 | E10: E-Fuels: A technoeconomic assessment of European domestic production and imports towards 2050 – Update, Concawe Table 123
A11: H2 Storage Capacity | B11: 2050 | C11: 56.97 | D11: Million Nm3 | E11: E-Fuels: A technoeconomic assessment of European domestic production and imports towards 2050 – Update, Concawe Table 125
A12: Process Parameters
A13: Parameter | B13: Year | C13: Value | D13: Unit | E13: Source | F13: Notes
A14: CO2 Capture | B14: Both | C14: 3.715 | D14: kg/kg fuel
A15: Annual CO2 requirement | B15: Both | C15: =(C14*C18*10^9) / 10^6 -> 2229 | D15: kt | F15: Calculated from energy balance
A16: Electrolyser Specific Electricity Consumption | B16: Both | C16: 0.0649 | D16: kWh/Nm3 | E16: E-Fuels: A technoeconomic assessment of European domestic production and imports towards 2050 – Update, Concawe Table 123
A17: Annual Electrolysis Electricity Consumption | B17: Both | C17: =(C26*C16) / 10^6 -> 213.30467 | D17: GWh
A18: Annual Fuel Production | B18: Both | C18: 0.6 | D18: Million tons | E18: E-Fuels: A technoeconomic assessment of European domestic production and imports towards 2050 – Update, Concawe Table 123
A19: Annual Fuel Production | B19: Both | C19: =C18 * 10^9 * 10^3 / C36 -> 800000000 | D19: litres | F19: Calculated
A20: Electricity Consumption | B20: Both | C20: 2.6293 | D20: MJ/MJ fuel | E20: E-Fuels: A technoeconomic assessment of European domestic production and imports towards 2050 – Update, Concawe Figure 127
A21: Anuual Electricity Consumption (FT) | B21: Both | C21: =(C20* Inputs!$C$13*C18*10^9 / 3600) / 10^3 +C17 -> 19144.265 | D21: GWh
A22: DAC Electricity Consumption | B22: Both | C22: 1.82 | D22: MJ/kg CO2
A23: Annual DAC Electricity Consumption | B23: Both | C23: =(C22*C15 * 10^6) / 3600 / 10^3 -> 1126.8833 | D23: GWh
A24: Hydrogen Consumption | B24: Both | C24: 0.493 | D24: kg/kg fuel
A25: Annual Hydrogen Consumption | B25: Both | C25: =C24*C18 -> 0.2958 | D25: Million tons
A26: Annual Hydrogen Consumption | B26: Both | C26: =(C25 * 10^9) / 0.09 -> 3.2866667e+09 | D26: Nm3
A27: External Inputs
A28: Parameter | B28: Year | C28: Value | D28: Unit | E28: Source | F28: Notes
A29: CO2 Price | B29: 2020 | C29: 177 | D29: €/tCO2
A30: CO2 Price | B30: 2050 | C30: 158 | D30: €/tCO2
A31: Electricity Price (2020) | B31: 2020 | C31: 65 | D31: €/MWh | E31: E-Fuels: A technoeconomic assessment of European domestic production and imports towards 2050 – Update, Concawe Table 19 | F31: Average EU
A32: Electricity Price (2050) | B32: 2050 | C32: 52 | D32: €/MWh | E32: E-Fuels: A technoeconomic assessment of European domestic production and imports towards 2050 – Update, Concawe Table 19 | F32: Average EU
A33: Fuel Characteristics
A34: Parameter | B34: Year | C34: Value | D34: Unit | E34: Source
A35: Syn-fuel emissions | B35: Both | C35: 5.9 | D35: gCO2/MJ | E35: E-Fuels: A technoeconomic assessment of European domestic production and imports towards 2050 – Update, Concawe Key Message GHG Emissions
A36: Volumetric Density | B36: Both | C36: 750 | D36: kg/m3 | E36: E-Fuels: A technoeconomic assessment of European domestic production and imports towards 2050 – Update, Concawe Table 10
A37: LHV | B37: Both | C37: 43.1 | D37: MJ/kg | E37: E-Fuels: A technoeconomic assessment of European domestic production and imports towards 2050 – Update, Concawe Table 22

Sheet Levelised Cost of Removal
A1: Economic Assumptions 2024 EU-N | G1: Economic Assumptions 2050
A2: CAPEX | G2: CAPEX
A3: Component | B3: Value | C3: Unit | D3: Source | E3: Notes | G3: Component | H3: Value | I3: Unit | J3: Source | K3: Notes
A4: DAC CAPEX | B4: 1345 | C4: M€ | D4: E-Fuels: A technoeconomic assessment of European domestic production and imports towards 2050 – Update, Concawe Table 126 | G4: DAC CAPEX | H4: 1294 | I4: M€ | J4: E-Fuels: A technoeconomic assessment of European domestic production and imports towards 2050 – Update, Concawe Table 126
A5: Liquefaction | B5: 79 | C5: M€ | D5: E-Fuels: A technoeconomic assessment of European domestic production and imports towards 2050 – Update, Concawe Table 126 | G5: Liquefaction | H5: 80.67 | I5: M€ | J5: E-Fuels: A technoeconomic assessment of European domestic production and imports towards 2050 – Update, Concawe Table 126
A6: Storage | B6: 166 | C6: M€ | D6: E-Fuels: A technoeconomic assessment of European domestic production and imports towards 2050 – Update, Concawe Table 126 | G6: Storage | H6: 37 | I6: M€ | J6: E-Fuels: A technoeconomic assessment of European domestic production and imports towards 2050 – Update, Concawe Table 126
A7: Total CAPEX | B7: =SUM(B4:B6) -> 1590 | C7: M€ | G7: Total CAPEX | H7: =SUM(H4:H6) -> 1411.67 | I7: M€
A8: OPEX | G8: OPEX
A9: Component | B9: Value | C9: Unit | D9: Source | E9: Notes | G9: Component | H9: Value | I9: Unit | J9: Source | K9: Notes
A10: Maintenance and Repair | B10: =0.025*B4 -> 33.625 | C10: M€/year | D10: E-Fuels: A technoeconomic assessment of European domestic production and imports towards 2050 – Update, Concawe Table 126 | G10: Maintenance and Repair | H10: =0.025*H4 -> 32.35 | I10: M€/year | J10: E-Fuels: A technoeconomic assessment of European domestic production and imports towards 2050 – Update, Concawe Table 126
A11: Insurance | B11: =0.02*B4 -> 26.9 | C11: M€/year | D11: E-Fuels: A technoeconomic assessment of European domestic production and imports towards 2050 – Update, Concawe Table 126 | G11: Insurance | H11: =0.02*H4 -> 25.88 | I11: M€/year | J11: E-Fuels: A technoeconomic assessment of European domestic production and imports towards 2050 – Update, Concawe Table 126
A12: Labor | B12: 2.16 | C12: M€/year | D12: E-Fuels: A technoeconomic assessment of European domestic production and imports towards 2050 – Update, Concawe Table 126 | G12: Labor | H12: 2.16 | I12: M€/year | J12: E-Fuels: A technoeconomic assessment of European domestic production and imports towards 2050 – Update, Concawe Table 126
A13: Administration | B13: =0.3 * B10 -> 10.0875 | C13: M€/year | D13: E-Fuels: A technoeconomic assessment of European domestic production and imports towards 2050 – Update, Concawe Table 126 | G13: Administration | H13: =0.3 * H10 -> 9.705 | I13: M€/year | J13: E-Fuels: A technoeconomic assessment of European domestic production and imports towards 2050 – Update, Concawe Table 126
A14: Electricity | B14: =(B24*B23) / 10^6 -> 503.07292 | C14: M€/year | E14: Calculated | G14: Electricity | H14: =(B25*B23) / 10^6 -> 402.45833 | I14: M€/year | K14: Calculated
A15: OPEX Liquefaction | B15: =0.1*B5 -> 7.9 | C15: M€/year | D15: E-Fuels: A technoeconomic assessment of European domestic production and imports towards 2050 – Update, Concawe Table 126 | G15: OPEX Liquefaction | H15: =0.1*H5 -> 8.067 | I15: M€/year
A16: OPEX Storage | B16: =0.05 *B6 -> 8.3 | C16: M€/year | D16: E-Fuels: A technoeconomic assessment of European domestic production and imports towards 2050 – Update, Concawe Table 126 | G16: OPEX Storage | H16: =0.05 *H6 -> 1.85 | I16: M€/year
A17: Total OPEX | B17: =SUM(B10:B16) -> 592.04542 | C17: M€/year | G17: Total OPEX | H17: =SUM(H10:H16) -> 482.47033 | I17: M€/year
A19: Process Parameters
A20: Parameter | B20: Value | C20: Unit | D20: Source | E20: Notes
A21: CO2 Capacity | B21: 3715 | C21: kt/year | D21: E-Fuels: A technoeconomic assessment of European domestic production and imports towards 2050 – Update, Concawe Table 126
A22: Electricity Consumption | B22: 7.5 | C22: MJ/kgCO2 | D22: E-Fuels: A technoeconomic assessment of European domestic production and imports towards 2050 – Update, Concawe Table 126
A23: Electricity Consumption | B23: =(B22 / 3600 * B21 * 10^6) -> 7739583.3 | C23: MWh/year | D23: E-Fuels: A technoeconomic assessment of European domestic production and imports towards 2050 – Update, Concawe Table 126
A24: Electricity Price (2020) | B24: ='Study Parameters'!C31 -> 65 | C24: €/MWh | D24: E-Fuels: A technoeconomic assessment of European domestic production and imports towards 2050 – Update, Concawe Table 19 | E24: Average EU
A25: Electricity Price (2050) | B25: ='Study Parameters'!C32 -> 52 | C25: €/MWh | D25: E-Fuels: A technoeconomic assessment of European domestic production and imports towards 2050 – Update, Concawe Table 19 | E25: Average EU
A26: Lifetime DAC Plant | B26: 25 | C26: years
A28: LCOR 2024
A29: Year | B29: 0 | C29: 1 | D29: 2 | E29: 3 | F29: 4 | G29: 5 | H29: 6 | I29: 7 | J29: 8 | K29: 9 | L29: 10 | M29: 11 | N29: 12 | O29: 13 | P29: 14 | Q29: 15 | R29: 16 | S29: 17 | T29: 18 | U29: 19 | V29: 20 | W29: 21 | X29: 22 | Y29: 23 | Z29: 24 | AA29: 25
A30: Cost (€) | B30: =B7 * 10^6 -> 1590000000 | C30: =$B$17 * 10^6 -> 5.9204542e+08 | D30: =$B$17 * 10^6 -> 5.9204542e+08 | E30: =$B$17 * 10^6 -> 5.9204542e+08 | F30: =$B$17 * 10^6 -> 5.9204542e+08 | G30: =$B$17 * 10^6 -> 5.9204542e+08 | H30: =$B$17 * 10^6 -> 5.9204542e+08 | I30: =$B$17 * 10^6 -> 5.9204542e+08 | J30: =$B$17 * 10^6 -> 5.9204542e+08 | ... AA30: =$B$17 * 10^6 -> 5.9204542e+08
A31: Discounted Cost (€) | B31: =B30/(1+'Study Parameters'!$C$4)^'Levelised Cost of Removal'!B29 -> 1590000000 | C31: =C30/(1+'Study Parameters'!$C$4)^'Levelised Cost of Removal'!C29 -> 5.481902e+08 | D31: =D30/(1+'Study Parameters'!$C$4)^'Levelised Cost of Removal'!D29 -> 5.0758352e+08 | E31: =E30/(1+'Study Parameters'!$C$4)^'Levelised Cost of Removal'!E29 -> 4.6998474e+08 | F31: =F30/(1+'Study Parameters'!$C$4)^'Levelised Cost of Removal'!F29 -> 4.3517106e+08 | G31: =G30/(1+'Study Parameters'!$C$4)^'Levelised Cost of Removal'!G29 -> 4.0293616e+08 | H31: =H30/(1+'Study Parameters'!$C$4)^'Levelised Cost of Removal'!H29 -> 3.7308904e+08 | I31: =I30/(1+'Study Parameters'!$C$4)^'Levelised Cost of Removal'!I29 -> 3.4545281e+08 | ... AA31: =AA30/(1+'Study Parameters'!$C$4)^'Levelised Cost of Removal'!AA29 -> 86449231
A32: Removal (t) | B32: =$B$21 * 10^3 -> 3715000 | C32: =$B$21 * 10^3 -> 3715000 | D32: =$B$21 * 10^3 -> 3715000 | E32: =$B$21 * 10^3 -> 3715000 | F32: =$B$21 * 10^3 -> 3715000 | G32: =$B$21 * 10^3 -> 3715000 | H32: =$B$21 * 10^3 -> 3715000 | I32: =$B$21 * 10^3 -> 3715000 | ... AA32: =$B$21 * 10^3 -> 3715000
A33: Discounted Removal (t) | B33: =B32/(1+'Study Parameters'!$C$4)^'Levelised Cost of Removal'!B29 -> 3715000 | C33: =C32/(1+'Study Parameters'!$C$4)^'Levelised Cost of Removal'!C29 -> 3439814.8 | D33: =D32/(1+'Study Parameters'!$C$4)^'Levelised Cost of Removal'!D29 -> 3185013.7 | E33: =E32/(1+'Study Parameters'!$C$4)^'Levelised Cost of Removal'!E29 -> 2949086.8 | F33: =F32/(1+'Study Parameters'!$C$4)^'Levelised Cost of Removal'!F29 -> 2730635.9 | G33: =G32/(1+'Study Parameters'!$C$4)^'Levelised Cost of Removal'!G29 -> 2528366.6 | H33: =H32/(1+'Study Parameters'!$C$4)^'Levelised Cost of Removal'!H29 -> 2341080.2 | I33: =I32/(1+'Study Parameters'!$C$4)^'Levelised Cost of Removal'!I29 -> 2167666.8 | ... AA33: =AA32/(1+'Study Parameters'!$C$4)^'Levelised Cost of Removal'!AA29 -> 542456.52
A35: LCOR (€/tCO2) | B35: =SUM(B31:AF31) / SUM(B33:AF33) -> 182.3755
A37: LCOR 2050
A38: Year | B38: 0 | C38: 1 | D38: 2 | E38: 3 | F38: 4 | G38: 5 | H38: 6 | I38: 7 | J38: 8 | K38: 9 | L38: 10 | M38: 11 | N38: 12 | O38: 13 | P38: 14 | Q38: 15 | R38: 16 | S38: 17 | T38: 18 | U38: 19 | V38: 20 | W38: 21 | X38: 22 | Y38: 23 | Z38: 24 | AA38: 25
A39: Cost (€) | B39: =H7*10^6 -> 1411670000 | C39: =$H$17 * 10^6 -> 4.8247033e+08 | D39: =$H$17 * 10^6 -> 4.8247033e+08 | E39: =$H$17 * 10^6 -> 4.8247033e+08 | F39: =$H$17 * 10^6 -> 4.8247033e+08 | G39: =$H$17 * 10^6 -> 4.8247033e+08 | H39: =$H$17 * 10^6 -> 4.8247033e+08 | I39: =$H$17 * 10^6 -> 4.8247033e+08 | J39: =$H$17 * 10^6 -> 4.8247033e+08 | ... AA39: =$H$17 * 10^6 -> 4.8247033e+08
A40: Discounted Cost (€) | B40: =B39/(1+'Study Parameters'!$C$4)^'Levelised Cost of Removal'!B38 -> 1411670000 | C40: =C39/(1+'Study Parameters'!$C$4)^'Levelised Cost of Removal'!C38 -> 4.4673179e+08 | D40: =D39/(1+'Study Parameters'!$C$4)^'Levelised Cost of Removal'!D38 -> 4.1364055e+08 | E40: =E39/(1+'Study Parameters'!$C$4)^'Levelised Cost of Removal'!E38 -> 3.8300051e+08 | F40: =F39/(1+'Study Parameters'!$C$4)^'Levelised Cost of Removal'!F38 -> 3.546301e+08 | G40: =G39/(1+'Study Parameters'!$C$4)^'Levelised Cost of Removal'!G38 -> 3.283612e+08 | H40: =H39/(1+'Study Parameters'!$C$4)^'Levelised Cost of Removal'!H38 -> 3.0403815e+08 | I40: =I39/(1+'Study Parameters'!$C$4)^'Levelised Cost of Removal'!I38 -> 2.8151681e+08 | ... AA40: =AA39/(1+'Study Parameters'!$C$4)^'Levelised Cost of Removal'!AA38 -> 70449307
A41: Removal (t) | B41: =$B$21 * 10^3 -> 3715000 | C41: =$B$21 * 10^3 -> 3715000 | D41: =$B$21 * 10^3 -> 3715000 | E41: =$B$21 * 10^3 -> 3715000 | F41: =$B$21 * 10^3 -> 3715000 | G41: =$B$21 * 10^3 -> 3715000 | H41: =$B$21 * 10^3 -> 3715000 | I41: =$B$21 * 10^3 -> 3715000 | ... AA41: =$B$21 * 10^3 -> 3715000
A42: Discounted Removal (t) | B42: =B41/(1+'Study Parameters'!$C$4)^'Levelised Cost of Removal'!B38 -> 3715000 | C42: =C41/(1+'Study Parameters'!$C$4)^'Levelised Cost of Removal'!C38 -> 3439814.8 | D42: =D41/(1+'Study Parameters'!$C$4)^'Levelised Cost of Removal'!D38 -> 3185013.7 | E42: =E41/(1+'Study Parameters'!$C$4)^'Levelised Cost of Removal'!E38 -> 2949086.8 | F42: =F41/(1+'Study Parameters'!$C$4)^'Levelised Cost of Removal'!F38 -> 2730635.9 | G42: =G41/(1+'Study Parameters'!$C$4)^'Levelised Cost of Removal'!G38 -> 2528366.6 | H42: =H41/(1+'Study Parameters'!$C$4)^'Levelised Cost of Removal'!H38 -> 2341080.2 | I42: =I41/(1+'Study Parameters'!$C$4)^'Levelised Cost of Removal'!I38 -> 2167666.8 | ... AA42: =AA41/(1+'Study Parameters'!$C$4)^'Levelised Cost of Removal'!AA38 -> 542456.52
A44: LCOR (€/tCO2) | B44: =SUM(B40:AF40) / SUM(B42:AF42) -> 151.29494

Sheet Cost Components
A1: Economic Assumptions 2024 EU-North | G1: Economic Assumptions 2024 EU-Central | M1: Economic Assumptions 2024 EU-South
A2: CAPEX | G2: CAPEX | M2: CAPEX
A3: Component | B3: Value | C3: Unit | D3: Source | E3: Notes | G3: Component | H3: Value | I3: Unit | J3: Source | K3: Notes | M3: Component | N3: Value | O3: Unit | P3: Source | Q3: Notes
A4: Electrolyser | B4: 249 | C4: M€ | D4: E-Fuels: A technoeconomic assessment of European domestic production and imports towards 2050 – Update, Concawe Table 123 | E4: Average EU | G4: Electrolyser | H4: 278 | I4: M€ | J4: E-Fuels: A technoeconomic assessment of European domestic production and imports towards 2050 – Update, Concawe Table 123 | K4: Average EU | M4: Electrolyser | N4: 264 | O4: M€ | P4: E-Fuels: A technoeconomic assessment of European domestic production and imports towards 2050 – Update, Concawe Table 123 | Q4: Average EU
A5: H2 Storage | B5: 4140 | C5: M€ | D5: E-Fuels: A technoeconomic assessment of European domestic production and imports towards 2050 – Update, Concawe Table 123 | E5: Average EU | G5: H2 Storage | H5: 2916 | I5: M€ | J5: E-Fuels: A technoeconomic assessment of European domestic production and imports towards 2050 – Update, Concawe Table 123 | K5: Average EU | M5: H2 Storage | N5: 4263 | O5: M€ | P5: E-Fuels: A technoeconomic assessment of European domestic production and imports towards 2050 – Update, Concawe Table 123 | Q5: Average EU
A6: FT Synthesis Plant | B6: 1678 | C6: M€ | D6: E-Fuels: A technoeconomic assessment of European domestic production and imports towards 2050 – Update, Concawe Table 130 | E6: Average EU | G6: FT Synthesis Plant | H6: 1676 | I6: M€ | J6: E-Fuels: A technoeconomic assessment of European domestic production and imports towards 2050 – Update, Concawe Table 130 | K6: Average EU | M6: FT Synthesis Plant | N6: 1637 | O6: M€ | P6: E-Fuels: A technoeconomic assessment of European domestic production and imports towards 2050 – Update, Concawe Table 130 | Q6: Average EU
A7: CO2 Storage | B7: 173 | C7: M€ | G7: CO2 Storage | H7: 86 | I7: M€ | M7: CO2 Storage | N7: 240 | O7: M€
A8: Total CAPEX | B8: =SUM(B4:B7) -> 6240 | C8: M€ | G8: Total CAPEX | H8: =SUM(H4:H7) -> 4956 | I8: M€ | M8: Total CAPEX | N8: =SUM(N4:N7) -> 6404 | O8: M€
A9: Amortized CAPEX | B9: =PMT('Study Parameters'!$C$4,'Study Parameters'!$C$3, -B8*10^6) -> 5.5428318e+08 | C9: €/year | G9: Amortized CAPEX | H9: =PMT('Study Parameters'!$C$4,'Study Parameters'!$C$3, -H8*10^6) -> 4.4022876e+08 | I9: €/year | M9: Amortized CAPEX | N9: =PMT('Study Parameters'!$C$4,'Study Parameters'!$C$3, -N8*10^6) -> 5.6885088e+08 | O9: €/year
A10: OPEX | G10: OPEX | M10: OPEX
A11: Component | B11: Value | C11: Unit | D11: Source | E11: Notes | G11: Component | H11: Value | I11: Unit | J11: Source | K11: Notes | M11: Component | N11: Value | O11: Unit | P11: Source | Q11: Notes
A12: Electrolyser O&M | B12: =0.03 * B4 -> 7.47 | C12: M€/year | D12: E-Fuels: A technoeconomic assessment of European domestic production and imports towards 2050 – Update, Concawe Table 123 | G12: Electrolyser O&M | H12: =0.03 * H4 -> 8.34 | I12: M€/year | J12: E-Fuels: A technoeconomic assessment of European domestic production and imports towards 2050 – Update, Concawe Table 123 | M12: Electrolyser O&M | N12: =0.03 * N4 -> 7.92 | O12: M€/year | P12: E-Fuels: A technoeconomic assessment of European domestic production and imports towards 2050 – Update, Concawe Table 123
A13: FT Synthesis Fixed O&M | B13: =0.03 * B6 -> 50.34 | C13: M€/year | D13: E-Fuels: A technoeconomic assessment of European domestic production and imports towards 2050 – Update, Concawe Table 130 | G13: FT Synthesis Fixed O&M | H13: =0.03 * H6 -> 50.28 | I13: M€/year | J13: E-Fuels: A technoeconomic assessment of European domestic production and imports towards 2050 – Update, Concawe Table 130 | M13: FT Synthesis Fixed O&M | N13: =0.03 * N6 -> 49.11 | O13: M€/year | P13: E-Fuels: A technoeconomic assessment of European domestic production and imports towards 2050 – Update, Concawe Table 130
A14: FT Synthesis Variable O&M | B14: =(1.53 * (1/'Study Parameters'!$C$37) * 'Study Parameters'!$C$18 * 10^9 / 10^3) / 10^6 -> 0.021299304 | C14: M€/year | D14: E-Fuels: A technoeconomic assessment of European domestic production and imports towards 2050 – Update, Concawe Table 130 | G14: FT Synthesis Variable O&M | H14: =(1.53 * (1/'Study Parameters'!$C$37) * 'Study Parameters'!$C$18 * 10^9 / 10^3) / 10^6 -> 0.021299304 | I14: M€/year | J14: E-Fuels: A technoeconomic assessment of European domestic production and imports towards 2050 – Update, Concawe Table 130 | M14: FT Synthesis Variable O&M | N14: =(1.53 * (1/'Study Parameters'!$C$37) * 'Study Parameters'!$C$18 * 10^9 / 10^3) / 10^6 -> 0.021299304 | O14: M€/year | P14: E-Fuels: A technoeconomic assessment of European domestic production and imports towards 2050 – Update, Concawe Table 130
A15: CO2 Storage O&M | B15: =0.1 * B7 -> 17.3 | C15: M€/year | D15: E-Fuels: A technoeconomic assessment of European domestic production and imports towards 2050 – Update, Concawe Table 130 | G15: CO2 Storage O&M | H15: =0.1 * H7 -> 8.6 | I15: M€/year | J15: E-Fuels: A technoeconomic assessment of European domestic production and imports towards 2050 – Update, Concawe Table 130 | M15: CO2 Storage O&M | N15: =0.1 * N7 -> 24 | O15: M€/year | P15: E-Fuels: A technoeconomic assessment of European domestic production and imports towards 2050 – Update, Concawe Table 130
A16: Electricity | B16: =('Study Parameters'!$C$21*10^3*'Study Parameters'!$C$31) / 10^6 -> 1244.3772 | C16: M€/year | G16: Electricity | H16: =('Study Parameters'!$C$21*10^3*'Study Parameters'!$C$31) / 10^6 -> 1244.3772 | I16: M€/year | M16: Electricity | N16: =('Study Parameters'!$C$21*10^3*'Study Parameters'!$C$31) / 10^6 -> 1244.3772 | O16: M€/year
A17: CO2 Supply | B17: =('Study Parameters'!$C$29*'Study Parameters'!$C$15 * 10^3) / 10^6 -> 394.533 | C17: M€/year | G17: CO2 Supply | H17: =('Study Parameters'!$C$29*'Study Parameters'!$C$15 * 10^3) / 10^6 -> 394.533 | I17: M€/year | M17: CO2 Supply | N17: =('Study Parameters'!$C$29*'Study Parameters'!$C$15 * 10^3) / 10^6 -> 394.533 | O17: M€/year
A18: Total OPEX | B18: =SUM(B12:B17) -> 1714.0415 | C18: M€/year | G18: Total OPEX | H18: =SUM(H12:H17) -> 1706.1515 | I18: M€/year | M18: Total OPEX | N18: =SUM(N12:N17) -> 1719.9615 | O18: M€/year
A21: Economic Assumptions 2050 EU-North | G21: Economic Assumptions 2050 EU-Central | M21: Economic Assumptions 2050 EU-South
A22: CAPEX | G22: CAPEX | M22: CAPEX
A23: Component | B23: Value | C23: Unit | D23: Source | E23: Notes | G23: Component | H23: Value | I23: Unit | J23: Source | K23: Notes | M23: Component | N23: Value | O23: Unit | P23: Source | Q23: Notes
A24: Electrolyser | B24: 250 | C24: M€ | D24: E-Fuels: A technoeconomic assessment of European domestic production and imports towards 2050 – Update, Concawe Table 125 | E24: Average EU | G24: Electrolyser | H24: 291 | I24: M€ | J24: E-Fuels: A technoeconomic assessment of European domestic production and imports towards 2050 – Update, Concawe Table 125 | K24: Average EU | M24: Electrolyser | N24: 280 | O24: M€ | P24: E-Fuels: A technoeconomic assessment of European domestic production and imports towards 2050 – Update, Concawe Table 125 | Q24: Average EU
A25: H2 Storage | B25: 1628 | C25: M€ | D25: E-Fuels: A technoeconomic assessment of European domestic production and imports towards 2050 – Update, Concawe Table 125 | E25: Average EU | G25: H2 Storage | H25: 1503 | I25: M€ | J25: E-Fuels: A technoeconomic assessment of European domestic production and imports towards 2050 – Update, Concawe Table 125 | K25: Average EU | M25: H2 Storage | N25: 1616 | O25: M€ | P25: E-Fuels: A technoeconomic assessment of European domestic production and imports towards 2050 – Update, Concawe Table 125 | Q25: Average EU
A26: FT Synthesis Plant | B26: 1818 | C26: M€ | D26: E-Fuels: A technoeconomic assessment of European domestic production and imports towards 2050 – Update, Concawe Table 130 | E26: Average EU | G26: FT Synthesis Plant | H26: 1958 | I26: M€ | J26: E-Fuels: A technoeconomic assessment of European domestic production and imports towards 2050 – Update, Concawe Table 130 | K26: Average EU | M26: FT Synthesis Plant | N26: 1778 | O26: M€ | P26: E-Fuels: A technoeconomic assessment of European domestic production and imports towards 2050 – Update, Concawe Table 130 | Q26: Average EU
A27: CO2 Storage | B27: 40 | C27: M€ | G27: CO2 Storage | H27: 18 | I27: M€ | M27: CO2 Storage | N27: 53 | O27: M€
A28: Total CAPEX | B28: =SUM(B24:B27) -> 3736 | C28: M€ | G28: Total CAPEX | H28: =SUM(H24:H27) -> 3770 | I28: M€ | M28: Total CAPEX | N28: =SUM(N24:N27) -> 3727 | O28: M€
A29: Amortized CAPEX | B29: =PMT('Study Parameters'!$C$4,'Study Parameters'!$C$3, -B28*10^6) -> 3.3185929e+08 | C29: €/year | G29: Amortized CAPEX | H29: =PMT('Study Parameters'!$C$4,'Study Parameters'!$C$3, -H28*10^6) -> 3.3487942e+08 | I29: €/year | M29: Amortized CAPEX | N29: =PMT('Study Parameters'!$C$4,'Study Parameters'!$C$3, -N28*10^6) -> 3.3105984e+08 | O29: €/year
A30: OPEX | G30: OPEX | M30: OPEX
A31: Component | B31: Value | C31: Unit | D31: Source | E31: Notes | G31: Component | H31: Value | I31: Unit | J31: Source | K31: Notes | M31: Component | N31: Value | O31: Unit | P31: Source | Q31: Notes
A32: Electrolyser O&M | B32: =0.03 * B24 -> 7.5 | C32: M€/year | D32: E-Fuels: A technoeconomic assessment of European domestic production and imports towards 2050 – Update, Concawe Table 123 | G32: Electrolyser O&M | H32: =0.03 * H24 -> 8.73 | I32: M€/year | J32: E-Fuels: A technoeconomic assessment of European domestic production and imports towards 2050 – Update, Concawe Table 123 | M32: Electrolyser O&M | N32: =0.03 * N24 -> 8.4 | O32: M€/year | P32: E-Fuels: A technoeconomic assessment of European domestic production and imports towards 2050 – Update, Concawe Table 123
A33: FT Synthesis Fixed O&M | B33: =0.03 * B26 -> 54.54 | C33: M€/year | D33: E-Fuels: A technoeconomic assessment of European domestic production and imports towards 2050 – Update, Concawe Table 130 | G33: FT Synthesis Fixed O&M | H33: =0.03 * H26 -> 58.74 | I33: M€/year | J33: E-Fuels: A technoeconomic assessment of European domestic production and imports towards 2050 – Update, Concawe Table 130 | M33: FT Synthesis Fixed O&M | N33: =0.03 * N26 -> 53.34 | O33: M€/year | P33: E-Fuels: A technoeconomic assessment of European domestic production and imports towards 2050 – Update, Concawe Table 130
A34: FT Synthesis Variable O&M | B34: =(1.53 * (1/'Study Parameters'!$C$37) * 'Study Parameters'!$C$18 * 10^9 / 10^3) / 10^6 -> 0.021299304 | C34: M€/year | D34: E-Fuels: A technoeconomic assessment of European domestic production and imports towards 2050 – Update, Concawe Table 130 | G34: FT Synthesis Variable O&M | H34: =(1.53 * (1/'Study Parameters'!$C$37) * 'Study Parameters'!$C$18 * 10^9 / 10^3) / 10^6 -> 0.021299304 | I34: M€/year | J34: E-Fuels: A technoeconomic assessment of European domestic production and imports towards 2050 – Update, Concawe Table 130 | M34: FT Synthesis Variable O&M | N34: =(1.53 * (1/'Study Parameters'!$C$37) * 'Study Parameters'!$C$18 * 10^9 / 10^3) / 10^6 -> 0.021299304 | O34: M€/year | P34: E-Fuels: A technoeconomic assessment of European domestic production and imports towards 2050 – Update, Concawe Table 130
A35: CO2 Storage O&M | B35: =0.1 * B27 -> 4 | C35: M€/year | G35: CO2 Storage O&M | H35: =0.1 * H27 -> 1.8 | I35: M€/year | M35: CO2 Storage O&M | N35: =0.1 * N27 -> 5.3 | O35: M€/year
A36: Electricity | B36: =('Study Parameters'!$C$21*10^3*'Study Parameters'!$C$32) / 10^6 -> 995.50176 | C36: M€/year | G36: Electricity | H36: =('Study Parameters'!$C$21*10^3*'Study Parameters'!$C$32) / 10^6 -> 995.50176 | I36: M€/year | M36: Electricity | N36: =('Study Parameters'!$C$21*10^3*'Study Parameters'!$C$32) / 10^6 -> 995.50176 | O36: M€/year
A37: CO2 Cost | B37: =('Study Parameters'!$C$30*'Study Parameters'!$C$15 * 10^3) / 10^6 -> 352.182 | C37: M€/year | G37: CO2 Cost | H37: =('Study Parameters'!$C$30*'Study Parameters'!$C$15 * 10^3) / 10^6 -> 352.182 | I37: M€/year | M37: CO2 Cost | N37: =('Study Parameters'!$C$30*'Study Parameters'!$C$15 * 10^3) / 10^6 -> 352.182 | O37: M€/year
A38: Total OPEX | B38: =SUM(B32:B37) -> 1413.7451 | C38: M€/year | G38: Total OPEX | H38: =SUM(H32:H37) -> 1416.9751 | I38: M€/year | M38: Total OPEX | N38: =SUM(N32:N37) -> 1414.7451 | O38: M€/year
A41: Standardized Economic Assumptions 2024 EU-North | G41: Standardized Economic Assumptions 2024 EU-Central | M41: Standardized Economic Assumptions 2024 EU-South
A42: Electricity | B42: =('Study Parameters'!$C$21*10^3*Inputs!$C$8) / 10^6 -> 1225.2329 | C42: M€/year | G42: Electricity | H42: =('Study Parameters'!$C$21*10^3*Inputs!$C$8) / 10^6 -> 1225.2329 | I42: M€/year | M42: Electricity | N42: =('Study Parameters'!$C$21*10^3*Inputs!$C$8) / 10^6 -> 1225.2329 | O42: M€/year
A43: LCOE Corrected OPEX | B43: =B18-B16+B42 -> 1694.8972 | C43: M€/year | G43: LCOE Corrected OPEX | H43: =H18-H16+H42 -> 1687.0072 | I43: M€/year | M43: LCOE Corrected OPEX | N43: =N18-N16+N42 -> 1700.8172 | O43: M€/year
A44: CO2 Cost | B44: =(Inputs!$C$32*'Study Parameters'!$C$15 * 10^3) / 10^6 -> 2857.578 | C44: M€/year | G44: CO2 Cost | H44: =(Inputs!$C$32*'Study Parameters'!$C$15 * 10^3) / 10^6 -> 2857.578 | I44: M€/year | M44: CO2 Cost | N44: =(Inputs!$C$32*'Study Parameters'!$C$15 * 10^3) / 10^6 -> 2857.578 | O44: M€/year
A45: CO2 Corrected OPEX | B45: =B43-B17+B44 -> 4157.9422 | C45: M€/year | G45: CO2 Corrected OPEX | H45: =H43-H17+H44 -> 4150.0522 | I45: M€/year | M45: CO2 Corrected OPEX | N45: =N43-N17+N44 -> 4163.8622 | O45: M€/year
A46: WACC | B46: =Inputs!$C$5 -> 0.07 | G46: WACC | H46: =Inputs!$C$5 -> 0.07 | M46: WACC | N46: =Inputs!$C$5 -> 0.07
A47: WACC Corrected Amortized CAPEX | B47: =PMT(B46,'Study Parameters'!$C$3, -B8*10^6) -> 5.0285916e+08 | C47: €/year | G47: WACC Corrected Amortized CAPEX | H47: =PMT(H46,'Study Parameters'!$C$3, -H8*10^6) -> 3.9938622e+08 | I47: €/year | M47: WACC Corrected Amortized CAPEX | N47: =PMT(N46,'Study Parameters'!$C$3, -N8*10^6) -> 5.1607533e+08 | O47: €/year
A50: Standardized Economic Assumptions 2050 EU-North | G50: Standardized Economic Assumptions 2050 EU-Central | M50: Standardized Economic Assumptions 2050 EU-South
A51: Electricity | B51: =('Study Parameters'!$C$21*10^3*Inputs!$C$9) / 10^6 -> 210.58691 | C51: M€/year | G51: Electricity | H51: =('Study Parameters'!$C$21*10^3*Inputs!$C$9) / 10^6 -> 210.58691 | I51: M€/year | M51: Electricity | N51: =('Study Parameters'!$C$21*10^3*Inputs!$C$9) / 10^6 -> 210.58691 | O51: M€/year
A52: LCOE Corrected OPEX | B52: =B38-B36+B51 -> 628.83021 | C52: M€/year | G52: LCOE Corrected OPEX | H52: =H38-H36+H51 -> 632.06021 | I52: M€/year | M52: LCOE Corrected OPEX | N52: =N38-N36+N51 -> 629.83021 | O52: M€/year
A53: CO2 Cost | B53: =(Inputs!$C$33*'Study Parameters'!$C$15 * 10^3) / 10^6 -> 1069.92 | C53: M€/year | G53: CO2 Cost | H53: =(Inputs!$C$33*'Study Parameters'!$C$15 * 10^3) / 10^6 -> 1069.92 | I53: M€/year | M53: CO2 Cost | N53: =(Inputs!$C$33*'Study Parameters'!$C$15 * 10^3) / 10^6 -> 1069.92 | O53: M€/year
A54: CO2 Corrected OPEX | B54: =B52-B37+B53 -> 1346.5682 | C54: M€/year | G54: CO2 Corrected OPEX | H54: =H52-H37+H53 -> 1349.7982 | I54: M€/year | M54: CO2 Corrected OPEX | N54: =N52-N37+N53 -> 1347.5682 | O54: M€/year
A55: WACC | B55: =Inputs!$C$5 -> 0.07 | G55: WACC | H55: =Inputs!$C$5 -> 0.07 | M55: WACC | N55: =Inputs!$C$5 -> 0.07
A56: WACC Corrected Amortized CAPEX | B56: =PMT(B55,'Study Parameters'!$C$3, -B28*10^6) -> 3.010708e+08 | C56: €/year | G56: WACC Corrected Amortized CAPEX | H56: =PMT(H55,'Study Parameters'!$C$3, -H28*10^6) -> 3.0381074e+08 | I56: €/year | M56: WACC Corrected Amortized CAPEX | N56: =PMT(N55,'Study Parameters'!$C$3, -N28*10^6) -> 3.0034553e+08 | O56: €/year

Sheet MFSP Baseline
A1: Amortised Cash Flow Model 2024 EU-North
A2: Year | B2: 0 | C2: 1 | D2: 2 | E2: 3 | F2: 4 | G2: 5 | H2: 6 | I2: 7 | J2: 8 | K2: 9 | L2: 10 | M2: 11 | N2: 12 | O2: 13 | P2: 14 | Q2: 15 | R2: 16 | S2: 17 | T2: 18 | U2: 19 | V2: 20 | W2: 21 | X2: 22 | Y2: 23 | Z2: 24 | AA2: 25 | AB2: 26 | AC2: 27 | AD2: 28 | AE2: 29 | AF2: 30
A3: OPEX (€) | B3: 0 | C3: ='Cost Components'!$B$18 * 10^6 -> 1.7140415e+09 | D3: ='Cost Components'!$B$18 * 10^6 + 'Cost Components'!$B$9 -> 2.2683247e+09 | E3: ='Cost Components'!$B$18 * 10^6 + 'Cost Components'!$B$9 -> 2.2683247e+09 | F3: ='Cost Components'!$B$18 * 10^6 + 'Cost Components'!$B$9 -> 2.2683247e+09 | G3: ='Cost Components'!$B$18 * 10^6 + 'Cost Components'!$B$9 -> 2.2683247e+09 | H3: ='Cost Components'!$B$18 * 10^6 + 'Cost Components'!$B$9 -> 2.2683247e+09 | I3: ='Cost Components'!$B$18 * 10^6 + 'Cost Components'!$B$9 -> 2.2683247e+09 | J3: ='Cost Components'!$B$18 * 10^6 + 'Cost Components'!$B$9 -> 2.2683247e+09 | K3: ='Cost Components'!$B$18 * 10^6 + 'Cost Components'!$B$9 -> 2.2683247e+09 | ... AF3: ='Cost Components'!$B$18 * 10^6 + 'Cost Components'!$B$9 -> 2.2683247e+09
A4: Amortised CAPEX (€) | B4: 0 | C4: ='Cost Components'!$B$9 -> 5.5428318e+08 | D4: ='Cost Components'!$B$9 -> 5.5428318e+08 | E4: ='Cost Components'!$B$9 -> 5.5428318e+08 | F4: ='Cost Components'!$B$9 -> 5.5428318e+08 | G4: ='Cost Components'!$B$9 -> 5.5428318e+08 | H4: ='Cost Components'!$B$9 -> 5.5428318e+08 | I4: ='Cost Components'!$B$9 -> 5.5428318e+08 | J4: ='Cost Components'!$B$9 -> 5.5428318e+08 | ... AF4: ='Cost Components'!$B$9 -> 5.5428318e+08
A5: Discounted Cost (€) | B5: =B3/((1+'Study Parameters'!$C$4)^'MFSP Baseline'!B2) -> 0 | C5: =C3/((1+'Study Parameters'!$C$4)^'MFSP Baseline'!C2) + C4 -> 2.1413586e+09 | D5: =D3/((1+'Study Parameters'!$C$4)^'MFSP Baseline'!D2) + D4 -> 2.499006e+09 | E5: =E3/((1+'Study Parameters'!$C$4)^'MFSP Baseline'!E2) + E4 -> 2.3549525e+09 | F5: =F3/((1+'Study Parameters'!$C$4)^'MFSP Baseline'!F2) + F4 -> 2.2215695e+09 | G5: =G3/((1+'Study Parameters'!$C$4)^'MFSP Baseline'!G2) + G4 -> 2.0980669e+09 | H5: =H3/((1+'Study Parameters'!$C$4)^'MFSP Baseline'!H2) + H4 -> 1.9837125e+09 | I5: =I3/((1+'Study Parameters'!$C$4)^'MFSP Baseline'!I2) + I4 -> 1.8778289e+09 | J5: =J3/((1+'Study Parameters'!$C$4)^'MFSP Baseline'!J2) + J4 -> 1.7797884e+09 | ... AF5: =AF3/((1+'Study Parameters'!$C$4)^'MFSP Baseline'!AF2) + AF4 -> 7.7970324e+08
A6: Production (l) | B6: 0 | C6: ='Study Parameters'!$C$19 -> 800000000 | D6: ='Study Parameters'!$C$19 -> 800000000 | E6: ='Study Parameters'!$C$19 -> 800000000 | F6: ='Study Parameters'!$C$19 -> 800000000 | G6: ='Study Parameters'!$C$19 -> 800000000 | H6: ='Study Parameters'!$C$19 -> 800000000 | I6: ='Study Parameters'!$C$19 -> 800000000 | J6: ='Study Parameters'!$C$19 -> 800000000 | ... AF6: ='Study Parameters'!$C$19 -> 800000000
A7: Discounted Production (l) | B7: =B6/((1+'Study Parameters'!$C$4)^'MFSP Baseline'!B2) -> 0 | C7: =C6/((1+'Study Parameters'!$C$4)^'MFSP Baseline'!C2) -> 7.4074074e+08 | D7: =D6/((1+'Study Parameters'!$C$4)^'MFSP Baseline'!D2) -> 6.8587106e+08 | E7: =E6/((1+'Study Parameters'!$C$4)^'MFSP Baseline'!E2) -> 6.3506579e+08 | F7: =F6/((1+'Study Parameters'!$C$4)^'MFSP Baseline'!F2) -> 5.8802388e+08 | G7: =G6/((1+'Study Parameters'!$C$4)^'MFSP Baseline'!G2) -> 5.4446656e+08 | H7: =H6/((1+'Study Parameters'!$C$4)^'MFSP Baseline'!H2) -> 5.041357e+08 | I7: =I6/((1+'Study Parameters'!$C$4)^'MFSP Baseline'!I2) -> 4.6679232e+08 | ... AF7: =AF6/((1+'Study Parameters'!$C$4)^'MFSP Baseline'!AF2) -> 79501866
A9: Minimum Fuel Selling Price (€/l) | B9: =SUM(B5:AF5) / SUM(B7:AF7) -> 4.6247535
A11: Amortised Cash Flow Model 2050 EU-North
A12: Year | B12: 0 | C12: 1 | D12: 2 | E12: 3 | F12: 4 | G12: 5 | H12: 6 | I12: 7 | J12: 8 | K12: 9 | L12: 10 | M12: 11 | N12: 12 | O12: 13 | P12: 14 | Q12: 15 | R12: 16 | S12: 17 | T12: 18 | U12: 19 | V12: 20 | W12: 21 | X12: 22 | Y12: 23 | Z12: 24 | AA12: 25 | AB12: 26 | AC12: 27 | AD12: 28 | AE12: 29 | AF12: 30
A13: OPEX (€) | B13: 0 | C13: ='Cost Components'!$B$38*10^6 -> 1.4137451e+09 | D13: ='Cost Components'!$B$38*10^6 -> 1.4137451e+09 | E13: ='Cost Components'!$B$38*10^6 -> 1.4137451e+09 | F13: ='Cost Components'!$B$38*10^6 -> 1.4137451e+09 | G13: ='Cost Components'!$B$38*10^6 -> 1.4137451e+09 | H13: ='Cost Components'!$B$38*10^6 -> 1.4137451e+09 | I13: ='Cost Components'!$B$38*10^6 -> 1.4137451e+09 | J13: ='Cost Components'!$B$38*10^6 -> 1.4137451e+09 | ... AF13: ='Cost Components'!$B$38*10^6 -> 1.4137451e+09
A14: Amortised CAPEX (€) | B14: 0 | C14: ='Cost Components'!$B$29 -> 3.3185929e+08 | D14: ='Cost Components'!$B$29 -> 3.3185929e+08 | E14: ='Cost Components'!$B$29 -> 3.3185929e+08 | F14: ='Cost Components'!$B$29 -> 3.3185929e+08 | G14: ='Cost Components'!$B$29 -> 3.3185929e+08 | H14: ='Cost Components'!$B$29 -> 3.3185929e+08 | I14: ='Cost Components'!$B$29 -> 3.3185929e+08 | J14: ='Cost Components'!$B$29 -> 3.3185929e+08 | ... AF14: ='Cost Components'!$B$29 -> 3.3185929e+08
A15: Discounted Cost (€) | B15: 0 | C15: =C13/((1+'Study Parameters'!$C$4)^'MFSP Baseline'!C12) +C14 -> 1.6408825e+09 | D15: =D13/((1+'Study Parameters'!$C$4)^'MFSP Baseline'!D12) +D14 -> 1.5439178e+09 | E15: =E13/((1+'Study Parameters'!$C$4)^'MFSP Baseline'!E12) +E14 -> 1.4541357e+09 | F15: =F13/((1+'Study Parameters'!$C$4)^'MFSP Baseline'!F12) +F14 -> 1.3710041e+09 | G15: =G13/((1+'Study Parameters'!$C$4)^'MFSP Baseline'!G12) +G14 -> 1.2940304e+09 | H15: =H13/((1+'Study Parameters'!$C$4)^'MFSP Baseline'!H12) +H14 -> 1.2227585e+09 | I15: =I13/((1+'Study Parameters'!$C$4)^'MFSP Baseline'!I12) +I14 -> 1.156766e+09 | J15: =J13/((1+'Study Parameters'!$C$4)^'MFSP Baseline'!J12) +J14 -> 1.0956618e+09 | ... AF15: =AF13/((1+'Study Parameters'!$C$4)^'MFSP Baseline'!AF12) +AF14 -> 4.723535e+08
A16: Production (l) | B16: 0 | C16: ='Study Parameters'!$C$19 -> 800000000 | D16: ='Study Parameters'!$C$19 -> 800000000 | E16: ='Study Parameters'!$C$19 -> 800000000 | F16: ='Study Parameters'!$C$19 -> 800000000 | G16: ='Study Parameters'!$C$19 -> 800000000 | H16: ='Study Parameters'!$C$19 -> 800000000 | I16: ='Study Parameters'!$C$19 -> 800000000 | J16: ='Study Parameters'!$C$19 -> 800000000 | ... AF16: ='Study Parameters'!$C$19 -> 800000000
A17: Discounted Production (l) | B17: 0 | C17: =C16/((1+'Study Parameters'!$C$4)^'MFSP Baseline'!C12) -> 7.4074074e+08 | D17: =D16/((1+'Study Parameters'!$C$4)^'MFSP Baseline'!D12) -> 6.8587106e+08 | E17: =E16/((1+'Study Parameters'!$C$4)^'MFSP Baseline'!E12) -> 6.3506579e+08 | F17: =F16/((1+'Study Parameters'!$C$4)^'MFSP Baseline'!F12) -> 5.8802388e+08 | G17: =G16/((1+'Study Parameters'!$C$4)^'MFSP Baseline'!G12) -> 5.4446656e+08 | H17: =H16/((1+'Study Parameters'!$C$4)^'MFSP Baseline'!H12) -> 5.041357e+08 | I17: =I16/((1+'Study Parameters'!$C$4)^'MFSP Baseline'!I12) -> 4.6679232e+08 | J17: =J16/((1+'Study Parameters'!$C$4)^'MFSP Baseline'!J12) -> 4.3221511e+08 | ... AF17: =AF16/((1+'Study Parameters'!$C$4)^'MFSP Baseline'!AF12) -> 79501866
A19: Minimum Fuel Selling Price (€/l) | B19: =SUM(B15:AF15) / SUM(B17:AF17) -> 2.8726142
A23: Amortised Cash Flow Model 2024 EU-Central
A24: Year | B24: 0 | C24: 1 | D24: 2 | E24: 3 | F24: 4 | G24: 5 | H24: 6 | I24: 7 | J24: 8 | K24: 9 | L24: 10 | M24: 11 | N24: 12 | O24: 13 | P24: 14 | Q24: 15 | R24: 16 | S24: 17 | T24: 18 | U24: 19 | V24: 20 | W24: 21 | X24: 22 | Y24: 23 | Z24: 24 | AA24: 25 | AB24: 26 | AC24: 27 | AD24: 28 | AE24: 29 | AF24: 30
A25: OPEX (€) | B25: 0 | C25: ='Cost Components'!$H$18 * 10^6 -> 1.7061515e+09 | D25: ='Cost Components'!$H$9+'Cost Components'!$H$18 * 10^6 -> 2.1463803e+09 | E25: ='Cost Components'!$H$9+'Cost Components'!$H$18 * 10^6 -> 2.1463803e+09 | F25: ='Cost Components'!$H$9+'Cost Components'!$H$18 * 10^6 -> 2.1463803e+09 | G25: ='Cost Components'!$H$9+'Cost Components'!$H$18 * 10^6 -> 2.1463803e+09 | H25: ='Cost Components'!$H$9+'Cost Components'!$H$18 * 10^6 -> 2.1463803e+09 | I25: ='Cost Components'!$H$9+'Cost Components'!$H$18 * 10^6 -> 2.1463803e+09 | J25: ='Cost Components'!$H$9+'Cost Components'!$H$18 * 10^6 -> 2.1463803e+09 | K25: ='Cost Components'!$H$9+'Cost Components'!$H$18 * 10^6 -> 2.1463803e+09 | ... AF25: ='Cost Components'!$H$9+'Cost Components'!$H$18 * 10^6 -> 2.1463803e+09
A26: Amortised CAPEX (€) | B26: 0 | C26: ='Cost Components'!$H$9 -> 4.4022876e+08 | D26: ='Cost Components'!$H$9 -> 4.4022876e+08 | E26: ='Cost Components'!$H$9 -> 4.4022876e+08 | F26: ='Cost Components'!$H$9 -> 4.4022876e+08 | G26: ='Cost Components'!$H$9 -> 4.4022876e+08 | H26: ='Cost Components'!$H$9 -> 4.4022876e+08 | I26: ='Cost Components'!$H$9 -> 4.4022876e+08 | J26: ='Cost Components'!$H$9 -> 4.4022876e+08 | ... AF26: ='Cost Components'!$H$9 -> 4.4022876e+08
A27: Discounted Cost (€) | B27: =B25/((1+'Study Parameters'!$C$4)^'MFSP Baseline'!B24) -> 0 | C27: =C25/((1+'Study Parameters'!$C$4)^'MFSP Baseline'!C24) +C26 -> 2.0199987e+09 | D27: =D25/((1+'Study Parameters'!$C$4)^'MFSP Baseline'!D24) +D26 -> 2.2804039e+09 | E27: =E25/((1+'Study Parameters'!$C$4)^'MFSP Baseline'!E24) +E26 -> 2.1440946e+09 | F27: =F25/((1+'Study Parameters'!$C$4)^'MFSP Baseline'!F24) +F26 -> 2.0178823e+09 | G27: =G25/((1+'Study Parameters'!$C$4)^'MFSP Baseline'!G24) +G26 -> 1.9010191e+09 | H27: =H25/((1+'Study Parameters'!$C$4)^'MFSP Baseline'!H24) +H26 -> 1.7928124e+09 | I27: =I25/((1+'Study Parameters'!$C$4)^'MFSP Baseline'!I24) +I26 -> 1.692621e+09 | J27: =J25/((1+'Study Parameters'!$C$4)^'MFSP Baseline'!J24) +J26 -> 1.5998512e+09 | ... AF27: =AF25/((1+'Study Parameters'!$C$4)^'MFSP Baseline'!AF24) +AF26 -> 6.535303e+08
A28: Production (l) | B28: 0 | C28: ='Study Parameters'!$C$19 -> 800000000 | D28: ='Study Parameters'!$C$19 -> 800000000 | E28: ='Study Parameters'!$C$19 -> 800000000 | F28: ='Study Parameters'!$C$19 -> 800000000 | G28: ='Study Parameters'!$C$19 -> 800000000 | H28: ='Study Parameters'!$C$19 -> 800000000 | I28: ='Study Parameters'!$C$19 -> 800000000 | J28: ='Study Parameters'!$C$19 -> 800000000 | ... AF28: ='Study Parameters'!$C$19 -> 800000000
A29: Discounted Production (l) | B29: =B28/((1+'Study Parameters'!$C$4)^'MFSP Baseline'!B24) -> 0 | C29: =C28/((1+'Study Parameters'!$C$4)^'MFSP Baseline'!C24) -> 7.4074074e+08 | D29: =D28/((1+'Study Parameters'!$C$4)^'MFSP Baseline'!D24) -> 6.8587106e+08 | E29: =E28/((1+'Study Parameters'!$C$4)^'MFSP Baseline'!E24) -> 6.3506579e+08 | F29: =F28/((1+'Study Parameters'!$C$4)^'MFSP Baseline'!F24) -> 5.8802388e+08 | G29: =G28/((1+'Study Parameters'!$C$4)^'MFSP Baseline'!G24) -> 5.4446656e+08 | H29: =H28/((1+'Study Parameters'!$C$4)^'MFSP Baseline'!H24) -> 5.041357e+08 | I29: =I28/((1+'Study Parameters'!$C$4)^'MFSP Baseline'!I24) -> 4.6679232e+08 | ... AF29: =AF28/((1+'Study Parameters'!$C$4)^'MFSP Baseline'!AF24) -> 79501866
A31: Minimum Fuel Selling Price (€/l) | B31: =SUM(B27:AF27) / SUM(B29:AF29) -> 4.1041303
A33: Amortised Cash Flow Model 2050 EU-Central
A35: Year | B35: 0 | C35: 1 | D35: 2 | E35: 3 | F35: 4 | G35: 5 | H35: 6 | I35: 7 | J35: 8 | K35: 9 | L35: 10 | M35: 11 | N35: 12 | O35: 13 | P35: 14 | Q35: 15 | R35: 16 | S35: 17 | T35: 18 | U35: 19 | V35: 20 | W35: 21 | X35: 22 | Y35: 23 | Z35: 24 | AA35: 25 | AB35: 26 | AC35: 27 | AD35: 28 | AE35: 29 | AF35: 30
A36: OPEX (€) | B36: 0 | C36: ='Cost Components'!$H$38*10^6 -> 1.4169751e+09 | D36: ='Cost Components'!$H$29+'Cost Components'!$H$38*10^6 -> 1.7518545e+09 | E36: ='Cost Components'!$H$29+'Cost Components'!$H$38*10^6 -> 1.7518545e+09 | F36: ='Cost Components'!$H$29+'Cost Components'!$H$38*10^6 -> 1.7518545e+09 | G36: ='Cost Components'!$H$29+'Cost Components'!$H$38*10^6 -> 1.7518545e+09 | H36: ='Cost Components'!$H$29+'Cost Components'!$H$38*10^6 -> 1.7518545e+09 | I36: ='Cost Components'!$H$29+'Cost Components'!$H$38*10^6 -> 1.7518545e+09 | J36: ='Cost Components'!$H$29+'Cost Components'!$H$38*10^6 -> 1.7518545e+09 | K36: ='Cost Components'!$H$29+'Cost Components'!$H$38*10^6 -> 1.7518545e+09 | ... AF36: ='Cost Components'!$H$29+'Cost Components'!$H$38*10^6 -> 1.7518545e+09
A37: Amortized CAPEX (€) | C37: ='Cost Components'!$H$29 -> 3.3487942e+08 | D37: ='Cost Components'!$H$29 -> 3.3487942e+08 | E37: ='Cost Components'!$H$29 -> 3.3487942e+08 | F37: ='Cost Components'!$H$29 -> 3.3487942e+08 | G37: ='Cost Components'!$H$29 -> 3.3487942e+08 | H37: ='Cost Components'!$H$29 -> 3.3487942e+08 | I37: ='Cost Components'!$H$29 -> 3.3487942e+08 | J37: ='Cost Components'!$H$29 -> 3.3487942e+08 | ... AF37: ='Cost Components'!$H$29 -> 3.3487942e+08
A38: Discounted Cost (€) | B38: =B36/((1+'Study Parameters'!$C$4)^'MFSP Baseline'!B35) -> 0 | C38: =C36/((1+'Study Parameters'!$C$4)^'MFSP Baseline'!C35) +C37 -> 1.6468934e+09 | D38: =D36/((1+'Study Parameters'!$C$4)^'MFSP Baseline'!D35) +D37 -> 1.8368123e+09 | E38: =E36/((1+'Study Parameters'!$C$4)^'MFSP Baseline'!E35) +E37 -> 1.725558e+09 | F38: =F36/((1+'Study Parameters'!$C$4)^'MFSP Baseline'!F35) +F37 -> 1.6225448e+09 | G38: =G36/((1+'Study Parameters'!$C$4)^'MFSP Baseline'!G35) +G37 -> 1.5271622e+09 | H38: =H36/((1+'Study Parameters'!$C$4)^'MFSP Baseline'!H35) +H37 -> 1.4388449e+09 | I38: =I36/((1+'Study Parameters'!$C$4)^'MFSP Baseline'!I35) +I37 -> 1.3570697e+09 | J38: =J36/((1+'Study Parameters'!$C$4)^'MFSP Baseline'!J35) +J37 -> 1.2813519e+09 | ... AF38: =AF36/((1+'Study Parameters'!$C$4)^'MFSP Baseline'!AF35) +AF37 -> 5.0897405e+08
A39: Production (l) | B39: 0 | C39: ='Study Parameters'!$C$19 -> 800000000 | D39: ='Study Parameters'!$C$19 -> 800000000 | E39: ='Study Parameters'!$C$19 -> 800000000 | F39: ='Study Parameters'!$C$19 -> 800000000 | G39: ='Study Parameters'!$C$19 -> 800000000 | H39: ='Study Parameters'!$C$19 -> 800000000 | I39: ='Study Parameters'!$C$19 -> 800000000 | J39: ='Study Parameters'!$C$19 -> 800000000 | ... AF39: ='Study Parameters'!$C$19 -> 800000000
A40: Discounted Production (l) | B40: =B39/((1+'Study Parameters'!$C$4)^'MFSP Baseline'!B35) -> 0 | C40: =C39/((1+'Study Parameters'!$C$4)^'MFSP Baseline'!C35) -> 7.4074074e+08 | D40: =D39/((1+'Study Parameters'!$C$4)^'MFSP Baseline'!D35) -> 6.8587106e+08 | E40: =E39/((1+'Study Parameters'!$C$4)^'MFSP Baseline'!E35) -> 6.3506579e+08 | F40: =F39/((1+'Study Parameters'!$C$4)^'MFSP Baseline'!F35) -> 5.8802388e+08 | G40: =G39/((1+'Study Parameters'!$C$4)^'MFSP Baseline'!G35) -> 5.4446656e+08 | H40: =H39/((1+'Study Parameters'!$C$4)^'MFSP Baseline'!H35) -> 5.041357e+08 | I40: =I39/((1+'Study Parameters'!$C$4)^'MFSP Baseline'!I35) -> 4.6679232e+08 | ... AF40: =AF39/((1+'Study Parameters'!$C$4)^'MFSP Baseline'!AF35) -> 79501866
A42: Minimum Fuel Selling Price (€/l) | B42: =SUM(B38:AF38) / SUM(B40:AF40) -> 3.2708823
A46: Amortised Cash Flow Model 2024 EU-South
A48: Year | B48: 0 | C48: 1 | D48: 2 | E48: 3 | F48: 4 | G48: 5 | H48: 6 | I48: 7 | J48: 8 | K48: 9 | L48: 10 | M48: 11 | N48: 12 | O48: 13 | P48: 14 | Q48: 15 | R48: 16 | S48: 17 | T48: 18 | U48: 19 | V48: 20 | W48: 21 | X48: 22 | Y48: 23 | Z48: 24 | AA48: 25 | AB48: 26 | AC48: 27 | AD48: 28 | AE48: 29 | AF48: 30
A49: Cost (€) | B49: 0 | C49: ='Cost Components'!$N$18* 10^6 -> 1.7199615e+09 | D49: ='Cost Components'!$N$18* 10^6 -> 1.7199615e+09 | E49: ='Cost Components'!$N$18* 10^6 -> 1.7199615e+09 | F49: ='Cost Components'!$N$18* 10^6 -> 1.7199615e+09 | G49: ='Cost Components'!$N$18* 10^6 -> 1.7199615e+09 | H49: ='Cost Components'!$N$18* 10^6 -> 1.7199615e+09 | I49: ='Cost Components'!$N$18* 10^6 -> 1.7199615e+09 | J49: ='Cost Components'!$N$18* 10^6 -> 1.7199615e+09 | ... AF49: ='Cost Components'!$N$18* 10^6 -> 1.7199615e+09
A50: Amortized CAPEX (€) | B50: 0 | C50: ='Cost Components'!$N$9 -> 5.6885088e+08 | D50: ='Cost Components'!$N$9 -> 5.6885088e+08 | E50: ='Cost Components'!$N$9 -> 5.6885088e+08 | F50: ='Cost Components'!$N$9 -> 5.6885088e+08 | G50: ='Cost Components'!$N$9 -> 5.6885088e+08 | H50: ='Cost Components'!$N$9 -> 5.6885088e+08 | I50: ='Cost Components'!$N$9 -> 5.6885088e+08 | J50: ='Cost Components'!$N$9 -> 5.6885088e+08 | ... AF50: ='Cost Components'!$N$9 -> 5.6885088e+08
A51: Discounted Cost (€) | B51: 0 | C51: =C49/((1+'Study Parameters'!$C$4)^'MFSP Baseline'!C48) + C50 -> 2.1614078e+09 | D51: =D49/((1+'Study Parameters'!$C$4)^'MFSP Baseline'!D48) + D50 -> 2.0434406e+09 | E51: =E49/((1+'Study Parameters'!$C$4)^'MFSP Baseline'!E48) + E50 -> 1.9342118e+09 | F51: =F49/((1+'Study Parameters'!$C$4)^'MFSP Baseline'!F48) + F50 -> 1.8330739e+09 | G51: =G49/((1+'Study Parameters'!$C$4)^'MFSP Baseline'!G48) + G50 -> 1.7394278e+09 | H51: =H49/((1+'Study Parameters'!$C$4)^'MFSP Baseline'!H48) + H50 -> 1.6527184e+09 | I51: =I49/((1+'Study Parameters'!$C$4)^'MFSP Baseline'!I48) + I50 -> 1.5724319e+09 | J51: =J49/((1+'Study Parameters'!$C$4)^'MFSP Baseline'!J48) + J50 -> 1.4980926e+09 | ... AF51: =AF49/((1+'Study Parameters'!$C$4)^'MFSP Baseline'!AF48) + AF50 -> 7.3977607e+08
A52: Production (l) | B52: 0 | C52: ='Study Parameters'!$C$19 -> 800000000 | D52: ='Study Parameters'!$C$19 -> 800000000 | E52: ='Study Parameters'!$C$19 -> 800000000 | F52: ='Study Parameters'!$C$19 -> 800000000 | G52: ='Study Parameters'!$C$19 -> 800000000 | H52: ='Study Parameters'!$C$19 -> 800000000 | I52: ='Study Parameters'!$C$19 -> 800000000 | J52: ='Study Parameters'!$C$19 -> 800000000 | ... AF52: ='Study Parameters'!$C$19 -> 800000000
A53: Discounted Production (l) | B53: 0 | C53: =C52/((1+'Study Parameters'!$C$4)^'MFSP Baseline'!C48) -> 7.4074074e+08 | D53: =D52/((1+'Study Parameters'!$C$4)^'MFSP Baseline'!D48) -> 6.8587106e+08 | E53: =E52/((1+'Study Parameters'!$C$4)^'MFSP Baseline'!E48) -> 6.3506579e+08 | F53: =F52/((1+'Study Parameters'!$C$4)^'MFSP Baseline'!F48) -> 5.8802388e+08 | G53: =G52/((1+'Study Parameters'!$C$4)^'MFSP Baseline'!G48) -> 5.4446656e+08 | H53: =H52/((1+'Study Parameters'!$C$4)^'MFSP Baseline'!H48) -> 5.041357e+08 | I53: =I52/((1+'Study Parameters'!$C$4)^'MFSP Baseline'!I48) -> 4.6679232e+08 | J53: =J52/((1+'Study Parameters'!$C$4)^'MFSP Baseline'!J48) -> 4.3221511e+08 | ... AF53: =AF52/((1+'Study Parameters'!$C$4)^'MFSP Baseline'!AF48) -> 79501866
A55: Minimum Fuel Selling Price (€/l) | B55: =SUM(B51:AF51) / SUM(B53:AF53) -> 4.0448105
A57: Amortised Cash Flow Model 2050 EU-Central
A58: Year | B58: 0 | C58: 1 | D58: 2 | E58: 3 | F58: 4 | G58: 5 | H58: 6 | I58: 7 | J58: 8 | K58: 9 | L58: 10 | M58: 11 | N58: 12 | O58: 13 | P58: 14 | Q58: 15 | R58: 16 | S58: 17 | T58: 18 | U58: 19 | V58: 20 | W58: 21 | X58: 22 | Y58: 23 | Z58: 24 | AA58: 25 | AB58: 26 | AC58: 27 | AD58: 28 | AE58: 29 | AF58: 30
A59: Cost (€) | B59: 0 | C59: ='Cost Components'!$N$38*10^6 -> 1.4147451e+09 | D59: ='Cost Components'!$N$38*10^6 -> 1.4147451e+09 | E59: ='Cost Components'!$N$38*10^6 -> 1.4147451e+09 | F59: ='Cost Components'!$N$38*10^6 -> 1.4147451e+09 | G59: ='Cost Components'!$N$38*10^6 -> 1.4147451e+09 | H59: ='Cost Components'!$N$38*10^6 -> 1.4147451e+09 | I59: ='Cost Components'!$N$38*10^6 -> 1.4147451e+09 | J59: ='Cost Components'!$N$38*10^6 -> 1.4147451e+09 | ... AF59: ='Cost Components'!$N$38*10^6 -> 1.4147451e+09
A60: Amortized CAPEX (€) | B60: 0 | C60: ='Cost Components'!$N$29 -> 3.3105984e+08 | D60: ='Cost Components'!$N$29 -> 3.3105984e+08 | E60: ='Cost Components'!$N$29 -> 3.3105984e+08 | F60: ='Cost Components'!$N$29 -> 3.3105984e+08 | G60: ='Cost Components'!$N$29 -> 3.3105984e+08 | H60: ='Cost Components'!$N$29 -> 3.3105984e+08 | I60: ='Cost Components'!$N$29 -> 3.3105984e+08 | J60: ='Cost Components'!$N$29 -> 3.3105984e+08 | ... AF60: ='Cost Components'!$N$29 -> 3.3105984e+08
A61: Discounted Cost (€) | B61: 0 | C61: =C59/((1+'Study Parameters'!$C$4)^'MFSP Baseline'!C58) + C60 -> 1.641009e+09 | D61: =D59/((1+'Study Parameters'!$C$4)^'MFSP Baseline'!D58) + D60 -> 1.5439757e+09 | E61: =E59/((1+'Study Parameters'!$C$4)^'MFSP Baseline'!E58) + E60 -> 1.4541301e+09 | F61: =F59/((1+'Study Parameters'!$C$4)^'MFSP Baseline'!F58) + F60 -> 1.3709397e+09 | G61: =G59/((1+'Study Parameters'!$C$4)^'MFSP Baseline'!G58) + G60 -> 1.2939116e+09 | H61: =H59/((1+'Study Parameters'!$C$4)^'MFSP Baseline'!H58) + H60 -> 1.2225892e+09 | I61: =I59/((1+'Study Parameters'!$C$4)^'MFSP Baseline'!I58) + I60 -> 1.15655e+09 | J61: =J59/((1+'Study Parameters'!$C$4)^'MFSP Baseline'!J58) + J60 -> 1.0954026e+09 | ... AF61: =AF59/((1+'Study Parameters'!$C$4)^'MFSP Baseline'!AF58) + AF60 -> 4.7165343e+08
A62: Production (l) | B62: 0 | C62: ='Study Parameters'!$C$19 -> 800000000 | D62: ='Study Parameters'!$C$19 -> 800000000 | E62: ='Study Parameters'!$C$19 -> 800000000 | F62: ='Study Parameters'!$C$19 -> 800000000 | G62: ='Study Parameters'!$C$19 -> 800000000 | H62: ='Study Parameters'!$C$19 -> 800000000 | I62: ='Study Parameters'!$C$19 -> 800000000 | J62: ='Study Parameters'!$C$19 -> 800000000 | ... AF62: ='Study Parameters'!$C$19 -> 800000000
A63: Discounted Production (l) | B63: 0 | C63: =C62/((1+'Study Parameters'!$C$4)^'MFSP Baseline'!C58) -> 7.4074074e+08 | D63: =D62/((1+'Study Parameters'!$C$4)^'MFSP Baseline'!D58) -> 6.8587106e+08 | E63: =E62/((1+'Study Parameters'!$C$4)^'MFSP Baseline'!E58) -> 6.3506579e+08 | F63: =F62/((1+'Study Parameters'!$C$4)^'MFSP Baseline'!F58) -> 5.8802388e+08 | G63: =G62/((1+'Study Parameters'!$C$4)^'MFSP Baseline'!G58) -> 5.4446656e+08 | H63: =H62/((1+'Study Parameters'!$C$4)^'MFSP Baseline'!H58) -> 5.041357e+08 | I63: =I62/((1+'Study Parameters'!$C$4)^'MFSP Baseline'!I58) -> 4.6679232e+08 | J63: =J62/((1+'Study Parameters'!$C$4)^'MFSP Baseline'!J58) -> 4.3221511e+08 | ... AF63: =AF62/((1+'Study Parameters'!$C$4)^'MFSP Baseline'!AF58) -> 79501866
A65: Minimum Fuel Selling Price (€/l) | B65: =SUM(B61:AF61) / SUM(B63:AF63) -> 2.8712012

Sheet MFSP Electricity
A1: Amortised Cash Flow Model 2024 EU-North
A2: Year | B2: 0 | C2: 1 | D2: 2 | E2: 3 | F2: 4 | G2: 5 | H2: 6 | I2: 7 | J2: 8 | K2: 9 | L2: 10 | M2: 11 | N2: 12 | O2: 13 | P2: 14 | Q2: 15 | R2: 16 | S2: 17 | T2: 18 | U2: 19 | V2: 20 | W2: 21 | X2: 22 | Y2: 23 | Z2: 24 | AA2: 25 | AB2: 26 | AC2: 27 | AD2: 28 | AE2: 29 | AF2: 30
A3: Cost (€) | B3: 0 | C3: ='Cost Components'!$B$43 * 10^6 -> 1.6948972e+09 | D3: ='Cost Components'!$B$43 * 10^6 -> 1.6948972e+09 | E3: ='Cost Components'!$B$43 * 10^6 -> 1.6948972e+09 | F3: ='Cost Components'!$B$43 * 10^6 -> 1.6948972e+09 | G3: ='Cost Components'!$B$43 * 10^6 -> 1.6948972e+09 | H3: ='Cost Components'!$B$43 * 10^6 -> 1.6948972e+09 | I3: ='Cost Components'!$B$43 * 10^6 -> 1.6948972e+09 | J3: ='Cost Components'!$B$43 * 10^6 -> 1.6948972e+09 | ... AF3: ='Cost Components'!$B$43 * 10^6 -> 1.6948972e+09
A4: Amortised CAPEX (€) | B4: 0 | C4: ='Cost Components'!$B$9 -> 5.5428318e+08 | D4: ='Cost Components'!$B$9 -> 5.5428318e+08 | E4: ='Cost Components'!$B$9 -> 5.5428318e+08 | F4: ='Cost Components'!$B$9 -> 5.5428318e+08 | G4: ='Cost Components'!$B$9 -> 5.5428318e+08 | H4: ='Cost Components'!$B$9 -> 5.5428318e+08 | I4: ='Cost Components'!$B$9 -> 5.5428318e+08 | J4: ='Cost Components'!$B$9 -> 5.5428318e+08 | ... AF4: ='Cost Components'!$B$9 -> 5.5428318e+08
A5: Discounted Cost (€) | B5: =B3/((1+'Study Parameters'!$C$4)^'MFSP Baseline'!B2) -> 0 | C5: =C3/((1+'Study Parameters'!$C$4)^'MFSP Baseline'!C2) + C4 -> 2.1236325e+09 | D5: =D3/((1+'Study Parameters'!$C$4)^'MFSP Baseline'!D2) + D4 -> 2.0073844e+09 | E5: =E3/((1+'Study Parameters'!$C$4)^'MFSP Baseline'!E2) + E4 -> 1.8997473e+09 | F5: =F3/((1+'Study Parameters'!$C$4)^'MFSP Baseline'!F2) + F4 -> 1.8000833e+09 | G5: =G3/((1+'Study Parameters'!$C$4)^'MFSP Baseline'!G2) + G4 -> 1.7078018e+09 | H5: =H3/((1+'Study Parameters'!$C$4)^'MFSP Baseline'!H2) + H4 -> 1.6223559e+09 | I5: =I3/((1+'Study Parameters'!$C$4)^'MFSP Baseline'!I2) + I4 -> 1.5432394e+09 | J5: =J3/((1+'Study Parameters'!$C$4)^'MFSP Baseline'!J2) + J4 -> 1.4699834e+09 | ... AF5: =AF3/((1+'Study Parameters'!$C$4)^'MFSP Baseline'!AF2) + AF4 -> 7.2271755e+08
A6: Production (l) | B6: 0 | C6: ='Study Parameters'!$C$19 -> 800000000 | D6: ='Study Parameters'!$C$19 -> 800000000 | E6: ='Study Parameters'!$C$19 -> 800000000 | F6: ='Study Parameters'!$C$19 -> 800000000 | G6: ='Study Parameters'!$C$19 -> 800000000 | H6: ='Study Parameters'!$C$19 -> 800000000 | I6: ='Study Parameters'!$C$19 -> 800000000 | J6: ='Study Parameters'!$C$19 -> 800000000 | ... AF6: ='Study Parameters'!$C$19 -> 800000000
A7: Discounted Production (l) | B7: =B6/((1+'Study Parameters'!$C$4)^'MFSP Baseline'!B2) -> 0 | C7: =C6/((1+'Study Parameters'!$C$4)^'MFSP Baseline'!C2) -> 7.4074074e+08 | D7: =D6/((1+'Study Parameters'!$C$4)^'MFSP Baseline'!D2) -> 6.8587106e+08 | E7: =E6/((1+'Study Parameters'!$C$4)^'MFSP Baseline'!E2) -> 6.3506579e+08 | F7: =F6/((1+'Study Parameters'!$C$4)^'MFSP Baseline'!F2) -> 5.8802388e+08 | G7: =G6/((1+'Study Parameters'!$C$4)^'MFSP Baseline'!G2) -> 5.4446656e+08 | H7: =H6/((1+'Study Parameters'!$C$4)^'MFSP Baseline'!H2) -> 5.041357e+08 | I7: =I6/((1+'Study Parameters'!$C$4)^'MFSP Baseline'!I2) -> 4.6679232e+08 | ... AF7: =AF6/((1+'Study Parameters'!$C$4)^'MFSP Baseline'!AF2) -> 79501866
A9: Minimum Fuel Selling Price (€/l) | B9: =SUM(B5:AF5) / SUM(B7:AF7) -> 3.9649548
A11: Amortised Cash Flow Model 2050 EU-North
A12: Year | B12: 0 | C12: 1 | D12: 2 | E12: 3 | F12: 4 | G12: 5 | H12: 6 | I12: 7 | J12: 8 | K12: 9 | L12: 10 | M12: 11 | N12: 12 | O12: 13 | P12: 14 | Q12: 15 | R12: 16 | S12: 17 | T12: 18 | U12: 19 | V12: 20 | W12: 21 | X12: 22 | Y12: 23 | Z12: 24 | AA12: 25 | AB12: 26 | AC12: 27 | AD12: 28 | AE12: 29 | AF12: 30
A13: Cost (€) | B13: 0 | C13: ='Cost Components'!$B$52*10^6 -> 6.2883021e+08 | D13: ='Cost Components'!$B$52*10^6 -> 6.2883021e+08 | E13: ='Cost Components'!$B$52*10^6 -> 6.2883021e+08 | F13: ='Cost Components'!$B$52*10^6 -> 6.2883021e+08 | G13: ='Cost Components'!$B$52*10^6 -> 6.2883021e+08 | H13: ='Cost Components'!$B$52*10^6 -> 6.2883021e+08 | I13: ='Cost Components'!$B$52*10^6 -> 6.2883021e+08 | J13: ='Cost Components'!$B$52*10^6 -> 6.2883021e+08 | ... AF13: ='Cost Components'!$B$52*10^6 -> 6.2883021e+08
A14: Amortised CAPEX (€) | B14: 0 | C14: ='Cost Components'!$B$29 -> 3.3185929e+08 | D14: ='Cost Components'!$B$29 -> 3.3185929e+08 | E14: ='Cost Components'!$B$29 -> 3.3185929e+08 | F14: ='Cost Components'!$B$29 -> 3.3185929e+08 | G14: ='Cost Components'!$B$29 -> 3.3185929e+08 | H14: ='Cost Components'!$B$29 -> 3.3185929e+08 | I14: ='Cost Components'!$B$29 -> 3.3185929e+08 | J14: ='Cost Components'!$B$29 -> 3.3185929e+08 | ... AF14: ='Cost Components'!$B$29 -> 3.3185929e+08
A15: Discounted Cost (€) | B15: 0 | C15: =C13/((1+'Study Parameters'!$C$4)^'MFSP Baseline'!C12) + C14 -> 9.1410949e+08 | D15: =D13/((1+'Study Parameters'!$C$4)^'MFSP Baseline'!D12) + D14 -> 8.7097984e+08 | E15: =E13/((1+'Study Parameters'!$C$4)^'MFSP Baseline'!E12) + E14 -> 8.3104499e+08 | F15: =F13/((1+'Study Parameters'!$C$4)^'MFSP Baseline'!F12) + F14 -> 7.9406827e+08 | G15: =G13/((1+'Study Parameters'!$C$4)^'MFSP Baseline'!G12) + G14 -> 7.5983057e+08 | H15: =H13/((1+'Study Parameters'!$C$4)^'MFSP Baseline'!H12) + H14 -> 7.2812899e+08 | I15: =I13/((1+'Study Parameters'!$C$4)^'MFSP Baseline'!I12) + I14 -> 6.9877568e+08 | J15: =J13/((1+'Study Parameters'!$C$4)^'MFSP Baseline'!J12) + J14 -> 6.7159669e+08 | ... AF15: =AF13/((1+'Study Parameters'!$C$4)^'MFSP Baseline'!AF12) + AF14 -> 3.9435076e+08
A16: Production (l) | B16: 0 | C16: ='Study Parameters'!$C$19 -> 800000000 | D16: ='Study Parameters'!$C$19 -> 800000000 | E16: ='Study Parameters'!$C$19 -> 800000000 | F16: ='Study Parameters'!$C$19 -> 800000000 | G16: ='Study Parameters'!$C$19 -> 800000000 | H16: ='Study Parameters'!$C$19 -> 800000000 | I16: ='Study Parameters'!$C$19 -> 800000000 | J16: ='Study Parameters'!$C$19 -> 800000000 | ... AF16: ='Study Parameters'!$C$19 -> 800000000
A17: Discounted Production (l) | B17: 0 | C17: =C16/((1+'Study Parameters'!$C$4)^'MFSP Baseline'!C12) -> 7.4074074e+08 | D17: =D16/((1+'Study Parameters'!$C$4)^'MFSP Baseline'!D12) -> 6.8587106e+08 | E17: =E16/((1+'Study Parameters'!$C$4)^'MFSP Baseline'!E12) -> 6.3506579e+08 | F17: =F16/((1+'Study Parameters'!$C$4)^'MFSP Baseline'!F12) -> 5.8802388e+08 | G17: =G16/((1+'Study Parameters'!$C$4)^'MFSP Baseline'!G12) -> 5.4446656e+08 | H17: =H16/((1+'Study Parameters'!$C$4)^'MFSP Baseline'!H12) -> 5.041357e+08 | I17: =I16/((1+'Study Parameters'!$C$4)^'MFSP Baseline'!I12) -> 4.6679232e+08 | J17: =J16/((1+'Study Parameters'!$C$4)^'MFSP Baseline'!J12) -> 4.3221511e+08 | ... AF17: =AF16/((1+'Study Parameters'!$C$4)^'MFSP Baseline'!AF12) -> 79501866
A19: Minimum Fuel Selling Price (€/l) | B19: =SUM(B15:AF15) / SUM(B17:AF17) -> 1.8914706
A23: Amortised Cash Flow Model 2024 EU-Central
A24: Year | B24: 0 | C24: 1 | D24: 2 | E24: 3 | F24: 4 | G24: 5 | H24: 6 | I24: 7 | J24: 8 | K24: 9 | L24: 10 | M24: 11 | N24: 12 | O24: 13 | P24: 14 | Q24: 15 | R24: 16 | S24: 17 | T24: 18 | U24: 19 | V24: 20 | W24: 21 | X24: 22 | Y24: 23 | Z24: 24 | AA24: 25 | AB24: 26 | AC24: 27 | AD24: 28 | AE24: 29 | AF24: 30
A25: Cost (€) | B25: 0 | C25: ='Cost Components'!$H$43 * 10^6 -> 1.6870072e+09 | D25: ='Cost Components'!$H$43 * 10^6 -> 1.6870072e+09 | E25: ='Cost Components'!$H$43 * 10^6 -> 1.6870072e+09 | F25: ='Cost Components'!$H$43 * 10^6 -> 1.6870072e+09 | G25: ='Cost Components'!$H$43 * 10^6 -> 1.6870072e+09 | H25: ='Cost Components'!$H$43 * 10^6 -> 1.6870072e+09 | I25: ='Cost Components'!$H$43 * 10^6 -> 1.6870072e+09 | J25: ='Cost Components'!$H$43 * 10^6 -> 1.6870072e+09 | ... AF25: ='Cost Components'!$H$43 * 10^6 -> 1.6870072e+09
A26: Amortised CAPEX (€) | B26: 0 | C26: ='Cost Components'!$H$9 -> 4.4022876e+08 | D26: ='Cost Components'!$H$9 -> 4.4022876e+08 | E26: ='Cost Components'!$H$9 -> 4.4022876e+08 | F26: ='Cost Components'!$H$9 -> 4.4022876e+08 | G26: ='Cost Components'!$H$9 -> 4.4022876e+08 | H26: ='Cost Components'!$H$9 -> 4.4022876e+08 | I26: ='Cost Components'!$H$9 -> 4.4022876e+08 | J26: ='Cost Components'!$H$9 -> 4.4022876e+08 | ... AF26: ='Cost Components'!$H$9 -> 4.4022876e+08
A27: Discounted Cost (€) | B27: =B25/((1+'Study Parameters'!$C$4)^'MFSP Baseline'!B24) -> 0 | C27: =C25/((1+'Study Parameters'!$C$4)^'MFSP Baseline'!C24) + C26 -> 2.0022725e+09 | D27: =D25/((1+'Study Parameters'!$C$4)^'MFSP Baseline'!D24) + D26 -> 1.8865656e+09 | E27: =E25/((1+'Study Parameters'!$C$4)^'MFSP Baseline'!E24) + E26 -> 1.7794295e+09 | F27: =F25/((1+'Study Parameters'!$C$4)^'MFSP Baseline'!F24) + F26 -> 1.6802294e+09 | G27: =G25/((1+'Study Parameters'!$C$4)^'MFSP Baseline'!G24) + G26 -> 1.5883775e+09 | H27: =H25/((1+'Study Parameters'!$C$4)^'MFSP Baseline'!H24) + H26 -> 1.5033295e+09 | I27: =I25/((1+'Study Parameters'!$C$4)^'MFSP Baseline'!I24) + I26 -> 1.4245813e+09 | J27: =J25/((1+'Study Parameters'!$C$4)^'MFSP Baseline'!J24) + J26 -> 1.3516663e+09 | ... AF27: =AF25/((1+'Study Parameters'!$C$4)^'MFSP Baseline'!AF24) + AF26 -> 6.0787904e+08
A28: Production (l) | B28: 0 | C28: ='Study Parameters'!$C$19 -> 800000000 | D28: ='Study Parameters'!$C$19 -> 800000000 | E28: ='Study Parameters'!$C$19 -> 800000000 | F28: ='Study Parameters'!$C$19 -> 800000000 | G28: ='Study Parameters'!$C$19 -> 800000000 | H28: ='Study Parameters'!$C$19 -> 800000000 | I28: ='Study Parameters'!$C$19 -> 800000000 | J28: ='Study Parameters'!$C$19 -> 800000000 | ... AF28: ='Study Parameters'!$C$19 -> 800000000
A29: Discounted Production (l) | B29: =B28/((1+'Study Parameters'!$C$4)^'MFSP Baseline'!B24) -> 0 | C29: =C28/((1+'Study Parameters'!$C$4)^'MFSP Baseline'!C24) -> 7.4074074e+08 | D29: =D28/((1+'Study Parameters'!$C$4)^'MFSP Baseline'!D24) -> 6.8587106e+08 | E29: =E28/((1+'Study Parameters'!$C$4)^'MFSP Baseline'!E24) -> 6.3506579e+08 | F29: =F28/((1+'Study Parameters'!$C$4)^'MFSP Baseline'!F24) -> 5.8802388e+08 | G29: =G28/((1+'Study Parameters'!$C$4)^'MFSP Baseline'!G24) -> 5.4446656e+08 | H29: =H28/((1+'Study Parameters'!$C$4)^'MFSP Baseline'!H24) -> 5.041357e+08 | I29: =I28/((1+'Study Parameters'!$C$4)^'MFSP Baseline'!I24) -> 4.6679232e+08 | ... AF29: =AF28/((1+'Study Parameters'!$C$4)^'MFSP Baseline'!AF24) -> 79501866
A31: Minimum Fuel Selling Price (€/l) | B31: =SUM(B27:AF27) / SUM(B29:AF29) -> 3.5751737
A33: Amortised Cash Flow Model 2050 EU-Central
A35: Year | B35: 0 | C35: 1 | D35: 2 | E35: 3 | F35: 4 | G35: 5 | H35: 6 | I35: 7 | J35: 8 | K35: 9 | L35: 10 | M35: 11 | N35: 12 | O35: 13 | P35: 14 | Q35: 15 | R35: 16 | S35: 17 | T35: 18 | U35: 19 | V35: 20 | W35: 21 | X35: 22 | Y35: 23 | Z35: 24 | AA35: 25 | AB35: 26 | AC35: 27 | AD35: 28 | AE35: 29 | AF35: 30
A36: Cost (€) | B36: 0 | C36: ='Cost Components'!$H$52*10^6 -> 6.3206021e+08 | D36: ='Cost Components'!$H$52*10^6 -> 6.3206021e+08 | E36: ='Cost Components'!$H$52*10^6 -> 6.3206021e+08 | F36: ='Cost Components'!$H$52*10^6 -> 6.3206021e+08 | G36: ='Cost Components'!$H$52*10^6 -> 6.3206021e+08 | H36: ='Cost Components'!$H$52*10^6 -> 6.3206021e+08 | I36: ='Cost Components'!$H$52*10^6 -> 6.3206021e+08 | J36: ='Cost Components'!$H$52*10^6 -> 6.3206021e+08 | ... AF36: ='Cost Components'!$H$52*10^6 -> 6.3206021e+08
A37: Amortised CAPEX (€) | B37: 0 | C37: ='Cost Components'!$H$29 -> 3.3487942e+08 | D37: ='Cost Components'!$H$29 -> 3.3487942e+08 | E37: ='Cost Components'!$H$29 -> 3.3487942e+08 | F37: ='Cost Components'!$H$29 -> 3.3487942e+08 | G37: ='Cost Components'!$H$29 -> 3.3487942e+08 | H37: ='Cost Components'!$H$29 -> 3.3487942e+08 | I37: ='Cost Components'!$H$29 -> 3.3487942e+08 | J37: ='Cost Components'!$H$29 -> 3.3487942e+08 | ... AF37: ='Cost Components'!$H$29 -> 3.3487942e+08
A38: Discounted Cost (€) | B38: =B36/((1+'Study Parameters'!$C$4)^'MFSP Baseline'!B35) -> 0 | C38: =C36/((1+'Study Parameters'!$C$4)^'MFSP Baseline'!C35)+C37 -> 9.2012036e+08 | D38: =D36/((1+'Study Parameters'!$C$4)^'MFSP Baseline'!D35)+D37 -> 8.7676918e+08 | E38: =E36/((1+'Study Parameters'!$C$4)^'MFSP Baseline'!E35)+E37 -> 8.366292e+08 | F38: =F36/((1+'Study Parameters'!$C$4)^'MFSP Baseline'!F35)+F37 -> 7.9946255e+08 | G38: =G36/((1+'Study Parameters'!$C$4)^'MFSP Baseline'!G35)+G37 -> 7.6504898e+08 | H38: =H36/((1+'Study Parameters'!$C$4)^'MFSP Baseline'!H35)+H37 -> 7.3318457e+08 | I38: =I36/((1+'Study Parameters'!$C$4)^'MFSP Baseline'!I35)+I37 -> 7.0368049e+08 | J38: =J36/((1+'Study Parameters'!$C$4)^'MFSP Baseline'!J35)+J37 -> 6.7636189e+08 | ... AF38: =AF36/((1+'Study Parameters'!$C$4)^'MFSP Baseline'!AF35)+AF37 -> 3.9769188e+08
A39: Production (l) | B39: 0 | C39: ='Study Parameters'!$C$19 -> 800000000 | D39: ='Study Parameters'!$C$19 -> 800000000 | E39: ='Study Parameters'!$C$19 -> 800000000 | F39: ='Study Parameters'!$C$19 -> 800000000 | G39: ='Study Parameters'!$C$19 -> 800000000 | H39: ='Study Parameters'!$C$19 -> 800000000 | I39: ='Study Parameters'!$C$19 -> 800000000 | J39: ='Study Parameters'!$C$19 -> 800000000 | ... AF39: ='Study Parameters'!$C$19 -> 800000000
A40: Discounted Production (l) | B40: =B39/((1+'Study Parameters'!$C$4)^'MFSP Baseline'!B35) -> 0 | C40: =C39/((1+'Study Parameters'!$C$4)^'MFSP Baseline'!C35) -> 7.4074074e+08 | D40: =D39/((1+'Study Parameters'!$C$4)^'MFSP Baseline'!D35) -> 6.8587106e+08 | E40: =E39/((1+'Study Parameters'!$C$4)^'MFSP Baseline'!E35) -> 6.3506579e+08 | F40: =F39/((1+'Study Parameters'!$C$4)^'MFSP Baseline'!F35) -> 5.8802388e+08 | G40: =G39/((1+'Study Parameters'!$C$4)^'MFSP Baseline'!G35) -> 5.4446656e+08 | H40: =H39/((1+'Study Parameters'!$C$4)^'MFSP Baseline'!H35) -> 5.041357e+08 | I40: =I39/((1+'Study Parameters'!$C$4)^'MFSP Baseline'!I35) -> 4.6679232e+08 | ... AF40: =AF39/((1+'Study Parameters'!$C$4)^'MFSP Baseline'!AF35) -> 79501866
A42: Minimum Fuel Selling Price (€/l) | B42: =SUM(B38:AF38) / SUM(B40:AF40) -> 1.9055683
A46: Amortised Cash Flow Model 2024 EU-South
A48: Year | B48: 0 | C48: 1 | D48: 2 | E48: 3 | F48: 4 | G48: 5 | H48: 6 | I48: 7 | J48: 8 | K48: 9 | L48: 10 | M48: 11 | N48: 12 | O48: 13 | P48: 14 | Q48: 15 | R48: 16 | S48: 17 | T48: 18 | U48: 19 | V48: 20 | W48: 21 | X48: 22 | Y48: 23 | Z48: 24 | AA48: 25 | AB48: 26 | AC48: 27 | AD48: 28 | AE48: 29 | AF48: 30
A49: Cost (€) | B49: 0 | C49: ='Cost Components'!$N$43 * 10^6 -> 1.7008172e+09 | D49: ='Cost Components'!$N$43 * 10^6 -> 1.7008172e+09 | E49: ='Cost Components'!$N$43 * 10^6 -> 1.7008172e+09 | F49: ='Cost Components'!$N$43 * 10^6 -> 1.7008172e+09 | G49: ='Cost Components'!$N$43 * 10^6 -> 1.7008172e+09 | H49: ='Cost Components'!$N$43 * 10^6 -> 1.7008172e+09 | I49: ='Cost Components'!$N$43 * 10^6 -> 1.7008172e+09 | J49: ='Cost Components'!$N$43 * 10^6 -> 1.7008172e+09 | ... AF49: ='Cost Components'!$N$43 * 10^6 -> 1.7008172e+09
A50: Amortised CAPEX (€) | B50: 0 | C50: ='Cost Components'!$N$9 -> 5.6885088e+08 | D50: ='Cost Components'!$N$9 -> 5.6885088e+08 | E50: ='Cost Components'!$N$9 -> 5.6885088e+08 | F50: ='Cost Components'!$N$9 -> 5.6885088e+08 | G50: ='Cost Components'!$N$9 -> 5.6885088e+08 | H50: ='Cost Components'!$N$9 -> 5.6885088e+08 | I50: ='Cost Components'!$N$9 -> 5.6885088e+08 | J50: ='Cost Components'!$N$9 -> 5.6885088e+08 | ... AF50: ='Cost Components'!$N$9 -> 5.6885088e+08
A51: Discounted Cost (€) | B51: 0 | C51: =C49/((1+'Study Parameters'!$C$4)^'MFSP Baseline'!C48) + C50 -> 2.1436817e+09 | D51: =D49/((1+'Study Parameters'!$C$4)^'MFSP Baseline'!D48) + D50 -> 2.0270275e+09 | E51: =E49/((1+'Study Parameters'!$C$4)^'MFSP Baseline'!E48) + E50 -> 1.9190144e+09 | F51: =F49/((1+'Study Parameters'!$C$4)^'MFSP Baseline'!F48) + F50 -> 1.8190023e+09 | G51: =G49/((1+'Study Parameters'!$C$4)^'MFSP Baseline'!G48) + G50 -> 1.7263985e+09 | H51: =H49/((1+'Study Parameters'!$C$4)^'MFSP Baseline'!H48) + H50 -> 1.6406542e+09 | I51: =I49/((1+'Study Parameters'!$C$4)^'MFSP Baseline'!I48) + I50 -> 1.5612614e+09 | J51: =J49/((1+'Study Parameters'!$C$4)^'MFSP Baseline'!J48) + J50 -> 1.4877495e+09 | ... AF51: =AF49/((1+'Study Parameters'!$C$4)^'MFSP Baseline'!AF48) + AF50 -> 7.3787356e+08
A52: Production (l) | B52: 0 | C52: ='Study Parameters'!$C$19 -> 800000000 | D52: ='Study Parameters'!$C$19 -> 800000000 | E52: ='Study Parameters'!$C$19 -> 800000000 | F52: ='Study Parameters'!$C$19 -> 800000000 | G52: ='Study Parameters'!$C$19 -> 800000000 | H52: ='Study Parameters'!$C$19 -> 800000000 | I52: ='Study Parameters'!$C$19 -> 800000000 | J52: ='Study Parameters'!$C$19 -> 800000000 | ... AF52: ='Study Parameters'!$C$19 -> 800000000
A53: Discounted Production (l) | B53: 0 | C53: =C52/((1+'Study Parameters'!$C$4)^'MFSP Baseline'!C48) -> 7.4074074e+08 | D53: =D52/((1+'Study Parameters'!$C$4)^'MFSP Baseline'!D48) -> 6.8587106e+08 | E53: =E52/((1+'Study Parameters'!$C$4)^'MFSP Baseline'!E48) -> 6.3506579e+08 | F53: =F52/((1+'Study Parameters'!$C$4)^'MFSP Baseline'!F48) -> 5.8802388e+08 | G53: =G52/((1+'Study Parameters'!$C$4)^'MFSP Baseline'!G48) -> 5.4446656e+08 | H53: =H52/((1+'Study Parameters'!$C$4)^'MFSP Baseline'!H48) -> 5.041357e+08 | I53: =I52/((1+'Study Parameters'!$C$4)^'MFSP Baseline'!I48) -> 4.6679232e+08 | J53: =J52/((1+'Study Parameters'!$C$4)^'MFSP Baseline'!J48) -> 4.3221511e+08 | ... AF53: =AF52/((1+'Study Parameters'!$C$4)^'MFSP Baseline'!AF48) -> 79501866
A55: Minimum Fuel Selling Price (€/l) | B55: =SUM(B51:AF51) / SUM(B53:AF53) -> 4.0208802
A57: Amortised Cash Flow Model 2050 EU-Central
A58: Year | B58: 0 | C58: 1 | D58: 2 | E58: 3 | F58: 4 | G58: 5 | H58: 6 | I58: 7 | J58: 8 | K58: 9 | L58: 10 | M58: 11 | N58: 12 | O58: 13 | P58: 14 | Q58: 15 | R58: 16 | S58: 17 | T58: 18 | U58: 19 | V58: 20 | W58: 21 | X58: 22 | Y58: 23 | Z58: 24 | AA58: 25 | AB58: 26 | AC58: 27 | AD58: 28 | AE58: 29 | AF58: 30
A59: Cost (€) | B59: 0 | C59: ='Cost Components'!$N$52*10^6 -> 6.2983021e+08 | D59: ='Cost Components'!$N$52*10^6 -> 6.2983021e+08 | E59: ='Cost Components'!$N$52*10^6 -> 6.2983021e+08 | F59: ='Cost Components'!$N$52*10^6 -> 6.2983021e+08 | G59: ='Cost Components'!$N$52*10^6 -> 6.2983021e+08 | H59: ='Cost Components'!$N$52*10^6 -> 6.2983021e+08 | I59: ='Cost Components'!$N$52*10^6 -> 6.2983021e+08 | J59: ='Cost Components'!$N$52*10^6 -> 6.2983021e+08 | ... AF59: ='Cost Components'!$N$52*10^6 -> 6.2983021e+08
A60: Amortised CAPEX (€) | B60: 0 | C60: ='Cost Components'!$N$29 -> 3.3105984e+08 | D60: ='Cost Components'!$N$29 -> 3.3105984e+08 | E60: ='Cost Components'!$N$29 -> 3.3105984e+08 | F60: ='Cost Components'!$N$29 -> 3.3105984e+08 | G60: ='Cost Components'!$N$29 -> 3.3105984e+08 | H60: ='Cost Components'!$N$29 -> 3.3105984e+08 | I60: ='Cost Components'!$N$29 -> 3.3105984e+08 | J60: ='Cost Components'!$N$29 -> 3.3105984e+08 | ... AF60: ='Cost Components'!$N$29 -> 3.3105984e+08
A61: Discounted Cost (€) | B61: 0 | C61: =C59/((1+'Study Parameters'!$C$4)^'MFSP Baseline'!C58) + C60 -> 9.1423597e+08 | D61: =D59/((1+'Study Parameters'!$C$4)^'MFSP Baseline'!D58) + D60 -> 8.7103773e+08 | E61: =E59/((1+'Study Parameters'!$C$4)^'MFSP Baseline'!E58) + E60 -> 8.3103937e+08 | F61: =F59/((1+'Study Parameters'!$C$4)^'MFSP Baseline'!F58) + F60 -> 7.9400385e+08 | G61: =G59/((1+'Study Parameters'!$C$4)^'MFSP Baseline'!G58) + G60 -> 7.597117e+08 | H61: =H59/((1+'Study Parameters'!$C$4)^'MFSP Baseline'!H58) + H60 -> 7.2795971e+08 | I61: =I59/((1+'Study Parameters'!$C$4)^'MFSP Baseline'!I58) + I60 -> 6.9855972e+08 | J61: =J59/((1+'Study Parameters'!$C$4)^'MFSP Baseline'!J58) + J60 -> 6.7133751e+08 | ... AF61: =AF59/((1+'Study Parameters'!$C$4)^'MFSP Baseline'!AF58) + AF60 -> 3.9365069e+08
A62: Production (l) | B62: 0 | C62: ='Study Parameters'!$C$19 -> 800000000 | D62: ='Study Parameters'!$C$19 -> 800000000 | E62: ='Study Parameters'!$C$19 -> 800000000 | F62: ='Study Parameters'!$C$19 -> 800000000 | G62: ='Study Parameters'!$C$19 -> 800000000 | H62: ='Study Parameters'!$C$19 -> 800000000 | I62: ='Study Parameters'!$C$19 -> 800000000 | J62: ='Study Parameters'!$C$19 -> 800000000 | ... AF62: ='Study Parameters'!$C$19 -> 800000000
A63: Discounted Production (l) | B63: 0 | C63: =C62/((1+'Study Parameters'!$C$4)^'MFSP Baseline'!C58) -> 7.4074074e+08 | D63: =D62/((1+'Study Parameters'!$C$4)^'MFSP Baseline'!D58) -> 6.8587106e+08 | E63: =E62/((1+'Study Parameters'!$C$4)^'MFSP Baseline'!E58) -> 6.3506579e+08 | F63: =F62/((1+'Study Parameters'!$C$4)^'MFSP Baseline'!F58) -> 5.8802388e+08 | G63: =G62/((1+'Study Parameters'!$C$4)^'MFSP Baseline'!G58) -> 5.4446656e+08 | H63: =H62/((1+'Study Parameters'!$C$4)^'MFSP Baseline'!H58) -> 5.041357e+08 | I63: =I62/((1+'Study Parameters'!$C$4)^'MFSP Baseline'!I58) -> 4.6679232e+08 | J63: =J62/((1+'Study Parameters'!$C$4)^'MFSP Baseline'!J58) -> 4.3221511e+08 | ... AF63: =AF62/((1+'Study Parameters'!$C$4)^'MFSP Baseline'!AF58) -> 79501866
A65: Minimum Fuel Selling Price (€/l) | B65: =SUM(B61:AF61) / SUM(B63:AF63) -> 1.8900576

Sheet MFSP CO2 Corrected
A1: Amortised Cash Flow Model 2024 EU-North
A2: Year | B2: 0 | C2: 1 | D2: 2 | E2: 3 | F2: 4 | G2: 5 | H2: 6 | I2: 7 | J2: 8 | K2: 9 | L2: 10 | M2: 11 | N2: 12 | O2: 13 | P2: 14 | Q2: 15 | R2: 16 | S2: 17 | T2: 18 | U2: 19 | V2: 20 | W2: 21 | X2: 22 | Y2: 23 | Z2: 24 | AA2: 25 | AB2: 26 | AC2: 27 | AD2: 28 | AE2: 29 | AF2: 30
A3: Cost (€) | B3: 0 | C3: ='Cost Components'!$B$45 * 10^6 -> 4.1579422e+09 | D3: ='Cost Components'!$B$45 * 10^6 -> 4.1579422e+09 | E3: ='Cost Components'!$B$45 * 10^6 -> 4.1579422e+09 | F3: ='Cost Components'!$B$45 * 10^6 -> 4.1579422e+09 | G3: ='Cost Components'!$B$45 * 10^6 -> 4.1579422e+09 | H3: ='Cost Components'!$B$45 * 10^6 -> 4.1579422e+09 | I3: ='Cost Components'!$B$45 * 10^6 -> 4.1579422e+09 | J3: ='Cost Components'!$B$45 * 10^6 -> 4.1579422e+09 | ... AF3: ='Cost Components'!$B$45 * 10^6 -> 4.1579422e+09
A4: Amortised CAPEX (€) | B4: 0 | C4: ='Cost Components'!$B$9 -> 5.5428318e+08 | D4: ='Cost Components'!$B$9 -> 5.5428318e+08 | E4: ='Cost Components'!$B$9 -> 5.5428318e+08 | F4: ='Cost Components'!$B$9 -> 5.5428318e+08 | G4: ='Cost Components'!$B$9 -> 5.5428318e+08 | H4: ='Cost Components'!$B$9 -> 5.5428318e+08 | I4: ='Cost Components'!$B$9 -> 5.5428318e+08 | J4: ='Cost Components'!$B$9 -> 5.5428318e+08 | ... AF4: ='Cost Components'!$B$9 -> 5.5428318e+08
A5: Discounted Cost (€) | B5: =B3/((1+'Study Parameters'!$C$4)^'MFSP Baseline'!B2) -> 0 | C5: =C3/((1+'Study Parameters'!$C$4)^'MFSP Baseline'!C2) + C4 -> 4.4042297e+09 | D5: =D3/((1+'Study Parameters'!$C$4)^'MFSP Baseline'!D2) + D4 -> 4.1190485e+09 | E5: =E3/((1+'Study Parameters'!$C$4)^'MFSP Baseline'!E2) + E4 -> 3.8549918e+09 | F5: =F3/((1+'Study Parameters'!$C$4)^'MFSP Baseline'!F2) + F4 -> 3.6104949e+09 | G5: =G3/((1+'Study Parameters'!$C$4)^'MFSP Baseline'!G2) + G4 -> 3.3841088e+09 | H5: =H3/((1+'Study Parameters'!$C$4)^'MFSP Baseline'!H2) + H4 -> 3.1744921e+09 | I5: =I3/((1+'Study Parameters'!$C$4)^'MFSP Baseline'!I2) + I4 -> 2.9804025e+09 | J5: =J3/((1+'Study Parameters'!$C$4)^'MFSP Baseline'!J2) + J4 -> 2.80069e+09 | ... AF5: =AF3/((1+'Study Parameters'!$C$4)^'MFSP Baseline'!AF2) + AF4 -> 9.6748839e+08
A6: Production (l) | B6: 0 | C6: ='Study Parameters'!$C$19 -> 800000000 | D6: ='Study Parameters'!$C$19 -> 800000000 | E6: ='Study Parameters'!$C$19 -> 800000000 | F6: ='Study Parameters'!$C$19 -> 800000000 | G6: ='Study Parameters'!$C$19 -> 800000000 | H6: ='Study Parameters'!$C$19 -> 800000000 | I6: ='Study Parameters'!$C$19 -> 800000000 | J6: ='Study Parameters'!$C$19 -> 800000000 | ... AF6: ='Study Parameters'!$C$19 -> 800000000
A7: Discounted Production (l) | B7: =B6/((1+'Study Parameters'!$C$4)^'MFSP Baseline'!B2) -> 0 | C7: =C6/((1+'Study Parameters'!$C$4)^'MFSP Baseline'!C2) -> 7.4074074e+08 | D7: =D6/((1+'Study Parameters'!$C$4)^'MFSP Baseline'!D2) -> 6.8587106e+08 | E7: =E6/((1+'Study Parameters'!$C$4)^'MFSP Baseline'!E2) -> 6.3506579e+08 | F7: =F6/((1+'Study Parameters'!$C$4)^'MFSP Baseline'!F2) -> 5.8802388e+08 | G7: =G6/((1+'Study Parameters'!$C$4)^'MFSP Baseline'!G2) -> 5.4446656e+08 | H7: =H6/((1+'Study Parameters'!$C$4)^'MFSP Baseline'!H2) -> 5.041357e+08 | I7: =I6/((1+'Study Parameters'!$C$4)^'MFSP Baseline'!I2) -> 4.6679232e+08 | ... AF7: =AF6/((1+'Study Parameters'!$C$4)^'MFSP Baseline'!AF2) -> 79501866
A9: Minimum Fuel Selling Price (€/l) | B9: =SUM(B5:AF5) / SUM(B7:AF7) -> 7.043761
A11: Amortised Cash Flow Model 2050 EU-North
A12: Year | B12: 0 | C12: 1 | D12: 2 | E12: 3 | F12: 4 | G12: 5 | H12: 6 | I12: 7 | J12: 8 | K12: 9 | L12: 10 | M12: 11 | N12: 12 | O12: 13 | P12: 14 | Q12: 15 | R12: 16 | S12: 17 | T12: 18 | U12: 19 | V12: 20 | W12: 21 | X12: 22 | Y12: 23 | Z12: 24 | AA12: 25 | AB12: 26 | AC12: 27 | AD12: 28 | AE12: 29 | AF12: 30
A13: Cost (€) | B13: 0 | C13: ='Cost Components'!$B$54*10^6 -> 1.3465682e+09 | D13: ='Cost Components'!$B$54*10^6 -> 1.3465682e+09 | E13: ='Cost Components'!$B$54*10^6 -> 1.3465682e+09 | F13: ='Cost Components'!$B$54*10^6 -> 1.3465682e+09 | G13: ='Cost Components'!$B$54*10^6 -> 1.3465682e+09 | H13: ='Cost Components'!$B$54*10^6 -> 1.3465682e+09 | I13: ='Cost Components'!$B$54*10^6 -> 1.3465682e+09 | J13: ='Cost Components'!$B$54*10^6 -> 1.3465682e+09 | ... AF13: ='Cost Components'!$B$54*10^6 -> 1.3465682e+09
A14: Amortised CAPEX (€) | B14: 0 | C14: ='Cost Components'!$B$29 -> 3.3185929e+08 | D14: ='Cost Components'!$B$29 -> 3.3185929e+08 | E14: ='Cost Components'!$B$29 -> 3.3185929e+08 | F14: ='Cost Components'!$B$29 -> 3.3185929e+08 | G14: ='Cost Components'!$B$29 -> 3.3185929e+08 | H14: ='Cost Components'!$B$29 -> 3.3185929e+08 | I14: ='Cost Components'!$B$29 -> 3.3185929e+08 | J14: ='Cost Components'!$B$29 -> 3.3185929e+08 | ... AF14: ='Cost Components'!$B$29 -> 3.3185929e+08
A15: Discounted Cost (€) | B15: 0 | C15: =C13/((1+'Study Parameters'!$C$4)^'MFSP Baseline'!C12) +C14 -> 1.5786817e+09 | D15: =D13/((1+'Study Parameters'!$C$4)^'MFSP Baseline'!D12) +D14 -> 1.4863245e+09 | E15: =E13/((1+'Study Parameters'!$C$4)^'MFSP Baseline'!E12) +E14 -> 1.4008086e+09 | F15: =F13/((1+'Study Parameters'!$C$4)^'MFSP Baseline'!F12) +F14 -> 1.3216271e+09 | G15: =G13/((1+'Study Parameters'!$C$4)^'MFSP Baseline'!G12) +G14 -> 1.248311e+09 | H15: =H13/((1+'Study Parameters'!$C$4)^'MFSP Baseline'!H12) +H14 -> 1.1804257e+09 | I15: =I13/((1+'Study Parameters'!$C$4)^'MFSP Baseline'!I12) +I14 -> 1.1175689e+09 | J15: =J13/((1+'Study Parameters'!$C$4)^'MFSP Baseline'!J12) +J14 -> 1.0593682e+09 | ... AF15: =AF13/((1+'Study Parameters'!$C$4)^'MFSP Baseline'!AF12) +AF14 -> 4.6567765e+08
A16: Production (l) | B16: 0 | C16: ='Study Parameters'!$C$19 -> 800000000 | D16: ='Study Parameters'!$C$19 -> 800000000 | E16: ='Study Parameters'!$C$19 -> 800000000 | F16: ='Study Parameters'!$C$19 -> 800000000 | G16: ='Study Parameters'!$C$19 -> 800000000 | H16: ='Study Parameters'!$C$19 -> 800000000 | I16: ='Study Parameters'!$C$19 -> 800000000 | J16: ='Study Parameters'!$C$19 -> 800000000 | ... AF16: ='Study Parameters'!$C$19 -> 800000000
A17: Discounted Production (l) | B17: 0 | C17: =C16/((1+'Study Parameters'!$C$4)^'MFSP Baseline'!C12) -> 7.4074074e+08 | D17: =D16/((1+'Study Parameters'!$C$4)^'MFSP Baseline'!D12) -> 6.8587106e+08 | E17: =E16/((1+'Study Parameters'!$C$4)^'MFSP Baseline'!E12) -> 6.3506579e+08 | F17: =F16/((1+'Study Parameters'!$C$4)^'MFSP Baseline'!F12) -> 5.8802388e+08 | G17: =G16/((1+'Study Parameters'!$C$4)^'MFSP Baseline'!G12) -> 5.4446656e+08 | H17: =H16/((1+'Study Parameters'!$C$4)^'MFSP Baseline'!H12) -> 5.041357e+08 | I17: =I16/((1+'Study Parameters'!$C$4)^'MFSP Baseline'!I12) -> 4.6679232e+08 | J17: =J16/((1+'Study Parameters'!$C$4)^'MFSP Baseline'!J12) -> 4.3221511e+08 | ... AF17: =AF16/((1+'Study Parameters'!$C$4)^'MFSP Baseline'!AF12) -> 79501866
A19: Minimum Fuel Selling Price (€/l) | B19: =SUM(B15:AF15) / SUM(B17:AF17) -> 2.7886431
A23: Amortised Cash Flow Model 2024 EU-Central
A24: Year | B24: 0 | C24: 1 | D24: 2 | E24: 3 | F24: 4 | G24: 5 | H24: 6 | I24: 7 | J24: 8 | K24: 9 | L24: 10 | M24: 11 | N24: 12 | O24: 13 | P24: 14 | Q24: 15 | R24: 16 | S24: 17 | T24: 18 | U24: 19 | V24: 20 | W24: 21 | X24: 22 | Y24: 23 | Z24: 24 | AA24: 25 | AB24: 26 | AC24: 27 | AD24: 28 | AE24: 29 | AF24: 30
A25: Cost (€) | B25: 0 | C25: ='Cost Components'!$H$45 * 10^6 -> 4.1500522e+09 | D25: ='Cost Components'!$H$45 * 10^6 -> 4.1500522e+09 | E25: ='Cost Components'!$H$45 * 10^6 -> 4.1500522e+09 | F25: ='Cost Components'!$H$45 * 10^6 -> 4.1500522e+09 | G25: ='Cost Components'!$H$45 * 10^6 -> 4.1500522e+09 | H25: ='Cost Components'!$H$45 * 10^6 -> 4.1500522e+09 | I25: ='Cost Components'!$H$45 * 10^6 -> 4.1500522e+09 | J25: ='Cost Components'!$H$45 * 10^6 -> 4.1500522e+09 | ... AF25: ='Cost Components'!$H$45 * 10^6 -> 4.1500522e+09
A26: Amortised CAPEX (€) | B26: 0 | C26: ='Cost Components'!$H$9 -> 4.4022876e+08 | D26: ='Cost Components'!$H$9 -> 4.4022876e+08 | E26: ='Cost Components'!$H$9 -> 4.4022876e+08 | F26: ='Cost Components'!$H$9 -> 4.4022876e+08 | G26: ='Cost Components'!$H$9 -> 4.4022876e+08 | H26: ='Cost Components'!$H$9 -> 4.4022876e+08 | I26: ='Cost Components'!$H$9 -> 4.4022876e+08 | J26: ='Cost Components'!$H$9 -> 4.4022876e+08 | ... AF26: ='Cost Components'!$H$9 -> 4.4022876e+08
A27: Discounted Cost (€) | B27: =B25/((1+'Study Parameters'!$C$4)^'MFSP Baseline'!B24) -> 0 | C27: =C25/((1+'Study Parameters'!$C$4)^'MFSP Baseline'!C24) + C26 -> 4.2828697e+09 | D27: =D25/((1+'Study Parameters'!$C$4)^'MFSP Baseline'!D24) + D26 -> 3.9982296e+09 | E27: =E25/((1+'Study Parameters'!$C$4)^'MFSP Baseline'!E24) + E26 -> 3.734674e+09 | F27: =F25/((1+'Study Parameters'!$C$4)^'MFSP Baseline'!F24) + F26 -> 3.490641e+09 | G27: =G25/((1+'Study Parameters'!$C$4)^'MFSP Baseline'!G24) + G26 -> 3.2646846e+09 | H27: =H25/((1+'Study Parameters'!$C$4)^'MFSP Baseline'!H24) + H26 -> 3.0554656e+09 | I27: =I25/((1+'Study Parameters'!$C$4)^'MFSP Baseline'!I24) + I26 -> 2.8617444e+09 | J27: =J25/((1+'Study Parameters'!$C$4)^'MFSP Baseline'!J24) + J26 -> 2.6823729e+09 | ... AF27: =AF25/((1+'Study Parameters'!$C$4)^'MFSP Baseline'!AF24) + AF26 -> 8.5264988e+08
A28: Production (l) | B28: 0 | C28: ='Study Parameters'!$C$19 -> 800000000 | D28: ='Study Parameters'!$C$19 -> 800000000 | E28: ='Study Parameters'!$C$19 -> 800000000 | F28: ='Study Parameters'!$C$19 -> 800000000 | G28: ='Study Parameters'!$C$19 -> 800000000 | H28: ='Study Parameters'!$C$19 -> 800000000 | I28: ='Study Parameters'!$C$19 -> 800000000 | J28: ='Study Parameters'!$C$19 -> 800000000 | ... AF28: ='Study Parameters'!$C$19 -> 800000000
A29: Discounted Production (l) | B29: =B28/((1+'Study Parameters'!$C$4)^'MFSP Baseline'!B24) -> 0 | C29: =C28/((1+'Study Parameters'!$C$4)^'MFSP Baseline'!C24) -> 7.4074074e+08 | D29: =D28/((1+'Study Parameters'!$C$4)^'MFSP Baseline'!D24) -> 6.8587106e+08 | E29: =E28/((1+'Study Parameters'!$C$4)^'MFSP Baseline'!E24) -> 6.3506579e+08 | F29: =F28/((1+'Study Parameters'!$C$4)^'MFSP Baseline'!F24) -> 5.8802388e+08 | G29: =G28/((1+'Study Parameters'!$C$4)^'MFSP Baseline'!G24) -> 5.4446656e+08 | H29: =H28/((1+'Study Parameters'!$C$4)^'MFSP Baseline'!H24) -> 5.041357e+08 | I29: =I28/((1+'Study Parameters'!$C$4)^'MFSP Baseline'!I24) -> 4.6679232e+08 | ... AF29: =AF28/((1+'Study Parameters'!$C$4)^'MFSP Baseline'!AF24) -> 79501866
A31: Minimum Fuel Selling Price (€/l) | B31: =SUM(B27:AF27) / SUM(B29:AF29) -> 6.65398
A33: Amortised Cash Flow Model 2050 EU-Central
A35: Year | B35: 0 | C35: 1 | D35: 2 | E35: 3 | F35: 4 | G35: 5 | H35: 6 | I35: 7 | J35: 8 | K35: 9 | L35: 10 | M35: 11 | N35: 12 | O35: 13 | P35: 14 | Q35: 15 | R35: 16 | S35: 17 | T35: 18 | U35: 19 | V35: 20 | W35: 21 | X35: 22 | Y35: 23 | Z35: 24 | AA35: 25 | AB35: 26 | AC35: 27 | AD35: 28 | AE35: 29 | AF35: 30
A36: Cost (€) | B36: 0 | C36: ='Cost Components'!$H$54*10^6 -> 1.3497982e+09 | D36: ='Cost Components'!$H$54*10^6 -> 1.3497982e+09 | E36: ='Cost Components'!$H$54*10^6 -> 1.3497982e+09 | F36: ='Cost Components'!$H$54*10^6 -> 1.3497982e+09 | G36: ='Cost Components'!$H$54*10^6 -> 1.3497982e+09 | H36: ='Cost Components'!$H$54*10^6 -> 1.3497982e+09 | I36: ='Cost Components'!$H$54*10^6 -> 1.3497982e+09 | J36: ='Cost Components'!$H$54*10^6 -> 1.3497982e+09 | ... AF36: ='Cost Components'!$H$54*10^6 -> 1.3497982e+09
A37: Amortised CAPEX (€) | B37: 0 | C37: ='Cost Components'!$H$29 -> 3.3487942e+08 | D37: ='Cost Components'!$H$29 -> 3.3487942e+08 | E37: ='Cost Components'!$H$29 -> 3.3487942e+08 | F37: ='Cost Components'!$H$29 -> 3.3487942e+08 | G37: ='Cost Components'!$H$29 -> 3.3487942e+08 | H37: ='Cost Components'!$H$29 -> 3.3487942e+08 | I37: ='Cost Components'!$H$29 -> 3.3487942e+08 | J37: ='Cost Components'!$H$29 -> 3.3487942e+08 | ... AF37: ='Cost Components'!$H$29 -> 3.3487942e+08
A38: Discounted Cost (€) | B38: =B36/((1+'Study Parameters'!$C$4)^'MFSP Baseline'!B35) -> 0 | C38: =C36/((1+'Study Parameters'!$C$4)^'MFSP Baseline'!C35) + C37 -> 1.5846926e+09 | D38: =D36/((1+'Study Parameters'!$C$4)^'MFSP Baseline'!D35) + D37 -> 1.4921138e+09 | E38: =E36/((1+'Study Parameters'!$C$4)^'MFSP Baseline'!E35) + E37 -> 1.4063928e+09 | F38: =F36/((1+'Study Parameters'!$C$4)^'MFSP Baseline'!F35) + F37 -> 1.3270214e+09 | G38: =G36/((1+'Study Parameters'!$C$4)^'MFSP Baseline'!G35) + G37 -> 1.2535294e+09 | H38: =H36/((1+'Study Parameters'!$C$4)^'MFSP Baseline'!H35) + H37 -> 1.1854813e+09 | I38: =I36/((1+'Study Parameters'!$C$4)^'MFSP Baseline'!I35) + I37 -> 1.1224737e+09 | J38: =J36/((1+'Study Parameters'!$C$4)^'MFSP Baseline'!J35) + J37 -> 1.0641334e+09 | ... AF38: =AF36/((1+'Study Parameters'!$C$4)^'MFSP Baseline'!AF35) + AF37 -> 4.6901877e+08
A39: Production (l) | B39: 0 | C39: ='Study Parameters'!$C$19 -> 800000000 | D39: ='Study Parameters'!$C$19 -> 800000000 | E39: ='Study Parameters'!$C$19 -> 800000000 | F39: ='Study Parameters'!$C$19 -> 800000000 | G39: ='Study Parameters'!$C$19 -> 800000000 | H39: ='Study Parameters'!$C$19 -> 800000000 | I39: ='Study Parameters'!$C$19 -> 800000000 | J39: ='Study Parameters'!$C$19 -> 800000000 | ... AF39: ='Study Parameters'!$C$19 -> 800000000
A40: Discounted Production (l) | B40: =B39/((1+'Study Parameters'!$C$4)^'MFSP Baseline'!B35) -> 0 | C40: =C39/((1+'Study Parameters'!$C$4)^'MFSP Baseline'!C35) -> 7.4074074e+08 | D40: =D39/((1+'Study Parameters'!$C$4)^'MFSP Baseline'!D35) -> 6.8587106e+08 | E40: =E39/((1+'Study Parameters'!$C$4)^'MFSP Baseline'!E35) -> 6.3506579e+08 | F40: =F39/((1+'Study Parameters'!$C$4)^'MFSP Baseline'!F35) -> 5.8802388e+08 | G40: =G39/((1+'Study Parameters'!$C$4)^'MFSP Baseline'!G35) -> 5.4446656e+08 | H40: =H39/((1+'Study Parameters'!$C$4)^'MFSP Baseline'!H35) -> 5.041357e+08 | I40: =I39/((1+'Study Parameters'!$C$4)^'MFSP Baseline'!I35) -> 4.6679232e+08 | ... AF40: =AF39/((1+'Study Parameters'!$C$4)^'MFSP Baseline'!AF35) -> 79501866
A42: Minimum Fuel Selling Price (€/l) | B42: =SUM(B38:AF38) / SUM(B40:AF40) -> 2.8027408
A46: Amortised Cash Flow Model 2024 EU-South
A48: Year | B48: 0 | C48: 1 | D48: 2 | E48: 3 | F48: 4 | G48: 5 | H48: 6 | I48: 7 | J48: 8 | K48: 9 | L48: 10 | M48: 11 | N48: 12 | O48: 13 | P48: 14 | Q48: 15 | R48: 16 | S48: 17 | T48: 18 | U48: 19 | V48: 20 | W48: 21 | X48: 22 | Y48: 23 | Z48: 24 | AA48: 25 | AB48: 26 | AC48: 27 | AD48: 28 | AE48: 29 | AF48: 30
A49: Cost (€) | B49: 0 | C49: ='Cost Components'!$N$45 * 10^6 -> 4.1638622e+09 | D49: ='Cost Components'!$N$45 * 10^6 -> 4.1638622e+09 | E49: ='Cost Components'!$N$45 * 10^6 -> 4.1638622e+09 | F49: ='Cost Components'!$N$45 * 10^6 -> 4.1638622e+09 | G49: ='Cost Components'!$N$45 * 10^6 -> 4.1638622e+09 | H49: ='Cost Components'!$N$45 * 10^6 -> 4.1638622e+09 | I49: ='Cost Components'!$N$45 * 10^6 -> 4.1638622e+09 | J49: ='Cost Components'!$N$45 * 10^6 -> 4.1638622e+09 | ... AF49: ='Cost Components'!$N$45 * 10^6 -> 4.1638622e+09
A50: Amortised CAPEX (€) | B50: 0 | C50: ='Cost Components'!$N$9 -> 5.6885088e+08 | D50: ='Cost Components'!$N$9 -> 5.6885088e+08 | E50: ='Cost Components'!$N$9 -> 5.6885088e+08 | F50: ='Cost Components'!$N$9 -> 5.6885088e+08 | G50: ='Cost Components'!$N$9 -> 5.6885088e+08 | H50: ='Cost Components'!$N$9 -> 5.6885088e+08 | I50: ='Cost Components'!$N$9 -> 5.6885088e+08 | J50: ='Cost Components'!$N$9 -> 5.6885088e+08 | ... AF50: ='Cost Components'!$N$9 -> 5.6885088e+08
A51: Discounted Cost (€) | B51: 0 | C51: =C49/((1+'Study Parameters'!$C$4)^'MFSP Baseline'!C48) + C50 -> 4.4242789e+09 | D51: =D49/((1+'Study Parameters'!$C$4)^'MFSP Baseline'!D48) + D50 -> 4.1386916e+09 | E51: =E49/((1+'Study Parameters'!$C$4)^'MFSP Baseline'!E48) + E50 -> 3.874259e+09 | F51: =F49/((1+'Study Parameters'!$C$4)^'MFSP Baseline'!F48) + F50 -> 3.6294139e+09 | G51: =G49/((1+'Study Parameters'!$C$4)^'MFSP Baseline'!G48) + G50 -> 3.4027056e+09 | H51: =H49/((1+'Study Parameters'!$C$4)^'MFSP Baseline'!H48) + H50 -> 3.1927904e+09 | I51: =I49/((1+'Study Parameters'!$C$4)^'MFSP Baseline'!I48) + I50 -> 2.9984245e+09 | J51: =J49/((1+'Study Parameters'!$C$4)^'MFSP Baseline'!J48) + J50 -> 2.8184561e+09 | ... AF51: =AF49/((1+'Study Parameters'!$C$4)^'MFSP Baseline'!AF48) + AF50 -> 9.8264441e+08
A52: Production (l) | B52: 0 | C52: ='Study Parameters'!$C$19 -> 800000000 | D52: ='Study Parameters'!$C$19 -> 800000000 | E52: ='Study Parameters'!$C$19 -> 800000000 | F52: ='Study Parameters'!$C$19 -> 800000000 | G52: ='Study Parameters'!$C$19 -> 800000000 | H52: ='Study Parameters'!$C$19 -> 800000000 | I52: ='Study Parameters'!$C$19 -> 800000000 | J52: ='Study Parameters'!$C$19 -> 800000000 | ... AF52: ='Study Parameters'!$C$19 -> 800000000
A53: Discounted Production (l) | B53: 0 | C53: =C52/((1+'Study Parameters'!$C$4)^'MFSP Baseline'!C48) -> 7.4074074e+08 | D53: =D52/((1+'Study Parameters'!$C$4)^'MFSP Baseline'!D48) -> 6.8587106e+08 | E53: =E52/((1+'Study Parameters'!$C$4)^'MFSP Baseline'!E48) -> 6.3506579e+08 | F53: =F52/((1+'Study Parameters'!$C$4)^'MFSP Baseline'!F48) -> 5.8802388e+08 | G53: =G52/((1+'Study Parameters'!$C$4)^'MFSP Baseline'!G48) -> 5.4446656e+08 | H53: =H52/((1+'Study Parameters'!$C$4)^'MFSP Baseline'!H48) -> 5.041357e+08 | I53: =I52/((1+'Study Parameters'!$C$4)^'MFSP Baseline'!I48) -> 4.6679232e+08 | J53: =J52/((1+'Study Parameters'!$C$4)^'MFSP Baseline'!J48) -> 4.3221511e+08 | ... AF53: =AF52/((1+'Study Parameters'!$C$4)^'MFSP Baseline'!AF48) -> 79501866
A55: Minimum Fuel Selling Price (€/l) | B55: =SUM(B51:AF51) / SUM(B53:AF53) -> 7.0996864
A57: Amortised Cash Flow Model 2050 EU-Central
A58: Year | B58: 0 | C58: 1 | D58: 2 | E58: 3 | F58: 4 | G58: 5 | H58: 6 | I58: 7 | J58: 8 | K58: 9 | L58: 10 | M58: 11 | N58: 12 | O58: 13 | P58: 14 | Q58: 15 | R58: 16 | S58: 17 | T58: 18 | U58: 19 | V58: 20 | W58: 21 | X58: 22 | Y58: 23 | Z58: 24 | AA58: 25 | AB58: 26 | AC58: 27 | AD58: 28 | AE58: 29 | AF58: 30
A59: Cost (€) | B59: 0 | C59: ='Cost Components'!$N$54*10^6 -> 1.3475682e+09 | D59: ='Cost Components'!$N$54*10^6 -> 1.3475682e+09 | E59: ='Cost Components'!$N$54*10^6 -> 1.3475682e+09 | F59: ='Cost Components'!$N$54*10^6 -> 1.3475682e+09 | G59: ='Cost Components'!$N$54*10^6 -> 1.3475682e+09 | H59: ='Cost Components'!$N$54*10^6 -> 1.3475682e+09 | I59: ='Cost Components'!$N$54*10^6 -> 1.3475682e+09 | J59: ='Cost Components'!$N$54*10^6 -> 1.3475682e+09 | ... AF59: ='Cost Components'!$N$54*10^6 -> 1.3475682e+09
A60: Amortised CAPEX (€) | B60: 0 | C60: ='Cost Components'!$N$29 -> 3.3105984e+08 | D60: ='Cost Components'!$N$29 -> 3.3105984e+08 | E60: ='Cost Components'!$N$29 -> 3.3105984e+08 | F60: ='Cost Components'!$N$29 -> 3.3105984e+08 | G60: ='Cost Components'!$N$29 -> 3.3105984e+08 | H60: ='Cost Components'!$N$29 -> 3.3105984e+08 | I60: ='Cost Components'!$N$29 -> 3.3105984e+08 | J60: ='Cost Components'!$N$29 -> 3.3105984e+08 | ... AF60: ='Cost Components'!$N$29 -> 3.3105984e+08
A61: Discounted Cost (€) | B61: 0 | C61: =C59/((1+'Study Parameters'!$C$4)^'MFSP Baseline'!C58) + C60 -> 1.5788082e+09 | D61: =D59/((1+'Study Parameters'!$C$4)^'MFSP Baseline'!D58) + D60 -> 1.4863824e+09 | E61: =E59/((1+'Study Parameters'!$C$4)^'MFSP Baseline'!E58) + E60 -> 1.4008029e+09 | F61: =F59/((1+'Study Parameters'!$C$4)^'MFSP Baseline'!F58) + F60 -> 1.3215627e+09 | G61: =G59/((1+'Study Parameters'!$C$4)^'MFSP Baseline'!G58) + G60 -> 1.2481921e+09 | H61: =H59/((1+'Study Parameters'!$C$4)^'MFSP Baseline'!H58) + H60 -> 1.1802564e+09 | I61: =I59/((1+'Study Parameters'!$C$4)^'MFSP Baseline'!I58) + I60 -> 1.117353e+09 | J61: =J59/((1+'Study Parameters'!$C$4)^'MFSP Baseline'!J58) + J60 -> 1.059109e+09 | ... AF61: =AF59/((1+'Study Parameters'!$C$4)^'MFSP Baseline'!AF58) + AF60 -> 4.6497758e+08
A62: Production (l) | B62: 0 | C62: ='Study Parameters'!$C$19 -> 800000000 | D62: ='Study Parameters'!$C$19 -> 800000000 | E62: ='Study Parameters'!$C$19 -> 800000000 | F62: ='Study Parameters'!$C$19 -> 800000000 | G62: ='Study Parameters'!$C$19 -> 800000000 | H62: ='Study Parameters'!$C$19 -> 800000000 | I62: ='Study Parameters'!$C$19 -> 800000000 | J62: ='Study Parameters'!$C$19 -> 800000000 | ... AF62: ='Study Parameters'!$C$19 -> 800000000
A63: Discounted Production (l) | B63: 0 | C63: =C62/((1+'Study Parameters'!$C$4)^'MFSP Baseline'!C58) -> 7.4074074e+08 | D63: =D62/((1+'Study Parameters'!$C$4)^'MFSP Baseline'!D58) -> 6.8587106e+08 | E63: =E62/((1+'Study Parameters'!$C$4)^'MFSP Baseline'!E58) -> 6.3506579e+08 | F63: =F62/((1+'Study Parameters'!$C$4)^'MFSP Baseline'!F58) -> 5.8802388e+08 | G63: =G62/((1+'Study Parameters'!$C$4)^'MFSP Baseline'!G58) -> 5.4446656e+08 | H63: =H62/((1+'Study Parameters'!$C$4)^'MFSP Baseline'!H58) -> 5.041357e+08 | I63: =I62/((1+'Study Parameters'!$C$4)^'MFSP Baseline'!I58) -> 4.6679232e+08 | J63: =J62/((1+'Study Parameters'!$C$4)^'MFSP Baseline'!J58) -> 4.3221511e+08 | ... AF63: =AF62/((1+'Study Parameters'!$C$4)^'MFSP Baseline'!AF58) -> 79501866
A65: Minimum Fuel Selling Price (€/l) | B65: =SUM(B61:AF61) / SUM(B63:AF63) -> 2.7872301

Sheet MFSP WACC Corrected
A1: Amortised Cash Flow Model 2024 EU-North
A2: Year | B2: 0 | C2: 1 | D2: 2 | E2: 3 | F2: 4 | G2: 5 | H2: 6 | I2: 7 | J2: 8 | K2: 9 | L2: 10 | M2: 11 | N2: 12 | O2: 13 | P2: 14 | Q2: 15 | R2: 16 | S2: 17 | T2: 18 | U2: 19 | V2: 20 | W2: 21 | X2: 22 | Y2: 23 | Z2: 24 | AA2: 25 | AB2: 26 | AC2: 27 | AD2: 28 | AE2: 29 | AF2: 30
A3: Cost (€) | B3: 0 | C3: ='Cost Components'!$B$45 * 10^6 -> 4.1579422e+09 | D3: ='Cost Components'!$B$45 * 10^6 -> 4.1579422e+09 | E3: ='Cost Components'!$B$45 * 10^6 -> 4.1579422e+09 | F3: ='Cost Components'!$B$45 * 10^6 -> 4.1579422e+09 | G3: ='Cost Components'!$B$45 * 10^6 -> 4.1579422e+09 | H3: ='Cost Components'!$B$45 * 10^6 -> 4.1579422e+09 | I3: ='Cost Components'!$B$45 * 10^6 -> 4.1579422e+09 | J3: ='Cost Components'!$B$45 * 10^6 -> 4.1579422e+09 | ... AF3: ='Cost Components'!$B$45 * 10^6 -> 4.1579422e+09
A4: Amortised CAPEX (€) | B4: 0 | C4: ='Cost Components'!$B$47 -> 5.0285916e+08 | D4: ='Cost Components'!$B$47 -> 5.0285916e+08 | E4: ='Cost Components'!$B$47 -> 5.0285916e+08 | F4: ='Cost Components'!$B$47 -> 5.0285916e+08 | G4: ='Cost Components'!$B$47 -> 5.0285916e+08 | H4: ='Cost Components'!$B$47 -> 5.0285916e+08 | I4: ='Cost Components'!$B$47 -> 5.0285916e+08 | J4: ='Cost Components'!$B$47 -> 5.0285916e+08 | ... AF4: ='Cost Components'!$B$47 -> 5.0285916e+08
A5: Discounted Cost (€) | B5: =B3/((1+'Study Parameters'!$C$4)^'MFSP Baseline'!B2) -> 0 | C5: =C3/((1+'Cost Components'!$B$46)^'MFSP Baseline'!C2)+C4 -> 4.3887865e+09 | D5: =D3/((1+'Cost Components'!$B$46)^'MFSP Baseline'!D2)+D4 -> 4.1345669e+09 | E5: =E3/((1+'Cost Components'!$B$46)^'MFSP Baseline'!E2)+E4 -> 3.8969786e+09 | F5: =F3/((1+'Cost Components'!$B$46)^'MFSP Baseline'!F2)+F4 -> 3.6749334e+09 | G5: =G3/((1+'Cost Components'!$B$46)^'MFSP Baseline'!G2)+G4 -> 3.4674145e+09 | H5: =H3/((1+'Cost Components'!$B$46)^'MFSP Baseline'!H2)+H4 -> 3.2734716e+09 | I5: =I3/((1+'Cost Components'!$B$46)^'MFSP Baseline'!I2)+I4 -> 3.0922166e+09 | J5: =J3/((1+'Cost Components'!$B$46)^'MFSP Baseline'!J2)+J4 -> 2.9228194e+09 | ... AF5: =AF3/((1+'Cost Components'!$B$46)^'MFSP Baseline'!AF2)+AF4 -> 1.049076e+09
A6: Production (l) | B6: 0 | C6: ='Study Parameters'!$C$19 -> 800000000 | D6: ='Study Parameters'!$C$19 -> 800000000 | E6: ='Study Parameters'!$C$19 -> 800000000 | F6: ='Study Parameters'!$C$19 -> 800000000 | G6: ='Study Parameters'!$C$19 -> 800000000 | H6: ='Study Parameters'!$C$19 -> 800000000 | I6: ='Study Parameters'!$C$19 -> 800000000 | J6: ='Study Parameters'!$C$19 -> 800000000 | ... AF6: ='Study Parameters'!$C$19 -> 800000000
A7: Discounted Production (l) | B7: =B6/((1+'Study Parameters'!$C$4)^'MFSP Baseline'!B2) -> 0 | C7: =C6/((1+'Cost Components'!$B$46)^'MFSP Baseline'!C2) -> 7.4766355e+08 | D7: =D6/((1+'Cost Components'!$B$46)^'MFSP Baseline'!D2) -> 6.9875098e+08 | E7: =E6/((1+'Cost Components'!$B$46)^'MFSP Baseline'!E2) -> 6.530383e+08 | F7: =F6/((1+'Cost Components'!$B$46)^'MFSP Baseline'!F2) -> 6.1031617e+08 | G7: =G6/((1+'Cost Components'!$B$46)^'MFSP Baseline'!G2) -> 5.7038894e+08 | H7: =H6/((1+'Cost Components'!$B$46)^'MFSP Baseline'!H2) -> 5.3307378e+08 | I7: =I6/((1+'Cost Components'!$B$46)^'MFSP Baseline'!I2) -> 4.9819979e+08 | J7: =J6/((1+'Cost Components'!$B$46)^'MFSP Baseline'!J2) -> 4.6560728e+08 | ... AF7: =AF6/((1+'Cost Components'!$B$46)^'MFSP Baseline'!AF2) -> 1.0509369e+08
A9: Minimum Fuel Selling Price (€/l) | B9: =SUM(B5:AF5) / SUM(B7:AF7) -> 6.7170632
A11: Amortised Cash Flow Model 2050 EU-North
A12: Year | B12: 0 | C12: 1 | D12: 2 | E12: 3 | F12: 4 | G12: 5 | H12: 6 | I12: 7 | J12: 8 | K12: 9 | L12: 10 | M12: 11 | N12: 12 | O12: 13 | P12: 14 | Q12: 15 | R12: 16 | S12: 17 | T12: 18 | U12: 19 | V12: 20 | W12: 21 | X12: 22 | Y12: 23 | Z12: 24 | AA12: 25 | AB12: 26 | AC12: 27 | AD12: 28 | AE12: 29 | AF12: 30
A13: Cost (€) | B13: 0 | C13: ='Cost Components'!$B$54*10^6 -> 1.3465682e+09 | D13: ='Cost Components'!$B$54*10^6 -> 1.3465682e+09 | E13: ='Cost Components'!$B$54*10^6 -> 1.3465682e+09 | F13: ='Cost Components'!$B$54*10^6 -> 1.3465682e+09 | G13: ='Cost Components'!$B$54*10^6 -> 1.3465682e+09 | H13: ='Cost Components'!$B$54*10^6 -> 1.3465682e+09 | I13: ='Cost Components'!$B$54*10^6 -> 1.3465682e+09 | J13: ='Cost Components'!$B$54*10^6 -> 1.3465682e+09 | ... AF13: ='Cost Components'!$B$54*10^6 -> 1.3465682e+09
A14: Amortised CAPEX (€) | B14: 0 | C14: ='Cost Components'!$B$56 -> 3.010708e+08 | D14: ='Cost Components'!$B$56 -> 3.010708e+08 | E14: ='Cost Components'!$B$56 -> 3.010708e+08 | F14: ='Cost Components'!$B$56 -> 3.010708e+08 | G14: ='Cost Components'!$B$56 -> 3.010708e+08 | H14: ='Cost Components'!$B$56 -> 3.010708e+08 | I14: ='Cost Components'!$B$56 -> 3.010708e+08 | J14: ='Cost Components'!$B$56 -> 3.010708e+08 | ... AF14: ='Cost Components'!$B$56 -> 3.010708e+08
A15: Discounted Cost (€) | B15: 0 | C15: =C13/((1+'Cost Components'!$B$55)^'MFSP Baseline'!C12) + C14 -> 1.5595458e+09 | D15: =D13/((1+'Cost Components'!$B$55)^'MFSP Baseline'!D12) + D14 -> 1.4772156e+09 | E15: =E13/((1+'Cost Components'!$B$55)^'MFSP Baseline'!E12) + E14 -> 1.4002716e+09 | F15: =F13/((1+'Cost Components'!$B$55)^'MFSP Baseline'!F12) + F14 -> 1.3283612e+09 | G15: =G13/((1+'Cost Components'!$B$55)^'MFSP Baseline'!G12) + G14 -> 1.2611553e+09 | H15: =H13/((1+'Cost Components'!$B$55)^'MFSP Baseline'!H12) + H14 -> 1.1983461e+09 | I15: =I13/((1+'Cost Components'!$B$55)^'MFSP Baseline'!I12) + I14 -> 1.1396458e+09 | J15: =J13/((1+'Cost Components'!$B$55)^'MFSP Baseline'!J12) + J14 -> 1.0847858e+09 | ... AF15: =AF13/((1+'Cost Components'!$B$55)^'MFSP Baseline'!AF12) + AF14 -> 4.7796559e+08
A16: Production (l) | B16: 0 | C16: ='Study Parameters'!$C$19 -> 800000000 | D16: ='Study Parameters'!$C$19 -> 800000000 | E16: ='Study Parameters'!$C$19 -> 800000000 | F16: ='Study Parameters'!$C$19 -> 800000000 | G16: ='Study Parameters'!$C$19 -> 800000000 | H16: ='Study Parameters'!$C$19 -> 800000000 | I16: ='Study Parameters'!$C$19 -> 800000000 | J16: ='Study Parameters'!$C$19 -> 800000000 | ... AF16: ='Study Parameters'!$C$19 -> 800000000
A17: Discounted Production (l) | B17: 0 | C17: =C16/((1+'Cost Components'!$B$55)^'MFSP Baseline'!C12) -> 7.4766355e+08 | D17: =D16/((1+'Cost Components'!$B$55)^'MFSP Baseline'!D12) -> 6.9875098e+08 | E17: =E16/((1+'Cost Components'!$B$55)^'MFSP Baseline'!E12) -> 6.530383e+08 | F17: =F16/((1+'Cost Components'!$B$55)^'MFSP Baseline'!F12) -> 6.1031617e+08 | G17: =G16/((1+'Cost Components'!$B$55)^'MFSP Baseline'!G12) -> 5.7038894e+08 | H17: =H16/((1+'Cost Components'!$B$55)^'MFSP Baseline'!H12) -> 5.3307378e+08 | I17: =I16/((1+'Cost Components'!$B$55)^'MFSP Baseline'!I12) -> 4.9819979e+08 | J17: =J16/((1+'Cost Components'!$B$55)^'MFSP Baseline'!J12) -> 4.6560728e+08 | ... AF17: =AF16/((1+'Cost Components'!$B$55)^'MFSP Baseline'!AF12) -> 1.0509369e+08
A19: Minimum Fuel Selling Price (€/l) | B19: =SUM(B15:AF15) / SUM(B17:AF17) -> 2.5930433
A23: Amortised Cash Flow Model 2024 EU-Central
A24: Year | B24: 0 | C24: 1 | D24: 2 | E24: 3 | F24: 4 | G24: 5 | H24: 6 | I24: 7 | J24: 8 | K24: 9 | L24: 10 | M24: 11 | N24: 12 | O24: 13 | P24: 14 | Q24: 15 | R24: 16 | S24: 17 | T24: 18 | U24: 19 | V24: 20 | W24: 21 | X24: 22 | Y24: 23 | Z24: 24 | AA24: 25 | AB24: 26 | AC24: 27 | AD24: 28 | AE24: 29 | AF24: 30
A25: Cost (€) | B25: 0 | C25: ='Cost Components'!$H$45 * 10^6 -> 4.1500522e+09 | D25: ='Cost Components'!$H$45 * 10^6 -> 4.1500522e+09 | E25: ='Cost Components'!$H$45 * 10^6 -> 4.1500522e+09 | F25: ='Cost Components'!$H$45 * 10^6 -> 4.1500522e+09 | G25: ='Cost Components'!$H$45 * 10^6 -> 4.1500522e+09 | H25: ='Cost Components'!$H$45 * 10^6 -> 4.1500522e+09 | I25: ='Cost Components'!$H$45 * 10^6 -> 4.1500522e+09 | J25: ='Cost Components'!$H$45 * 10^6 -> 4.1500522e+09 | ... AF25: ='Cost Components'!$H$45 * 10^6 -> 4.1500522e+09
A26: Amortised CAPEX (€) | B26: 0 | C26: ='Cost Components'!$H$47 -> 3.9938622e+08 | D26: ='Cost Components'!$H$47 -> 3.9938622e+08 | E26: ='Cost Components'!$H$47 -> 3.9938622e+08 | F26: ='Cost Components'!$H$47 -> 3.9938622e+08 | G26: ='Cost Components'!$H$47 -> 3.9938622e+08 | H26: ='Cost Components'!$H$47 -> 3.9938622e+08 | I26: ='Cost Components'!$H$47 -> 3.9938622e+08 | J26: ='Cost Components'!$H$47 -> 3.9938622e+08 | ... AF26: ='Cost Components'!$H$47 -> 3.9938622e+08
A27: Discounted Cost (€) | B27: =B25/((1+'Study Parameters'!$C$4)^'MFSP Baseline'!B24) -> 0 | C27: =C25/((1+'Cost Components'!$H$46)^'MFSP Baseline'!C24) + C26 -> 4.2779397e+09 | D27: =D25/((1+'Cost Components'!$H$46)^'MFSP Baseline'!D24) + D26 -> 4.0242026e+09 | E27: =E25/((1+'Cost Components'!$H$46)^'MFSP Baseline'!E24) + E26 -> 3.787065e+09 | F27: =F25/((1+'Cost Components'!$H$46)^'MFSP Baseline'!F24) + F26 -> 3.5654412e+09 | G27: =G25/((1+'Cost Components'!$H$46)^'MFSP Baseline'!G24) + G26 -> 3.3583161e+09 | H27: =H25/((1+'Cost Components'!$H$46)^'MFSP Baseline'!H24) + H26 -> 3.1647413e+09 | I27: =I25/((1+'Cost Components'!$H$46)^'MFSP Baseline'!I24) + I26 -> 2.9838302e+09 | J27: =J25/((1+'Cost Components'!$H$46)^'MFSP Baseline'!J24) + J26 -> 2.8147544e+09 | ... AF27: =AF25/((1+'Cost Components'!$H$46)^'MFSP Baseline'!AF24) + AF26 -> 9.4456661e+08
A28: Production (l) | B28: 0 | C28: ='Study Parameters'!$C$19 -> 800000000 | D28: ='Study Parameters'!$C$19 -> 800000000 | E28: ='Study Parameters'!$C$19 -> 800000000 | F28: ='Study Parameters'!$C$19 -> 800000000 | G28: ='Study Parameters'!$C$19 -> 800000000 | H28: ='Study Parameters'!$C$19 -> 800000000 | I28: ='Study Parameters'!$C$19 -> 800000000 | J28: ='Study Parameters'!$C$19 -> 800000000 | ... AF28: ='Study Parameters'!$C$19 -> 800000000
A29: Discounted Production (l) | B29: =B28/((1+'Study Parameters'!$C$4)^'MFSP Baseline'!B24) -> 0 | C29: =C28/((1+'Cost Components'!$H$46)^'MFSP Baseline'!C24) -> 7.4766355e+08 | D29: =D28/((1+'Cost Components'!$H$46)^'MFSP Baseline'!D24) -> 6.9875098e+08 | E29: =E28/((1+'Cost Components'!$H$46)^'MFSP Baseline'!E24) -> 6.530383e+08 | F29: =F28/((1+'Cost Components'!$H$46)^'MFSP Baseline'!F24) -> 6.1031617e+08 | G29: =G28/((1+'Cost Components'!$H$46)^'MFSP Baseline'!G24) -> 5.7038894e+08 | H29: =H28/((1+'Cost Components'!$H$46)^'MFSP Baseline'!H24) -> 5.3307378e+08 | I29: =I28/((1+'Cost Components'!$H$46)^'MFSP Baseline'!I24) -> 4.9819979e+08 | J29: =J28/((1+'Cost Components'!$H$46)^'MFSP Baseline'!J24) -> 4.6560728e+08 | ... AF29: =AF28/((1+'Cost Components'!$H$46)^'MFSP Baseline'!AF24) -> 1.0509369e+08
A31: Minimum Fuel Selling Price (€/l) | B31: =SUM(B27:AF27) / SUM(B29:AF29) -> 6.3945065
A33: Amortised Cash Flow Model 2050 EU-Central
A35: Year | B35: 0 | C35: 1 | D35: 2 | E35: 3 | F35: 4 | G35: 5 | H35: 6 | I35: 7 | J35: 8 | K35: 9 | L35: 10 | M35: 11 | N35: 12 | O35: 13 | P35: 14 | Q35: 15 | R35: 16 | S35: 17 | T35: 18 | U35: 19 | V35: 20 | W35: 21 | X35: 22 | Y35: 23 | Z35: 24 | AA35: 25 | AB35: 26 | AC35: 27 | AD35: 28 | AE35: 29 | AF35: 30
A36: Cost (€) | B36: 0 | C36: ='Cost Components'!$H$54*10^6 -> 1.3497982e+09 | D36: ='Cost Components'!$H$54*10^6 -> 1.3497982e+09 | E36: ='Cost Components'!$H$54*10^6 -> 1.3497982e+09 | F36: ='Cost Components'!$H$54*10^6 -> 1.3497982e+09 | G36: ='Cost Components'!$H$54*10^6 -> 1.3497982e+09 | H36: ='Cost Components'!$H$54*10^6 -> 1.3497982e+09 | I36: ='Cost Components'!$H$54*10^6 -> 1.3497982e+09 | J36: ='Cost Components'!$H$54*10^6 -> 1.3497982e+09 | ... AF36: ='Cost Components'!$H$54*10^6 -> 1.3497982e+09
A37: Amortised CAPEX (€) | B37: 0 | C37: ='Cost Components'!$H$56 -> 3.0381074e+08 | D37: ='Cost Components'!$H$56 -> 3.0381074e+08 | E37: ='Cost Components'!$H$56 -> 3.0381074e+08 | F37: ='Cost Components'!$H$56 -> 3.0381074e+08 | G37: ='Cost Components'!$H$56 -> 3.0381074e+08 | H37: ='Cost Components'!$H$56 -> 3.0381074e+08 | I37: ='Cost Components'!$H$56 -> 3.0381074e+08 | J37: ='Cost Components'!$H$56 -> 3.0381074e+08 | ... AF37: ='Cost Components'!$H$56 -> 3.0381074e+08
A38: Discounted Cost (€) | B38: =B36/((1+'Study Parameters'!$C$4)^'MFSP Baseline'!B35) -> 0 | C38: =C36/((1+'Cost Components'!$H$55)^'MFSP Baseline'!C35) + C37 -> 1.5653044e+09 | D38: =D36/((1+'Cost Components'!$H$55)^'MFSP Baseline'!D35) + D37 -> 1.4827768e+09 | E38: =E36/((1+'Cost Components'!$H$55)^'MFSP Baseline'!E35) + E37 -> 1.4056482e+09 | F38: =F36/((1+'Cost Components'!$H$55)^'MFSP Baseline'!F35) + F37 -> 1.3335653e+09 | G38: =G36/((1+'Cost Components'!$H$55)^'MFSP Baseline'!G35) + G37 -> 1.2661982e+09 | H38: =H36/((1+'Cost Components'!$H$55)^'MFSP Baseline'!H35) + H37 -> 1.2032383e+09 | I38: =I36/((1+'Cost Components'!$H$55)^'MFSP Baseline'!I35) + I37 -> 1.1443972e+09 | J38: =J36/((1+'Cost Components'!$H$55)^'MFSP Baseline'!J35) + J37 -> 1.0894056e+09 | ... AF38: =AF36/((1+'Cost Components'!$H$55)^'MFSP Baseline'!AF35) + AF37 -> 4.8112984e+08
A39: Production (l) | B39: 0 | C39: ='Study Parameters'!$C$19 -> 800000000 | D39: ='Study Parameters'!$C$19 -> 800000000 | E39: ='Study Parameters'!$C$19 -> 800000000 | F39: ='Study Parameters'!$C$19 -> 800000000 | G39: ='Study Parameters'!$C$19 -> 800000000 | H39: ='Study Parameters'!$C$19 -> 800000000 | I39: ='Study Parameters'!$C$19 -> 800000000 | J39: ='Study Parameters'!$C$19 -> 800000000 | ... AF39: ='Study Parameters'!$C$19 -> 800000000
A40: Discounted Production (l) | B40: =B39/((1+'Study Parameters'!$C$4)^'MFSP Baseline'!B35) -> 0 | C40: =C39/((1+'Cost Components'!$H$55)^'MFSP Baseline'!C35) -> 7.4766355e+08 | D40: =D39/((1+'Cost Components'!$H$55)^'MFSP Baseline'!D35) -> 6.9875098e+08 | E40: =E39/((1+'Cost Components'!$H$55)^'MFSP Baseline'!E35) -> 6.530383e+08 | F40: =F39/((1+'Cost Components'!$H$55)^'MFSP Baseline'!F35) -> 6.1031617e+08 | G40: =G39/((1+'Cost Components'!$H$55)^'MFSP Baseline'!G35) -> 5.7038894e+08 | H40: =H39/((1+'Cost Components'!$H$55)^'MFSP Baseline'!H35) -> 5.3307378e+08 | I40: =I39/((1+'Cost Components'!$H$55)^'MFSP Baseline'!I35) -> 4.9819979e+08 | J40: =J39/((1+'Cost Components'!$H$55)^'MFSP Baseline'!J35) -> 4.6560728e+08 | ... AF40: =AF39/((1+'Cost Components'!$H$55)^'MFSP Baseline'!AF35) -> 1.0509369e+08
A42: Minimum Fuel Selling Price (€/l) | B42: =SUM(B38:AF38) / SUM(B40:AF40) -> 2.6053608
A46: Amortised Cash Flow Model 2024 EU-South
A48: Year | B48: 0 | C48: 1 | D48: 2 | E48: 3 | F48: 4 | G48: 5 | H48: 6 | I48: 7 | J48: 8 | K48: 9 | L48: 10 | M48: 11 | N48: 12 | O48: 13 | P48: 14 | Q48: 15 | R48: 16 | S48: 17 | T48: 18 | U48: 19 | V48: 20 | W48: 21 | X48: 22 | Y48: 23 | Z48: 24 | AA48: 25 | AB48: 26 | AC48: 27 | AD48: 28 | AE48: 29 | AF48: 30
A49: Cost (€) | B49: 0 | C49: ='Cost Components'!$N$45 * 10^6 -> 4.1638622e+09 | D49: ='Cost Components'!$N$45 * 10^6 -> 4.1638622e+09 | E49: ='Cost Components'!$N$45 * 10^6 -> 4.1638622e+09 | F49: ='Cost Components'!$N$45 * 10^6 -> 4.1638622e+09 | G49: ='Cost Components'!$N$45 * 10^6 -> 4.1638622e+09 | H49: ='Cost Components'!$N$45 * 10^6 -> 4.1638622e+09 | I49: ='Cost Components'!$N$45 * 10^6 -> 4.1638622e+09 | J49: ='Cost Components'!$N$45 * 10^6 -> 4.1638622e+09 | ... AF49: ='Cost Components'!$N$45 * 10^6 -> 4.1638622e+09
A50: Amortised CAPEX (€) | B50: 0 | C50: ='Cost Components'!$N$47 -> 5.1607533e+08 | D50: ='Cost Components'!$N$47 -> 5.1607533e+08 | E50: ='Cost Components'!$N$47 -> 5.1607533e+08 | F50: ='Cost Components'!$N$47 -> 5.1607533e+08 | G50: ='Cost Components'!$N$47 -> 5.1607533e+08 | H50: ='Cost Components'!$N$47 -> 5.1607533e+08 | I50: ='Cost Components'!$N$47 -> 5.1607533e+08 | J50: ='Cost Components'!$N$47 -> 5.1607533e+08 | ... AF50: ='Cost Components'!$N$47 -> 5.1607533e+08
A51: Discounted Cost (€) | B51: 0 | C51: =C49/((1+'Cost Components'!$N$46)^'MFSP Baseline'!C48) + C50 -> 4.4075354e+09 | D51: =D49/((1+'Cost Components'!$N$46)^'MFSP Baseline'!D48) + D50 -> 4.1529539e+09 | E51: =E49/((1+'Cost Components'!$N$46)^'MFSP Baseline'!E48) + E50 -> 3.9150272e+09 | F51: =F49/((1+'Cost Components'!$N$46)^'MFSP Baseline'!F48) + F50 -> 3.6926659e+09 | G51: =G49/((1+'Cost Components'!$N$46)^'MFSP Baseline'!G48) + G50 -> 3.4848516e+09 | H51: =H49/((1+'Cost Components'!$N$46)^'MFSP Baseline'!H48) + H50 -> 3.2906326e+09 | I51: =I49/((1+'Cost Components'!$N$46)^'MFSP Baseline'!I48) + I50 -> 3.1091195e+09 | J51: =J49/((1+'Cost Components'!$N$46)^'MFSP Baseline'!J48) + J50 -> 2.9394811e+09 | ... AF51: =AF49/((1+'Cost Components'!$N$46)^'MFSP Baseline'!AF48) + AF50 -> 1.0630699e+09
A52: Production (l) | B52: 0 | C52: ='Study Parameters'!$C$19 -> 800000000 | D52: ='Study Parameters'!$C$19 -> 800000000 | E52: ='Study Parameters'!$C$19 -> 800000000 | F52: ='Study Parameters'!$C$19 -> 800000000 | G52: ='Study Parameters'!$C$19 -> 800000000 | H52: ='Study Parameters'!$C$19 -> 800000000 | I52: ='Study Parameters'!$C$19 -> 800000000 | J52: ='Study Parameters'!$C$19 -> 800000000 | ... AF52: ='Study Parameters'!$C$19 -> 800000000
A53: Discounted Production (l) | B53: 0 | C53: =C52/((1+'Cost Components'!$N$46)^'MFSP Baseline'!C48) -> 7.4766355e+08 | D53: =D52/((1+'Cost Components'!$N$46)^'MFSP Baseline'!D48) -> 6.9875098e+08 | E53: =E52/((1+'Cost Components'!$N$46)^'MFSP Baseline'!E48) -> 6.530383e+08 | F53: =F52/((1+'Cost Components'!$N$46)^'MFSP Baseline'!F48) -> 6.1031617e+08 | G53: =G52/((1+'Cost Components'!$N$46)^'MFSP Baseline'!G48) -> 5.7038894e+08 | H53: =H52/((1+'Cost Components'!$N$46)^'MFSP Baseline'!H48) -> 5.3307378e+08 | I53: =I52/((1+'Cost Components'!$N$46)^'MFSP Baseline'!I48) -> 4.9819979e+08 | J53: =J52/((1+'Cost Components'!$N$46)^'MFSP Baseline'!J48) -> 4.6560728e+08 | ... AF53: =AF52/((1+'Cost Components'!$N$46)^'MFSP Baseline'!AF48) -> 1.0509369e+08
A55: Minimum Fuel Selling Price (€/l) | B55: =SUM(B51:AF51) / SUM(B53:AF53) -> 6.7644023
A57: Amortised Cash Flow Model 2050 EU-Central
A58: Year | B58: 0 | C58: 1 | D58: 2 | E58: 3 | F58: 4 | G58: 5 | H58: 6 | I58: 7 | J58: 8 | K58: 9 | L58: 10 | M58: 11 | N58: 12 | O58: 13 | P58: 14 | Q58: 15 | R58: 16 | S58: 17 | T58: 18 | U58: 19 | V58: 20 | W58: 21 | X58: 22 | Y58: 23 | Z58: 24 | AA58: 25 | AB58: 26 | AC58: 27 | AD58: 28 | AE58: 29 | AF58: 30
A59: Cost (€) | B59: 0 | C59: ='Cost Components'!$N$54*10^6 -> 1.3475682e+09 | D59: ='Cost Components'!$N$54*10^6 -> 1.3475682e+09 | E59: ='Cost Components'!$N$54*10^6 -> 1.3475682e+09 | F59: ='Cost Components'!$N$54*10^6 -> 1.3475682e+09 | G59: ='Cost Components'!$N$54*10^6 -> 1.3475682e+09 | H59: ='Cost Components'!$N$54*10^6 -> 1.3475682e+09 | I59: ='Cost Components'!$N$54*10^6 -> 1.3475682e+09 | J59: ='Cost Components'!$N$54*10^6 -> 1.3475682e+09 | ... AF59: ='Cost Components'!$N$54*10^6 -> 1.3475682e+09
A60: Amortised CAPEX (€) | B60: 0 | C60: ='Cost Components'!$N$56 -> 3.0034553e+08 | D60: ='Cost Components'!$N$56 -> 3.0034553e+08 | E60: ='Cost Components'!$N$56 -> 3.0034553e+08 | F60: ='Cost Components'!$N$56 -> 3.0034553e+08 | G60: ='Cost Components'!$N$56 -> 3.0034553e+08 | H60: ='Cost Components'!$N$56 -> 3.0034553e+08 | I60: ='Cost Components'!$N$56 -> 3.0034553e+08 | J60: ='Cost Components'!$N$56 -> 3.0034553e+08 | ... AF60: ='Cost Components'!$N$56 -> 3.0034553e+08
A61: Discounted Cost (€) | B61: 0 | C61: =C59/((1+'Cost Components'!$N$55)^'MFSP Baseline'!C58) + C60 -> 1.5597551e+09 | D61: =D59/((1+'Cost Components'!$N$55)^'MFSP Baseline'!D58) + D60 -> 1.4773638e+09 | E61: =E59/((1+'Cost Components'!$N$55)^'MFSP Baseline'!E58) + E60 -> 1.4003626e+09 | F61: =F59/((1+'Cost Components'!$N$55)^'MFSP Baseline'!F58) + F60 -> 1.3283989e+09 | G61: =G59/((1+'Cost Components'!$N$55)^'MFSP Baseline'!G58) + G60 -> 1.261143e+09 | H61: =H59/((1+'Cost Components'!$N$55)^'MFSP Baseline'!H58) + H60 -> 1.1982871e+09 | I61: =I59/((1+'Cost Components'!$N$55)^'MFSP Baseline'!I58) + I60 -> 1.1395433e+09 | J61: =J59/((1+'Cost Components'!$N$55)^'MFSP Baseline'!J58) + J60 -> 1.0846425e+09 | ... AF61: =AF59/((1+'Cost Components'!$N$55)^'MFSP Baseline'!AF58) + AF60 -> 4.7737168e+08
A62: Production (l) | B62: 0 | C62: ='Study Parameters'!$C$19 -> 800000000 | D62: ='Study Parameters'!$C$19 -> 800000000 | E62: ='Study Parameters'!$C$19 -> 800000000 | F62: ='Study Parameters'!$C$19 -> 800000000 | G62: ='Study Parameters'!$C$19 -> 800000000 | H62: ='Study Parameters'!$C$19 -> 800000000 | I62: ='Study Parameters'!$C$19 -> 800000000 | J62: ='Study Parameters'!$C$19 -> 800000000 | ... AF62: ='Study Parameters'!$C$19 -> 800000000
A63: Discounted Production (l) | B63: 0 | C63: =C62/((1+'Cost Components'!$N$55)^'MFSP Baseline'!C58) -> 7.4766355e+08 | D63: =D62/((1+'Cost Components'!$N$55)^'MFSP Baseline'!D58) -> 6.9875098e+08 | E63: =E62/((1+'Cost Components'!$N$55)^'MFSP Baseline'!E58) -> 6.530383e+08 | F63: =F62/((1+'Cost Components'!$N$55)^'MFSP Baseline'!F58) -> 6.1031617e+08 | G63: =G62/((1+'Cost Components'!$N$55)^'MFSP Baseline'!G58) -> 5.7038894e+08 | H63: =H62/((1+'Cost Components'!$N$55)^'MFSP Baseline'!H58) -> 5.3307378e+08 | I63: =I62/((1+'Cost Components'!$N$55)^'MFSP Baseline'!I58) -> 4.9819979e+08 | J63: =J62/((1+'Cost Components'!$N$55)^'MFSP Baseline'!J58) -> 4.6560728e+08 | ... AF63: =AF62/((1+'Cost Components'!$N$55)^'MFSP Baseline'!AF58) -> 1.0509369e+08
A65: Minimum Fuel Selling Price (€/l) | B65: =SUM(B61:AF61) / SUM(B63:AF63) -> 2.5921015

Sheet Cost Breakdown
A1: Year | B1: 0 | C1: 1 | D1: 2 | E1: 3 | F1: 4 | G1: 5 | H1: 6 | I1: 7 | J1: 8 | K1: 9 | L1: 10 | M1: 11 | N1: 12 | O1: 13 | P1: 14 | Q1: 15 | R1: 16 | S1: 17 | T1: 18 | U1: 19 | V1: 20 | W1: 21 | X1: 22 | Y1: 23 | Z1: 24 | AA1: 25 | AB1: 26 | AC1: 27 | AD1: 28 | AE1: 29 | AF1: 30
A2: 2024 EU - North
A3: CO2 | B3: 0 | C3: =('Cost Components'!$B$44 * 10^6) / (1+'Cost Components'!$B$55) ^'Cost Breakdown'!C1 -> 2.6706336e+09 | D3: =('Cost Components'!$B$44 * 10^6) / (1+'Cost Components'!$B$55) ^'Cost Breakdown'!D1 -> 2.4959193e+09 | E3: =('Cost Components'!$B$44 * 10^6) / (1+'Cost Components'!$B$55) ^'Cost Breakdown'!E1 -> 2.3326349e+09 | F3: =('Cost Components'!$B$44 * 10^6) / (1+'Cost Components'!$B$55) ^'Cost Breakdown'!F1 -> 2.1800326e+09 | G3: =('Cost Components'!$B$44 * 10^6) / (1+'Cost Components'!$B$55) ^'Cost Breakdown'!G1 -> 2.0374136e+09 | H3: =('Cost Components'!$B$44 * 10^6) / (1+'Cost Components'!$B$55) ^'Cost Breakdown'!H1 -> 1.9041249e+09 | I3: =('Cost Components'!$B$44 * 10^6) / (1+'Cost Components'!$B$55) ^'Cost Breakdown'!I1 -> 1.779556e+09 | J3: =('Cost Components'!$B$44 * 10^6) / (1+'Cost Components'!$B$55) ^'Cost Breakdown'!J1 -> 1.6631364e+09 | ... AF3: =('Cost Components'!$B$44 * 10^6) / (1+'Cost Components'!$B$55) ^'Cost Breakdown'!AF1 -> 3.7539178e+08
A4: Electricity | B4: 0 | C4: =('Cost Components'!$B$42 * 10^6) / (1+'Cost Components'!$B$46) ^ 'Cost Breakdown'!C1 -> 1.1450775e+09 | D4: =('Cost Components'!$B$42 * 10^6) / (1+'Cost Components'!$B$46) ^ 'Cost Breakdown'!D1 -> 1.0701659e+09 | E4: =('Cost Components'!$B$42 * 10^6) / (1+'Cost Components'!$B$46) ^ 'Cost Breakdown'!E1 -> 1.000155e+09 | F4: =('Cost Components'!$B$42 * 10^6) / (1+'Cost Components'!$B$46) ^ 'Cost Breakdown'!F1 -> 9.3472434e+08 | G4: =('Cost Components'!$B$42 * 10^6) / (1+'Cost Components'!$B$46) ^ 'Cost Breakdown'!G1 -> 8.7357415e+08 | H4: =('Cost Components'!$B$42 * 10^6) / (1+'Cost Components'!$B$46) ^ 'Cost Breakdown'!H1 -> 8.1642444e+08 | I4: =('Cost Components'!$B$42 * 10^6) / (1+'Cost Components'!$B$46) ^ 'Cost Breakdown'!I1 -> 7.630135e+08 | J4: =('Cost Components'!$B$42 * 10^6) / (1+'Cost Components'!$B$46) ^ 'Cost Breakdown'!J1 -> 7.1309673e+08 | ... AF4: =('Cost Components'!$B$42 * 10^6) / (1+'Cost Components'!$B$46) ^ 'Cost Breakdown'!AF1 -> 1.6095532e+08
A5: CAPEX | B5: ='Cost Components'!$B$9 -> 5.5428318e+08 | C5: ='Cost Components'!$B$9 -> 5.5428318e+08 | D5: ='Cost Components'!$B$9 -> 5.5428318e+08 | E5: ='Cost Components'!$B$9 -> 5.5428318e+08 | F5: ='Cost Components'!$B$9 -> 5.5428318e+08 | G5: ='Cost Components'!$B$9 -> 5.5428318e+08 | H5: ='Cost Components'!$B$9 -> 5.5428318e+08 | I5: ='Cost Components'!$B$9 -> 5.5428318e+08 | ... AF5: ='Cost Components'!$B$9 -> 5.5428318e+08
A6: Other OPEX | B6: 0 | C6: =('Cost Components'!$B$18-'Cost Components'!$B$17-'Cost Components'!$B$16) * 10^6 -> 75131299 | D6: =('Cost Components'!$B$18-'Cost Components'!$B$17-'Cost Components'!$B$16) * 10^6 -> 75131299 | E6: =('Cost Components'!$B$18-'Cost Components'!$B$17-'Cost Components'!$B$16) * 10^6 -> 75131299 | F6: =('Cost Components'!$B$18-'Cost Components'!$B$17-'Cost Components'!$B$16) * 10^6 -> 75131299 | G6: =('Cost Components'!$B$18-'Cost Components'!$B$17-'Cost Components'!$B$16) * 10^6 -> 75131299 | H6: =('Cost Components'!$B$18-'Cost Components'!$B$17-'Cost Components'!$B$16) * 10^6 -> 75131299 | I6: =('Cost Components'!$B$18-'Cost Components'!$B$17-'Cost Components'!$B$16) * 10^6 -> 75131299 | J6: =('Cost Components'!$B$18-'Cost Components'!$B$17-'Cost Components'!$B$16) * 10^6 -> 75131299 | ... AF6: =('Cost Components'!$B$18-'Cost Components'!$B$17-'Cost Components'!$B$16) * 10^6 -> 75131299
A8: Contributions
A9: CO2 | B9: =SUM(B3:AF3) / SUM($B$3:$AF$6) -> 0.50584247
A10: Electricity | B10: =SUM(B4:AF4) / SUM($B$3:$AF$6) -> 0.21688817
A11: CAPEX | B11: =SUM(B5:AF5) / SUM($B$3:$AF$6) -> 0.2451164
A12: Other OPEX | B12: =SUM(B6:AF6) / SUM($B$3:$AF$6) -> 0.032152972
A14: 2050 EU - North
A15: CO2 | B15: 0 | C15: =('Cost Components'!$B$53 * 10^6) / (1+'Cost Components'!$B$55) ^'Cost Breakdown'!C13 -> 1.06992e+09 | D15: =('Cost Components'!$B$53 * 10^6) / (1+'Cost Components'!$B$55) ^'Cost Breakdown'!D13 -> 1.06992e+09 | E15: =('Cost Components'!$B$53 * 10^6) / (1+'Cost Components'!$B$55) ^'Cost Breakdown'!E13 -> 1.06992e+09 | F15: =('Cost Components'!$B$53 * 10^6) / (1+'Cost Components'!$B$55) ^'Cost Breakdown'!F13 -> 1.06992e+09 | G15: =('Cost Components'!$B$53 * 10^6) / (1+'Cost Components'!$B$55) ^'Cost Breakdown'!G13 -> 1.06992e+09 | H15: =('Cost Components'!$B$53 * 10^6) / (1+'Cost Components'!$B$55) ^'Cost Breakdown'!H13 -> 1.06992e+09 | I15: =('Cost Components'!$B$53 * 10^6) / (1+'Cost Components'!$B$55) ^'Cost Breakdown'!I13 -> 1.06992e+09 | J15: =('Cost Components'!$B$53 * 10^6) / (1+'Cost Components'!$B$55) ^'Cost Breakdown'!J13 -> 1.06992e+09 | ... AF15: =('Cost Components'!$B$53 * 10^6) / (1+'Cost Components'!$B$55) ^'Cost Breakdown'!AF13 -> 1.06992e+09
A16: Electricity | B16: 0 | C16: =('Cost Components'!$B$51 * 10^6) / (1+'Cost Components'!$B$46) ^ 'Cost Breakdown'!C13 -> 2.1058691e+08 | D16: =('Cost Components'!$B$51 * 10^6) / (1+'Cost Components'!$B$46) ^ 'Cost Breakdown'!D13 -> 2.1058691e+08 | E16: =('Cost Components'!$B$51 * 10^6) / (1+'Cost Components'!$B$46) ^ 'Cost Breakdown'!E13 -> 2.1058691e+08 | F16: =('Cost Components'!$B$51 * 10^6) / (1+'Cost Components'!$B$46) ^ 'Cost Breakdown'!F13 -> 2.1058691e+08 | G16: =('Cost Components'!$B$51 * 10^6) / (1+'Cost Components'!$B$46) ^ 'Cost Breakdown'!G13 -> 2.1058691e+08 | H16: =('Cost Components'!$B$51 * 10^6) / (1+'Cost Components'!$B$46) ^ 'Cost Breakdown'!H13 -> 2.1058691e+08 | I16: =('Cost Components'!$B$51 * 10^6) / (1+'Cost Components'!$B$46) ^ 'Cost Breakdown'!I13 -> 2.1058691e+08 | J16: =('Cost Components'!$B$51 * 10^6) / (1+'Cost Components'!$B$46) ^ 'Cost Breakdown'!J13 -> 2.1058691e+08 | ... AF16: =('Cost Components'!$B$51 * 10^6) / (1+'Cost Components'!$B$46) ^ 'Cost Breakdown'!AF13 -> 2.1058691e+08
A17: CAPEX | B17: ='Cost Components'!$B$56 -> 3.010708e+08 | C17: ='Cost Components'!$B$56 -> 3.010708e+08 | D17: ='Cost Components'!$B$56 -> 3.010708e+08 | E17: ='Cost Components'!$B$56 -> 3.010708e+08 | F17: ='Cost Components'!$B$56 -> 3.010708e+08 | G17: ='Cost Components'!$B$56 -> 3.010708e+08 | H17: ='Cost Components'!$B$56 -> 3.010708e+08 | I17: ='Cost Components'!$B$56 -> 3.010708e+08 | ... AF17: ='Cost Components'!$B$56 -> 3.010708e+08
A18: Other OPEX | B18: 0 | C18: =('Cost Components'!$B$38-'Cost Components'!$B$37-'Cost Components'!$B$36) * 10^6 -> 66061299 | D18: =('Cost Components'!$B$38-'Cost Components'!$B$37-'Cost Components'!$B$36) * 10^6 -> 66061299 | E18: =('Cost Components'!$B$38-'Cost Components'!$B$37-'Cost Components'!$B$36) * 10^6 -> 66061299 | F18: =('Cost Components'!$B$38-'Cost Components'!$B$37-'Cost Components'!$B$36) * 10^6 -> 66061299 | G18: =('Cost Components'!$B$38-'Cost Components'!$B$37-'Cost Components'!$B$36) * 10^6 -> 66061299 | H18: =('Cost Components'!$B$38-'Cost Components'!$B$37-'Cost Components'!$B$36) * 10^6 -> 66061299 | I18: =('Cost Components'!$B$38-'Cost Components'!$B$37-'Cost Components'!$B$36) * 10^6 -> 66061299 | J18: =('Cost Components'!$B$38-'Cost Components'!$B$37-'Cost Components'!$B$36) * 10^6 -> 66061299 | ... AF18: =('Cost Components'!$B$38-'Cost Components'!$B$37-'Cost Components'!$B$36) * 10^6 -> 66061299
A20: Contributions
A21: CO2 | B21: =SUM(B15:AF15) / SUM($B$15:$AF$18) -> 0.64543423
A22: Electricity | B22: =SUM(B16:AF16) / SUM($B$15:$AF$18) -> 0.12703754
A23: CAPEX | B23: =SUM(B17:AF17) / SUM($B$15:$AF$18) -> 0.18767645
A24: Other OPEX | B24: =SUM(B18:AF18) / SUM($B$15:$AF$18) -> 0.039851787

Sheet Outputs
A1: 2024 - EU - North | H1: 2024 - EU - Central | O1: 2024 - EU - South
A2: Parameter | B2: Unit | C2: Base case | D2: Electricity correction | E2: DAC correction | F2: WACC correction | H2: Parameter | I2: Unit | J2: Base case | K2: Electricity correction | L2: DAC correction | M2: WACC correction | O2: Parameter | P2: Unit | Q2: Base case | R2: Electricity correction | S2: DAC correction | T2: WACC correction
A3: Syn-Fuel cost | B3: €/l | C3: ='MFSP Baseline'!B9 -> 4.6247535 | D3: ='MFSP Electricity'!B9 -> 3.9649548 | E3: ='MFSP CO2 Corrected'!B9 -> 7.043761 | F3: ='MFSP WACC Corrected'!B9 -> 6.7170632 | H3: Syn-Fuel cost | I3: €/l | J3: ='MFSP Baseline'!B31 -> 4.1041303 | K3: ='MFSP Electricity'!B31 -> 3.5751737 | L3: ='MFSP CO2 Corrected'!B31 -> 6.65398 | M3: ='MFSP WACC Corrected'!B31 -> 6.3945065 | O3: Syn-Fuel cost | P3: €/l | Q3: ='MFSP Baseline'!B55 -> 4.0448105 | R3: ='MFSP Electricity'!B55 -> 4.0208802 | S3: ='MFSP CO2 Corrected'!B55 -> 7.0996864 | T3: ='MFSP WACC Corrected'!B55 -> 6.7644023
A4: Syn-Fuel cost | B4: $/l | C4: =C3/Inputs!$C$6 -> 5.138615 | D4: =D3/Inputs!$C$6 -> 4.4055053 | E4: =E3/Inputs!$C$6 -> 7.8264011 | F4: =F3/Inputs!$C$6 -> 7.4634036 | H4: Syn-Fuel cost | I4: $/l | J4: =J3/Inputs!$C$6 -> 4.5601447 | K4: =K3/Inputs!$C$6 -> 3.9724152 | L4: =L3/Inputs!$C$6 -> 7.3933111 | M4: =M3/Inputs!$C$6 -> 7.1050072 | O4: Syn-Fuel cost | P4: $/l | Q4: =Q3/Inputs!$C$6 -> 4.4942339 | R4: =R3/Inputs!$C$6 -> 4.4676447 | S4: =S3/Inputs!$C$6 -> 7.8885405 | T4: =T3/Inputs!$C$6 -> 7.5160026
A5: Fossil Fuel cost | B5: $/l | C5: =Inputs!$C$16 -> 0.8 | D5: =Inputs!$C$16 -> 0.8 | E5: =Inputs!$C$16 -> 0.8 | F5: =Inputs!$C$16 -> 0.8 | H5: Fossil Fuel cost | I5: $/l | J5: =Inputs!$C$16 -> 0.8 | K5: =Inputs!$C$16 -> 0.8 | L5: =Inputs!$C$16 -> 0.8 | M5: =Inputs!$C$16 -> 0.8 | O5: Fossil Fuel cost | P5: $/l | Q5: =Inputs!$C$16 -> 0.8 | R5: =Inputs!$C$16 -> 0.8 | S5: =Inputs!$C$16 -> 0.8 | T5: =Inputs!$C$16 -> 0.8
A6: Syn-Fuel emissions | B6: gCO2eq/MJ | C6: ='Study Parameters'!$C$35 -> 5.9 | D6: ='Study Parameters'!$C$35 -> 5.9 | E6: ='Study Parameters'!$C$35 -> 5.9 | F6: ='Study Parameters'!$C$35 -> 5.9 | H6: Syn-Fuel emissions | I6: gCO2eq/MJ | J6: ='Study Parameters'!$C$35 -> 5.9 | K6: ='Study Parameters'!$C$35 -> 5.9 | L6: ='Study Parameters'!$C$35 -> 5.9 | M6: ='Study Parameters'!$C$35 -> 5.9 | O6: Syn-Fuel emissions | P6: gCO2eq/MJ | Q6: ='Study Parameters'!$C$35 -> 5.9 | R6: ='Study Parameters'!$C$35 -> 5.9 | S6: ='Study Parameters'!$C$35 -> 5.9 | T6: ='Study Parameters'!$C$35 -> 5.9
A7: Fossil Fuel emissions | B7: gCO2eq/MJ | C7: =Inputs!$C$11 -> 88.7 | D7: =Inputs!$C$11 -> 88.7 | E7: =Inputs!$C$11 -> 88.7 | F7: =Inputs!$C$11 -> 88.7 | H7: Fossil Fuel emissions | I7: gCO2eq/MJ | J7: =Inputs!$C$11 -> 88.7 | K7: =Inputs!$C$11 -> 88.7 | L7: =Inputs!$C$11 -> 88.7 | M7: =Inputs!$C$11 -> 88.7 | O7: Fossil Fuel emissions | P7: gCO2eq/MJ | Q7: =Inputs!$C$11 -> 88.7 | R7: =Inputs!$C$11 -> 88.7 | S7: =Inputs!$C$11 -> 88.7 | T7: =Inputs!$C$11 -> 88.7
A8: CO2 Abated | B8: gCO2eq/MJ | C8: =C7-C6 -> 82.8 | D8: =D7-D6 -> 82.8 | E8: =E7-E6 -> 82.8 | F8: =F7-F6 -> 82.8 | H8: CO2 Abated | I8: gCO2eq/MJ | J8: =J7-J6 -> 82.8 | K8: =K7-K6 -> 82.8 | L8: =L7-L6 -> 82.8 | M8: =M7-M6 -> 82.8 | O8: CO2 Abated | P8: gCO2eq/MJ | Q8: =Q7-Q6 -> 82.8 | R8: =R7-R6 -> 82.8 | S8: =S7-S6 -> 82.8 | T8: =T7-T6 -> 82.8
A9: CO2 Abated | B9: gCO2eq/l | C9: =C8*Inputs!$C$14 -> 2872.2989 | D9: =D8*Inputs!$C$14 -> 2872.2989 | E9: =E8*Inputs!$C$14 -> 2872.2989 | F9: =F8*Inputs!$C$14 -> 2872.2989 | H9: CO2 Abated | I9: gCO2eq/l | J9: =J8*Inputs!$C$14 -> 2872.2989 | K9: =K8*Inputs!$C$14 -> 2872.2989 | L9: =L8*Inputs!$C$14 -> 2872.2989 | M9: =M8*Inputs!$C$14 -> 2872.2989 | O9: CO2 Abated | P9: gCO2eq/l | Q9: =Q8*Inputs!$C$14 -> 2872.2989 | R9: =R8*Inputs!$C$14 -> 2872.2989 | S9: =S8*Inputs!$C$14 -> 2872.2989 | T9: =T8*Inputs!$C$14 -> 2872.2989
A10: Abatement cost | B10: $/tCO2 | C10: =((C4-C5)/C9) * 10^6 -> 1510.5026 | D10: =((D4-D5)/D9) * 10^6 -> 1255.2682 | E10: =((E4-E5)/E9) * 10^6 -> 2446.2639 | F10: =((F4-F5)/F9) * 10^6 -> 2319.8852 | H10: Abatement cost | I10: $/tCO2 | J10: =((J4-J5)/J9) * 10^6 -> 1309.1064 | K10: =((K4-K5)/K9) * 10^6 -> 1104.4865 | L10: =((L4-L5)/L9) * 10^6 -> 2295.4822 | M10: =((M4-M5)/M9) * 10^6 -> 2195.1083 | O10: Abatement cost | P10: $/tCO2 | Q10: =((Q4-Q5)/Q9) * 10^6 -> 1286.1593 | R10: =((R4-R5)/R9) * 10^6 -> 1276.9022 | S10: =((S4-S5)/S9) * 10^6 -> 2467.8979 | T10: =((T4-T5)/T9) * 10^6 -> 2338.1977
A12: 2050 - EU - North | H12: 2050 - EU - Central | O12: 2050 - EU - South
A13: Parameter | B13: Unit | C13: Base case | D13: Electricity correction | E13: DAC correction | F13: WACC correction | H13: Parameter | I13: Unit | J13: Base case | K13: Electricity correction | L13: DAC correction | M13: WACC correction | O13: Parameter | P13: Unit | Q13: Base case | R13: Electricity correction | S13: DAC correction | T13: WACC correction
A14: Syn-Fuel cost | B14: €/l | C14: ='MFSP Baseline'!B19 -> 2.8726142 | D14: ='MFSP Electricity'!B19 -> 1.8914706 | E14: ='MFSP CO2 Corrected'!B19 -> 2.7886431 | F14: ='MFSP WACC Corrected'!B19 -> 2.5930433 | H14: Syn-Fuel cost | I14: €/l | J14: ='MFSP Baseline'!B42 -> 3.2708823 | K14: ='MFSP Electricity'!B42 -> 1.9055683 | L14: ='MFSP CO2 Corrected'!B42 -> 2.8027408 | M14: ='MFSP WACC Corrected'!B42 -> 2.6053608 | O14: Syn-Fuel cost | P14: €/l | Q14: ='MFSP Baseline'!B65 -> 2.8712012 | R14: ='MFSP Electricity'!B65 -> 1.8900576 | S14: ='MFSP CO2 Corrected'!B65 -> 2.7872301 | T14: ='MFSP WACC Corrected'!B65 -> 2.5921015
A15: Syn-Fuel cost | B15: $/l | C15: =C14/Inputs!$C$6 -> 3.1917935 | D15: =D14/Inputs!$C$6 -> 2.101634 | E15: =E14/Inputs!$C$6 -> 3.0984923 | F15: =F14/Inputs!$C$6 -> 2.8811592 | H15: Syn-Fuel cost | I15: $/l | J15: =J14/Inputs!$C$6 -> 3.6343137 | K15: =K14/Inputs!$C$6 -> 2.1172981 | L15: =L14/Inputs!$C$6 -> 3.1141564 | M15: =M14/Inputs!$C$6 -> 2.8948454 | O15: Syn-Fuel cost | P15: $/l | Q15: =Q14/Inputs!$C$6 -> 3.1902235 | R15: =R14/Inputs!$C$6 -> 2.100064 | S15: =S14/Inputs!$C$6 -> 3.0969224 | T15: =T14/Inputs!$C$6 -> 2.8801128
A16: Fossil Fuel cost | B16: $/l | C16: =Inputs!$C$18 -> 0.8 | D16: =Inputs!$C$18 -> 0.8 | E16: =Inputs!$C$18 -> 0.8 | F16: =Inputs!$C$18 -> 0.8 | H16: Fossil Fuel cost | I16: $/l | J16: =Inputs!$C$18 -> 0.8 | K16: =Inputs!$C$18 -> 0.8 | L16: =Inputs!$C$18 -> 0.8 | M16: =Inputs!$C$18 -> 0.8 | O16: Fossil Fuel cost | P16: $/l | Q16: =Inputs!$C$18 -> 0.8 | R16: =Inputs!$C$18 -> 0.8 | S16: =Inputs!$C$18 -> 0.8 | T16: =Inputs!$C$18 -> 0.8
A17: Syn-Fuel emissions | B17: gCO2eq/MJ | C17: ='Study Parameters'!$C$35 -> 5.9 | D17: ='Study Parameters'!$C$35 -> 5.9 | E17: ='Study Parameters'!$C$35 -> 5.9 | F17: ='Study Parameters'!$C$35 -> 5.9 | H17: Syn-Fuel emissions | I17: gCO2eq/MJ | J17: ='Study Parameters'!$C$35 -> 5.9 | K17: ='Study Parameters'!$C$35 -> 5.9 | L17: ='Study Parameters'!$C$35 -> 5.9 | M17: ='Study Parameters'!$C$35 -> 5.9 | O17: Syn-Fuel emissions | P17: gCO2eq/MJ | Q17: ='Study Parameters'!$C$35 -> 5.9 | R17: ='Study Parameters'!$C$35 -> 5.9 | S17: ='Study Parameters'!$C$35 -> 5.9 | T17: ='Study Parameters'!$C$35 -> 5.9
A18: Fossil Fuel emissions | B18: gCO2eq/MJ | C18: =Inputs!$C$11 -> 88.7 | D18: =Inputs!$C$11 -> 88.7 | E18: =Inputs!$C$11 -> 88.7 | F18: =Inputs!$C$11 -> 88.7 | H18: Fossil Fuel emissions | I18: gCO2eq/MJ | J18: =Inputs!$C$11 -> 88.7 | K18: =Inputs!$C$11 -> 88.7 | L18: =Inputs!$C$11 -> 88.7 | M18: =Inputs!$C$11 -> 88.7 | O18: Fossil Fuel emissions | P18: gCO2eq/MJ | Q18: =Inputs!$C$11 -> 88.7 | R18: =Inputs!$C$11 -> 88.7 | S18: =Inputs!$C$11 -> 88.7 | T18: =Inputs!$C$11 -> 88.7
A19: CO2 Abated | B19: gCO2eq/MJ | C19: =C18-C17 -> 82.8 | D19: =D18-D17 -> 82.8 | E19: =E18-E17 -> 82.8 | F19: =F18-F17 -> 82.8 | H19: CO2 Abated | I19: gCO2eq/MJ | J19: =J18-J17 -> 82.8 | K19: =K18-K17 -> 82.8 | L19: =L18-L17 -> 82.8 | M19: =M18-M17 -> 82.8 | O19: CO2 Abated | P19: gCO2eq/MJ | Q19: =Q18-Q17 -> 82.8 | R19: =R18-R17 -> 82.8 | S19: =S18-S17 -> 82.8 | T19: =T18-T17 -> 82.8
A20: CO2 Abated | B20: gCO2eq/l | C20: =C19*Inputs!$C$14 -> 2872.2989 | D20: =D19*Inputs!$C$14 -> 2872.2989 | E20: =E19*Inputs!$C$14 -> 2872.2989 | F20: =F19*Inputs!$C$14 -> 2872.2989 | H20: CO2 Abated | I20: gCO2eq/l | J20: =J19*Inputs!$C$14 -> 2872.2989 | K20: =K19*Inputs!$C$14 -> 2872.2989 | L20: =L19*Inputs!$C$14 -> 2872.2989 | M20: =M19*Inputs!$C$14 -> 2872.2989 | O20: CO2 Abated | P20: gCO2eq/l | Q20: =Q19*Inputs!$C$14 -> 2872.2989 | R20: =R19*Inputs!$C$14 -> 2872.2989 | S20: =S19*Inputs!$C$14 -> 2872.2989 | T20: =T19*Inputs!$C$14 -> 2872.2989
A21: Abatement cost | B21: $/tCO2 | C21: =((C15-C16)/C20) * 10^6 -> 832.71053 | D21: =((D15-D16)/D20) * 10^6 -> 453.16802 | E21: =((E15-E16)/E20) * 10^6 -> 800.22743 | F21: =((F15-F16)/F20) * 10^6 -> 724.56219 | H21: Abatement cost | I21: $/tCO2 | J21: =((J15-J16)/J20) * 10^6 -> 986.77533 | K21: =((K15-K16)/K20) * 10^6 -> 458.62151 | L21: =((L15-L16)/L20) * 10^6 -> 805.68092 | M21: =((M15-M16)/M20) * 10^6 -> 729.32708 | O21: Abatement cost | P21: $/tCO2 | Q21: =((Q15-Q16)/Q20) * 10^6 -> 832.16394 | R21: =((R15-R16)/R20) * 10^6 -> 452.62143 | S21: =((S15-S16)/S20) * 10^6 -> 799.68083 | T21: =((T15-T16)/T20) * 10^6 -> 724.19788
A23: Full Abatement - 2024 - EU - North | H23: Full Abatement - 2024 - EU - Central | O23: Full Abatement - 2024 - EU - South
A24: Parameter | B24: Unit | C24: Value | H24: Parameter | I24: Unit | J24: Value | O24: Parameter | P24: Unit | Q24: Value
A25: Residual Emissions | B25: gCO2eq/l | C25: =C6*Inputs!$C$14 -> 204.66864 | H25: Residual Emissions | I25: gCO2eq/l | J25: =J6*Inputs!$C$14 -> 204.66864 | O25: Residual Emissions | P25: gCO2eq/l | Q25: =Q6*Inputs!$C$14 -> 204.66864
A26: Emissions Reduction Cost | B26: $/l | C26: =C25*Inputs!$C$32 * 10^-6 -> 0.2623852 | H26: Emissions Reduction Cost | I26: $/l | J26: =J25*Inputs!$C$32 * 10^-6 -> 0.2623852 | O26: Emissions Reduction Cost | P26: $/l | Q26: =Q25*Inputs!$C$32 * 10^-6 -> 0.2623852
A27: Effective Synfuel Cost | B27: $/l | C27: =F4+C26 -> 7.7257888 | H27: Effective Synfuel Cost | I27: $/l | J27: =M4+J26 -> 7.3673924 | O27: Effective Synfuel Cost | P27: $/l | Q27: =T4+Q26 -> 7.7783878
A28: Effective Abatement Cost | B28: $/tCO2 | C28: =(C27-C16) /C20 * 10^6 -> 2411.2354 | H28: Effective Abatement Cost | I28: $/tCO2 | J28: =(J27-J16) /J20 * 10^6 -> 2286.4586 | O28: Effective Abatement Cost | P28: $/tCO2 | Q28: =(Q27-Q16) /Q20 * 10^6 -> 2429.5479
A30: Full Abatement - 2050 - EU - North | H30: Full Abatement - 2050 - EU - Central | O30: Full Abatement - 2050 - EU - South
A31: Parameter | B31: Unit | C31: Value | H31: Parameter | I31: Unit | J31: Value | O31: Parameter | P31: Unit | Q31: Value
A32: Residual Emissions | B32: gCO2eq/l | C32: =C15*Inputs!$C$14 -> 110.72204 | H32: Residual Emissions | I32: gCO2eq/l | J32: =J15*Inputs!$C$14 -> 126.07289 | O32: Residual Emissions | P32: gCO2eq/l | Q32: =Q15*Inputs!$C$14 -> 110.66758
A33: Emissions Reduction Cost | B33: $/l | C33: =C32*Inputs!$C$33 * 10^-6 -> 0.053146579 | H33: Emissions Reduction Cost | I33: $/l | J33: =J32*Inputs!$C$33 * 10^-6 -> 0.060514986 | O33: Emissions Reduction Cost | P33: $/l | Q33: =Q32*Inputs!$C$33 * 10^-6 -> 0.053120438
A34: Effective Synfuel Cost | B34: $/l | C34: =F15+C33 -> 2.9343058 | H34: Effective Synfuel Cost | I34: $/l | J34: =M15+J33 -> 2.9553603 | O34: Effective Synfuel Cost | P34: $/l | Q34: =T15+Q33 -> 2.9332332
A35: Effective Abatement Cost | B35: $/tCO2 | C35: =(C34-C16) /C20 * 10^6 -> 743.06534 | H35: Effective Abatement Cost | I35: $/tCO2 | J35: =(J34-J16) /J20 * 10^6 -> 750.39557 | O35: Effective Abatement Cost | P35: $/tCO2 | Q35: =(Q34-Q16) /Q20 * 10^6 -> 742.69193
A38: 2024 - FLH
A39: Parameter | B39: Unit | C39: Lower FLH
A40: Syn-Fuel cost | B40: €/l | C40: ='MFSP WACC Corrected'!B76 -> 0
A41: Syn-Fuel cost | B41: $/l | C41: =C40/Inputs!$C$6 -> 0
A42: Fossil Fuel cost | B42: $/l | C42: =Inputs!$C$16 -> 0.8
A43: Syn-Fuel emissions | B43: gCO2eq/MJ | C43: ='Study Parameters'!$C$35 -> 5.9
A44: Fossil Fuel emissions | B44: gCO2eq/MJ | C44: =Inputs!$C$11 -> 88.7
A45: CO2 Abated | B45: gCO2eq/MJ | C45: =C44-C43 -> 82.8
A46: CO2 Abated | B46: gCO2eq/l | C46: =C45*Inputs!$C$14 -> 2872.2989
A47: Abatement cost | B47: $/tCO2 | C47: =((C41-C42)/C46) * 10^6 -> -278.52255
