Workbook

Sheet Inputs
A1: Parameter | B1: Year | C1: Value | D1: Unit
A2: Standard Values
A3: Current Year | C3: =[1]Inputs!C4 -> 2024
A4: Inflation | C4: =[1]Inputs!C5 -> 0.02
A5: WACC | C5: =[1]Inputs!C6 -> 0.07
A6: USD to EUR | C6: =[1]Inputs!C7 -> 0.9
A7: Electricity
A8: LCOE | B8: 2024 | C8: =[1]Inputs!C9 -> 64 | D8: $/MWh
A9: LCOE | B9: 2050 | C9: =[1]Inputs!C10 -> 11 | D9: $/MWh
A10: Jet Fuel A-1 Characteristics
A11: Emissions Intensity | B11: 2024 | C11: =[1]Inputs!C12 -> 88.7 | D11: gCO2/MJ
A12: Emissions Intensity | B12: 2050 | C12: =[1]Inputs!C13 -> 88.7 | D12: gCO2/MJ
A13: Energy Density | C13: =[1]Inputs!C14 -> 43.2 | D13: MJ/kg
A14: Energy Density | C14: =[1]Inputs!C15 -> 34.6896 | D14: MJ/l
A15: Volumetric Density | C15: =[1]Inputs!C16 -> 0.803 | D15: kg/l
A16: Jet Fuel A-1 Price | B16: 2024 | C16: =[1]Inputs!C17 -> 0.8 | D16: $/l
A17: Scenario Specific Values
A18: Jet Fuel A-1 Price | B18: 2050 | C18: =[1]Inputs!C19 -> 1.7 | D18: $/l
A19: IEA Reference
A20: Jet Fuel A-1 Price | B20: 2024 | C20: =[1]Inputs!C21 -> 0.32246154 | D20: $/l
A21: Jet Fuel A-1 Price | B21: 2050 | C21: =[1]Inputs!C22 -> 0.20923077 | D21: $/l
A22: EIA Reference
A23: Jet Fuel A-1 Price | B23: 2024 | C23: =[1]Inputs!C24 -> 1.0209014 | D23: $/l
A24: Jet Fuel A-1 Price | B24: 2050 | C24: =[1]Inputs!C25 -> 2.0095594 | D24: $/l
A25: EIA Low Oil Price Scenario
A26: Jet Fuel A-1 Price | B26: 2024 | C26: =[1]Inputs!C27 -> 0.48286833 | D26: $/l
A27: Jet Fuel A-1 Price | B27: 2050 | C27: =[1]Inputs!C28 -> 0.89646575 | D27: $/l
A28: EIA High Scenario
A29: Jet Fuel A-1 Price | B29: 2024 | C29: =[1]Inputs!C30 -> 1.8838713 | D29: $/l
A30: Jet Fuel A-1 Price | B30: 2050 | C30: =[1]Inputs!C31 -> 3.7893731 | D30: $/l
A31: Direct Air Capture
A32: LCOR | B32: 2024 | C32: =[1]Inputs!C33 -> 1371 | D32: $/tCO2
A33: LCOR | B33: 2050 | C33: =[1]Inputs!C34 -> 523 | D33: $/tCO2

Sheet Study Parameters
A1: Key Parameters
A2: Parameter | B2: Year | C2: Value | D2: Unit | E2: Source | F2: Notes
A3: Discount Rate | B3: Both | C3: 0.05 | E3: Seymour et. al. 2024
A4: Plant Lifetime | B4: Both | C4: 30 | D4: years | E4: Seymour et. al. 2024 Table 1
A5: Li-Ion Battery Lifetime | B5: Both | C5: 15 | D5: years | E5: Seymour et. al. 2024 Table 1
A6: Electrolyser Stack Lifetime | B6: Both | C6: 10 | D6: years
A8: Plant Parameters
A9: Parameter | B9: Year | C9: Value | D9: Unit | E9: Source | F9: Notes
A10: Fuel Synthesis Capacity | B10: Both | C10: 2.5 | D10: MW | E10: Seymour et. al. 2024 Supporting Information
A11: Electrolyzer Capacity | B11: Both | C11: 12 | D11: MW | E11: Seymour et. al. 2024 Supporting Information
A12: Battery Capacity | B12: Both | C12: 2 | D12: MWh | E12: Seymour et. al. 2024 Supporting Information | F12: This cost may be neglected as grid supply is assumed
A13: CO2 Storage | B13: Both | C13: 150 | D13: tonnes | E13: Seymour et. al. 2024 Supporting Information
A14: H2 Storage | B14: Both | C14: 200 | D14: MWh | E14: Seymour et. al. 2024 Supporting Information
A15: Electric Boiler Capacity | B15: Both | C15: =5*10^6 /C21 -> 570.77626 | D15: kW | E15: Seymour et. al. 2024 Table 1 | F15: Calculated from boiler consumption and full load hours
A17: Process Parameters
A18: Parameter | B18: Year | C18: Value | D18: Unit | E18: Source | F18: Notes
A19: CO2 Caputre | B19: Both | C19: 0.7 | D19: t/hour | E19: Seymour et. al. 2024 Supporting Information
A20: CO2 Caputre | B20: Both | C20: =C19*C21 -> 6132 | D20: t/year | F20: Calculated
A21: Full Load Hours | B21: Both | C21: 8760 | D21: hours | F21: Calculated from Fuel Production and fuel synthesis capacity
A22: Annual Fuel Production | B22: Both | C22: 22 | D22: GWh | E22: Seymour et. al. 2024
A23: Annual Fuel Production | B23: Both | C23: 1700 | D23: tonnes | E23: Seymour et. al. 2024
A24: Annual Fuel Production | B24: Both | C24: =C23/Inputs!C15 * 10^3 -> 2117061 | D24: litres
A25: Annual Electricity Consumption | B25: Both | C25: 66.5 | D25: GWh | E25: Seymour et. al. 2024 Figure 6
A27: External Costs
A28: Parameter | B28: Year | C28: Value | D28: Unit | E28: Source | F28: Notes
A29: DAC CAPEX | B29: 2024 | C29: 790 | D29: €/tCO2 | E29: Seymour et. al. 2024 Table 1
A30: DAC CAPEX | B30: 2050 | C30: 199 | D30: €/tCO2 | E30: Seymour et. al. 2024 Table 1
A31: Electricity Price | B31: 2024 | C31: 60 | D31: €/MWh | E31: Seymour et. al. 2024 Figure 1 | F31: Electricity Price is inferred as LCOE from the study
A32: Electricity Price | B32: 2050 | C32: 30 | D32: €/MWh | E32: Seymour et. al. 2024 Figure 1 | F32: Electricity Price is inferred as LCOE from the study
A34: Fuel Parameters
A35: Parameter | B35: Year | C35: Value | D35: Unit | E35: Source | F35: Notes
A36: Syn-fuel emissions | B36: Both | C36: 0.38 | D36: kgCO2/kg fuel | E36: Seymour et. al. 2024
A37: Syn-fuel emissions | B37: Both | C37: =(C36 * 1000) / 43.2 -> 8.7962963 | D37: kgCO2eq/MJ | E37: Seymour et. al. 2024

Sheet Cost Components
A1: Economic Assumptions 2024 | G1: Economic Assumptions 2050
A2: CAPEX | G2: CAPEX
A3: Component | B3: Value | C3: Unit | D3: Source | E3: Notes | G3: Component | H3: Value | I3: Unit | J3: Source | K3: Notes
A4: Fuel Synthesis | B4: =('Study Parameters'!C10*1.25 * 10^3 * 799) / 10 ^ 6 -> 2.496875 | C4: M€ | D4: Seymour et. al. 2024 Table 1 | G4: Fuel Synthesis | H4: =('Study Parameters'!C10 * 452 * 10^3) / 10^6 -> 1.13 | I4: M€ | J4: Seymour et. al. 2024 Table 1
A5: Electrolyser | B5: =('Study Parameters'!C11*1084 * 10 ^ 3) / 10^6 -> 13.008 | C5: M€ | D5: Seymour et. al. 2024 Table 1 | G5: Electrolyser | H5: =('Study Parameters'!C11* 358 * 10 ^ 3) / 10^6 -> 4.296 | I5: M€ | J5: Seymour et. al. 2024 Table 1
A6: CO2 Storage | B6: =(1500 * 'Study Parameters'!C13) / 10^ 6 -> 0.225 | C6: M€ | D6: Seymour et. al. 2024 Table 1 | G6: CO2 Storage | H6: =(750 * 'Study Parameters'!C13) / 10^6 -> 0.1125 | I6: M€ | J6: Seymour et. al. 2024 Table 1
A7: H2 Storage | B7: =(21*'Study Parameters'!C14 * 10 ^ 3) / 10^6 -> 4.2 | C7: M€ | D7: Seymour et. al. 2024 Table 1 | G7: H2 Storage | H7: =('Study Parameters'!C14 * 11 * 10^3) / 10^6 -> 2.2 | I7: M€ | J7: Seymour et. al. 2024 Table 1
A8: Electrical Boiler | B8: =(100 * 'Study Parameters'!C15) / 10^6 -> 0.057077626 | C8: M€ | D8: Seymour et. al. 2024 Table 1 | G8: Electrical Boiler | H8: =(100 * 'Study Parameters'!C15) / 10^6 -> 0.057077626 | I8: M€ | J8: Seymour et. al. 2024 Table 1
A9: Li-Ion Battery | B9: =('Study Parameters'!C12 * 10^3 * 324) / 10^6 -> 0.648 | C9: M€ | D9: Seymour et. al. 2024 Table 1 | G9: Li-Ion Battery | H9: ='Study Parameters'!C12 * 10^3 * 129 / 10^6 -> 0.258 | I9: M€ | J9: Seymour et. al. 2024 Table 1
A10: Electrolyser Stack Replacement | B10: =0.33 * B5 -> 4.29264 | C10: M€ | D10: Seymour et. al. 2024 Table 1 | G10: Electrolyser Stack Replacement | H10: =0.25*H5 -> 1.074 | I10: M€ | J10: Seymour et. al. 2024 Table 1
A11: Total CAPEX | B11: =SUM(B4:B10) -> 24.927593 | C11: M€ | G11: Total CAPEX | H11: =SUM(H4:H10) -> 9.1275776 | I11: M€
A13: OPEX | G13: OPEX
A14: Component | B14: Value | C14: Unit | D14: Source | E14: Notes | G14: Component | H14: Value | I14: Unit | J14: Source | K14: Notes
A15: Fuel Synthesis | B15: =0.025 *B4 -> 0.062421875 | C15: M€/year | D15: Seymour et. al. 2024 Table 1 | G15: Fuel Synthesis | H15: =0.025 *H4 -> 0.02825 | I15: M€/year | J15: Seymour et. al. 2024 Table 1
A16: Electrolyser | B16: =0.025 * B5 -> 0.3252 | C16: M€/year | D16: Seymour et. al. 2024 Table 1 | G16: Electrolyser | H16: =0.025 * H5 -> 0.1074 | I16: M€/year | J16: Seymour et. al. 2024 Table 1
A17: CO2 Storage | B17: =0.025 * B6 -> 0.005625 | C17: M€/year | D17: Seymour et. al. 2024 Table 1 | G17: CO2 Storage | H17: =0.025 * H6 -> 0.0028125 | I17: M€/year | J17: Seymour et. al. 2024 Table 1
A18: H2 Storage | B18: =0.01*B7 -> 0.042 | C18: M€/year | D18: Seymour et. al. 2024 Table 1 | G18: H2 Storage | H18: =0.01*H7 -> 0.022 | I18: M€/year | J18: Seymour et. al. 2024 Table 1
A19: DAC | B19: =('Study Parameters'!C29*'Study Parameters'!C20) / 10^6 -> 4.84428 | C19: M€/year | D19: Seymour et. al. 2024 | E19: Calculated | G19: DAC | H19: =('Study Parameters'!C30*'Study Parameters'!C20) / 10^6 -> 1.220268 | I19: M€/year | J19: Seymour et. al. 2024 | K19: Calculated
A20: Li-Ion Battery | B20: =0.025*B9 -> 0.0162 | C20: M€/year | D20: Seymour et. al. 2024 Table 1 | G20: Li-Ion Battery | H20: =0.025*H9 -> 0.00645 | I20: M€/year
A21: Electricity | B21: =('Study Parameters'!C25 * 'Study Parameters'!C31 * 10^3) / 10^6 -> 3.99 | C21: M€/year | D21: Seymour et. al. 2024 | E21: Calculated | G21: Electricity | H21: =('Study Parameters'!C32*'Study Parameters'!C25 * 10^3) / 10^6 -> 1.995 | I21: M€/year | J21: Seymour et. al. 2024 | K21: Calculated
A22: Total OPEX | B22: =SUM(B15:B21) -> 9.2857269 | C22: M€/year | G22: Total OPEX | H22: =SUM(H15:H21) -> 3.3821805 | I22: M€/year
A24: Standardized Economic Assumptions 2024 | G24: Standardized Economic Assumptions 2050
A25: Component | B25: Value | C25: Unit | D25: Source | E25: Notes | G25: Component | H25: Value | I25: Unit | J25: Source | K25: Notes
A26: Electricity | B26: =(Inputs!C8*'Study Parameters'!C25 * 10^3) / 10^6 -> 4.256 | C26: M€/year | G26: Electricity | H26: =(Inputs!C9*'Study Parameters'!C25*10^3) / 10^6 -> 0.7315 | I26: M€/year
A27: LCOE Corrected OPEX | B27: =B22-B21-B20+B26 -> 9.5355269 | C27: M€/year | G27: LCOE Corrected OPEX | H27: =H22-H21-H20+H26 -> 2.1122305 | I27: M€/year
A28: CO2 Cost | B28: =(Inputs!C32*'Study Parameters'!C20)/10^6 -> 8.406972 | C28: M€/year | G28: CO2 Cost | H28: =(Inputs!C33*'Study Parameters'!C20) / 10^6 -> 3.207036 | I28: M€/year
A29: CO2 Corrected OPEX | B29: =B27-B19+B28 -> 13.098219 | C29: M€/year | G29: CO2 Corrected OPEX | H29: =H27-H19+H28 -> 4.0989985 | I29: M€/year
A30: WACC | B30: 0.07 | G30: WACC | H30: 0.07
A32: Standardized Economic Assumptions 2024 - FLH
A33: Component | B33: Value | C33: Unit | D33: Source | E33: Notes
A34: Electricity | B34: =B26*4200/8760 -> 2.0405479 | C34: M€/year
A35: LCOE Corrected OPEX | B35: =B22+B34-B21 -> 7.3362748 | C35: M€/year
A36: CO2 Cost | B36: =B28*4200/8760 -> 4.03074 | C36: M€/year
A37: CO2 Corrected OPEX | B37: =B27-B19+B36 -> 8.7219869 | C37: M€/year

Sheet MFSP Baseline
A1: Economic Model 2024
A2: Year | B2: 0 | C2: 1 | D2: 2 | E2: 3 | F2: 4 | G2: 5 | H2: 6 | I2: 7 | J2: 8 | K2: 9 | L2: 10 | M2: 11 | N2: 12 | O2: 13 | P2: 14 | Q2: 15 | R2: 16 | S2: 17 | T2: 18 | U2: 19 | V2: 20 | W2: 21 | X2: 22 | Y2: 23 | Z2: 24 | AA2: 25 | AB2: 26 | AC2: 27 | AD2: 28 | AE2: 29 | AF2: 30
A3: Cost (€) | B3: ='Cost Components'!B11 * 10^6 -> 24927593 | C3: ='Cost Components'!$B$22 * 10^6 -> 9285726.9 | D3: ='Cost Components'!$B$22 * 10^6 -> 9285726.9 | E3: ='Cost Components'!$B$22 * 10^6 -> 9285726.9 | F3: ='Cost Components'!$B$22 * 10^6 -> 9285726.9 | G3: ='Cost Components'!$B$22 * 10^6 -> 9285726.9 | H3: ='Cost Components'!$B$22 * 10^6 -> 9285726.9 | I3: ='Cost Components'!$B$22 * 10^6 -> 9285726.9 | J3: ='Cost Components'!$B$22 * 10^6 -> 9285726.9 | K3: ='Cost Components'!$B$22 * 10^6 -> 9285726.9 | L3: ='Cost Components'!$B$22 * 10^6 + 'Cost Components'!B10 * 10^6 -> 13578367 | M3: ='Cost Components'!$B$22 * 10^6 -> 9285726.9 | N3: ='Cost Components'!$B$22 * 10^6 -> 9285726.9 | O3: ='Cost Components'!$B$22 * 10^6 -> 9285726.9 | P3: ='Cost Components'!$B$22 * 10^6 -> 9285726.9 | Q3: ='Cost Components'!$B$22 * 10^6 + 'Cost Components'!B9 * 10^6 -> 9933726.9 | R3: ='Cost Components'!$B$22 * 10^6 -> 9285726.9 | S3: ='Cost Components'!$B$22 * 10^6 -> 9285726.9 | T3: ='Cost Components'!$B$22 * 10^6 -> 9285726.9 | U3: ='Cost Components'!$B$22 * 10^6 -> 9285726.9 | V3: ='Cost Components'!$B$22 * 10^6 + 'Cost Components'!B10 * 10^6 -> 13578367 | W3: ='Cost Components'!$B$22 * 10^6 -> 9285726.9 | X3: ='Cost Components'!$B$22 * 10^6 -> 9285726.9 | Y3: ='Cost Components'!$B$22 * 10^6 -> 9285726.9 | Z3: ='Cost Components'!$B$22 * 10^6 -> 9285726.9 | AA3: ='Cost Components'!$B$22 * 10^6 -> 9285726.9 | AB3: ='Cost Components'!$B$22 * 10^6 -> 9285726.9 | AC3: ='Cost Components'!$B$22 * 10^6 -> 9285726.9 | AD3: ='Cost Components'!$B$22 * 10^6 -> 9285726.9 | ... AF3: ='Cost Components'!$B$22 * 10^6 -> 9285726.9
A4: Discounted Cost (€) | B4: =B3 / (1+'Study Parameters'!$C$3) ^B2 -> 24927593 | C4: =C3 / (1+'Study Parameters'!$C$3) ^C2 -> 8843549.4 | D4: =D3 / (1+'Study Parameters'!$C$3) ^D2 -> 8422428 | E4: =E3 / (1+'Study Parameters'!$C$3) ^E2 -> 8021360 | F4: =F3 / (1+'Study Parameters'!$C$3) ^F2 -> 7639390.5 | G4: =G3 / (1+'Study Parameters'!$C$3) ^G2 -> 7275610 | H4: =H3 / (1+'Study Parameters'!$C$3) ^H2 -> 6929152.4 | I4: =I3 / (1+'Study Parameters'!$C$3) ^I2 -> 6599192.7 | ... AF4: =AF3 / (1+'Study Parameters'!$C$3) ^AF2 -> 2148507.8
A5: Production (l) | B5: ='Study Parameters'!$C$24 -> 2117061 | C5: ='Study Parameters'!$C$24 -> 2117061 | D5: ='Study Parameters'!$C$24 -> 2117061 | E5: ='Study Parameters'!$C$24 -> 2117061 | F5: ='Study Parameters'!$C$24 -> 2117061 | G5: ='Study Parameters'!$C$24 -> 2117061 | H5: ='Study Parameters'!$C$24 -> 2117061 | I5: ='Study Parameters'!$C$24 -> 2117061 | ... AF5: ='Study Parameters'!$C$24 -> 2117061
A6: Discounted Production (l) | B6: =B5/(1+'Study Parameters'!$C$3) ^'MFSP Baseline'!B2 -> 2117061 | C6: =C5/(1+'Study Parameters'!$C$3) ^'MFSP Baseline'!C2 -> 2016248.6 | D6: =D5/(1+'Study Parameters'!$C$3) ^'MFSP Baseline'!D2 -> 1920236.8 | E6: =E5/(1+'Study Parameters'!$C$3) ^'MFSP Baseline'!E2 -> 1828796.9 | F6: =F5/(1+'Study Parameters'!$C$3) ^'MFSP Baseline'!F2 -> 1741711.3 | G6: =G5/(1+'Study Parameters'!$C$3) ^'MFSP Baseline'!G2 -> 1658772.7 | H6: =H5/(1+'Study Parameters'!$C$3) ^'MFSP Baseline'!H2 -> 1579783.5 | I6: =I5/(1+'Study Parameters'!$C$3) ^'MFSP Baseline'!I2 -> 1504555.7 | ... AF6: =AF5/(1+'Study Parameters'!$C$3) ^'MFSP Baseline'!AF2 -> 489840.18
A8: Minimum Fuel Selling Price (€/l) | B8: =SUM(B4:AF4) /SUM(B6:AF6) -> 4.9691139
A10: Economic Model 2050
A11: Year | B11: 0 | C11: 1 | D11: 2 | E11: 3 | F11: 4 | G11: 5 | H11: 6 | I11: 7 | J11: 8 | K11: 9 | L11: 10 | M11: 11 | N11: 12 | O11: 13 | P11: 14 | Q11: 15 | R11: 16 | S11: 17 | T11: 18 | U11: 19 | V11: 20 | W11: 21 | X11: 22 | Y11: 23 | Z11: 24 | AA11: 25 | AB11: 26 | AC11: 27 | AD11: 28 | AE11: 29 | AF11: 30
A12: Cost (€) | B12: ='Cost Components'!H11 * 10^6 -> 9127577.6 | C12: ='Cost Components'!$H$22 * 10^6 -> 3382180.5 | D12: ='Cost Components'!$H$22 * 10^6 -> 3382180.5 | E12: ='Cost Components'!$H$22 * 10^6 -> 3382180.5 | F12: ='Cost Components'!$H$22 * 10^6 -> 3382180.5 | G12: ='Cost Components'!$H$22 * 10^6 -> 3382180.5 | H12: ='Cost Components'!$H$22 * 10^6 -> 3382180.5 | I12: ='Cost Components'!$H$22 * 10^6 -> 3382180.5 | J12: ='Cost Components'!$H$22 * 10^6 -> 3382180.5 | K12: ='Cost Components'!$H$22 * 10^6 -> 3382180.5 | L12: ='Cost Components'!$H$22 * 10^6 + 'Cost Components'!H10 * 10^6 -> 4456180.5 | M12: ='Cost Components'!$H$22 * 10^6 -> 3382180.5 | N12: ='Cost Components'!$H$22 * 10^6 -> 3382180.5 | O12: ='Cost Components'!$H$22 * 10^6 -> 3382180.5 | P12: ='Cost Components'!$H$22 * 10^6 -> 3382180.5 | Q12: ='Cost Components'!$H$22 * 10^6 + 'Cost Components'!H9*10^6 -> 3640180.5 | R12: ='Cost Components'!$H$22 * 10^6 -> 3382180.5 | S12: ='Cost Components'!$H$22 * 10^6 -> 3382180.5 | T12: ='Cost Components'!$H$22 * 10^6 -> 3382180.5 | U12: ='Cost Components'!$H$22 * 10^6 -> 3382180.5 | V12: ='Cost Components'!$H$22 * 10^6+ 'Cost Components'!H10 * 10^6 -> 4456180.5 | W12: ='Cost Components'!$H$22 * 10^6 -> 3382180.5 | X12: ='Cost Components'!$H$22 * 10^6 -> 3382180.5 | Y12: ='Cost Components'!$H$22 * 10^6 -> 3382180.5 | Z12: ='Cost Components'!$H$22 * 10^6 -> 3382180.5 | AA12: ='Cost Components'!$H$22 * 10^6 -> 3382180.5 | AB12: ='Cost Components'!$H$22 * 10^6 -> 3382180.5 | AC12: ='Cost Components'!$H$22 * 10^6 -> 3382180.5 | AD12: ='Cost Components'!$H$22 * 10^6 -> 3382180.5 | ... AF12: ='Cost Components'!$H$22 * 10^6 -> 3382180.5
A13: Discounted Cost (€) | B13: =B12 / (1+'Study Parameters'!$C$3) ^B11 -> 9127577.6 | C13: =C12 / (1+'Study Parameters'!$C$3) ^C11 -> 3221124.3 | D13: =D12 / (1+'Study Parameters'!$C$3) ^D11 -> 3067737.4 | E13: =E12 / (1+'Study Parameters'!$C$3) ^E11 -> 2921654.7 | F13: =F12 / (1+'Study Parameters'!$C$3) ^F11 -> 2782528.3 | G13: =G12 / (1+'Study Parameters'!$C$3) ^G11 -> 2650026.9 | H13: =H12 / (1+'Study Parameters'!$C$3) ^H11 -> 2523835.2 | I13: =I12 / (1+'Study Parameters'!$C$3) ^I11 -> 2403652.5 | ... AF13: =AF12 / (1+'Study Parameters'!$C$3) ^AF11 -> 782560.29
A14: Production (l) | B14: ='Study Parameters'!$C$24 -> 2117061 | C14: ='Study Parameters'!$C$24 -> 2117061 | D14: ='Study Parameters'!$C$24 -> 2117061 | E14: ='Study Parameters'!$C$24 -> 2117061 | F14: ='Study Parameters'!$C$24 -> 2117061 | G14: ='Study Parameters'!$C$24 -> 2117061 | H14: ='Study Parameters'!$C$24 -> 2117061 | I14: ='Study Parameters'!$C$24 -> 2117061 | ... AF14: ='Study Parameters'!$C$24 -> 2117061
A15: Discounted Production (l) | B15: =B14/(1+'Study Parameters'!$C$3) ^'MFSP Baseline'!B11 -> 2117061 | C15: =C14/(1+'Study Parameters'!$C$3) ^'MFSP Baseline'!C11 -> 2016248.6 | D15: =D14/(1+'Study Parameters'!$C$3) ^'MFSP Baseline'!D11 -> 1920236.8 | E15: =E14/(1+'Study Parameters'!$C$3) ^'MFSP Baseline'!E11 -> 1828796.9 | F15: =F14/(1+'Study Parameters'!$C$3) ^'MFSP Baseline'!F11 -> 1741711.3 | G15: =G14/(1+'Study Parameters'!$C$3) ^'MFSP Baseline'!G11 -> 1658772.7 | H15: =H14/(1+'Study Parameters'!$C$3) ^'MFSP Baseline'!H11 -> 1579783.5 | I15: =I14/(1+'Study Parameters'!$C$3) ^'MFSP Baseline'!I11 -> 1504555.7 | ... AF15: =AF14/(1+'Study Parameters'!$C$3) ^'MFSP Baseline'!AF11 -> 489840.18
A17: Minimum Fuel Selling Price (€/l) | B17: =SUM(B13:AF13) /SUM(B15:AF15) -> 1.7976212

Sheet MFSP LCOE Corrected
A1: Economic Model 2024
A2: Year | B2: 0 | C2: 1 | D2: 2 | E2: 3 | F2: 4 | G2: 5 | H2: 6 | I2: 7 | J2: 8 | K2: 9 | L2: 10 | M2: 11 | N2: 12 | O2: 13 | P2: 14 | Q2: 15 | R2: 16 | S2: 17 | T2: 18 | U2: 19 | V2: 20 | W2: 21 | X2: 22 | Y2: 23 | Z2: 24 | AA2: 25 | AB2: 26 | AC2: 27 | AD2: 28 | AE2: 29 | AF2: 30
A3: Cost (€) | B3: ='Cost Components'!B11 * 10^6 - 'Cost Components'!B9 -> 24927592 | C3: ='Cost Components'!$B$27 * 10^6 -> 9535526.9 | D3: ='Cost Components'!$B$27 * 10^6 -> 9535526.9 | E3: ='Cost Components'!$B$27 * 10^6 -> 9535526.9 | F3: ='Cost Components'!$B$27 * 10^6 -> 9535526.9 | G3: ='Cost Components'!$B$27 * 10^6 -> 9535526.9 | H3: ='Cost Components'!$B$27 * 10^6 -> 9535526.9 | I3: ='Cost Components'!$B$27 * 10^6 -> 9535526.9 | J3: ='Cost Components'!$B$27 * 10^6 -> 9535526.9 | K3: ='Cost Components'!$B$27 * 10^6 -> 9535526.9 | L3: ='Cost Components'!$B$27 * 10^6 + 'Cost Components'!B10 * 10^6 -> 13828167 | M3: ='Cost Components'!$B$27 * 10^6 -> 9535526.9 | N3: ='Cost Components'!$B$27 * 10^6 -> 9535526.9 | O3: ='Cost Components'!$B$27 * 10^6 -> 9535526.9 | P3: ='Cost Components'!$B$27 * 10^6 -> 9535526.9 | Q3: ='Cost Components'!$B$27 * 10^6 -> 9535526.9 | R3: ='Cost Components'!$B$27 * 10^6 -> 9535526.9 | S3: ='Cost Components'!$B$27 * 10^6 -> 9535526.9 | T3: ='Cost Components'!$B$27 * 10^6 -> 9535526.9 | U3: ='Cost Components'!$B$27 * 10^6 -> 9535526.9 | V3: ='Cost Components'!$B$27 * 10^6 + 'Cost Components'!B10 * 10^6 -> 13828167 | W3: ='Cost Components'!$B$27 * 10^6 -> 9535526.9 | X3: ='Cost Components'!$B$27 * 10^6 -> 9535526.9 | Y3: ='Cost Components'!$B$27 * 10^6 -> 9535526.9 | Z3: ='Cost Components'!$B$27 * 10^6 -> 9535526.9 | AA3: ='Cost Components'!$B$27 * 10^6 -> 9535526.9 | AB3: ='Cost Components'!$B$27 * 10^6 -> 9535526.9 | AC3: ='Cost Components'!$B$27 * 10^6 -> 9535526.9 | AD3: ='Cost Components'!$B$27 * 10^6 -> 9535526.9 | ... AF3: ='Cost Components'!$B$27 * 10^6 -> 9535526.9
A4: Discounted Cost (€) | B4: =B3 / (1+'Study Parameters'!$C$3) ^B2 -> 24927592 | C4: =C3 / (1+'Study Parameters'!$C$3) ^C2 -> 9081454.2 | D4: =D3 / (1+'Study Parameters'!$C$3) ^D2 -> 8649004 | E4: =E3 / (1+'Study Parameters'!$C$3) ^E2 -> 8237146.6 | F4: =F3 / (1+'Study Parameters'!$C$3) ^F2 -> 7844901.6 | G4: =G3 / (1+'Study Parameters'!$C$3) ^G2 -> 7471334.8 | H4: =H3 / (1+'Study Parameters'!$C$3) ^H2 -> 7115557 | I4: =I3 / (1+'Study Parameters'!$C$3) ^I2 -> 6776720.9 | ... AF4: =AF3 / (1+'Study Parameters'!$C$3) ^AF2 -> 2206305.9
A5: Production (l) | B5: ='Study Parameters'!$C$24 -> 2117061 | C5: ='Study Parameters'!$C$24 -> 2117061 | D5: ='Study Parameters'!$C$24 -> 2117061 | E5: ='Study Parameters'!$C$24 -> 2117061 | F5: ='Study Parameters'!$C$24 -> 2117061 | G5: ='Study Parameters'!$C$24 -> 2117061 | H5: ='Study Parameters'!$C$24 -> 2117061 | I5: ='Study Parameters'!$C$24 -> 2117061 | ... AF5: ='Study Parameters'!$C$24 -> 2117061
A6: Discounted Production (l) | B6: =B5/(1+'Study Parameters'!$C$3) ^'MFSP Baseline'!B2 -> 2117061 | C6: =C5/(1+'Study Parameters'!$C$3) ^'MFSP Baseline'!C2 -> 2016248.6 | D6: =D5/(1+'Study Parameters'!$C$3) ^'MFSP Baseline'!D2 -> 1920236.8 | E6: =E5/(1+'Study Parameters'!$C$3) ^'MFSP Baseline'!E2 -> 1828796.9 | F6: =F5/(1+'Study Parameters'!$C$3) ^'MFSP Baseline'!F2 -> 1741711.3 | G6: =G5/(1+'Study Parameters'!$C$3) ^'MFSP Baseline'!G2 -> 1658772.7 | H6: =H5/(1+'Study Parameters'!$C$3) ^'MFSP Baseline'!H2 -> 1579783.5 | I6: =I5/(1+'Study Parameters'!$C$3) ^'MFSP Baseline'!I2 -> 1504555.7 | ... AF6: =AF5/(1+'Study Parameters'!$C$3) ^'MFSP Baseline'!AF2 -> 489840.18
A8: Minimum Fuel Selling Price (€/l) | B8: =SUM(B4:AF4) /SUM(B6:AF6) -> 5.0709082
A10: Economic Model 2050
A11: Year | B11: 0 | C11: 1 | D11: 2 | E11: 3 | F11: 4 | G11: 5 | H11: 6 | I11: 7 | J11: 8 | K11: 9 | L11: 10 | M11: 11 | N11: 12 | O11: 13 | P11: 14 | Q11: 15 | R11: 16 | S11: 17 | T11: 18 | U11: 19 | V11: 20 | W11: 21 | X11: 22 | Y11: 23 | Z11: 24 | AA11: 25 | AB11: 26 | AC11: 27 | AD11: 28 | AE11: 29 | AF11: 30
A12: Cost (€) | B12: ='Cost Components'!H11 * 10^6 - 'Cost Components'!H9 -> 9127577.4 | C12: ='Cost Components'!$H$27 * 10^6 -> 2112230.5 | D12: ='Cost Components'!$H$27 * 10^6 -> 2112230.5 | E12: ='Cost Components'!$H$27 * 10^6 -> 2112230.5 | F12: ='Cost Components'!$H$27 * 10^6 -> 2112230.5 | G12: ='Cost Components'!$H$27 * 10^6 -> 2112230.5 | H12: ='Cost Components'!$H$27 * 10^6 -> 2112230.5 | I12: ='Cost Components'!$H$27 * 10^6 -> 2112230.5 | J12: ='Cost Components'!$H$27 * 10^6 -> 2112230.5 | K12: ='Cost Components'!$H$27 * 10^6 -> 2112230.5 | L12: ='Cost Components'!$H$27 * 10^6 + 'Cost Components'!H10 * 10^6 -> 3186230.5 | M12: ='Cost Components'!$H$27 * 10^6 -> 2112230.5 | N12: ='Cost Components'!$H$27 * 10^6 -> 2112230.5 | O12: ='Cost Components'!$H$27 * 10^6 -> 2112230.5 | P12: ='Cost Components'!$H$27 * 10^6 -> 2112230.5 | Q12: ='Cost Components'!$H$27 * 10^6 -> 2112230.5 | R12: ='Cost Components'!$H$27 * 10^6 -> 2112230.5 | S12: ='Cost Components'!$H$27 * 10^6 -> 2112230.5 | T12: ='Cost Components'!$H$27 * 10^6 -> 2112230.5 | U12: ='Cost Components'!$H$27 * 10^6 -> 2112230.5 | V12: ='Cost Components'!$H$27 * 10^6+ 'Cost Components'!H10 * 10^6 -> 3186230.5 | W12: ='Cost Components'!$H$27 * 10^6 -> 2112230.5 | X12: ='Cost Components'!$H$27 * 10^6 -> 2112230.5 | Y12: ='Cost Components'!$H$27 * 10^6 -> 2112230.5 | Z12: ='Cost Components'!$H$27 * 10^6 -> 2112230.5 | AA12: ='Cost Components'!$H$27 * 10^6 -> 2112230.5 | AB12: ='Cost Components'!$H$27 * 10^6 -> 2112230.5 | AC12: ='Cost Components'!$H$27 * 10^6 -> 2112230.5 | AD12: ='Cost Components'!$H$27 * 10^6 -> 2112230.5 | ... AF12: ='Cost Components'!$H$27 * 10^6 -> 2112230.5
A13: Discounted Cost (€) | B13: =B12 / (1+'Study Parameters'!$C$3) ^B11 -> 9127577.4 | C13: =C12 / (1+'Study Parameters'!$C$3) ^C11 -> 2011648.1 | D13: =D12 / (1+'Study Parameters'!$C$3) ^D11 -> 1915855.3 | E13: =E12 / (1+'Study Parameters'!$C$3) ^E11 -> 1824624.1 | F13: =F12 / (1+'Study Parameters'!$C$3) ^F11 -> 1737737.3 | G13: =G12 / (1+'Study Parameters'!$C$3) ^G11 -> 1654987.9 | H13: =H12 / (1+'Study Parameters'!$C$3) ^H11 -> 1576178.9 | I13: =I12 / (1+'Study Parameters'!$C$3) ^I11 -> 1501122.8 | ... AF13: =AF12 / (1+'Study Parameters'!$C$3) ^AF11 -> 488722.5
A14: Production (l) | B14: ='Study Parameters'!$C$24 -> 2117061 | C14: ='Study Parameters'!$C$24 -> 2117061 | D14: ='Study Parameters'!$C$24 -> 2117061 | E14: ='Study Parameters'!$C$24 -> 2117061 | F14: ='Study Parameters'!$C$24 -> 2117061 | G14: ='Study Parameters'!$C$24 -> 2117061 | H14: ='Study Parameters'!$C$24 -> 2117061 | I14: ='Study Parameters'!$C$24 -> 2117061 | ... AF14: ='Study Parameters'!$C$24 -> 2117061
A15: Discounted Production (l) | B15: =B14/(1+'Study Parameters'!$C$3) ^'MFSP Baseline'!B11 -> 2117061 | C15: =C14/(1+'Study Parameters'!$C$3) ^'MFSP Baseline'!C11 -> 2016248.6 | D15: =D14/(1+'Study Parameters'!$C$3) ^'MFSP Baseline'!D11 -> 1920236.8 | E15: =E14/(1+'Study Parameters'!$C$3) ^'MFSP Baseline'!E11 -> 1828796.9 | F15: =F14/(1+'Study Parameters'!$C$3) ^'MFSP Baseline'!F11 -> 1741711.3 | G15: =G14/(1+'Study Parameters'!$C$3) ^'MFSP Baseline'!G11 -> 1658772.7 | H15: =H14/(1+'Study Parameters'!$C$3) ^'MFSP Baseline'!H11 -> 1579783.5 | I15: =I14/(1+'Study Parameters'!$C$3) ^'MFSP Baseline'!I11 -> 1504555.7 | ... AF15: =AF14/(1+'Study Parameters'!$C$3) ^'MFSP Baseline'!AF11 -> 489840.18
A17: Minimum Fuel Selling Price (€/l) | B17: =SUM(B13:AF13) /SUM(B15:AF15) -> 1.2308148

Sheet MFSP CO2 Corrected
A1: Economic Model 2024
A2: Year | B2: 0 | C2: 1 | D2: 2 | E2: 3 | F2: 4 | G2: 5 | H2: 6 | I2: 7 | J2: 8 | K2: 9 | L2: 10 | M2: 11 | N2: 12 | O2: 13 | P2: 14 | Q2: 15 | R2: 16 | S2: 17 | T2: 18 | U2: 19 | V2: 20 | W2: 21 | X2: 22 | Y2: 23 | Z2: 24 | AA2: 25 | AB2: 26 | AC2: 27 | AD2: 28 | AE2: 29 | AF2: 30
A3: Cost (€) | B3: ='Cost Components'!B11 * 10^6 -> 24927593 | C3: ='Cost Components'!$B$29 * 10^6 -> 13098219 | D3: ='Cost Components'!$B$29 * 10^6 -> 13098219 | E3: ='Cost Components'!$B$29 * 10^6 -> 13098219 | F3: ='Cost Components'!$B$29 * 10^6 -> 13098219 | G3: ='Cost Components'!$B$29 * 10^6 -> 13098219 | H3: ='Cost Components'!$B$29 * 10^6 -> 13098219 | I3: ='Cost Components'!$B$29 * 10^6 -> 13098219 | J3: ='Cost Components'!$B$29 * 10^6 -> 13098219 | K3: ='Cost Components'!$B$29 * 10^6 -> 13098219 | L3: ='Cost Components'!$B$29 * 10^6 + 'Cost Components'!B10 * 10^6 -> 17390859 | M3: ='Cost Components'!$B$29 * 10^6 -> 13098219 | N3: ='Cost Components'!$B$29 * 10^6 -> 13098219 | O3: ='Cost Components'!$B$29 * 10^6 -> 13098219 | P3: ='Cost Components'!$B$29 * 10^6 -> 13098219 | Q3: ='Cost Components'!$B$29 * 10^6 -> 13098219 | R3: ='Cost Components'!$B$29 * 10^6 -> 13098219 | S3: ='Cost Components'!$B$29 * 10^6 -> 13098219 | T3: ='Cost Components'!$B$29 * 10^6 -> 13098219 | U3: ='Cost Components'!$B$29 * 10^6 -> 13098219 | V3: ='Cost Components'!$B$29 * 10^6 + 'Cost Components'!B10 * 10^6 -> 17390859 | W3: ='Cost Components'!$B$29 * 10^6 -> 13098219 | X3: ='Cost Components'!$B$29 * 10^6 -> 13098219 | Y3: ='Cost Components'!$B$29 * 10^6 -> 13098219 | Z3: ='Cost Components'!$B$29 * 10^6 -> 13098219 | AA3: ='Cost Components'!$B$29 * 10^6 -> 13098219 | AB3: ='Cost Components'!$B$29 * 10^6 -> 13098219 | AC3: ='Cost Components'!$B$29 * 10^6 -> 13098219 | AD3: ='Cost Components'!$B$29 * 10^6 -> 13098219 | ... AF3: ='Cost Components'!$B$29 * 10^6 -> 13098219
A4: Discounted Cost (€) | B4: =B3 / (1+'Study Parameters'!$C$3) ^B2 -> 24927593 | C4: =C3 / (1+'Study Parameters'!$C$3) ^C2 -> 12474494 | D4: =D3 / (1+'Study Parameters'!$C$3) ^D2 -> 11880471 | E4: =E3 / (1+'Study Parameters'!$C$3) ^E2 -> 11314734 | F4: =F3 / (1+'Study Parameters'!$C$3) ^F2 -> 10775937 | G4: =G3 / (1+'Study Parameters'!$C$3) ^G2 -> 10262797 | H4: =H3 / (1+'Study Parameters'!$C$3) ^H2 -> 9774092.6 | I4: =I3 / (1+'Study Parameters'!$C$3) ^I2 -> 9308659.6 | ... AF4: =AF3 / (1+'Study Parameters'!$C$3) ^AF2 -> 3030632.5
A5: Production (l) | B5: ='Study Parameters'!$C$24 -> 2117061 | C5: ='Study Parameters'!$C$24 -> 2117061 | D5: ='Study Parameters'!$C$24 -> 2117061 | E5: ='Study Parameters'!$C$24 -> 2117061 | F5: ='Study Parameters'!$C$24 -> 2117061 | G5: ='Study Parameters'!$C$24 -> 2117061 | H5: ='Study Parameters'!$C$24 -> 2117061 | I5: ='Study Parameters'!$C$24 -> 2117061 | ... AF5: ='Study Parameters'!$C$24 -> 2117061
A6: Discounted Production (l) | B6: =B5/(1+'Study Parameters'!$C$3) ^'MFSP Baseline'!B2 -> 2117061 | C6: =C5/(1+'Study Parameters'!$C$3) ^'MFSP Baseline'!C2 -> 2016248.6 | D6: =D5/(1+'Study Parameters'!$C$3) ^'MFSP Baseline'!D2 -> 1920236.8 | E6: =E5/(1+'Study Parameters'!$C$3) ^'MFSP Baseline'!E2 -> 1828796.9 | F6: =F5/(1+'Study Parameters'!$C$3) ^'MFSP Baseline'!F2 -> 1741711.3 | G6: =G5/(1+'Study Parameters'!$C$3) ^'MFSP Baseline'!G2 -> 1658772.7 | H6: =H5/(1+'Study Parameters'!$C$3) ^'MFSP Baseline'!H2 -> 1579783.5 | I6: =I5/(1+'Study Parameters'!$C$3) ^'MFSP Baseline'!I2 -> 1504555.7 | ... AF6: =AF5/(1+'Study Parameters'!$C$3) ^'MFSP Baseline'!AF2 -> 489840.18
A8: Minimum Fuel Selling Price (€/l) | B8: =SUM(B4:AF4) /SUM(B6:AF6) -> 6.6509709
A10: Economic Model 2050
A11: Year | B11: 0 | C11: 1 | D11: 2 | E11: 3 | F11: 4 | G11: 5 | H11: 6 | I11: 7 | J11: 8 | K11: 9 | L11: 10 | M11: 11 | N11: 12 | O11: 13 | P11: 14 | Q11: 15 | R11: 16 | S11: 17 | T11: 18 | U11: 19 | V11: 20 | W11: 21 | X11: 22 | Y11: 23 | Z11: 24 | AA11: 25 | AB11: 26 | AC11: 27 | AD11: 28 | AE11: 29 | AF11: 30
A12: Cost (€) | B12: ='Cost Components'!H11 * 10^6 -> 9127577.6 | C12: ='Cost Components'!$H$29 * 10^6 -> 4098998.5 | D12: ='Cost Components'!$H$29 * 10^6 -> 4098998.5 | E12: ='Cost Components'!$H$29 * 10^6 -> 4098998.5 | F12: ='Cost Components'!$H$29 * 10^6 -> 4098998.5 | G12: ='Cost Components'!$H$29 * 10^6 -> 4098998.5 | H12: ='Cost Components'!$H$29 * 10^6 -> 4098998.5 | I12: ='Cost Components'!$H$29 * 10^6 -> 4098998.5 | J12: ='Cost Components'!$H$29 * 10^6 -> 4098998.5 | K12: ='Cost Components'!$H$29 * 10^6 -> 4098998.5 | L12: ='Cost Components'!$H$29 * 10^6 + 'Cost Components'!H10 * 10^6 -> 5172998.5 | M12: ='Cost Components'!$H$29 * 10^6 -> 4098998.5 | N12: ='Cost Components'!$H$29 * 10^6 -> 4098998.5 | O12: ='Cost Components'!$H$29 * 10^6 -> 4098998.5 | P12: ='Cost Components'!$H$29 * 10^6 -> 4098998.5 | Q12: ='Cost Components'!$H$29 * 10^6 -> 4098998.5 | R12: ='Cost Components'!$H$29 * 10^6 -> 4098998.5 | S12: ='Cost Components'!$H$29 * 10^6 -> 4098998.5 | T12: ='Cost Components'!$H$29 * 10^6 -> 4098998.5 | U12: ='Cost Components'!$H$29 * 10^6 -> 4098998.5 | V12: ='Cost Components'!$H$29 * 10^6+ 'Cost Components'!H10 * 10^6 -> 5172998.5 | W12: ='Cost Components'!$H$29 * 10^6 -> 4098998.5 | X12: ='Cost Components'!$H$29 * 10^6 -> 4098998.5 | Y12: ='Cost Components'!$H$29 * 10^6 -> 4098998.5 | Z12: ='Cost Components'!$H$29 * 10^6 -> 4098998.5 | AA12: ='Cost Components'!$H$29 * 10^6 -> 4098998.5 | AB12: ='Cost Components'!$H$29 * 10^6 -> 4098998.5 | AC12: ='Cost Components'!$H$29 * 10^6 -> 4098998.5 | AD12: ='Cost Components'!$H$29 * 10^6 -> 4098998.5 | ... AF12: ='Cost Components'!$H$29 * 10^6 -> 4098998.5
A13: Discounted Cost (€) | B13: =B12 / (1+'Study Parameters'!$C$3) ^B11 -> 9127577.6 | C13: =C12 / (1+'Study Parameters'!$C$3) ^C11 -> 3903808.1 | D13: =D12 / (1+'Study Parameters'!$C$3) ^D11 -> 3717912.5 | E13: =E12 / (1+'Study Parameters'!$C$3) ^E11 -> 3540869 | F13: =F12 / (1+'Study Parameters'!$C$3) ^F11 -> 3372256.2 | G13: =G12 / (1+'Study Parameters'!$C$3) ^G11 -> 3211672.6 | H13: =H12 / (1+'Study Parameters'!$C$3) ^H11 -> 3058735.8 | I13: =I12 / (1+'Study Parameters'!$C$3) ^I11 -> 2913081.7 | ... AF13: =AF12 / (1+'Study Parameters'!$C$3) ^AF11 -> 948415.81
A14: Production (l) | B14: ='Study Parameters'!$C$24 -> 2117061 | C14: ='Study Parameters'!$C$24 -> 2117061 | D14: ='Study Parameters'!$C$24 -> 2117061 | E14: ='Study Parameters'!$C$24 -> 2117061 | F14: ='Study Parameters'!$C$24 -> 2117061 | G14: ='Study Parameters'!$C$24 -> 2117061 | H14: ='Study Parameters'!$C$24 -> 2117061 | I14: ='Study Parameters'!$C$24 -> 2117061 | ... AF14: ='Study Parameters'!$C$24 -> 2117061
A15: Discounted Production (l) | B15: =B14/(1+'Study Parameters'!$C$3) ^'MFSP Baseline'!B11 -> 2117061 | C15: =C14/(1+'Study Parameters'!$C$3) ^'MFSP Baseline'!C11 -> 2016248.6 | D15: =D14/(1+'Study Parameters'!$C$3) ^'MFSP Baseline'!D11 -> 1920236.8 | E15: =E14/(1+'Study Parameters'!$C$3) ^'MFSP Baseline'!E11 -> 1828796.9 | F15: =F14/(1+'Study Parameters'!$C$3) ^'MFSP Baseline'!F11 -> 1741711.3 | G15: =G14/(1+'Study Parameters'!$C$3) ^'MFSP Baseline'!G11 -> 1658772.7 | H15: =H14/(1+'Study Parameters'!$C$3) ^'MFSP Baseline'!H11 -> 1579783.5 | I15: =I14/(1+'Study Parameters'!$C$3) ^'MFSP Baseline'!I11 -> 1504555.7 | ... AF15: =AF14/(1+'Study Parameters'!$C$3) ^'MFSP Baseline'!AF11 -> 489840.18
A17: Minimum Fuel Selling Price (€/l) | B17: =SUM(B13:AF13) /SUM(B15:AF15) -> 2.1119513

Sheet MFSP WACC Corrected
A1: Economic Model 2024
A2: Year | B2: 0 | C2: 1 | D2: 2 | E2: 3 | F2: 4 | G2: 5 | H2: 6 | I2: 7 | J2: 8 | K2: 9 | L2: 10 | M2: 11 | N2: 12 | O2: 13 | P2: 14 | Q2: 15 | R2: 16 | S2: 17 | T2: 18 | U2: 19 | V2: 20 | W2: 21 | X2: 22 | Y2: 23 | Z2: 24 | AA2: 25 | AB2: 26 | AC2: 27 | AD2: 28 | AE2: 29 | AF2: 30
A3: Cost (€) | B3: ='Cost Components'!B11 * 10^6 -> 24927593 | C3: ='Cost Components'!$B$29 * 10^6 -> 13098219 | D3: ='Cost Components'!$B$29 * 10^6 -> 13098219 | E3: ='Cost Components'!$B$29 * 10^6 -> 13098219 | F3: ='Cost Components'!$B$29 * 10^6 -> 13098219 | G3: ='Cost Components'!$B$29 * 10^6 -> 13098219 | H3: ='Cost Components'!$B$29 * 10^6 -> 13098219 | I3: ='Cost Components'!$B$29 * 10^6 -> 13098219 | J3: ='Cost Components'!$B$29 * 10^6 -> 13098219 | K3: ='Cost Components'!$B$29 * 10^6 -> 13098219 | L3: ='Cost Components'!$B$29 * 10^6 + 'Cost Components'!B10 * 10^6 -> 17390859 | M3: ='Cost Components'!$B$29 * 10^6 -> 13098219 | N3: ='Cost Components'!$B$29 * 10^6 -> 13098219 | O3: ='Cost Components'!$B$29 * 10^6 -> 13098219 | P3: ='Cost Components'!$B$29 * 10^6 -> 13098219 | Q3: ='Cost Components'!$B$29 * 10^6 -> 13098219 | R3: ='Cost Components'!$B$29 * 10^6 -> 13098219 | S3: ='Cost Components'!$B$29 * 10^6 -> 13098219 | T3: ='Cost Components'!$B$29 * 10^6 -> 13098219 | U3: ='Cost Components'!$B$29 * 10^6 -> 13098219 | V3: ='Cost Components'!$B$29 * 10^6 + 'Cost Components'!B10 * 10^6 -> 17390859 | W3: ='Cost Components'!$B$29 * 10^6 -> 13098219 | X3: ='Cost Components'!$B$29 * 10^6 -> 13098219 | Y3: ='Cost Components'!$B$29 * 10^6 -> 13098219 | Z3: ='Cost Components'!$B$29 * 10^6 -> 13098219 | AA3: ='Cost Components'!$B$29 * 10^6 -> 13098219 | AB3: ='Cost Components'!$B$29 * 10^6 -> 13098219 | AC3: ='Cost Components'!$B$29 * 10^6 -> 13098219 | AD3: ='Cost Components'!$B$29 * 10^6 -> 13098219 | ... AF3: ='Cost Components'!$B$29 * 10^6 -> 13098219
A4: Discounted Cost (€) | B4: =B3 / (1+'Cost Components'!$B$30) ^B2 -> 24927593 | C4: =C3 / (1+'Cost Components'!$B$30) ^C2 -> 12241326 | D4: =D3 / (1+'Cost Components'!$B$30) ^D2 -> 11440492 | E4: =E3 / (1+'Cost Components'!$B$30) ^E2 -> 10692048 | F4: =F3 / (1+'Cost Components'!$B$30) ^F2 -> 9992568.5 | G4: =G3 / (1+'Cost Components'!$B$30) ^G2 -> 9338849 | H4: =H3 / (1+'Cost Components'!$B$30) ^H2 -> 8727896.3 | I4: =I3 / (1+'Cost Components'!$B$30) ^I2 -> 8156912.4 | ... AF4: =AF3 / (1+'Cost Components'!$B$30) ^AF2 -> 1720675.3
A5: Production (l) | B5: ='Study Parameters'!$C$24 -> 2117061 | C5: ='Study Parameters'!$C$24 -> 2117061 | D5: ='Study Parameters'!$C$24 -> 2117061 | E5: ='Study Parameters'!$C$24 -> 2117061 | F5: ='Study Parameters'!$C$24 -> 2117061 | G5: ='Study Parameters'!$C$24 -> 2117061 | H5: ='Study Parameters'!$C$24 -> 2117061 | I5: ='Study Parameters'!$C$24 -> 2117061 | ... AF5: ='Study Parameters'!$C$24 -> 2117061
A6: Discounted Production (l) | B6: =B5/(1+'Cost Components'!$B$30) ^'MFSP Baseline'!B2 -> 2117061 | C6: =C5/(1+'Cost Components'!$B$30) ^'MFSP Baseline'!C2 -> 1978561.7 | D6: =D5/(1+'Cost Components'!$B$30) ^'MFSP Baseline'!D2 -> 1849123.1 | E6: =E5/(1+'Cost Components'!$B$30) ^'MFSP Baseline'!E2 -> 1728152.4 | F6: =F5/(1+'Cost Components'!$B$30) ^'MFSP Baseline'!F2 -> 1615095.7 | G6: =G5/(1+'Cost Components'!$B$30) ^'MFSP Baseline'!G2 -> 1509435.2 | H6: =H5/(1+'Cost Components'!$B$30) ^'MFSP Baseline'!H2 -> 1410687.1 | I6: =I5/(1+'Cost Components'!$B$30) ^'MFSP Baseline'!I2 -> 1318399.2 | ... AF6: =AF5/(1+'Cost Components'!$B$30) ^'MFSP Baseline'!AF2 -> 278112.2
A8: Minimum Fuel Selling Price (€/l) | B8: =SUM(B4:AF4) /SUM(B6:AF6) -> 6.7196355
A10: Economic Model 2050
A11: Year | B11: 0 | C11: 1 | D11: 2 | E11: 3 | F11: 4 | G11: 5 | H11: 6 | I11: 7 | J11: 8 | K11: 9 | L11: 10 | M11: 11 | N11: 12 | O11: 13 | P11: 14 | Q11: 15 | R11: 16 | S11: 17 | T11: 18 | U11: 19 | V11: 20 | W11: 21 | X11: 22 | Y11: 23 | Z11: 24 | AA11: 25 | AB11: 26 | AC11: 27 | AD11: 28 | AE11: 29 | AF11: 30
A12: Cost (€) | B12: ='Cost Components'!H11 * 10^6 -> 9127577.6 | C12: ='Cost Components'!$H$29 * 10^6 -> 4098998.5 | D12: ='Cost Components'!$H$29 * 10^6 -> 4098998.5 | E12: ='Cost Components'!$H$29 * 10^6 -> 4098998.5 | F12: ='Cost Components'!$H$29 * 10^6 -> 4098998.5 | G12: ='Cost Components'!$H$29 * 10^6 -> 4098998.5 | H12: ='Cost Components'!$H$29 * 10^6 -> 4098998.5 | I12: ='Cost Components'!$H$29 * 10^6 -> 4098998.5 | J12: ='Cost Components'!$H$29 * 10^6 -> 4098998.5 | K12: ='Cost Components'!$H$29 * 10^6 -> 4098998.5 | L12: ='Cost Components'!$H$29 * 10^6 + 'Cost Components'!H10 * 10^6 -> 5172998.5 | M12: ='Cost Components'!$H$29 * 10^6 -> 4098998.5 | N12: ='Cost Components'!$H$29 * 10^6 -> 4098998.5 | O12: ='Cost Components'!$H$29 * 10^6 -> 4098998.5 | P12: ='Cost Components'!$H$29 * 10^6 -> 4098998.5 | Q12: ='Cost Components'!$H$29 * 10^6 -> 4098998.5 | R12: ='Cost Components'!$H$29 * 10^6 -> 4098998.5 | S12: ='Cost Components'!$H$29 * 10^6 -> 4098998.5 | T12: ='Cost Components'!$H$29 * 10^6 -> 4098998.5 | U12: ='Cost Components'!$H$29 * 10^6 -> 4098998.5 | V12: ='Cost Components'!$H$29 * 10^6+ 'Cost Components'!H10 * 10^6 -> 5172998.5 | W12: ='Cost Components'!$H$29 * 10^6 -> 4098998.5 | X12: ='Cost Components'!$H$29 * 10^6 -> 4098998.5 | Y12: ='Cost Components'!$H$29 * 10^6 -> 4098998.5 | Z12: ='Cost Components'!$H$29 * 10^6 -> 4098998.5 | AA12: ='Cost Components'!$H$29 * 10^6 -> 4098998.5 | AB12: ='Cost Components'!$H$29 * 10^6 -> 4098998.5 | AC12: ='Cost Components'!$H$29 * 10^6 -> 4098998.5 | AD12: ='Cost Components'!$H$29 * 10^6 -> 4098998.5 | ... AF12: ='Cost Components'!$H$29 * 10^6 -> 4098998.5
A13: Discounted Cost (€) | B13: =B12 / (1+'Cost Components'!$B$30) ^B11 -> 9127577.6 | C13: =C12 / (1+'Cost Components'!$B$30) ^C11 -> 3830839.7 | D13: =D12 / (1+'Cost Components'!$B$30) ^D11 -> 3580224 | E13: =E12 / (1+'Cost Components'!$B$30) ^E11 -> 3346003.8 | F13: =F12 / (1+'Cost Components'!$B$30) ^F11 -> 3127106.3 | G13: =G12 / (1+'Cost Components'!$B$30) ^G11 -> 2922529.3 | H13: =H12 / (1+'Cost Components'!$B$30) ^H11 -> 2731335.8 | I13: =I12 / (1+'Cost Components'!$B$30) ^I11 -> 2552650.3 | ... AF13: =AF12 / (1+'Cost Components'!$B$30) ^AF11 -> 538473.62
A14: Production (l) | B14: ='Study Parameters'!$C$24 -> 2117061 | C14: ='Study Parameters'!$C$24 -> 2117061 | D14: ='Study Parameters'!$C$24 -> 2117061 | E14: ='Study Parameters'!$C$24 -> 2117061 | F14: ='Study Parameters'!$C$24 -> 2117061 | G14: ='Study Parameters'!$C$24 -> 2117061 | H14: ='Study Parameters'!$C$24 -> 2117061 | I14: ='Study Parameters'!$C$24 -> 2117061 | ... AF14: ='Study Parameters'!$C$24 -> 2117061
A15: Discounted Production (l) | B15: =B14/(1+'Cost Components'!$B$30) ^'MFSP Baseline'!B11 -> 2117061 | C15: =C14/(1+'Cost Components'!$B$30) ^'MFSP Baseline'!C11 -> 1978561.7 | D15: =D14/(1+'Cost Components'!$B$30) ^'MFSP Baseline'!D11 -> 1849123.1 | E15: =E14/(1+'Cost Components'!$B$30) ^'MFSP Baseline'!E11 -> 1728152.4 | F15: =F14/(1+'Cost Components'!$B$30) ^'MFSP Baseline'!F11 -> 1615095.7 | G15: =G14/(1+'Cost Components'!$B$30) ^'MFSP Baseline'!G11 -> 1509435.2 | H15: =H14/(1+'Cost Components'!$B$30) ^'MFSP Baseline'!H11 -> 1410687.1 | I15: =I14/(1+'Cost Components'!$B$30) ^'MFSP Baseline'!I11 -> 1318399.2 | ... AF15: =AF14/(1+'Cost Components'!$B$30) ^'MFSP Baseline'!AF11 -> 278112.2
A17: Minimum Fuel Selling Price (€/l) | B17: =SUM(B13:AF13) /SUM(B15:AF15) -> 2.1423223
A19: Cost Drivers 2024
A20: Year | B20: 0 | C20: 1 | D20: 2 | E20: 3 | F20: 4 | G20: 5 | H20: 6 | I20: 7 | J20: 8 | K20: 9 | L20: 10 | M20: 11 | N20: 12 | O20: 13 | P20: 14 | Q20: 15 | R20: 16 | S20: 17 | T20: 18 | U20: 19 | V20: 20 | W20: 21 | X20: 22 | Y20: 23 | Z20: 24 | AA20: 25 | AB20: 26 | AC20: 27 | AD20: 28 | AE20: 29 | AF20: 30
A21: Discounted Electricity Cost (€) | B21: 0 | C21: =('Cost Components'!$B$26 * 10^6) / (1+Inputs!$C$5) ^'MFSP WACC Corrected'!C20 -> 3977570.1 | D21: =('Cost Components'!$B$26 * 10^6) / (1+Inputs!$C$5) ^'MFSP WACC Corrected'!D20 -> 3717355.2 | E21: =('Cost Components'!$B$26 * 10^6) / (1+Inputs!$C$5) ^'MFSP WACC Corrected'!E20 -> 3474163.8 | F21: =('Cost Components'!$B$26 * 10^6) / (1+Inputs!$C$5) ^'MFSP WACC Corrected'!F20 -> 3246882 | G21: =('Cost Components'!$B$26 * 10^6) / (1+Inputs!$C$5) ^'MFSP WACC Corrected'!G20 -> 3034469.2 | H21: =('Cost Components'!$B$26 * 10^6) / (1+Inputs!$C$5) ^'MFSP WACC Corrected'!H20 -> 2835952.5 | I21: =('Cost Components'!$B$26 * 10^6) / (1+Inputs!$C$5) ^'MFSP WACC Corrected'!I20 -> 2650422.9 | J21: =('Cost Components'!$B$26 * 10^6) / (1+Inputs!$C$5) ^'MFSP WACC Corrected'!J20 -> 2477030.7 | ... AF21: =('Cost Components'!$B$26 * 10^6) / (1+Inputs!$C$5) ^'MFSP WACC Corrected'!AF20 -> 559098.45
A22: Discounted CO2 Cost (€) | B22: 0 | C22: =('Cost Components'!$B$28 * 10^6) / (1+Inputs!$C$5) ^'MFSP WACC Corrected'!C20 -> 7856983.2 | D22: =('Cost Components'!$B$28 * 10^6) / (1+Inputs!$C$5) ^'MFSP WACC Corrected'!D20 -> 7342974.9 | E22: =('Cost Components'!$B$28 * 10^6) / (1+Inputs!$C$5) ^'MFSP WACC Corrected'!E20 -> 6862593.4 | F22: =('Cost Components'!$B$28 * 10^6) / (1+Inputs!$C$5) ^'MFSP WACC Corrected'!F20 -> 6413638.7 | G22: =('Cost Components'!$B$28 * 10^6) / (1+Inputs!$C$5) ^'MFSP WACC Corrected'!G20 -> 5994054.8 | H22: =('Cost Components'!$B$28 * 10^6) / (1+Inputs!$C$5) ^'MFSP WACC Corrected'!H20 -> 5601920.4 | I22: =('Cost Components'!$B$28 * 10^6) / (1+Inputs!$C$5) ^'MFSP WACC Corrected'!I20 -> 5235439.6 | J22: =('Cost Components'!$B$28 * 10^6) / (1+Inputs!$C$5) ^'MFSP WACC Corrected'!J20 -> 4892934.2 | ... AF22: =('Cost Components'!$B$28 * 10^6) / (1+Inputs!$C$5) ^'MFSP WACC Corrected'!AF20 -> 1104399.7
A23: CAPEX (€) | B23: ='Cost Components'!B11 * 10^6 -> 24927593 | C23: 0 | D23: 0 | E23: 0 | F23: 0 | G23: 0 | H23: 0 | I23: 0 | J23: 0 | K23: 0 | L23: 0 | M23: 0 | N23: 0 | O23: 0 | P23: 0 | Q23: 0 | R23: 0 | S23: 0 | T23: 0 | U23: 0 | V23: 0 | W23: 0 | X23: 0 | Y23: 0 | Z23: 0 | AA23: 0 | AB23: 0 | AC23: 0 | AD23: 0 | AE23: 0 | AF23: 0
A24: Other OPEX (€) | B24: 0 | C24: =SUM('Cost Components'!$B$15:$B$18) * 10^6 -> 435246.88 | D24: =SUM('Cost Components'!$B$15:$B$18) * 10^6 -> 435246.88 | E24: =SUM('Cost Components'!$B$15:$B$18) * 10^6 -> 435246.88 | F24: =SUM('Cost Components'!$B$15:$B$18) * 10^6 -> 435246.88 | G24: =SUM('Cost Components'!$B$15:$B$18) * 10^6 -> 435246.88 | H24: =SUM('Cost Components'!$B$15:$B$18) * 10^6 -> 435246.88 | I24: =SUM('Cost Components'!$B$15:$B$18) * 10^6 -> 435246.88 | J24: =SUM('Cost Components'!$B$15:$B$18) * 10^6 -> 435246.88 | ... AF24: =SUM('Cost Components'!$B$15:$B$18) * 10^6 -> 435246.88
A25: Total | B25: =SUM(B21:B24) -> 24927593 | C25: =SUM(C21:C24) -> 12269800 | D25: =SUM(D21:D24) -> 11495577 | E25: =SUM(E21:E24) -> 10772004 | F25: =SUM(F21:F24) -> 10095768 | G25: =SUM(G21:G24) -> 9463770.9 | H25: =SUM(H21:H24) -> 8873119.8 | I25: =SUM(I21:I24) -> 8321109.4 | ... AF25: =SUM(AF21:AF24) -> 2098745
A27: Breakdown 2024
A28: Electricity | B28: =SUM(B21:AF21) / SUM(B25:AF25) -> 0.27066824
A29: CO2 | B29: =SUM(B22:AF22) / SUM(B25:AF25) -> 0.53465703
A30: CAPEX | B30: =SUM(B23:AF23) / SUM(B25:AF25) -> 0.12775497
A31: Other OPEX | B31: =SUM(B24:AF24) / SUM(B25:AF25) -> 0.06691976
A33: Cost Drivers 2050
A34: Year | B34: 0 | C34: 1 | D34: 2 | E34: 3 | F34: 4 | G34: 5 | H34: 6 | I34: 7 | J34: 8 | K34: 9 | L34: 10 | M34: 11 | N34: 12 | O34: 13 | P34: 14 | Q34: 15 | R34: 16 | S34: 17 | T34: 18 | U34: 19 | V34: 20 | W34: 21 | X34: 22 | Y34: 23 | Z34: 24 | AA34: 25 | AB34: 26 | AC34: 27 | AD34: 28 | AE34: 29 | AF34: 30
A35: Discounted Electricity Cost (€) | B35: 0 | C35: =('Cost Components'!$H$26 * 10^6) / (1+Inputs!$C$5) ^'MFSP WACC Corrected'!C34 -> 683644.86 | D35: =('Cost Components'!$H$26 * 10^6) / (1+Inputs!$C$5) ^'MFSP WACC Corrected'!D34 -> 638920.43 | E35: =('Cost Components'!$H$26 * 10^6) / (1+Inputs!$C$5) ^'MFSP WACC Corrected'!E34 -> 597121.9 | F35: =('Cost Components'!$H$26 * 10^6) / (1+Inputs!$C$5) ^'MFSP WACC Corrected'!F34 -> 558057.85 | G35: =('Cost Components'!$H$26 * 10^6) / (1+Inputs!$C$5) ^'MFSP WACC Corrected'!G34 -> 521549.39 | H35: =('Cost Components'!$H$26 * 10^6) / (1+Inputs!$C$5) ^'MFSP WACC Corrected'!H34 -> 487429.34 | I35: =('Cost Components'!$H$26 * 10^6) / (1+Inputs!$C$5) ^'MFSP WACC Corrected'!I34 -> 455541.44 | J35: =('Cost Components'!$H$26 * 10^6) / (1+Inputs!$C$5) ^'MFSP WACC Corrected'!J34 -> 425739.66 | ... AF35: =('Cost Components'!$H$26 * 10^6) / (1+Inputs!$C$5) ^'MFSP WACC Corrected'!AF34 -> 96095.046
A36: Discounted CO2 Cost (€) | B36: 0 | C36: =('Cost Components'!$H$28 * 10^6) / (1+Inputs!$C$5) ^'MFSP WACC Corrected'!C34 -> 2997229.9 | D36: =('Cost Components'!$H$28 * 10^6) / (1+Inputs!$C$5) ^'MFSP WACC Corrected'!D34 -> 2801149.4 | E36: =('Cost Components'!$H$28 * 10^6) / (1+Inputs!$C$5) ^'MFSP WACC Corrected'!E34 -> 2617896.7 | F36: =('Cost Components'!$H$28 * 10^6) / (1+Inputs!$C$5) ^'MFSP WACC Corrected'!F34 -> 2446632.4 | G36: =('Cost Components'!$H$28 * 10^6) / (1+Inputs!$C$5) ^'MFSP WACC Corrected'!G34 -> 2286572.3 | H36: =('Cost Components'!$H$28 * 10^6) / (1+Inputs!$C$5) ^'MFSP WACC Corrected'!H34 -> 2136983.5 | I36: =('Cost Components'!$H$28 * 10^6) / (1+Inputs!$C$5) ^'MFSP WACC Corrected'!I34 -> 1997180.8 | J36: =('Cost Components'!$H$28 * 10^6) / (1+Inputs!$C$5) ^'MFSP WACC Corrected'!J34 -> 1866524.2 | ... AF36: =('Cost Components'!$H$28 * 10^6) / (1+Inputs!$C$5) ^'MFSP WACC Corrected'!AF34 -> 421299.07
A37: CAPEX (€) | B37: ='Cost Components'!H11 * 10^6 -> 9127577.6 | C37: 0 | D37: 0 | E37: 0 | F37: 0 | G37: 0 | H37: 0 | I37: 0 | J37: 0 | K37: 0 | L37: 0 | M37: 0 | N37: 0 | O37: 0 | P37: 0 | Q37: 0 | R37: 0 | S37: 0 | T37: 0 | U37: 0 | V37: 0 | W37: 0 | X37: 0 | Y37: 0 | Z37: 0 | AA37: 0 | AB37: 0 | AC37: 0 | AD37: 0 | AE37: 0 | AF37: 0
A38: Other OPEX (€) | B38: 0 | C38: =SUM('Cost Components'!$H$15:$H$18) * 10^6 -> 160462.5 | D38: =SUM('Cost Components'!$H$15:$H$18) * 10^6 -> 160462.5 | E38: =SUM('Cost Components'!$H$15:$H$18) * 10^6 -> 160462.5 | F38: =SUM('Cost Components'!$H$15:$H$18) * 10^6 -> 160462.5 | G38: =SUM('Cost Components'!$H$15:$H$18) * 10^6 -> 160462.5 | H38: =SUM('Cost Components'!$H$15:$H$18) * 10^6 -> 160462.5 | I38: =SUM('Cost Components'!$H$15:$H$18) * 10^6 -> 160462.5 | J38: =SUM('Cost Components'!$H$15:$H$18) * 10^6 -> 160462.5 | ... AF38: =SUM('Cost Components'!$H$15:$H$18) * 10^6 -> 160462.5
A39: Total | B39: =SUM(B35:B38) -> 9127577.6 | C39: =SUM(C35:C38) -> 3841337.3 | D39: =SUM(D35:D38) -> 3600532.4 | E39: =SUM(E35:E38) -> 3375481.1 | F39: =SUM(F35:F38) -> 3165152.8 | G39: =SUM(G35:G38) -> 2968584.2 | H39: =SUM(H35:H38) -> 2784875.3 | I39: =SUM(I35:I38) -> 2613184.8 | ... AF39: =SUM(AF35:AF38) -> 677856.62
A40: Breakdown 2050
A41: Electricity | B41: =SUM(B35:AF35) / SUM(B39:AF39) -> 0.14450731
A42: CO2 | B42: =SUM(B36:AF36) / SUM(B39:AF39) -> 0.63354772
A43: CAPEX | B43: =SUM(B37:AF37) / SUM(B39:AF39) -> 0.1453091
A44: Other OPEX | B44: =SUM(B38:AF38) / SUM(B39:AF39) -> 0.076635868

Sheet FLH Sensitivity Note
A1: In order to assess sensitviity to full load hours, battery, CO2 and H2 storage is removed and full load hours are decreased according to the capacity factor of power supply. Component sizing is not changed.

Sheet FLH Sensitivity Parameters
A1: Parameter | B1: Original Value | C1: New Value | D1: Source | E1: Notes
A2: Full load hours | B2: 8760 | C2: 4200 | D2: Seymour et. al. SI Figure 5, 6 | E2: Combined wind and PV optimised installation assumed
A3: Fuel Production | B3: ='Study Parameters'!C24 -> 2117061 | C3: =(C2/B2) * B3 -> 1015029.3
A5: 2024
A6: Year | B6: 0 | C6: 1 | D6: 2 | E6: 3 | F6: 4 | G6: 5 | H6: 6 | I6: 7 | J6: 8 | K6: 9 | L6: 10 | M6: 11 | N6: 12 | O6: 13 | P6: 14 | Q6: 15 | R6: 16 | S6: 17 | T6: 18 | U6: 19 | V6: 20 | W6: 21 | X6: 22 | Y6: 23 | Z6: 24 | AA6: 25 | AB6: 26 | AC6: 27 | AD6: 28 | AE6: 29 | AF6: 30
A7: Cost (€) | B7: =('Cost Components'!B11-'Cost Components'!B9-'Cost Components'!B7-'Cost Components'!B6) * 10^6 -> 19854593 | C7: =('Cost Components'!$B$37-'Cost Components'!$B$17-'Cost Components'!$B$18-'Cost Components'!$B$20) * 10^6 -> 8658161.9 | D7: =('Cost Components'!$B$37-'Cost Components'!$B$17-'Cost Components'!$B$18-'Cost Components'!$B$20) * 10^6 -> 8658161.9 | E7: =('Cost Components'!$B$37-'Cost Components'!$B$17-'Cost Components'!$B$18-'Cost Components'!$B$20) * 10^6 -> 8658161.9 | F7: =('Cost Components'!$B$37-'Cost Components'!$B$17-'Cost Components'!$B$18-'Cost Components'!$B$20) * 10^6 -> 8658161.9 | G7: =('Cost Components'!$B$37-'Cost Components'!$B$17-'Cost Components'!$B$18-'Cost Components'!$B$20) * 10^6 -> 8658161.9 | H7: =('Cost Components'!$B$37-'Cost Components'!$B$17-'Cost Components'!$B$18-'Cost Components'!$B$20) * 10^6 -> 8658161.9 | I7: =('Cost Components'!$B$37-'Cost Components'!$B$17-'Cost Components'!$B$18-'Cost Components'!$B$20) * 10^6 -> 8658161.9 | J7: =('Cost Components'!$B$37-'Cost Components'!$B$17-'Cost Components'!$B$18-'Cost Components'!$B$20) * 10^6 -> 8658161.9 | ... AF7: =('Cost Components'!$B$37-'Cost Components'!$B$17-'Cost Components'!$B$18-'Cost Components'!$B$20) * 10^6 -> 8658161.9
A8: Discounted Cost (€) | B8: =B7 / (1+'Cost Components'!$B$30) ^B6 -> 19854593 | C8: =C7 / (1+'Cost Components'!$B$30) ^C6 -> 8091740.1 | D8: =D7 / (1+'Cost Components'!$B$30) ^D6 -> 7562373.9 | E8: =E7 / (1+'Cost Components'!$B$30) ^E6 -> 7067639.2 | F8: =F7 / (1+'Cost Components'!$B$30) ^F6 -> 6605270.2 | G8: =G7 / (1+'Cost Components'!$B$30) ^G6 -> 6173149.8 | H8: =H7 / (1+'Cost Components'!$B$30) ^H6 -> 5769298.8 | I8: =I7 / (1+'Cost Components'!$B$30) ^I6 -> 5391868.1 | ... AF8: =AF7 / (1+'Cost Components'!$B$30) ^AF6 -> 1137397.8
A9: Production (l) | B9: 0 | C9: =$C$3 -> 1015029.3 | D9: =$C$3 -> 1015029.3 | E9: =$C$3 -> 1015029.3 | F9: =$C$3 -> 1015029.3 | G9: =$C$3 -> 1015029.3 | H9: =$C$3 -> 1015029.3 | I9: =$C$3 -> 1015029.3 | J9: =$C$3 -> 1015029.3 | ... AF9: =$C$3 -> 1015029.3
A10: Discounted Production (l) | B10: 0 | C10: =C9/(1+'Cost Components'!$B$30) ^'FLH Sensitivity Parameters'!C6 -> 948625.47 | D10: =D9/(1+'Cost Components'!$B$30) ^'FLH Sensitivity Parameters'!D6 -> 886565.86 | E10: =E9/(1+'Cost Components'!$B$30) ^'FLH Sensitivity Parameters'!E6 -> 828566.23 | F10: =F9/(1+'Cost Components'!$B$30) ^'FLH Sensitivity Parameters'!F6 -> 774360.96 | G10: =G9/(1+'Cost Components'!$B$30) ^'FLH Sensitivity Parameters'!G6 -> 723701.83 | H10: =H9/(1+'Cost Components'!$B$30) ^'FLH Sensitivity Parameters'!H6 -> 676356.85 | I10: =I9/(1+'Cost Components'!$B$30) ^'FLH Sensitivity Parameters'!I6 -> 632109.21 | J10: =J9/(1+'Cost Components'!$B$30) ^'FLH Sensitivity Parameters'!J6 -> 590756.27 | ... AF10: =AF9/(1+'Cost Components'!$B$30) ^'FLH Sensitivity Parameters'!AF6 -> 133341.47
A12: Minimum Fuel Selling Price (€/l) | B12: =SUM(B8:AF8) /SUM(B10:AF10) -> 10.106282

Sheet Outputs
A1: 2024 | I1: 2050
A2: Parameter | B2: Unit | C2: Base Case | D2: LCOE Corrected | E2: CO2 Cost Corrected | F2: WACC Corrected | G2: Low FLH | I2: Parameter | J2: Unit | K2: Base Case | L2: LCOE Corrected | M2: CO2 Cost Corrected | N2: WACC Corrected
A3: Syn-Fuel cost | B3: €/l | C3: ='MFSP Baseline'!B8 -> 4.9691139 | D3: ='MFSP LCOE Corrected'!B8 -> 5.0709082 | E3: ='MFSP CO2 Corrected'!B8 -> 6.6509709 | F3: ='MFSP WACC Corrected'!B8 -> 6.7196355 | G3: ='FLH Sensitivity Parameters'!B12 -> 10.106282 | I3: Syn-Fuel cost | J3: €/l | K3: ='MFSP Baseline'!B17 -> 1.7976212 | L3: ='MFSP LCOE Corrected'!B17 -> 1.2308148 | M3: ='MFSP CO2 Corrected'!B17 -> 2.1119513 | N3: ='MFSP WACC Corrected'!B17 -> 2.1423223
A4: Syn-Fuel cost | B4: $/l | C4: =C3/Inputs!$C$6 -> 5.5212377 | D4: =D3/Inputs!$C$6 -> 5.6343424 | E4: =E3/Inputs!$C$6 -> 7.3899677 | F4: =F3/Inputs!$C$6 -> 7.4662617 | G4: =G3/Inputs!$C$6 -> 11.229202 | I4: Syn-Fuel cost | J4: $/l | K4: =K3/Inputs!$C$6 -> 1.9973569 | L4: =L3/Inputs!$C$6 -> 1.367572 | M4: =M3/Inputs!$C$6 -> 2.3466126 | N4: =N3/Inputs!$C$6 -> 2.3803581
A5: Fossil Fuel cost | B5: $/l | C5: =Inputs!$C$16 -> 0.8 | D5: =Inputs!$C$16 -> 0.8 | E5: =Inputs!$C$16 -> 0.8 | F5: =Inputs!$C$16 -> 0.8 | G5: =Inputs!$C$16 -> 0.8 | I5: Fossil Fuel cost | J5: $/l | K5: =Inputs!$C$18 -> 1.7 | L5: =Inputs!$C$18 -> 1.7 | M5: =Inputs!$C$18 -> 1.7 | N5: =Inputs!$C$18 -> 1.7
A6: Syn-Fuel emissions | B6: gCO2eq/MJ | C6: ='Study Parameters'!$C$37 -> 8.7962963 | D6: ='Study Parameters'!$C$37 -> 8.7962963 | E6: ='Study Parameters'!$C$37 -> 8.7962963 | F6: ='Study Parameters'!$C$37 -> 8.7962963 | G6: ='Study Parameters'!$C$37 -> 8.7962963 | I6: Syn-Fuel emissions | J6: gCO2eq/MJ | K6: ='Study Parameters'!$C$37 -> 8.7962963 | L6: ='Study Parameters'!$C$37 -> 8.7962963 | M6: ='Study Parameters'!$C$37 -> 8.7962963 | N6: ='Study Parameters'!$C$37 -> 8.7962963
A7: Fossil Fuel emissions | B7: gCO2eq/MJ | C7: =Inputs!$C$11 -> 88.7 | D7: =Inputs!$C$11 -> 88.7 | E7: =Inputs!$C$11 -> 88.7 | F7: =Inputs!$C$11 -> 88.7 | G7: =Inputs!$C$11 -> 88.7 | I7: Fossil Fuel emissions | J7: gCO2eq/MJ | K7: =Inputs!$C$12 -> 88.7 | L7: =Inputs!$C$12 -> 88.7 | M7: =Inputs!$C$12 -> 88.7 | N7: =Inputs!$C$12 -> 88.7
A8: CO2 Abated | B8: gCO2eq/MJ | C8: =C7-C6 -> 79.903704 | D8: =D7-D6 -> 79.903704 | E8: =E7-E6 -> 79.903704 | F8: =F7-F6 -> 79.903704 | G8: =G7-G6 -> 79.903704 | I8: CO2 Abated | J8: gCO2eq/MJ | K8: =K7-K6 -> 79.903704 | L8: =L7-L6 -> 79.903704 | M8: =M7-M6 -> 79.903704 | N8: =N7-N6 -> 79.903704
A9: CO2 Abated | B9: gCO2eq/l | C9: =C8*Inputs!$C$14 -> 2771.8275 | D9: =D8*Inputs!$C$14 -> 2771.8275 | E9: =E8*Inputs!$C$14 -> 2771.8275 | F9: =F8*Inputs!$C$14 -> 2771.8275 | G9: =G8*Inputs!$C$14 -> 2771.8275 | I9: CO2 Abated | J9: gCO2eq/l | K9: =K8*Inputs!$C$14 -> 2771.8275 | L9: =L8*Inputs!$C$14 -> 2771.8275 | M9: =M8*Inputs!$C$14 -> 2771.8275 | N9: =N8*Inputs!$C$14 -> 2771.8275
A10: Abatement cost | B10: $/tCO2 | C10: =((C4-C5) /C9 )* 10^6 -> 1703.2942 | D10: =((D4-D5) /D9 )* 10^6 -> 1744.0993 | E10: =((E4-E5) /E9 )* 10^6 -> 2377.4811 | F10: =((F4-F5) /F9 )* 10^6 -> 2405.006 | G10: =((G4-G5) /G9 )* 10^6 -> 3762.5727 | I10: Abatement cost | J10: $/tCO2 | K10: =((K4-K5) /K9 )* 10^6 -> 107.27827 | L10: =((L4-L5) /L9 )* 10^6 -> -119.93099 | M10: =((M4-M5) /M9 )* 10^6 -> 233.28023 | N10: =((N4-N5) /N9 )* 10^6 -> 245.45471
A12: Full Abatement | I12: Full Abatement
A13: Parameter | B13: Unit | C13: Value | I13: Parameter | J13: Unit | K13: Value
A14: Residual Emissions | B14: gCO2eq/l | C14: =C6*Inputs!$C$14 -> 305.14 | I14: Residual Emissions | J14: gCO2eq/l | K14: =K6*Inputs!$C$14 -> 305.14
A15: Emissions Reduction Cost | B15: $/l | C15: =C14*10^-6*Inputs!$C$32 -> 0.41834694 | I15: Emissions Reduction Cost | J15: $/l | K15: =K14*10^-6*Inputs!$C$33 -> 0.15958822
A16: Effective Synfuel Cost | B16: $/l | C16: =F4+C15 -> 7.8846086 | I16: Effective Synfuel Cost | J16: $/l | K16: =N4+K15 -> 2.5399463
A17: Effective Abatement Cost | B17: $/tCO2 | C17: =(C16-C5) /C9 * 10^6 -> 2555.9342 | I17: Effective Abatement Cost | J17: $/tCO2 | K17: =(K16-K5) /K9 * 10^6 -> 303.0298
