Workbook
Name DACS_average_2030: #REF!

Sheet Inputs
A1: Parameter | B1: Year | C1: Value | D1: Unit
A2: Standard Values
A3: Current Year | C3: =[1]Inputs!C4 -> 2024
A4: Inflation | C4: =[1]Inputs!C5 -> 0.02
A5: WACC | C5: =[1]Inputs!C6 -> 0.07
A6: USD to EUR | C6: =[1]Inputs!C7 -> 0.9
A7: Electricity
A8: LCOE | B8: 2024 | C8: =[1]Inputs!C9 -> 64 | D8: $/MWh
A9: LCOE | B9: 2050 | C9: =[1]Inputs!C10 -> 11 | D9: $/MWh
A10: Jet Fuel A-1 Characteristics
A11: Emissions Intensity | B11: 2024 | C11: =[1]Inputs!C12 -> 88.7 | D11: gCO2/MJ
A12: Emissions Intensity | B12: 2050 | C12: =[1]Inputs!C13 -> 88.7 | D12: gCO2/MJ
A13: Energy Density | C13: =[1]Inputs!C14 -> 43.2 | D13: MJ/kg
A14: Energy Density | C14: =[1]Inputs!C15 -> 34.6896 | D14: MJ/l
A15: Volumetric Density | C15: =[1]Inputs!C16 -> 0.803 | D15: kg/l
A16: Jet Fuel A-1 Price | B16: 2024 | C16: =[1]Inputs!C17 -> 0.8 | D16: $/l
A17: Scenario Specific Values
A18: Jet Fuel A-1 Price | B18: 2050 | C18: =[1]Inputs!C19 -> 0.8 | D18: $/l
A19: IEA Reference
A20: Jet Fuel A-1 Price | B20: 2024 | C20: =[1]Inputs!C21 -> 0.32246154 | D20: $/l
A21: Jet Fuel A-1 Price | B21: 2050 | C21: =[1]Inputs!C22 -> 0.20923077 | D21: $/l
A22: EIA Reference
A23: Jet Fuel A-1 Price | B23: 2024 | C23: =[1]Inputs!C24 -> 1.0209014 | D23: $/l
A24: Jet Fuel A-1 Price | B24: 2050 | C24: =[1]Inputs!C25 -> 2.0095594 | D24: $/l
A25: EIA Low Oil Price Scenario
A26: Jet Fuel A-1 Price | B26: 2024 | C26: =[1]Inputs!C27 -> 0.48286833 | D26: $/l
A27: Jet Fuel A-1 Price | B27: 2050 | C27: =[1]Inputs!C28 -> 0.89646575 | D27: $/l
A28: EIA High Scenario
A29: Jet Fuel A-1 Price | B29: 2024 | C29: =[1]Inputs!C30 -> 1.8838713 | D29: $/l
A30: Jet Fuel A-1 Price | B30: 2050 | C30: =[1]Inputs!C31 -> 3.7893731 | D30: $/l
A31: Direct Air Capture
A32: LCOR | B32: 2024 | C32: =[1]Inputs!C33 -> 1282 | D32: $/tCO2
A33: LCOR | B33: 2050 | C33: =[1]Inputs!C34 -> 480 | D33: $/tCO2

Sheet Standardization
B2: Step 1: Define slop of sensitivity function
C3: % CAPEX change | D3: CAPEX | F3: Total fuel cost | G3: Change in % fuel cost | I3: Corresponds to year
B4: Change in generation capital cost | C4: =D4/D5-1 -> -0.2 | D4: 400 | E4: -0.09 | F4: =F5+E4 -> 1.59 | G4: =F4/F5 -> 0.94642857 | I4: 2050
D5: 500 | E5: 0 | F5: 1.68 | G5: - | I5: Next decade
C6: =D6/D5-1 -> 0.8 | D6: 900 | E6: 0.35 | F6: =F5+E6 -> 2.03 | G6: =F6/F5 -> 1.2083333 | I6: Today
B8: Step 2: Calculation of marginal abatement costs
C9: MSP | D9: High Fuel cost | E9: Low Fuel cost | F9: Low AC | G9: High AC
B10: Solar PV | C10: 4.657 | D10: 0.81 | E10: 0.35 | F10: =($C10-D10)/(2.75)*1000 -> 1398.9091 | G10: =($C10-E10)/(2.75)*1000 -> 1566.1818 | I10: Today, Low-Temp
C11: 1.676 | D11: 0.81 | E11: 0.35 | F11: =(C11-D11)/(2.75)*1000 -> 314.90909 | G11: =($C11-E11)/(2.75)*1000 -> 482.18182 | I11: Next-decade, low-temp
C12: 1.698 | D12: 0.81 | E12: 0.35 | F12: =(C12-D12)/(2.75)*1000 -> 322.90909 | G12: =($C12-E12)/(2.75)*1000 -> 490.18182 | I12: Next-decade, high-temp
C13: 0.9514 | D13: 0.81 | E13: 0.35 | F13: =(C13-D13)/(2.75)*1000 -> 51.418182 | G13: =($C13-E13)/(2.75)*1000 -> 218.69091 | I13: 2050, low-temp
C14: 0.9519 | D14: 0.81 | E14: 0.35 | F14: =(C14-D14)/(2.75)*1000 -> 51.6 | G14: =($C14-E14)/(2.75)*1000 -> 218.87273 | I14: 2050, high temp
B15: Wind | C15: 4.415 | D15: 0.81 | E15: 0.35 | F15: =(C15-D15)/(2.75)*1000 -> 1310.9091 | G15: =($C15-E15)/(2.75)*1000 -> 1478.1818 | I15: Today, Low-Temp
C16: 1.761 | D16: 0.81 | E16: 0.35 | F16: =(C16-D16)/(2.75)*1000 -> 345.81818 | G16: =($C16-E16)/(2.75)*1000 -> 513.09091 | I16: Next-decade, low-temp
C17: 1.77 | D17: 0.81 | E17: 0.35 | F17: =(C17-D17)/(2.75)*1000 -> 349.09091 | G17: =($C17-E17)/(2.75)*1000 -> 516.36364 | I17: Next-decade, high-temp
C18: 0.9877 | D18: 0.81 | E18: 0.35 | F18: =(C18-D18)/(2.75)*1000 -> 64.618182 | G18: =($C18-E18)/(2.75)*1000 -> 231.89091 | I18: 2050, low-temp
C19: 0.9821 | D19: 0.81 | E19: 0.35 | F19: =(C19-D19)/(2.75)*1000 -> 62.581818 | G19: =($C19-E19)/(2.75)*1000 -> 229.85455 | I19: 2050, high temp
B21: Step 3: Calculate effect of MSP sensitivitiy on abatement cost sensitivitiy
C23: MSP * 1,21 | D23: High Fuel cost | E23: Low Fuel cost | F23: Low AC (High Fuel cost) | G23: High AC (low fuel cost) | H23: Change in AC in for 80% increase in CAPEX | N23: Change in AC for change in 100% of CAPEX
B24: Solar PV | C24: =C10*$G$6 -> 5.6272083 | D24: 0.81 | E24: 0.35 | F24: =($C24-D24)/(2.75)*1000 -> 1751.7121 | G24: =($C24-E24)/(2.75)*1000 -> 1918.9848 | H24: =F24/F10 -> 1.2521987 | I24: =G24/G10 -> 1.2252631 | K24: Today, Low-Temp | N24: =(H24-1)/($C$6)+1 -> 1.3152484 | O24: =(I24-1)/($C$6)+1 -> 1.2815789
C25: =C11*$G$6 -> 2.0251667 | D25: 0.81 | E25: 0.35 | F25: =($C25-D25)/(2.75)*1000 -> 441.87879 | G25: =($C25-E25)/(2.75)*1000 -> 609.15152 | H25: =F25/F11 -> 1.4031948 | I25: =G25/G11 -> 1.2633233 | K25: Next-decade, low-temp | N25: =(H25-1)/($C$6)+1 -> 1.5039935 | O25: =(I25-1)/($C$6)+1 -> 1.3291541
C26: =C12*$G$6 -> 2.05175 | D26: 0.81 | E26: 0.35 | F26: =($C26-D26)/(2.75)*1000 -> 451.54545 | G26: =($C26-E26)/(2.75)*1000 -> 618.81818 | H26: =F26/F12 -> 1.3983671 | I26: =G26/G12 -> 1.2624258 | K26: Next-decade, high-temp | N26: =(H26-1)/($C$6)+1 -> 1.4979589 | O26: =(I26-1)/($C$6)+1 -> 1.3280323
C27: =C13*$G$6 -> 1.1496083 | D27: 0.81 | E27: 0.35 | F27: =($C27-D27)/(2.75)*1000 -> 123.49394 | G27: =($C27-E27)/(2.75)*1000 -> 290.76667 | H27: =F27/F13 -> 2.4017562 | I27: =G27/G13 -> 1.3295782 | K27: 2050, low-temp | N27: =(H27-1)/($C$6)+1 -> 2.7521953 | O27: =(I27-1)/($C$6)+1 -> 1.4119728
C28: =C14*$G$6 -> 1.1502125 | D28: 0.81 | E28: 0.35 | F28: =($C28-D28)/(2.75)*1000 -> 123.71364 | G28: =($C28-E28)/(2.75)*1000 -> 290.98636 | H28: =F28/F14 -> 2.3975511 | I28: =G28/G14 -> 1.3294775 | K28: 2050, high temp | N28: =(H28-1)/($C$6)+1 -> 2.7469389 | O28: =(I28-1)/($C$6)+1 -> 1.4118469
B29: Wind | C29: =C15*$G$6 -> 5.3347917 | D29: 0.81 | E29: 0.35 | F29: =($C29-D29)/(2.75)*1000 -> 1645.3788 | G29: =($C29-E29)/(2.75)*1000 -> 1812.6515 | H29: =F29/F15 -> 1.2551433 | I29: =G29/G15 -> 1.226271 | K29: Today, Low-Temp | N29: =(H29-1)/($C$6)+1 -> 1.3189291 | O29: =(I29-1)/($C$6)+1 -> 1.2828388
C30: =C16*$G$6 -> 2.127875 | D30: 0.81 | E30: 0.35 | F30: =($C30-D30)/(2.75)*1000 -> 479.22727 | G30: =($C30-E30)/(2.75)*1000 -> 646.5 | H30: =F30/F16 -> 1.3857781 | I30: =G30/G16 -> 1.2600106 | K30: Next-decade, low-temp | N30: =(H30-1)/($C$6)+1 -> 1.4822227 | O30: =(I30-1)/($C$6)+1 -> 1.3250133
C31: =C17*$G$6 -> 2.13875 | D31: 0.81 | E31: 0.35 | F31: =($C31-D31)/(2.75)*1000 -> 483.18182 | G31: =($C31-E31)/(2.75)*1000 -> 650.45455 | H31: =F31/F17 -> 1.3841146 | I31: =G31/G17 -> 1.2596831 | K31: Next-decade, high-temp | N31: =(H31-1)/($C$6)+1 -> 1.4801432 | O31: =(I31-1)/($C$6)+1 -> 1.3246039
C32: =C18*$G$6 -> 1.1934708 | D32: 0.81 | E32: 0.35 | F32: =($C32-D32)/(2.75)*1000 -> 139.44394 | G32: =($C32-E32)/(2.75)*1000 -> 306.71667 | H32: =F32/F18 -> 2.1579675 | I32: =G32/G18 -> 1.3226765 | K32: 2050, low-temp | N32: =(H32-1)/($C$6)+1 -> 2.4474594 | O32: =(I32-1)/($C$6)+1 -> 1.4033457
C33: =C19*$G$6 -> 1.1867042 | D33: 0.81 | E33: 0.35 | F33: =($C33-D33)/(2.75)*1000 -> 136.98333 | G33: =($C33-E33)/(2.75)*1000 -> 304.25606 | H33: =F33/F19 -> 2.1888679 | I33: =G33/G19 -> 1.3236896 | K33: 2050, high temp | N33: =(H33-1)/($C$6)+1 -> 2.4860849 | O33: =(I33-1)/($C$6)+1 -> 1.4046119
B35: Step 4: Calculate LCOE manually
B37: Year 0 | C37: 0 | D37: 1 | E37: 2 | F37: 3 | G37: 4 | H37: 5 | I37: 6 | J37: 7 | K37: 8 | L37: 9 | M37: 10 | N37: 11 | O37: 12 | P37: 13 | Q37: 14 | R37: 15 | S37: 16 | T37: 17 | U37: 18 | V37: 19 | W37: 20 | X37: 21 | Y37: 22 | Z37: 23 | AA37: 24 | AB37: 25
B38: Costs | C38: 900 | D38: =$C$38*1%/(1.1)^D$37 -> 8.1818182 | E38: =$C$38*1%/(1.1)^E$37 -> 7.4380165 | F38: =$C$38*1%/(1.1)^F$37 -> 6.7618332 | G38: =$C$38*1%/(1.1)^G$37 -> 6.1471211 | H38: =$C$38*1%/(1.1)^H$37 -> 5.5882919 | I38: =$C$38*1%/(1.1)^I$37 -> 5.0802654 | J38: =$C$38*1%/(1.1)^J$37 -> 4.6184231 | K38: =$C$38*1%/(1.1)^K$37 -> 4.1985664 | ... AB38: =$C$38*1%/(1.1)^AB$37 -> 0.83066398 | AC38: =SUM(C38:AB38) -> 981.69336
B39: Production | C39: 0 | D39: =8760*29.3%/(1.1)^D37 -> 2333.3455 | E39: =8760*29.3%/(1.1)^E37 -> 2121.2231 | F39: =8760*29.3%/(1.1)^F37 -> 1928.3847 | G39: =8760*29.3%/(1.1)^G37 -> 1753.077 | H39: =8760*29.3%/(1.1)^H37 -> 1593.7063 | I39: =8760*29.3%/(1.1)^I37 -> 1448.8239 | J39: =8760*29.3%/(1.1)^J37 -> 1317.1127 | K39: =8760*29.3%/(1.1)^K37 -> 1197.3752 | ... AB39: =8760*29.3%/(1.1)^AB37 -> 236.89429 | AC39: =SUM(C39:AB39) -> 23297.857
AC40: =AC38/AC39*1000 -> 42.136638 | AD40: $/MWh
B41: Year 0 | C41: 0 | D41: 1 | E41: 2 | F41: 3 | G41: 4 | H41: 5 | I41: 6 | J41: 7 | K41: 8 | L41: 9 | M41: 10 | N41: 11 | O41: 12 | P41: 13 | Q41: 14 | R41: 15 | S41: 16 | T41: 17 | U41: 18 | V41: 19 | W41: 20 | X41: 21 | Y41: 22 | Z41: 23 | AA41: 24 | AB41: 25
B42: Costs | C42: =900*G6 -> 1087.5 | D42: =$C$42*1%/(1.1)^D$41 -> 9.8863636 | E42: =$C$42*1%/(1.1)^E$41 -> 8.9876033 | F42: =$C$42*1%/(1.1)^F$41 -> 8.1705485 | G42: =$C$42*1%/(1.1)^G$41 -> 7.4277713 | H42: =$C$42*1%/(1.1)^H$41 -> 6.7525194 | I42: =$C$42*1%/(1.1)^I$41 -> 6.138654 | J42: =$C$42*1%/(1.1)^J$41 -> 5.5805945 | K42: =$C$42*1%/(1.1)^K$41 -> 5.0732678 | ... AB42: =$C$42*1%/(1.1)^AB$41 -> 1.003719 | AC42: =SUM(C42:AB42) -> 1186.2128
B43: Production | C43: 0 | D43: =8760*29.3%/(1.1)^D41 -> 2333.3455 | E43: =8760*29.3%/(1.1)^E41 -> 2121.2231 | F43: =8760*29.3%/(1.1)^F41 -> 1928.3847 | G43: =8760*29.3%/(1.1)^G41 -> 1753.077 | H43: =8760*29.3%/(1.1)^H41 -> 1593.7063 | I43: =8760*29.3%/(1.1)^I41 -> 1448.8239 | J43: =8760*29.3%/(1.1)^J41 -> 1317.1127 | K43: =8760*29.3%/(1.1)^K41 -> 1197.3752 | ... AB43: =8760*29.3%/(1.1)^AB41 -> 236.89429 | AC43: =SUM(C43:AB43) -> 23297.857
AC44: =AC42/AC43*1000 -> 50.915104 | AD44: $/MWh
B45: Change in CAPEX by | D45: =G6 -> 1.2083333
B46: Causes change in LCOE by | D46: =AC44/AC40 -> 1.2083333
B48: Step 5: Sensitivity of abatement cost caused by LCOE change
B50: not necessary - change in CAPEX and change in LCOE is the same
B52: Appendix: LCOE calculations
B54: Electricity CAPEX | C54: Electricity OPEX | D54: Lifetime | E54: Discount rate | F54: Hours running | H54: LCOE
B55: 900 | C55: 0.01 | D55: 25 | E55: 0.1 | F55: 2566.68 | H55: 39 | I55: $/MWh
B56: 500 | C56: 0.01 | D56: 25 | E56: 0.08 | F56: 2566.68 | H56: 20.8 | I56: $/MWh
B57: 500 | C57: 0.01 | D57: 25 | E57: 0.08 | F57: 2566.68 | H57: 20.8 | I57: $/MWh
B58: 400 | C58: 0.01 | D58: 25 | E58: 0.05 | F58: 2566.68 | H58: 18.8 | I58: $/MWh
B59: 400 | C59: 0.01 | D59: 25 | E59: 0.05 | F59: 2566.68 | H59: 18.8 | I59: $/MWh
B60: 1500 | C60: 0.025 | D60: 25 | E60: 0.1 | F60: 5037 | H60: 40.2 | I60: $/MWh
B61: 1250 | C61: 0.025 | D61: 25 | E61: 0.08 | F61: 5037 | H61: 29.4 | I61: $/MWh
B62: 1250 | C62: 0.025 | D62: 25 | E62: 0.08 | F62: 5037 | H62: 29.4 | I62: $/MWh
B63: 1000 | C63: 0.025 | D63: 25 | E63: 0.05 | F63: 5037 | H63: 19 | I63: $/MWh
B64: 1000 | C64: 0.025 | D64: 25 | E64: 0.05 | F64: 5037 | H64: 19 | I64: $/MWh
B65: 900 | C65: 0.01 | D65: 25 | E65: 0.1 | F65: 2566.68 | H65: 39 | I65: $/MWh
B66: 500 | C66: 0.01 | D66: 25 | E66: 0.08 | F66: 2566.68 | H66: 20.8 | I66: $/MWh
... B74: 1000 | C74: 0.025 | D74: 25 | E74: 0.05 | F74: 5037 | H74: 19 | I74: $/MWh
B78: Figure 2 | D78: $(2017)/liter of gasoline equivalent
B79: Solar PV | D79: Today, low-temp | E79: Next-decade, high-temp | F79: Next-decade, low-temp | G79: Breakthrough, high-temp | H79: Breakthrough, low-temp | J79: Solar PV LCOE | K79: Today, low-temp | L79: Next-decade, high-temp | M79: Next-decade, low-temp | N79: Breakthrough, high-temp | O79: Breakthrough, low-temp
B80: Renewable generation | D80: 1.145 | E80: 0.4566 | F80: 0.456 | G80: 0.2713 | H80: 0.2474 | I80: $/l | J80: CAPEX | K80: 900 | L80: 500 | M80: 500 | N80: 400 | O80: 400
B81: Electricity storage | D81: 0.08127 | E81: 0 | F81: 0 | G81: =2.584*10^-3 -> 0.002584 | H81: =5.71*10^-3 -> 0.00571 | I81: $/l | J81: OPEX | K81: 0.01 | L81: 0.01 | M81: 0.01 | N81: 0.01 | O81: 0.01
B82: Electricity: Variable | D82: 0 | E82: 0 | F82: 0 | G82: 0 | H82: 0 | I82: $/l | J82: WACC | K82: 0.1 | L82: 0.08 | M82: 0.08 | N82: 0.05 | O82: 0.05
B83: Electrolyzer | D83: 1.279 | E83: 0.5419 | F83: 0.5499 | G83: 0.3276 | H83: 0.3475 | I83: $/l | J83: Capacity | K83: 0.29 | L83: 0.29 | M83: 0.29 | N83: 0.29 | O83: 0.29
B84: Hydrogen storage | D84: 0.1166 | E84: 0.02931 | F84: 0.0307 | G84: =8.794*10^-3 -> 0.008794 | H84: =9.629*10^-3 -> 0.009629 | I84: $/l
B85: Hydrogen: Variable | D85: 0 | E85: 0 | F85: 0 | G85: 0 | H85: 0 | I85: $/l | J85: LCOE | K85: 39 | L85: 18.8 | M85: 18.8 | N85: 11.8 | O85: 11.8
B86: Electric kiln | D86: 0 | E86: =4.722*10^-3 -> 0.004722 | F86: =1.674*10^-3 -> 0.001674 | G86: =4.789*10^-3 -> 0.004789 | H86: 0 | I86: $/l
B87: Heat storage | D87: 0 | E87: =263.6*10^-6 -> 0.0002636 | F87: 0 | G87: 0.0142 | H87: =1.291*10^-3 -> 0.001291 | I87: $/l | J87: WACC sensitivity | K87: 7.065 | L87: 6.344 | P87: $/GGE
B88: Heat: Variable | D88: 0 | E88: 0 | F88: 0 | G88: 0 | H88: 0 | I88: $/l | L88: =((K87/L87)-1)/2+1 -> 1.0568253
B89: DAC | D89: 0.7654 | E89: 0.2829 | F89: 0.3283 | G89: 0.1604 | H89: 0.221 | I89: $/l
B90: CO2 storage | D90: 0 | E90: =3.26*10^-3 -> 0.00326 | F90: =3.424*10^-3 -> 0.003424 | G90: =3.41*10^-3 -> 0.00341 | H90: =1.906*10^-3 -> 0.001906 | I90: $/l
B91: Fuel synthesis | D91: 0.2701 | E91: 0.1602 | F91: 0.1633 | G91: 0.1011 | H91: 0.102 | I91: $/l
B92: Fuel storage | D92: 0 | E92: 0 | F92: 0 | G92: 0 | H92: 0 | I92: $/l
B93: Fuel: Variable | D93: 0 | E93: 0 | F93: 0 | G93: 0 | H93: 0 | I93: $/l
B94: Grid interconnection | D94: 0.112 | E94: 0.02452 | F94: 0.02574 | G94: =71.05*10^-6 -> 7.105e-05 | H94: =80.82*10^-6 -> 8.082e-05 | I94: $/l
B95: Grid electricity | D95: 0.08062 | E95: =6.261*10^-3 -> 0.006261 | F95: 0.02156 | G95: =304.1*10^-6 -> 0.0003041 | H95: =243.1*10^-6 -> 0.0002431 | I95: $/l
B96: Fuel pipeline | D96: =2.442*10^-3 -> 0.002442 | E96: =1.23*10^-3 -> 0.00123 | F96: =1.254*10^-3 -> 0.001254 | G96: =194.1*10^-6 -> 0.0001941 | H96: =195.9*10^-6 -> 0.0001959 | I96: $/l
B97: Fuel pipeline: Variable | D97: 0 | E97: 0 | F97: 0 | G97: 0 | H97: 0 | I97: $/l
B98: Natural gas interconnection | D98: 0.01139 | E98: =4.331*10^-3 -> 0.004331 | F98: =4.573*10^-3 -> 0.004573 | G98: =642.6*10^-6 -> 0.0006426 | H98: =347.1*10^-6 -> 0.0003471 | I98: $/l
B99: Natural gas | D99: 0.03776 | E99: 0.02435 | F99: 0.01876 | G99: 0.0114 | H99: =4.668*10^-3 -> 0.004668 | I99: $/l
B100: Water interconnection | D100: 0 | E100: 0 | F100: 0 | G100: 0 | H100: 0 | I100: $/l
B101: Water | D101: =1.107*10^-3 -> 0.001107 | E101: 0.01179 | F101: =439.4*10^-6 -> 0.0004394 | G101: 0.01286 | H101: 0 | I101: $/l
B102: Carbon payments | D102: 0.7544 | E102: 0.1243 | F102: 0.09252 | G102: 0.03182 | H102: 0.01003 | I102: $/l
B103: Totals | D103: 4.657 | E103: 1.676 | F103: 1.698 | G103: 0.9514 | H103: 0.9519 | I103: $/l
J104: SS
B105: Assumed DAC costs | D105: 600 | E105: 230 | F105: 200 | G105: 130 | H105: 100 | J105: LS
B106: New DAC costs | D106: =Inputs!$C$32 -> 1282 | E106: 473.00612 | F106: 473.00612 | G106: =Inputs!$C$33 -> 480 | H106: =Inputs!$C$33 -> 480
B108: Assumed LCOE | D108: 39 | E108: 18.8 | F108: 18.8 | G108: 11.8 | H108: 11.8
B109: New LCOE | D109: =Inputs!$C$8 -> 64 | E109: 35 | F109: 35 | G109: =Inputs!$C$9 -> 11 | H109: =Inputs!$C$9 -> 11
B111: WACC | D111: 0.1 | E111: 0.08 | F111: 0.08 | G111: 0.05 | H111: 0.05
B112: Assumed WACC | D112: =Inputs!$C$5 -> 0.07 | E112: =Inputs!$C$5 -> 0.07 | F112: =Inputs!$C$5 -> 0.07 | G112: =Inputs!$C$5 -> 0.07 | H112: =Inputs!$C$5 -> 0.07
B114: New DAC | D114: =D89/D105*D106 -> 1.6354047 | E114: =E89/E105*E106 -> 0.58179753 | F114: =F89/F105*F106 -> 0.77643955 | G114: =G89/G105*G106 -> 0.59224615 | H114: =H89/H105*H106 -> 1.0608 | I114: $/l
B115: New Carbon payments | D115: =D102/D105*D106 -> 1.6119013 | E115: =E102/E105*E106 -> 0.25562896 | F115: =F102/F105*F106 -> 0.21881263 | G115: =G102/G105*G106 -> 0.11748923 | H115: =H102/H105*H106 -> 0.048144 | I115: $/l
B116: New Renewable generation | D116: =D80/D108*D109 -> 1.8789744 | E116: =E80/E108*E109 -> 0.85005319 | F116: =F80/F108*F109 -> 0.84893617 | G116: =G80/G108*G109 -> 0.25290678 | H116: =H80/H108*H109 -> 0.23062712 | I116: $/l
B118: WACC correction | D118: =(D112-D111)*100*($L$88-1)+1 -> 0.82952396 | E118: =(E112-E111)*100*($L$88-1)+1 -> 0.94317465 | F118: =(F112-F111)*100*($L$88-1)+1 -> 0.94317465 | G118: =(G112-G111)*100*($L$88-1)+1 -> 1.1136507 | H118: =(H112-H111)*100*($L$88-1)+1 -> 1.1136507
B120: New Total | C120: w/LCOE | D120: =D103-D80+D116 -> 5.3909744 | E120: =E103-E80+E116 -> 2.0694532 | F120: =F103-F80+F116 -> 2.0909362 | G120: =G103-G80+G116 -> 0.93300678 | H120: =H103-H80+H116 -> 0.93512712
B121: New Total | C121: w/LCOE + DAC | D121: =D103+(D114-D89)+(D115-D102)+(D116-D80) -> 7.1184804 | E121: =E103+(E114-E89)+(E115-E102)+(E116-E80) -> 2.4996797 | F121: =F103+(F114-F89)+(F115-F102)+(F116-F80) -> 2.6653683 | G121: =G103+(G114-G89)+(G115-G102)+(G116-G80) -> 1.4505222 | H121: =H103+(H114-H89)+(H115-H102)+(H116-H80) -> 1.8130411
B122: New Total | C122: w/LCOE + DAC + WACC | D122: =D103*D118+(D114-D89)+(D115-D102)+(D116-D80) -> 6.3245734 | E122: =E103*E118+(E114-E89)+(E115-E102)+(E116-E80) -> 2.4044404 | F122: =F103*F118+(F114-F89)+(F115-F102)+(F116-F80) -> 2.5688789 | G122: =G103*G118+(G114-G89)+(G115-G102)+(G116-G80) -> 1.5586494 | H122: =H103*H118+(H114-H89)+(H115-H102)+(H116-H80) -> 1.9212252
B125: Wind | C125: Today, no storage | D125: Today, low-temp | E125: Next-decade, high-temp | F125: Next-decade, low-temp | G125: Breakthrough, high-temp | H125: Breakthrough, low-temp | J125: Wind LCOE | K125: Today, low-temp | L125: Next-decade, high-temp | M125: Next-decade, low-temp | N125: Breakthrough, high-temp | O125: Breakthrough, low-temp
B126: Renewable generation | C126: Null | D126: 1.205 | E126: 0.6408 | F126: 0.6428 | G126: 0.3642 | H126: 0.3579 | J126: CAPEX | K126: - | L126: - | M126: - | N126: - | O126: -
B127: Electricity storage | C127: Null | D127: 0 | E127: 0 | F127: 0 | G127: 0 | H127: 0 | J127: OPEX | K127: - | L127: - | M127: - | N127: - | O127: -
...

Sheet Outputs
A1: 2024 | H1: 2050
A2: Parameter | B2: Unit | C2: Base case | D2: Electricity correction | E2: DAC correction | F2: WACC correction | H2: Parameter | I2: Unit | J2: Base case | K2: Electricity correction | L2: DAC correction | M2: WACC correction
A3: Syn-Fuel cost | B3: $/l | C3: =Standardization!D103 -> 4.657 | D3: =Standardization!D120 -> 5.3909744 | E3: =Standardization!D121 -> 7.1184804 | F3: =Standardization!D122 -> 6.3245734 | H3: Syn-Fuel cost | I3: $/l | J3: =Standardization!H103 -> 0.9519 | K3: =Standardization!H120 -> 0.93512712 | L3: =Standardization!H121 -> 1.8130411 | M3: =Standardization!H122 -> 1.9212252
A4: Fossil Fuel cost | B4: $/l | C4: =Inputs!$C$16 -> 0.8 | D4: =Inputs!$C$16 -> 0.8 | E4: =Inputs!$C$16 -> 0.8 | F4: =Inputs!$C$16 -> 0.8 | H4: Fossil Fuel cost | I4: $/l | J4: =Inputs!$C$18 -> 0.8 | K4: =Inputs!$C$18 -> 0.8 | L4: =Inputs!$C$18 -> 0.8 | M4: =Inputs!$C$18 -> 0.8
A5: Syn-Fuel emissions | B5: gCO2eq/MJ | C5: 0 | D5: 0 | E5: 0 | F5: 0 | H5: Syn-Fuel emissions | I5: gCO2eq/MJ | J5: 0 | K5: 0 | L5: 0 | M5: 0
A6: Fossil Fuel emissions | B6: gCO2eq/MJ | C6: =Inputs!$C$11 -> 88.7 | D6: =Inputs!$C$11 -> 88.7 | E6: =Inputs!$C$11 -> 88.7 | F6: =Inputs!$C$11 -> 88.7 | H6: Fossil Fuel emissions | I6: gCO2eq/MJ | J6: =Inputs!$C$11 -> 88.7 | K6: =Inputs!$C$11 -> 88.7 | L6: =Inputs!$C$11 -> 88.7 | M6: =Inputs!$C$11 -> 88.7
A7: CO2 Abated | B7: gCO2eq/MJ | C7: =C6-C5 -> 88.7 | D7: =D6-D5 -> 88.7 | E7: =E6-E5 -> 88.7 | F7: =F6-F5 -> 88.7 | H7: CO2 Abated | I7: gCO2eq/MJ | J7: =J6-J5 -> 88.7 | K7: =K6-K5 -> 88.7 | L7: =L6-L5 -> 88.7 | M7: =M6-M5 -> 88.7
A8: CO2 Abated | B8: gCO2eq/l | C8: =C7*Inputs!$C$14 -> 3076.9675 | D8: =D7*Inputs!$C$14 -> 3076.9675 | E8: =E7*Inputs!$C$14 -> 3076.9675 | F8: =F7*Inputs!$C$14 -> 3076.9675 | H8: CO2 Abated | I8: gCO2eq/l | J8: =J7*Inputs!$C$14 -> 3076.9675 | K8: =K7*Inputs!$C$14 -> 3076.9675 | L8: =L7*Inputs!$C$14 -> 3076.9675 | M8: =M7*Inputs!$C$14 -> 3076.9675
A9: Abatement cost | B9: $/tCO2 | C9: =(C3-C4) / C8 * 10^6 -> 1253.5069 | D9: =(D3-D4) / D8 * 10^6 -> 1492.0451 | E9: =(E3-E4) / E8 * 10^6 -> 2053.4765 | F9: =(F3-F4) / F8 * 10^6 -> 1795.4604 | H9: Abatement cost | I9: $/tCO2 | J9: =(J3-J4) / J8 * 10^6 -> 49.366787 | K9: =(K3-K4) / K8 * 10^6 -> 43.915679 | L9: =(L3-L4) / L8 * 10^6 -> 329.23361 | M9: =(M3-M4) / M8 * 10^6 -> 364.39293
A12: Parameter | B12: Unit | C12: Low FLH
A13: Syn-Fuel cost | B13: $/l
A14: Fossil Fuel cost | B14: $/l
A15: Syn-Fuel emissions | B15: gCO2eq/MJ
A16: Fossil Fuel emissions | B16: gCO2eq/MJ
A17: CO2 Abated | B17: gCO2eq/MJ
A18: CO2 Abated | B18: gCO2eq/l
A19: Abatement cost | B19: $/tCO2
